Workbook

Sheet Input-Start
A2: 0. >> INSTRUCTION << | D2: I. | F2: TRAFFIC DATA | M2: IIa. | N2: COSTS INFORMATION--Baseline (No ETC) | V2: IIb. | W2: COSTS INFORMATION--ETC Alternative | AF2: III. | AG2: FACT OF TOLL TRANSACTION | AO2: IV. | AP2: TRAVEL AT THE TOLL PLAZA | AX2: V. | AY2: FUEL CONSUMPTION & OTHER ASSUMPTIONS
A3: This spreadsheet model is designed exclusively for benefit-cost evaluation of | C3: INSTRUCTION: | L3: INSTRUCTION: | U3: INSTRUCTION: | AE3: INSTRUCTION: | AN3: INSTRUCTION: | AW3: INSTRUCTION:
A4: Electronic Toll Collection system. | D4: In this section, You are asked to give information about annual traffic | M4: In this section, You are asked to give information about costs for baseline | V4: In this section, You are asked to give information about costs under ETC scenario. | AF4: Required Inputs - white cells | AO4: In this section, You are asked to give information about travel fact at the toll plaza | AX4: In this section, You are asked to give information about fuel consumption in
D5: volume, peak hour volume, D factor and duration of peak period and ETC | M5: operations. Costs are broken down into two categories: one-time costs and | V5: Costs are broken down into two categories: capital investment and operating costs. | AF5: If you have more information about payment split other base year and year 20, go to | AO5: Required Inputs - white cells | AX5: order to estimate the fuel reduction, and other general assumptions.
A6: Where to Start? | D6: Split both in base year and in year 20 or one of them. | M6: continuing costs. All the costs are presented in current value. | V6: All the costs are presented in current value. | AF6: Table IV, expected payment split, in sheet"Input-Details" after completing this table. | AO6: a)Ramp Distance prior to (leading from) the Toll Plaza: The distance that a vehicle | AX6: The Numbers shown in pink cells are the values from previously studies and
A7: Please start with sheet "Input-Start" and fill out all required cells. You may check | D7: If you have information in between, go to sheet "Input-Detail" table Ia, Ib, and 1c | M7: Go to sheet "Input-Detail" table IIa after completing this table if you have | V7: If you have more information, go to sheet "Input-Detail" table IIb after completing this table. | AF7: Default Values - pink cells | AO7: starts to slow down from the normal speed (to accelerate from complete stop). | AX7: used as default values to run the model. Please update it if you have
A8: "Input-Detail" and make some changes based on your own knowledge, or go to the | D8: after completing this table. | M8: detailed information regarding baseline costs. | V8: Required Inputs - white cells | AF8: The values shown in the pink cells are the default number we used previously to run | AO8: b)Prevailing Travel Speed: The travel speed in the adjacent highway sections that | AX8: different values in your case.
A9: "Results Summary" and "Results-Detail" directly to find out the analytical results. | D9: Required Inputs - white cells | M9: Required Inputs - white cells | V9: a) Capital Investment: Initial investment needed to implement ETC project | AF9: the model, please change it if you have different numbers. | AO9: is not influenced by the existence of the toll plaza.
A10: Notice that:always complete this sheet first. | D10: a) Annual Traffic Volume in Base Year as well as in Year 20: | M10: a) One-Time Costs: Costs which occur only once at a specific point of time. | V10: b) Operating Costs: Costs in order to operate the system under ETC scenario | AF10: a) Avg. Tags per Account: The ratio of the number of transponders issued over | AO10: Default Values - pink cells | AX10: Assumptions about Fuel Consumption
D11: "Annual Traffic Volume" here is defined as the number of traffic goes | M11: enter "0" if no costs incurred. | V11: 1) One-time costs: costs which occur only once at a specific point of time | AF11: over the number of accounts open. Several cars may share one account. | AO11: The numbers in pink cells are used previously to run the model, please update it
A12: Other sheets in this files are for the sake of estimation. You may want to have a | D12: through the Toll Plaza per year. | M12: b) Continuing Costs: Costs incurred every year | V12: 2) Operations/Materials Costs | AF12: b)Avg. Usage per Year: Total number of transactions divided by the total | AO12: if your case has different values . | AX12: Average Mileage of Consuming one Gallon of Fuel | BA12: 25
A13: glance and get a general idea of how to get these numbers. You can refer to | D13: b) Expected ETC Split in Base Year as well as in Year 20 | M13: 1) Operations/Materials Costs | V13: 3) Others | AF13: number of accounts open. | AX13: Fuel Price per Gallon | BA13: 1.1
A14: footnotes right below the spreadsheet which provide formula and assumptions | D14: c) Peak Hour Volume (PHV) in Base Year. | M14: 2) Others | V14: Staff Costs is estimated automatically by given units of personal year needed for toll | AF14: c)Deposits: This number refers to the required deposits for transponders. | AX14: Emission Rates during Acceleration (grams/gallon)
A15: employed to proceed the clalculation. | D15: "Peak Hour Volume" here is defined as traffic volume in both direction during | M15: Staff Costs is estimated automatically by given units of personal year needed for | V15: collection and information technology, and costs per personal year. | AO15: Configuration of the Toll Plaza | AY15: Nox | BA15: 24.7
D16: the peak period. | M16: toll collection and information technology, and costs per personal year. | AF16: Transaction Time (sec) | AP16: Total Number of Lanes (max 22) | AR16: 12 | AY16: HC | BA16: 9.5
A17: q SHEET "Input-Start" | D17: d) Peak Hour Duration (T) in Base Year | V17: Year | W17: Capital Investment | X17: Operating Costs | AG17: Cash | AI17: 7 | AP17: Ramp Distance prior to the Toll Plaza (miles) | AR17: 0.2 | AY17: CO | BA17: 209
A18: In this Sheet, you are asked to give the basic information required for Benefit-Cost analysis. | D18: e) D factor (D) in Base Year - directional split | M18: Year | N18: One-Time Costs | O18: Continuing Costs: | X18: One-Time Costs | Y18: Staff | Z18: Operations/Materials | AA18: Other | AG18: Ticket | AI18: 4.5 | AP18: Ramp Distance leading from the toll Plaza (miles) | AR18: 0.2 | AX18: Emission Rates during Idling (grams/minute)
A19: Basically, you have to provide the data for Base Year as well as for Year 20. | O19: Staff | P19: Operations/Materials | Q19: Other | V19: Base | W19: 3009339.7 | X19: 0 | Z19: 8356 | AA19: 301760 | AG19: ETC (headway) | AI19: 2.4 | AY19: Nox | BA19: 0
A20: Then, the model estimates the numbers in between automatically by linear interpolation. | D20: Estimated Annual Traffic Volume (ATV) | M20: Base | N20: 0 | P20: 8356.16 | Q20: 297120 | V20: 1 | W20: 0 | X20: 0 | AF20: Payment Split | AO20: Prevailing Travel Speed (mph) | AR20: 55 | AY20: HC | BA20: 0.15
A21: If you have more data regarding information required other than base in year and in year 20, | F21: Base Year | G21: Year 20 | M21: 1 | N21: 0 | V21: 2 | W21: 284813 | X21: 0 | AF21: Manual Lane-Baseline | AH21: Base Year | AI21: Year 20 | AY21: CO | BA21: 2.5
A22: enter the basic data required in this sheet first; | E22: Traffic Volume | F22: 19016173 | G22: 30000000 | M22: 2 | N22: 0 | V22: 3 | W22: 448581 | X22: 0 | AG22: Cash | AH22: 0.83 | AI22: 0.83 | AO22: Mode Split among ETC Users | AX22: Cost of Air Polution ($/kg of pollutant)
A23: then, go to the sheet "Input-Detail" to change the number shown in blue cells. | E23: ETC Split | F23: 0 | G23: 0.99 | M23: 3 | N23: 0 | V23: 4 | W23: 273801 | X23: 0 | AG23: Ticket | AH23: =1-AH22 -> 0.17 | AI23: =1-AI22 -> 0.17 | AP23: Auto | AR23: 0.9476 | AY23: Nox | BA23: 1.275
M24: 4 | N24: 0 | V24: 5 | W24: 289568 | X24: 0 | AF24: Manual Lane-ETC Alternative | AP24: Truck | AR24: 0.0511 | AY24: HC | BA24: 1.275
A25: q SHEET "Input-Detail" | D25: Peak Hour Statistics in Base Year | M25: 5 | N25: 0 | V25: 6 | W25: 306036 | X25: 0 | AG25: Cash | AH25: 0.83 | AI25: 1 | AP25: Bus | AR25: 0.0013 | AY25: CO | BA25: 0.0063
A26: In this Sheet, you you may change the numbers estimated automatically by this model based | F26: Morning | G26: Evening | M26: 6 | N26: 0 | V26: 7 | W26: 323231 | X26: 0 | AG26: Ticket | AH26: =1-AH25 -> 0.17 | AI26: =1-AI25 -> 0 | AO26: Average Vehicle Occupancy
A27: on the numbers you enter in "Input-Start". | E27: PHV (veh/hr) | F27: 8200 | G27: 8200 | M27: 7 | N27: 0 | V27: 8 | W27: 341183 | X27: 0 | AF27: ETC Lane-ETC Alternative | AP27: Auto | AR27: 1.8
E28: T (hr) | F28: 2 | G28: 2 | M28: 8 | N28: 0 | V28: 9 | W28: 359920 | X28: 0 | AG28: Cash, Checks | AH28: 0.64 | AI28: 0.64 | AP28: Truck | AR28: 1.1 | AX28: General Assumptions
A29: q SHEET "Results Summary" | E29: D factor | F29: 0.3 | G29: 0.7 | M29: 9 | N29: 0 | V29: 10 | W29: 379475 | X29: 0 | AG29: Credit Card | AH29: =1-AH28 -> 0.36 | AI29: =1-AI28 -> 0.36 | AP29: Bus | AR29: 20
A30: In this Sheet, , overall analytical results are presented as well as benefit-cost ratio and | M30: 10 | N30: 0 | V30: 11 | W30: 0 | X30: 0 | AF30: ETC Account Fact | AX30: Inflation Rate | BA30: 0.03
A31: estimated internal interest rate. | M31: 11 | N31: 0 | V31: 12 | W31: 0 | X31: 0 | AF31: Cash & Checks Account | AI31: Base Year | AO31: Time Value of a User for Each Mode ($/hr) | AX31: Annual Interest Rate | BA31: 0.05
M32: 12 | N32: 0 | V32: 13 | W32: 0 | X32: 0 | AG32: Avg. Tags per Accout | AI32: 1.35 | AP32: Auto | AR32: 12.75 | AX32: Discount Rate | BA32: 0.02
A33: q SHEET "Results-Detail" | M33: 13 | N33: 0 | V33: 14 | W33: 0 | X33: 0 | AG33: Avg. Usage per Year | AI33: 160 | AP33: Truck | AR33: 33.41 | AX33: Personal Year (PY)
A34: In this Sheet, benefit-cost analyses are shown for Toll Agency, Users, and Community. | M34: 14 | N34: 0 | V34: 15 | W34: 0 | X34: 0 | AG34: Deposits | AI34: 30 | AP34: Bus (per rider) | AR34: 12.75 | AY34: Hours per Unit Personal Year | BA34: 1768
A35: respectively. | M35: 15 | N35: 0 | V35: 16 | W35: 0 | X35: 0 | AG35: Avg. Balance other than Deposit | AI35: 20 | AY35: PY for Information Technology | BA35: 0.11
M36: 16 | N36: 0 | V36: 17 | W36: 0 | X36: 0 | AF36: Credit Card Account | AI36: Base Year | AY36: PY for Program Costs (Toll Collection) | BA36: 61.5
M37: 17 | N37: 0 | V37: 18 | W37: 0 | X37: 0 | AG37: Avg. Tags per Accout | AI37: 1.35 | AY37: Unit Cost per Personal Year | BA37: 65000
M38: 18 | N38: 0 | V38: 19 | W38: 0 | X38: 0 | AG38: Avg. Usage per Year | AI38: 160
M39: 19 | N39: 0 | V39: 20 | W39: 0 | X39: 0 | AG39: Deposits | AI39: 0
M40: 20 | N40: 0 | AG40: Avg. Balance other than Deposit | AI40: 20

Sheet Input-Detail
C2: Ia. | D2: TRAFFIC DATA - Annual | L2: Ib. | M2: TRAFFIC DATA - Morning Peak | U2: Ic. | V2: TRAFFIC DATA - Evening Peak | AD2: IIa. | AE2: COSTS INFORMATION--Baseline (No ETC) | AM2: IIa. | AN2: COSTS INFORMATION--ETC Alternative | AW2: III. | AX2: FACT OF TOLL TRANSACTION & Travel at Toll Plaza | BF2: IV. | BI2: EXPECTED PAYMENT SPLIT | BS2: V. | BT2: FUEL CONSUMPTION & OTHER ASSUMPTIONS
B3: INSTRUCTION: | K3: INSTRUCTION: | T3: INSTRUCTION: | AC3: INSTRUCTION: | AL3: INSTRUCTION: | AV3: INSTRUCTION: | BE3: INSTRUCTION: | BR3: INSTRUCTION:
C4: Change the numbers in blue cells only - | L4: Change the numbers in blue cells only - | U4: Change the numbers in blue cells only - | AD4: Change the numbers in blue cells only - | AM4: Change the numbers in blue cells only - | AW4: The values shown in pink cells are the default number we used to run the model. | BF4: Change the numbers in blue cells only - | BS4: The values shown in pink cells are the default number we used to run the model.
C5: The data in Base Year and Year 20 you enter in sheet "Input-Start" are | L5: The data in Base Year and Year 20 you enter in sheet "Input-Start" are | U5: The data in Base Year and Year 20 you enter in sheet "Input-Start" are | AD5: The data in Base Year and Year 20 you enter in sheet "Input-Start" are shown | AM5: The data in Base Year and Year 20 you enter in sheet "Input-Start" are | AW5: The numbers in white cells are those you entered in Table III &IV in "Input-Start" Sheet. | BF5: the numbers in white cells are those you entered in "Input-Start" Sheet about . | BS5: The numbers in white cells are those you entered in Table V in "Input-Start" Sheet.
C6: shown on white cells. | L6: shown on white cells. | U6: shown on white cells. | AD6: on white cells after inflation effect. That is, the number show on this table | AM6: shown on white cells after inflation effect. That is, the number show on this | AW6: You can not make any change here. | BF6: payment split among Manual Users as well as among ETC Users. | BS6: You can not make any change here.
C7: Based on these data, the model estimated automatically annual traffic volume | L7: Based on these data, the model estimated automatically peak hour traffic | U7: Based on these data, the model estimated automatically peak hour traffic | AD7: are no longer current value but nominal value in year i. | AM7: table are no longer current value but nominal value. | AW7: If you would like to make any change, go back to the sheet "Input-Start". | BS7: If you would like to make any change, go back to the sheet "Input-Start".
C8: and ETC Split in between by interpolation. | L8: volume, duration of peak period, and D factor for each year. | U8: volume, duration of peak period, and D factor. | AD8: Based on these data, the model estimates continuing costs automatically. | AM8: Based on these data, the model estimated continuing cost automatically. | BF8: Payment Split
C9: Please make reasonable adjustions in blue cells. | L9: a) Peak Hour Volume (PHV): assume that ATV/PHV remains constant over | U9: a) Peak Hour Volume (PHV) - assume that ATV/PHV remains constant over | AD9: For the knowledge of estimation, check the footnote right below the table. | AM9: For the knowledge of estimation, check the footnote right below the table. | AW9: Transaction Time (sec) | BS9: Assumptions about Fuel Consumption
L10: the analysis period. Thus, peak hour volume in year i is estimated by | U10: the analysis period. Thus, peak hour volume in year i is estimated by | AD10: Please make reasonable adjustions in blue cells. | AM10: Please make reasonable adjustions in blue cells. | AX10: Cash | AZ10: ='Input-Start'!AI17 -> 7 | BG10: Year | BH10: Baseline | BJ10: ETC Alternative
C11: Estimated Annual Traffic Volume (ATV) | L11: estimated annual traffic volume times ATV/PHV. | U11: estimated annual traffic volume times ATV/PHV. | AX11: Ticket | AZ11: ='Input-Start'!AI18 -> 4.5 | BH11: Manual Users | BJ11: Manual Users | BL11: ETC Users | BS11: Average Milage of Consuming one Gallon of Fuel | BV11: ='Input-Start'!BA12 -> 25
L12: b) ATV/PHV - the ratio of annual traffic volume over peak hour volume. | U12: b) ATV/PHV - the ratio of annual traffic volume over peak hour volume. | AD12: Year | AE12: One-Time Costs | AF12: Continuing Costs: | AM12: Year | AN12: Capital Investment | AO12: Continuing Costs: | AX12: ETC (headway) | AZ12: ='Input-Start'!AI19 -> 2.4 | BH12: Cash | BI12: Ticket | BJ12: Cash | BK12: Ticket | BL12: Cash &Checks | BM12: Credit Card | BS12: Fuel Price per Gallon | BV12: ='Input-Start'!BA13 -> 1.1
D13: Year | E13: Traffic Vol. | F13: ETC Split | L13: c) Duration of Peak Period (T) in the morning peak in Based Year, hrs/day. | U13: c) Duration of Peak Period (T) in the evening peak in Based Year, hrs/day | AF13: Staff* | AG13: Operations/Materials | AH13: Other | AO13: One-Time Costs | AP13: Staff | AQ13: Operations/Materials | AR13: Other | AW13: ETC Account Fact | BG13: Base | BH13: ='Input-Start'!AH22 -> 0.83 | BI13: =1-BH13 -> 0.17 | BJ13: ='Input-Start'!AH25 -> 0.83 | BK13: =1-BJ13 -> 0.17 | BL13: ='Input-Start'!AH28 -> 0.64 | BM13: =1-BL13 -> 0.36 | BS13: Emission Rates during Acceleration (grams/gallon)
D14: Base | E14: ='Input-Start'!F22 -> 19016173 | F14: ='Input-Start'!F23 -> 0 | L14: d) Direction Factor (D) during the morning peak in Base Year | U14: d) Direction Factor (D) during the evening peak in Base Year | AD14: Base | AE14: ='Input-Start'!N20 -> 0 | AF14: =Cost_PY*('Input-Start'!BA36+PY_for_Inf) -> 4004650 | AG14: ='Input-Start'!P20 -> 8356.16 | AH14: ='Input-Start'!Q20 -> 297120 | AM14: Base | AN14: ='Input-Start'!W19 -> 3009339.7 | AO14: ='Input-Start'!X19 -> 0 | AP14: =Cost_PY*(PY_for_Inf+PY!$Q6) -> 4004650 | AQ14: ='Input-Start'!Z19 -> 8356 | AR14: ='Input-Start'!AA19 -> 301760 | AW14: Cash & Checks | BG14: 1 | BH14: =BH$13+(BH$33-BH$13)*$D15/$D$34 -> 0.83 | BI14: =1-BH14 -> 0.17 | BJ14: =BJ$13+(BJ$33-BJ$13)*$D15/$D$34 -> 0.8385 | BK14: =1-BJ14 -> 0.1615 | BL14: =BL$13+(BL$33-BL$13)*$D15/$D$34 -> 0.64 | BM14: =1-BL14 -> 0.36 | BT14: Nox | BV14: ='Input-Start'!BA15 -> 24.7
D15: 1 | E15: =E$14+(E$34-E$14)*$D15/$D$34 -> 19565364 | F15: =F$14+(F$34-F$14)*$D15/$D$34 -> 0.0495 | L15: Please make reasonable adjustions in blue cells. | U15: Please make reasonable adjustions in blue cells. | AD15: 1 | AE15: ='Input-Start'!N21^(1+Inflation_Rate)^Year -> 0 | AF15: =Cost_PY*(PY_for_Inf+PY!$L7)*(1+Inflation_Rate)^Year -> 4230053.2 | AG15: =AG14*(1+Inflation_Rate) -> 8606.8448 | AH15: =AH14*(1+Inflation_Rate) -> 306033.6 | AM15: 1 | AN15: ='Input-Start'!W20*(1+Inflation_Rate)^Year -> 0 | AO15: ='Input-Start'!X20*(1+Inflation_Rate)^'Input-Detail'!$AM15 -> 0 | AP15: =Cost_PY*(PY_for_Inf+PY!$Q7)*(1+Inflation_Rate)^Year -> 4005040.9 | AQ15: =AQ14*(1+Inflation_Rate) -> 8606.68 | AR15: =AR14*(1+Inflation_Rate) -> 310812.8 | AX15: Avg. Tags per Accout | AZ15: ='Input-Start'!AI32 -> 1.35 | BG15: 2 | BH15: =BH$13+(BH$33-BH$13)*$D16/$D$34 -> 0.83 | BI15: =1-BH15 -> 0.17 | BJ15: =BJ$13+(BJ$33-BJ$13)*$D16/$D$34 -> 0.847 | BK15: =1-BJ15 -> 0.153 | BL15: =BL$13+(BL$33-BL$13)*$D16/$D$34 -> 0.64 | BM15: =1-BL15 -> 0.36 | BT15: HC | BV15: ='Input-Start'!BA16 -> 9.5
D16: 2 | E16: =E$14+(E$34-E$14)*$D16/$D$34 -> 20114556 | F16: =F$14+(F$34-F$14)*$D16/$D$34 -> 0.099 | AD16: 2 | AE16: ='Input-Start'!N22^(1+Inflation_Rate)^Year -> 0 | AF16: =Cost_PY*(PY_for_Inf+PY!$L8)*(1+Inflation_Rate)^Year -> 4465376.4 | AG16: =AG15*(1+Inflation_Rate) -> 8865.0501 | AH16: =AH15*(1+Inflation_Rate) -> 315214.61 | AM16: 2 | AN16: ='Input-Start'!W21*(1+Inflation_Rate)^Year -> 302158.11 | AO16: ='Input-Start'!X21*(1+Inflation_Rate)^'Input-Detail'!$AM16 -> 0 | AP16: =Cost_PY*(PY_for_Inf+PY!$Q8)*(1+Inflation_Rate)^$AM16 -> 4031681.1 | AQ16: =AQ15*(1+Inflation_Rate) -> 8864.8804 | AR16: =AR15*(1+Inflation_Rate) -> 320137.18 | AX16: Avg. Usage per Year | AZ16: ='Input-Start'!AI33 -> 160 | BG16: 3 | BH16: =BH$13+(BH$33-BH$13)*$D17/$D$34 -> 0.83 | BI16: =1-BH16 -> 0.17 | BJ16: =BJ$13+(BJ$33-BJ$13)*$D17/$D$34 -> 0.8555 | BK16: =1-BJ16 -> 0.1445 | BL16: =BL$13+(BL$33-BL$13)*$D17/$D$34 -> 0.64 | BM16: =1-BL16 -> 0.36 | BT16: CO | BV16: ='Input-Start'!BA17 -> 209
D17: 3 | E17: =E$14+(E$34-E$14)*$D17/$D$34 -> 20663747 | F17: =F$14+(F$34-F$14)*$D17/$D$34 -> 0.1485 | L17: Year | M17: PHV | N17: ATV/PHV | O17: T (hr) | P17: K | U17: Year | V17: PHV | W17: ATV/PHV | X17: T (hr) | Y17: K | AD17: 3 | AE17: ='Input-Start'!N23^(1+Inflation_Rate)^Year -> 0 | AF17: =Cost_PY*(PY_for_Inf+PY!$L9)*(1+Inflation_Rate)^Year -> 4711012 | AG17: =AG16*(1+Inflation_Rate) -> 9131.0016 | AH17: =AH16*(1+Inflation_Rate) -> 324671.05 | AM17: 3 | AN17: ='Input-Start'!W22*(1+Inflation_Rate)^Year -> 490176.57 | AO17: ='Input-Start'!X22*(1+Inflation_Rate)^'Input-Detail'!$AM17 -> 0 | AP17: =Cost_PY*(PY_for_Inf+PY!$Q9)*(1+Inflation_Rate)^$AM17 -> 4045259.5 | AQ17: =AQ16*(1+Inflation_Rate) -> 9130.8268 | AR17: =AR16*(1+Inflation_Rate) -> 329741.3 | AX17: Deposits | AZ17: ='Input-Start'!AI34 -> 30 | BG17: 4 | BH17: =BH$13+(BH$33-BH$13)*$D18/$D$34 -> 0.83 | BI17: =1-BH17 -> 0.17 | BJ17: =BJ$13+(BJ$33-BJ$13)*$D18/$D$34 -> 0.864 | BK17: =1-BJ17 -> 0.136 | BL17: =BL$13+(BL$33-BL$13)*$D18/$D$34 -> 0.64 | BM17: =1-BL17 -> 0.36 | BS17: Emission Rates during Idling (grams/minute)
D18: 4 | E18: =E$14+(E$34-E$14)*$D18/$D$34 -> 21212938 | F18: =F$14+(F$34-F$14)*$D18/$D$34 -> 0.198 | L18: Base | M18: ='Input-Start'!F27 -> 8200 | N18: =E14/M18 -> 2319.0455 | O18: ='Input-Start'!F28 -> 2 | P18: ='Input-Start'!F29 -> 0.3 | U18: Base | V18: ='Input-Start'!G27 -> 8200 | W18: =E14/V18 -> 2319.0455 | X18: ='Input-Start'!G28 -> 2 | Y18: ='Input-Start'!G29 -> 0.7 | AD18: 4 | AE18: ='Input-Start'!N24^(1+Inflation_Rate)^Year -> 0 | AF18: =Cost_PY*(PY_for_Inf+PY!$L10)*(1+Inflation_Rate)^Year -> 4967366.8 | AG18: =AG17*(1+Inflation_Rate) -> 9404.9317 | AH18: =AH17*(1+Inflation_Rate) -> 334411.18 | AM18: 4 | AN18: ='Input-Start'!W23*(1+Inflation_Rate)^Year -> 308165.44 | AO18: ='Input-Start'!X23*(1+Inflation_Rate)^'Input-Detail'!$AM18 -> 0 | AP18: =Cost_PY*(PY_for_Inf+PY!$Q10)*(1+Inflation_Rate)^$AM18 -> 4044636.6 | AQ18: =AQ17*(1+Inflation_Rate) -> 9404.7516 | AR18: =AR17*(1+Inflation_Rate) -> 339633.54 | AX18: Avg. Balance other than Deposit | AZ18: ='Input-Start'!AI35 -> 20 | BG18: 5 | BH18: =BH$13+(BH$33-BH$13)*$D19/$D$34 -> 0.83 | BI18: =1-BH18 -> 0.17 | BJ18: =BJ$13+(BJ$33-BJ$13)*$D19/$D$34 -> 0.8725 | BK18: =1-BJ18 -> 0.1275 | BL18: =BL$13+(BL$33-BL$13)*$D19/$D$34 -> 0.64 | BM18: =1-BL18 -> 0.36 | BT18: Nox | BV18: ='Input-Start'!BA19 -> 0
D19: 5 | E19: =E$14+(E$34-E$14)*$D19/$D$34 -> 21762130 | F19: =F$14+(F$34-F$14)*$D19/$D$34 -> 0.2475 | L19: 1 | M19: =E15/$N$18 -> 8436.8178 | N19: =E15/M19 -> 2319.0455 | O19: =O18 -> 2 | P19: =P18 -> 0.3 | U19: 1 | V19: =E15/$W$18 -> 8436.8178 | W19: =E15/V19 -> 2319.0455 | X19: =X18 -> 2 | Y19: =Y18 -> 0.7 | AD19: 5 | AE19: ='Input-Start'!N25^(1+Inflation_Rate)^Year -> 0 | AF19: =Cost_PY*(PY_for_Inf+PY!$L11)*(1+Inflation_Rate)^Year -> 5234863.1 | AG19: =AG18*(1+Inflation_Rate) -> 9687.0796 | AH19: =AH18*(1+Inflation_Rate) -> 344443.51 | AM19: 5 | AN19: ='Input-Start'!W24*(1+Inflation_Rate)^Year -> 335688.68 | AO19: ='Input-Start'!X24*(1+Inflation_Rate)^'Input-Detail'!$AM19 -> 0 | AP19: =Cost_PY*(PY_for_Inf+PY!$Q11)*(1+Inflation_Rate)^$AM19 -> 3984281.4 | AQ19: =AQ18*(1+Inflation_Rate) -> 9686.8942 | AR19: =AR18*(1+Inflation_Rate) -> 349822.54 | AW19: Credit Card | BG19: 6 | BH19: =BH$13+(BH$33-BH$13)*$D20/$D$34 -> 0.83 | BI19: =1-BH19 -> 0.17 | BJ19: =BJ$13+(BJ$33-BJ$13)*$D20/$D$34 -> 0.881 | BK19: =1-BJ19 -> 0.119 | BL19: =BL$13+(BL$33-BL$13)*$D20/$D$34 -> 0.64 | BM19: =1-BL19 -> 0.36 | BT19: HC | BV19: ='Input-Start'!BA20 -> 0.15
D20: 6 | E20: =E$14+(E$34-E$14)*$D20/$D$34 -> 22311321 | F20: =F$14+(F$34-F$14)*$D20/$D$34 -> 0.297 | L20: 2 | M20: =E16/$N$18 -> 8673.6357 | N20: =E16/M20 -> 2319.0455 | O20: =O19 -> 2 | P20: =P19 -> 0.3 | U20: 2 | V20: =E16/$W$18 -> 8673.6357 | W20: =E16/V20 -> 2319.0455 | X20: =X19 -> 2 | Y20: =Y19 -> 0.7 | AD20: 6 | AE20: ='Input-Start'!N26^(1+Inflation_Rate)^Year -> 0 | AF20: =Cost_PY*(PY_for_Inf+PY!$L12)*(1+Inflation_Rate)^Year -> 5513938.4 | AG20: =AG19*(1+Inflation_Rate) -> 9977.692 | AH20: =AH19*(1+Inflation_Rate) -> 354776.82 | AM20: 6 | AN20: ='Input-Start'!W25*(1+Inflation_Rate)^Year -> 365422.99 | AO20: ='Input-Start'!X25*(1+Inflation_Rate)^'Input-Detail'!$AM20 -> 0 | AP20: =Cost_PY*(PY_for_Inf+PY!$Q12)*(1+Inflation_Rate)^$AM20 -> 3950238.7 | AQ20: =AQ19*(1+Inflation_Rate) -> 9977.501 | AR20: =AR19*(1+Inflation_Rate) -> 360317.22 | AX20: Avg. Tags per Accout | AZ20: ='Input-Start'!AI37 -> 1.35 | BG20: 7 | BH20: =BH$13+(BH$33-BH$13)*$D21/$D$34 -> 0.83 | BI20: =1-BH20 -> 0.17 | BJ20: =BJ$13+(BJ$33-BJ$13)*$D21/$D$34 -> 0.8895 | BK20: =1-BJ20 -> 0.1105 | BL20: =BL$13+(BL$33-BL$13)*$D21/$D$34 -> 0.64 | BM20: =1-BL20 -> 0.36 | BT20: CO | BV20: ='Input-Start'!BA21 -> 2.5
D21: 7 | E21: =E$14+(E$34-E$14)*$D21/$D$34 -> 22860512 | F21: =F$14+(F$34-F$14)*$D21/$D$34 -> 0.3465 | L21: 3 | M21: =E17/$N$18 -> 8910.4535 | N21: =E17/M21 -> 2319.0455 | O21: =O20 -> 2 | P21: =P20 -> 0.3 | U21: 3 | V21: =E17/$W$18 -> 8910.4535 | W21: =E17/V21 -> 2319.0455 | X21: =X20 -> 2 | Y21: =Y20 -> 0.7 | AD21: 7 | AE21: ='Input-Start'!N27^(1+Inflation_Rate)^Year -> 0 | AF21: =Cost_PY*(PY_for_Inf+PY!$L13)*(1+Inflation_Rate)^Year -> 5805047 | AG21: =AG20*(1+Inflation_Rate) -> 10277.023 | AH21: =AH20*(1+Inflation_Rate) -> 365420.12 | AM21: 7 | AN21: ='Input-Start'!W26*(1+Inflation_Rate)^Year -> 397533.36 | AO21: ='Input-Start'!X26*(1+Inflation_Rate)^'Input-Detail'!$AM21 -> 0 | AP21: =Cost_PY*(PY_for_Inf+PY!$Q13)*(1+Inflation_Rate)^$AM21 -> 3898124.2 | AQ21: =AQ20*(1+Inflation_Rate) -> 10276.826 | AR21: =AR20*(1+Inflation_Rate) -> 371126.74 | AX21: Avg. Usage per Year | AZ21: ='Input-Start'!AI38 -> 160 | BG21: 8 | BH21: =BH$13+(BH$33-BH$13)*$D22/$D$34 -> 0.83 | BI21: =1-BH21 -> 0.17 | BJ21: =BJ$13+(BJ$33-BJ$13)*$D22/$D$34 -> 0.898 | BK21: =1-BJ21 -> 0.102 | BL21: =BL$13+(BL$33-BL$13)*$D22/$D$34 -> 0.64 | BM21: =1-BL21 -> 0.36 | BS21: Cost of Air Polution ($/kg of pollutant)
D22: 8 | E22: =E$14+(E$34-E$14)*$D22/$D$34 -> 23409704 | F22: =F$14+(F$34-F$14)*$D22/$D$34 -> 0.396 | L22: 4 | M22: =E18/$N$18 -> 9147.2714 | N22: =E18/M22 -> 2319.0455 | O22: =O21 -> 2 | P22: =P21 -> 0.3 | U22: 4 | V22: =E18/$W$18 -> 9147.2714 | W22: =E18/V22 -> 2319.0455 | X22: =X21 -> 2 | Y22: =Y21 -> 0.7 | AD22: 8 | AE22: ='Input-Start'!N28^(1+Inflation_Rate)^Year -> 0 | AF22: =Cost_PY*(PY_for_Inf+PY!$L14)*(1+Inflation_Rate)^Year -> 6108659.4 | AG22: =AG21*(1+Inflation_Rate) -> 10585.333 | AH22: =AH21*(1+Inflation_Rate) -> 376382.73 | AM22: 8 | AN22: ='Input-Start'!W27*(1+Inflation_Rate)^Year -> 432200.42 | AO22: ='Input-Start'!X27*(1+Inflation_Rate)^'Input-Detail'!$AM22 -> 0 | AP22: =Cost_PY*(PY_for_Inf+PY!$Q14)*(1+Inflation_Rate)^$AM22 -> 3778075.7 | AQ22: =AQ21*(1+Inflation_Rate) -> 10585.131 | AR22: =AR21*(1+Inflation_Rate) -> 382260.54 | AX22: Deposits | AZ22: ='Input-Start'!AI39 -> 0 | BG22: 9 | BH22: =BH$13+(BH$33-BH$13)*$D23/$D$34 -> 0.83 | BI22: =1-BH22 -> 0.17 | BJ22: =BJ$13+(BJ$33-BJ$13)*$D23/$D$34 -> 0.9065 | BK22: =1-BJ22 -> 0.0935 | BL22: =BL$13+(BL$33-BL$13)*$D23/$D$34 -> 0.64 | BM22: =1-BL22 -> 0.36 | BT22: Nox | BV22: ='Input-Start'!BA23 -> 1.275
D23: 9 | E23: =E$14+(E$34-E$14)*$D23/$D$34 -> 23958895 | F23: =F$14+(F$34-F$14)*$D23/$D$34 -> 0.4455 | L23: 5 | M23: =E19/$N$18 -> 9384.0892 | N23: =E19/M23 -> 2319.0455 | O23: =O22 -> 2 | P23: =P22 -> 0.3 | U23: 5 | V23: =E19/$W$18 -> 9384.0892 | W23: =E19/V23 -> 2319.0455 | X23: =X22 -> 2 | Y23: =Y22 -> 0.7 | AD23: 9 | AE23: ='Input-Start'!N29^(1+Inflation_Rate)^Year -> 0 | AF23: =Cost_PY*(PY_for_Inf+PY!$L15)*(1+Inflation_Rate)^Year -> 6425264.1 | AG23: =AG22*(1+Inflation_Rate) -> 10902.893 | AH23: =AH22*(1+Inflation_Rate) -> 387674.21 | AM23: 9 | AN23: ='Input-Start'!W28*(1+Inflation_Rate)^Year -> 469613.96 | AO23: ='Input-Start'!X28*(1+Inflation_Rate)^'Input-Detail'!$AM23 -> 0 | AP23: =Cost_PY*(PY_for_Inf+PY!$Q15)*(1+Inflation_Rate)^$AM23 -> 3684003.2 | AQ23: =AQ22*(1+Inflation_Rate) -> 10902.685 | AR23: =AR22*(1+Inflation_Rate) -> 393728.36 | AX23: Avg. Balance other than Deposit | AZ23: ='Input-Start'!AI40 -> 20 | BG23: 10 | BH23: =BH$13+(BH$33-BH$13)*$D24/$D$34 -> 0.83 | BI23: =1-BH23 -> 0.17 | BJ23: =BJ$13+(BJ$33-BJ$13)*$D24/$D$34 -> 0.915 | BK23: =1-BJ23 -> 0.085 | BL23: =BL$13+(BL$33-BL$13)*$D24/$D$34 -> 0.64 | BM23: =1-BL23 -> 0.36 | BT23: HC | BV23: ='Input-Start'!BA24 -> 1.275
D24: 10 | E24: =E$14+(E$34-E$14)*$D24/$D$34 -> 24508086 | F24: =F$14+(F$34-F$14)*$D24/$D$34 -> 0.495 | L24: 6 | M24: =E20/$N$18 -> 9620.9071 | N24: =E20/M24 -> 2319.0455 | O24: =O23 -> 2 | P24: =P23 -> 0.3 | U24: 6 | V24: =E20/$W$18 -> 9620.9071 | W24: =E20/V24 -> 2319.0455 | X24: =X23 -> 2 | Y24: =Y23 -> 0.7 | AD24: 10 | AE24: ='Input-Start'!N30^(1+Inflation_Rate)^Year -> 0 | AF24: =Cost_PY*(PY_for_Inf+PY!$L16)*(1+Inflation_Rate)^Year -> 6755367.3 | AG24: =AG23*(1+Inflation_Rate) -> 11229.98 | AH24: =AH23*(1+Inflation_Rate) -> 399304.43 | AM24: 10 | AN24: ='Input-Start'!W29*(1+Inflation_Rate)^Year -> 509982.67 | AO24: ='Input-Start'!X29*(1+Inflation_Rate)^'Input-Detail'!$AM24 -> 0 | AP24: =Cost_PY*(PY_for_Inf+PY!$Q16)*(1+Inflation_Rate)^$AM24 -> 3567289 | AQ24: =AQ23*(1+Inflation_Rate) -> 11229.765 | AR24: =AR23*(1+Inflation_Rate) -> 405540.21 | AW24: Configuration of the Toll Plaza | BG24: 11 | BH24: =BH$13+(BH$33-BH$13)*$D25/$D$34 -> 0.83 | BI24: =1-BH24 -> 0.17 | BJ24: =BJ$13+(BJ$33-BJ$13)*$D25/$D$34 -> 0.9235 | BK24: =1-BJ24 -> 0.0765 | BL24: =BL$13+(BL$33-BL$13)*$D25/$D$34 -> 0.64 | BM24: =1-BL24 -> 0.36 | BT24: CO | BV24: ='Input-Start'!BA25 -> 0.0063
D25: 11 | E25: =E$14+(E$34-E$14)*$D25/$D$34 -> 25057278 | F25: =F$14+(F$34-F$14)*$D25/$D$34 -> 0.5445 | L25: 7 | M25: =E21/$N$18 -> 9857.7249 | N25: =E21/M25 -> 2319.0455 | O25: =O24 -> 2 | P25: =P24 -> 0.3 | U25: 7 | V25: =E21/$W$18 -> 9857.7249 | W25: =E21/V25 -> 2319.0455 | X25: =X24 -> 2 | Y25: =Y24 -> 0.7 | AD25: 11 | AE25: ='Input-Start'!N31^(1+Inflation_Rate)^Year -> 0 | AF25: =Cost_PY*(PY_for_Inf+PY!$L17)*(1+Inflation_Rate)^Year -> 7099494 | AG25: =AG24*(1+Inflation_Rate) -> 11566.88 | AH25: =AH24*(1+Inflation_Rate) -> 411283.57 | AM25: 11 | AN25: ='Input-Start'!W30*(1+Inflation_Rate)^Year -> 0 | AO25: ='Input-Start'!X30*(1+Inflation_Rate)^'Input-Detail'!$AM25 -> 0 | AP25: =Cost_PY*(PY_for_Inf+PY!$Q17)*(1+Inflation_Rate)^$AM25 -> 3373324.5 | AQ25: =AQ24*(1+Inflation_Rate) -> 11566.658 | AR25: =AR24*(1+Inflation_Rate) -> 417706.41 | AX25: Total Number of Lanes | AZ25: ='Input-Start'!AR16 -> 12 | BG25: 12 | BH25: =BH$13+(BH$33-BH$13)*$D26/$D$34 -> 0.83 | BI25: =1-BH25 -> 0.17 | BJ25: =BJ$13+(BJ$33-BJ$13)*$D26/$D$34 -> 0.932 | BK25: =1-BJ25 -> 0.068 | BL25: =BL$13+(BL$33-BL$13)*$D26/$D$34 -> 0.64 | BM25: =1-BL25 -> 0.36
D26: 12 | E26: =E$14+(E$34-E$14)*$D26/$D$34 -> 25606469 | F26: =F$14+(F$34-F$14)*$D26/$D$34 -> 0.594 | L26: 8 | M26: =E22/$N$18 -> 10094.543 | N26: =E22/M26 -> 2319.0455 | O26: =O25 -> 2 | P26: =P25 -> 0.3 | U26: 8 | V26: =E22/$W$18 -> 10094.543 | W26: =E22/V26 -> 2319.0455 | X26: =X25 -> 2 | Y26: =Y25 -> 0.7 | AD26: 12 | AE26: ='Input-Start'!N32^(1+Inflation_Rate)^Year -> 0 | AF26: =Cost_PY*(PY_for_Inf+PY!$L18)*(1+Inflation_Rate)^Year -> 7458188.4 | AG26: =AG25*(1+Inflation_Rate) -> 11913.886 | AH26: =AH25*(1+Inflation_Rate) -> 423622.07 | AM26: 12 | AN26: ='Input-Start'!W31*(1+Inflation_Rate)^Year -> 0 | AO26: ='Input-Start'!X31*(1+Inflation_Rate)^'Input-Detail'!$AM26 -> 0 | AP26: =Cost_PY*(PY_for_Inf+PY!$Q18)*(1+Inflation_Rate)^$AM26 -> 3204600.8 | AQ26: =AQ25*(1+Inflation_Rate) -> 11913.658 | AR26: =AR25*(1+Inflation_Rate) -> 430237.61 | AX26: Ramp Distance prior to the Toll Plaza (miles) | AZ26: ='Input-Start'!AR17 -> 0.2 | BG26: 13 | BH26: =BH$13+(BH$33-BH$13)*$D27/$D$34 -> 0.83 | BI26: =1-BH26 -> 0.17 | BJ26: =BJ$13+(BJ$33-BJ$13)*$D27/$D$34 -> 0.9405 | BK26: =1-BJ26 -> 0.0595 | BL26: =BL$13+(BL$33-BL$13)*$D27/$D$34 -> 0.64 | BM26: =1-BL26 -> 0.36
D27: 13 | E27: =E$14+(E$34-E$14)*$D27/$D$34 -> 26155661 | F27: =F$14+(F$34-F$14)*$D27/$D$34 -> 0.6435 | L27: 9 | M27: =E23/$N$18 -> 10331.361 | N27: =E23/M27 -> 2319.0455 | O27: =O26 -> 2 | P27: =P26 -> 0.3 | U27: 9 | V27: =E23/$W$18 -> 10331.361 | W27: =E23/V27 -> 2319.0455 | X27: =X26 -> 2 | Y27: =Y26 -> 0.7 | AD27: 13 | AE27: ='Input-Start'!N33^(1+Inflation_Rate)^Year -> 0 | AF27: =Cost_PY*(PY_for_Inf+PY!$L19)*(1+Inflation_Rate)^Year -> 7832014.9 | AG27: =AG26*(1+Inflation_Rate) -> 12271.303 | AH27: =AH26*(1+Inflation_Rate) -> 436330.74 | AM27: 13 | AN27: ='Input-Start'!W32*(1+Inflation_Rate)^Year -> 0 | AO27: ='Input-Start'!X32*(1+Inflation_Rate)^'Input-Detail'!$AM27 -> 0 | AP27: =Cost_PY*(PY_for_Inf+PY!$Q19)*(1+Inflation_Rate)^$AM27 -> 2951709.9 | AQ27: =AQ26*(1+Inflation_Rate) -> 12271.068 | AR27: =AR26*(1+Inflation_Rate) -> 443144.73 | AX27: Ramp Distance leading from the toll Plaza (miles) | AZ27: ='Input-Start'!AR18 -> 0.2 | BG27: 14 | BH27: =BH$13+(BH$33-BH$13)*$D28/$D$34 -> 0.83 | BI27: =1-BH27 -> 0.17 | BJ27: =BJ$13+(BJ$33-BJ$13)*$D28/$D$34 -> 0.949 | BK27: =1-BJ27 -> 0.051 | BL27: =BL$13+(BL$33-BL$13)*$D28/$D$34 -> 0.64 | BM27: =1-BL27 -> 0.36 | BS27: General Assumptions
D28: 14 | E28: =E$14+(E$34-E$14)*$D28/$D$34 -> 26704852 | F28: =F$14+(F$34-F$14)*$D28/$D$34 -> 0.693 | L28: 10 | M28: =E24/$N$18 -> 10568.178 | N28: =E24/M28 -> 2319.0455 | O28: =O27 -> 2 | P28: =P27 -> 0.3 | U28: 10 | V28: =E24/$W$18 -> 10568.178 | W28: =E24/V28 -> 2319.0455 | X28: =X27 -> 2 | Y28: =Y27 -> 0.7 | AD28: 14 | AE28: ='Input-Start'!N34^(1+Inflation_Rate)^Year -> 0 | AF28: =Cost_PY*(PY_for_Inf+PY!$L20)*(1+Inflation_Rate)^Year -> 8221558.6 | AG28: =AG27*(1+Inflation_Rate) -> 12639.442 | AH28: =AH27*(1+Inflation_Rate) -> 449420.66 | AM28: 14 | AN28: ='Input-Start'!W33*(1+Inflation_Rate)^Year -> 0 | AO28: ='Input-Start'!X33*(1+Inflation_Rate)^'Input-Detail'!$AM28 -> 0 | AP28: =Cost_PY*(PY_for_Inf+PY!$Q20)*(1+Inflation_Rate)^$AM28 -> 2723291.9 | AQ28: =AQ27*(1+Inflation_Rate) -> 12639.2 | AR28: =AR27*(1+Inflation_Rate) -> 456439.08 | BG28: 15 | BH28: =BH$13+(BH$33-BH$13)*$D29/$D$34 -> 0.83 | BI28: =1-BH28 -> 0.17 | BJ28: =BJ$13+(BJ$33-BJ$13)*$D29/$D$34 -> 0.9575 | BK28: =1-BJ28 -> 0.0425 | BL28: =BL$13+(BL$33-BL$13)*$D29/$D$34 -> 0.64 | BM28: =1-BL28 -> 0.36
D29: 15 | E29: =E$14+(E$34-E$14)*$D29/$D$34 -> 27254043 | F29: =F$14+(F$34-F$14)*$D29/$D$34 -> 0.7425 | L29: 11 | M29: =E25/$N$18 -> 10804.996 | N29: =E25/M29 -> 2319.0455 | O29: =O28 -> 2 | P29: =P28 -> 0.3 | U29: 11 | V29: =E25/$W$18 -> 10804.996 | W29: =E25/V29 -> 2319.0455 | X29: =X28 -> 2 | Y29: =Y28 -> 0.7 | AD29: 15 | AE29: ='Input-Start'!N35^(1+Inflation_Rate)^Year -> 0 | AF29: =Cost_PY*(PY_for_Inf+PY!$L21)*(1+Inflation_Rate)^Year -> 8627426.2 | AG29: =AG28*(1+Inflation_Rate) -> 13018.625 | AH29: =AH28*(1+Inflation_Rate) -> 462903.28 | AM29: 15 | AN29: ='Input-Start'!W34*(1+Inflation_Rate)^Year -> 0 | AO29: ='Input-Start'!X34*(1+Inflation_Rate)^'Input-Detail'!$AM29 -> 0 | AP29: =Cost_PY*(PY_for_Inf+PY!$Q21)*(1+Inflation_Rate)^$AM29 -> 2403180.1 | AQ29: =AQ28*(1+Inflation_Rate) -> 13018.376 | AR29: =AR28*(1+Inflation_Rate) -> 470132.25 | AW29: Prevailing Travel Speed (mph) | AZ29: ='Input-Start'!AR20 -> 55 | BG29: 16 | BH29: =BH$13+(BH$33-BH$13)*$D30/$D$34 -> 0.83 | BI29: =1-BH29 -> 0.17 | BJ29: =BJ$13+(BJ$33-BJ$13)*$D30/$D$34 -> 0.966 | BK29: =1-BJ29 -> 0.034 | BL29: =BL$13+(BL$33-BL$13)*$D30/$D$34 -> 0.64 | BM29: =1-BL29 -> 0.36 | BS29: Inflation Rate | BV29: ='Input-Start'!BA30 -> 0.03
D30: 16 | E30: =E$14+(E$34-E$14)*$D30/$D$34 -> 27803235 | F30: =F$14+(F$34-F$14)*$D30/$D$34 -> 0.792 | L30: 12 | M30: =E26/$N$18 -> 11041.814 | N30: =E26/M30 -> 2319.0455 | O30: =O29 -> 2 | P30: =P29 -> 0.3 | U30: 12 | V30: =E26/$W$18 -> 11041.814 | W30: =E26/V30 -> 2319.0455 | X30: =X29 -> 2 | Y30: =Y29 -> 0.7 | AD30: 16 | AE30: ='Input-Start'!N36^(1+Inflation_Rate)^Year -> 0 | AF30: =Cost_PY*(PY_for_Inf+PY!$L22)*(1+Inflation_Rate)^Year -> 9050246.4 | AG30: =AG29*(1+Inflation_Rate) -> 13409.184 | AH30: =AH29*(1+Inflation_Rate) -> 476790.38 | AM30: 16 | AN30: ='Input-Start'!W35*(1+Inflation_Rate)^Year -> 0 | AO30: ='Input-Start'!X35*(1+Inflation_Rate)^'Input-Detail'!$AM30 -> 0 | AP30: =Cost_PY*(PY_for_Inf+PY!$Q22)*(1+Inflation_Rate)^$AM30 -> 2045174.9 | AQ30: =AQ29*(1+Inflation_Rate) -> 13408.927 | AR30: =AR29*(1+Inflation_Rate) -> 484236.22 | AW30: Mode Split among ETC Users | BG30: 17 | BH30: =BH$13+(BH$33-BH$13)*$D31/$D$34 -> 0.83 | BI30: =1-BH30 -> 0.17 | BJ30: =BJ$13+(BJ$33-BJ$13)*$D31/$D$34 -> 0.9745 | BK30: =1-BJ30 -> 0.0255 | BL30: =BL$13+(BL$33-BL$13)*$D31/$D$34 -> 0.64 | BM30: =1-BL30 -> 0.36 | BS30: Annual Interest Rate | BV30: ='Input-Start'!BA31 -> 0.05
D31: 17 | E31: =E$14+(E$34-E$14)*$D31/$D$34 -> 28352426 | F31: =F$14+(F$34-F$14)*$D31/$D$34 -> 0.8415 | L31: 13 | M31: =E27/$N$18 -> 11278.632 | N31: =E27/M31 -> 2319.0455 | O31: =O30 -> 2 | P31: =P30 -> 0.3 | U31: 13 | V31: =E27/$W$18 -> 11278.632 | W31: =E27/V31 -> 2319.0455 | X31: =X30 -> 2 | Y31: =Y30 -> 0.7 | AD31: 17 | AE31: ='Input-Start'!N37^(1+Inflation_Rate)^Year -> 0 | AF31: =Cost_PY*(PY_for_Inf+PY!$L23)*(1+Inflation_Rate)^Year -> 9490671.1 | AG31: =AG30*(1+Inflation_Rate) -> 13811.459 | AH31: =AH30*(1+Inflation_Rate) -> 491094.09 | AM31: 17 | AN31: ='Input-Start'!W36*(1+Inflation_Rate)^Year -> 0 | AO31: ='Input-Start'!X36*(1+Inflation_Rate)^'Input-Detail'!$AM31 -> 0 | AP31: =Cost_PY*(PY_for_Inf+PY!$Q23)*(1+Inflation_Rate)^$AM31 -> 1710000.8 | AQ31: =AQ30*(1+Inflation_Rate) -> 13811.195 | AR31: =AR30*(1+Inflation_Rate) -> 498763.3 | AX31: Auto | AZ31: ='Input-Start'!AR23 -> 0.9476 | BG31: 18 | BH31: =BH$13+(BH$33-BH$13)*$D32/$D$34 -> 0.83 | BI31: =1-BH31 -> 0.17 | BJ31: =BJ$13+(BJ$33-BJ$13)*$D32/$D$34 -> 0.983 | BK31: =1-BJ31 -> 0.017 | BL31: =BL$13+(BL$33-BL$13)*$D32/$D$34 -> 0.64 | BM31: =1-BL31 -> 0.36 | BS31: Discount Rate | BV31: ='Input-Start'!BA32 -> 0.02
D32: 18 | E32: =E$14+(E$34-E$14)*$D32/$D$34 -> 28901617 | F32: =F$14+(F$34-F$14)*$D32/$D$34 -> 0.891 | L32: 14 | M32: =E28/$N$18 -> 11515.45 | N32: =E28/M32 -> 2319.0455 | O32: =O31 -> 2 | P32: =P31 -> 0.3 | U32: 14 | V32: =E28/$W$18 -> 11515.45 | W32: =E28/V32 -> 2319.0455 | X32: =X31 -> 2 | Y32: =Y31 -> 0.7 | AD32: 18 | AE32: ='Input-Start'!N38^(1+Inflation_Rate)^Year -> 0 | AF32: =Cost_PY*(PY_for_Inf+PY!$L24)*(1+Inflation_Rate)^Year -> 9949376.1 | AG32: =AG31*(1+Inflation_Rate) -> 14225.803 | AH32: =AH31*(1+Inflation_Rate) -> 505826.91 | AM32: 18 | AN32: ='Input-Start'!W37*(1+Inflation_Rate)^Year -> 0 | AO32: ='Input-Start'!X37*(1+Inflation_Rate)^'Input-Detail'!$AM32 -> 0 | AP32: =Cost_PY*(PY_for_Inf+PY!$Q24)*(1+Inflation_Rate)^$AM32 -> 1270558 | AQ32: =AQ31*(1+Inflation_Rate) -> 14225.531 | AR32: =AR31*(1+Inflation_Rate) -> 513726.2 | AX32: Truck | AZ32: ='Input-Start'!AR24 -> 0.0511 | BG32: 19 | BH32: =BH$13+(BH$33-BH$13)*$D33/$D$34 -> 0.83 | BI32: =1-BH32 -> 0.17 | BJ32: =BJ$13+(BJ$33-BJ$13)*$D33/$D$34 -> 0.9915 | BK32: =1-BJ32 -> 0.0085 | BL32: =BL$13+(BL$33-BL$13)*$D33/$D$34 -> 0.64 | BM32: =1-BL32 -> 0.36 | BS32: Personal Year (PY)
D33: 19 | E33: =E$14+(E$34-E$14)*$D33/$D$34 -> 29450809 | F33: =F$14+(F$34-F$14)*$D33/$D$34 -> 0.9405 | L33: 15 | M33: =E29/$N$18 -> 11752.268 | N33: =E29/M33 -> 2319.0455 | O33: =O32 -> 2 | P33: =P32 -> 0.3 | U33: 15 | V33: =E29/$W$18 -> 11752.268 | W33: =E29/V33 -> 2319.0455 | X33: =X32 -> 2 | Y33: =Y32 -> 0.7 | AD33: 19 | AE33: ='Input-Start'!N39^(1+Inflation_Rate)^Year -> 0 | AF33: =Cost_PY*(PY_for_Inf+PY!$L25)*(1+Inflation_Rate)^Year -> 10427062 | AG33: =AG32*(1+Inflation_Rate) -> 14652.577 | AH33: =AH32*(1+Inflation_Rate) -> 521001.72 | AM33: 19 | AN33: ='Input-Start'!W38*(1+Inflation_Rate)^Year -> 0 | AO33: ='Input-Start'!X38*(1+Inflation_Rate)^'Input-Detail'!$AM33 -> 0 | AP33: =Cost_PY*(PY_for_Inf+PY!$Q25)*(1+Inflation_Rate)^$AM33 -> 785468.51 | AQ33: =AQ32*(1+Inflation_Rate) -> 14652.297 | AR33: =AR32*(1+Inflation_Rate) -> 529137.99 | AX33: Bus | AZ33: ='Input-Start'!AR25 -> 0.0013 | BG33: 20 | BH33: ='Input-Start'!AI22 -> 0.83 | BI33: =1-BH33 -> 0.17 | BJ33: ='Input-Start'!AI25 -> 1 | BK33: =1-BJ33 -> 0 | BL33: ='Input-Start'!AI28 -> 0.64 | BM33: =1-BL33 -> 0.36 | BT33: Hours per Unit Personal Year | BV33: ='Input-Start'!BA34 -> 1768
D34: 20 | E34: ='Input-Start'!G22 -> 30000000 | F34: ='Input-Start'!G23 -> 0.99 | L34: 16 | M34: =E30/$N$18 -> 11989.085 | N34: =E30/M34 -> 2319.0455 | O34: =O33 -> 2 | P34: =P33 -> 0.3 | U34: 16 | V34: =E30/$W$18 -> 11989.085 | W34: =E30/V34 -> 2319.0455 | X34: =X33 -> 2 | Y34: =Y33 -> 0.7 | AD34: 20 | AE34: ='Input-Start'!N40^(1+Inflation_Rate)^Year -> 0 | AF34: =Cost_PY*(PY_for_Inf+PY!$L26)*(1+Inflation_Rate)^Year -> 10924454 | AG34: =AG33*(1+Inflation_Rate) -> 15092.154 | AH34: =AH33*(1+Inflation_Rate) -> 536631.77 | AM34: 20 | AN34: ='Input-Start'!W39*(1+Inflation_Rate)^Year -> 0 | AO34: ='Input-Start'!X39*(1+Inflation_Rate)^'Input-Detail'!$AM34 -> 0 | AP34: =Cost_PY*(PY_for_Inf+PY!$Q26)*(1+Inflation_Rate)^$AM34 -> 182799.43 | AQ34: =AQ33*(1+Inflation_Rate) -> 15091.865 | AR34: =AR33*(1+Inflation_Rate) -> 545012.13 | AW34: Average Vehicle Occupancy | BT34: PY for Information Technology | BV34: ='Input-Start'!BA35 -> 0.11
L35: 17 | M35: =E31/$N$18 -> 12225.903 | N35: =E31/M35 -> 2319.0455 | O35: =O34 -> 2 | P35: =P34 -> 0.3 | U35: 17 | V35: =E31/$W$18 -> 12225.903 | W35: =E31/V35 -> 2319.0455 | X35: =X34 -> 2 | Y35: =Y34 -> 0.7 | AX35: Auto | AZ35: ='Input-Start'!AR27 -> 1.8 | BT35: PY for Program Costs (Toll Collection) | BV35: ='Input-Start'!BA36 -> 61.5
L36: 18 | M36: =E32/$N$18 -> 12462.721 | N36: =E32/M36 -> 2319.0455 | O36: =O35 -> 2 | P36: =P35 -> 0.3 | U36: 18 | V36: =E32/$W$18 -> 12462.721 | W36: =E32/V36 -> 2319.0455 | X36: =X35 -> 2 | Y36: =Y35 -> 0.7 | AX36: Truck | AZ36: ='Input-Start'!AR28 -> 1.1 | BT36: Unit Cost per Personal Year | BV36: ='Input-Start'!BA37 -> 65000
L37: 19 | M37: =E33/$N$18 -> 12699.539 | N37: =E33/M37 -> 2319.0455 | O37: =O36 -> 2 | P37: =P36 -> 0.3 | U37: 19 | V37: =E33/$W$18 -> 12699.539 | W37: =E33/V37 -> 2319.0455 | X37: =X36 -> 2 | Y37: =Y36 -> 0.7 | AX37: Bus | AZ37: ='Input-Start'!AR29 -> 20
L38: 20 | M38: =E34/$N$18 -> 12936.357 | N38: =E34/M38 -> 2319.0455 | O38: =O37 -> 2 | P38: =P37 -> 0.3 | U38: 20 | V38: =E34/$W$18 -> 12936.357 | W38: =E34/V38 -> 2319.0455 | X38: =X37 -> 2 | Y38: =Y37 -> 0.7 | AW38: Time Value for Each Mode ($/hr)
AX39: Auto | AZ39: ='Input-Start'!AR32 -> 12.75
AX40: Truck | AZ40: ='Input-Start'!AR33 -> 33.41
AX41: Bus (per rider) | AZ41: ='Input-Start'!AR34 -> 12.75
AC44: Footnote:
AC45: For costs other than staff:
AC46: C(m,n) of item m in year n = C(m,n-1)*(1+ inflation rate), given the amount of cost (m,o)
AC47: in base year
AC49: For staff costs,
AC50: SC(n) of staff costs in year n =
AC51: ($/PY in base year)*[(PY for information technology)+(PY for toll collection)]*(1+inflation rate)n
AC52: Assumpions:
AC53: a. PY needed for technology information doesn't change over time.
AC54: b. PYs needed for toll collection are estimated in sheet "PY" based on traffic level.
AC56: Inflation Rate (If) | AF56: ='Input-Detail'!$BV$29 -> 0.03
AC57: $/PY(unit cost of personal year): | AF57: ='Input-Detail'!$BV$36 -> 65000
AC58: PY for Information Technology: | AF58: =PY_for_Inf -> 0.11

Sheet Results Summary
A2: Analytical Result: | C2: NPV1 = | D2: ='Results-Detail'!R26 -> 60859829 | E2: PVB2 = | F2: ='Results-Detail'!Q26 -> 67060995 | G2: NPC3 = | H2: ='Results-Detail'!P26 -> 6201165.9
C3: B/C4 = | D3: ='Results-Detail'!Q26/'Results-Detail'!P26 -> 10.814256 | E3: IRR5= | F3: =IRR(B13:B33) -> 0.3178927
A4: 1NPV: net present value, NPV = PVB - PVC
A5: 2PVB: present value of benefits
A6: 3PVC: present value of costs
A7: 4B/C: Total benefit over capital investment, B/C = PVB/PVC
A8: 5IRR: Internal Rate of Return
A10: y Overall Values of Benefits & Costs ($ in base year)
A11: Discount Rate: | C11: ='Input-Detail'!BV31 -> 0.02
A12: Year | B12: B-C | C12: NPV | D12: Capital Invesment | E12: PVC ($ in Base Year) | F12: DFuel Value* | G12: Dtime Value | H12: DEnv Value** | I12: DCost Reduction | J12: DOperational Revenue*** | K12: DInterest Gain | L12: Total Benefit | M12: PVB ($ in Base Year)
A13: Base | B13: =L13-D13 -> -3013979.5 | C13: =M13-E13 -> -3013979.5 | D13: ='Results-Detail'!B5 -> 3009339.7 | E13: ='Results-Detail'!C5 -> 3009339.7 | F13: ='Results-Detail'!F5 -> 0 | G13: ='Results-Detail'!G5 -> 0 | H13: ='Results-Detail'!H5 -> 0 | I13: ='Results-Detail'!I5 -> -4639.84 | J13: ='Results-Detail'!J5 -> 0 | K13: ='Results-Detail'!K5 -> 0 | L13: ='Results-Detail'!L5 -> -4639.84 | M13: ='Results-Detail'!M5 -> -4639.84
A14: 1 | B14: =L14-D14 -> 232661.25 | C14: =M14-E14 -> 228099.26 | D14: ='Results-Detail'!B6 -> 0 | E14: ='Results-Detail'!C6 -> 0 | F14: ='Results-Detail'!F6 -> 8778.3529 | G14: ='Results-Detail'!G6 -> 3338.5093 | H14: ='Results-Detail'!H6 -> 311.09272 | I14: ='Results-Detail'!I6 -> 220233.29 | J14: ='Results-Detail'!J6 -> 13897.767 | K14: ='Results-Detail'!K6 -> -13897.767 | L14: ='Results-Detail'!L6 -> 232661.25 | M14: ='Results-Detail'!M6 -> 228099.26
A15: 2 | B15: =L15-D15 -> 158447.87 | C15: =M15-E15 -> 152295.14 | D15: ='Results-Detail'!B7 -> 302158.11 | E15: ='Results-Detail'!C7 -> 290424.94 | F15: ='Results-Detail'!F7 -> 18591 | G15: ='Results-Detail'!G7 -> 12508.863 | H15: ='Results-Detail'!H7 -> 733.21246 | I15: ='Results-Detail'!I7 -> 428772.9 | J15: ='Results-Detail'!J7 -> 28575.744 | K15: ='Results-Detail'!K7 -> -28575.744 | L15: ='Results-Detail'!L7 -> 460605.98 | M15: ='Results-Detail'!M7 -> 442720.09
A16: 3 | B16: =L16-D16 -> 222516.26 | C16: =M16-E16 -> 209682.04 | D16: ='Results-Detail'!B8 -> 490176.57 | E16: ='Results-Detail'!C8 -> 461904.33 | F16: ='Results-Detail'!F8 -> 29507.327 | G16: ='Results-Detail'!G8 -> 21311.698 | H16: ='Results-Detail'!H8 -> 1191.376 | I16: ='Results-Detail'!I8 -> 660682.43 | J16: ='Results-Detail'!J8 -> 44033.928 | K16: ='Results-Detail'!K8 -> -44033.928 | L16: ='Results-Detail'!L8 -> 712692.83 | M16: ='Results-Detail'!M8 -> 671586.37
A17: 4 | B17: =L17-D17 -> 681356.37 | C17: =M17-E17 -> 629467.96 | D17: ='Results-Detail'!B9 -> 308165.44 | E17: ='Results-Detail'!C9 -> 284697.23 | F17: ='Results-Detail'!F9 -> 41600.408 | G17: ='Results-Detail'!G9 -> 28739.717 | H17: ='Results-Detail'!H9 -> 1673.6152 | I17: ='Results-Detail'!I9 -> 917508.06 | J17: ='Results-Detail'!J9 -> 60272.322 | K17: ='Results-Detail'!K9 -> -60272.322 | L17: ='Results-Detail'!L9 -> 989521.8 | M17: ='Results-Detail'!M9 -> 914165.19
A18: 5 | B18: =L18-D18 -> 1004000 | C18: =M18-E18 -> 909353.72 | D18: ='Results-Detail'!B10 -> 335688.68 | E18: ='Results-Detail'!C10 -> 304043.58 | F18: ='Results-Detail'!F10 -> 54947.178 | G18: ='Results-Detail'!G10 -> 37321.349 | H18: ='Results-Detail'!H10 -> 2217.2843 | I18: ='Results-Detail'!I10 -> 1245202.9 | J18: ='Results-Detail'!J10 -> 77290.924 | K18: ='Results-Detail'!K10 -> -77290.924 | L18: ='Results-Detail'!L10 -> 1339688.7 | M18: ='Results-Detail'!M10 -> 1213397.3
A19: 6 | B19: =L19-D19 -> 1313275.9 | C19: =M19-E19 -> 1166151.4 | D19: ='Results-Detail'!B11 -> 365422.99 | E19: ='Results-Detail'!C11 -> 324485.16 | F19: ='Results-Detail'!F11 -> 69628.615 | G19: ='Results-Detail'!G11 -> 48069.037 | H19: ='Results-Detail'!H11 -> 2841.6568 | I19: ='Results-Detail'!I11 -> 1558159.5 | J19: ='Results-Detail'!J11 -> 95089.735 | K19: ='Results-Detail'!K11 -> -95089.735 | L19: ='Results-Detail'!L11 -> 1678698.9 | M19: ='Results-Detail'!M11 -> 1490636.5
A20: 7 | B20: =L20-D20 -> 1650849.4 | C20: =M20-E20 -> 1437163.8 | D20: ='Results-Detail'!B12 -> 397533.36 | E20: ='Results-Detail'!C12 -> 346076.71 | F20: ='Results-Detail'!F12 -> 85729.925 | G20: ='Results-Detail'!G12 -> 57930.594 | H20: ='Results-Detail'!H12 -> 3505.951 | I20: ='Results-Detail'!I12 -> 1901216.3 | J20: ='Results-Detail'!J12 -> 113668.75 | K20: ='Results-Detail'!K12 -> -113668.75 | L20: ='Results-Detail'!L12 -> 2048382.8 | M20: ='Results-Detail'!M12 -> 1783240.5
A21: 8 | B21: =L21-D21 -> 2068012.4 | C21: =M21-E21 -> 1765028.6 | D21: ='Results-Detail'!B13 -> 432200.42 | E21: ='Results-Detail'!C13 -> 368878.89 | F21: ='Results-Detail'!F13 -> 103340.74 | G21: ='Results-Detail'!G13 -> 67937.569 | H21: ='Results-Detail'!H13 -> 4228.3637 | I21: ='Results-Detail'!I13 -> 2324706.1 | J21: ='Results-Detail'!J13 -> 133027.98 | K21: ='Results-Detail'!K13 -> -133027.98 | L21: ='Results-Detail'!L13 -> 2500212.8 | M21: ='Results-Detail'!M13 -> 2133907.5
A22: 9 | B22: =L22-D22 -> 2472752.3 | C22: =M22-E22 -> 2069088.5 | D22: ='Results-Detail'!B14 -> 469613.96 | E22: ='Results-Detail'!C14 -> 392951.96 | F22: ='Results-Detail'!F14 -> 122555.33 | G22: ='Results-Detail'!G14 -> 79567.611 | H22: ='Results-Detail'!H14 -> 5036.3543 | I22: ='Results-Detail'!I14 -> 2735207 | J22: ='Results-Detail'!J14 -> 153167.42 | K22: ='Results-Detail'!K14 -> -153167.42 | L22: ='Results-Detail'!L14 -> 2942366.2 | M22: ='Results-Detail'!M14 -> 2462040.5
A23: 10 | B23: =L23-D23 -> 2911728.4 | C23: =M23-E23 -> 2388631.4 | D23: ='Results-Detail'!B15 -> 509982.67 | E23: ='Results-Detail'!C15 -> 418363.41 | F23: ='Results-Detail'!F15 -> 143472.78 | G23: ='Results-Detail'!G15 -> 90498.451 | H23: ='Results-Detail'!H15 -> 5897.007 | I23: ='Results-Detail'!I15 -> 3181842.8 | J23: ='Results-Detail'!J15 -> 174087.07 | K23: ='Results-Detail'!K15 -> -174087.07 | L23: ='Results-Detail'!L15 -> 3421711 | M23: ='Results-Detail'!M15 -> 2806994.8
A24: 11 | B24: =L24-D24 -> 3995492 | C24: =M24-E24 -> 3213426.5 | D24: ='Results-Detail'!B16 -> 0 | E24: ='Results-Detail'!C16 -> 0 | F24: ='Results-Detail'!F16 -> 166197.28 | G24: ='Results-Detail'!G16 -> 102701.04 | H24: ='Results-Detail'!H16 -> 6846.8788 | I24: ='Results-Detail'!I16 -> 3719746.8 | J24: ='Results-Detail'!J16 -> 195786.92 | K24: ='Results-Detail'!K16 -> -195786.92 | L24: ='Results-Detail'!L16 -> 3995492 | M24: ='Results-Detail'!M16 -> 3213426.5
A25: 12 | B25: =L25-D25 -> 4560534 | C25: =M25-E25 -> 3595949.9 | D25: ='Results-Detail'!B17 -> 0 | E25: ='Results-Detail'!C17 -> 0 | F25: ='Results-Detail'!F17 -> 190838.29 | G25: ='Results-Detail'!G17 -> 114855.05 | H25: ='Results-Detail'!H17 -> 7868.4317 | I25: ='Results-Detail'!I17 -> 4246972.2 | J25: ='Results-Detail'!J17 -> 218266.98 | K25: ='Results-Detail'!K17 -> -218266.98 | L25: ='Results-Detail'!L17 -> 4560534 | M25: ='Results-Detail'!M17 -> 3595949.9
... A33: 20 | B33: =L33-D33 -> 11452876 | C33: =M33-E33 -> 7707457.5 | D33: ='Results-Detail'!B25 -> 0 | E33: ='Results-Detail'!C25 -> 0 | F33: ='Results-Detail'!F25 -> 472045.23 | G33: ='Results-Detail'!G25 -> 228009.63 | H33: ='Results-Detail'!H25 -> 19546.739 | I33: ='Results-Detail'!I25 -> 10733275 | J33: ='Results-Detail'!J25 -> 426195 | K33: ='Results-Detail'!K25 -> -426195 | L33: ='Results-Detail'!L25 -> 11452876 | M33: ='Results-Detail'!M25 -> 7707457.5
A34: Total | C34: =SUM(C13:C33) -> 60859829 | E34: =SUM(E13:E33) -> 6201165.9 | M34: =SUM(M13:M33) -> 67060995 | S34: b/c | T34: =C34/#REF! -> #REF!
A36: *Fuel Value is the costs reduction of purchasing fuels.
A37: ** Environmental Value is estimated by the value of reduction in fuel emission.
A38: *** Agency's operational revenue is equal to user's loss in interest gain.

Sheet Results-Detail
A2: y Total Cost Streams of Baseline and ETC | E2: y Total Benefit Streams | O2: y Total Net Benefit ($ in base year)
A3: Discount Rate: | C3: ='Input-Detail'!BV31 -> 0.02
A4: Year | B4: Capital Invesment | C4: PVC ($ in Base Year) | E4: Year | F4: DFuel Value | G4: DTime Value | H4: DEnv Value | I4: Agency Cost Reduction | J4: DOperational Revenue | K4: DInterest Gain | L4: Total Benefit | M4: PVB ($ in Base Year) | O4: Year | P4: PVC | Q4: PVB | R4: NPV
A5: Base | B5: =B31+B57+B83 -> 3009339.7 | C5: =B5/(1+Discount_Rate)^0 -> 3009339.7 | E5: Base | F5: =F57 -> 0 | G5: =G57 -> 0 | H5: =F83 -> 0 | I5: =F31 -> -4639.84 | J5: =G31 -> 0 | K5: =H57 -> 0 | L5: =SUM(F5:K5) -> -4639.84 | M5: =L5/(1+Discount_Rate)^0 -> -4639.84 | O5: Base | P5: =C5 -> 3009339.7 | Q5: =M5 -> -4639.84 | R5: =Q5-P5 -> -3013979.5
A6: 1 | B6: =B32+B58+B84 -> 0 | C6: =B6/(1+Discount_Rate)^A6 -> 0 | E6: 1 | F6: =F58 -> 8778.3529 | G6: =G58 -> 3338.5093 | H6: =F84 -> 311.09272 | I6: =F32 -> 220233.29 | J6: =G32 -> 13897.767 | K6: =H58 -> -13897.767 | L6: =SUM(F6:K6) -> 232661.25 | M6: =L6/(1+Discount_Rate)^E6 -> 228099.26 | O6: 1 | P6: =C6 -> 0 | Q6: =M6 -> 228099.26 | R6: =Q6-P6 -> 228099.26
A7: 2 | B7: =B33+B59+B85 -> 302158.11 | C7: =B7/(1+Discount_Rate)^A7 -> 290424.94 | E7: 2 | F7: =F59 -> 18591 | G7: =G59 -> 12508.863 | H7: =F85 -> 733.21246 | I7: =F33 -> 428772.9 | J7: =G33 -> 28575.744 | K7: =H59 -> -28575.744 | L7: =SUM(F7:K7) -> 460605.98 | M7: =L7/(1+Discount_Rate)^E7 -> 442720.09 | O7: 2 | P7: =C7 -> 290424.94 | Q7: =M7 -> 442720.09 | R7: =Q7-P7 -> 152295.14
A8: 3 | B8: =B34+B60+B86 -> 490176.57 | C8: =B8/(1+Discount_Rate)^A8 -> 461904.33 | E8: 3 | F8: =F60 -> 29507.327 | G8: =G60 -> 21311.698 | H8: =F86 -> 1191.376 | I8: =F34 -> 660682.43 | J8: =G34 -> 44033.928 | K8: =H60 -> -44033.928 | L8: =SUM(F8:K8) -> 712692.83 | M8: =L8/(1+Discount_Rate)^E8 -> 671586.37 | O8: 3 | P8: =C8 -> 461904.33 | Q8: =M8 -> 671586.37 | R8: =Q8-P8 -> 209682.04
A9: 4 | B9: =B35+B61+B87 -> 308165.44 | C9: =B9/(1+Discount_Rate)^A9 -> 284697.23 | E9: 4 | F9: =F61 -> 41600.408 | G9: =G61 -> 28739.717 | H9: =F87 -> 1673.6152 | I9: =F35 -> 917508.06 | J9: =G35 -> 60272.322 | K9: =H61 -> -60272.322 | L9: =SUM(F9:K9) -> 989521.8 | M9: =L9/(1+Discount_Rate)^E9 -> 914165.19 | O9: 4 | P9: =C9 -> 284697.23 | Q9: =M9 -> 914165.19 | R9: =Q9-P9 -> 629467.96
A10: 5 | B10: =B36+B62+B88 -> 335688.68 | C10: =B10/(1+Discount_Rate)^A10 -> 304043.58 | E10: 5 | F10: =F62 -> 54947.178 | G10: =G62 -> 37321.349 | H10: =F88 -> 2217.2843 | I10: =F36 -> 1245202.9 | J10: =G36 -> 77290.924 | K10: =H62 -> -77290.924 | L10: =SUM(F10:K10) -> 1339688.7 | M10: =L10/(1+Discount_Rate)^E10 -> 1213397.3 | O10: 5 | P10: =C10 -> 304043.58 | Q10: =M10 -> 1213397.3 | R10: =Q10-P10 -> 909353.72
A11: 6 | B11: =B37+B63+B89 -> 365422.99 | C11: =B11/(1+Discount_Rate)^A11 -> 324485.16 | E11: 6 | F11: =F63 -> 69628.615 | G11: =G63 -> 48069.037 | H11: =F89 -> 2841.6568 | I11: =F37 -> 1558159.5 | J11: =G37 -> 95089.735 | K11: =H63 -> -95089.735 | L11: =SUM(F11:K11) -> 1678698.9 | M11: =L11/(1+Discount_Rate)^E11 -> 1490636.5 | O11: 6 | P11: =C11 -> 324485.16 | Q11: =M11 -> 1490636.5 | R11: =Q11-P11 -> 1166151.4
A12: 7 | B12: =B38+B64+B90 -> 397533.36 | C12: =B12/(1+Discount_Rate)^A12 -> 346076.71 | E12: 7 | F12: =F64 -> 85729.925 | G12: =G64 -> 57930.594 | H12: =F90 -> 3505.951 | I12: =F38 -> 1901216.3 | J12: =G38 -> 113668.75 | K12: =H64 -> -113668.75 | L12: =SUM(F12:K12) -> 2048382.8 | M12: =L12/(1+Discount_Rate)^E12 -> 1783240.5 | O12: 7 | P12: =C12 -> 346076.71 | Q12: =M12 -> 1783240.5 | R12: =Q12-P12 -> 1437163.8
A13: 8 | B13: =B39+B65+B91 -> 432200.42 | C13: =B13/(1+Discount_Rate)^A13 -> 368878.89 | E13: 8 | F13: =F65 -> 103340.74 | G13: =G65 -> 67937.569 | H13: =F91 -> 4228.3637 | I13: =F39 -> 2324706.1 | J13: =G39 -> 133027.98 | K13: =H65 -> -133027.98 | L13: =SUM(F13:K13) -> 2500212.8 | M13: =L13/(1+Discount_Rate)^E13 -> 2133907.5 | O13: 8 | P13: =C13 -> 368878.89 | Q13: =M13 -> 2133907.5 | R13: =Q13-P13 -> 1765028.6
A14: 9 | B14: =B40+B66+B92 -> 469613.96 | C14: =B14/(1+Discount_Rate)^A14 -> 392951.96 | E14: 9 | F14: =F66 -> 122555.33 | G14: =G66 -> 79567.611 | H14: =F92 -> 5036.3543 | I14: =F40 -> 2735207 | J14: =G40 -> 153167.42 | K14: =H66 -> -153167.42 | L14: =SUM(F14:K14) -> 2942366.2 | M14: =L14/(1+Discount_Rate)^E14 -> 2462040.5 | O14: 9 | P14: =C14 -> 392951.96 | Q14: =M14 -> 2462040.5 | R14: =Q14-P14 -> 2069088.5
A15: 10 | B15: =B41+B67+B93 -> 509982.67 | C15: =B15/(1+Discount_Rate)^A15 -> 418363.41 | E15: 10 | F15: =F67 -> 143472.78 | G15: =G67 -> 90498.451 | H15: =F93 -> 5897.007 | I15: =F41 -> 3181842.8 | J15: =G41 -> 174087.07 | K15: =H67 -> -174087.07 | L15: =SUM(F15:K15) -> 3421711 | M15: =L15/(1+Discount_Rate)^E15 -> 2806994.8 | O15: 10 | P15: =C15 -> 418363.41 | Q15: =M15 -> 2806994.8 | R15: =Q15-P15 -> 2388631.4
A16: 11 | B16: =B42+B68+B94 -> 0 | C16: =B16/(1+Discount_Rate)^A16 -> 0 | E16: 11 | F16: =F68 -> 166197.28 | G16: =G68 -> 102701.04 | H16: =F94 -> 6846.8788 | I16: =F42 -> 3719746.8 | J16: =G42 -> 195786.92 | K16: =H68 -> -195786.92 | L16: =SUM(F16:K16) -> 3995492 | M16: =L16/(1+Discount_Rate)^E16 -> 3213426.5 | O16: 11 | P16: =C16 -> 0 | Q16: =M16 -> 3213426.5 | R16: =Q16-P16 -> 3213426.5
A17: 12 | B17: =B43+B69+B95 -> 0 | C17: =B17/(1+Discount_Rate)^A17 -> 0 | E17: 12 | F17: =F69 -> 190838.29 | G17: =G69 -> 114855.05 | H17: =F95 -> 7868.4317 | I17: =F43 -> 4246972.2 | J17: =G43 -> 218266.98 | K17: =H69 -> -218266.98 | L17: =SUM(F17:K17) -> 4560534 | M17: =L17/(1+Discount_Rate)^E17 -> 3595949.9 | O17: 12 | P17: =C17 -> 0 | Q17: =M17 -> 3595949.9 | R17: =Q17-P17 -> 3595949.9
... A25: 20 | B25: =B51+B77+B103 -> 0 | C25: =B25/(1+Discount_Rate)^A25 -> 0 | E25: 20 | F25: =F77 -> 472045.23 | G25: =G77 -> 228009.63 | H25: =F103 -> 19546.739 | I25: =F51 -> 10733275 | J25: =G51 -> 426195 | K25: =H77 -> -426195 | L25: =SUM(F25:K25) -> 11452876 | M25: =L25/(1+Discount_Rate)^E25 -> 7707457.5 | O25: 20 | P25: =C25 -> 0 | Q25: =M25 -> 7707457.5 | R25: =Q25-P25 -> 7707457.5
O26: Total | P26: =SUM(P5:P25) -> 6201165.9 | Q26: =SUM(Q5:Q25) -> 67060995 | R26: =SUM(R5:R25) -> 60859829
A28: a Cost Streams of Toll Agency | E28: a Benefit Streams of Toll Agency | O28: a Net Benefit of Toll Agency ($ in base year)
A30: Year | B30: Capital Investment | C30: PVC ($ in Base Year) | E30: Year | F30: Cost Reduction | G30: DOperational Revenue* | H30: Total Benefit | I30: PVB ($ in Base Year) | O30: Year | P30: PVC | Q30: PVB | R30: NPV
A31: Base | B31: ='Input-Detail'!AN14 -> 3009339.7 | C31: =B31/(1+Discount_Rate)^0 -> 3009339.7 | E31: Base | F31: ='Agency Costs Reduction'!L6 -> -4639.84 | G31: ='Interest Gain'!T6 -> 0 | H31: =SUM(F31:G31) -> -4639.84 | I31: =H31/(1+Discount_Rate)^0 -> -4639.84 | O31: Base | P31: =C31 -> 3009339.7 | Q31: =I31 -> -4639.84 | R31: =Q31-P31 -> -3013979.5
A32: 1 | B32: ='Input-Detail'!AN15 -> 0 | C32: =B32/(1+Discount_Rate)^A32 -> 0 | E32: 1 | F32: ='Agency Costs Reduction'!L7 -> 220233.29 | G32: ='Interest Gain'!T7 -> 13897.767 | H32: =SUM(F32:G32) -> 234131.06 | I32: =H32/(1+Discount_Rate)^E32 -> 229540.25 | O32: 1 | P32: =C32 -> 0 | Q32: =I32 -> 229540.25 | R32: =Q32-P32 -> 229540.25
A33: 2 | B33: ='Input-Detail'!AN16 -> 302158.11 | C33: =B33/(1+Discount_Rate)^A33 -> 290424.94 | E33: 2 | F33: ='Agency Costs Reduction'!L8 -> 428772.9 | G33: ='Interest Gain'!T8 -> 28575.744 | H33: =SUM(F33:G33) -> 457348.65 | I33: =H33/(1+Discount_Rate)^E33 -> 439589.24 | O33: 2 | P33: =C33 -> 290424.94 | Q33: =I33 -> 439589.24 | R33: =Q33-P33 -> 149164.3
A34: 3 | B34: ='Input-Detail'!AN17 -> 490176.57 | C34: =B34/(1+Discount_Rate)^A34 -> 461904.33 | E34: 3 | F34: ='Agency Costs Reduction'!L9 -> 660682.43 | G34: ='Interest Gain'!T9 -> 44033.928 | H34: =SUM(F34:G34) -> 704716.36 | I34: =H34/(1+Discount_Rate)^E34 -> 664069.97 | O34: 3 | P34: =C34 -> 461904.33 | Q34: =I34 -> 664069.97 | R34: =Q34-P34 -> 202165.64
A35: 4 | B35: ='Input-Detail'!AN18 -> 308165.44 | C35: =B35/(1+Discount_Rate)^A35 -> 284697.23 | E35: 4 | F35: ='Agency Costs Reduction'!L10 -> 917508.06 | G35: ='Interest Gain'!T10 -> 60272.322 | H35: =SUM(F35:G35) -> 977780.39 | I35: =H35/(1+Discount_Rate)^E35 -> 903317.94 | O35: 4 | P35: =C35 -> 284697.23 | Q35: =I35 -> 903317.94 | R35: =Q35-P35 -> 618620.71
A36: 5 | B36: ='Input-Detail'!AN19 -> 335688.68 | C36: =B36/(1+Discount_Rate)^A36 -> 304043.58 | E36: 5 | F36: ='Agency Costs Reduction'!L11 -> 1245202.9 | G36: ='Interest Gain'!T11 -> 77290.924 | H36: =SUM(F36:G36) -> 1322493.8 | I36: =H36/(1+Discount_Rate)^E36 -> 1197823.4 | O36: 5 | P36: =C36 -> 304043.58 | Q36: =I36 -> 1197823.4 | R36: =Q36-P36 -> 893779.78
A37: 6 | B37: ='Input-Detail'!AN20 -> 365422.99 | C37: =B37/(1+Discount_Rate)^A37 -> 324485.16 | E37: 6 | F37: ='Agency Costs Reduction'!L12 -> 1558159.5 | G37: ='Interest Gain'!T12 -> 95089.735 | H37: =SUM(F37:G37) -> 1653249.3 | I37: =H37/(1+Discount_Rate)^E37 -> 1468038 | O37: 6 | P37: =C37 -> 324485.16 | Q37: =I37 -> 1468038 | R37: =Q37-P37 -> 1143552.9
A38: 7 | B38: ='Input-Detail'!AN21 -> 397533.36 | C38: =B38/(1+Discount_Rate)^A38 -> 346076.71 | E38: 7 | F38: ='Agency Costs Reduction'!L13 -> 1901216.3 | G38: ='Interest Gain'!T13 -> 113668.75 | H38: =SUM(F38:G38) -> 2014885.1 | I38: =H38/(1+Discount_Rate)^E38 -> 1754078.7 | O38: 7 | P38: =C38 -> 346076.71 | Q38: =I38 -> 1754078.7 | R38: =Q38-P38 -> 1408002
A39: 8 | B39: ='Input-Detail'!AN22 -> 432200.42 | C39: =B39/(1+Discount_Rate)^A39 -> 368878.89 | E39: 8 | F39: ='Agency Costs Reduction'!L14 -> 2324706.1 | G39: ='Interest Gain'!T14 -> 133027.98 | H39: =SUM(F39:G39) -> 2457734.1 | I39: =H39/(1+Discount_Rate)^E39 -> 2097652.4 | O39: 8 | P39: =C39 -> 368878.89 | Q39: =I39 -> 2097652.4 | R39: =Q39-P39 -> 1728773.5
A40: 9 | B40: ='Input-Detail'!AN23 -> 469613.96 | C40: =B40/(1+Discount_Rate)^A40 -> 392951.96 | E40: 9 | F40: ='Agency Costs Reduction'!L15 -> 2735207 | G40: ='Interest Gain'!T15 -> 153167.42 | H40: =SUM(F40:G40) -> 2888374.4 | I40: =H40/(1+Discount_Rate)^E40 -> 2416862.5 | O40: 9 | P40: =C40 -> 392951.96 | Q40: =I40 -> 2416862.5 | R40: =Q40-P40 -> 2023910.5
A41: 10 | B41: ='Input-Detail'!AN24 -> 509982.67 | C41: =B41/(1+Discount_Rate)^A41 -> 418363.41 | E41: 10 | F41: ='Agency Costs Reduction'!L16 -> 3181842.8 | G41: ='Interest Gain'!T16 -> 174087.07 | H41: =SUM(F41:G41) -> 3355929.9 | I41: =H41/(1+Discount_Rate)^E41 -> 2753031.4 | O41: 10 | P41: =C41 -> 418363.41 | Q41: =I41 -> 2753031.4 | R41: =Q41-P41 -> 2334667.9
A42: 11 | B42: ='Input-Detail'!AN25 -> 0 | C42: =B42/(1+Discount_Rate)^A42 -> 0 | E42: 11 | F42: ='Agency Costs Reduction'!L17 -> 3719746.8 | G42: ='Interest Gain'!T17 -> 195786.92 | H42: =SUM(F42:G42) -> 3915533.7 | I42: =H42/(1+Discount_Rate)^E42 -> 3149119 | O42: 11 | P42: =C42 -> 0 | Q42: =I42 -> 3149119 | R42: =Q42-P42 -> 3149119
A43: 12 | B43: ='Input-Detail'!AN26 -> 0 | C43: =B43/(1+Discount_Rate)^A43 -> 0 | E43: 12 | F43: ='Agency Costs Reduction'!L18 -> 4246972.2 | G43: ='Interest Gain'!T18 -> 218266.98 | H43: =SUM(F43:G43) -> 4465239.2 | I43: =H43/(1+Discount_Rate)^E43 -> 3520810.7 | O43: 12 | P43: =C43 -> 0 | Q43: =I43 -> 3520810.7 | R43: =Q43-P43 -> 3520810.7
... A51: 20 | B51: ='Input-Detail'!AN34 -> 0 | C51: =B51/(1+Discount_Rate)^A51 -> 0 | E51: 20 | F51: ='Agency Costs Reduction'!L26 -> 10733275 | G51: ='Interest Gain'!T26 -> 426195 | H51: =SUM(F51:G51) -> 11159470 | I51: =H51/(1+Discount_Rate)^E51 -> 7510003.2 | O51: 20 | P51: =C51 -> 0 | Q51: =I51 -> 7510003.2 | R51: =Q51-P51 -> 7510003.2
E52: *DOperational Benefit = the amount of DInterest Gain of users | O52: Total | P52: =SUM(P31:P51) -> 6201165.9 | Q52: =SUM(Q31:Q51) -> 65589981 | R52: =SUM(R31:R51) -> 59388815
A54: a Cost Streams of Users | E54: a Benefit Streams of Users | O54: a Net Benefit of Users ($ in base year)
A56: Year | B56: Capital Investment | C56: PVC ($ in Base Year) | E56: Year | F56: DFuel Value | G56: DTime Value | H56: DInterest Gain | I56: DTotal | J56: PVB ($ in Base Year) | O56: Year | P56: PVC | Q56: PVB | R56: NPV
A57: Base | B57: 0 | C57: =B57/(1+Discount_Rate)^0 -> 0 | E57: Base | F57: ='Fuel & Emission'!O6 -> 0 | G57: ='Time Value'!AH6 -> 0 | H57: =(-1)*'Interest Gain'!T6 -> 0 | I57: =SUM(F57:H57) -> 0 | J57: =I57/(1+Discount_Rate)^0 -> 0 | O57: Base | P57: =C57 -> 0 | Q57: =J57 -> 0 | R57: =Q57-P57 -> 0
A58: 1 | B58: 0 | C58: =B58/(1+Discount_Rate)^A58 -> 0 | E58: 1 | F58: ='Fuel & Emission'!O7 -> 8778.3529 | G58: ='Time Value'!AH7 -> 3338.5093 | H58: =(-1)*'Interest Gain'!T7 -> -13897.767 | I58: =SUM(F58:H58) -> -1780.9052 | J58: =I58/(1+Discount_Rate)^E58 -> -1745.9855 | O58: 1 | P58: =C58 -> 0 | Q58: =J58 -> -1745.9855 | R58: =Q58-P58 -> -1745.9855
A59: 2 | B59: 0 | C59: =B59/(1+Discount_Rate)^A59 -> 0 | E59: 2 | F59: ='Fuel & Emission'!O8 -> 18591 | G59: ='Time Value'!AH8 -> 12508.863 | H59: =(-1)*'Interest Gain'!T8 -> -28575.744 | I59: =SUM(F59:H59) -> 2524.1201 | J59: =I59/(1+Discount_Rate)^E59 -> 2426.1054 | O59: 2 | P59: =C59 -> 0 | Q59: =J59 -> 2426.1054 | R59: =Q59-P59 -> 2426.1054
A60: 3 | B60: 0 | C60: =B60/(1+Discount_Rate)^A60 -> 0 | E60: 3 | F60: ='Fuel & Emission'!O9 -> 29507.327 | G60: ='Time Value'!AH9 -> 21311.698 | H60: =(-1)*'Interest Gain'!T9 -> -44033.928 | I60: =SUM(F60:H60) -> 6785.097 | J60: =I60/(1+Discount_Rate)^E60 -> 6393.7484 | O60: 3 | P60: =C60 -> 0 | Q60: =J60 -> 6393.7484 | R60: =Q60-P60 -> 6393.7484
A61: 4 | B61: 0 | C61: =B61/(1+Discount_Rate)^A61 -> 0 | E61: 4 | F61: ='Fuel & Emission'!O10 -> 41600.408 | G61: ='Time Value'!AH10 -> 28739.717 | H61: =(-1)*'Interest Gain'!T10 -> -60272.322 | I61: =SUM(F61:H61) -> 10067.803 | J61: =I61/(1+Discount_Rate)^E61 -> 9301.0941 | O61: 4 | P61: =C61 -> 0 | Q61: =J61 -> 9301.0941 | R61: =Q61-P61 -> 9301.0941
A62: 5 | B62: 0 | C62: =B62/(1+Discount_Rate)^A62 -> 0 | E62: 5 | F62: ='Fuel & Emission'!O11 -> 54947.178 | G62: ='Time Value'!AH11 -> 37321.349 | H62: =(-1)*'Interest Gain'!T11 -> -77290.924 | I62: =SUM(F62:H62) -> 14977.603 | J62: =I62/(1+Discount_Rate)^E62 -> 13565.677 | O62: 5 | P62: =C62 -> 0 | Q62: =J62 -> 13565.677 | R62: =Q62-P62 -> 13565.677
A63: 6 | B63: 0 | C63: =B63/(1+Discount_Rate)^A63 -> 0 | E63: 6 | F63: ='Fuel & Emission'!O12 -> 69628.615 | G63: ='Time Value'!AH12 -> 48069.037 | H63: =(-1)*'Interest Gain'!T12 -> -95089.735 | I63: =SUM(F63:H63) -> 22607.917 | J63: =I63/(1+Discount_Rate)^E63 -> 20075.183 | O63: 6 | P63: =C63 -> 0 | Q63: =J63 -> 20075.183 | R63: =Q63-P63 -> 20075.183
A64: 7 | B64: 0 | C64: =B64/(1+Discount_Rate)^A64 -> 0 | E64: 7 | F64: ='Fuel & Emission'!O13 -> 85729.925 | G64: ='Time Value'!AH13 -> 57930.594 | H64: =(-1)*'Interest Gain'!T13 -> -113668.75 | I64: =SUM(F64:H64) -> 29991.764 | J64: =I64/(1+Discount_Rate)^E64 -> 26109.636 | O64: 7 | P64: =C64 -> 0 | Q64: =J64 -> 26109.636 | R64: =Q64-P64 -> 26109.636
A65: 8 | B65: 0 | C65: =B65/(1+Discount_Rate)^A65 -> 0 | E65: 8 | F65: ='Fuel & Emission'!O14 -> 103340.74 | G65: ='Time Value'!AH14 -> 67937.569 | H65: =(-1)*'Interest Gain'!T14 -> -133027.98 | I65: =SUM(F65:H65) -> 38250.328 | J65: =I65/(1+Discount_Rate)^E65 -> 32646.287 | O65: 8 | P65: =C65 -> 0 | Q65: =J65 -> 32646.287 | R65: =Q65-P65 -> 32646.287
A66: 9 | B66: 0 | C66: =B66/(1+Discount_Rate)^A66 -> 0 | E66: 9 | F66: ='Fuel & Emission'!O15 -> 122555.33 | G66: ='Time Value'!AH15 -> 79567.611 | H66: =(-1)*'Interest Gain'!T15 -> -153167.42 | I66: =SUM(F66:H66) -> 48955.518 | J66: =I66/(1+Discount_Rate)^E66 -> 40963.787 | O66: 9 | P66: =C66 -> 0 | Q66: =J66 -> 40963.787 | R66: =Q66-P66 -> 40963.787
A67: 10 | B67: 0 | C67: =B67/(1+Discount_Rate)^A67 -> 0 | E67: 10 | F67: ='Fuel & Emission'!O16 -> 143472.78 | G67: ='Time Value'!AH16 -> 90498.451 | H67: =(-1)*'Interest Gain'!T16 -> -174087.07 | I67: =SUM(F67:H67) -> 59884.169 | J67: =I67/(1+Discount_Rate)^E67 -> 49125.876 | O67: 10 | P67: =C67 -> 0 | Q67: =J67 -> 49125.876 | R67: =Q67-P67 -> 49125.876
A68: 11 | B68: 0 | C68: =B68/(1+Discount_Rate)^A68 -> 0 | E68: 11 | F68: ='Fuel & Emission'!O17 -> 166197.28 | G68: ='Time Value'!AH17 -> 102701.04 | H68: =(-1)*'Interest Gain'!T17 -> -195786.92 | I68: =SUM(F68:H68) -> 73111.398 | J68: =I68/(1+Discount_Rate)^E68 -> 58800.795 | O68: 11 | P68: =C68 -> 0 | Q68: =J68 -> 58800.795 | R68: =Q68-P68 -> 58800.795
A69: 12 | B69: 0 | C69: =B69/(1+Discount_Rate)^A69 -> 0 | E69: 12 | F69: ='Fuel & Emission'!O18 -> 190838.29 | G69: ='Time Value'!AH18 -> 114855.05 | H69: =(-1)*'Interest Gain'!T18 -> -218266.98 | I69: =SUM(F69:H69) -> 87426.356 | J69: =I69/(1+Discount_Rate)^E69 -> 68935.085 | O69: 12 | P69: =C69 -> 0 | Q69: =J69 -> 68935.085 | R69: =Q69-P69 -> 68935.085
... A77: 20 | B77: 0 | C77: =B77/(1+Discount_Rate)^A77 -> 0 | E77: 20 | F77: ='Fuel & Emission'!O26 -> 472045.23 | G77: ='Time Value'!AH26 -> 228009.63 | H77: =(-1)*'Interest Gain'!T26 -> -426195 | I77: =SUM(F77:H77) -> 273859.86 | J77: =I77/(1+Discount_Rate)^E77 -> 184299.84 | O77: 20 | P77: =C77 -> 0 | Q77: =J77 -> 184299.84 | R77: =Q77-P77 -> 184299.84
O78: Total | P78: =SUM(P57:P77) -> 0 | Q78: =SUM(Q57:Q77) -> 1356116 | R78: =SUM(R57:R77) -> 1356116
A80: a Cost Streams of Community | E80: a Benefit Streams of Community | O80: a Net Benefit of Community ($ in base year)
A82: Year | B82: Capital Investment | C82: PVC ($ in Base Year) | E82: Year | F82: DEnv. Value** | G82: DTotal | H82: PVB | O82: Year | P82: PVC | Q82: PVB | R82: NPV
A83: Base | B83: =0 -> 0 | C83: =B83/(1+Discount_Rate)^0 -> 0 | E83: Base | F83: ='Fuel & Emission'!N6 -> 0 | G83: =SUM(F83) -> 0 | H83: =G83/(1+Discount_Rate)^0 -> 0 | O83: Base | P83: =C83 -> 0 | Q83: =H83 -> 0 | R83: =Q83-P83 -> 0
A84: 1 | B84: =0 -> 0 | C84: =B84/(1+Discount_Rate)^A84 -> 0 | E84: 1 | F84: ='Fuel & Emission'!N7 -> 311.09272 | G84: =SUM(F84) -> 311.09272 | H84: =G84/(1+Discount_Rate)^E84 -> 304.99286 | O84: 1 | P84: =C84 -> 0 | Q84: =H84 -> 304.99286 | R84: =Q84-P84 -> 304.99286
A85: 2 | B85: =0 -> 0 | C85: =B85/(1+Discount_Rate)^A85 -> 0 | E85: 2 | F85: ='Fuel & Emission'!N8 -> 733.21246 | G85: =SUM(F85) -> 733.21246 | H85: =G85/(1+Discount_Rate)^E85 -> 704.74093 | O85: 2 | P85: =C85 -> 0 | Q85: =H85 -> 704.74093 | R85: =Q85-P85 -> 704.74093
A86: 3 | B86: =0 -> 0 | C86: =B86/(1+Discount_Rate)^A86 -> 0 | E86: 3 | F86: ='Fuel & Emission'!N9 -> 1191.376 | G86: =SUM(F86) -> 1191.376 | H86: =G86/(1+Discount_Rate)^E86 -> 1122.6602 | O86: 3 | P86: =C86 -> 0 | Q86: =H86 -> 1122.6602 | R86: =Q86-P86 -> 1122.6602
A87: 4 | B87: =0 -> 0 | C87: =B87/(1+Discount_Rate)^A87 -> 0 | E87: 4 | F87: ='Fuel & Emission'!N10 -> 1673.6152 | G87: =SUM(F87) -> 1673.6152 | H87: =G87/(1+Discount_Rate)^E87 -> 1546.1617 | O87: 4 | P87: =C87 -> 0 | Q87: =H87 -> 1546.1617 | R87: =Q87-P87 -> 1546.1617
A88: 5 | B88: =0 -> 0 | C88: =B88/(1+Discount_Rate)^A88 -> 0 | E88: 5 | F88: ='Fuel & Emission'!N11 -> 2217.2843 | G88: =SUM(F88) -> 2217.2843 | H88: =G88/(1+Discount_Rate)^E88 -> 2008.2627 | O88: 5 | P88: =C88 -> 0 | Q88: =H88 -> 2008.2627 | R88: =Q88-P88 -> 2008.2627
A89: 6 | B89: =0 -> 0 | C89: =B89/(1+Discount_Rate)^A89 -> 0 | E89: 6 | F89: ='Fuel & Emission'!N12 -> 2841.6568 | G89: =SUM(F89) -> 2841.6568 | H89: =G89/(1+Discount_Rate)^E89 -> 2523.3099 | O89: 6 | P89: =C89 -> 0 | Q89: =H89 -> 2523.3099 | R89: =Q89-P89 -> 2523.3099
A90: 7 | B90: =0 -> 0 | C90: =B90/(1+Discount_Rate)^A90 -> 0 | E90: 7 | F90: ='Fuel & Emission'!N13 -> 3505.951 | G90: =SUM(F90) -> 3505.951 | H90: =G90/(1+Discount_Rate)^E90 -> 3052.1413 | O90: 7 | P90: =C90 -> 0 | Q90: =H90 -> 3052.1413 | R90: =Q90-P90 -> 3052.1413
A91: 8 | B91: =0 -> 0 | C91: =B91/(1+Discount_Rate)^A91 -> 0 | E91: 8 | F91: ='Fuel & Emission'!N14 -> 4228.3637 | G91: =SUM(F91) -> 4228.3637 | H91: =G91/(1+Discount_Rate)^E91 -> 3608.8677 | O91: 8 | P91: =C91 -> 0 | Q91: =H91 -> 3608.8677 | R91: =Q91-P91 -> 3608.8677
A92: 9 | B92: =0 -> 0 | C92: =B92/(1+Discount_Rate)^A92 -> 0 | E92: 9 | F92: ='Fuel & Emission'!N15 -> 5036.3543 | G92: =SUM(F92) -> 5036.3543 | H92: =G92/(1+Discount_Rate)^E92 -> 4214.196 | O92: 9 | P92: =C92 -> 0 | Q92: =H92 -> 4214.196 | R92: =Q92-P92 -> 4214.196
A93: 10 | B93: =0 -> 0 | C93: =B93/(1+Discount_Rate)^A93 -> 0 | E93: 10 | F93: ='Fuel & Emission'!N16 -> 5897.007 | G93: =SUM(F93) -> 5897.007 | H93: =G93/(1+Discount_Rate)^E93 -> 4837.5997 | O93: 10 | P93: =C93 -> 0 | Q93: =H93 -> 4837.5997 | R93: =Q93-P93 -> 4837.5997
A94: 11 | B94: =0 -> 0 | C94: =B94/(1+Discount_Rate)^A94 -> 0 | E94: 11 | F94: ='Fuel & Emission'!N17 -> 6846.8788 | G94: =SUM(F94) -> 6846.8788 | H94: =G94/(1+Discount_Rate)^E94 -> 5506.6916 | O94: 11 | P94: =C94 -> 0 | Q94: =H94 -> 5506.6916 | R94: =Q94-P94 -> 5506.6916
A95: 12 | B95: =0 -> 0 | C95: =B95/(1+Discount_Rate)^A95 -> 0 | E95: 12 | F95: ='Fuel & Emission'!N18 -> 7868.4317 | G95: =SUM(F95) -> 7868.4317 | H95: =G95/(1+Discount_Rate)^E95 -> 6204.2047 | O95: 12 | P95: =C95 -> 0 | Q95: =H95 -> 6204.2047 | R95: =Q95-P95 -> 6204.2047
... A103: 20 | B103: =0 -> 0 | C103: =B103/(1+Discount_Rate)^A103 -> 0 | E103: 20 | F103: ='Fuel & Emission'!N26 -> 19546.739 | G103: =SUM(F103) -> 19546.739 | H103: =G103/(1+Discount_Rate)^E103 -> 13154.395 | O103: 20 | P103: =C103 -> 0 | Q103: =H103 -> 13154.395 | R103: =Q103-P103 -> 13154.395
E104: ** Environmental value is estimated by the value of emission reduction. | O104: Total | P104: =SUM(P83:P103) -> 0 | Q104: =SUM(Q83:Q103) -> 114897.64 | R104: =SUM(R83:R103) -> 114897.64

Sheet Agency Costs Reduction
F2: y Reduction of Operating Costs
A4: Year | B4: Baseline | G4: ETC Alternative | L4: Cost Saving
B5: One-Time | C5: Staff | D5: Operations/Materials | E5: Others | F5: Total | G5: One-Time | H5: Staff | I5: Operations/Materials | J5: Others | K5: Total
A6: Base | B6: ='Input-Detail'!AE14 -> 0 | C6: ='Input-Detail'!AF14 -> 4004650 | D6: ='Input-Detail'!AG14 -> 8356.16 | E6: ='Input-Detail'!AH14 -> 297120 | F6: =SUM(B6:E6) -> 4310126.2 | G6: ='Input-Detail'!AO14 -> 0 | H6: ='Input-Detail'!AP14 -> 4004650 | I6: ='Input-Detail'!AQ14 -> 8356 | J6: ='Input-Detail'!AR14 -> 301760 | K6: =SUM(G6:J6) -> 4314766 | L6: =F6-K6 -> -4639.84
A7: 1 | B7: ='Input-Detail'!AE15 -> 0 | C7: ='Input-Detail'!AF15 -> 4230053.2 | D7: ='Input-Detail'!AG15 -> 8606.8448 | E7: ='Input-Detail'!AH15 -> 306033.6 | F7: =SUM(B7:E7) -> 4544693.6 | G7: ='Input-Detail'!AO15 -> 0 | H7: ='Input-Detail'!AP15 -> 4005040.9 | I7: ='Input-Detail'!AQ15 -> 8606.68 | J7: ='Input-Detail'!AR15 -> 310812.8 | K7: =SUM(G7:J7) -> 4324460.4 | L7: =F7-K7 -> 220233.29
A8: 2 | B8: ='Input-Detail'!AE16 -> 0 | C8: ='Input-Detail'!AF16 -> 4465376.4 | D8: ='Input-Detail'!AG16 -> 8865.0501 | E8: ='Input-Detail'!AH16 -> 315214.61 | F8: =SUM(B8:E8) -> 4789456.1 | G8: ='Input-Detail'!AO16 -> 0 | H8: ='Input-Detail'!AP16 -> 4031681.1 | I8: ='Input-Detail'!AQ16 -> 8864.8804 | J8: ='Input-Detail'!AR16 -> 320137.18 | K8: =SUM(G8:J8) -> 4360683.2 | L8: =F8-K8 -> 428772.9
A9: 3 | B9: ='Input-Detail'!AE17 -> 0 | C9: ='Input-Detail'!AF17 -> 4711012 | D9: ='Input-Detail'!AG17 -> 9131.0016 | E9: ='Input-Detail'!AH17 -> 324671.05 | F9: =SUM(B9:E9) -> 5044814 | G9: ='Input-Detail'!AO17 -> 0 | H9: ='Input-Detail'!AP17 -> 4045259.5 | I9: ='Input-Detail'!AQ17 -> 9130.8268 | J9: ='Input-Detail'!AR17 -> 329741.3 | K9: =SUM(G9:J9) -> 4384131.6 | L9: =F9-K9 -> 660682.43
A10: 4 | B10: ='Input-Detail'!AE18 -> 0 | C10: ='Input-Detail'!AF18 -> 4967366.8 | D10: ='Input-Detail'!AG18 -> 9404.9317 | E10: ='Input-Detail'!AH18 -> 334411.18 | F10: =SUM(B10:E10) -> 5311182.9 | G10: ='Input-Detail'!AO18 -> 0 | H10: ='Input-Detail'!AP18 -> 4044636.6 | I10: ='Input-Detail'!AQ18 -> 9404.7516 | J10: ='Input-Detail'!AR18 -> 339633.54 | K10: =SUM(G10:J10) -> 4393674.9 | L10: =F10-K10 -> 917508.06
A11: 5 | B11: ='Input-Detail'!AE19 -> 0 | C11: ='Input-Detail'!AF19 -> 5234863.1 | D11: ='Input-Detail'!AG19 -> 9687.0796 | E11: ='Input-Detail'!AH19 -> 344443.51 | F11: =SUM(B11:E11) -> 5588993.7 | G11: ='Input-Detail'!AO19 -> 0 | H11: ='Input-Detail'!AP19 -> 3984281.4 | I11: ='Input-Detail'!AQ19 -> 9686.8942 | J11: ='Input-Detail'!AR19 -> 349822.54 | K11: =SUM(G11:J11) -> 4343790.8 | L11: =F11-K11 -> 1245202.9
A12: 6 | B12: ='Input-Detail'!AE20 -> 0 | C12: ='Input-Detail'!AF20 -> 5513938.4 | D12: ='Input-Detail'!AG20 -> 9977.692 | E12: ='Input-Detail'!AH20 -> 354776.82 | F12: =SUM(B12:E12) -> 5878692.9 | G12: ='Input-Detail'!AO20 -> 0 | H12: ='Input-Detail'!AP20 -> 3950238.7 | I12: ='Input-Detail'!AQ20 -> 9977.501 | J12: ='Input-Detail'!AR20 -> 360317.22 | K12: =SUM(G12:J12) -> 4320533.4 | L12: =F12-K12 -> 1558159.5
A13: 7 | B13: ='Input-Detail'!AE21 -> 0 | C13: ='Input-Detail'!AF21 -> 5805047 | D13: ='Input-Detail'!AG21 -> 10277.023 | E13: ='Input-Detail'!AH21 -> 365420.12 | F13: =SUM(B13:E13) -> 6180744.1 | G13: ='Input-Detail'!AO21 -> 0 | H13: ='Input-Detail'!AP21 -> 3898124.2 | I13: ='Input-Detail'!AQ21 -> 10276.826 | J13: ='Input-Detail'!AR21 -> 371126.74 | K13: =SUM(G13:J13) -> 4279527.8 | L13: =F13-K13 -> 1901216.3
A14: 8 | B14: ='Input-Detail'!AE22 -> 0 | C14: ='Input-Detail'!AF22 -> 6108659.4 | D14: ='Input-Detail'!AG22 -> 10585.333 | E14: ='Input-Detail'!AH22 -> 376382.73 | F14: =SUM(B14:E14) -> 6495627.5 | G14: ='Input-Detail'!AO22 -> 0 | H14: ='Input-Detail'!AP22 -> 3778075.7 | I14: ='Input-Detail'!AQ22 -> 10585.131 | J14: ='Input-Detail'!AR22 -> 382260.54 | K14: =SUM(G14:J14) -> 4170921.4 | L14: =F14-K14 -> 2324706.1
A15: 9 | B15: ='Input-Detail'!AE23 -> 0 | C15: ='Input-Detail'!AF23 -> 6425264.1 | D15: ='Input-Detail'!AG23 -> 10902.893 | E15: ='Input-Detail'!AH23 -> 387674.21 | F15: =SUM(B15:E15) -> 6823841.2 | G15: ='Input-Detail'!AO23 -> 0 | H15: ='Input-Detail'!AP23 -> 3684003.2 | I15: ='Input-Detail'!AQ23 -> 10902.685 | J15: ='Input-Detail'!AR23 -> 393728.36 | K15: =SUM(G15:J15) -> 4088634.3 | L15: =F15-K15 -> 2735207
A16: 10 | B16: ='Input-Detail'!AE24 -> 0 | C16: ='Input-Detail'!AF24 -> 6755367.3 | D16: ='Input-Detail'!AG24 -> 11229.98 | E16: ='Input-Detail'!AH24 -> 399304.43 | F16: =SUM(B16:E16) -> 7165901.7 | G16: ='Input-Detail'!AO24 -> 0 | H16: ='Input-Detail'!AP24 -> 3567289 | I16: ='Input-Detail'!AQ24 -> 11229.765 | J16: ='Input-Detail'!AR24 -> 405540.21 | K16: =SUM(G16:J16) -> 3984058.9 | L16: =F16-K16 -> 3181842.8
A17: 11 | B17: ='Input-Detail'!AE25 -> 0 | C17: ='Input-Detail'!AF25 -> 7099494 | D17: ='Input-Detail'!AG25 -> 11566.88 | E17: ='Input-Detail'!AH25 -> 411283.57 | F17: =SUM(B17:E17) -> 7522344.4 | G17: ='Input-Detail'!AO25 -> 0 | H17: ='Input-Detail'!AP25 -> 3373324.5 | I17: ='Input-Detail'!AQ25 -> 11566.658 | J17: ='Input-Detail'!AR25 -> 417706.41 | K17: =SUM(G17:J17) -> 3802597.6 | L17: =F17-K17 -> 3719746.8
A18: 12 | B18: ='Input-Detail'!AE26 -> 0 | C18: ='Input-Detail'!AF26 -> 7458188.4 | D18: ='Input-Detail'!AG26 -> 11913.886 | E18: ='Input-Detail'!AH26 -> 423622.07 | F18: =SUM(B18:E18) -> 7893724.3 | G18: ='Input-Detail'!AO26 -> 0 | H18: ='Input-Detail'!AP26 -> 3204600.8 | I18: ='Input-Detail'!AQ26 -> 11913.658 | J18: ='Input-Detail'!AR26 -> 430237.61 | K18: =SUM(G18:J18) -> 3646752.1 | L18: =F18-K18 -> 4246972.2
... A26: 20 | B26: ='Input-Detail'!AE34 -> 0 | C26: ='Input-Detail'!AF34 -> 10924454 | D26: ='Input-Detail'!AG34 -> 15092.154 | E26: ='Input-Detail'!AH34 -> 536631.77 | F26: =SUM(B26:E26) -> 11476178 | G26: ='Input-Detail'!AO34 -> 0 | H26: ='Input-Detail'!AP34 -> 182799.43 | I26: ='Input-Detail'!AQ34 -> 15091.865 | J26: ='Input-Detail'!AR34 -> 545012.13 | K26: =SUM(G26:J26) -> 742903.42 | L26: =F26-K26 -> 10733275

Sheet Delay
Z1: Optimal Number of ETC Lanes
B3: 1 Transaction Facts | K3: y Queueing Delayper Year (hrs) | W3: a) Random and Stop Delay in the System during the Evening Peak per Day (hr) | BG3: b) Average Random Delay per Manual User (sec) | CK3: c) Average Random Delay per ETC User (sec)
H5: Year | I5: Traffic Vol. | J5: ETC (%) | K5: Peak Arrival Rate in the evening | L5: Suggeted Number of ETC Lanes | M5: Delay per Day (Baseline) | P5: Delay Per Year* (hr) | Q5: Delay per Day (ETC) | T5: Delay Per Year* (hr) | W5: Year | X5: Traffic Vol. | Y5: ETC (%) | Z5: PHV | AA5: ATV/PHV | AB5: T (hr) | AC5: K | AD5: Total Arrival Rate | AE5: Number of ETC Lanes | BA5: Optimal # of ETC Ln* | BB5: Delay per Day**(hr) | BC5: Suggested # of ETC Ln*** | BD5: Delay per Day**(hr) | BG5: Year | BH5: ETC (%) | BI5: Total Arrival Rate | BJ5: Arrival Rate for Manual Lanes | BK5: Number of ETC Lanes | CI5: Mean Transaction Time (sec) | CK5: Year | CL5: ETC (%) | CM5: Total Arrival Rate | CN5: Arrival Rate for ETC Users | CO5: Number of ETC Lanes | DK5: Mean Headway (sec)
B6: Transaction Time (sec) | M6: Morning | N6: Evening | O6: Total | Q6: Morning | R6: Evening | S6: Total | AE6: Manual Only | AF6: 1 | AG6: 2 | AH6: 3 | AI6: 4 | AJ6: 5 | AK6: 6 | AL6: 7 | AM6: 8 | AN6: 9 | AO6: 10 | AP6: 11 | AQ6: 12 | AR6: 13 | AS6: 14 | AT6: 15 | AU6: 16 | AV6: 17 | AW6: 18 | AX6: 19 | AY6: 20 | AZ6: 21 | BK6: l/sc for no ETC | BL6: Manual Only | BM6: l/sc under ETC | BN6: 1 | BO6: 2 | BP6: 3 | BQ6: 4 | BR6: 5 | BS6: 6 | BT6: 7 | BU6: 8 | BV6: 9 | BW6: 10 | BX6: 11 | BY6: 12 | BZ6: 13 | CA6: 14 | CB6: 15 | CC6: 16 | CD6: 17 | CE6: 18 | CF6: 19 | CG6: 20 | CH6: 21 | CO6: l/sc under ETC | CP6: 1 | CQ6: 2 | CR6: 3 | CS6: 4 | CT6: 5 | CU6: 6 | CV6: 7 | CW6: 8 | CX6: 9 | CY6: 10 | CZ6: 11 | DA6: 12 | DB6: 13 | DC6: 14 | DD6: 15 | DE6: 16 | DF6: 17 | DG6: 18 | DH6: 19 | DI6: 20 | DJ6: 21
C7: Cash | D7: ='Input-Detail'!AZ10 -> 7 | H7: Base | I7: ='Input-Detail'!E14 -> 19016173 | J7: ='Input-Detail'!F14 -> 0 | K7: =AD7 -> 5740 | L7: =0 -> 0 | W7: Base | X7: ='Input-Detail'!E14 -> 19016173 | Y7: =J7 -> 0 | Z7: ='Input-Detail'!V18 -> 8200 | AA7: ='Input-Detail'!W18 -> 2319.0455 | AB7: ='Input-Detail'!X18 -> 2 | AC7: ='Input-Detail'!Y18 -> 0.7 | AD7: =Z7*AC7 -> 5740 | AE7: =Peak_Time_Eve*$BI7*(3600/K40+BL7)/3600 -> 32.946409 | BG7: Base | BH7: =$Y7 -> 0 | BI7: =$AD7 -> 5740 | BJ7: =BI7*(1-BH7) -> 5740 | BK7: =Peak_Arrival_Manual/K40 -> 10.483472 | BL7: =900*Peak_Time_Eve*(BK7/Total_Lanes-1+SQRT((BK7/Total_Lanes-1)^2+8*(BK7/Total_Lanes)/(Peak_Time_Eve*$K40*Total_Lanes))) -> 3.7566264 | BM7: =Peak_Arrival_Manual/N40 -> 10.483472 | BN7: =IF(BN$6<Total_Lanes,900*Peak_Time_Eve*(($BM7/(Total_Lanes-BN$6))-1+SQRT((($BM7/(Total_Lanes-BN$6))-1)^2+8*($BM7/(Total_Lanes-BN$6))/(Peak_Time_Eve*$N40*(Total_Lanes-BN$6)))),"-") -> 11.367139 | BO7: =IF(BO$6<Total_Lanes,900*Peak_Time_Eve*(($BM7/(Total_Lanes-BO$6))-1+SQRT((($BM7/(Total_Lanes-BO$6))-1)^2+8*($BM7/(Total_Lanes-BO$6))/(Peak_Time_Eve*$N40*(Total_Lanes-BO$6)))),"-") -> 187.29857 | BP7: =IF(BP$6<Total_Lanes,900*Peak_Time_Eve*(($BM7/(Total_Lanes-BP$6))-1+SQRT((($BM7/(Total_Lanes-BP$6))-1)^2+8*($BM7/(Total_Lanes-BP$6))/(Peak_Time_Eve*$N40*(Total_Lanes-BP$6)))),"-") -> 598.50746 | BQ7: =IF(BQ$6<Total_Lanes,900*Peak_Time_Eve*(($BM7/(Total_Lanes-BQ$6))-1+SQRT((($BM7/(Total_Lanes-BQ$6))-1)^2+8*($BM7/(Total_Lanes-BQ$6))/(Peak_Time_Eve*$N40*(Total_Lanes-BQ$6)))),"-") -> 1121.0212 | BR7: =IF(BR$6<Total_Lanes,900*Peak_Time_Eve*(($BM7/(Total_Lanes-BR$6))-1+SQRT((($BM7/(Total_Lanes-BR$6))-1)^2+8*($BM7/(Total_Lanes-BR$6))/(Peak_Time_Eve*$N40*(Total_Lanes-BR$6)))),"-") -> 1794.3223 | BS7: =IF(BS$6<Total_Lanes,900*Peak_Time_Eve*(($BM7/(Total_Lanes-BS$6))-1+SQRT((($BM7/(Total_Lanes-BS$6))-1)^2+8*($BM7/(Total_Lanes-BS$6))/(Peak_Time_Eve*$N40*(Total_Lanes-BS$6)))),"-") -> 2692.6432 | BT7: =IF(BT$6<Total_Lanes,900*Peak_Time_Eve*(($BM7/(Total_Lanes-BT$6))-1+SQRT((($BM7/(Total_Lanes-BT$6))-1)^2+8*($BM7/(Total_Lanes-BT$6))/(Peak_Time_Eve*$N40*(Total_Lanes-BT$6)))),"-") -> 3950.6125 | BU7: =IF(BU$6<Total_Lanes,900*Peak_Time_Eve*(($BM7/(Total_Lanes-BU$6))-1+SQRT((($BM7/(Total_Lanes-BU$6))-1)^2+8*($BM7/(Total_Lanes-BU$6))/(Peak_Time_Eve*$N40*(Total_Lanes-BU$6)))),"-") -> 5837.7817 | ... CH7: =IF(CH$6<Total_Lanes,900*Peak_Time_Eve*(($BM7/(Total_Lanes-CH$6))-1+SQRT((($BM7/(Total_Lanes-CH$6))-1)^2+8*($BM7/(Total_Lanes-CH$6))/(Peak_Time_Eve*$N40*(Total_Lanes-CH$6)))),"-") -> - | CI7: =3600/N40 -> 6.575 | CK7: Base | CL7: =$Y7 -> 0 | CM7: =$AD7 -> 5740 | CN7: =CM7*CL7 -> 0
C8: Ticket | D8: ='Input-Detail'!AZ11 -> 4.5 | H8: 1 | I8: ='Input-Detail'!E15 -> 19565364 | J8: ='Input-Detail'!F15 -> 0.0495 | K8: =AD8 -> 5905.7725 | L8: =IF(AD8>AD56,BC8,BC56) -> 1 | M8: =AE56 -> 9.7202288 | N8: =AE8 -> 32.054381 | O8: =SUM(M8:N8) -> 41.774609 | P8: =$S$34*O8 -> 10861.398 | Q8: =SUMIF($AF$54:$AZ$54,L8,$AF56:$AZ56) -> 9.3671674 | R8: =SUMIF($AF$6:$AZ$6,$L8,$AF8:$AZ8) -> 46.657526 | S8: =SUM(Q8:R8) -> 56.024693 | T8: =$S$34*S8 -> 14566.42 | W8: 1 | X8: =X$7+(X$27-X$7)*$W8/20 -> 19565364 | Y8: =J8 -> 0.0495 | Z8: ='Input-Detail'!E15/AA8 -> 8436.8178 | AA8: =AA7 -> 2319.0455 | AB8: =AB7 -> 2 | AC8: =AC7 -> 0.7 | AD8: =Z8*AC8 -> 5905.7725 | AE8: =Peak_Time_Eve*$BI8*(3600/K41+BL8)/3600 -> 32.054381 | AF8: =IF(AF$6<Total_Lanes,($BJ8*($CI8+BN8)+$CN8*CP8)*Peak_Time_Eve/3600,"-") -> 46.657526 | AG8: =IF(AG$6<Total_Lanes,($BJ8*($CI8+BO8)+$CN8*CQ8)*Peak_Time_Eve/3600,"-") -> 403.15795 | AH8: =IF(AH$6<Total_Lanes,($BJ8*($CI8+BP8)+$CN8*CR8)*Peak_Time_Eve/3600,"-") -> 1642.1781 | AI8: =IF(AI$6<Total_Lanes,($BJ8*($CI8+BQ8)+$CN8*CS8)*Peak_Time_Eve/3600,"-") -> 3239.4186 | AJ8: =IF(AJ$6<Total_Lanes,($BJ8*($CI8+BR8)+$CN8*CT8)*Peak_Time_Eve/3600,"-") -> 5299.0965 | AK8: =IF(AK$6<Total_Lanes,($BJ8*($CI8+BS8)+$CN8*CU8)*Peak_Time_Eve/3600,"-") -> 8047.5005 | AL8: =IF(AL$6<Total_Lanes,($BJ8*($CI8+BT8)+$CN8*CV8)*Peak_Time_Eve/3600,"-") -> 11896.397 | AM8: =IF(AM$6<Total_Lanes,($BJ8*($CI8+BU8)+$CN8*CW8)*Peak_Time_Eve/3600,"-") -> 17670.481 | ... AZ8: =IF(AZ$6<Total_Lanes,($BJ8*($CI8+CH8)+$CN8*DJ8)*Peak_Time_Eve/3600,"-") -> - | BA8: =SUMIF(AF8:AZ8,BB8,$AF$6:$AZ$6) -> 1 | BB8: =MIN(AF8:AZ8) -> 46.657526 | BC8: =IF((SUMIF($BN6:$CH6,$BA8,$BN8:$CH8)+$CI8)<(SUMIF($CP6:$DJ6,$BA8,$CP8:$DJ8)+$DK8),BA8+1,BA8) -> 1 | BD8: =SUMIF($AF$6:$AZ$6,$BC8,$AF8:$AZ8) -> 46.657526 | BG8: 1 | BH8: =$Y8 -> 0.0495 | BI8: =$AD8 -> 5905.7725 | BJ8: =BI8*(1-BH8) -> 5613.4368 | BK8: =Peak_Arrival_Manual/K41 -> 10.252319 | BL8: =900*Peak_Time_Eve*(BK8/Total_Lanes-1+SQRT((BK8/Total_Lanes-1)^2+8*(BK8/Total_Lanes)/(Peak_Time_Eve*$K41*Total_Lanes))) -> 3.194744 | BM8: =Peak_Arrival_Manual/N41 -> 10.285453 | BN8: =IF(BN$6<Total_Lanes,900*Peak_Time_Eve*(($BM8/(Total_Lanes-BN$6))-1+SQRT((($BM8/(Total_Lanes-BN$6))-1)^2+8*($BM8/(Total_Lanes-BN$6))/(Peak_Time_Eve*$N41*(Total_Lanes-BN$6)))),"-") -> 8.3346647 | BO8: =IF(BO$6<Total_Lanes,900*Peak_Time_Eve*(($BM8/(Total_Lanes-BO$6))-1+SQRT((($BM8/(Total_Lanes-BO$6))-1)^2+8*($BM8/(Total_Lanes-BO$6))/(Peak_Time_Eve*$N41*(Total_Lanes-BO$6)))),"-") -> 122.6733 | BP8: =IF(BP$6<Total_Lanes,900*Peak_Time_Eve*(($BM8/(Total_Lanes-BP$6))-1+SQRT((($BM8/(Total_Lanes-BP$6))-1)^2+8*($BM8/(Total_Lanes-BP$6))/(Peak_Time_Eve*$N41*(Total_Lanes-BP$6)))),"-") -> 519.98033 | BQ8: =IF(BQ$6<Total_Lanes,900*Peak_Time_Eve*(($BM8/(Total_Lanes-BQ$6))-1+SQRT((($BM8/(Total_Lanes-BQ$6))-1)^2+8*($BM8/(Total_Lanes-BQ$6))/(Peak_Time_Eve*$N41*(Total_Lanes-BQ$6)))),"-") -> 1032.1514 | BR8: =IF(BR$6<Total_Lanes,900*Peak_Time_Eve*(($BM8/(Total_Lanes-BR$6))-1+SQRT((($BM8/(Total_Lanes-BR$6))-1)^2+8*($BM8/(Total_Lanes-BR$6))/(Peak_Time_Eve*$N41*(Total_Lanes-BR$6)))),"-") -> 1692.6066 | BS8: =IF(BS$6<Total_Lanes,900*Peak_Time_Eve*(($BM8/(Total_Lanes-BS$6))-1+SQRT((($BM8/(Total_Lanes-BS$6))-1)^2+8*($BM8/(Total_Lanes-BS$6))/(Peak_Time_Eve*$N41*(Total_Lanes-BS$6)))),"-") -> 2573.9079 | BT8: =IF(BT$6<Total_Lanes,900*Peak_Time_Eve*(($BM8/(Total_Lanes-BT$6))-1+SQRT((($BM8/(Total_Lanes-BT$6))-1)^2+8*($BM8/(Total_Lanes-BT$6))/(Peak_Time_Eve*$N41*(Total_Lanes-BT$6)))),"-") -> 3808.092 | BU8: =IF(BU$6<Total_Lanes,900*Peak_Time_Eve*(($BM8/(Total_Lanes-BU$6))-1+SQRT((($BM8/(Total_Lanes-BU$6))-1)^2+8*($BM8/(Total_Lanes-BU$6))/(Peak_Time_Eve*$N41*(Total_Lanes-BU$6)))),"-") -> 5659.6053 | ... CH8: =IF(CH$6<Total_Lanes,900*Peak_Time_Eve*(($BM8/(Total_Lanes-CH$6))-1+SQRT((($BM8/(Total_Lanes-CH$6))-1)^2+8*($BM8/(Total_Lanes-CH$6))/(Peak_Time_Eve*$N41*(Total_Lanes-CH$6)))),"-") -> - | CI8: =3600/N41 -> 6.59625 | CK8: 1 | CL8: =$Y8 -> 0.0495 | CM8: =$AD8 -> 5905.7725 | CN8: =CM8*CL8 -> 292.33574 | CO8: =CN8/O40 -> 0.19489049 | CP8: =IF(CP$6<Total_Lanes,900*Peak_Time_Eve*(($CO8/CP$6-1)+SQRT(($CO8/CP$6-1)^2+8*($CO8/CP$6)/(Peak_Time_Eve*$O41*CP$6))),"-") -> 0.58084454 | CQ8: =IF(CQ$6<Total_Lanes,900*Peak_Time_Eve*(($CO8/CQ$6-1)+SQRT(($CO8/CQ$6-1)^2+8*($CO8/CQ$6)/(Peak_Time_Eve*$O41*CQ$6))),"-") -> 0.12955406 | CR8: =IF(CR$6<Total_Lanes,900*Peak_Time_Eve*(($CO8/CR$6-1)+SQRT(($CO8/CR$6-1)^2+8*($CO8/CR$6)/(Peak_Time_Eve*$O41*CR$6))),"-") -> 0.055580653 | CS8: =IF(CS$6<Total_Lanes,900*Peak_Time_Eve*(($CO8/CS$6-1)+SQRT(($CO8/CS$6-1)^2+8*($CO8/CS$6)/(Peak_Time_Eve*$O41*CS$6))),"-") -> 0.030730586 | CT8: =IF(CT$6<Total_Lanes,900*Peak_Time_Eve*(($CO8/CT$6-1)+SQRT(($CO8/CT$6-1)^2+8*($CO8/CT$6)/(Peak_Time_Eve*$O41*CT$6))),"-") -> 0.019468216 | CU8: =IF(CU$6<Total_Lanes,900*Peak_Time_Eve*(($CO8/CU$6-1)+SQRT(($CO8/CU$6-1)^2+8*($CO8/CU$6)/(Peak_Time_Eve*$O41*CU$6))),"-") -> 0.013428842 | CV8: =IF(CV$6<Total_Lanes,900*Peak_Time_Eve*(($CO8/CV$6-1)+SQRT(($CO8/CV$6-1)^2+8*($CO8/CV$6)/(Peak_Time_Eve*$O41*CV$6))),"-") -> 0.0098190058 | CW8: =IF(CW$6<Total_Lanes,900*Peak_Time_Eve*(($CO8/CW$6-1)+SQRT(($CO8/CW$6-1)^2+8*($CO8/CW$6)/(Peak_Time_Eve*$O41*CW$6))),"-") -> 0.0074908652 | ... DJ8: =IF(DJ$6<Total_Lanes,900*Peak_Time_Eve*(($CO8/DJ$6-1)+SQRT(($CO8/DJ$6-1)^2+8*($CO8/DJ$6)/(Peak_Time_Eve*$O41*DJ$6))),"-") -> - | DK8: =3600/O41 -> 2.4
C9: ETC | D9: ='Input-Detail'!AZ12 -> 2.4 | H9: 2 | I9: ='Input-Detail'!E16 -> 20114556 | J9: ='Input-Detail'!F16 -> 0.099 | K9: =AD9 -> 6071.545 | L9: =IF(AD9>AD57,BC9,BC57) -> 1 | M9: =AE57 -> 10.005677 | N9: =AE9 -> 31.329017 | O9: =SUM(M9:N9) -> 41.334694 | P9: =$S$34*O9 -> 10747.02 | Q9: =SUMIF($AF$54:$AZ$54,L9,$AF57:$AZ57) -> 9.1950869 | R9: =SUMIF($AF$6:$AZ$6,$L9,$AF9:$AZ9) -> 39.730441 | S9: =SUM(Q9:R9) -> 48.925528 | T9: =$S$34*S9 -> 12720.637 | W9: 2 | X9: =X$7+(X$27-X$7)*$W9/20 -> 20114556 | Y9: =J9 -> 0.099 | Z9: ='Input-Detail'!E16/AA9 -> 8673.6357 | AA9: =AA8 -> 2319.0455 | AB9: =AB8 -> 2 | AC9: =AC8 -> 0.7 | AD9: =Z9*AC9 -> 6071.545 | AE9: =Peak_Time_Eve*$BI9*(3600/K42+BL9)/3600 -> 31.329017 | AF9: =IF(AF$6<Total_Lanes,($BJ9*($CI9+BN9)+$CN9*CP9)*Peak_Time_Eve/3600,"-") -> 39.730441 | AG9: =IF(AG$6<Total_Lanes,($BJ9*($CI9+BO9)+$CN9*CQ9)*Peak_Time_Eve/3600,"-") -> 202.56924 | AH9: =IF(AH$6<Total_Lanes,($BJ9*($CI9+BP9)+$CN9*CR9)*Peak_Time_Eve/3600,"-") -> 1324.5538 | AI9: =IF(AI$6<Total_Lanes,($BJ9*($CI9+BQ9)+$CN9*CS9)*Peak_Time_Eve/3600,"-") -> 2843.8843 | AJ9: =IF(AJ$6<Total_Lanes,($BJ9*($CI9+BR9)+$CN9*CT9)*Peak_Time_Eve/3600,"-") -> 4805.7013 | AK9: =IF(AK$6<Total_Lanes,($BJ9*($CI9+BS9)+$CN9*CU9)*Peak_Time_Eve/3600,"-") -> 7424.073 | AL9: =IF(AL$6<Total_Lanes,($BJ9*($CI9+BT9)+$CN9*CV9)*Peak_Time_Eve/3600,"-") -> 11091.078 | AM9: =IF(AM$6<Total_Lanes,($BJ9*($CI9+BU9)+$CN9*CW9)*Peak_Time_Eve/3600,"-") -> 16592.399 | ... AZ9: =IF(AZ$6<Total_Lanes,($BJ9*($CI9+CH9)+$CN9*DJ9)*Peak_Time_Eve/3600,"-") -> - | BA9: =SUMIF(AF9:AZ9,BB9,$AF$6:$AZ$6) -> 1 | BB9: =MIN(AF9:AZ9) -> 39.730441 | BC9: =IF((SUMIF($BN7:$CH7,$BA9,$BN9:$CH9)+$CI9)<(SUMIF($CP7:$DJ7,$BA9,$CP9:$DJ9)+$DK9),BA9+1,BA9) -> 1 | BD9: =SUMIF($AF$6:$AZ$6,$BC9,$AF9:$AZ9) -> 39.730441 | BG9: 2 | BH9: =$Y9 -> 0.099 | BI9: =$AD9 -> 6071.545 | BJ9: =BI9*(1-BH9) -> 5470.462 | BK9: =Peak_Arrival_Manual/K42 -> 9.9911911 | BL9: =900*Peak_Time_Eve*(BK9/Total_Lanes-1+SQRT((BK9/Total_Lanes-1)^2+8*(BK9/Total_Lanes)/(Peak_Time_Eve*$K42*Total_Lanes))) -> 2.7129541 | BM9: =Peak_Arrival_Manual/N42 -> 10.055773 | BN9: =IF(BN$6<Total_Lanes,900*Peak_Time_Eve*(($BM9/(Total_Lanes-BN$6))-1+SQRT((($BM9/(Total_Lanes-BN$6))-1)^2+8*($BM9/(Total_Lanes-BN$6))/(Peak_Time_Eve*$N42*(Total_Lanes-BN$6)))),"-") -> 6.2791952 | BO9: =IF(BO$6<Total_Lanes,900*Peak_Time_Eve*(($BM9/(Total_Lanes-BO$6))-1+SQRT((($BM9/(Total_Lanes-BO$6))-1)^2+8*($BM9/(Total_Lanes-BO$6))/(Peak_Time_Eve*$N42*(Total_Lanes-BO$6)))),"-") -> 60.002818 | BP9: =IF(BP$6<Total_Lanes,900*Peak_Time_Eve*(($BM9/(Total_Lanes-BP$6))-1+SQRT((($BM9/(Total_Lanes-BP$6))-1)^2+8*($BM9/(Total_Lanes-BP$6))/(Peak_Time_Eve*$N42*(Total_Lanes-BP$6)))),"-") -> 429.19992 | BQ9: =IF(BQ$6<Total_Lanes,900*Peak_Time_Eve*(($BM9/(Total_Lanes-BQ$6))-1+SQRT((($BM9/(Total_Lanes-BQ$6))-1)^2+8*($BM9/(Total_Lanes-BQ$6))/(Peak_Time_Eve*$N42*(Total_Lanes-BQ$6)))),"-") -> 929.12644 | BR9: =IF(BR$6<Total_Lanes,900*Peak_Time_Eve*(($BM9/(Total_Lanes-BR$6))-1+SQRT((($BM9/(Total_Lanes-BR$6))-1)^2+8*($BM9/(Total_Lanes-BR$6))/(Peak_Time_Eve*$N42*(Total_Lanes-BR$6)))),"-") -> 1574.6451 | BS9: =IF(BS$6<Total_Lanes,900*Peak_Time_Eve*(($BM9/(Total_Lanes-BS$6))-1+SQRT((($BM9/(Total_Lanes-BS$6))-1)^2+8*($BM9/(Total_Lanes-BS$6))/(Peak_Time_Eve*$N42*(Total_Lanes-BS$6)))),"-") -> 2436.1952 | BT9: =IF(BT$6<Total_Lanes,900*Peak_Time_Eve*(($BM9/(Total_Lanes-BT$6))-1+SQRT((($BM9/(Total_Lanes-BT$6))-1)^2+8*($BM9/(Total_Lanes-BT$6))/(Peak_Time_Eve*$N42*(Total_Lanes-BT$6)))),"-") -> 3642.787 | BU9: =IF(BU$6<Total_Lanes,900*Peak_Time_Eve*(($BM9/(Total_Lanes-BU$6))-1+SQRT((($BM9/(Total_Lanes-BU$6))-1)^2+8*($BM9/(Total_Lanes-BU$6))/(Peak_Time_Eve*$N42*(Total_Lanes-BU$6)))),"-") -> 5452.9414 | ... CH9: =IF(CH$6<Total_Lanes,900*Peak_Time_Eve*(($BM9/(Total_Lanes-CH$6))-1+SQRT((($BM9/(Total_Lanes-CH$6))-1)^2+8*($BM9/(Total_Lanes-CH$6))/(Peak_Time_Eve*$N42*(Total_Lanes-CH$6)))),"-") -> - | CI9: =3600/N42 -> 6.6175 | CK9: 2 | CL9: =$Y9 -> 0.099 | CM9: =$AD9 -> 6071.545 | CN9: =CM9*CL9 -> 601.08295 | CO9: =CN9/O41 -> 0.40072197 | CP9: =IF(CP$6<Total_Lanes,900*Peak_Time_Eve*(($CO9/CP$6-1)+SQRT(($CO9/CP$6-1)^2+8*($CO9/CP$6)/(Peak_Time_Eve*$O42*CP$6))),"-") -> 1.6036269 | CQ9: =IF(CQ$6<Total_Lanes,900*Peak_Time_Eve*(($CO9/CQ$6-1)+SQRT(($CO9/CQ$6-1)^2+8*($CO9/CQ$6)/(Peak_Time_Eve*$O42*CQ$6))),"-") -> 0.30064575 | CR9: =IF(CR$6<Total_Lanes,900*Peak_Time_Eve*(($CO9/CR$6-1)+SQRT(($CO9/CR$6-1)^2+8*($CO9/CR$6)/(Peak_Time_Eve*$O42*CR$6))),"-") -> 0.12332844 | CS9: =IF(CS$6<Total_Lanes,900*Peak_Time_Eve*(($CO9/CS$6-1)+SQRT(($CO9/CS$6-1)^2+8*($CO9/CS$6)/(Peak_Time_Eve*$O42*CS$6))),"-") -> 0.066799014 | CT9: =IF(CT$6<Total_Lanes,900*Peak_Time_Eve*(($CO9/CT$6-1)+SQRT(($CO9/CT$6-1)^2+8*($CO9/CT$6)/(Peak_Time_Eve*$O42*CT$6))),"-") -> 0.041820502 | CU9: =IF(CU$6<Total_Lanes,900*Peak_Time_Eve*(($CO9/CU$6-1)+SQRT(($CO9/CU$6-1)^2+8*($CO9/CU$6)/(Peak_Time_Eve*$O42*CU$6))),"-") -> 0.028626444 | CV9: =IF(CV$6<Total_Lanes,900*Peak_Time_Eve*(($CO9/CV$6-1)+SQRT(($CO9/CV$6-1)^2+8*($CO9/CV$6)/(Peak_Time_Eve*$O42*CV$6))),"-") -> 0.020818875 | CW9: =IF(CW$6<Total_Lanes,900*Peak_Time_Eve*(($CO9/CW$6-1)+SQRT(($CO9/CW$6-1)^2+8*($CO9/CW$6)/(Peak_Time_Eve*$O42*CW$6))),"-") -> 0.015819402 | ... DJ9: =IF(DJ$6<Total_Lanes,900*Peak_Time_Eve*(($CO9/DJ$6-1)+SQRT(($CO9/DJ$6-1)^2+8*($CO9/DJ$6)/(Peak_Time_Eve*$O42*DJ$6))),"-") -> - | DK9: =3600/O42 -> 2.4
B10: Total Number of Lanes | D10: ='Input-Detail'!AZ25 -> 12 | H10: 3 | I10: ='Input-Detail'!E17 -> 20663747 | J10: ='Input-Detail'!F17 -> 0.1485 | K10: =AD10 -> 6237.3175 | L10: =IF(AD10>AD58,BC10,BC58) -> 1 | M10: =AE58 -> 10.290303 | N10: =AE10 -> 30.764537 | O10: =SUM(M10:N10) -> 41.05484 | P10: =$S$34*O10 -> 10674.258 | Q10: =SUMIF($AF$54:$AZ$54,L10,$AF58:$AZ58) -> 9.0562335 | R10: =SUMIF($AF$6:$AZ$6,$L10,$AF10:$AZ10) -> 35.864564 | S10: =SUM(Q10:R10) -> 44.920797 | T10: =$S$34*S10 -> 11679.407 | W10: 3 | X10: =X$7+(X$27-X$7)*$W10/20 -> 20663747 | Y10: =J10 -> 0.1485 | Z10: ='Input-Detail'!E17/AA10 -> 8910.4535 | AA10: =AA9 -> 2319.0455 | AB10: =AB9 -> 2 | AC10: =AC9 -> 0.7 | AD10: =Z10*AC10 -> 6237.3175 | AE10: =Peak_Time_Eve*$BI10*(3600/K43+BL10)/3600 -> 30.764537 | AF10: =IF(AF$6<Total_Lanes,($BJ10*($CI10+BN10)+$CN10*CP10)*Peak_Time_Eve/3600,"-") -> 35.864564 | AG10: =IF(AG$6<Total_Lanes,($BJ10*($CI10+BO10)+$CN10*CQ10)*Peak_Time_Eve/3600,"-") -> 90.342706 | AH10: =IF(AH$6<Total_Lanes,($BJ10*($CI10+BP10)+$CN10*CR10)*Peak_Time_Eve/3600,"-") -> 983.08511 | AI10: =IF(AI$6<Total_Lanes,($BJ10*($CI10+BQ10)+$CN10*CS10)*Peak_Time_Eve/3600,"-") -> 2415.1406 | AJ10: =IF(AJ$6<Total_Lanes,($BJ10*($CI10+BR10)+$CN10*CT10)*Peak_Time_Eve/3600,"-") -> 4269.378 | AK10: =IF(AK$6<Total_Lanes,($BJ10*($CI10+BS10)+$CN10*CU10)*Peak_Time_Eve/3600,"-") -> 6745.0176 | AL10: =IF(AL$6<Total_Lanes,($BJ10*($CI10+BT10)+$CN10*CV10)*Peak_Time_Eve/3600,"-") -> 10212.419 | AM10: =IF(AM$6<Total_Lanes,($BJ10*($CI10+BU10)+$CN10*CW10)*Peak_Time_Eve/3600,"-") -> 15414.433 | ... AZ10: =IF(AZ$6<Total_Lanes,($BJ10*($CI10+CH10)+$CN10*DJ10)*Peak_Time_Eve/3600,"-") -> - | BA10: =SUMIF(AF10:AZ10,BB10,$AF$6:$AZ$6) -> 1 | BB10: =MIN(AF10:AZ10) -> 35.864564 | BC10: =IF((SUMIF($BN8:$CH8,$BA10,$BN10:$CH10)+$CI10)<(SUMIF($CP8:$DJ8,$BA10,$CP10:$DJ10)+$DK10),BA10+1,BA10) -> 1 | BD10: =SUMIF($AF$6:$AZ$6,$BC10,$AF10:$AZ10) -> 35.864564 | BG10: 3 | BH10: =$Y10 -> 0.1485 | BI10: =$AD10 -> 6237.3175 | BJ10: =BI10*(1-BH10) -> 5311.0758 | BK10: =Peak_Arrival_Manual/K43 -> 9.7000899 | BL10: =900*Peak_Time_Eve*(BK10/Total_Lanes-1+SQRT((BK10/Total_Lanes-1)^2+8*(BK10/Total_Lanes)/(Peak_Time_Eve*$K43*Total_Lanes))) -> 2.3032024 | BM10: =Peak_Arrival_Manual/N43 -> 9.7941402 | BN10: =IF(BN$6<Total_Lanes,900*Peak_Time_Eve*(($BM10/(Total_Lanes-BN$6))-1+SQRT((($BM10/(Total_Lanes-BN$6))-1)^2+8*($BM10/(Total_Lanes-BN$6))/(Peak_Time_Eve*$N43*(Total_Lanes-BN$6)))),"-") -> 4.8424659 | BO10: =IF(BO$6<Total_Lanes,900*Peak_Time_Eve*(($BM10/(Total_Lanes-BO$6))-1+SQRT((($BM10/(Total_Lanes-BO$6))-1)^2+8*($BM10/(Total_Lanes-BO$6))/(Peak_Time_Eve*$N43*(Total_Lanes-BO$6)))),"-") -> 23.886239 | BP10: =IF(BP$6<Total_Lanes,900*Peak_Time_Eve*(($BM10/(Total_Lanes-BP$6))-1+SQRT((($BM10/(Total_Lanes-BP$6))-1)^2+8*($BM10/(Total_Lanes-BP$6))/(Peak_Time_Eve*$N43*(Total_Lanes-BP$6)))),"-") -> 326.50678 | BQ10: =IF(BQ$6<Total_Lanes,900*Peak_Time_Eve*(($BM10/(Total_Lanes-BQ$6))-1+SQRT((($BM10/(Total_Lanes-BQ$6))-1)^2+8*($BM10/(Total_Lanes-BQ$6))/(Peak_Time_Eve*$N43*(Total_Lanes-BQ$6)))),"-") -> 811.86803 | BR10: =IF(BR$6<Total_Lanes,900*Peak_Time_Eve*(($BM10/(Total_Lanes-BR$6))-1+SQRT((($BM10/(Total_Lanes-BR$6))-1)^2+8*($BM10/(Total_Lanes-BR$6))/(Peak_Time_Eve*$N43*(Total_Lanes-BR$6)))),"-") -> 1440.3031 | BS10: =IF(BS$6<Total_Lanes,900*Peak_Time_Eve*(($BM10/(Total_Lanes-BS$6))-1+SQRT((($BM10/(Total_Lanes-BS$6))-1)^2+8*($BM10/(Total_Lanes-BS$6))/(Peak_Time_Eve*$N43*(Total_Lanes-BS$6)))),"-") -> 2279.3367 | BT10: =IF(BT$6<Total_Lanes,900*Peak_Time_Eve*(($BM10/(Total_Lanes-BT$6))-1+SQRT((($BM10/(Total_Lanes-BT$6))-1)^2+8*($BM10/(Total_Lanes-BT$6))/(Peak_Time_Eve*$N43*(Total_Lanes-BT$6)))),"-") -> 3454.4913 | BU10: =IF(BU$6<Total_Lanes,900*Peak_Time_Eve*(($BM10/(Total_Lanes-BU$6))-1+SQRT((($BM10/(Total_Lanes-BU$6))-1)^2+8*($BM10/(Total_Lanes-BU$6))/(Peak_Time_Eve*$N43*(Total_Lanes-BU$6)))),"-") -> 5217.5301 | ... CH10: =IF(CH$6<Total_Lanes,900*Peak_Time_Eve*(($BM10/(Total_Lanes-CH$6))-1+SQRT((($BM10/(Total_Lanes-CH$6))-1)^2+8*($BM10/(Total_Lanes-CH$6))/(Peak_Time_Eve*$N43*(Total_Lanes-CH$6)))),"-") -> - | CI10: =3600/N43 -> 6.63875 | CK10: 3 | CL10: =$Y10 -> 0.1485 | CM10: =$AD10 -> 6237.3175 | CN10: =CM10*CL10 -> 926.24164 | CO10: =CN10/O42 -> 0.61749443 | CP10: =IF(CP$6<Total_Lanes,900*Peak_Time_Eve*(($CO10/CP$6-1)+SQRT(($CO10/CP$6-1)^2+8*($CO10/CP$6)/(Peak_Time_Eve*$O43*CP$6))),"-") -> 3.8635782 | CQ10: =IF(CQ$6<Total_Lanes,900*Peak_Time_Eve*(($CO10/CQ$6-1)+SQRT(($CO10/CQ$6-1)^2+8*($CO10/CQ$6)/(Peak_Time_Eve*$O43*CQ$6))),"-") -> 0.53586315 | CR10: =IF(CR$6<Total_Lanes,900*Peak_Time_Eve*(($CO10/CR$6-1)+SQRT(($CO10/CR$6-1)^2+8*($CO10/CR$6)/(Peak_Time_Eve*$O43*CR$6))),"-") -> 0.20732784 | CS10: =IF(CS$6<Total_Lanes,900*Peak_Time_Eve*(($CO10/CS$6-1)+SQRT(($CO10/CS$6-1)^2+8*($CO10/CS$6)/(Peak_Time_Eve*$O43*CS$6))),"-") -> 0.10952926 | CT10: =IF(CT$6<Total_Lanes,900*Peak_Time_Eve*(($CO10/CT$6-1)+SQRT(($CO10/CT$6-1)^2+8*($CO10/CT$6)/(Peak_Time_Eve*$O43*CT$6))),"-") -> 0.067630484 | CU10: =IF(CU$6<Total_Lanes,900*Peak_Time_Eve*(($CO10/CU$6-1)+SQRT(($CO10/CU$6-1)^2+8*($CO10/CU$6)/(Peak_Time_Eve*$O43*CU$6))),"-") -> 0.045888343 | CV10: =IF(CV$6<Total_Lanes,900*Peak_Time_Eve*(($CO10/CV$6-1)+SQRT(($CO10/CV$6-1)^2+8*($CO10/CV$6)/(Peak_Time_Eve*$O43*CV$6))),"-") -> 0.033170396 | CW10: =IF(CW$6<Total_Lanes,900*Peak_Time_Eve*(($CO10/CW$6-1)+SQRT(($CO10/CW$6-1)^2+8*($CO10/CW$6)/(Peak_Time_Eve*$O43*CW$6))),"-") -> 0.025092691 | ... DJ10: =IF(DJ$6<Total_Lanes,900*Peak_Time_Eve*(($CO10/DJ$6-1)+SQRT(($CO10/DJ$6-1)^2+8*($CO10/DJ$6)/(Peak_Time_Eve*$O43*DJ$6))),"-") -> - | DK10: =3600/O43 -> 2.4
H11: 4 | I11: ='Input-Detail'!E18 -> 21212938 | J11: ='Input-Detail'!F18 -> 0.198 | K11: =AD11 -> 6403.09 | L11: =IF(AD11>AD59,BC11,BC59) -> 1 | M11: =AE59 -> 10.574158 | N11: =AE11 -> 30.346439 | O11: =SUM(M11:N11) -> 40.920598 | P11: =$S$34*O11 -> 10639.355 | Q11: =SUMIF($AF$54:$AZ$54,L11,$AF59:$AZ59) -> 8.9892734 | R11: =SUMIF($AF$6:$AZ$6,$L11,$AF11:$AZ11) -> 38.880994 | S11: =SUM(Q11:R11) -> 47.870268 | T11: =$S$34*S11 -> 12446.27 | W11: 4 | X11: =X$7+(X$27-X$7)*$W11/20 -> 21212938 | Y11: =J11 -> 0.198 | Z11: ='Input-Detail'!E18/AA11 -> 9147.2714 | AA11: =AA10 -> 2319.0455 | AB11: =AB10 -> 2 | AC11: =AC10 -> 0.7 | AD11: =Z11*AC11 -> 6403.09 | AE11: =Peak_Time_Eve*$BI11*(3600/K44+BL11)/3600 -> 30.346439 | AF11: =IF(AF$6<Total_Lanes,($BJ11*($CI11+BN11)+$CN11*CP11)*Peak_Time_Eve/3600,"-") -> 38.880994 | AG11: =IF(AG$6<Total_Lanes,($BJ11*($CI11+BO11)+$CN11*CQ11)*Peak_Time_Eve/3600,"-") -> 53.503046 | AH11: =IF(AH$6<Total_Lanes,($BJ11*($CI11+BP11)+$CN11*CR11)*Peak_Time_Eve/3600,"-") -> 627.72379 | AI11: =IF(AI$6<Total_Lanes,($BJ11*($CI11+BQ11)+$CN11*CS11)*Peak_Time_Eve/3600,"-") -> 1960.1069 | AJ11: =IF(AJ$6<Total_Lanes,($BJ11*($CI11+BR11)+$CN11*CT11)*Peak_Time_Eve/3600,"-") -> 3697.7982 | AK11: =IF(AK$6<Total_Lanes,($BJ11*($CI11+BS11)+$CN11*CU11)*Peak_Time_Eve/3600,"-") -> 6019.2402 | AL11: =IF(AL$6<Total_Lanes,($BJ11*($CI11+BT11)+$CN11*CV11)*Peak_Time_Eve/3600,"-") -> 9271.0931 | AM11: =IF(AM$6<Total_Lanes,($BJ11*($CI11+BU11)+$CN11*CW11)*Peak_Time_Eve/3600,"-") -> 14149.92 | ... AZ11: =IF(AZ$6<Total_Lanes,($BJ11*($CI11+CH11)+$CN11*DJ11)*Peak_Time_Eve/3600,"-") -> - | BA11: =SUMIF(AF11:AZ11,BB11,$AF$6:$AZ$6) -> 1 | BB11: =MIN(AF11:AZ11) -> 38.880994 | BC11: =IF((SUMIF($BN9:$CH9,$BA11,$BN11:$CH11)+$CI11)<(SUMIF($CP9:$DJ9,$BA11,$CP11:$DJ11)+$DK11),BA11+1,BA11) -> 1 | BD11: =SUMIF($AF$6:$AZ$6,$BC11,$AF11:$AZ11) -> 38.880994 | BG11: 4 | BH11: =$Y11 -> 0.198 | BI11: =$AD11 -> 6403.09 | BJ11: =BI11*(1-BH11) -> 5135.2781 | BK11: =Peak_Arrival_Manual/K44 -> 9.379015 | BL11: =900*Peak_Time_Eve*(BK11/Total_Lanes-1+SQRT((BK11/Total_Lanes-1)^2+8*(BK11/Total_Lanes)/(Peak_Time_Eve*$K44*Total_Lanes))) -> 1.9558173 | BM11: =Peak_Arrival_Manual/N44 -> 9.5002646 | BN11: =IF(BN$6<Total_Lanes,900*Peak_Time_Eve*(($BM11/(Total_Lanes-BN$6))-1+SQRT((($BM11/(Total_Lanes-BN$6))-1)^2+8*($BM11/(Total_Lanes-BN$6))/(Peak_Time_Eve*$N44*(Total_Lanes-BN$6)))),"-") -> 3.8058186 | BO11: =IF(BO$6<Total_Lanes,900*Peak_Time_Eve*(($BM11/(Total_Lanes-BO$6))-1+SQRT((($BM11/(Total_Lanes-BO$6))-1)^2+8*($BM11/(Total_Lanes-BO$6))/(Peak_Time_Eve*$N44*(Total_Lanes-BO$6)))),"-") -> 11.876959 | BP11: =IF(BP$6<Total_Lanes,900*Peak_Time_Eve*(($BM11/(Total_Lanes-BP$6))-1+SQRT((($BM11/(Total_Lanes-BP$6))-1)^2+8*($BM11/(Total_Lanes-BP$6))/(Peak_Time_Eve*$N44*(Total_Lanes-BP$6)))),"-") -> 213.29012 | BQ11: =IF(BQ$6<Total_Lanes,900*Peak_Time_Eve*(($BM11/(Total_Lanes-BQ$6))-1+SQRT((($BM11/(Total_Lanes-BQ$6))-1)^2+8*($BM11/(Total_Lanes-BQ$6))/(Peak_Time_Eve*$N44*(Total_Lanes-BQ$6)))),"-") -> 680.35024 | BR11: =IF(BR$6<Total_Lanes,900*Peak_Time_Eve*(($BM11/(Total_Lanes-BR$6))-1+SQRT((($BM11/(Total_Lanes-BR$6))-1)^2+8*($BM11/(Total_Lanes-BR$6))/(Peak_Time_Eve*$N44*(Total_Lanes-BR$6)))),"-") -> 1289.4554 | BS11: =IF(BS$6<Total_Lanes,900*Peak_Time_Eve*(($BM11/(Total_Lanes-BS$6))-1+SQRT((($BM11/(Total_Lanes-BS$6))-1)^2+8*($BM11/(Total_Lanes-BS$6))/(Peak_Time_Eve*$N44*(Total_Lanes-BS$6)))),"-") -> 2103.1671 | BT11: =IF(BT$6<Total_Lanes,900*Peak_Time_Eve*(($BM11/(Total_Lanes-BT$6))-1+SQRT((($BM11/(Total_Lanes-BT$6))-1)^2+8*($BM11/(Total_Lanes-BT$6))/(Peak_Time_Eve*$N44*(Total_Lanes-BT$6)))),"-") -> 3243 | BU11: =IF(BU$6<Total_Lanes,900*Peak_Time_Eve*(($BM11/(Total_Lanes-BU$6))-1+SQRT((($BM11/(Total_Lanes-BU$6))-1)^2+8*($BM11/(Total_Lanes-BU$6))/(Peak_Time_Eve*$N44*(Total_Lanes-BU$6)))),"-") -> 4953.1123 | ... CH11: =IF(CH$6<Total_Lanes,900*Peak_Time_Eve*(($BM11/(Total_Lanes-CH$6))-1+SQRT((($BM11/(Total_Lanes-CH$6))-1)^2+8*($BM11/(Total_Lanes-CH$6))/(Peak_Time_Eve*$N44*(Total_Lanes-CH$6)))),"-") -> - | CI11: =3600/N44 -> 6.66 | CK11: 4 | CL11: =$Y11 -> 0.198 | CM11: =$AD11 -> 6403.09 | CN11: =CM11*CL11 -> 1267.8118 | CO11: =CN11/O43 -> 0.84520787 | CP11: =IF(CP$6<Total_Lanes,900*Peak_Time_Eve*(($CO11/CP$6-1)+SQRT(($CO11/CP$6-1)^2+8*($CO11/CP$6)/(Peak_Time_Eve*$O44*CP$6))),"-") -> 12.810182 | CQ11: =IF(CQ$6<Total_Lanes,900*Peak_Time_Eve*(($CO11/CQ$6-1)+SQRT(($CO11/CQ$6-1)^2+8*($CO11/CQ$6)/(Peak_Time_Eve*$O44*CQ$6))),"-") -> 0.87792533 | CR11: =IF(CR$6<Total_Lanes,900*Peak_Time_Eve*(($CO11/CR$6-1)+SQRT(($CO11/CR$6-1)^2+8*($CO11/CR$6)/(Peak_Time_Eve*$O44*CR$6))),"-") -> 0.31375846 | CS11: =IF(CS$6<Total_Lanes,900*Peak_Time_Eve*(($CO11/CS$6-1)+SQRT(($CO11/CS$6-1)^2+8*($CO11/CS$6)/(Peak_Time_Eve*$O44*CS$6))),"-") -> 0.16073833 | CT11: =IF(CT$6<Total_Lanes,900*Peak_Time_Eve*(($CO11/CT$6-1)+SQRT(($CO11/CT$6-1)^2+8*($CO11/CT$6)/(Peak_Time_Eve*$O44*CT$6))),"-") -> 0.097643041 | CU11: =IF(CU$6<Total_Lanes,900*Peak_Time_Eve*(($CO11/CU$6-1)+SQRT(($CO11/CU$6-1)^2+8*($CO11/CU$6)/(Peak_Time_Eve*$O44*CU$6))),"-") -> 0.065584794 | CV11: =IF(CV$6<Total_Lanes,900*Peak_Time_Eve*(($CO11/CV$6-1)+SQRT(($CO11/CV$6-1)^2+8*($CO11/CV$6)/(Peak_Time_Eve*$O44*CV$6))),"-") -> 0.047082215 | CW11: =IF(CW$6<Total_Lanes,900*Peak_Time_Eve*(($CO11/CW$6-1)+SQRT(($CO11/CW$6-1)^2+8*($CO11/CW$6)/(Peak_Time_Eve*$O44*CW$6))),"-") -> 0.035439125 | ... DJ11: =IF(DJ$6<Total_Lanes,900*Peak_Time_Eve*(($CO11/DJ$6-1)+SQRT(($CO11/DJ$6-1)^2+8*($CO11/DJ$6)/(Peak_Time_Eve*$O44*DJ$6))),"-") -> - | DK11: =3600/O44 -> 2.4
H12: 5 | I12: ='Input-Detail'!E19 -> 21762130 | J12: ='Input-Detail'!F19 -> 0.2475 | K12: =AD12 -> 6568.8625 | L12: =IF(AD12>AD60,BC12,BC60) -> 2 | M12: =AE60 -> 10.857316 | N12: =AE12 -> 30.057209 | O12: =SUM(M12:N12) -> 40.914525 | P12: =$S$34*O12 -> 10637.776 | Q12: =SUMIF($AF$54:$AZ$54,L12,$AF60:$AZ60) -> 8.5131682 | R12: =SUMIF($AF$6:$AZ$6,$L12,$AF12:$AZ12) -> 39.518604 | S12: =SUM(Q12:R12) -> 48.031773 | T12: =$S$34*S12 -> 12488.261 | W12: 5 | X12: =X$7+(X$27-X$7)*$W12/20 -> 21762130 | Y12: =J12 -> 0.2475 | Z12: ='Input-Detail'!E19/AA12 -> 9384.0892 | AA12: =AA11 -> 2319.0455 | AB12: =AB11 -> 2 | AC12: =AC11 -> 0.7 | AD12: =Z12*AC12 -> 6568.8625 | AE12: =Peak_Time_Eve*$BI12*(3600/K45+BL12)/3600 -> 30.057209 | AF12: =IF(AF$6<Total_Lanes,($BJ12*($CI12+BN12)+$CN12*CP12)*Peak_Time_Eve/3600,"-") -> 324.98113 | AG12: =IF(AG$6<Total_Lanes,($BJ12*($CI12+BO12)+$CN12*CQ12)*Peak_Time_Eve/3600,"-") -> 39.518604 | AH12: =IF(AH$6<Total_Lanes,($BJ12*($CI12+BP12)+$CN12*CR12)*Peak_Time_Eve/3600,"-") -> 286.46737 | AI12: =IF(AI$6<Total_Lanes,($BJ12*($CI12+BQ12)+$CN12*CS12)*Peak_Time_Eve/3600,"-") -> 1486.8689 | AJ12: =IF(AJ$6<Total_Lanes,($BJ12*($CI12+BR12)+$CN12*CT12)*Peak_Time_Eve/3600,"-") -> 3099.6373 | AK12: =IF(AK$6<Total_Lanes,($BJ12*($CI12+BS12)+$CN12*CU12)*Peak_Time_Eve/3600,"-") -> 5256.7802 | AL12: =IF(AL$6<Total_Lanes,($BJ12*($CI12+BT12)+$CN12*CV12)*Peak_Time_Eve/3600,"-") -> 8279.1242 | AM12: =IF(AM$6<Total_Lanes,($BJ12*($CI12+BU12)+$CN12*CW12)*Peak_Time_Eve/3600,"-") -> 12813.88 | ... AZ12: =IF(AZ$6<Total_Lanes,($BJ12*($CI12+CH12)+$CN12*DJ12)*Peak_Time_Eve/3600,"-") -> - | BA12: =SUMIF(AF12:AZ12,BB12,$AF$6:$AZ$6) -> 2 | BB12: =MIN(AF12:AZ12) -> 39.518604 | BC12: =IF((SUMIF($BN10:$CH10,$BA12,$BN12:$CH12)+$CI12)<(SUMIF($CP10:$DJ10,$BA12,$CP12:$DJ12)+$DK12),BA12+1,BA12) -> 2 | BD12: =SUMIF($AF$6:$AZ$6,$BC12,$AF12:$AZ12) -> 39.518604 | BG12: 5 | BH12: =$Y12 -> 0.2475 | BI12: =$AD12 -> 6568.8625 | BJ12: =BI12*(1-BH12) -> 4943.069 | BK12: =Peak_Arrival_Manual/K45 -> 9.0279663 | BL12: =900*Peak_Time_Eve*(BK12/Total_Lanes-1+SQRT((BK12/Total_Lanes-1)^2+8*(BK12/Total_Lanes)/(Peak_Time_Eve*$K45*Total_Lanes))) -> 1.6612778 | BM12: =Peak_Arrival_Manual/N45 -> 9.1738555 | BN12: =IF(BN$6<Total_Lanes,900*Peak_Time_Eve*(($BM12/(Total_Lanes-BN$6))-1+SQRT((($BM12/(Total_Lanes-BN$6))-1)^2+8*($BM12/(Total_Lanes-BN$6))/(Peak_Time_Eve*$N45*(Total_Lanes-BN$6)))),"-") -> 3.0358569 | BO12: =IF(BO$6<Total_Lanes,900*Peak_Time_Eve*(($BM12/(Total_Lanes-BO$6))-1+SQRT((($BM12/(Total_Lanes-BO$6))-1)^2+8*($BM12/(Total_Lanes-BO$6))/(Peak_Time_Eve*$N45*(Total_Lanes-BO$6)))),"-") -> 7.2427602 | BP12: =IF(BP$6<Total_Lanes,900*Peak_Time_Eve*(($BM12/(Total_Lanes-BP$6))-1+SQRT((($BM12/(Total_Lanes-BP$6))-1)^2+8*($BM12/(Total_Lanes-BP$6))/(Peak_Time_Eve*$N45*(Total_Lanes-BP$6)))),"-") -> 97.485962 | BQ12: =IF(BQ$6<Total_Lanes,900*Peak_Time_Eve*(($BM12/(Total_Lanes-BQ$6))-1+SQRT((($BM12/(Total_Lanes-BQ$6))-1)^2+8*($BM12/(Total_Lanes-BQ$6))/(Peak_Time_Eve*$N45*(Total_Lanes-BQ$6)))),"-") -> 534.68312 | BR12: =IF(BR$6<Total_Lanes,900*Peak_Time_Eve*(($BM12/(Total_Lanes-BR$6))-1+SQRT((($BM12/(Total_Lanes-BR$6))-1)^2+8*($BM12/(Total_Lanes-BR$6))/(Peak_Time_Eve*$N45*(Total_Lanes-BR$6)))),"-") -> 1121.9963 | BS12: =IF(BS$6<Total_Lanes,900*Peak_Time_Eve*(($BM12/(Total_Lanes-BS$6))-1+SQRT((($BM12/(Total_Lanes-BS$6))-1)^2+8*($BM12/(Total_Lanes-BS$6))/(Peak_Time_Eve*$N45*(Total_Lanes-BS$6)))),"-") -> 1907.5265 | BT12: =IF(BT$6<Total_Lanes,900*Peak_Time_Eve*(($BM12/(Total_Lanes-BT$6))-1+SQRT((($BM12/(Total_Lanes-BT$6))-1)^2+8*($BM12/(Total_Lanes-BT$6))/(Peak_Time_Eve*$N45*(Total_Lanes-BT$6)))),"-") -> 3008.1101 | BU12: =IF(BU$6<Total_Lanes,900*Peak_Time_Eve*(($BM12/(Total_Lanes-BU$6))-1+SQRT((($BM12/(Total_Lanes-BU$6))-1)^2+8*($BM12/(Total_Lanes-BU$6))/(Peak_Time_Eve*$N45*(Total_Lanes-BU$6)))),"-") -> 4659.4297 | ... CH12: =IF(CH$6<Total_Lanes,900*Peak_Time_Eve*(($BM12/(Total_Lanes-CH$6))-1+SQRT((($BM12/(Total_Lanes-CH$6))-1)^2+8*($BM12/(Total_Lanes-CH$6))/(Peak_Time_Eve*$N45*(Total_Lanes-CH$6)))),"-") -> - | CI12: =3600/N45 -> 6.68125 | CK12: 5 | CL12: =$Y12 -> 0.2475 | CM12: =$AD12 -> 6568.8625 | CN12: =CM12*CL12 -> 1625.7935 | CO12: =CN12/O44 -> 1.0838623 | CP12: =IF(CP$6<Total_Lanes,900*Peak_Time_Eve*(($CO12/CP$6-1)+SQRT(($CO12/CP$6-1)^2+8*($CO12/CP$6)/(Peak_Time_Eve*$O45*CP$6))),"-") -> 330.25948 | CQ12: =IF(CQ$6<Total_Lanes,900*Peak_Time_Eve*(($CO12/CQ$6-1)+SQRT(($CO12/CQ$6-1)^2+8*($CO12/CQ$6)/(Peak_Time_Eve*$O45*CQ$6))),"-") -> 1.4184734 | CR12: =IF(CR$6<Total_Lanes,900*Peak_Time_Eve*(($CO12/CR$6-1)+SQRT(($CO12/CR$6-1)^2+8*($CO12/CR$6)/(Peak_Time_Eve*$O45*CR$6))),"-") -> 0.45243057 | CS12: =IF(CS$6<Total_Lanes,900*Peak_Time_Eve*(($CO12/CS$6-1)+SQRT(($CO12/CS$6-1)^2+8*($CO12/CS$6)/(Peak_Time_Eve*$O45*CS$6))),"-") -> 0.22298746 | CT12: =IF(CT$6<Total_Lanes,900*Peak_Time_Eve*(($CO12/CT$6-1)+SQRT(($CO12/CT$6-1)^2+8*($CO12/CT$6)/(Peak_Time_Eve*$O45*CT$6))),"-") -> 0.13284247 | CU12: =IF(CU$6<Total_Lanes,900*Peak_Time_Eve*(($CO12/CU$6-1)+SQRT(($CO12/CU$6-1)^2+8*($CO12/CU$6)/(Peak_Time_Eve*$O45*CU$6))),"-") -> 0.08818548 | CV12: =IF(CV$6<Total_Lanes,900*Peak_Time_Eve*(($CO12/CV$6-1)+SQRT(($CO12/CV$6-1)^2+8*($CO12/CV$6)/(Peak_Time_Eve*$O45*CV$6))),"-") -> 0.062811632 | CW12: =IF(CW$6<Total_Lanes,900*Peak_Time_Eve*(($CO12/CW$6-1)+SQRT(($CO12/CW$6-1)^2+8*($CO12/CW$6)/(Peak_Time_Eve*$O45*CW$6))),"-") -> 0.04701378 | ... DJ12: =IF(DJ$6<Total_Lanes,900*Peak_Time_Eve*(($CO12/DJ$6-1)+SQRT(($CO12/DJ$6-1)^2+8*($CO12/DJ$6)/(Peak_Time_Eve*$O45*DJ$6))),"-") -> - | DK12: =3600/O45 -> 2.4
H13: 6 | I13: ='Input-Detail'!E20 -> 22311321 | J13: ='Input-Detail'!F20 -> 0.297 | K13: =AD13 -> 6734.6349 | L13: =IF(AD13>AD61,BC13,BC61) -> 2 | M13: =AE61 -> 11.139864 | N13: =AE13 -> 29.879337 | O13: =SUM(M13:N13) -> 41.019201 | P13: =$S$34*O13 -> 10664.992 | Q13: =SUMIF($AF$54:$AZ$54,L13,$AF61:$AZ61) -> 8.2425912 | R13: =SUMIF($AF$6:$AZ$6,$L13,$AF13:$AZ13) -> 33.251289 | S13: =SUM(Q13:R13) -> 41.49388 | T13: =$S$34*S13 -> 10788.409 | W13: 6 | X13: =X$7+(X$27-X$7)*$W13/20 -> 22311321 | Y13: =J13 -> 0.297 | Z13: ='Input-Detail'!E20/AA13 -> 9620.9071 | AA13: =AA12 -> 2319.0455 | AB13: =AB12 -> 2 | AC13: =AC12 -> 0.7 | AD13: =Z13*AC13 -> 6734.6349 | AE13: =Peak_Time_Eve*$BI13*(3600/K46+BL13)/3600 -> 29.879337 | AF13: =IF(AF$6<Total_Lanes,($BJ13*($CI13+BN13)+$CN13*CP13)*Peak_Time_Eve/3600,"-") -> 1368.6075 | AG13: =IF(AG$6<Total_Lanes,($BJ13*($CI13+BO13)+$CN13*CQ13)*Peak_Time_Eve/3600,"-") -> 33.251289 | AH13: =IF(AH$6<Total_Lanes,($BJ13*($CI13+BP13)+$CN13*CR13)*Peak_Time_Eve/3600,"-") -> 87.18173 | AI13: =IF(AI$6<Total_Lanes,($BJ13*($CI13+BQ13)+$CN13*CS13)*Peak_Time_Eve/3600,"-") -> 1005.4418 | AJ13: =IF(AJ$6<Total_Lanes,($BJ13*($CI13+BR13)+$CN13*CT13)*Peak_Time_Eve/3600,"-") -> 2484.6351 | AK13: =IF(AK$6<Total_Lanes,($BJ13*($CI13+BS13)+$CN13*CU13)*Peak_Time_Eve/3600,"-") -> 4468.8335 | AL13: =IF(AL$6<Total_Lanes,($BJ13*($CI13+BT13)+$CN13*CV13)*Peak_Time_Eve/3600,"-") -> 7249.9099 | AM13: =IF(AM$6<Total_Lanes,($BJ13*($CI13+BU13)+$CN13*CW13)*Peak_Time_Eve/3600,"-") -> 11423.049 | ... AZ13: =IF(AZ$6<Total_Lanes,($BJ13*($CI13+CH13)+$CN13*DJ13)*Peak_Time_Eve/3600,"-") -> - | BA13: =SUMIF(AF13:AZ13,BB13,$AF$6:$AZ$6) -> 2 | BB13: =MIN(AF13:AZ13) -> 33.251289 | BC13: =IF((SUMIF($BN11:$CH11,$BA13,$BN13:$CH13)+$CI13)<(SUMIF($CP11:$DJ11,$BA13,$CP13:$DJ13)+$DK13),BA13+1,BA13) -> 2 | BD13: =SUMIF($AF$6:$AZ$6,$BC13,$AF13:$AZ13) -> 33.251289 | BG13: 6 | BH13: =$Y13 -> 0.297 | BI13: =$AD13 -> 6734.6349 | BJ13: =BI13*(1-BH13) -> 4734.4484 | BK13: =Peak_Arrival_Manual/K46 -> 8.6469439 | BL13: =900*Peak_Time_Eve*(BK13/Total_Lanes-1+SQRT((BK13/Total_Lanes-1)^2+8*(BK13/Total_Lanes)/(Peak_Time_Eve*$K46*Total_Lanes))) -> 1.4110018 | BM13: =Peak_Arrival_Manual/N46 -> 8.8146223 | BN13: =IF(BN$6<Total_Lanes,900*Peak_Time_Eve*(($BM13/(Total_Lanes-BN$6))-1+SQRT((($BM13/(Total_Lanes-BN$6))-1)^2+8*($BM13/(Total_Lanes-BN$6))/(Peak_Time_Eve*$N46*(Total_Lanes-BN$6)))),"-") -> 2.4492697 | BO13: =IF(BO$6<Total_Lanes,900*Peak_Time_Eve*(($BM13/(Total_Lanes-BO$6))-1+SQRT((($BM13/(Total_Lanes-BO$6))-1)^2+8*($BM13/(Total_Lanes-BO$6))/(Peak_Time_Eve*$N46*(Total_Lanes-BO$6)))),"-") -> 4.9271756 | BP13: =IF(BP$6<Total_Lanes,900*Peak_Time_Eve*(($BM13/(Total_Lanes-BP$6))-1+SQRT((($BM13/(Total_Lanes-BP$6))-1)^2+8*($BM13/(Total_Lanes-BP$6))/(Peak_Time_Eve*$N46*(Total_Lanes-BP$6)))),"-") -> 26.172965 | BQ13: =IF(BQ$6<Total_Lanes,900*Peak_Time_Eve*(($BM13/(Total_Lanes-BQ$6))-1+SQRT((($BM13/(Total_Lanes-BQ$6))-1)^2+8*($BM13/(Total_Lanes-BQ$6))/(Peak_Time_Eve*$N46*(Total_Lanes-BQ$6)))),"-") -> 375.43183 | BR13: =IF(BR$6<Total_Lanes,900*Peak_Time_Eve*(($BM13/(Total_Lanes-BR$6))-1+SQRT((($BM13/(Total_Lanes-BR$6))-1)^2+8*($BM13/(Total_Lanes-BR$6))/(Peak_Time_Eve*$N46*(Total_Lanes-BR$6)))),"-") -> 937.86246 | BS13: =IF(BS$6<Total_Lanes,900*Peak_Time_Eve*(($BM13/(Total_Lanes-BS$6))-1+SQRT((($BM13/(Total_Lanes-BS$6))-1)^2+8*($BM13/(Total_Lanes-BS$6))/(Peak_Time_Eve*$N46*(Total_Lanes-BS$6)))),"-") -> 1692.2645 | BT13: =IF(BT$6<Total_Lanes,900*Peak_Time_Eve*(($BM13/(Total_Lanes-BT$6))-1+SQRT((($BM13/(Total_Lanes-BT$6))-1)^2+8*($BM13/(Total_Lanes-BT$6))/(Peak_Time_Eve*$N46*(Total_Lanes-BT$6)))),"-") -> 2749.6221 | BU13: =IF(BU$6<Total_Lanes,900*Peak_Time_Eve*(($BM13/(Total_Lanes-BU$6))-1+SQRT((($BM13/(Total_Lanes-BU$6))-1)^2+8*($BM13/(Total_Lanes-BU$6))/(Peak_Time_Eve*$N46*(Total_Lanes-BU$6)))),"-") -> 4336.2256 | ... CH13: =IF(CH$6<Total_Lanes,900*Peak_Time_Eve*(($BM13/(Total_Lanes-CH$6))-1+SQRT((($BM13/(Total_Lanes-CH$6))-1)^2+8*($BM13/(Total_Lanes-CH$6))/(Peak_Time_Eve*$N46*(Total_Lanes-CH$6)))),"-") -> - | CI13: =3600/N46 -> 6.7025 | CK13: 6 | CL13: =$Y13 -> 0.297 | CM13: =$AD13 -> 6734.6349 | CN13: =CM13*CL13 -> 2000.1866 | CO13: =CN13/O45 -> 1.3334577 | CP13: =IF(CP$6<Total_Lanes,900*Peak_Time_Eve*(($CO13/CP$6-1)+SQRT(($CO13/CP$6-1)^2+8*($CO13/CP$6)/(Peak_Time_Eve*$O46*CP$6))),"-") -> 1209.9696 | CQ13: =IF(CQ$6<Total_Lanes,900*Peak_Time_Eve*(($CO13/CQ$6-1)+SQRT(($CO13/CQ$6-1)^2+8*($CO13/CQ$6)/(Peak_Time_Eve*$O46*CQ$6))),"-") -> 2.3958873 | CR13: =IF(CR$6<Total_Lanes,900*Peak_Time_Eve*(($CO13/CR$6-1)+SQRT(($CO13/CR$6-1)^2+8*($CO13/CR$6)/(Peak_Time_Eve*$O46*CR$6))),"-") -> 0.63990272 | CS13: =IF(CS$6<Total_Lanes,900*Peak_Time_Eve*(($CO13/CS$6-1)+SQRT(($CO13/CS$6-1)^2+8*($CO13/CS$6)/(Peak_Time_Eve*$O46*CS$6))),"-") -> 0.30000448 | CT13: =IF(CT$6<Total_Lanes,900*Peak_Time_Eve*(($CO13/CT$6-1)+SQRT(($CO13/CT$6-1)^2+8*($CO13/CT$6)/(Peak_Time_Eve*$O46*CT$6))),"-") -> 0.17455612 | CU13: =IF(CU$6<Total_Lanes,900*Peak_Time_Eve*(($CO13/CU$6-1)+SQRT(($CO13/CU$6-1)^2+8*($CO13/CU$6)/(Peak_Time_Eve*$O46*CU$6))),"-") -> 0.11429476 | CV13: =IF(CV$6<Total_Lanes,900*Peak_Time_Eve*(($CO13/CV$6-1)+SQRT(($CO13/CV$6-1)^2+8*($CO13/CV$6)/(Peak_Time_Eve*$O46*CV$6))),"-") -> 0.080679332 | CW13: =IF(CW$6<Total_Lanes,900*Peak_Time_Eve*(($CO13/CW$6-1)+SQRT(($CO13/CW$6-1)^2+8*($CO13/CW$6)/(Peak_Time_Eve*$O46*CW$6))),"-") -> 0.060005517 | ... DJ13: =IF(DJ$6<Total_Lanes,900*Peak_Time_Eve*(($CO13/DJ$6-1)+SQRT(($CO13/DJ$6-1)^2+8*($CO13/DJ$6)/(Peak_Time_Eve*$O46*DJ$6))),"-") -> - | DK13: =3600/O46 -> 2.4
H14: 7 | I14: ='Input-Detail'!E21 -> 22860512 | J14: ='Input-Detail'!F21 -> 0.3465 | K14: =AD14 -> 6900.4074 | L14: =IF(AD14>AD62,BC14,BC62) -> 2 | M14: =AE62 -> 11.421906 | N14: =AE14 -> 29.796729 | O14: =SUM(M14:N14) -> 41.218635 | P14: =$S$34*O14 -> 10716.845 | Q14: =SUMIF($AF$54:$AZ$54,L14,$AF62:$AZ62) -> 7.98108 | R14: =SUMIF($AF$6:$AZ$6,$L14,$AF14:$AZ14) -> 31.9987 | S14: =SUM(Q14:R14) -> 39.97978 | T14: =$S$34*S14 -> 10394.743 | W14: 7 | X14: =X$7+(X$27-X$7)*$W14/20 -> 22860512 | Y14: =J14 -> 0.3465 | Z14: ='Input-Detail'!E21/AA14 -> 9857.7249 | AA14: =AA13 -> 2319.0455 | AB14: =AB13 -> 2 | AC14: =AC13 -> 0.7 | AD14: =Z14*AC14 -> 6900.4074 | AE14: =Peak_Time_Eve*$BI14*(3600/K47+BL14)/3600 -> 29.796729 | AF14: =IF(AF$6<Total_Lanes,($BJ14*($CI14+BN14)+$CN14*CP14)*Peak_Time_Eve/3600,"-") -> 2870.8349 | AG14: =IF(AG$6<Total_Lanes,($BJ14*($CI14+BO14)+$CN14*CQ14)*Peak_Time_Eve/3600,"-") -> 31.9987 | AH14: =IF(AH$6<Total_Lanes,($BJ14*($CI14+BP14)+$CN14*CR14)*Peak_Time_Eve/3600,"-") -> 44.156331 | AI14: =IF(AI$6<Total_Lanes,($BJ14*($CI14+BQ14)+$CN14*CS14)*Peak_Time_Eve/3600,"-") -> 532.25376 | AJ14: =IF(AJ$6<Total_Lanes,($BJ14*($CI14+BR14)+$CN14*CT14)*Peak_Time_Eve/3600,"-") -> 1863.7484 | AK14: =IF(AK$6<Total_Lanes,($BJ14*($CI14+BS14)+$CN14*CU14)*Peak_Time_Eve/3600,"-") -> 3667.7866 | AL14: =IF(AL$6<Total_Lanes,($BJ14*($CI14+BT14)+$CN14*CV14)*Peak_Time_Eve/3600,"-") -> 6198.2424 | AM14: =IF(AM$6<Total_Lanes,($BJ14*($CI14+BU14)+$CN14*CW14)*Peak_Time_Eve/3600,"-") -> 9995.8953 | ... AZ14: =IF(AZ$6<Total_Lanes,($BJ14*($CI14+CH14)+$CN14*DJ14)*Peak_Time_Eve/3600,"-") -> - | BA14: =SUMIF(AF14:AZ14,BB14,$AF$6:$AZ$6) -> 2 | BB14: =MIN(AF14:AZ14) -> 31.9987 | BC14: =IF((SUMIF($BN12:$CH12,$BA14,$BN14:$CH14)+$CI14)<(SUMIF($CP12:$DJ12,$BA14,$CP14:$DJ14)+$DK14),BA14+1,BA14) -> 2 | BD14: =SUMIF($AF$6:$AZ$6,$BC14,$AF14:$AZ14) -> 31.9987 | BG14: 7 | BH14: =$Y14 -> 0.3465 | BI14: =$AD14 -> 6900.4074 | BJ14: =BI14*(1-BH14) -> 4509.4163 | BK14: =Peak_Arrival_Manual/K47 -> 8.2359477 | BL14: =900*Peak_Time_Eve*(BK14/Total_Lanes-1+SQRT((BK14/Total_Lanes-1)^2+8*(BK14/Total_Lanes)/(Peak_Time_Eve*$K47*Total_Lanes))) -> 1.1976009 | BM14: =Peak_Arrival_Manual/N47 -> 8.4222743 | BN14: =IF(BN$6<Total_Lanes,900*Peak_Time_Eve*(($BM14/(Total_Lanes-BN$6))-1+SQRT((($BM14/(Total_Lanes-BN$6))-1)^2+8*($BM14/(Total_Lanes-BN$6))/(Peak_Time_Eve*$N47*(Total_Lanes-BN$6)))),"-") -> 1.9924483 | BO14: =IF(BO$6<Total_Lanes,900*Peak_Time_Eve*(($BM14/(Total_Lanes-BO$6))-1+SQRT((($BM14/(Total_Lanes-BO$6))-1)^2+8*($BM14/(Total_Lanes-BO$6))/(Peak_Time_Eve*$N47*(Total_Lanes-BO$6)))),"-") -> 3.5668974 | BP14: =IF(BP$6<Total_Lanes,900*Peak_Time_Eve*(($BM14/(Total_Lanes-BP$6))-1+SQRT((($BM14/(Total_Lanes-BP$6))-1)^2+8*($BM14/(Total_Lanes-BP$6))/(Peak_Time_Eve*$N47*(Total_Lanes-BP$6)))),"-") -> 10.421267 | BQ14: =IF(BQ$6<Total_Lanes,900*Peak_Time_Eve*(($BM14/(Total_Lanes-BQ$6))-1+SQRT((($BM14/(Total_Lanes-BQ$6))-1)^2+8*($BM14/(Total_Lanes-BQ$6))/(Peak_Time_Eve*$N47*(Total_Lanes-BQ$6)))),"-") -> 205.52246 | BR14: =IF(BR$6<Total_Lanes,900*Peak_Time_Eve*(($BM14/(Total_Lanes-BR$6))-1+SQRT((($BM14/(Total_Lanes-BR$6))-1)^2+8*($BM14/(Total_Lanes-BR$6))/(Peak_Time_Eve*$N47*(Total_Lanes-BR$6)))),"-") -> 737.09981 | BS14: =IF(BS$6<Total_Lanes,900*Peak_Time_Eve*(($BM14/(Total_Lanes-BS$6))-1+SQRT((($BM14/(Total_Lanes-BS$6))-1)^2+8*($BM14/(Total_Lanes-BS$6))/(Peak_Time_Eve*$N47*(Total_Lanes-BS$6)))),"-") -> 1457.2506 | BT14: =IF(BT$6<Total_Lanes,900*Peak_Time_Eve*(($BM14/(Total_Lanes-BT$6))-1+SQRT((($BM14/(Total_Lanes-BT$6))-1)^2+8*($BM14/(Total_Lanes-BT$6))/(Peak_Time_Eve*$N47*(Total_Lanes-BT$6)))),"-") -> 2467.3425 | BU14: =IF(BU$6<Total_Lanes,900*Peak_Time_Eve*(($BM14/(Total_Lanes-BU$6))-1+SQRT((($BM14/(Total_Lanes-BU$6))-1)^2+8*($BM14/(Total_Lanes-BU$6))/(Peak_Time_Eve*$N47*(Total_Lanes-BU$6)))),"-") -> 3983.2457 | ... CH14: =IF(CH$6<Total_Lanes,900*Peak_Time_Eve*(($BM14/(Total_Lanes-CH$6))-1+SQRT((($BM14/(Total_Lanes-CH$6))-1)^2+8*($BM14/(Total_Lanes-CH$6))/(Peak_Time_Eve*$N47*(Total_Lanes-CH$6)))),"-") -> - | CI14: =3600/N47 -> 6.72375 | CK14: 7 | CL14: =$Y14 -> 0.3465 | CM14: =$AD14 -> 6900.4074 | CN14: =CM14*CL14 -> 2390.9912 | CO14: =CN14/O46 -> 1.5939941 | CP14: =IF(CP$6<Total_Lanes,900*Peak_Time_Eve*(($CO14/CP$6-1)+SQRT(($CO14/CP$6-1)^2+8*($CO14/CP$6)/(Peak_Time_Eve*$O47*CP$6))),"-") -> 2144.8 | CQ14: =IF(CQ$6<Total_Lanes,900*Peak_Time_Eve*(($CO14/CQ$6-1)+SQRT(($CO14/CQ$6-1)^2+8*($CO14/CQ$6)/(Peak_Time_Eve*$O47*CQ$6))),"-") -> 4.6812583 | CR14: =IF(CR$6<Total_Lanes,900*Peak_Time_Eve*(($CO14/CR$6-1)+SQRT(($CO14/CR$6-1)^2+8*($CO14/CR$6)/(Peak_Time_Eve*$O47*CR$6))),"-") -> 0.90647597 | CS14: =IF(CS$6<Total_Lanes,900*Peak_Time_Eve*(($CO14/CS$6-1)+SQRT(($CO14/CS$6-1)^2+8*($CO14/CS$6)/(Peak_Time_Eve*$O47*CS$6))),"-") -> 0.39743085 | CT14: =IF(CT$6<Total_Lanes,900*Peak_Time_Eve*(($CO14/CT$6-1)+SQRT(($CO14/CT$6-1)^2+8*($CO14/CT$6)/(Peak_Time_Eve*$O47*CT$6))),"-") -> 0.22461708 | CU14: =IF(CU$6<Total_Lanes,900*Peak_Time_Eve*(($CO14/CU$6-1)+SQRT(($CO14/CU$6-1)^2+8*($CO14/CU$6)/(Peak_Time_Eve*$O47*CU$6))),"-") -> 0.14470311 | CV14: =IF(CV$6<Total_Lanes,900*Peak_Time_Eve*(($CO14/CV$6-1)+SQRT(($CO14/CV$6-1)^2+8*($CO14/CV$6)/(Peak_Time_Eve*$O47*CV$6))),"-") -> 0.10108986 | CW14: =IF(CW$6<Total_Lanes,900*Peak_Time_Eve*(($CO14/CW$6-1)+SQRT(($CO14/CW$6-1)^2+8*($CO14/CW$6)/(Peak_Time_Eve*$O47*CW$6))),"-") -> 0.07464649 | ... DJ14: =IF(DJ$6<Total_Lanes,900*Peak_Time_Eve*(($CO14/DJ$6-1)+SQRT(($CO14/DJ$6-1)^2+8*($CO14/DJ$6)/(Peak_Time_Eve*$O47*DJ$6))),"-") -> - | DK14: =3600/O47 -> 2.4
H15: 8 | I15: ='Input-Detail'!E22 -> 23409704 | J15: ='Input-Detail'!F22 -> 0.396 | K15: =AD15 -> 7066.1799 | L15: =IF(AD15>AD63,BC15,BC63) -> 3 | M15: =AE63 -> 11.703555 | N15: =AE15 -> 29.795228 | O15: =SUM(M15:N15) -> 41.498784 | P15: =$S$34*O15 -> 10789.684 | Q15: =SUMIF($AF$54:$AZ$54,L15,$AF63:$AZ63) -> 7.5160203 | R15: =SUMIF($AF$6:$AZ$6,$L15,$AF15:$AZ15) -> 31.991909 | S15: =SUM(Q15:R15) -> 39.507929 | T15: =$S$34*S15 -> 10272.062 | W15: 8 | X15: =X$7+(X$27-X$7)*$W15/20 -> 23409704 | Y15: =J15 -> 0.396 | Z15: ='Input-Detail'!E22/AA15 -> 10094.543 | AA15: =AA14 -> 2319.0455 | AB15: =AB14 -> 2 | AC15: =AC14 -> 0.7 | AD15: =Z15*AC15 -> 7066.1799 | AE15: =Peak_Time_Eve*$BI15*(3600/K48+BL15)/3600 -> 29.795228 | AF15: =IF(AF$6<Total_Lanes,($BJ15*($CI15+BN15)+$CN15*CP15)*Peak_Time_Eve/3600,"-") -> 4871.4233 | AG15: =IF(AG$6<Total_Lanes,($BJ15*($CI15+BO15)+$CN15*CQ15)*Peak_Time_Eve/3600,"-") -> 46.652176 | AH15: =IF(AH$6<Total_Lanes,($BJ15*($CI15+BP15)+$CN15*CR15)*Peak_Time_Eve/3600,"-") -> 31.991909 | AI15: =IF(AI$6<Total_Lanes,($BJ15*($CI15+BQ15)+$CN15*CS15)*Peak_Time_Eve/3600,"-") -> 145.56777 | AJ15: =IF(AJ$6<Total_Lanes,($BJ15*($CI15+BR15)+$CN15*CT15)*Peak_Time_Eve/3600,"-") -> 1249.6805 | AK15: =IF(AK$6<Total_Lanes,($BJ15*($CI15+BS15)+$CN15*CU15)*Peak_Time_Eve/3600,"-") -> 2867.2754 | AL15: =IF(AL$6<Total_Lanes,($BJ15*($CI15+BT15)+$CN15*CV15)*Peak_Time_Eve/3600,"-") -> 5140.3362 | AM15: =IF(AM$6<Total_Lanes,($BJ15*($CI15+BU15)+$CN15*CW15)*Peak_Time_Eve/3600,"-") -> 8552.6486 | ... AZ15: =IF(AZ$6<Total_Lanes,($BJ15*($CI15+CH15)+$CN15*DJ15)*Peak_Time_Eve/3600,"-") -> - | BA15: =SUMIF(AF15:AZ15,BB15,$AF$6:$AZ$6) -> 3 | BB15: =MIN(AF15:AZ15) -> 31.991909 | BC15: =IF((SUMIF($BN13:$CH13,$BA15,$BN15:$CH15)+$CI15)<(SUMIF($CP13:$DJ13,$BA15,$CP15:$DJ15)+$DK15),BA15+1,BA15) -> 3 | BD15: =SUMIF($AF$6:$AZ$6,$BC15,$AF15:$AZ15) -> 31.991909 | BG15: 8 | BH15: =$Y15 -> 0.396 | BI15: =$AD15 -> 7066.1799 | BJ15: =BI15*(1-BH15) -> 4267.9727 | BK15: =Peak_Arrival_Manual/K48 -> 7.7949779 | BL15: =900*Peak_Time_Eve*(BK15/Total_Lanes-1+SQRT((BK15/Total_Lanes-1)^2+8*(BK15/Total_Lanes)/(Peak_Time_Eve*$K48*Total_Lanes))) -> 1.0148734 | BM15: =Peak_Arrival_Manual/N48 -> 7.996521 | BN15: =IF(BN$6<Total_Lanes,900*Peak_Time_Eve*(($BM15/(Total_Lanes-BN$6))-1+SQRT((($BM15/(Total_Lanes-BN$6))-1)^2+8*($BM15/(Total_Lanes-BN$6))/(Peak_Time_Eve*$N48*(Total_Lanes-BN$6)))),"-") -> 1.6298448 | BO15: =IF(BO$6<Total_Lanes,900*Peak_Time_Eve*(($BM15/(Total_Lanes-BO$6))-1+SQRT((($BM15/(Total_Lanes-BO$6))-1)^2+8*($BM15/(Total_Lanes-BO$6))/(Peak_Time_Eve*$N48*(Total_Lanes-BO$6)))),"-") -> 2.6821694 | BP15: =IF(BP$6<Total_Lanes,900*Peak_Time_Eve*(($BM15/(Total_Lanes-BP$6))-1+SQRT((($BM15/(Total_Lanes-BP$6))-1)^2+8*($BM15/(Total_Lanes-BP$6))/(Peak_Time_Eve*$N48*(Total_Lanes-BP$6)))),"-") -> 5.885863 | BQ15: =IF(BQ$6<Total_Lanes,900*Peak_Time_Eve*(($BM15/(Total_Lanes-BQ$6))-1+SQRT((($BM15/(Total_Lanes-BQ$6))-1)^2+8*($BM15/(Total_Lanes-BQ$6))/(Peak_Time_Eve*$N48*(Total_Lanes-BQ$6)))),"-") -> 54.303914 | BR15: =IF(BR$6<Total_Lanes,900*Peak_Time_Eve*(($BM15/(Total_Lanes-BR$6))-1+SQRT((($BM15/(Total_Lanes-BR$6))-1)^2+8*($BM15/(Total_Lanes-BR$6))/(Peak_Time_Eve*$N48*(Total_Lanes-BR$6)))),"-") -> 520.11538 | BS15: =IF(BS$6<Total_Lanes,900*Peak_Time_Eve*(($BM15/(Total_Lanes-BS$6))-1+SQRT((($BM15/(Total_Lanes-BS$6))-1)^2+8*($BM15/(Total_Lanes-BS$6))/(Peak_Time_Eve*$N48*(Total_Lanes-BS$6)))),"-") -> 1202.3984 | BT15: =IF(BT$6<Total_Lanes,900*Peak_Time_Eve*(($BM15/(Total_Lanes-BT$6))-1+SQRT((($BM15/(Total_Lanes-BT$6))-1)^2+8*($BM15/(Total_Lanes-BT$6))/(Peak_Time_Eve*$N48*(Total_Lanes-BT$6)))),"-") -> 2161.0891 | BU15: =IF(BU$6<Total_Lanes,900*Peak_Time_Eve*(($BM15/(Total_Lanes-BU$6))-1+SQRT((($BM15/(Total_Lanes-BU$6))-1)^2+8*($BM15/(Total_Lanes-BU$6))/(Peak_Time_Eve*$N48*(Total_Lanes-BU$6)))),"-") -> 3600.2397 | ... CH15: =IF(CH$6<Total_Lanes,900*Peak_Time_Eve*(($BM15/(Total_Lanes-CH$6))-1+SQRT((($BM15/(Total_Lanes-CH$6))-1)^2+8*($BM15/(Total_Lanes-CH$6))/(Peak_Time_Eve*$N48*(Total_Lanes-CH$6)))),"-") -> - | CI15: =3600/N48 -> 6.745 | CK15: 8 | CL15: =$Y15 -> 0.396 | CM15: =$AD15 -> 7066.1799 | CN15: =CM15*CL15 -> 2798.2072 | CO15: =CN15/O47 -> 1.8654715 | CP15: =IF(CP$6<Total_Lanes,900*Peak_Time_Eve*(($CO15/CP$6-1)+SQRT(($CO15/CP$6-1)^2+8*($CO15/CP$6)/(Peak_Time_Eve*$O48*CP$6))),"-") -> 3120.8619 | CQ15: =IF(CQ$6<Total_Lanes,900*Peak_Time_Eve*(($CO15/CQ$6-1)+SQRT(($CO15/CQ$6-1)^2+8*($CO15/CQ$6)/(Peak_Time_Eve*$O48*CQ$6))),"-") -> 15.631085 | CR15: =IF(CR$6<Total_Lanes,900*Peak_Time_Eve*(($CO15/CR$6-1)+SQRT(($CO15/CR$6-1)^2+8*($CO15/CR$6)/(Peak_Time_Eve*$O48*CR$6))),"-") -> 1.3141477 | CS15: =IF(CS$6<Total_Lanes,900*Peak_Time_Eve*(($CO15/CS$6-1)+SQRT(($CO15/CS$6-1)^2+8*($CO15/CS$6)/(Peak_Time_Eve*$O48*CS$6))),"-") -> 0.52422704 | CT15: =IF(CT$6<Total_Lanes,900*Peak_Time_Eve*(($CO15/CT$6-1)+SQRT(($CO15/CT$6-1)^2+8*($CO15/CT$6)/(Peak_Time_Eve*$O48*CT$6))),"-") -> 0.28562924 | CU15: =IF(CU$6<Total_Lanes,900*Peak_Time_Eve*(($CO15/CU$6-1)+SQRT(($CO15/CU$6-1)^2+8*($CO15/CU$6)/(Peak_Time_Eve*$O48*CU$6))),"-") -> 0.18046419 | CV15: =IF(CV$6<Total_Lanes,900*Peak_Time_Eve*(($CO15/CV$6-1)+SQRT(($CO15/CV$6-1)^2+8*($CO15/CV$6)/(Peak_Time_Eve*$O48*CV$6))),"-") -> 0.12456062 | CW15: =IF(CW$6<Total_Lanes,900*Peak_Time_Eve*(($CO15/CW$6-1)+SQRT(($CO15/CW$6-1)^2+8*($CO15/CW$6)/(Peak_Time_Eve*$O48*CW$6))),"-") -> 0.091225097 | ... DJ15: =IF(DJ$6<Total_Lanes,900*Peak_Time_Eve*(($CO15/DJ$6-1)+SQRT(($CO15/DJ$6-1)^2+8*($CO15/DJ$6)/(Peak_Time_Eve*$O48*DJ$6))),"-") -> - | DK15: =3600/O48 -> 2.4
H16: 9 | I16: ='Input-Detail'!E23 -> 23958895 | J16: ='Input-Detail'!F23 -> 0.4455 | K16: =AD16 -> 7231.9524 | L16: =IF(AD16>AD64,BC16,BC64) -> 3 | M16: =AE64 -> 11.984936 | N16: =AE16 -> 29.862682 | O16: =SUM(M16:N16) -> 41.847619 | P16: =$S$34*O16 -> 10880.381 | Q16: =SUMIF($AF$54:$AZ$54,L16,$AF64:$AZ64) -> 7.1337567 | R16: =SUMIF($AF$6:$AZ$6,$L16,$AF16:$AZ16) -> 27.249281 | S16: =SUM(Q16:R16) -> 34.383037 | T16: =$S$34*S16 -> 8939.5897 | W16: 9 | X16: =X$7+(X$27-X$7)*$W16/20 -> 23958895 | Y16: =J16 -> 0.4455 | Z16: ='Input-Detail'!E23/AA16 -> 10331.361 | AA16: =AA15 -> 2319.0455 | AB16: =AB15 -> 2 | AC16: =AC15 -> 0.7 | AD16: =Z16*AC16 -> 7231.9524 | AE16: =Peak_Time_Eve*$BI16*(3600/K49+BL16)/3600 -> 29.862682 | AF16: =IF(AF$6<Total_Lanes,($BJ16*($CI16+BN16)+$CN16*CP16)*Peak_Time_Eve/3600,"-") -> 7422.7057 | AG16: =IF(AG$6<Total_Lanes,($BJ16*($CI16+BO16)+$CN16*CQ16)*Peak_Time_Eve/3600,"-") -> 525.53621 | AH16: =IF(AH$6<Total_Lanes,($BJ16*($CI16+BP16)+$CN16*CR16)*Peak_Time_Eve/3600,"-") -> 27.249281 | AI16: =IF(AI$6<Total_Lanes,($BJ16*($CI16+BQ16)+$CN16*CS16)*Peak_Time_Eve/3600,"-") -> 45.200123 | AJ16: =IF(AJ$6<Total_Lanes,($BJ16*($CI16+BR16)+$CN16*CT16)*Peak_Time_Eve/3600,"-") -> 659.93644 | AK16: =IF(AK$6<Total_Lanes,($BJ16*($CI16+BS16)+$CN16*CU16)*Peak_Time_Eve/3600,"-") -> 2082.3326 | AL16: =IF(AL$6<Total_Lanes,($BJ16*($CI16+BT16)+$CN16*CV16)*Peak_Time_Eve/3600,"-") -> 4093.865 | AM16: =IF(AM$6<Total_Lanes,($BJ16*($CI16+BU16)+$CN16*CW16)*Peak_Time_Eve/3600,"-") -> 7115.3293 | ... AZ16: =IF(AZ$6<Total_Lanes,($BJ16*($CI16+CH16)+$CN16*DJ16)*Peak_Time_Eve/3600,"-") -> - | BA16: =SUMIF(AF16:AZ16,BB16,$AF$6:$AZ$6) -> 3 | BB16: =MIN(AF16:AZ16) -> 27.249281 | BC16: =IF((SUMIF($BN14:$CH14,$BA16,$BN16:$CH16)+$CI16)<(SUMIF($CP14:$DJ14,$BA16,$CP16:$DJ16)+$DK16),BA16+1,BA16) -> 3 | BD16: =SUMIF($AF$6:$AZ$6,$BC16,$AF16:$AZ16) -> 27.249281 | BG16: 9 | BH16: =$Y16 -> 0.4455 | BI16: =$AD16 -> 7231.9524 | BJ16: =BI16*(1-BH16) -> 4010.1176 | BK16: =Peak_Arrival_Manual/K49 -> 7.3240342 | BL16: =900*Peak_Time_Eve*(BK16/Total_Lanes-1+SQRT((BK16/Total_Lanes-1)^2+8*(BK16/Total_Lanes)/(Peak_Time_Eve*$K49*Total_Lanes))) -> 0.85768557 | BM16: =Peak_Arrival_Manual/N49 -> 7.5370717 | BN16: =IF(BN$6<Total_Lanes,900*Peak_Time_Eve*(($BM16/(Total_Lanes-BN$6))-1+SQRT((($BM16/(Total_Lanes-BN$6))-1)^2+8*($BM16/(Total_Lanes-BN$6))/(Peak_Time_Eve*$N49*(Total_Lanes-BN$6)))),"-") -> 1.3372185 | BO16: =IF(BO$6<Total_Lanes,900*Peak_Time_Eve*(($BM16/(Total_Lanes-BO$6))-1+SQRT((($BM16/(Total_Lanes-BO$6))-1)^2+8*($BM16/(Total_Lanes-BO$6))/(Peak_Time_Eve*$N49*(Total_Lanes-BO$6)))),"-") -> 2.0657999 | BP16: =IF(BP$6<Total_Lanes,900*Peak_Time_Eve*(($BM16/(Total_Lanes-BP$6))-1+SQRT((($BM16/(Total_Lanes-BP$6))-1)^2+8*($BM16/(Total_Lanes-BP$6))/(Peak_Time_Eve*$N49*(Total_Lanes-BP$6)))),"-") -> 3.8480315 | BQ16: =IF(BQ$6<Total_Lanes,900*Peak_Time_Eve*(($BM16/(Total_Lanes-BQ$6))-1+SQRT((($BM16/(Total_Lanes-BQ$6))-1)^2+8*($BM16/(Total_Lanes-BQ$6))/(Peak_Time_Eve*$N49*(Total_Lanes-BQ$6)))),"-") -> 12.96368 | BR16: =IF(BR$6<Total_Lanes,900*Peak_Time_Eve*(($BM16/(Total_Lanes-BR$6))-1+SQRT((($BM16/(Total_Lanes-BR$6))-1)^2+8*($BM16/(Total_Lanes-BR$6))/(Peak_Time_Eve*$N49*(Total_Lanes-BR$6)))),"-") -> 289.16551 | BS16: =IF(BS$6<Total_Lanes,900*Peak_Time_Eve*(($BM16/(Total_Lanes-BS$6))-1+SQRT((($BM16/(Total_Lanes-BS$6))-1)^2+8*($BM16/(Total_Lanes-BS$6))/(Peak_Time_Eve*$N49*(Total_Lanes-BS$6)))),"-") -> 927.74003 | BT16: =IF(BT$6<Total_Lanes,900*Peak_Time_Eve*(($BM16/(Total_Lanes-BT$6))-1+SQRT((($BM16/(Total_Lanes-BT$6))-1)^2+8*($BM16/(Total_Lanes-BT$6))/(Peak_Time_Eve*$N49*(Total_Lanes-BT$6)))),"-") -> 1830.7031 | BU16: =IF(BU$6<Total_Lanes,900*Peak_Time_Eve*(($BM16/(Total_Lanes-BU$6))-1+SQRT((($BM16/(Total_Lanes-BU$6))-1)^2+8*($BM16/(Total_Lanes-BU$6))/(Peak_Time_Eve*$N49*(Total_Lanes-BU$6)))),"-") -> 3186.965 | ... CH16: =IF(CH$6<Total_Lanes,900*Peak_Time_Eve*(($BM16/(Total_Lanes-CH$6))-1+SQRT((($BM16/(Total_Lanes-CH$6))-1)^2+8*($BM16/(Total_Lanes-CH$6))/(Peak_Time_Eve*$N49*(Total_Lanes-CH$6)))),"-") -> - | CI16: =3600/N49 -> 6.76625 | CK16: 9 | CL16: =$Y16 -> 0.4455 | CM16: =$AD16 -> 7231.9524 | CN16: =CM16*CL16 -> 3221.8348 | CO16: =CN16/O48 -> 2.1478899 | CP16: =IF(CP$6<Total_Lanes,900*Peak_Time_Eve*(($CO16/CP$6-1)+SQRT(($CO16/CP$6-1)^2+8*($CO16/CP$6)/(Peak_Time_Eve*$O49*CP$6))),"-") -> 4136.8894 | CQ16: =IF(CQ$6<Total_Lanes,900*Peak_Time_Eve*(($CO16/CQ$6-1)+SQRT(($CO16/CQ$6-1)^2+8*($CO16/CQ$6)/(Peak_Time_Eve*$O49*CQ$6))),"-") -> 282.61772 | CR16: =IF(CR$6<Total_Lanes,900*Peak_Time_Eve*(($CO16/CR$6-1)+SQRT(($CO16/CR$6-1)^2+8*($CO16/CR$6)/(Peak_Time_Eve*$O49*CR$6))),"-") -> 2.0125761 | CS16: =IF(CS$6<Total_Lanes,900*Peak_Time_Eve*(($CO16/CS$6-1)+SQRT(($CO16/CS$6-1)^2+8*($CO16/CS$6)/(Peak_Time_Eve*$O49*CS$6))),"-") -> 0.69552905 | CT16: =IF(CT$6<Total_Lanes,900*Peak_Time_Eve*(($CO16/CT$6-1)+SQRT(($CO16/CT$6-1)^2+8*($CO16/CT$6)/(Peak_Time_Eve*$O49*CT$6))),"-") -> 0.36141862 | CU16: =IF(CU$6<Total_Lanes,900*Peak_Time_Eve*(($CO16/CU$6-1)+SQRT(($CO16/CU$6-1)^2+8*($CO16/CU$6)/(Peak_Time_Eve*$O49*CU$6))),"-") -> 0.22301363 | CV16: =IF(CV$6<Total_Lanes,900*Peak_Time_Eve*(($CO16/CV$6-1)+SQRT(($CO16/CV$6-1)^2+8*($CO16/CV$6)/(Peak_Time_Eve*$O49*CV$6))),"-") -> 0.15176378 | CW16: =IF(CW$6<Total_Lanes,900*Peak_Time_Eve*(($CO16/CW$6-1)+SQRT(($CO16/CW$6-1)^2+8*($CO16/CW$6)/(Peak_Time_Eve*$O49*CW$6))),"-") -> 0.11010388 | ... DJ16: =IF(DJ$6<Total_Lanes,900*Peak_Time_Eve*(($CO16/DJ$6-1)+SQRT(($CO16/DJ$6-1)^2+8*($CO16/DJ$6)/(Peak_Time_Eve*$O49*DJ$6))),"-") -> - | DK16: =3600/O49 -> 2.4
H17: 10 | I17: ='Input-Detail'!E24 -> 24508086 | J17: ='Input-Detail'!F24 -> 0.495 | K17: =AD17 -> 7397.7249 | L17: =IF(AD17>AD65,BC17,BC65) -> 3 | M17: =AE65 -> 12.266177 | N17: =AE17 -> 29.988803 | O17: =SUM(M17:N17) -> 42.25498 | P17: =$S$34*O17 -> 10986.295 | Q17: =SUMIF($AF$54:$AZ$54,L17,$AF65:$AZ65) -> 6.7493544 | R17: =SUMIF($AF$6:$AZ$6,$L17,$AF17:$AZ17) -> 26.777395 | S17: =SUM(Q17:R17) -> 33.526749 | T17: =$S$34*S17 -> 8716.9549 | W17: 10 | X17: =X$7+(X$27-X$7)*$W17/20 -> 24508086 | Y17: =J17 -> 0.495 | Z17: ='Input-Detail'!E24/AA17 -> 10568.178 | AA17: =AA16 -> 2319.0455 | AB17: =AB16 -> 2 | AC17: =AC16 -> 0.7 | AD17: =Z17*AC17 -> 7397.7249 | AE17: =Peak_Time_Eve*$BI17*(3600/K50+BL17)/3600 -> 29.988803 | AF17: =IF(AF$6<Total_Lanes,($BJ17*($CI17+BN17)+$CN17*CP17)*Peak_Time_Eve/3600,"-") -> 10579.975 | AG17: =IF(AG$6<Total_Lanes,($BJ17*($CI17+BO17)+$CN17*CQ17)*Peak_Time_Eve/3600,"-") -> 1646.6329 | AH17: =IF(AH$6<Total_Lanes,($BJ17*($CI17+BP17)+$CN17*CR17)*Peak_Time_Eve/3600,"-") -> 26.777395 | AI17: =IF(AI$6<Total_Lanes,($BJ17*($CI17+BQ17)+$CN17*CS17)*Peak_Time_Eve/3600,"-") -> 28.783774 | AJ17: =IF(AJ$6<Total_Lanes,($BJ17*($CI17+BR17)+$CN17*CT17)*Peak_Time_Eve/3600,"-") -> 163.49723 | AK17: =IF(AK$6<Total_Lanes,($BJ17*($CI17+BS17)+$CN17*CU17)*Peak_Time_Eve/3600,"-") -> 1329.9257 | AL17: =IF(AL$6<Total_Lanes,($BJ17*($CI17+BT17)+$CN17*CV17)*Peak_Time_Eve/3600,"-") -> 3078.0285 | AM17: =IF(AM$6<Total_Lanes,($BJ17*($CI17+BU17)+$CN17*CW17)*Peak_Time_Eve/3600,"-") -> 5707.7791 | ... AZ17: =IF(AZ$6<Total_Lanes,($BJ17*($CI17+CH17)+$CN17*DJ17)*Peak_Time_Eve/3600,"-") -> - | BA17: =SUMIF(AF17:AZ17,BB17,$AF$6:$AZ$6) -> 3 | BB17: =MIN(AF17:AZ17) -> 26.777395 | BC17: =IF((SUMIF($BN15:$CH15,$BA17,$BN17:$CH17)+$CI17)<(SUMIF($CP15:$DJ15,$BA17,$CP17:$DJ17)+$DK17),BA17+1,BA17) -> 3 | BD17: =SUMIF($AF$6:$AZ$6,$BC17,$AF17:$AZ17) -> 26.777395 | BG17: 10 | BH17: =$Y17 -> 0.495 | BI17: =$AD17 -> 7397.7249 | BJ17: =BI17*(1-BH17) -> 3735.8511 | BK17: =Peak_Arrival_Manual/K50 -> 6.8231169 | BL17: =900*Peak_Time_Eve*(BK17/Total_Lanes-1+SQRT((BK17/Total_Lanes-1)^2+8*(BK17/Total_Lanes)/(Peak_Time_Eve*$K50*Total_Lanes))) -> 0.7218171 | BM17: =Peak_Arrival_Manual/N50 -> 7.0436359 | BN17: =IF(BN$6<Total_Lanes,900*Peak_Time_Eve*(($BM17/(Total_Lanes-BN$6))-1+SQRT((($BM17/(Total_Lanes-BN$6))-1)^2+8*($BM17/(Total_Lanes-BN$6))/(Peak_Time_Eve*$N50*(Total_Lanes-BN$6)))),"-") -> 1.0976144 | BO17: =IF(BO$6<Total_Lanes,900*Peak_Time_Eve*(($BM17/(Total_Lanes-BO$6))-1+SQRT((($BM17/(Total_Lanes-BO$6))-1)^2+8*($BM17/(Total_Lanes-BO$6))/(Peak_Time_Eve*$N50*(Total_Lanes-BO$6)))),"-") -> 1.6146947 | BP17: =IF(BP$6<Total_Lanes,900*Peak_Time_Eve*(($BM17/(Total_Lanes-BP$6))-1+SQRT((($BM17/(Total_Lanes-BP$6))-1)^2+8*($BM17/(Total_Lanes-BP$6))/(Peak_Time_Eve*$N50*(Total_Lanes-BP$6)))),"-") -> 2.7059228 | BQ17: =IF(BQ$6<Total_Lanes,900*Peak_Time_Eve*(($BM17/(Total_Lanes-BQ$6))-1+SQRT((($BM17/(Total_Lanes-BQ$6))-1)^2+8*($BM17/(Total_Lanes-BQ$6))/(Peak_Time_Eve*$N50*(Total_Lanes-BQ$6)))),"-") -> 6.1605675 | BR17: =IF(BR$6<Total_Lanes,900*Peak_Time_Eve*(($BM17/(Total_Lanes-BR$6))-1+SQRT((($BM17/(Total_Lanes-BR$6))-1)^2+8*($BM17/(Total_Lanes-BR$6))/(Peak_Time_Eve*$N50*(Total_Lanes-BR$6)))),"-") -> 71.539619 | BS17: =IF(BS$6<Total_Lanes,900*Peak_Time_Eve*(($BM17/(Total_Lanes-BS$6))-1+SQRT((($BM17/(Total_Lanes-BS$6))-1)^2+8*($BM17/(Total_Lanes-BS$6))/(Peak_Time_Eve*$N50*(Total_Lanes-BS$6)))),"-") -> 633.72559 | BT17: =IF(BT$6<Total_Lanes,900*Peak_Time_Eve*(($BM17/(Total_Lanes-BT$6))-1+SQRT((($BM17/(Total_Lanes-BT$6))-1)^2+8*($BM17/(Total_Lanes-BT$6))/(Peak_Time_Eve*$N50*(Total_Lanes-BT$6)))),"-") -> 1476.0818 | BU17: =IF(BU$6<Total_Lanes,900*Peak_Time_Eve*(($BM17/(Total_Lanes-BU$6))-1+SQRT((($BM17/(Total_Lanes-BU$6))-1)^2+8*($BM17/(Total_Lanes-BU$6))/(Peak_Time_Eve*$N50*(Total_Lanes-BU$6)))),"-") -> 2743.1936 | ... CH17: =IF(CH$6<Total_Lanes,900*Peak_Time_Eve*(($BM17/(Total_Lanes-CH$6))-1+SQRT((($BM17/(Total_Lanes-CH$6))-1)^2+8*($BM17/(Total_Lanes-CH$6))/(Peak_Time_Eve*$N50*(Total_Lanes-CH$6)))),"-") -> - | CI17: =3600/N50 -> 6.7875 | CK17: 10 | CL17: =$Y17 -> 0.495 | CM17: =$AD17 -> 7397.7249 | CN17: =CM17*CL17 -> 3661.8738 | CO17: =CN17/O49 -> 2.4412492 | CP17: =IF(CP$6<Total_Lanes,900*Peak_Time_Eve*(($CO17/CP$6-1)+SQRT(($CO17/CP$6-1)^2+8*($CO17/CP$6)/(Peak_Time_Eve*$O50*CP$6))),"-") -> 5192.5592 | CQ17: =IF(CQ$6<Total_Lanes,900*Peak_Time_Eve*(($CO17/CQ$6-1)+SQRT(($CO17/CQ$6-1)^2+8*($CO17/CQ$6)/(Peak_Time_Eve*$O50*CQ$6))),"-") -> 800.83311 | CR17: =IF(CR$6<Total_Lanes,900*Peak_Time_Eve*(($CO17/CR$6-1)+SQRT(($CO17/CR$6-1)^2+8*($CO17/CR$6)/(Peak_Time_Eve*$O50*CR$6))),"-") -> 3.4772627 | CS17: =IF(CS$6<Total_Lanes,900*Peak_Time_Eve*(($CO17/CS$6-1)+SQRT(($CO17/CS$6-1)^2+8*($CO17/CS$6)/(Peak_Time_Eve*$O50*CS$6))),"-") -> 0.9390659 | CT17: =IF(CT$6<Total_Lanes,900*Peak_Time_Eve*(($CO17/CT$6-1)+SQRT(($CO17/CT$6-1)^2+8*($CO17/CT$6)/(Peak_Time_Eve*$O50*CT$6))),"-") -> 0.45784392 | CU17: =IF(CU$6<Total_Lanes,900*Peak_Time_Eve*(($CO17/CU$6-1)+SQRT(($CO17/CU$6-1)^2+8*($CO17/CU$6)/(Peak_Time_Eve*$O50*CU$6))),"-") -> 0.2743587 | CV17: =IF(CV$6<Total_Lanes,900*Peak_Time_Eve*(($CO17/CV$6-1)+SQRT(($CO17/CV$6-1)^2+8*($CO17/CV$6)/(Peak_Time_Eve*$O50*CV$6))),"-") -> 0.18358849 | CW17: =IF(CW$6<Total_Lanes,900*Peak_Time_Eve*(($CO17/CW$6-1)+SQRT(($CO17/CW$6-1)^2+8*($CO17/CW$6)/(Peak_Time_Eve*$O50*CW$6))),"-") -> 0.13174474 | ... DJ17: =IF(DJ$6<Total_Lanes,900*Peak_Time_Eve*(($CO17/DJ$6-1)+SQRT(($CO17/DJ$6-1)^2+8*($CO17/DJ$6)/(Peak_Time_Eve*$O50*DJ$6))),"-") -> - | DK17: =3600/O50 -> 2.4
H18: 11 | I18: ='Input-Detail'!E25 -> 25057278 | J18: ='Input-Detail'!F25 -> 0.5445 | K18: =AD18 -> 7563.4974 | L18: =IF(AD18>AD66,BC18,BC66) -> 4 | M18: =AE66 -> 12.547411 | N18: =AE18 -> 30.164942 | O18: =SUM(M18:N18) -> 42.712353 | P18: =$S$34*O18 -> 11105.212 | Q18: =SUMIF($AF$54:$AZ$54,L18,$AF66:$AZ66) -> 6.2045548 | R18: =SUMIF($AF$6:$AZ$6,$L18,$AF18:$AZ18) -> 23.145431 | S18: =SUM(Q18:R18) -> 29.349986 | T18: =$S$34*S18 -> 7630.9964 | W18: 11 | X18: =X$7+(X$27-X$7)*$W18/20 -> 25057278 | Y18: =J18 -> 0.5445 | Z18: ='Input-Detail'!E25/AA18 -> 10804.996 | AA18: =AA17 -> 2319.0455 | AB18: =AB17 -> 2 | AC18: =AC17 -> 0.7 | AD18: =Z18*AC18 -> 7563.4974 | AE18: =Peak_Time_Eve*$BI18*(3600/K51+BL18)/3600 -> 30.164942 | AF18: =IF(AF$6<Total_Lanes,($BJ18*($CI18+BN18)+$CN18*CP18)*Peak_Time_Eve/3600,"-") -> 14400.862 | AG18: =IF(AG$6<Total_Lanes,($BJ18*($CI18+BO18)+$CN18*CQ18)*Peak_Time_Eve/3600,"-") -> 3095.9591 | AH18: =IF(AH$6<Total_Lanes,($BJ18*($CI18+BP18)+$CN18*CR18)*Peak_Time_Eve/3600,"-") -> 36.043487 | AI18: =IF(AI$6<Total_Lanes,($BJ18*($CI18+BQ18)+$CN18*CS18)*Peak_Time_Eve/3600,"-") -> 23.145431 | AJ18: =IF(AJ$6<Total_Lanes,($BJ18*($CI18+BR18)+$CN18*CT18)*Peak_Time_Eve/3600,"-") -> 38.232949 | AK18: =IF(AK$6<Total_Lanes,($BJ18*($CI18+BS18)+$CN18*CU18)*Peak_Time_Eve/3600,"-") -> 632.55167 | AL18: =IF(AL$6<Total_Lanes,($BJ18*($CI18+BT18)+$CN18*CV18)*Peak_Time_Eve/3600,"-") -> 2113.7281 | AM18: =IF(AM$6<Total_Lanes,($BJ18*($CI18+BU18)+$CN18*CW18)*Peak_Time_Eve/3600,"-") -> 4355.7065 | ... AZ18: =IF(AZ$6<Total_Lanes,($BJ18*($CI18+CH18)+$CN18*DJ18)*Peak_Time_Eve/3600,"-") -> - | BA18: =SUMIF(AF18:AZ18,BB18,$AF$6:$AZ$6) -> 4 | BB18: =MIN(AF18:AZ18) -> 23.145431 | BC18: =IF((SUMIF($BN16:$CH16,$BA18,$BN18:$CH18)+$CI18)<(SUMIF($CP16:$DJ16,$BA18,$CP18:$DJ18)+$DK18),BA18+1,BA18) -> 4 | BD18: =SUMIF($AF$6:$AZ$6,$BC18,$AF18:$AZ18) -> 23.145431 | BG18: 11 | BH18: =$Y18 -> 0.5445 | BI18: =$AD18 -> 7563.4974 | BJ18: =BI18*(1-BH18) -> 3445.1731 | BK18: =Peak_Arrival_Manual/K51 -> 6.2922258 | BL18: =900*Peak_Time_Eve*(BK18/Total_Lanes-1+SQRT((BK18/Total_Lanes-1)^2+8*(BK18/Total_Lanes)/(Peak_Time_Eve*$K51*Total_Lanes))) -> 0.60380807 | BM18: =Peak_Arrival_Manual/N51 -> 6.5159228 | BN18: =IF(BN$6<Total_Lanes,900*Peak_Time_Eve*(($BM18/(Total_Lanes-BN$6))-1+SQRT((($BM18/(Total_Lanes-BN$6))-1)^2+8*($BM18/(Total_Lanes-BN$6))/(Peak_Time_Eve*$N51*(Total_Lanes-BN$6)))),"-") -> 0.89890048 | BO18: =IF(BO$6<Total_Lanes,900*Peak_Time_Eve*(($BM18/(Total_Lanes-BO$6))-1+SQRT((($BM18/(Total_Lanes-BO$6))-1)^2+8*($BM18/(Total_Lanes-BO$6))/(Peak_Time_Eve*$N51*(Total_Lanes-BO$6)))),"-") -> 1.2720826 | BP18: =IF(BP$6<Total_Lanes,900*Peak_Time_Eve*(($BM18/(Total_Lanes-BP$6))-1+SQRT((($BM18/(Total_Lanes-BP$6))-1)^2+8*($BM18/(Total_Lanes-BP$6))/(Peak_Time_Eve*$N51*(Total_Lanes-BP$6)))),"-") -> 1.9804823 | BQ18: =IF(BQ$6<Total_Lanes,900*Peak_Time_Eve*(($BM18/(Total_Lanes-BQ$6))-1+SQRT((($BM18/(Total_Lanes-BQ$6))-1)^2+8*($BM18/(Total_Lanes-BQ$6))/(Peak_Time_Eve*$N51*(Total_Lanes-BQ$6)))),"-") -> 3.7160962 | BR18: =IF(BR$6<Total_Lanes,900*Peak_Time_Eve*(($BM18/(Total_Lanes-BR$6))-1+SQRT((($BM18/(Total_Lanes-BR$6))-1)^2+8*($BM18/(Total_Lanes-BR$6))/(Peak_Time_Eve*$N51*(Total_Lanes-BR$6)))),"-") -> 12.468297 | BS18: =IF(BS$6<Total_Lanes,900*Peak_Time_Eve*(($BM18/(Total_Lanes-BS$6))-1+SQRT((($BM18/(Total_Lanes-BS$6))-1)^2+8*($BM18/(Total_Lanes-BS$6))/(Peak_Time_Eve*$N51*(Total_Lanes-BS$6)))),"-") -> 323.27728 | BT18: =IF(BT$6<Total_Lanes,900*Peak_Time_Eve*(($BM18/(Total_Lanes-BT$6))-1+SQRT((($BM18/(Total_Lanes-BT$6))-1)^2+8*($BM18/(Total_Lanes-BT$6))/(Peak_Time_Eve*$N51*(Total_Lanes-BT$6)))),"-") -> 1097.2866 | BU18: =IF(BU$6<Total_Lanes,900*Peak_Time_Eve*(($BM18/(Total_Lanes-BU$6))-1+SQRT((($BM18/(Total_Lanes-BU$6))-1)^2+8*($BM18/(Total_Lanes-BU$6))/(Peak_Time_Eve*$N51*(Total_Lanes-BU$6)))),"-") -> 2268.7304 | ... CH18: =IF(CH$6<Total_Lanes,900*Peak_Time_Eve*(($BM18/(Total_Lanes-CH$6))-1+SQRT((($BM18/(Total_Lanes-CH$6))-1)^2+8*($BM18/(Total_Lanes-CH$6))/(Peak_Time_Eve*$N51*(Total_Lanes-CH$6)))),"-") -> - | CI18: =3600/N51 -> 6.80875 | CK18: 11 | CL18: =$Y18 -> 0.5445 | CM18: =$AD18 -> 7563.4974 | CN18: =CM18*CL18 -> 4118.3243 | CO18: =CN18/O50 -> 2.7455496 | CP18: =IF(CP$6<Total_Lanes,900*Peak_Time_Eve*(($CO18/CP$6-1)+SQRT(($CO18/CP$6-1)^2+8*($CO18/CP$6)/(Peak_Time_Eve*$O51*CP$6))),"-") -> 6287.751 | CQ18: =IF(CQ$6<Total_Lanes,900*Peak_Time_Eve*(($CO18/CQ$6-1)+SQRT(($CO18/CQ$6-1)^2+8*($CO18/CQ$6)/(Peak_Time_Eve*$O51*CQ$6))),"-") -> 1346.3938 | CR18: =IF(CR$6<Total_Lanes,900*Peak_Time_Eve*(($CO18/CR$6-1)+SQRT(($CO18/CR$6-1)^2+8*($CO18/CR$6)/(Peak_Time_Eve*$O51*CR$6))),"-") -> 8.4009532 | CS18: =IF(CS$6<Total_Lanes,900*Peak_Time_Eve*(($CO18/CS$6-1)+SQRT(($CO18/CS$6-1)^2+8*($CO18/CS$6)/(Peak_Time_Eve*$O51*CS$6))),"-") -> 1.3116645 | CT18: =IF(CT$6<Total_Lanes,900*Peak_Time_Eve*(($CO18/CT$6-1)+SQRT(($CO18/CT$6-1)^2+8*($CO18/CT$6)/(Peak_Time_Eve*$O51*CT$6))),"-") -> 0.58435062 | CU18: =IF(CU$6<Total_Lanes,900*Peak_Time_Eve*(($CO18/CU$6-1)+SQRT(($CO18/CU$6-1)^2+8*($CO18/CU$6)/(Peak_Time_Eve*$O51*CU$6))),"-") -> 0.3373934 | CV18: =IF(CV$6<Total_Lanes,900*Peak_Time_Eve*(($CO18/CV$6-1)+SQRT(($CO18/CV$6-1)^2+8*($CO18/CV$6)/(Peak_Time_Eve*$O51*CV$6))),"-") -> 0.22123565 | CW18: =IF(CW$6<Total_Lanes,900*Peak_Time_Eve*(($CO18/CW$6-1)+SQRT(($CO18/CW$6-1)^2+8*($CO18/CW$6)/(Peak_Time_Eve*$O51*CW$6))),"-") -> 0.15674527 | ... DJ18: =IF(DJ$6<Total_Lanes,900*Peak_Time_Eve*(($CO18/DJ$6-1)+SQRT(($CO18/DJ$6-1)^2+8*($CO18/DJ$6)/(Peak_Time_Eve*$O51*DJ$6))),"-") -> - | DK18: =3600/O51 -> 2.4
H19: 12 | I19: ='Input-Detail'!E26 -> 25606469 | J19: ='Input-Detail'!F26 -> 0.594 | K19: =AD19 -> 7729.2699 | L19: =IF(AD19>AD67,BC19,BC67) -> 4 | M19: =AE67 -> 12.82877 | N19: =AE19 -> 30.383854 | O19: =SUM(M19:N19) -> 43.212625 | P19: =$S$34*O19 -> 11235.282 | Q19: =SUMIF($AF$54:$AZ$54,L19,$AF67:$AZ67) -> 5.7218142 | R19: =SUMIF($AF$6:$AZ$6,$L19,$AF19:$AZ19) -> 21.201949 | S19: =SUM(Q19:R19) -> 26.923763 | T19: =$S$34*S19 -> 7000.1785 | W19: 12 | X19: =X$7+(X$27-X$7)*$W19/20 -> 25606469 | Y19: =J19 -> 0.594 | Z19: ='Input-Detail'!E26/AA19 -> 11041.814 | AA19: =AA18 -> 2319.0455 | AB19: =AB18 -> 2 | AC19: =AC18 -> 0.7 | AD19: =Z19*AC19 -> 7729.2699 | AE19: =Peak_Time_Eve*$BI19*(3600/K52+BL19)/3600 -> 30.383854 | AF19: =IF(AF$6<Total_Lanes,($BJ19*($CI19+BN19)+$CN19*CP19)*Peak_Time_Eve/3600,"-") -> 18945.221 | AG19: =IF(AG$6<Total_Lanes,($BJ19*($CI19+BO19)+$CN19*CQ19)*Peak_Time_Eve/3600,"-") -> 4892.7622 | AH19: =IF(AH$6<Total_Lanes,($BJ19*($CI19+BP19)+$CN19*CR19)*Peak_Time_Eve/3600,"-") -> 274.17291 | AI19: =IF(AI$6<Total_Lanes,($BJ19*($CI19+BQ19)+$CN19*CS19)*Peak_Time_Eve/3600,"-") -> 21.201949 | AJ19: =IF(AJ$6<Total_Lanes,($BJ19*($CI19+BR19)+$CN19*CT19)*Peak_Time_Eve/3600,"-") -> 23.419518 | AK19: =IF(AK$6<Total_Lanes,($BJ19*($CI19+BS19)+$CN19*CU19)*Peak_Time_Eve/3600,"-") -> 102.50837 | AL19: =IF(AL$6<Total_Lanes,($BJ19*($CI19+BT19)+$CN19*CV19)*Peak_Time_Eve/3600,"-") -> 1224.3172 | AM19: =IF(AM$6<Total_Lanes,($BJ19*($CI19+BU19)+$CN19*CW19)*Peak_Time_Eve/3600,"-") -> 3086.7722 | ... AZ19: =IF(AZ$6<Total_Lanes,($BJ19*($CI19+CH19)+$CN19*DJ19)*Peak_Time_Eve/3600,"-") -> - | BA19: =SUMIF(AF19:AZ19,BB19,$AF$6:$AZ$6) -> 4 | BB19: =MIN(AF19:AZ19) -> 21.201949 | BC19: =IF((SUMIF($BN17:$CH17,$BA19,$BN19:$CH19)+$CI19)<(SUMIF($CP17:$DJ17,$BA19,$CP19:$DJ19)+$DK19),BA19+1,BA19) -> 4 | BD19: =SUMIF($AF$6:$AZ$6,$BC19,$AF19:$AZ19) -> 21.201949 | BG19: 12 | BH19: =$Y19 -> 0.594 | BI19: =$AD19 -> 7729.2699 | BJ19: =BI19*(1-BH19) -> 3138.0836 | BK19: =Peak_Arrival_Manual/K52 -> 5.731361 | BL19: =900*Peak_Time_Eve*(BK19/Total_Lanes-1+SQRT((BK19/Total_Lanes-1)^2+8*(BK19/Total_Lanes)/(Peak_Time_Eve*$K52*Total_Lanes))) -> 0.50082197 | BM19: =Peak_Arrival_Manual/N52 -> 5.9536419 | BN19: =IF(BN$6<Total_Lanes,900*Peak_Time_Eve*(($BM19/(Total_Lanes-BN$6))-1+SQRT((($BM19/(Total_Lanes-BN$6))-1)^2+8*($BM19/(Total_Lanes-BN$6))/(Peak_Time_Eve*$N52*(Total_Lanes-BN$6)))),"-") -> 0.73221759 | BO19: =IF(BO$6<Total_Lanes,900*Peak_Time_Eve*(($BM19/(Total_Lanes-BO$6))-1+SQRT((($BM19/(Total_Lanes-BO$6))-1)^2+8*($BM19/(Total_Lanes-BO$6))/(Peak_Time_Eve*$N52*(Total_Lanes-BO$6)))),"-") -> 1.0042453 | BP19: =IF(BP$6<Total_Lanes,900*Peak_Time_Eve*(($BM19/(Total_Lanes-BP$6))-1+SQRT((($BM19/(Total_Lanes-BP$6))-1)^2+8*($BM19/(Total_Lanes-BP$6))/(Peak_Time_Eve*$N52*(Total_Lanes-BP$6)))),"-") -> 1.4813317 | BQ19: =IF(BQ$6<Total_Lanes,900*Peak_Time_Eve*(($BM19/(Total_Lanes-BQ$6))-1+SQRT((($BM19/(Total_Lanes-BQ$6))-1)^2+8*($BM19/(Total_Lanes-BQ$6))/(Peak_Time_Eve*$N52*(Total_Lanes-BQ$6)))),"-") -> 2.4772227 | BR19: =IF(BR$6<Total_Lanes,900*Peak_Time_Eve*(($BM19/(Total_Lanes-BR$6))-1+SQRT((($BM19/(Total_Lanes-BR$6))-1)^2+8*($BM19/(Total_Lanes-BR$6))/(Peak_Time_Eve*$N52*(Total_Lanes-BR$6)))),"-") -> 5.4955648 | BS19: =IF(BS$6<Total_Lanes,900*Peak_Time_Eve*(($BM19/(Total_Lanes-BS$6))-1+SQRT((($BM19/(Total_Lanes-BS$6))-1)^2+8*($BM19/(Total_Lanes-BS$6))/(Peak_Time_Eve*$N52*(Total_Lanes-BS$6)))),"-") -> 51.359358 | BT19: =IF(BT$6<Total_Lanes,900*Peak_Time_Eve*(($BM19/(Total_Lanes-BT$6))-1+SQRT((($BM19/(Total_Lanes-BT$6))-1)^2+8*($BM19/(Total_Lanes-BT$6))/(Peak_Time_Eve*$N52*(Total_Lanes-BT$6)))),"-") -> 695.04681 | BU19: =IF(BU$6<Total_Lanes,900*Peak_Time_Eve*(($BM19/(Total_Lanes-BU$6))-1+SQRT((($BM19/(Total_Lanes-BU$6))-1)^2+8*($BM19/(Total_Lanes-BU$6))/(Peak_Time_Eve*$N52*(Total_Lanes-BU$6)))),"-") -> 1763.4659 | ... CH19: =IF(CH$6<Total_Lanes,900*Peak_Time_Eve*(($BM19/(Total_Lanes-CH$6))-1+SQRT((($BM19/(Total_Lanes-CH$6))-1)^2+8*($BM19/(Total_Lanes-CH$6))/(Peak_Time_Eve*$N52*(Total_Lanes-CH$6)))),"-") -> - | CI19: =3600/N52 -> 6.83 | CK19: 12 | CL19: =$Y19 -> 0.594 | CM19: =$AD19 -> 7729.2699 | CN19: =CM19*CL19 -> 4591.1863 | CO19: =CN19/O51 -> 3.0607909 | CP19: =IF(CP$6<Total_Lanes,900*Peak_Time_Eve*(($CO19/CP$6-1)+SQRT(($CO19/CP$6-1)^2+8*($CO19/CP$6)/(Peak_Time_Eve*$O52*CP$6))),"-") -> 7422.41 | CQ19: =IF(CQ$6<Total_Lanes,900*Peak_Time_Eve*(($CO19/CQ$6-1)+SQRT(($CO19/CQ$6-1)^2+8*($CO19/CQ$6)/(Peak_Time_Eve*$O52*CQ$6))),"-") -> 1912.8798 | CR19: =IF(CR$6<Total_Lanes,900*Peak_Time_Eve*(($CO19/CR$6-1)+SQRT(($CO19/CR$6-1)^2+8*($CO19/CR$6)/(Peak_Time_Eve*$O52*CR$6))),"-") -> 101.8102 | CS19: =IF(CS$6<Total_Lanes,900*Peak_Time_Eve*(($CO19/CS$6-1)+SQRT(($CO19/CS$6-1)^2+8*($CO19/CS$6)/(Peak_Time_Eve*$O52*CS$6))),"-") -> 1.9508391 | CT19: =IF(CT$6<Total_Lanes,900*Peak_Time_Eve*(($CO19/CT$6-1)+SQRT(($CO19/CT$6-1)^2+8*($CO19/CT$6)/(Peak_Time_Eve*$O52*CT$6))),"-") -> 0.75720729 | CU19: =IF(CU$6<Total_Lanes,900*Peak_Time_Eve*(($CO19/CU$6-1)+SQRT(($CO19/CU$6-1)^2+8*($CO19/CU$6)/(Peak_Time_Eve*$O52*CU$6))),"-") -> 0.41644784 | CV19: =IF(CV$6<Total_Lanes,900*Peak_Time_Eve*(($CO19/CV$6-1)+SQRT(($CO19/CV$6-1)^2+8*($CO19/CV$6)/(Peak_Time_Eve*$O52*CV$6))),"-") -> 0.26636719 | CW19: =IF(CW$6<Total_Lanes,900*Peak_Time_Eve*(($CO19/CW$6-1)+SQRT(($CO19/CW$6-1)^2+8*($CO19/CW$6)/(Peak_Time_Eve*$O52*CW$6))),"-") -> 0.1858922 | ... DJ19: =IF(DJ$6<Total_Lanes,900*Peak_Time_Eve*(($CO19/DJ$6-1)+SQRT(($CO19/DJ$6-1)^2+8*($CO19/DJ$6)/(Peak_Time_Eve*$O52*DJ$6))),"-") -> - | DK19: =3600/O52 -> 2.4
H20: 13 | I20: ='Input-Detail'!E27 -> 26155661 | J20: ='Input-Detail'!F27 -> 0.6435 | K20: =AD20 -> 7895.0424 | L20: =IF(AD20>AD68,BC20,BC68) -> 5 | M20: =AE68 -> 13.11039 | N20: =AE20 -> 30.639472 | O20: =SUM(M20:N20) -> 43.749862 | P20: =$S$34*O20 -> 11374.964 | Q20: =SUMIF($AF$54:$AZ$54,L20,$AF68:$AZ68) -> 5.1487892 | R20: =SUMIF($AF$6:$AZ$6,$L20,$AF20:$AZ20) -> 18.524582 | S20: =SUM(Q20:R20) -> 23.673371 | T20: =$S$34*S20 -> 6155.0764 | W20: 13 | X20: =X$7+(X$27-X$7)*$W20/20 -> 26155661 | Y20: =J20 -> 0.6435 | Z20: ='Input-Detail'!E27/AA20 -> 11278.632 | AA20: =AA19 -> 2319.0455 | AB20: =AB19 -> 2 | AC20: =AC19 -> 0.7 | AD20: =Z20*AC20 -> 7895.0424 | AE20: =Peak_Time_Eve*$BI20*(3600/K53+BL20)/3600 -> 30.639472 | AF20: =IF(AF$6<Total_Lanes,($BJ20*($CI20+BN20)+$CN20*CP20)*Peak_Time_Eve/3600,"-") -> 24275.087 | AG20: =IF(AG$6<Total_Lanes,($BJ20*($CI20+BO20)+$CN20*CQ20)*Peak_Time_Eve/3600,"-") -> 7066.6709 | AH20: =IF(AH$6<Total_Lanes,($BJ20*($CI20+BP20)+$CN20*CR20)*Peak_Time_Eve/3600,"-") -> 1342.603 | AI20: =IF(AI$6<Total_Lanes,($BJ20*($CI20+BQ20)+$CN20*CS20)*Peak_Time_Eve/3600,"-") -> 22.723481 | AJ20: =IF(AJ$6<Total_Lanes,($BJ20*($CI20+BR20)+$CN20*CT20)*Peak_Time_Eve/3600,"-") -> 18.524582 | AK20: =IF(AK$6<Total_Lanes,($BJ20*($CI20+BS20)+$CN20*CU20)*Peak_Time_Eve/3600,"-") -> 26.689585 | AL20: =IF(AL$6<Total_Lanes,($BJ20*($CI20+BT20)+$CN20*CV20)*Peak_Time_Eve/3600,"-") -> 442.93929 | AM20: =IF(AM$6<Total_Lanes,($BJ20*($CI20+BU20)+$CN20*CW20)*Peak_Time_Eve/3600,"-") -> 1930.8467 | ... AZ20: =IF(AZ$6<Total_Lanes,($BJ20*($CI20+CH20)+$CN20*DJ20)*Peak_Time_Eve/3600,"-") -> - | BA20: =SUMIF(AF20:AZ20,BB20,$AF$6:$AZ$6) -> 5 | BB20: =MIN(AF20:AZ20) -> 18.524582 | BC20: =IF((SUMIF($BN18:$CH18,$BA20,$BN20:$CH20)+$CI20)<(SUMIF($CP18:$DJ18,$BA20,$CP20:$DJ20)+$DK20),BA20+1,BA20) -> 5 | BD20: =SUMIF($AF$6:$AZ$6,$BC20,$AF20:$AZ20) -> 18.524582 | BG20: 13 | BH20: =$Y20 -> 0.6435 | BI20: =$AD20 -> 7895.0424 | BJ20: =BI20*(1-BH20) -> 2814.5826 | BK20: =Peak_Arrival_Manual/K53 -> 5.1405224 | BL20: =900*Peak_Time_Eve*(BK20/Total_Lanes-1+SQRT((BK20/Total_Lanes-1)^2+8*(BK20/Total_Lanes)/(Peak_Time_Eve*$K53*Total_Lanes))) -> 0.41052924 | BM20: =Peak_Arrival_Manual/N53 -> 5.3565025 | BN20: =IF(BN$6<Total_Lanes,900*Peak_Time_Eve*(($BM20/(Total_Lanes-BN$6))-1+SQRT((($BM20/(Total_Lanes-BN$6))-1)^2+8*($BM20/(Total_Lanes-BN$6))/(Peak_Time_Eve*$N53*(Total_Lanes-BN$6)))),"-") -> 0.5909778 | BO20: =IF(BO$6<Total_Lanes,900*Peak_Time_Eve*(($BM20/(Total_Lanes-BO$6))-1+SQRT((($BM20/(Total_Lanes-BO$6))-1)^2+8*($BM20/(Total_Lanes-BO$6))/(Peak_Time_Eve*$N53*(Total_Lanes-BO$6)))),"-") -> 0.78995206 | BP20: =IF(BP$6<Total_Lanes,900*Peak_Time_Eve*(($BM20/(Total_Lanes-BP$6))-1+SQRT((($BM20/(Total_Lanes-BP$6))-1)^2+8*($BM20/(Total_Lanes-BP$6))/(Peak_Time_Eve*$N53*(Total_Lanes-BP$6)))),"-") -> 1.1182967 | BQ20: =IF(BQ$6<Total_Lanes,900*Peak_Time_Eve*(($BM20/(Total_Lanes-BQ$6))-1+SQRT((($BM20/(Total_Lanes-BQ$6))-1)^2+8*($BM20/(Total_Lanes-BQ$6))/(Peak_Time_Eve*$N53*(Total_Lanes-BQ$6)))),"-") -> 1.7328066 | BR20: =IF(BR$6<Total_Lanes,900*Peak_Time_Eve*(($BM20/(Total_Lanes-BR$6))-1+SQRT((($BM20/(Total_Lanes-BR$6))-1)^2+8*($BM20/(Total_Lanes-BR$6))/(Peak_Time_Eve*$N53*(Total_Lanes-BR$6)))),"-") -> 3.1780022 | BS20: =IF(BS$6<Total_Lanes,900*Peak_Time_Eve*(($BM20/(Total_Lanes-BS$6))-1+SQRT((($BM20/(Total_Lanes-BS$6))-1)^2+8*($BM20/(Total_Lanes-BS$6))/(Peak_Time_Eve*$N53*(Total_Lanes-BS$6)))),"-") -> 9.2818816 | BT20: =IF(BT$6<Total_Lanes,900*Peak_Time_Eve*(($BM20/(Total_Lanes-BT$6))-1+SQRT((($BM20/(Total_Lanes-BT$6))-1)^2+8*($BM20/(Total_Lanes-BT$6))/(Peak_Time_Eve*$N53*(Total_Lanes-BT$6)))),"-") -> 275.84008 | BU20: =IF(BU$6<Total_Lanes,900*Peak_Time_Eve*(($BM20/(Total_Lanes-BU$6))-1+SQRT((($BM20/(Total_Lanes-BU$6))-1)^2+8*($BM20/(Total_Lanes-BU$6))/(Peak_Time_Eve*$N53*(Total_Lanes-BU$6)))),"-") -> 1227.5787 | ... CH20: =IF(CH$6<Total_Lanes,900*Peak_Time_Eve*(($BM20/(Total_Lanes-CH$6))-1+SQRT((($BM20/(Total_Lanes-CH$6))-1)^2+8*($BM20/(Total_Lanes-CH$6))/(Peak_Time_Eve*$N53*(Total_Lanes-CH$6)))),"-") -> - | CI20: =3600/N53 -> 6.85125 | CK20: 13 | CL20: =$Y20 -> 0.6435 | CM20: =$AD20 -> 7895.0424 | CN20: =CM20*CL20 -> 5080.4598 | CO20: =CN20/O52 -> 3.3869732 | CP20: =IF(CP$6<Total_Lanes,900*Peak_Time_Eve*(($CO20/CP$6-1)+SQRT(($CO20/CP$6-1)^2+8*($CO20/CP$6)/(Peak_Time_Eve*$O53*CP$6))),"-") -> 8596.5075 | CQ20: =IF(CQ$6<Total_Lanes,900*Peak_Time_Eve*(($CO20/CQ$6-1)+SQRT(($CO20/CQ$6-1)^2+8*($CO20/CQ$6)/(Peak_Time_Eve*$O53*CQ$6))),"-") -> 2499.4787 | CR20: =IF(CR$6<Total_Lanes,900*Peak_Time_Eve*(($CO20/CR$6-1)+SQRT(($CO20/CR$6-1)^2+8*($CO20/CR$6)/(Peak_Time_Eve*$O53*CR$6))),"-") -> 471.26728 | CS20: =IF(CS$6<Total_Lanes,900*Peak_Time_Eve*(($CO20/CS$6-1)+SQRT(($CO20/CS$6-1)^2+8*($CO20/CS$6)/(Peak_Time_Eve*$O53*CS$6))),"-") -> 3.2953178 | CT20: =IF(CT$6<Total_Lanes,900*Peak_Time_Eve*(($CO20/CT$6-1)+SQRT(($CO20/CT$6-1)^2+8*($CO20/CT$6)/(Peak_Time_Eve*$O53*CT$6))),"-") -> 1.0070128 | CU20: =IF(CU$6<Total_Lanes,900*Peak_Time_Eve*(($CO20/CU$6-1)+SQRT(($CO20/CU$6-1)^2+8*($CO20/CU$6)/(Peak_Time_Eve*$O53*CU$6))),"-") -> 0.51830373 | CV20: =IF(CV$6<Total_Lanes,900*Peak_Time_Eve*(($CO20/CV$6-1)+SQRT(($CO20/CV$6-1)^2+8*($CO20/CV$6)/(Peak_Time_Eve*$O53*CV$6))),"-") -> 0.32135027 | CW20: =IF(CW$6<Total_Lanes,900*Peak_Time_Eve*(($CO20/CW$6-1)+SQRT(($CO20/CW$6-1)^2+8*($CO20/CW$6)/(Peak_Time_Eve*$O53*CW$6))),"-") -> 0.22024241 | ... DJ20: =IF(DJ$6<Total_Lanes,900*Peak_Time_Eve*(($CO20/DJ$6-1)+SQRT(($CO20/DJ$6-1)^2+8*($CO20/DJ$6)/(Peak_Time_Eve*$O53*DJ$6))),"-") -> - | DK20: =3600/O53 -> 2.4
H21: 14 | I21: ='Input-Detail'!E28 -> 26704852 | J21: ='Input-Detail'!F28 -> 0.693 | K21: =AD21 -> 8060.8149 | L21: =IF(AD21>AD69,BC21,BC69) -> 5 | M21: =AE69 -> 13.3924 | N21: =AE21 -> 30.92671 | O21: =SUM(M21:N21) -> 44.31911 | P21: =$S$34*O21 -> 11522.968 | Q21: =SUMIF($AF$54:$AZ$54,L21,$AF69:$AZ69) -> 4.5840062 | R21: =SUMIF($AF$6:$AZ$6,$L21,$AF21:$AZ21) -> 16.586845 | S21: =SUM(Q21:R21) -> 21.170851 | T21: =$S$34*S21 -> 5504.4214 | W21: 14 | X21: =X$7+(X$27-X$7)*$W21/20 -> 26704852 | Y21: =J21 -> 0.693 | Z21: ='Input-Detail'!E28/AA21 -> 11515.45 | AA21: =AA20 -> 2319.0455 | AB21: =AB20 -> 2 | AC21: =AC20 -> 0.7 | AD21: =Z21*AC21 -> 8060.8149 | AE21: =Peak_Time_Eve*$BI21*(3600/K54+BL21)/3600 -> 30.92671 | AF21: =IF(AF$6<Total_Lanes,($BJ21*($CI21+BN21)+$CN21*CP21)*Peak_Time_Eve/3600,"-") -> 30454.668 | AG21: =IF(AG$6<Total_Lanes,($BJ21*($CI21+BO21)+$CN21*CQ21)*Peak_Time_Eve/3600,"-") -> 9649.384 | AH21: =IF(AH$6<Total_Lanes,($BJ21*($CI21+BP21)+$CN21*CR21)*Peak_Time_Eve/3600,"-") -> 2719.9219 | AI21: =IF(AI$6<Total_Lanes,($BJ21*($CI21+BQ21)+$CN21*CS21)*Peak_Time_Eve/3600,"-") -> 35.513609 | AJ21: =IF(AJ$6<Total_Lanes,($BJ21*($CI21+BR21)+$CN21*CT21)*Peak_Time_Eve/3600,"-") -> 16.586845 | AK21: =IF(AK$6<Total_Lanes,($BJ21*($CI21+BS21)+$CN21*CU21)*Peak_Time_Eve/3600,"-") -> 17.277992 | AL21: =IF(AL$6<Total_Lanes,($BJ21*($CI21+BT21)+$CN21*CV21)*Peak_Time_Eve/3600,"-") -> 39.896468 | AM21: =IF(AM$6<Total_Lanes,($BJ21*($CI21+BU21)+$CN21*CW21)*Peak_Time_Eve/3600,"-") -> 921.50703 | ... AZ21: =IF(AZ$6<Total_Lanes,($BJ21*($CI21+CH21)+$CN21*DJ21)*Peak_Time_Eve/3600,"-") -> - | BA21: =SUMIF(AF21:AZ21,BB21,$AF$6:$AZ$6) -> 5 | BB21: =MIN(AF21:AZ21) -> 16.586845 | BC21: =IF((SUMIF($BN19:$CH19,$BA21,$BN21:$CH21)+$CI21)<(SUMIF($CP19:$DJ19,$BA21,$CP21:$DJ21)+$DK21),BA21+1,BA21) -> 5 | BD21: =SUMIF($AF$6:$AZ$6,$BC21,$AF21:$AZ21) -> 16.586845 | BG21: 14 | BH21: =$Y21 -> 0.693 | BI21: =$AD21 -> 8060.8149 | BJ21: =BI21*(1-BH21) -> 2474.6702 | BK21: =Peak_Arrival_Manual/K54 -> 4.5197101 | BL21: =900*Peak_Time_Eve*(BK21/Total_Lanes-1+SQRT((BK21/Total_Lanes-1)^2+8*(BK21/Total_Lanes)/(Peak_Time_Eve*$K54*Total_Lanes))) -> 0.33101114 | BM21: =Peak_Arrival_Manual/N54 -> 4.7242141 | BN21: =IF(BN$6<Total_Lanes,900*Peak_Time_Eve*(($BM21/(Total_Lanes-BN$6))-1+SQRT((($BM21/(Total_Lanes-BN$6))-1)^2+8*($BM21/(Total_Lanes-BN$6))/(Peak_Time_Eve*$N54*(Total_Lanes-BN$6)))),"-") -> 0.4702016 | BO21: =IF(BO$6<Total_Lanes,900*Peak_Time_Eve*(($BM21/(Total_Lanes-BO$6))-1+SQRT((($BM21/(Total_Lanes-BO$6))-1)^2+8*($BM21/(Total_Lanes-BO$6))/(Peak_Time_Eve*$N54*(Total_Lanes-BO$6)))),"-") -> 0.61520025 | BP21: =IF(BP$6<Total_Lanes,900*Peak_Time_Eve*(($BM21/(Total_Lanes-BP$6))-1+SQRT((($BM21/(Total_Lanes-BP$6))-1)^2+8*($BM21/(Total_Lanes-BP$6))/(Peak_Time_Eve*$N54*(Total_Lanes-BP$6)))),"-") -> 0.84327996 | BQ21: =IF(BQ$6<Total_Lanes,900*Peak_Time_Eve*(($BM21/(Total_Lanes-BQ$6))-1+SQRT((($BM21/(Total_Lanes-BQ$6))-1)^2+8*($BM21/(Total_Lanes-BQ$6))/(Peak_Time_Eve*$N54*(Total_Lanes-BQ$6)))),"-") -> 1.2378678 | BR21: =IF(BR$6<Total_Lanes,900*Peak_Time_Eve*(($BM21/(Total_Lanes-BR$6))-1+SQRT((($BM21/(Total_Lanes-BR$6))-1)^2+8*($BM21/(Total_Lanes-BR$6))/(Peak_Time_Eve*$N54*(Total_Lanes-BR$6)))),"-") -> 2.0345136 | BS21: =IF(BS$6<Total_Lanes,900*Peak_Time_Eve*(($BM21/(Total_Lanes-BS$6))-1+SQRT((($BM21/(Total_Lanes-BS$6))-1)^2+8*($BM21/(Total_Lanes-BS$6))/(Peak_Time_Eve*$N54*(Total_Lanes-BS$6)))),"-") -> 4.218214 | BT21: =IF(BT$6<Total_Lanes,900*Peak_Time_Eve*(($BM21/(Total_Lanes-BT$6))-1+SQRT((($BM21/(Total_Lanes-BT$6))-1)^2+8*($BM21/(Total_Lanes-BT$6))/(Peak_Time_Eve*$N54*(Total_Lanes-BT$6)))),"-") -> 21.267356 | BU21: =IF(BU$6<Total_Lanes,900*Peak_Time_Eve*(($BM21/(Total_Lanes-BU$6))-1+SQRT((($BM21/(Total_Lanes-BU$6))-1)^2+8*($BM21/(Total_Lanes-BU$6))/(Peak_Time_Eve*$N54*(Total_Lanes-BU$6)))),"-") -> 662.81403 | ... CH21: =IF(CH$6<Total_Lanes,900*Peak_Time_Eve*(($BM21/(Total_Lanes-CH$6))-1+SQRT((($BM21/(Total_Lanes-CH$6))-1)^2+8*($BM21/(Total_Lanes-CH$6))/(Peak_Time_Eve*$N54*(Total_Lanes-CH$6)))),"-") -> - | CI21: =3600/N54 -> 6.8725 | CK21: 14 | CL21: =$Y21 -> 0.693 | CM21: =$AD21 -> 8060.8149 | CN21: =CM21*CL21 -> 5586.1447 | CO21: =CN21/O53 -> 3.7240965 | CP21: =IF(CP$6<Total_Lanes,900*Peak_Time_Eve*(($CO21/CP$6-1)+SQRT(($CO21/CP$6-1)^2+8*($CO21/CP$6)/(Peak_Time_Eve*$O54*CP$6))),"-") -> 9810.0272 | CQ21: =IF(CQ$6<Total_Lanes,900*Peak_Time_Eve*(($CO21/CQ$6-1)+SQRT(($CO21/CQ$6-1)^2+8*($CO21/CQ$6)/(Peak_Time_Eve*$O54*CQ$6))),"-") -> 3105.9635 | CR21: =IF(CR$6<Total_Lanes,900*Peak_Time_Eve*(($CO21/CR$6-1)+SQRT(($CO21/CR$6-1)^2+8*($CO21/CR$6)/(Peak_Time_Eve*$O54*CR$6))),"-") -> 873.01093 | CS21: =IF(CS$6<Total_Lanes,900*Peak_Time_Eve*(($CO21/CS$6-1)+SQRT(($CO21/CS$6-1)^2+8*($CO21/CS$6)/(Peak_Time_Eve*$O54*CS$6))),"-") -> 7.8504966 | CT21: =IF(CT$6<Total_Lanes,900*Peak_Time_Eve*(($CO21/CT$6-1)+SQRT(($CO21/CT$6-1)^2+8*($CO21/CT$6)/(Peak_Time_Eve*$O54*CT$6))),"-") -> 1.3988898 | CU21: =IF(CU$6<Total_Lanes,900*Peak_Time_Eve*(($CO21/CU$6-1)+SQRT(($CO21/CU$6-1)^2+8*($CO21/CU$6)/(Peak_Time_Eve*$O54*CU$6))),"-") -> 0.65421282 | CV21: =IF(CV$6<Total_Lanes,900*Peak_Time_Eve*(($CO21/CV$6-1)+SQRT(($CO21/CV$6-1)^2+8*($CO21/CV$6)/(Peak_Time_Eve*$O54*CV$6))),"-") -> 0.38967503 | CW21: =IF(CW$6<Total_Lanes,900*Peak_Time_Eve*(($CO21/CW$6-1)+SQRT(($CO21/CW$6-1)^2+8*($CO21/CW$6)/(Peak_Time_Eve*$O54*CW$6))),"-") -> 0.26124941 | ... DJ21: =IF(DJ$6<Total_Lanes,900*Peak_Time_Eve*(($CO21/DJ$6-1)+SQRT(($CO21/DJ$6-1)^2+8*($CO21/DJ$6)/(Peak_Time_Eve*$O54*DJ$6))),"-") -> - | DK21: =3600/O54 -> 2.4
H22: 15 | I22: ='Input-Detail'!E29 -> 27254043 | J22: ='Input-Detail'!F29 -> 0.7425 | K22: =AD22 -> 8226.5874 | L22: =IF(AD22>AD70,BC22,BC70) -> 6 | M22: =AE70 -> 13.674928 | N22: =AE22 -> 31.241295 | O22: =SUM(M22:N22) -> 44.916224 | P22: =$S$34*O22 -> 11678.218 | Q22: =SUMIF($AF$54:$AZ$54,L22,$AF70:$AZ70) -> 3.9519518 | R22: =SUMIF($AF$6:$AZ$6,$L22,$AF22:$AZ22) -> 13.79452 | S22: =SUM(Q22:R22) -> 17.746472 | T22: =$S$34*S22 -> 4614.0826 | W22: 15 | X22: =X$7+(X$27-X$7)*$W22/20 -> 27254043 | Y22: =J22 -> 0.7425 | Z22: ='Input-Detail'!E29/AA22 -> 11752.268 | AA22: =AA21 -> 2319.0455 | AB22: =AB21 -> 2 | AC22: =AC21 -> 0.7 | AD22: =Z22*AC22 -> 8226.5874 | AE22: =Peak_Time_Eve*$BI22*(3600/K55+BL22)/3600 -> 31.241295 | AF22: =IF(AF$6<Total_Lanes,($BJ22*($CI22+BN22)+$CN22*CP22)*Peak_Time_Eve/3600,"-") -> 37550.333 | AG22: =IF(AG$6<Total_Lanes,($BJ22*($CI22+BO22)+$CN22*CQ22)*Peak_Time_Eve/3600,"-") -> 12673.921 | AH22: =IF(AH$6<Total_Lanes,($BJ22*($CI22+BP22)+$CN22*CR22)*Peak_Time_Eve/3600,"-") -> 4385.15 | AI22: =IF(AI$6<Total_Lanes,($BJ22*($CI22+BQ22)+$CN22*CS22)*Peak_Time_Eve/3600,"-") -> 312.90856 | AJ22: =IF(AJ$6<Total_Lanes,($BJ22*($CI22+BR22)+$CN22*CT22)*Peak_Time_Eve/3600,"-") -> 16.835228 | AK22: =IF(AK$6<Total_Lanes,($BJ22*($CI22+BS22)+$CN22*CU22)*Peak_Time_Eve/3600,"-") -> 13.79452 | AL22: =IF(AL$6<Total_Lanes,($BJ22*($CI22+BT22)+$CN22*CV22)*Peak_Time_Eve/3600,"-") -> 16.646918 | AM22: =IF(AM$6<Total_Lanes,($BJ22*($CI22+BU22)+$CN22*CW22)*Peak_Time_Eve/3600,"-") -> 137.1092 | ... AZ22: =IF(AZ$6<Total_Lanes,($BJ22*($CI22+CH22)+$CN22*DJ22)*Peak_Time_Eve/3600,"-") -> - | BA22: =SUMIF(AF22:AZ22,BB22,$AF$6:$AZ$6) -> 6 | BB22: =MIN(AF22:AZ22) -> 13.79452 | BC22: =IF((SUMIF($BN20:$CH20,$BA22,$BN22:$CH22)+$CI22)<(SUMIF($CP20:$DJ20,$BA22,$CP22:$DJ22)+$DK22),BA22+1,BA22) -> 6 | BD22: =SUMIF($AF$6:$AZ$6,$BC22,$AF22:$AZ22) -> 13.79452 | BG22: 15 | BH22: =$Y22 -> 0.7425 | BI22: =$AD22 -> 8226.5874 | BJ22: =BI22*(1-BH22) -> 2118.3462 | BK22: =Peak_Arrival_Manual/K55 -> 3.868924 | BL22: =900*Peak_Time_Eve*(BK22/Total_Lanes-1+SQRT((BK22/Total_Lanes-1)^2+8*(BK22/Total_Lanes)/(Peak_Time_Eve*$K55*Total_Lanes))) -> 0.26068155 | BM22: =Peak_Arrival_Manual/N55 -> 4.0564859 | BN22: =IF(BN$6<Total_Lanes,900*Peak_Time_Eve*(($BM22/(Total_Lanes-BN$6))-1+SQRT((($BM22/(Total_Lanes-BN$6))-1)^2+8*($BM22/(Total_Lanes-BN$6))/(Peak_Time_Eve*$N55*(Total_Lanes-BN$6)))),"-") -> 0.3660695 | BO22: =IF(BO$6<Total_Lanes,900*Peak_Time_Eve*(($BM22/(Total_Lanes-BO$6))-1+SQRT((($BM22/(Total_Lanes-BO$6))-1)^2+8*($BM22/(Total_Lanes-BO$6))/(Peak_Time_Eve*$N55*(Total_Lanes-BO$6)))),"-") -> 0.47039938 | BP22: =IF(BP$6<Total_Lanes,900*Peak_Time_Eve*(($BM22/(Total_Lanes-BP$6))-1+SQRT((($BM22/(Total_Lanes-BP$6))-1)^2+8*($BM22/(Total_Lanes-BP$6))/(Peak_Time_Eve*$N55*(Total_Lanes-BP$6)))),"-") -> 0.6283321 | BQ22: =IF(BQ$6<Total_Lanes,900*Peak_Time_Eve*(($BM22/(Total_Lanes-BQ$6))-1+SQRT((($BM22/(Total_Lanes-BQ$6))-1)^2+8*($BM22/(Total_Lanes-BQ$6))/(Peak_Time_Eve*$N55*(Total_Lanes-BQ$6)))),"-") -> 0.88596254 | BR22: =IF(BR$6<Total_Lanes,900*Peak_Time_Eve*(($BM22/(Total_Lanes-BR$6))-1+SQRT((($BM22/(Total_Lanes-BR$6))-1)^2+8*($BM22/(Total_Lanes-BR$6))/(Peak_Time_Eve*$N55*(Total_Lanes-BR$6)))),"-") -> 1.3559776 | BS22: =IF(BS$6<Total_Lanes,900*Peak_Time_Eve*(($BM22/(Total_Lanes-BS$6))-1+SQRT((($BM22/(Total_Lanes-BS$6))-1)^2+8*($BM22/(Total_Lanes-BS$6))/(Peak_Time_Eve*$N55*(Total_Lanes-BS$6)))),"-") -> 2.3931845 | BT22: =IF(BT$6<Total_Lanes,900*Peak_Time_Eve*(($BM22/(Total_Lanes-BT$6))-1+SQRT((($BM22/(Total_Lanes-BT$6))-1)^2+8*($BM22/(Total_Lanes-BT$6))/(Peak_Time_Eve*$N55*(Total_Lanes-BT$6)))),"-") -> 5.8768718 | BU22: =IF(BU$6<Total_Lanes,900*Peak_Time_Eve*(($BM22/(Total_Lanes-BU$6))-1+SQRT((($BM22/(Total_Lanes-BU$6))-1)^2+8*($BM22/(Total_Lanes-BU$6))/(Peak_Time_Eve*$N55*(Total_Lanes-BU$6)))),"-") -> 108.71393 | ... CH22: =IF(CH$6<Total_Lanes,900*Peak_Time_Eve*(($BM22/(Total_Lanes-CH$6))-1+SQRT((($BM22/(Total_Lanes-CH$6))-1)^2+8*($BM22/(Total_Lanes-CH$6))/(Peak_Time_Eve*$N55*(Total_Lanes-CH$6)))),"-") -> - | CI22: =3600/N55 -> 6.89375 | CK22: 15 | CL22: =$Y22 -> 0.7425 | CM22: =$AD22 -> 8226.5874 | CN22: =CM22*CL22 -> 6108.2411 | CO22: =CN22/O54 -> 4.0721607 | CP22: =IF(CP$6<Total_Lanes,900*Peak_Time_Eve*(($CO22/CP$6-1)+SQRT(($CO22/CP$6-1)^2+8*($CO22/CP$6)/(Peak_Time_Eve*$O55*CP$6))),"-") -> 11062.959 | CQ22: =IF(CQ$6<Total_Lanes,900*Peak_Time_Eve*(($CO22/CQ$6-1)+SQRT(($CO22/CQ$6-1)^2+8*($CO22/CQ$6)/(Peak_Time_Eve*$O55*CQ$6))),"-") -> 3732.2461 | CR22: =IF(CR$6<Total_Lanes,900*Peak_Time_Eve*(($CO22/CR$6-1)+SQRT(($CO22/CR$6-1)^2+8*($CO22/CR$6)/(Peak_Time_Eve*$O55*CR$6))),"-") -> 1289.6242 | CS22: =IF(CS$6<Total_Lanes,900*Peak_Time_Eve*(($CO22/CS$6-1)+SQRT(($CO22/CS$6-1)^2+8*($CO22/CS$6)/(Peak_Time_Eve*$O55*CS$6))),"-") -> 89.511084 | CT22: =IF(CT$6<Total_Lanes,900*Peak_Time_Eve*(($CO22/CT$6-1)+SQRT(($CO22/CT$6-1)^2+8*($CO22/CT$6)/(Peak_Time_Eve*$O55*CT$6))),"-") -> 2.1000532 | CU22: =IF(CU$6<Total_Lanes,900*Peak_Time_Eve*(($CO22/CU$6-1)+SQRT(($CO22/CU$6-1)^2+8*($CO22/CU$6)/(Peak_Time_Eve*$O55*CU$6))),"-") -> 0.8443008 | CV22: =IF(CV$6<Total_Lanes,900*Peak_Time_Eve*(($CO22/CV$6-1)+SQRT(($CO22/CV$6-1)^2+8*($CO22/CV$6)/(Peak_Time_Eve*$O55*CV$6))),"-") -> 0.47670907 | CW22: =IF(CW$6<Total_Lanes,900*Peak_Time_Eve*(($CO22/CW$6-1)+SQRT(($CO22/CW$6-1)^2+8*($CO22/CW$6)/(Peak_Time_Eve*$O55*CW$6))),"-") -> 0.31096826 | ... DJ22: =IF(DJ$6<Total_Lanes,900*Peak_Time_Eve*(($CO22/DJ$6-1)+SQRT(($CO22/DJ$6-1)^2+8*($CO22/DJ$6)/(Peak_Time_Eve*$O55*DJ$6))),"-") -> - | DK22: =3600/O55 -> 2.4
... H26: 19 | I26: ='Input-Detail'!E33 -> 29450809 | J26: ='Input-Detail'!F33 -> 0.9405 | K26: =AD26 -> 8889.6773 | L26: =IF(AD26>AD74,BC26,BC74) -> 9 | M26: =AE74 -> 14.812593 | N26: =AE26 -> 32.708927 | O26: =SUM(M26:N26) -> 47.52152 | P26: =$S$34*O26 -> 12355.595 | Q26: =SUMIF($AF$54:$AZ$54,L26,$AF74:$AZ74) -> 1.1209527 | R26: =SUMIF($AF$6:$AZ$6,$L26,$AF26:$AZ26) -> 4.4199165 | S26: =SUM(Q26:R26) -> 5.5408692 | T26: =$S$34*S26 -> 1440.626 | W26: 19 | X26: =X$7+(X$27-X$7)*$W26/20 -> 29450809 | Y26: =J26 -> 0.9405 | Z26: ='Input-Detail'!E33/AA26 -> 12699.539 | AA26: =AA25 -> 2319.0455 | AB26: =AB25 -> 2 | AC26: =AC25 -> 0.7 | AD26: =Z26*AC26 -> 8889.6773 | AE26: =Peak_Time_Eve*$BI26*(3600/K59+BL26)/3600 -> 32.708927 | AF26: =IF(AF$6<Total_Lanes,($BJ26*($CI26+BN26)+$CN26*CP26)*Peak_Time_Eve/3600,"-") -> 76496.834 | AG26: =IF(AG$6<Total_Lanes,($BJ26*($CI26+BO26)+$CN26*CQ26)*Peak_Time_Eve/3600,"-") -> 29890.614 | AH26: =IF(AH$6<Total_Lanes,($BJ26*($CI26+BP26)+$CN26*CR26)*Peak_Time_Eve/3600,"-") -> 14356.194 | AI26: =IF(AI$6<Total_Lanes,($BJ26*($CI26+BQ26)+$CN26*CS26)*Peak_Time_Eve/3600,"-") -> 6591.1269 | AJ26: =IF(AJ$6<Total_Lanes,($BJ26*($CI26+BR26)+$CN26*CT26)*Peak_Time_Eve/3600,"-") -> 1942.5683 | AK26: =IF(AK$6<Total_Lanes,($BJ26*($CI26+BS26)+$CN26*CU26)*Peak_Time_Eve/3600,"-") -> 25.943055 | AL26: =IF(AL$6<Total_Lanes,($BJ26*($CI26+BT26)+$CN26*CV26)*Peak_Time_Eve/3600,"-") -> 8.369157 | AM26: =IF(AM$6<Total_Lanes,($BJ26*($CI26+BU26)+$CN26*CW26)*Peak_Time_Eve/3600,"-") -> 5.426686 | ... AZ26: =IF(AZ$6<Total_Lanes,($BJ26*($CI26+CH26)+$CN26*DJ26)*Peak_Time_Eve/3600,"-") -> - | BA26: =SUMIF(AF26:AZ26,BB26,$AF$6:$AZ$6) -> 9 | BB26: =MIN(AF26:AZ26) -> 4.4199165 | BC26: =IF((SUMIF($BN24:$CH24,$BA26,$BN26:$CH26)+$CI26)<(SUMIF($CP24:$DJ24,$BA26,$CP26:$DJ26)+$DK26),BA26+1,BA26) -> 9 | BD26: =SUMIF($AF$6:$AZ$6,$BC26,$AF26:$AZ26) -> 4.4199165 | BG26: 19 | BH26: =$Y26 -> 0.9405 | BI26: =$AD26 -> 8889.6773 | BJ26: =BI26*(1-BH26) -> 528.9358 | BK26: =Peak_Arrival_Manual/K59 -> 0.96604247 | BL26: =900*Peak_Time_Eve*(BK26/Total_Lanes-1+SQRT((BK26/Total_Lanes-1)^2+8*(BK26/Total_Lanes)/(Peak_Time_Eve*$K59*Total_Lanes))) -> 0.047970377 | BM26: =Peak_Arrival_Manual/N59 -> 1.0253641 | BN26: =IF(BN$6<Total_Lanes,900*Peak_Time_Eve*(($BM26/(Total_Lanes-BN$6))-1+SQRT((($BM26/(Total_Lanes-BN$6))-1)^2+8*($BM26/(Total_Lanes-BN$6))/(Peak_Time_Eve*$N59*(Total_Lanes-BN$6)))),"-") -> 0.065216476 | BO26: =IF(BO$6<Total_Lanes,900*Peak_Time_Eve*(($BM26/(Total_Lanes-BO$6))-1+SQRT((($BM26/(Total_Lanes-BO$6))-1)^2+8*($BM26/(Total_Lanes-BO$6))/(Peak_Time_Eve*$N59*(Total_Lanes-BO$6)))),"-") -> 0.079731179 | BP26: =IF(BP$6<Total_Lanes,900*Peak_Time_Eve*(($BM26/(Total_Lanes-BP$6))-1+SQRT((($BM26/(Total_Lanes-BP$6))-1)^2+8*($BM26/(Total_Lanes-BP$6))/(Peak_Time_Eve*$N59*(Total_Lanes-BP$6)))),"-") -> 0.099698539 | BQ26: =IF(BQ$6<Total_Lanes,900*Peak_Time_Eve*(($BM26/(Total_Lanes-BQ$6))-1+SQRT((($BM26/(Total_Lanes-BQ$6))-1)^2+8*($BM26/(Total_Lanes-BQ$6))/(Peak_Time_Eve*$N59*(Total_Lanes-BQ$6)))),"-") -> 0.12824087 | BR26: =IF(BR$6<Total_Lanes,900*Peak_Time_Eve*(($BM26/(Total_Lanes-BR$6))-1+SQRT((($BM26/(Total_Lanes-BR$6))-1)^2+8*($BM26/(Total_Lanes-BR$6))/(Peak_Time_Eve*$N59*(Total_Lanes-BR$6)))),"-") -> 0.171089 | BS26: =IF(BS$6<Total_Lanes,900*Peak_Time_Eve*(($BM26/(Total_Lanes-BS$6))-1+SQRT((($BM26/(Total_Lanes-BS$6))-1)^2+8*($BM26/(Total_Lanes-BS$6))/(Peak_Time_Eve*$N59*(Total_Lanes-BS$6)))),"-") -> 0.23972223 | BT26: =IF(BT$6<Total_Lanes,900*Peak_Time_Eve*(($BM26/(Total_Lanes-BT$6))-1+SQRT((($BM26/(Total_Lanes-BT$6))-1)^2+8*($BM26/(Total_Lanes-BT$6))/(Peak_Time_Eve*$N59*(Total_Lanes-BT$6)))),"-") -> 0.36002591 | BU26: =IF(BU$6<Total_Lanes,900*Peak_Time_Eve*(($BM26/(Total_Lanes-BU$6))-1+SQRT((($BM26/(Total_Lanes-BU$6))-1)^2+8*($BM26/(Total_Lanes-BU$6))/(Peak_Time_Eve*$N59*(Total_Lanes-BU$6)))),"-") -> 0.6012629 | ... CH26: =IF(CH$6<Total_Lanes,900*Peak_Time_Eve*(($BM26/(Total_Lanes-CH$6))-1+SQRT((($BM26/(Total_Lanes-CH$6))-1)^2+8*($BM26/(Total_Lanes-CH$6))/(Peak_Time_Eve*$N59*(Total_Lanes-CH$6)))),"-") -> - | CI26: =3600/N59 -> 6.97875 | CK26: 19 | CL26: =$Y26 -> 0.9405 | CM26: =$AD26 -> 8889.6773 | CN26: =CM26*CL26 -> 8360.7415 | CO26: =CN26/O58 -> 5.5738277 | CP26: =IF(CP$6<Total_Lanes,900*Peak_Time_Eve*(($CO26/CP$6-1)+SQRT(($CO26/CP$6-1)^2+8*($CO26/CP$6)/(Peak_Time_Eve*$O59*CP$6))),"-") -> 16468.704 | CQ26: =IF(CQ$6<Total_Lanes,900*Peak_Time_Eve*(($CO26/CQ$6-1)+SQRT(($CO26/CQ$6-1)^2+8*($CO26/CQ$6)/(Peak_Time_Eve*$O59*CQ$6))),"-") -> 6434.7608 | CR26: =IF(CR$6<Total_Lanes,900*Peak_Time_Eve*(($CO26/CR$6-1)+SQRT(($CO26/CR$6-1)^2+8*($CO26/CR$6)/(Peak_Time_Eve*$O59*CR$6))),"-") -> 3090.3247 | CS26: =IF(CS$6<Total_Lanes,900*Peak_Time_Eve*(($CO26/CS$6-1)+SQRT(($CO26/CS$6-1)^2+8*($CO26/CS$6)/(Peak_Time_Eve*$O59*CS$6))),"-") -> 1418.5667 | CT26: =IF(CT$6<Total_Lanes,900*Peak_Time_Eve*(($CO26/CT$6-1)+SQRT(($CO26/CT$6-1)^2+8*($CO26/CT$6)/(Peak_Time_Eve*$O59*CT$6))),"-") -> 417.76691 | CU26: =IF(CU$6<Total_Lanes,900*Peak_Time_Eve*(($CO26/CU$6-1)+SQRT(($CO26/CU$6-1)^2+8*($CO26/CU$6)/(Peak_Time_Eve*$O59*CU$6))),"-") -> 5.1286589 | CV26: =IF(CV$6<Total_Lanes,900*Peak_Time_Eve*(($CO26/CV$6-1)+SQRT(($CO26/CV$6-1)^2+8*($CO26/CV$6)/(Peak_Time_Eve*$O59*CV$6))),"-") -> 1.3375298 | CW26: =IF(CW$6<Total_Lanes,900*Peak_Time_Eve*(($CO26/CW$6-1)+SQRT(($CO26/CW$6-1)^2+8*($CO26/CW$6)/(Peak_Time_Eve*$O59*CW$6))),"-") -> 0.68877797 | ... DJ26: =IF(DJ$6<Total_Lanes,900*Peak_Time_Eve*(($CO26/DJ$6-1)+SQRT(($CO26/DJ$6-1)^2+8*($CO26/DJ$6)/(Peak_Time_Eve*$O59*DJ$6))),"-") -> - | DK26: =3600/O59 -> 2.4
H27: 20 | I27: ='Input-Detail'!E34 -> 30000000 | J27: ='Input-Detail'!F34 -> 0.99 | K27: =AD27 -> 9055.4498 | L27: =IF(AD27>AD75,BC27,BC75) -> 11 | M27: =AE75 -> 15.099436 | N27: =AE27 -> 33.116067 | O27: =SUM(M27:N27) -> 48.215503 | P27: =$S$34*O27 -> 12536.031 | Q27: =SUMIF($AF$54:$AZ$54,L27,$AF75:$AZ75) -> 0.30459556 | R27: =SUMIF($AF$6:$AZ$6,$L27,$AF27:$AZ27) -> 1.72002 | S27: =SUM(Q27:R27) -> 2.0246156 | T27: =$S$34*S27 -> 526.40006 | W27: 20 | X27: ='Input-Detail'!E34 -> 30000000 | Y27: =J27 -> 0.99 | Z27: ='Input-Detail'!E34/AA27 -> 12936.357 | AA27: =AA26 -> 2319.0455 | AB27: =AB26 -> 2 | AC27: =AC26 -> 0.7 | AD27: =Z27*AC27 -> 9055.4498 | AE27: =Peak_Time_Eve*$BI27*(3600/K60+BL27)/3600 -> 33.116067 | AF27: =IF(AF$6<Total_Lanes,($BJ27*($CI27+BN27)+$CN27*CP27)*Peak_Time_Eve/3600,"-") -> 89244.045 | AG27: =IF(AG$6<Total_Lanes,($BJ27*($CI27+BO27)+$CN27*CQ27)*Peak_Time_Eve/3600,"-") -> 35659.108 | AH27: =IF(AH$6<Total_Lanes,($BJ27*($CI27+BP27)+$CN27*CR27)*Peak_Time_Eve/3600,"-") -> 17798.269 | AI27: =IF(AI$6<Total_Lanes,($BJ27*($CI27+BQ27)+$CN27*CS27)*Peak_Time_Eve/3600,"-") -> 8869.3716 | AJ27: =IF(AJ$6<Total_Lanes,($BJ27*($CI27+BR27)+$CN27*CT27)*Peak_Time_Eve/3600,"-") -> 3516.9586 | AK27: =IF(AK$6<Total_Lanes,($BJ27*($CI27+BS27)+$CN27*CU27)*Peak_Time_Eve/3600,"-") -> 157.22758 | AL27: =IF(AL$6<Total_Lanes,($BJ27*($CI27+BT27)+$CN27*CV27)*Peak_Time_Eve/3600,"-") -> 10.289326 | AM27: =IF(AM$6<Total_Lanes,($BJ27*($CI27+BU27)+$CN27*CW27)*Peak_Time_Eve/3600,"-") -> 4.7652445 | ... AZ27: =IF(AZ$6<Total_Lanes,($BJ27*($CI27+CH27)+$CN27*DJ27)*Peak_Time_Eve/3600,"-") -> - | BA27: =SUMIF(AF27:AZ27,BB27,$AF$6:$AZ$6) -> 11 | BB27: =MIN(AF27:AZ27) -> 1.72002 | BC27: =IF((SUMIF($BN25:$CH25,$BA27,$BN27:$CH27)+$CI27)<(SUMIF($CP25:$DJ25,$BA27,$CP27:$DJ27)+$DK27),BA27+1,BA27) -> 11 | BD27: =SUMIF($AF$6:$AZ$6,$BC27,$AF27:$AZ27) -> 1.72002 | BG27: 20 | BH27: =$Y27 -> 0.99 | BI27: =$AD27 -> 9055.4498 | BJ27: =BI27*(1-BH27) -> 90.554498 | BK27: =Peak_Arrival_Manual/K60 -> 0.16538773 | BL27: =900*Peak_Time_Eve*(BK27/Total_Lanes-1+SQRT((BK27/Total_Lanes-1)^2+8*(BK27/Total_Lanes)/(Peak_Time_Eve*$K60*Total_Lanes))) -> 0.0076570736 | BM27: =Peak_Arrival_Manual/N60 -> 0.17607819 | BN27: =IF(BN$6<Total_Lanes,900*Peak_Time_Eve*(($BM27/(Total_Lanes-BN$6))-1+SQRT((($BM27/(Total_Lanes-BN$6))-1)^2+8*($BM27/(Total_Lanes-BN$6))/(Peak_Time_Eve*$N60*(Total_Lanes-BN$6)))),"-") -> 0.010352018 | BO27: =IF(BO$6<Total_Lanes,900*Peak_Time_Eve*(($BM27/(Total_Lanes-BO$6))-1+SQRT((($BM27/(Total_Lanes-BO$6))-1)^2+8*($BM27/(Total_Lanes-BO$6))/(Peak_Time_Eve*$N60*(Total_Lanes-BO$6)))),"-") -> 0.012546343 | BP27: =IF(BP$6<Total_Lanes,900*Peak_Time_Eve*(($BM27/(Total_Lanes-BP$6))-1+SQRT((($BM27/(Total_Lanes-BP$6))-1)^2+8*($BM27/(Total_Lanes-BP$6))/(Peak_Time_Eve*$N60*(Total_Lanes-BP$6)))),"-") -> 0.015520208 | BQ27: =IF(BQ$6<Total_Lanes,900*Peak_Time_Eve*(($BM27/(Total_Lanes-BQ$6))-1+SQRT((($BM27/(Total_Lanes-BQ$6))-1)^2+8*($BM27/(Total_Lanes-BQ$6))/(Peak_Time_Eve*$N60*(Total_Lanes-BQ$6)))),"-") -> 0.019691858 | BR27: =IF(BR$6<Total_Lanes,900*Peak_Time_Eve*(($BM27/(Total_Lanes-BR$6))-1+SQRT((($BM27/(Total_Lanes-BR$6))-1)^2+8*($BM27/(Total_Lanes-BR$6))/(Peak_Time_Eve*$N60*(Total_Lanes-BR$6)))),"-") -> 0.025802889 | BS27: =IF(BS$6<Total_Lanes,900*Peak_Time_Eve*(($BM27/(Total_Lanes-BS$6))-1+SQRT((($BM27/(Total_Lanes-BS$6))-1)^2+8*($BM27/(Total_Lanes-BS$6))/(Peak_Time_Eve*$N60*(Total_Lanes-BS$6)))),"-") -> 0.035272191 | BT27: =IF(BT$6<Total_Lanes,900*Peak_Time_Eve*(($BM27/(Total_Lanes-BT$6))-1+SQRT((($BM27/(Total_Lanes-BT$6))-1)^2+8*($BM27/(Total_Lanes-BT$6))/(Peak_Time_Eve*$N60*(Total_Lanes-BT$6)))),"-") -> 0.051100712 | BU27: =IF(BU$6<Total_Lanes,900*Peak_Time_Eve*(($BM27/(Total_Lanes-BU$6))-1+SQRT((($BM27/(Total_Lanes-BU$6))-1)^2+8*($BM27/(Total_Lanes-BU$6))/(Peak_Time_Eve*$N60*(Total_Lanes-BU$6)))),"-") -> 0.080579477 | ... CH27: =IF(CH$6<Total_Lanes,900*Peak_Time_Eve*(($BM27/(Total_Lanes-CH$6))-1+SQRT((($BM27/(Total_Lanes-CH$6))-1)^2+8*($BM27/(Total_Lanes-CH$6))/(Peak_Time_Eve*$N60*(Total_Lanes-CH$6)))),"-") -> - | CI27: =3600/N60 -> 7 | CK27: 20 | CL27: =$Y27 -> 0.99 | CM27: =$AD27 -> 9055.4498 | CN27: =CM27*CL27 -> 8964.8953 | CO27: =CN27/O59 -> 5.9765969 | CP27: =IF(CP$6<Total_Lanes,900*Peak_Time_Eve*(($CO27/CP$6-1)+SQRT(($CO27/CP$6-1)^2+8*($CO27/CP$6)/(Peak_Time_Eve*$O60*CP$6))),"-") -> 17918.631 | CQ27: =IF(CQ$6<Total_Lanes,900*Peak_Time_Eve*(($CO27/CQ$6-1)+SQRT(($CO27/CQ$6-1)^2+8*($CO27/CQ$6)/(Peak_Time_Eve*$O60*CQ$6))),"-") -> 7159.6774 | CR27: =IF(CR$6<Total_Lanes,900*Peak_Time_Eve*(($CO27/CR$6-1)+SQRT(($CO27/CR$6-1)^2+8*($CO27/CR$6)/(Peak_Time_Eve*$O60*CR$6))),"-") -> 3573.5218 | CS27: =IF(CS$6<Total_Lanes,900*Peak_Time_Eve*(($CO27/CS$6-1)+SQRT(($CO27/CS$6-1)^2+8*($CO27/CS$6)/(Peak_Time_Eve*$O60*CS$6))),"-") -> 1780.7495 | CT27: =IF(CT$6<Total_Lanes,900*Peak_Time_Eve*(($CO27/CT$6-1)+SQRT(($CO27/CT$6-1)^2+8*($CO27/CT$6)/(Peak_Time_Eve*$O60*CT$6))),"-") -> 706.07509 | CU27: =IF(CU$6<Total_Lanes,900*Peak_Time_Eve*(($CO27/CU$6-1)+SQRT(($CO27/CU$6-1)^2+8*($CO27/CU$6)/(Peak_Time_Eve*$O60*CU$6))),"-") -> 31.497586 | CV27: =IF(CV$6<Total_Lanes,900*Peak_Time_Eve*(($CO27/CV$6-1)+SQRT(($CO27/CV$6-1)^2+8*($CO27/CV$6)/(Peak_Time_Eve*$O60*CV$6))),"-") -> 1.9947001 | CW27: =IF(CW$6<Total_Lanes,900*Peak_Time_Eve*(($CO27/CW$6-1)+SQRT(($CO27/CW$6-1)^2+8*($CO27/CW$6)/(Peak_Time_Eve*$O60*CW$6))),"-") -> 0.88525984 | ... DJ27: =IF(DJ$6<Total_Lanes,900*Peak_Time_Eve*(($CO27/DJ$6-1)+SQRT(($CO27/DJ$6-1)^2+8*($CO27/DJ$6)/(Peak_Time_Eve*$O60*DJ$6))),"-") -> - | DK27: =3600/O60 -> 2.4
H30: Footnote: | W30: Footnote:
H31: *Suppose peak hours happen in weekdays. Therefore, 5 weekdays per week. | W31: *Criterion of Choosing Optimal Number of ETC Lanes--Minimize Total Delay in the System During the Peak Hour
H32: Or you can change the number of days (in white cell) | W32: Average Delay Formula: ADi = (3600/mi) + 900* (T)*{(r-1)+[(r-1)2+8*k*I*r/(T*mimi)]0.5}
H33: # of weeks per year | S33: 52 | W33: where
H34: # of weekdays per year | S34: =5*S33 -> 260 | W34: 1/m : mean transaction time (hr)
W35: i : 1 for manual lane and 2 for ETC lane.
W36: T : duration of peak period (hr) per day,
H37: y Estimated Mean Service Rate (vhe/hrs) given payment split | W37: r : degree of saturation, ri = li/mimi
H38: Year | I38: Payment Split (Baseline)-Manual | L38: Payment Split (ETC Alternative)-Manual | O38: Mean Capacity per Lane-ETC | W38: m : number of lanes,
I39: Cash/Chect | J39: Ticket | K39: Mean Service Rate | L39: Cash/Check | M39: Ticket | N39: Mean Service Rate | W39: l : arrival rate during the peak period (veh/hr),
H40: Base | I40: ='Input-Detail'!BH13 -> 0.83 | J40: =1-I40 -> 0.17 | K40: =3600/(Trans_Time_Cash*I40+Trans_Time_Ticket*J40) -> 547.52852 | L40: ='Input-Detail'!BJ13 -> 0.83 | M40: =1-L40 -> 0.17 | N40: =3600/(Trans_Time_Cash*L40+Trans_Time_Ticket*M40) -> 547.52852 | O40: =3600/Headway_ETC -> 1500 | W40: k : parameter for given arrival and service distribution, k = 1 for Poisson Arrivals and exponentil service time,
H41: 1 | I41: ='Input-Detail'!BH14 -> 0.83 | J41: =1-I41 -> 0.17 | K41: =3600/(Trans_Time_Cash*I41+Trans_Time_Ticket*J41) -> 547.52852 | L41: ='Input-Detail'!BJ14 -> 0.8385 | M41: =1-L41 -> 0.1615 | N41: =3600/(Trans_Time_Cash*L41+Trans_Time_Ticket*M41) -> 545.76464 | O41: =3600/Headway_ETC -> 1500 | W41: I : variance to mean ratio of arrivals; I = 1 for Poisson Arrivals.
H42: 2 | I42: ='Input-Detail'!BH15 -> 0.83 | J42: =1-I42 -> 0.17 | K42: =3600/(Trans_Time_Cash*I42+Trans_Time_Ticket*J42) -> 547.52852 | L42: ='Input-Detail'!BJ15 -> 0.847 | M42: =1-L42 -> 0.153 | N42: =3600/(Trans_Time_Cash*L42+Trans_Time_Ticket*M42) -> 544.01209 | O42: =3600/Headway_ETC -> 1500 | W42: For ETC lanes,no stop needed; mean transaction time is zero.
H43: 3 | I43: ='Input-Detail'!BH16 -> 0.83 | J43: =1-I43 -> 0.17 | K43: =3600/(Trans_Time_Cash*I43+Trans_Time_Ticket*J43) -> 547.52852 | L43: ='Input-Detail'!BJ16 -> 0.8555 | M43: =1-L43 -> 0.1445 | N43: =3600/(Trans_Time_Cash*L43+Trans_Time_Ticket*M43) -> 542.27076 | O43: =3600/Headway_ETC -> 1500
H44: 4 | I44: ='Input-Detail'!BH17 -> 0.83 | J44: =1-I44 -> 0.17 | K44: =3600/(Trans_Time_Cash*I44+Trans_Time_Ticket*J44) -> 547.52852 | L44: ='Input-Detail'!BJ17 -> 0.864 | M44: =1-L44 -> 0.136 | N44: =3600/(Trans_Time_Cash*L44+Trans_Time_Ticket*M44) -> 540.54054 | O44: =3600/Headway_ETC -> 1500 | W44: Total Delay (hr) Occurs in the System per day: (AD1*l1+AD2*l2)*T/3600
H45: 5 | I45: ='Input-Detail'!BH18 -> 0.83 | J45: =1-I45 -> 0.17 | K45: =3600/(Trans_Time_Cash*I45+Trans_Time_Ticket*J45) -> 547.52852 | L45: ='Input-Detail'!BJ18 -> 0.8725 | M45: =1-L45 -> 0.1275 | N45: =3600/(Trans_Time_Cash*L45+Trans_Time_Ticket*M45) -> 538.82133 | O45: =3600/Headway_ETC -> 1500 | W45: Given total number of lanes, peak hour traffic and ETC split, we can find out the optimal number of ETC lanes.
H46: 6 | I46: ='Input-Detail'!BH19 -> 0.83 | J46: =1-I46 -> 0.17 | K46: =3600/(Trans_Time_Cash*I46+Trans_Time_Ticket*J46) -> 547.52852 | L46: ='Input-Detail'!BJ19 -> 0.881 | M46: =1-L46 -> 0.119 | N46: =3600/(Trans_Time_Cash*L46+Trans_Time_Ticket*M46) -> 537.11302 | O46: =3600/Headway_ETC -> 1500 | W46: ** Delay happens to those people who arrival during the evening peak period.
H47: 7 | I47: ='Input-Detail'!BH20 -> 0.83 | J47: =1-I47 -> 0.17 | K47: =3600/(Trans_Time_Cash*I47+Trans_Time_Ticket*J47) -> 547.52852 | L47: ='Input-Detail'!BJ20 -> 0.8895 | M47: =1-L47 -> 0.1105 | N47: =3600/(Trans_Time_Cash*L47+Trans_Time_Ticket*M47) -> 535.4155 | O47: =3600/Headway_ETC -> 1500
H48: 8 | I48: ='Input-Detail'!BH21 -> 0.83 | J48: =1-I48 -> 0.17 | K48: =3600/(Trans_Time_Cash*I48+Trans_Time_Ticket*J48) -> 547.52852 | L48: ='Input-Detail'!BJ21 -> 0.898 | M48: =1-L48 -> 0.102 | N48: =3600/(Trans_Time_Cash*L48+Trans_Time_Ticket*M48) -> 533.72869 | O48: =3600/Headway_ETC -> 1500 | W48: ***Suggested Number of ETC Lanes:The number of ETC Lanes, which is close to optimal number of ETC Lanes, such that average delay in ETC lanes is less than average delay in Manual Lanes.
H49: 9 | I49: ='Input-Detail'!BH22 -> 0.83 | J49: =1-I49 -> 0.17 | K49: =3600/(Trans_Time_Cash*I49+Trans_Time_Ticket*J49) -> 547.52852 | L49: ='Input-Detail'!BJ22 -> 0.9065 | M49: =1-L49 -> 0.0935 | N49: =3600/(Trans_Time_Cash*L49+Trans_Time_Ticket*M49) -> 532.05247 | O49: =3600/Headway_ETC -> 1500
H50: 10 | I50: ='Input-Detail'!BH23 -> 0.83 | J50: =1-I50 -> 0.17 | K50: =3600/(Trans_Time_Cash*I50+Trans_Time_Ticket*J50) -> 547.52852 | L50: ='Input-Detail'!BJ23 -> 0.915 | M50: =1-L50 -> 0.085 | N50: =3600/(Trans_Time_Cash*L50+Trans_Time_Ticket*M50) -> 530.38674 | O50: =3600/Headway_ETC -> 1500
H51: 11 | I51: ='Input-Detail'!BH24 -> 0.83 | J51: =1-I51 -> 0.17 | K51: =3600/(Trans_Time_Cash*I51+Trans_Time_Ticket*J51) -> 547.52852 | L51: ='Input-Detail'!BJ24 -> 0.9235 | M51: =1-L51 -> 0.0765 | N51: =3600/(Trans_Time_Cash*L51+Trans_Time_Ticket*M51) -> 528.73141 | O51: =3600/Headway_ETC -> 1500 | W51: a) Random and Stop Delay in the System during the Morning Peak per Day (hr) | BG51: b) Average Random Delay per Manual User (sec) | CK51: c) Average Random Delay per ETC User (sec)
H52: 12 | I52: ='Input-Detail'!BH25 -> 0.83 | J52: =1-I52 -> 0.17 | K52: =3600/(Trans_Time_Cash*I52+Trans_Time_Ticket*J52) -> 547.52852 | L52: ='Input-Detail'!BJ25 -> 0.932 | M52: =1-L52 -> 0.068 | N52: =3600/(Trans_Time_Cash*L52+Trans_Time_Ticket*M52) -> 527.08638 | O52: =3600/Headway_ETC -> 1500
H53: 13 | I53: ='Input-Detail'!BH26 -> 0.83 | J53: =1-I53 -> 0.17 | K53: =3600/(Trans_Time_Cash*I53+Trans_Time_Ticket*J53) -> 547.52852 | L53: ='Input-Detail'!BJ26 -> 0.9405 | M53: =1-L53 -> 0.0595 | N53: =3600/(Trans_Time_Cash*L53+Trans_Time_Ticket*M53) -> 525.45156 | O53: =3600/Headway_ETC -> 1500 | W53: Year | X53: Traffic Vol. | Y53: ETC (%) | Z53: PHV | AA53: ATV/PHV | AB53: T (hr) | AC53: K | AD53: Total Arrival Rate | AE53: Number of ETC Lanes | BA53: Optimal # of ETC Ln* | BB53: Delay per Day**(hr) | BC53: Suggested # of ETC Ln*** | BD53: Delay per Day**(hr) | BG53: Year | BH53: ETC (%) | BI53: Total Arrival Rate | BJ53: Arrival Rate for Manual Users | BK53: Number of ETC Lanes | CI53: Mean Transaction Time (sec) | CK53: Year | CL53: ETC (%) | CM53: Total Arrival Rate | CN53: Arrival Rate for ETC Users | CO53: Number of ETC Lanes | DK53: Mean Transaction Time (sec)
H54: 14 | I54: ='Input-Detail'!BH27 -> 0.83 | J54: =1-I54 -> 0.17 | K54: =3600/(Trans_Time_Cash*I54+Trans_Time_Ticket*J54) -> 547.52852 | L54: ='Input-Detail'!BJ27 -> 0.949 | M54: =1-L54 -> 0.051 | N54: =3600/(Trans_Time_Cash*L54+Trans_Time_Ticket*M54) -> 523.82685 | O54: =3600/Headway_ETC -> 1500 | AE54: Manual Only | AF54: 1 | AG54: 2 | AH54: 3 | AI54: 4 | AJ54: 5 | AK54: 6 | AL54: 7 | AM54: 8 | AN54: 9 | AO54: 10 | AP54: 11 | AQ54: 12 | AR54: 13 | AS54: 14 | AT54: 15 | AU54: 16 | AV54: 17 | AW54: 18 | AX54: 19 | AY54: 20 | AZ54: 21 | BK54: l/sc for no ETC | BL54: Manual Only | BM54: l/sc under ETC | BN54: 1 | BO54: 2 | BP54: 3 | BQ54: 4 | BR54: 5 | BS54: 6 | BT54: 7 | BU54: 8 | BV54: 9 | BW54: 10 | BX54: 11 | BY54: 12 | BZ54: 13 | CA54: 14 | CB54: 15 | CC54: 16 | CD54: 17 | CE54: 18 | CF54: 19 | CG54: 20 | CH54: 21 | CO54: l/sc under ETC | CP54: 1 | CQ54: 2 | CR54: 3 | CS54: 4 | CT54: 5 | CU54: 6 | CV54: 7 | CW54: 8 | CX54: 9 | CY54: 10 | CZ54: 11 | DA54: 12 | DB54: 13 | DC54: 14 | DD54: 15 | DE54: 16 | DF54: 17 | DG54: 18 | DH54: 19 | DI54: 20 | DJ54: 21
H55: 15 | I55: ='Input-Detail'!BH28 -> 0.83 | J55: =1-I55 -> 0.17 | K55: =3600/(Trans_Time_Cash*I55+Trans_Time_Ticket*J55) -> 547.52852 | L55: ='Input-Detail'!BJ28 -> 0.9575 | M55: =1-L55 -> 0.0425 | N55: =3600/(Trans_Time_Cash*L55+Trans_Time_Ticket*M55) -> 522.21215 | O55: =3600/Headway_ETC -> 1500 | W55: Base | X55: =X7 -> 19016173 | Y55: =Y7 -> 0 | Z55: ='Input-Detail'!M18 -> 8200 | AA55: ='Input-Detail'!N18 -> 2319.0455 | AB55: ='Input-Detail'!O18 -> 2 | AC55: ='Input-Detail'!P18 -> 0.3 | AD55: =Z55*AC55 -> 2460 | AE55: =Peak_Time_Mor*$BI55*(CI55+BL55)/3600 -> 9.4339293 | BG55: Base | BH55: =$Y55 -> 0 | BI55: =$AD55 -> 2460 | BJ55: =BI55*(1-BH55) -> 2460 | BK55: =Peak_Arrival_Manual_Mor/K40 -> 4.4929167 | BL55: =900*Peak_Time_Mor*($BK55/Total_Lanes-1+SQRT(($BK55/Total_Lanes-1)^2+8*($BK55/Total_Lanes)/(Peak_Time_Mor*$K40*Total_Lanes))) -> 0.32787508 | BM55: =Peak_Arrival_Manual_Mor/N40 -> 4.4929167 | BN55: =IF(BN$6<Total_Lanes,900*Peak_Time_Mor*($BM55/(Total_Lanes-BN$6)-1+SQRT(($BM55/(Total_Lanes-BN$6)-1)^2+8*($BM55/(Total_Lanes-BN$6))/(Peak_Time_Mor*$N40*(Total_Lanes-BN$6)))),"-") -> 0.41263012 | BO55: =IF(BO$6<Total_Lanes,900*Peak_Time_Mor*($BM55/(Total_Lanes-BO$6)-1+SQRT(($BM55/(Total_Lanes-BO$6)-1)^2+8*($BM55/(Total_Lanes-BO$6))/(Peak_Time_Mor*$N40*(Total_Lanes-BO$6)))),"-") -> 0.53627187 | BP55: =IF(BP$6<Total_Lanes,900*Peak_Time_Mor*($BM55/(Total_Lanes-BP$6)-1+SQRT(($BM55/(Total_Lanes-BP$6)-1)^2+8*($BM55/(Total_Lanes-BP$6))/(Peak_Time_Mor*$N40*(Total_Lanes-BP$6)))),"-") -> 0.72796533 | BQ55: =IF(BQ$6<Total_Lanes,900*Peak_Time_Mor*($BM55/(Total_Lanes-BQ$6)-1+SQRT(($BM55/(Total_Lanes-BQ$6)-1)^2+8*($BM55/(Total_Lanes-BQ$6))/(Peak_Time_Mor*$N40*(Total_Lanes-BQ$6)))),"-") -> 1.0522007 | BR55: =IF(BR$6<Total_Lanes,900*Peak_Time_Mor*($BM55/(Total_Lanes-BR$6)-1+SQRT(($BM55/(Total_Lanes-BR$6)-1)^2+8*($BM55/(Total_Lanes-BR$6))/(Peak_Time_Mor*$N40*(Total_Lanes-BR$6)))),"-") -> 1.6810918 | BS55: =IF(BS$6<Total_Lanes,900*Peak_Time_Mor*($BM55/(Total_Lanes-BS$6)-1+SQRT(($BM55/(Total_Lanes-BS$6)-1)^2+8*($BM55/(Total_Lanes-BS$6))/(Peak_Time_Mor*$N40*(Total_Lanes-BS$6)))),"-") -> 3.25518 | BT55: =IF(BT$6<Total_Lanes,900*Peak_Time_Mor*($BM55/(Total_Lanes-BT$6)-1+SQRT(($BM55/(Total_Lanes-BT$6)-1)^2+8*($BM55/(Total_Lanes-BT$6))/(Peak_Time_Mor*$N40*(Total_Lanes-BT$6)))),"-") -> 11.301479 | BU55: =IF(BU$6<Total_Lanes,900*Peak_Time_Mor*($BM55/(Total_Lanes-BU$6)-1+SQRT(($BM55/(Total_Lanes-BU$6)-1)^2+8*($BM55/(Total_Lanes-BU$6))/(Peak_Time_Mor*$N40*(Total_Lanes-BU$6)))),"-") -> 458.13324 | ... CH55: =IF(CH$6<Total_Lanes,900*Peak_Time_Mor*($BM55/(Total_Lanes-CH$6)-1+SQRT(($BM55/(Total_Lanes-CH$6)-1)^2+8*($BM55/(Total_Lanes-CH$6))/(Peak_Time_Mor*$N40*(Total_Lanes-CH$6)))),"-") -> - | CI55: =3600/N40 -> 6.575 | CK55: Base | CL55: =$Y55 -> 0 | CM55: =$AD55 -> 2460 | CN55: =CM55*CL55 -> 0
H56: 16 | I56: ='Input-Detail'!BH29 -> 0.83 | J56: =1-I56 -> 0.17 | K56: =3600/(Trans_Time_Cash*I56+Trans_Time_Ticket*J56) -> 547.52852 | L56: ='Input-Detail'!BJ29 -> 0.966 | M56: =1-L56 -> 0.034 | N56: =3600/(Trans_Time_Cash*L56+Trans_Time_Ticket*M56) -> 520.60738 | O56: =3600/Headway_ETC -> 1500 | W56: 1 | X56: =X8 -> 19565364 | Y56: =Y8 -> 0.0495 | Z56: =Z8 -> 8436.8178 | AA56: =X56/Z56 -> 2319.0455 | AB56: =AB8 -> 2 | AC56: =1-AC8 -> 0.3 | AD56: =Z56*AC56 -> 2531.0454 | AE56: =Peak_Time_Mor*$BI56*(CI56+BL56)/3600 -> 9.7202288 | AF56: =IF(AF$54<Total_Lanes,($BJ56*($CI56+BN56)+$CN56*CP56)*Peak_Time_Mor/3600,"-") -> 9.3671674 | AG56: =IF(AG$54<Total_Lanes,($BJ56*($CI56+BO56)+$CN56*CQ56)*Peak_Time_Mor/3600,"-") -> 9.5145242 | AH56: =IF(AH$54<Total_Lanes,($BJ56*($CI56+BP56)+$CN56*CR56)*Peak_Time_Mor/3600,"-") -> 9.7576752 | AI56: =IF(AI$54<Total_Lanes,($BJ56*($CI56+BQ56)+$CN56*CS56)*Peak_Time_Mor/3600,"-") -> 10.168542 | AJ56: =IF(AJ$54<Total_Lanes,($BJ56*($CI56+BR56)+$CN56*CT56)*Peak_Time_Mor/3600,"-") -> 10.956 | AK56: =IF(AK$54<Total_Lanes,($BJ56*($CI56+BS56)+$CN56*CU56)*Peak_Time_Mor/3600,"-") -> 12.872193 | AL56: =IF(AL$54<Total_Lanes,($BJ56*($CI56+BT56)+$CN56*CV56)*Peak_Time_Mor/3600,"-") -> 21.657076 | AM56: =IF(AM$54<Total_Lanes,($BJ56*($CI56+BU56)+$CN56*CW56)*Peak_Time_Mor/3600,"-") -> 522.40749 | ... AZ56: =IF(AZ$54<Total_Lanes,($BJ56*($CI56+CH56)+$CN56*DJ56)*Peak_Time_Mor/3600,"-") -> - | BA56: =SUMIF(AF56:AZ56,BB56,$AF$54:$AZ$54) -> 1 | BB56: =MIN(AF56:AZ56) -> 9.3671674 | BC56: =IF((SUMIF($BN54:$CH54,$BA56,$BN56:$CH56)+$CI56)<(SUMIF($CP54:$DJ54,$BA56,$CP56:$DJ56)+$DK56),BA56+1,BA56) -> 1 | BD56: =SUMIF($AF$54:$AZ$54,$BC56,$AF56:$AZ56) -> 9.3671674 | BG56: 1 | BH56: =$Y56 -> 0.0495 | BI56: =$AD56 -> 2531.0454 | BJ56: =BI56*(1-BH56) -> 2405.7586 | BK56: =Peak_Arrival_Manual_Mor/K41 -> 4.3938508 | BL56: =900*Peak_Time_Mor*($BK56/Total_Lanes-1+SQRT(($BK56/Total_Lanes-1)^2+8*($BK56/Total_Lanes)/(Peak_Time_Mor*$K41*Total_Lanes))) -> 0.3164716 | BM56: =Peak_Arrival_Manual_Mor/N41 -> 4.4080514 | BN56: =IF(BN$6<Total_Lanes,900*Peak_Time_Mor*($BM56/(Total_Lanes-BN$6)-1+SQRT(($BM56/(Total_Lanes-BN$6)-1)^2+8*($BM56/(Total_Lanes-BN$6))/(Peak_Time_Mor*$N41*(Total_Lanes-BN$6)))),"-") -> 0.40091893 | BO56: =IF(BO$6<Total_Lanes,900*Peak_Time_Mor*($BM56/(Total_Lanes-BO$6)-1+SQRT(($BM56/(Total_Lanes-BO$6)-1)^2+8*($BM56/(Total_Lanes-BO$6))/(Peak_Time_Mor*$N41*(Total_Lanes-BO$6)))),"-") -> 0.51983853 | BP56: =IF(BP$6<Total_Lanes,900*Peak_Time_Mor*($BM56/(Total_Lanes-BP$6)-1+SQRT(($BM56/(Total_Lanes-BP$6)-1)^2+8*($BM56/(Total_Lanes-BP$6))/(Peak_Time_Mor*$N41*(Total_Lanes-BP$6)))),"-") -> 0.70329573 | BQ56: =IF(BQ$6<Total_Lanes,900*Peak_Time_Mor*($BM56/(Total_Lanes-BQ$6)-1+SQRT(($BM56/(Total_Lanes-BQ$6)-1)^2+8*($BM56/(Total_Lanes-BQ$6))/(Peak_Time_Mor*$N41*(Total_Lanes-BQ$6)))),"-") -> 1.0112349 | BR56: =IF(BR$6<Total_Lanes,900*Peak_Time_Mor*($BM56/(Total_Lanes-BR$6)-1+SQRT(($BM56/(Total_Lanes-BR$6)-1)^2+8*($BM56/(Total_Lanes-BR$6))/(Peak_Time_Mor*$N41*(Total_Lanes-BR$6)))),"-") -> 1.6006566 | BS56: =IF(BS$6<Total_Lanes,900*Peak_Time_Mor*($BM56/(Total_Lanes-BS$6)-1+SQRT(($BM56/(Total_Lanes-BS$6)-1)^2+8*($BM56/(Total_Lanes-BS$6))/(Peak_Time_Mor*$N41*(Total_Lanes-BS$6)))),"-") -> 3.0344917 | BT56: =IF(BT$6<Total_Lanes,900*Peak_Time_Mor*($BM56/(Total_Lanes-BT$6)-1+SQRT(($BM56/(Total_Lanes-BT$6)-1)^2+8*($BM56/(Total_Lanes-BT$6))/(Peak_Time_Mor*$N41*(Total_Lanes-BT$6)))),"-") -> 9.6074614 | BU56: =IF(BU$6<Total_Lanes,900*Peak_Time_Mor*($BM56/(Total_Lanes-BU$6)-1+SQRT(($BM56/(Total_Lanes-BU$6)-1)^2+8*($BM56/(Total_Lanes-BU$6))/(Peak_Time_Mor*$N41*(Total_Lanes-BU$6)))),"-") -> 384.27135 | ... CH56: =IF(CH$6<Total_Lanes,900*Peak_Time_Mor*($BM56/(Total_Lanes-CH$6)-1+SQRT(($BM56/(Total_Lanes-CH$6)-1)^2+8*($BM56/(Total_Lanes-CH$6))/(Peak_Time_Mor*$N41*(Total_Lanes-CH$6)))),"-") -> - | CI56: =3600/N41 -> 6.59625 | CK56: 1 | CL56: =$Y56 -> 0.0495 | CM56: =$AD56 -> 2531.0454 | CN56: =CM56*CL56 -> 125.28674 | CO56: =CN56/O41 -> 0.083524497 | CP56: =IF(CP$54<Total_Lanes,900*Peak_Time_Mor*($CO56/CP$54-1+SQRT(($CO56/CP$54-1)^2+8*($CO56/CP$54)/(Peak_Time_Mor*$O41*CP$54))),"-") -> 0.21871343 | CQ56: =IF(CQ$54<Total_Lanes,900*Peak_Time_Mor*($CO56/CQ$54-1+SQRT(($CO56/CQ$54-1)^2+8*($CO56/CQ$54)/(Peak_Time_Mor*$O41*CQ$54))),"-") -> 0.052298021 | CR56: =IF(CR$54<Total_Lanes,900*Peak_Time_Mor*($CO56/CR$54-1+SQRT(($CO56/CR$54-1)^2+8*($CO56/CR$54)/(Peak_Time_Mor*$O41*CR$54))),"-") -> 0.022910928 | CS56: =IF(CS$54<Total_Lanes,900*Peak_Time_Mor*($CO56/CS$54-1+SQRT(($CO56/CS$54-1)^2+8*($CO56/CS$54)/(Peak_Time_Mor*$O41*CS$54))),"-") -> 0.01279582 | CT56: =IF(CT$54<Total_Lanes,900*Peak_Time_Mor*($CO56/CT$54-1+SQRT(($CO56/CT$54-1)^2+8*($CO56/CT$54)/(Peak_Time_Mor*$O41*CT$54))),"-") -> 0.0081545542 | CU56: =IF(CU$54<Total_Lanes,900*Peak_Time_Mor*($CO56/CU$54-1+SQRT(($CO56/CU$54-1)^2+8*($CO56/CU$54)/(Peak_Time_Mor*$O41*CU$54))),"-") -> 0.0056469 | CV56: =IF(CV$54<Total_Lanes,900*Peak_Time_Mor*($CO56/CV$54-1+SQRT(($CO56/CV$54-1)^2+8*($CO56/CV$54)/(Peak_Time_Mor*$O41*CV$54))),"-") -> 0.0041403945 | CW56: =IF(CW$54<Total_Lanes,900*Peak_Time_Mor*($CO56/CW$54-1+SQRT(($CO56/CW$54-1)^2+8*($CO56/CW$54)/(Peak_Time_Mor*$O41*CW$54))),"-") -> 0.0031652124 | ... DJ56: =IF(DJ$54<Total_Lanes,900*Peak_Time_Mor*($CO56/DJ$54-1+SQRT(($CO56/DJ$54-1)^2+8*($CO56/DJ$54)/(Peak_Time_Mor*$O41*DJ$54))),"-") -> - | DK56: =3600/$O41 -> 2.4
H57: 17 | I57: ='Input-Detail'!BH30 -> 0.83 | J57: =1-I57 -> 0.17 | K57: =3600/(Trans_Time_Cash*I57+Trans_Time_Ticket*J57) -> 547.52852 | L57: ='Input-Detail'!BJ30 -> 0.9745 | M57: =1-L57 -> 0.0255 | N57: =3600/(Trans_Time_Cash*L57+Trans_Time_Ticket*M57) -> 519.01243 | O57: =3600/Headway_ETC -> 1500 | W57: 2 | X57: =X9 -> 20114556 | Y57: =Y9 -> 0.099 | Z57: =Z9 -> 8673.6357 | AA57: =X57/Z57 -> 2319.0455 | AB57: =AB9 -> 2 | AC57: =1-AC9 -> 0.3 | AD57: =Z57*AC57 -> 2602.0907 | AE57: =Peak_Time_Mor*$BI57*(CI57+BL57)/3600 -> 10.005677 | AF57: =IF(AF$54<Total_Lanes,($BJ57*($CI57+BN57)+$CN57*CP57)*Peak_Time_Mor/3600,"-") -> 9.1950869 | AG57: =IF(AG$54<Total_Lanes,($BJ57*($CI57+BO57)+$CN57*CQ57)*Peak_Time_Mor/3600,"-") -> 9.2879845 | AH57: =IF(AH$54<Total_Lanes,($BJ57*($CI57+BP57)+$CN57*CR57)*Peak_Time_Mor/3600,"-") -> 9.5058164 | AI57: =IF(AI$54<Total_Lanes,($BJ57*($CI57+BQ57)+$CN57*CS57)*Peak_Time_Mor/3600,"-") -> 9.8805441 | AJ57: =IF(AJ$54<Total_Lanes,($BJ57*($CI57+BR57)+$CN57*CT57)*Peak_Time_Mor/3600,"-") -> 10.591924 | AK57: =IF(AK$54<Total_Lanes,($BJ57*($CI57+BS57)+$CN57*CU57)*Peak_Time_Mor/3600,"-") -> 12.273267 | AL57: =IF(AL$54<Total_Lanes,($BJ57*($CI57+BT57)+$CN57*CV57)*Peak_Time_Mor/3600,"-") -> 19.20819 | AM57: =IF(AM$54<Total_Lanes,($BJ57*($CI57+BU57)+$CN57*CW57)*Peak_Time_Mor/3600,"-") -> 399.42148 | ... AZ57: =IF(AZ$54<Total_Lanes,($BJ57*($CI57+CH57)+$CN57*DJ57)*Peak_Time_Mor/3600,"-") -> - | BA57: =SUMIF(AF57:AZ57,BB57,$AF$54:$AZ$54) -> 1 | BB57: =MIN(AF57:AZ57) -> 9.1950869 | BC57: =IF((SUMIF($BN55:$CH55,$BA57,$BN57:$CH57)+$CI57)<(SUMIF($CP55:$DJ55,$BA57,$CP57:$DJ57)+$DK57),BA57+1,BA57) -> 1 | BD57: =SUMIF($AF$54:$AZ$54,$BC57,$AF57:$AZ57) -> 9.1950869 | BG57: 2 | BH57: =$Y57 -> 0.099 | BI57: =$AD57 -> 2602.0907 | BJ57: =BI57*(1-BH57) -> 2344.4837 | BK57: =Peak_Arrival_Manual_Mor/K42 -> 4.281939 | BL57: =900*Peak_Time_Mor*($BK57/Total_Lanes-1+SQRT(($BK57/Total_Lanes-1)^2+8*($BK57/Total_Lanes)/(Peak_Time_Mor*$K42*Total_Lanes))) -> 0.30394134 | BM57: =Peak_Arrival_Manual_Mor/N42 -> 4.309617 | BN57: =IF(BN$6<Total_Lanes,900*Peak_Time_Mor*($BM57/(Total_Lanes-BN$6)-1+SQRT(($BM57/(Total_Lanes-BN$6)-1)^2+8*($BM57/(Total_Lanes-BN$6))/(Peak_Time_Mor*$N42*(Total_Lanes-BN$6)))),"-") -> 0.38744683 | BO57: =IF(BO$6<Total_Lanes,900*Peak_Time_Mor*($BM57/(Total_Lanes-BO$6)-1+SQRT(($BM57/(Total_Lanes-BO$6)-1)^2+8*($BM57/(Total_Lanes-BO$6))/(Peak_Time_Mor*$N42*(Total_Lanes-BO$6)))),"-") -> 0.50105443 | BP57: =IF(BP$6<Total_Lanes,900*Peak_Time_Mor*($BM57/(Total_Lanes-BP$6)-1+SQRT(($BM57/(Total_Lanes-BP$6)-1)^2+8*($BM57/(Total_Lanes-BP$6))/(Peak_Time_Mor*$N42*(Total_Lanes-BP$6)))),"-") -> 0.67534471 | BQ57: =IF(BQ$6<Total_Lanes,900*Peak_Time_Mor*($BM57/(Total_Lanes-BQ$6)-1+SQRT(($BM57/(Total_Lanes-BQ$6)-1)^2+8*($BM57/(Total_Lanes-BQ$6))/(Peak_Time_Mor*$N42*(Total_Lanes-BQ$6)))),"-") -> 0.96542555 | BR57: =IF(BR$6<Total_Lanes,900*Peak_Time_Mor*($BM57/(Total_Lanes-BR$6)-1+SQRT(($BM57/(Total_Lanes-BR$6)-1)^2+8*($BM57/(Total_Lanes-BR$6))/(Peak_Time_Mor*$N42*(Total_Lanes-BR$6)))),"-") -> 1.512676 | BS57: =IF(BS$6<Total_Lanes,900*Peak_Time_Mor*($BM57/(Total_Lanes-BS$6)-1+SQRT(($BM57/(Total_Lanes-BS$6)-1)^2+8*($BM57/(Total_Lanes-BS$6))/(Peak_Time_Mor*$N42*(Total_Lanes-BS$6)))),"-") -> 2.8041237 | BT57: =IF(BT$6<Total_Lanes,900*Peak_Time_Mor*($BM57/(Total_Lanes-BT$6)-1+SQRT(($BM57/(Total_Lanes-BT$6)-1)^2+8*($BM57/(Total_Lanes-BT$6))/(Peak_Time_Mor*$N42*(Total_Lanes-BT$6)))),"-") -> 8.1288256 | BU57: =IF(BU$6<Total_Lanes,900*Peak_Time_Mor*($BM57/(Total_Lanes-BU$6)-1+SQRT(($BM57/(Total_Lanes-BU$6)-1)^2+8*($BM57/(Total_Lanes-BU$6))/(Peak_Time_Mor*$N42*(Total_Lanes-BU$6)))),"-") -> 300.04148 | ... CH57: =IF(CH$6<Total_Lanes,900*Peak_Time_Mor*($BM57/(Total_Lanes-CH$6)-1+SQRT(($BM57/(Total_Lanes-CH$6)-1)^2+8*($BM57/(Total_Lanes-CH$6))/(Peak_Time_Mor*$N42*(Total_Lanes-CH$6)))),"-") -> - | CI57: =3600/N42 -> 6.6175 | CK57: 2 | CL57: =$Y57 -> 0.099 | CM57: =$AD57 -> 2602.0907 | CN57: =CM57*CL57 -> 257.60698 | CO57: =CN57/O42 -> 0.17173799 | CP57: =IF(CP$54<Total_Lanes,900*Peak_Time_Mor*($CO57/CP$54-1+SQRT(($CO57/CP$54-1)^2+8*($CO57/CP$54)/(Peak_Time_Mor*$O42*CP$54))),"-") -> 0.49755077 | CQ57: =IF(CQ$54<Total_Lanes,900*Peak_Time_Mor*($CO57/CQ$54-1+SQRT(($CO57/CQ$54-1)^2+8*($CO57/CQ$54)/(Peak_Time_Mor*$O42*CQ$54))),"-") -> 0.11271827 | CR57: =IF(CR$54<Total_Lanes,900*Peak_Time_Mor*($CO57/CR$54-1+SQRT(($CO57/CR$54-1)^2+8*($CO57/CR$54)/(Peak_Time_Mor*$O42*CR$54))),"-") -> 0.048576978 | CS57: =IF(CS$54<Total_Lanes,900*Peak_Time_Mor*($CO57/CS$54-1+SQRT(($CO57/CS$54-1)^2+8*($CO57/CS$54)/(Peak_Time_Mor*$O42*CS$54))),"-") -> 0.026916127 | CT57: =IF(CT$54<Total_Lanes,900*Peak_Time_Mor*($CO57/CT$54-1+SQRT(($CO57/CT$54-1)^2+8*($CO57/CT$54)/(Peak_Time_Mor*$O42*CT$54))),"-") -> 0.017073189 | CU57: =IF(CU$54<Total_Lanes,900*Peak_Time_Mor*($CO57/CU$54-1+SQRT(($CO57/CU$54-1)^2+8*($CO57/CU$54)/(Peak_Time_Mor*$O42*CU$54))),"-") -> 0.011786526 | CV57: =IF(CV$54<Total_Lanes,900*Peak_Time_Mor*($CO57/CV$54-1+SQRT(($CO57/CV$54-1)^2+8*($CO57/CV$54)/(Peak_Time_Mor*$O42*CV$54))),"-") -> 0.0086231973 | CW57: =IF(CW$54<Total_Lanes,900*Peak_Time_Mor*($CO57/CW$54-1+SQRT(($CO57/CW$54-1)^2+8*($CO57/CW$54)/(Peak_Time_Mor*$O42*CW$54))),"-") -> 0.006581448 | ... DJ57: =IF(DJ$54<Total_Lanes,900*Peak_Time_Mor*($CO57/DJ$54-1+SQRT(($CO57/DJ$54-1)^2+8*($CO57/DJ$54)/(Peak_Time_Mor*$O42*DJ$54))),"-") -> - | DK57: =3600/$O42 -> 2.4
