Workbook

Sheet Input-Start
A2: 0. >> INSTRUCTION << | D2: I. | F2: TRAFFIC DATA | M2: IIa. | N2: COSTS INFORMATION--Baseline (No ETC) | V2: IIb. | W2: COSTS INFORMATION--ETC Alternative | AF2: III. | AG2: FACT OF TOLL TRANSACTION | AO2: IV. | AP2: TRAVEL AT THE TOLL PLAZA | AX2: V. | AY2: FUEL CONSUMPTION & OTHER ASSUMPTIONS
A3: This spreadsheet model is designed exclusively for benefit-cost evaluation of | C3: INSTRUCTION: | L3: INSTRUCTION: | U3: INSTRUCTION: | AE3: INSTRUCTION: | AN3: INSTRUCTION: | AW3: INSTRUCTION:
A4: Electronic Toll Collection system. | D4: In this section, You are asked to give information about annual traffic | M4: In this section, You are asked to give information about costs for baseline | V4: In this section, You are asked to give information about costs under ETC scenario. | AF4: Required Inputs - white cells | AO4: In this section, You are asked to give information about travel fact at the toll plaza | AX4: In this section, You are asked to give information about fuel consumption in
D5: volume, peak hour volume, D factor and duration of peak period and ETC | M5: operations. Costs are broken down into two categories: one-time costs and | V5: Costs are broken down into two categories: capital investment and operating costs. | AF5: If you have more information about payment split other base year and year 20, go to | AO5: Required Inputs - white cells | AX5: order to estimate the fuel reduction, and other general assumptions.
A6: Where to Start? | D6: Split both in base year and in year 20 or one of them. | M6: continuing costs. All the costs are presented in current value. | V6: All the costs are presented in current value. | AF6: Table IV, expected payment split, in sheet"Input-Details" after completing this table. | AO6: a)Ramp Distance prior to (leading from) the Toll Plaza: The distance that a vehicle | AX6: The Numbers shown in pink cells are the values from previously studies and
A7: Please start with sheet "Input-Start" and fill out all required cells. You may check | D7: If you have information in between, go to sheet "Input-Detail" table Ia, Ib, and 1c | M7: Go to sheet "Input-Detail" table IIa after completing this table if you have | V7: If you have more information, go to sheet "Input-Detail" table IIb after completing this table. | AF7: Default Values - pink cells | AO7: starts to slow down from the normal speed (to accelerate from complete stop). | AX7: used as default values to run the model. Please update it if you have
A8: "Input-Detail" and make some changes based on your own knowledge, or go to the | D8: after completing this table. | M8: detailed information regarding baseline costs. | V8: Required Inputs - white cells | AF8: The values shown in the pink cells are the default number we used previously to run | AO8: b)Prevailing Travel Speed: The travel speed in the adjacent highway sections that | AX8: different values in your case.
A9: "Results Summary" and "Results-Detail" directly to find out the analytical results. | D9: Required Inputs - white cells | M9: Required Inputs - white cells | V9: a) Capital Investment: Initial investment needed to implement ETC project | AF9: the model, please change it if you have different numbers. | AO9: is not influenced by the existence of the toll plaza.
A10: Notice that:always complete this sheet first. | D10: a) Annual Traffic Volume in Base Year as well as in Year 20: | M10: a) One-Time Costs: Costs which occur only once at a specific point of time. | V10: b) Operating Costs: Costs in order to operate the system under ETC scenario | AF10: a) Avg. Tags per Account: The ratio of the number of transponders issued over | AO10: Default Values - pink cells | AX10: Assumptions about Fuel Consumption
D11: "Annual Traffic Volume" here is defined as the number of traffic goes | M11: enter "0" if no costs incurred. | V11: 1) One-time costs: costs which occur only once at a specific point of time | AF11: over the number of accounts open. Several cars may share one account. | AO11: The numbers in pink cells are used previously to run the model, please update it
A12: Other sheets in this files are for the sake of estimation. You may want to have a | D12: through the Toll Plaza per year. | M12: b) Continuing Costs: Costs incurred every year | V12: 2) Operations/Materials Costs | AF12: b)Avg. Usage per Year: Total number of transactions divided by the total | AO12: if your case has different values . | AX12: Average Milage of Consuming one Gallon of Fuel | BA12: 25
A13: glance and get a general idea of how to get these numbers. You can refer to | D13: b) Expected ETC Split in Base Year as well as in Year 20 | M13: 1) Operations/Materials Costs | V13: 3) Others | AF13: number of accounts open. | AX13: Fuel Price per Gallon | BA13: 1.1
A14: footnotes right below the spreadsheet which provide formula and assumptions | D14: c) Peak Hour Volume (PHV) in Base Year. | M14: 2) Others | V14: Staff Costs is estimated automatically by given units of personal year needed for toll | AF14: c)Deposits: This number refers to the required deposits for transponders. | AX14: Emission Rates during Acceleration (grams/gallon)
A15: employed to proceed the clalculation. | D15: "Peak Hour Volume" here is defined as traffic volume in both direction during | M15: Staff Costs is estimated automatically by given units of personal year needed for | V15: collection and information technology, and costs per personal year. | AO15: Configuration of the Toll Plaza | AY15: Nox | BA15: 24.7
D16: the peak period. | M16: toll collection and information technology, and costs per personal year. | AF16: Transaction Time (sec) | AP16: Total Number of Lanes (max 22) | AR16: 12 | AY16: HC | BA16: 9.5
A17: q SHEET "Input-Start" | D17: d) Peak Hour Duration (T) in Base Year | V17: Year | W17: Capital Investment | X17: Operating Costs | AG17: Cash | AI17: 7 | AP17: Ramp Distance prior to the Toll Plaza (miles) | AR17: 0.2 | AY17: CO | BA17: 209
A18: In this Sheet, you are asked to give the basic information required for Benefit-Cost analysis. | D18: e) D factor (D) in Base Year - directional split | M18: Year | N18: One-Time Costs | O18: Continuing Costs: | X18: One-Time Costs | Y18: Staff | Z18: Operations/Materials | AA18: Other | AG18: Ticket | AI18: 4.5 | AP18: Ramp Distance leading from the toll Plaza (miles) | AR18: 0.2 | AX18: Emission Rates during Idling (grams/minute)
A19: Basically, you have to provide the data for Base Year as well as for Year 20. | O19: Staff | P19: Operations/Materials | Q19: Other | V19: Base | W19: 3009340 | X19: 0 | Z19: 8356 | AA19: 301760 | AG19: ETC (headway) | AI19: 2.4 | AY19: Nox | BA19: 0
A20: Then, the model estimates the numbers in between automatically by linear interpolation. | D20: Estimated Annual Traffic Volume (ATV) | M20: Base | N20: 0 | P20: 8356.16 | Q20: 297120 | V20: 1 | W20: 0 | X20: 231886.25 | AF20: Payment Split | AO20: Prevailing Travel Speed (mph) | AR20: 55 | AY20: HC | BA20: 0.15
A21: If you have more data regarding information required other than base in year and in year 20, | F21: Base Year | G21: Year 20 | M21: 1 | N21: 0 | V21: 2 | W21: 0 | X21: 244904.15 | AF21: Manual Lane-Baseline | AH21: Base Year | AI21: Year 20 | AY21: CO | BA21: 2.5
A22: enter the basic data required in this sheet first; | E22: Traffic Volume | F22: 19016173 | G22: 30000000 | M22: 2 | N22: 0 | V22: 3 | W22: 0 | X22: 257922.04 | AG22: Cash | AH22: 0.83 | AI22: 0.83 | AO22: Mode Split among ETC Users | AX22: Cost of Air Polution ($/kg of pollutant)
A23: then, go to the sheet "Input-Detail" to change the number shown in blue cells. | E23: ETC Split | F23: 0 | G23: 0.95 | M23: 3 | N23: 0 | V23: 4 | W23: 0 | X23: 270939.94 | AG23: Ticket | AH23: =1-AH22 -> 0.17 | AI23: =1-AI22 -> 0.17 | AP23: Auto | AR23: 0.9476 | AY23: Nox | BA23: 1.275
M24: 4 | N24: 0 | V24: 5 | W24: 0 | X24: 283957.83 | AF24: Manual Lane-ETC Alternative | AP24: Truck | AR24: 0.0511 | AY24: HC | BA24: 1.275
A25: q SHEET "Input-Detail" | D25: Peak Hour Statistics in Base Year | M25: 5 | N25: 0 | V25: 6 | W25: 0 | X25: 296975.72 | AG25: Cash | AH25: 0.83 | AI25: 1 | AP25: Bus | AR25: 0.0013 | AY25: CO | BA25: 0.0063
A26: In this Sheet, you you may change the numbers estimated automatically by this model based | F26: Morning | G26: Evening | M26: 6 | N26: 0 | V26: 7 | W26: 0 | X26: 309993.62 | AG26: Ticket | AH26: =1-AH25 -> 0.17 | AI26: =1-AI25 -> 0 | AO26: Average Vehicle Occupancy
A27: on the numbers you enter in "Input-Start". | E27: PHV (veh/hr) | F27: 8200 | G27: 8200 | M27: 7 | N27: 0 | V27: 8 | W27: 0 | X27: 323011.51 | AF27: ETC Lane-ETC Alternative | AP27: Auto | AR27: 1.8
E28: T (hr) | F28: 2 | G28: 2 | M28: 8 | N28: 0 | V28: 9 | W28: 0 | X28: 336029.41 | AG28: Cash, Checks | AH28: 0.64 | AI28: 0.64 | AP28: Truck | AR28: 1.1 | AX28: General Assumptions
A29: q SHEET "Results Summary" | E29: D factor | F29: 0.3 | G29: 0.7 | M29: 9 | N29: 0 | V29: 10 | W29: 0 | X29: 349047.3 | AG29: Credit Card | AH29: =1-AH28 -> 0.36 | AI29: =1-AI28 -> 0.36 | AP29: Bus | AR29: 20
A30: In this Sheet, , overall analytical results are presented as well as benefit-cost ratio and | M30: 10 | N30: 0 | V30: 11 | W30: 0 | X30: 362065.2 | AF30: ETC Account Fact | AX30: Inflation Rate | BA30: 0.03
A31: estimated internal interest rate. | M31: 11 | N31: 0 | V31: 12 | W31: 0 | X31: 375083.09 | AF31: Cash & Checks Account | AI31: Base Year | AO31: Time Value for Each Mode ($/hr) | AX31: Annual Interest Rate | BA31: 0.06
M32: 12 | N32: 0 | V32: 13 | W32: 0 | X32: 388100.99 | AG32: Avg. Tags per Accout | AI32: 1.35 | AP32: Auto | AR32: 12.75 | AX32: Discount Rate | BA32: 0.03
A33: q SHEET "Results-Detail" | M33: 13 | N33: 0 | V33: 14 | W33: 0 | X33: 401118.88 | AG33: Avg. Usage per Year | AI33: 160 | AP33: Truck | AR33: 33.41 | AX33: Personal Year (PY)
A34: In this Sheet, benefit-cost analyses are shown for Toll Agency, Users, and Community. | M34: 14 | N34: 0 | V34: 15 | W34: 0 | X34: 414136.78 | AG34: Deposits | AI34: 30 | AP34: Bus (per rider) | AR34: 12.75 | AY34: Hours per Unit Personal Year | BA34: 1768
A35: respectively. | M35: 15 | N35: 0 | V35: 16 | W35: 0 | X35: 427154.67 | AG35: Avg. Balance other than Deposit | AI35: 20 | AY35: PY for Information Technology | BA35: 0.11
M36: 16 | N36: 0 | V36: 17 | W36: 0 | X36: 440172.56 | AF36: Credit Card Account | AI36: Base Year | AY36: PY for Program Costs (Toll Collection) | BA36: 61.5
M37: 17 | N37: 0 | V37: 18 | W37: 0 | X37: 453190.46 | AG37: Avg. Tags per Accout | AI37: 1.35 | AY37: Unit Cost per Personal Year | BA37: 65000
M38: 18 | N38: 0 | V38: 19 | W38: 0 | X38: 466208.35 | AG38: Avg. Usage per Year | AI38: 160
M39: 19 | N39: 0 | V39: 20 | W39: 0 | X39: 479226.25 | AG39: Deposits | AI39: 0
M40: 20 | N40: 0 | AG40: Avg. Balance other than Deposit | AI40: 20

Sheet Input-Detail
C2: Ia. | D2: TRAFFIC DATA - Annual | L2: Ib. | M2: TRAFFIC DATA - Morning Peak | U2: Ic. | V2: TRAFFIC DATA - Evening Peak | AD2: IIa. | AE2: COSTS INFORMATION--Baseline (No ETC) | AM2: IIa. | AN2: COSTS INFORMATION--ETC Alternative | AW2: III. | AX2: FACT OF TOLL TRANSACTION & Travel at Toll Plaza | BF2: IV. | BI2: EXPECTED PAYMENT SPLIT | BS2: V. | BT2: FUEL CONSUMPTION & OTHER ASSUMPTIONS
B3: INSTRUCTION: | K3: INSTRUCTION: | T3: INSTRUCTION: | AC3: INSTRUCTION: | AL3: INSTRUCTION: | AV3: INSTRUCTION: | BE3: INSTRUCTION: | BR3: INSTRUCTION:
C4: Change the numbers in blue cells only - | L4: Change the numbers in blue cells only - | U4: Change the numbers in blue cells only - | AD4: Change the numbers in blue cells only - | AM4: Change the numbers in blue cells only - | AW4: The values shown in pink cells are the default number we used to run the model. | BF4: Change the numbers in blue cells only - | BS4: The values shown in pink cells are the default number we used to run the model.
C5: The data in Base Year and Year 20 you enter in sheet "Input-Start" are | L5: The data in Base Year and Year 20 you enter in sheet "Input-Start" are | U5: The data in Base Year and Year 20 you enter in sheet "Input-Start" are | AD5: The data in Base Year and Year 20 you enter in sheet "Input-Start" are shown | AM5: The data in Base Year and Year 20 you enter in sheet "Input-Start" are | AW5: The numbers in white cells are those you entered in Table III &IV in "Input-Start" Sheet. | BF5: the numbers in white cells are those you entered in "Input-Start" Sheet about . | BS5: The numbers in white cells are those you entered in Table V in "Input-Start" Sheet.
C6: shown on white cells. | L6: shown on white cells. | U6: shown on white cells. | AD6: on white cells after inflation effect. That is, the number show on this table | AM6: shown on white cells after inflation effect. That is, the number show on this | AW6: You can not make any change here. | BF6: payment split among Manual Users as well as among ETC Users. | BS6: You can not make any change here.
C7: Based on these data, the model estimated automatically annual traffic volume | L7: Based on these data, the model estimated automatically peak hour traffic | U7: Based on these data, the model estimated automatically peak hour traffic | AD7: are no longer current value but nominal value in year i. | AM7: table are no longer current value but nominal value. | AW7: If you would like to make any change, go back to the sheet "Input-Start". | BS7: If you would like to make any change, go back to the sheet "Input-Start".
C8: and ETC Split in between by interpolation. | L8: volume, duration of peak period, and D factor for each year. | U8: volume, duration of peak period, and D factor. | AD8: Based on these data, the model estimates continuing costs automatically. | AM8: Based on these data, the model estimated continuing cost automatically. | BF8: Payment Split
C9: Please make reasonable adjustions in blue cells. | L9: a) Peak Hour Volume (PHV): assume that ATV/PHV remains constant over | U9: a) Peak Hour Volume (PHV) - assume that ATV/PHV remains constant over | AD9: For the knowledge of estimation, check the footnote right below the table. | AM9: For the knowledge of estimation, check the footnote right below the table. | AW9: Transaction Time (sec) | BS9: Assumptions about Fuel Consumption
L10: the analysis period. Thus, peak hour volume in year i is estimated by | U10: the analysis period. Thus, peak hour volume in year i is estimated by | AD10: Please make reasonable adjustions in blue cells. | AM10: Please make reasonable adjustions in blue cells. | AX10: Cash | AZ10: ='Input-Start'!AI17 -> 7 | BG10: Year | BH10: Baseline | BJ10: ETC Alternative
C11: Estimated Annual Traffic Volume (ATV) | L11: estimated annual traffic volume times ATV/PHV. | U11: estimated annual traffic volume times ATV/PHV. | AX11: Ticket | AZ11: ='Input-Start'!AI18 -> 4.5 | BH11: Manual Users | BJ11: Manual Users | BL11: ETC Users | BS11: Average Milage of Consuming one Gallon of Fuel | BV11: ='Input-Start'!BA12 -> 25
L12: b) ATV/PHV - the ratio of annual traffic volume over peak hour volume. | U12: b) ATV/PHV - the ratio of annual traffic volume over peak hour volume. | AD12: Year | AE12: One-Time Costs | AF12: Continuing Costs: | AM12: Year | AN12: Capital Investment | AO12: Continuing Costs: | AX12: ETC (headway) | AZ12: ='Input-Start'!AI19 -> 2.4 | BH12: Cash | BI12: Ticket | BJ12: Cash | BK12: Ticket | BL12: Cash &Checks | BM12: Credit Card | BS12: Fuel Price per Gallon | BV12: ='Input-Start'!BA13 -> 1.1
D13: Year | E13: Traffic Vol. | F13: ETC Split | L13: c) Duration of Peak Period (T) in the morning peak in Based Year, hrs/day. | U13: c) Duration of Peak Period (T) in the evening peak in Based Year, hrs/day | AF13: Staff* | AG13: Operations/Materials | AH13: Other | AO13: One-Time Costs | AP13: Staff | AQ13: Operations/Materials | AR13: Other | AW13: ETC Account Fact | BG13: Base | BH13: ='Input-Start'!AH22 -> 0.83 | BI13: =1-BH13 -> 0.17 | BJ13: ='Input-Start'!AH25 -> 0.83 | BK13: =1-BJ13 -> 0.17 | BL13: ='Input-Start'!AH28 -> 0.64 | BM13: =1-BL13 -> 0.36 | BS13: Emission Rates during Acceleration (grams/gallon)
D14: Base | E14: ='Input-Start'!F22 -> 19016173 | F14: ='Input-Start'!F23 -> 0 | L14: d) Direction Factor (D) during the morning peak in Base Year | U14: d) Direction Factor (D) during the evening peak in Base Year | AD14: Base | AE14: ='Input-Start'!N20 -> 0 | AF14: =Cost_PY*('Input-Start'!BA36+PY_for_Inf) -> 4004650 | AG14: 8356.16 | AH14: 297120 | AM14: Base | AN14: ='Input-Start'!W19 -> 3009340 | AO14: ='Input-Start'!X19 -> 0 | AP14: =Cost_PY*('Input-Start'!BA36+PY_for_Inf) -> 4004650 | AQ14: 8356.16 | AR14: 301760 | AW14: Cash & Checks | BG14: 1 | BH14: =BH$13+(BH$33-BH$13)*$D15/$D$34 -> 0.83 | BI14: =1-BH14 -> 0.17 | BJ14: =BJ$13+(BJ$33-BJ$13)*$D15/$D$34 -> 0.8385 | BK14: =1-BJ14 -> 0.1615 | BL14: =BL$13+(BL$33-BL$13)*$D15/$D$34 -> 0.64 | BM14: =1-BL14 -> 0.36 | BT14: Nox | BV14: ='Input-Start'!BA15 -> 24.7
D15: 1 | E15: =E$14+(E$34-E$14)*$D15/$D$34 -> 19565364 | F15: 0.06 | L15: Please make reasonable adjustions in blue cells. | U15: Please make reasonable adjustions in blue cells. | AD15: 1 | AE15: ='Input-Start'!N21^(1+Inflation_Rate)^Year -> 0 | AF15: =Cost_PY*(PY_for_Inf+PY!$L7)*(1+Inflation_Rate)^Year -> 4230053.2 | AG15: 9390.3712 | AH15: 302720 | AM15: 1 | AN15: ='Input-Start'!W20*(1+Inflation_Rate)^Year -> 0 | AO15: ='Input-Start'!X20*(1+Inflation_Rate)^'Input-Detail'!$AM15 -> 238842.84 | AP15: =Cost_PY*(PY_for_Inf+PY!$Q7)*(1+Inflation_Rate)^Year -> 3965664.8 | AQ15: 9390.4 | AR15: 325760 | AX15: Avg. Tags per Accout | AZ15: ='Input-Start'!AI32 -> 1.35 | BG15: 2 | BH15: =BH$13+(BH$33-BH$13)*$D16/$D$34 -> 0.83 | BI15: =1-BH15 -> 0.17 | BJ15: =BJ$13+(BJ$33-BJ$13)*$D16/$D$34 -> 0.847 | BK15: =1-BJ15 -> 0.153 | BL15: =BL$13+(BL$33-BL$13)*$D16/$D$34 -> 0.64 | BM15: =1-BL15 -> 0.36 | BT15: HC | BV15: ='Input-Start'!BA16 -> 9.5
D16: 2 | E16: =E$14+(E$34-E$14)*$D16/$D$34 -> 20114556 | F16: 0.15 | AD16: 2 | AE16: ='Input-Start'!N22^(1+Inflation_Rate)^Year -> 0 | AF16: =Cost_PY*(PY_for_Inf+PY!$L8)*(1+Inflation_Rate)^Year -> 4465376.4 | AG16: 10586.833 | AH16: 308800 | AM16: 2 | AN16: ='Input-Start'!W21*(1+Inflation_Rate)^Year -> 0 | AO16: ='Input-Start'!X21*(1+Inflation_Rate)^'Input-Detail'!$AM16 -> 259818.81 | AP16: =Cost_PY*(PY_for_Inf+PY!$Q8)*(1+Inflation_Rate)^Year -> 3829158.8 | AQ16: 3600 | AR16: 122080 | AX16: Avg. Usage per Year | AZ16: ='Input-Start'!AI33 -> 160 | BG16: 3 | BH16: =BH$13+(BH$33-BH$13)*$D17/$D$34 -> 0.83 | BI16: =1-BH16 -> 0.17 | BJ16: =BJ$13+(BJ$33-BJ$13)*$D17/$D$34 -> 0.8555 | BK16: =1-BJ16 -> 0.1445 | BL16: =BL$13+(BL$33-BL$13)*$D17/$D$34 -> 0.64 | BM16: =1-BL16 -> 0.36 | BT16: CO | BV16: ='Input-Start'!BA17 -> 209
D17: 3 | E17: =E$14+(E$34-E$14)*$D17/$D$34 -> 20663747 | F17: 0.2 | L17: Year | M17: PHV | N17: ATV/PHV | O17: T (hr) | P17: K | U17: Year | V17: PHV | W17: ATV/PHV | X17: T (hr) | Y17: K | AD17: 3 | AE17: ='Input-Start'!N23^(1+Inflation_Rate)^Year -> 0 | AF17: =Cost_PY*(PY_for_Inf+PY!$L9)*(1+Inflation_Rate)^Year -> 4711012 | AG17: 11974.875 | AH17: 315200 | AM17: 3 | AN17: ='Input-Start'!W22*(1+Inflation_Rate)^Year -> 0 | AO17: ='Input-Start'!X22*(1+Inflation_Rate)^'Input-Detail'!$AM17 -> 281838.38 | AP17: =Cost_PY*(PY_for_Inf+PY!$Q9)*(1+Inflation_Rate)^Year -> 3828865.2 | AQ17: 3780 | AR17: 133760 | AX17: Deposits | AZ17: ='Input-Start'!AI34 -> 30 | BG17: 4 | BH17: =BH$13+(BH$33-BH$13)*$D18/$D$34 -> 0.83 | BI17: =1-BH17 -> 0.17 | BJ17: =BJ$13+(BJ$33-BJ$13)*$D18/$D$34 -> 0.864 | BK17: =1-BJ17 -> 0.136 | BL17: =BL$13+(BL$33-BL$13)*$D18/$D$34 -> 0.64 | BM17: =1-BL17 -> 0.36 | BS17: Emission Rates during Idling (grams/minute)
D18: 4 | E18: =E$14+(E$34-E$14)*$D18/$D$34 -> 21212938 | F18: 0.25 | L18: Base | M18: ='Input-Start'!F27 -> 8200 | N18: =E14/M18 -> 2319.0455 | O18: ='Input-Start'!F28 -> 2 | P18: ='Input-Start'!F29 -> 0.3 | U18: Base | V18: ='Input-Start'!G27 -> 8200 | W18: =E14/V18 -> 2319.0455 | X18: ='Input-Start'!G28 -> 2 | Y18: ='Input-Start'!G29 -> 0.7 | AD18: 4 | AE18: ='Input-Start'!N24^(1+Inflation_Rate)^Year -> 0 | AF18: =Cost_PY*(PY_for_Inf+PY!$L10)*(1+Inflation_Rate)^Year -> 4967366.8 | AG18: 13589.472 | AH18: 322240 | AM18: 4 | AN18: ='Input-Start'!W23*(1+Inflation_Rate)^Year -> 0 | AO18: ='Input-Start'!X23*(1+Inflation_Rate)^'Input-Detail'!$AM18 -> 304945.28 | AP18: =Cost_PY*(PY_for_Inf+PY!$Q10)*(1+Inflation_Rate)^Year -> 3770571.1 | AQ18: 3969.04 | AR18: 133920 | AX18: Avg. Balance other than Deposit | AZ18: ='Input-Start'!AI35 -> 20 | BG18: 5 | BH18: =BH$13+(BH$33-BH$13)*$D19/$D$34 -> 0.83 | BI18: =1-BH18 -> 0.17 | BJ18: =BJ$13+(BJ$33-BJ$13)*$D19/$D$34 -> 0.8725 | BK18: =1-BJ18 -> 0.1275 | BL18: =BL$13+(BL$33-BL$13)*$D19/$D$34 -> 0.64 | BM18: =1-BL18 -> 0.36 | BT18: Nox | BV18: ='Input-Start'!BA19 -> 0
D19: 5 | E19: =E$14+(E$34-E$14)*$D19/$D$34 -> 21762130 | F19: 0.3 | L19: 1 | M19: =E15/$N$18 -> 8436.8178 | N19: =E15/M19 -> 2319.0455 | O19: =O18 -> 2 | P19: =P18 -> 0.3 | U19: 1 | V19: =E15/$W$18 -> 8436.8178 | W19: =E15/V19 -> 2319.0455 | X19: =X18 -> 2 | Y19: =Y18 -> 0.7 | AD19: 5 | AE19: ='Input-Start'!N25^(1+Inflation_Rate)^Year -> 0 | AF19: =Cost_PY*(PY_for_Inf+PY!$L11)*(1+Inflation_Rate)^Year -> 5234863.1 | AG19: 15472.362 | AH19: 329760 | AM19: 5 | AN19: ='Input-Start'!W24*(1+Inflation_Rate)^Year -> 0 | AO19: ='Input-Start'!X24*(1+Inflation_Rate)^'Input-Detail'!$AM19 -> 329184.95 | AP19: =Cost_PY*(PY_for_Inf+PY!$Q11)*(1+Inflation_Rate)^Year -> 3737811.1 | AQ19: 4167.44 | AR19: 134080 | AW19: Credit Card | BG19: 6 | BH19: =BH$13+(BH$33-BH$13)*$D20/$D$34 -> 0.83 | BI19: =1-BH19 -> 0.17 | BJ19: =BJ$13+(BJ$33-BJ$13)*$D20/$D$34 -> 0.881 | BK19: =1-BJ19 -> 0.119 | BL19: =BL$13+(BL$33-BL$13)*$D20/$D$34 -> 0.64 | BM19: =1-BL19 -> 0.36 | BT19: HC | BV19: ='Input-Start'!BA20 -> 0.15
D20: 6 | E20: =E$14+(E$34-E$14)*$D20/$D$34 -> 22311321 | F20: 0.35 | L20: 2 | M20: =E16/$N$18 -> 8673.6357 | N20: =E16/M20 -> 2319.0455 | O20: =O19 -> 2 | P20: =P19 -> 0.3 | U20: 2 | V20: =E16/$W$18 -> 8673.6357 | W20: =E16/V20 -> 2319.0455 | X20: =X19 -> 2 | Y20: =Y19 -> 0.7 | AD20: 6 | AE20: ='Input-Start'!N26^(1+Inflation_Rate)^Year -> 0 | AF20: =Cost_PY*(PY_for_Inf+PY!$L12)*(1+Inflation_Rate)^Year -> 5513938.4 | AG20: 17673.38 | AH20: 339652.8 | AM20: 6 | AN20: ='Input-Start'!W25*(1+Inflation_Rate)^Year -> 0 | AO20: ='Input-Start'!X25*(1+Inflation_Rate)^'Input-Detail'!$AM20 -> 354604.55 | AP20: =Cost_PY*(PY_for_Inf+PY!$Q12)*(1+Inflation_Rate)^Year -> 3687489 | AQ20: 4375.812 | AR20: 138102.4 | AX20: Avg. Tags per Accout | AZ20: ='Input-Start'!AI37 -> 1.35 | BG20: 7 | BH20: =BH$13+(BH$33-BH$13)*$D21/$D$34 -> 0.83 | BI20: =1-BH20 -> 0.17 | BJ20: =BJ$13+(BJ$33-BJ$13)*$D21/$D$34 -> 0.8895 | BK20: =1-BJ20 -> 0.1105 | BL20: =BL$13+(BL$33-BL$13)*$D21/$D$34 -> 0.64 | BM20: =1-BL20 -> 0.36 | BT20: CO | BV20: ='Input-Start'!BA21 -> 2.5
D21: 7 | E21: =E$14+(E$34-E$14)*$D21/$D$34 -> 22860512 | F21: 0.4 | L21: 3 | M21: =E17/$N$18 -> 8910.4535 | N21: =E17/M21 -> 2319.0455 | O21: =O20 -> 2 | P21: =P20 -> 0.3 | U21: 3 | V21: =E17/$W$18 -> 8910.4535 | W21: =E17/V21 -> 2319.0455 | X21: =X20 -> 2 | Y21: =Y20 -> 0.7 | AD21: 7 | AE21: ='Input-Start'!N27^(1+Inflation_Rate)^Year -> 0 | AF21: =Cost_PY*(PY_for_Inf+PY!$L13)*(1+Inflation_Rate)^Year -> 5805047 | AG21: 20252.059 | AH21: 349842.38 | AM21: 7 | AN21: ='Input-Start'!W26*(1+Inflation_Rate)^Year -> 0 | AO21: ='Input-Start'!X26*(1+Inflation_Rate)^'Input-Detail'!$AM21 -> 381253.05 | AP21: =Cost_PY*(PY_for_Inf+PY!$Q13)*(1+Inflation_Rate)^Year -> 3571189.9 | AQ21: 4594.6026 | AR21: 142245.47 | AX21: Avg. Usage per Year | AZ21: ='Input-Start'!AI38 -> 160 | BG21: 8 | BH21: =BH$13+(BH$33-BH$13)*$D22/$D$34 -> 0.83 | BI21: =1-BH21 -> 0.17 | BJ21: =BJ$13+(BJ$33-BJ$13)*$D22/$D$34 -> 0.898 | BK21: =1-BJ21 -> 0.102 | BL21: =BL$13+(BL$33-BL$13)*$D22/$D$34 -> 0.64 | BM21: =1-BL21 -> 0.36 | BS21: Cost of Air Polution ($/kg of pollutant)
D22: 8 | E22: =E$14+(E$34-E$14)*$D22/$D$34 -> 23409704 | F22: 0.45 | L22: 4 | M22: =E18/$N$18 -> 9147.2714 | N22: =E18/M22 -> 2319.0455 | O22: =O21 -> 2 | P22: =P21 -> 0.3 | U22: 4 | V22: =E18/$W$18 -> 9147.2714 | W22: =E18/V22 -> 2319.0455 | X22: =X21 -> 2 | Y22: =Y21 -> 0.7 | AD22: 8 | AE22: ='Input-Start'!N28^(1+Inflation_Rate)^Year -> 0 | AF22: =Cost_PY*(PY_for_Inf+PY!$L14)*(1+Inflation_Rate)^Year -> 6108659.4 | AG22: 23279.555 | AH22: 360337.66 | AM22: 8 | AN22: ='Input-Start'!W27*(1+Inflation_Rate)^Year -> 0 | AO22: ='Input-Start'!X27*(1+Inflation_Rate)^'Input-Detail'!$AM22 -> 409181.32 | AP22: =Cost_PY*(PY_for_Inf+PY!$Q14)*(1+Inflation_Rate)^Year -> 3480083.3 | AQ22: 4824.3327 | AR22: 146512.84 | AX22: Deposits | AZ22: ='Input-Start'!AI39 -> 0 | BG22: 9 | BH22: =BH$13+(BH$33-BH$13)*$D23/$D$34 -> 0.83 | BI22: =1-BH22 -> 0.17 | BJ22: =BJ$13+(BJ$33-BJ$13)*$D23/$D$34 -> 0.9065 | BK22: =1-BJ22 -> 0.0935 | BL22: =BL$13+(BL$33-BL$13)*$D23/$D$34 -> 0.64 | BM22: =1-BL22 -> 0.36 | BT22: Nox | BV22: ='Input-Start'!BA23 -> 1.275
D23: 9 | E23: =E$14+(E$34-E$14)*$D23/$D$34 -> 23958895 | F23: 0.5 | L23: 5 | M23: =E19/$N$18 -> 9384.0892 | N23: =E19/M23 -> 2319.0455 | O23: =O22 -> 2 | P23: =P22 -> 0.3 | U23: 5 | V23: =E19/$W$18 -> 9384.0892 | W23: =E19/V23 -> 2319.0455 | X23: =X22 -> 2 | Y23: =Y22 -> 0.7 | AD23: 9 | AE23: ='Input-Start'!N29^(1+Inflation_Rate)^Year -> 0 | AF23: =Cost_PY*(PY_for_Inf+PY!$L15)*(1+Inflation_Rate)^Year -> 6425264.1 | AG23: 26840.945 | AH23: 371147.79 | AM23: 9 | AN23: ='Input-Start'!W28*(1+Inflation_Rate)^Year -> 0 | AO23: ='Input-Start'!X28*(1+Inflation_Rate)^'Input-Detail'!$AM23 -> 438442.16 | AP23: =Cost_PY*(PY_for_Inf+PY!$Q15)*(1+Inflation_Rate)^Year -> 3366961.8 | AQ23: 5065.5494 | AR23: 150908.22 | AX23: Avg. Balance other than Deposit | AZ23: ='Input-Start'!AI40 -> 20 | BG23: 10 | BH23: =BH$13+(BH$33-BH$13)*$D24/$D$34 -> 0.83 | BI23: =1-BH23 -> 0.17 | BJ23: =BJ$13+(BJ$33-BJ$13)*$D24/$D$34 -> 0.915 | BK23: =1-BJ23 -> 0.085 | BL23: =BL$13+(BL$33-BL$13)*$D24/$D$34 -> 0.64 | BM23: =1-BL23 -> 0.36 | BT23: HC | BV23: ='Input-Start'!BA24 -> 1.275
D24: 10 | E24: =E$14+(E$34-E$14)*$D24/$D$34 -> 24508086 | F24: 0.55 | L24: 6 | M24: =E20/$N$18 -> 9620.9071 | N24: =E20/M24 -> 2319.0455 | O24: =O23 -> 2 | P24: =P23 -> 0.3 | U24: 6 | V24: =E20/$W$18 -> 9620.9071 | W24: =E20/V24 -> 2319.0455 | X24: =X23 -> 2 | Y24: =Y23 -> 0.7 | AD24: 10 | AE24: ='Input-Start'!N30^(1+Inflation_Rate)^Year -> 0 | AF24: =Cost_PY*(PY_for_Inf+PY!$L16)*(1+Inflation_Rate)^Year -> 6755367.3 | AG24: 31038 | AH24: 382282.22 | AM24: 10 | AN24: ='Input-Start'!W29*(1+Inflation_Rate)^Year -> 0 | AO24: ='Input-Start'!X29*(1+Inflation_Rate)^'Input-Detail'!$AM24 -> 469090.39 | AP24: =Cost_PY*(PY_for_Inf+PY!$Q16)*(1+Inflation_Rate)^Year -> 3178801.3 | AQ24: 5318.8268 | AR24: 153494.93 | AW24: Configuration of the Toll Plaza | BG24: 11 | BH24: =BH$13+(BH$33-BH$13)*$D25/$D$34 -> 0.83 | BI24: =1-BH24 -> 0.17 | BJ24: =BJ$13+(BJ$33-BJ$13)*$D25/$D$34 -> 0.9235 | BK24: =1-BJ24 -> 0.0765 | BL24: =BL$13+(BL$33-BL$13)*$D25/$D$34 -> 0.64 | BM24: =1-BL24 -> 0.36 | BT24: CO | BV24: ='Input-Start'!BA25 -> 0.0063
D25: 11 | E25: =E$14+(E$34-E$14)*$D25/$D$34 -> 25057278 | F25: 0.6 | L25: 7 | M25: =E21/$N$18 -> 9857.7249 | N25: =E21/M25 -> 2319.0455 | O25: =O24 -> 2 | P25: =P24 -> 0.3 | U25: 7 | V25: =E21/$W$18 -> 9857.7249 | W25: =E21/V25 -> 2319.0455 | X25: =X24 -> 2 | Y25: =Y24 -> 0.7 | AD25: 11 | AE25: ='Input-Start'!N31^(1+Inflation_Rate)^Year -> 0 | AF25: =Cost_PY*(PY_for_Inf+PY!$L17)*(1+Inflation_Rate)^Year -> 7099494 | AG25: 32589.9 | AH25: 393750.69 | AM25: 11 | AN25: ='Input-Start'!W30*(1+Inflation_Rate)^Year -> 0 | AO25: ='Input-Start'!X30*(1+Inflation_Rate)^'Input-Detail'!$AM25 -> 501182.91 | AP25: =Cost_PY*(PY_for_Inf+PY!$Q17)*(1+Inflation_Rate)^Year -> 3015101 | AQ25: 5584.7682 | AR25: 158099.78 | AX25: Total Number of Lanes | AZ25: ='Input-Start'!AR16 -> 12 | BG25: 12 | BH25: =BH$13+(BH$33-BH$13)*$D26/$D$34 -> 0.83 | BI25: =1-BH25 -> 0.17 | BJ25: =BJ$13+(BJ$33-BJ$13)*$D26/$D$34 -> 0.932 | BK25: =1-BJ25 -> 0.068 | BL25: =BL$13+(BL$33-BL$13)*$D26/$D$34 -> 0.64 | BM25: =1-BL25 -> 0.36
D26: 12 | E26: =E$14+(E$34-E$14)*$D26/$D$34 -> 25606469 | F26: 0.65 | L26: 8 | M26: =E22/$N$18 -> 10094.543 | N26: =E22/M26 -> 2319.0455 | O26: =O25 -> 2 | P26: =P25 -> 0.3 | U26: 8 | V26: =E22/$W$18 -> 10094.543 | W26: =E22/V26 -> 2319.0455 | X26: =X25 -> 2 | Y26: =Y25 -> 0.7 | AD26: 12 | AE26: ='Input-Start'!N32^(1+Inflation_Rate)^Year -> 0 | AF26: =Cost_PY*(PY_for_Inf+PY!$L18)*(1+Inflation_Rate)^Year -> 7458188.4 | AG26: 34219.395 | AH26: 405563.21 | AM26: 12 | AN26: ='Input-Start'!W31*(1+Inflation_Rate)^Year -> 0 | AO26: ='Input-Start'!X31*(1+Inflation_Rate)^'Input-Detail'!$AM26 -> 534778.8 | AP26: =Cost_PY*(PY_for_Inf+PY!$Q18)*(1+Inflation_Rate)^Year -> 2769632.4 | AQ26: 5864.0066 | AR26: 162842.78 | AX26: Ramp Distance prior to the Toll Plaza (miles) | AZ26: ='Input-Start'!AR17 -> 0.2 | BG26: 13 | BH26: =BH$13+(BH$33-BH$13)*$D27/$D$34 -> 0.83 | BI26: =1-BH26 -> 0.17 | BJ26: =BJ$13+(BJ$33-BJ$13)*$D27/$D$34 -> 0.9405 | BK26: =1-BJ26 -> 0.0595 | BL26: =BL$13+(BL$33-BL$13)*$D27/$D$34 -> 0.64 | BM26: =1-BL26 -> 0.36
D27: 13 | E27: =E$14+(E$34-E$14)*$D27/$D$34 -> 26155661 | F27: 0.7 | L27: 9 | M27: =E23/$N$18 -> 10331.361 | N27: =E23/M27 -> 2319.0455 | O27: =O26 -> 2 | P27: =P26 -> 0.3 | U27: 9 | V27: =E23/$W$18 -> 10331.361 | W27: =E23/V27 -> 2319.0455 | X27: =X26 -> 2 | Y27: =Y26 -> 0.7 | AD27: 13 | AE27: ='Input-Start'!N33^(1+Inflation_Rate)^Year -> 0 | AF27: =Cost_PY*(PY_for_Inf+PY!$L19)*(1+Inflation_Rate)^Year -> 7832014.9 | AG27: 35930.365 | AH27: 417730.1 | AM27: 13 | AN27: ='Input-Start'!W32*(1+Inflation_Rate)^Year -> 0 | AO27: ='Input-Start'!X32*(1+Inflation_Rate)^'Input-Detail'!$AM27 -> 569939.38 | AP27: =Cost_PY*(PY_for_Inf+PY!$Q19)*(1+Inflation_Rate)^Year -> 2547863.9 | AQ27: 6157.2069 | AR27: 167728.06 | AX27: Ramp Distance leading from the toll Plaza (miles) | AZ27: ='Input-Start'!AR18 -> 0.2 | BG27: 14 | BH27: =BH$13+(BH$33-BH$13)*$D28/$D$34 -> 0.83 | BI27: =1-BH27 -> 0.17 | BJ27: =BJ$13+(BJ$33-BJ$13)*$D28/$D$34 -> 0.949 | BK27: =1-BJ27 -> 0.051 | BL27: =BL$13+(BL$33-BL$13)*$D28/$D$34 -> 0.64 | BM27: =1-BL27 -> 0.36 | BS27: General Assumptions
D28: 14 | E28: =E$14+(E$34-E$14)*$D28/$D$34 -> 26704852 | F28: 0.75 | L28: 10 | M28: =E24/$N$18 -> 10568.178 | N28: =E24/M28 -> 2319.0455 | O28: =O27 -> 2 | P28: =P27 -> 0.3 | U28: 10 | V28: =E24/$W$18 -> 10568.178 | W28: =E24/V28 -> 2319.0455 | X28: =X27 -> 2 | Y28: =Y27 -> 0.7 | AD28: 14 | AE28: ='Input-Start'!N34^(1+Inflation_Rate)^Year -> 0 | AF28: =Cost_PY*(PY_for_Inf+PY!$L20)*(1+Inflation_Rate)^Year -> 8221558.6 | AG28: 37726.883 | AH28: 430262.01 | AM28: 14 | AN28: ='Input-Start'!W33*(1+Inflation_Rate)^Year -> 0 | AO28: ='Input-Start'!X33*(1+Inflation_Rate)^'Input-Detail'!$AM28 -> 606728.3 | AP28: =Cost_PY*(PY_for_Inf+PY!$Q20)*(1+Inflation_Rate)^Year -> 2237003.9 | AQ28: 6465.0673 | AR28: 172759.9 | BG28: 15 | BH28: =BH$13+(BH$33-BH$13)*$D29/$D$34 -> 0.83 | BI28: =1-BH28 -> 0.17 | BJ28: =BJ$13+(BJ$33-BJ$13)*$D29/$D$34 -> 0.9575 | BK28: =1-BJ28 -> 0.0425 | BL28: =BL$13+(BL$33-BL$13)*$D29/$D$34 -> 0.64 | BM28: =1-BL28 -> 0.36
D29: 15 | E29: =E$14+(E$34-E$14)*$D29/$D$34 -> 27254043 | F29: 0.8 | L29: 11 | M29: =E25/$N$18 -> 10804.996 | N29: =E25/M29 -> 2319.0455 | O29: =O28 -> 2 | P29: =P28 -> 0.3 | U29: 11 | V29: =E25/$W$18 -> 10804.996 | W29: =E25/V29 -> 2319.0455 | X29: =X28 -> 2 | Y29: =Y28 -> 0.7 | AD29: 15 | AE29: ='Input-Start'!N35^(1+Inflation_Rate)^Year -> 0 | AF29: =Cost_PY*(PY_for_Inf+PY!$L21)*(1+Inflation_Rate)^Year -> 8627426.2 | AG29: 39613.227 | AH29: 443169.87 | AM29: 15 | AN29: ='Input-Start'!W34*(1+Inflation_Rate)^Year -> 0 | AO29: ='Input-Start'!X34*(1+Inflation_Rate)^'Input-Detail'!$AM29 -> 645211.6 | AP29: =Cost_PY*(PY_for_Inf+PY!$Q21)*(1+Inflation_Rate)^Year -> 1889277.1 | AQ29: 6788.3206 | AR29: 177942.7 | AW29: Prevailing Travel Speed (mph) | AZ29: ='Input-Start'!AR20 -> 55 | BG29: 16 | BH29: =BH$13+(BH$33-BH$13)*$D30/$D$34 -> 0.83 | BI29: =1-BH29 -> 0.17 | BJ29: =BJ$13+(BJ$33-BJ$13)*$D30/$D$34 -> 0.966 | BK29: =1-BJ29 -> 0.034 | BL29: =BL$13+(BL$33-BL$13)*$D30/$D$34 -> 0.64 | BM29: =1-BL29 -> 0.36 | BS29: Inflation Rate | BV29: ='Input-Start'!BA30 -> 0.03
D30: 16 | E30: =E$14+(E$34-E$14)*$D30/$D$34 -> 27803235 | F30: 0.85 | L30: 12 | M30: =E26/$N$18 -> 11041.814 | N30: =E26/M30 -> 2319.0455 | O30: =O29 -> 2 | P30: =P29 -> 0.3 | U30: 12 | V30: =E26/$W$18 -> 11041.814 | W30: =E26/V30 -> 2319.0455 | X30: =X29 -> 2 | Y30: =Y29 -> 0.7 | AD30: 16 | AE30: ='Input-Start'!N36^(1+Inflation_Rate)^Year -> 0 | AF30: =Cost_PY*(PY_for_Inf+PY!$L22)*(1+Inflation_Rate)^Year -> 9050246.4 | AG30: 41593.888 | AH30: 456464.96 | AM30: 16 | AN30: ='Input-Start'!W35*(1+Inflation_Rate)^Year -> 0 | AO30: ='Input-Start'!X35*(1+Inflation_Rate)^'Input-Detail'!$AM30 -> 685457.85 | AP30: =Cost_PY*(PY_for_Inf+PY!$Q22)*(1+Inflation_Rate)^Year -> 1502273.7 | AQ30: 7127.7367 | AR30: 183280.98 | AW30: Mode Split among ETC Users | BG30: 17 | BH30: =BH$13+(BH$33-BH$13)*$D31/$D$34 -> 0.83 | BI30: =1-BH30 -> 0.17 | BJ30: =BJ$13+(BJ$33-BJ$13)*$D31/$D$34 -> 0.9745 | BK30: =1-BJ30 -> 0.0255 | BL30: =BL$13+(BL$33-BL$13)*$D31/$D$34 -> 0.64 | BM30: =1-BL30 -> 0.36 | BS30: Annual Interest Rate | BV30: ='Input-Start'!BA31 -> 0.06
D31: 17 | E31: =E$14+(E$34-E$14)*$D31/$D$34 -> 28352426 | F31: 0.9 | L31: 13 | M31: =E27/$N$18 -> 11278.632 | N31: =E27/M31 -> 2319.0455 | O31: =O30 -> 2 | P31: =P30 -> 0.3 | U31: 13 | V31: =E27/$W$18 -> 11278.632 | W31: =E27/V31 -> 2319.0455 | X31: =X30 -> 2 | Y31: =Y30 -> 0.7 | AD31: 17 | AE31: ='Input-Start'!N37^(1+Inflation_Rate)^Year -> 0 | AF31: =Cost_PY*(PY_for_Inf+PY!$L23)*(1+Inflation_Rate)^Year -> 9490671.1 | AG31: 43673.583 | AH31: 470158.91 | AM31: 17 | AN31: ='Input-Start'!W36*(1+Inflation_Rate)^Year -> 0 | AO31: ='Input-Start'!X36*(1+Inflation_Rate)^'Input-Detail'!$AM31 -> 727538.18 | AP31: =Cost_PY*(PY_for_Inf+PY!$Q23)*(1+Inflation_Rate)^Year -> 1073458 | AQ31: 7484.1235 | AR31: 188779.41 | AX31: Auto | AZ31: ='Input-Start'!AR23 -> 0.9476 | BG31: 18 | BH31: =BH$13+(BH$33-BH$13)*$D32/$D$34 -> 0.83 | BI31: =1-BH31 -> 0.17 | BJ31: =BJ$13+(BJ$33-BJ$13)*$D32/$D$34 -> 0.983 | BK31: =1-BJ31 -> 0.017 | BL31: =BL$13+(BL$33-BL$13)*$D32/$D$34 -> 0.64 | BM31: =1-BL31 -> 0.36 | BS31: Discount Rate | BV31: ='Input-Start'!BA32 -> 0.03
D32: 18 | E32: =E$14+(E$34-E$14)*$D32/$D$34 -> 28901617 | F32: 0.95 | L32: 14 | M32: =E28/$N$18 -> 11515.45 | N32: =E28/M32 -> 2319.0455 | O32: =O31 -> 2 | P32: =P31 -> 0.3 | U32: 14 | V32: =E28/$W$18 -> 11515.45 | W32: =E28/V32 -> 2319.0455 | X32: =X31 -> 2 | Y32: =Y31 -> 0.7 | AD32: 18 | AE32: ='Input-Start'!N38^(1+Inflation_Rate)^Year -> 0 | AF32: =Cost_PY*(PY_for_Inf+PY!$L24)*(1+Inflation_Rate)^Year -> 9949376.1 | AG32: 45857.262 | AH32: 484263.68 | AM32: 18 | AN32: ='Input-Start'!W37*(1+Inflation_Rate)^Year -> 0 | AO32: ='Input-Start'!X37*(1+Inflation_Rate)^'Input-Detail'!$AM32 -> 771526.42 | AP32: =Cost_PY*(PY_for_Inf+PY!$Q24)*(1+Inflation_Rate)^Year -> 600162.82 | AQ32: 7858.3297 | AR32: 194442.79 | AX32: Truck | AZ32: ='Input-Start'!AR24 -> 0.0511 | BG32: 19 | BH32: =BH$13+(BH$33-BH$13)*$D33/$D$34 -> 0.83 | BI32: =1-BH32 -> 0.17 | BJ32: =BJ$13+(BJ$33-BJ$13)*$D33/$D$34 -> 0.9915 | BK32: =1-BJ32 -> 0.0085 | BL32: =BL$13+(BL$33-BL$13)*$D33/$D$34 -> 0.64 | BM32: =1-BL32 -> 0.36 | BS32: Personal Year (PY)
D33: 19 | E33: =E$14+(E$34-E$14)*$D33/$D$34 -> 29450809 | F33: 0.95 | L33: 15 | M33: =E29/$N$18 -> 11752.268 | N33: =E29/M33 -> 2319.0455 | O33: =O32 -> 2 | P33: =P32 -> 0.3 | U33: 15 | V33: =E29/$W$18 -> 11752.268 | W33: =E29/V33 -> 2319.0455 | X33: =X32 -> 2 | Y33: =Y32 -> 0.7 | AD33: 19 | AE33: ='Input-Start'!N39^(1+Inflation_Rate)^Year -> 0 | AF33: =Cost_PY*(PY_for_Inf+PY!$L25)*(1+Inflation_Rate)^Year -> 10427062 | AG33: 48150.125 | AH33: 498791.59 | AM33: 19 | AN33: ='Input-Start'!W38*(1+Inflation_Rate)^Year -> 0 | AO33: ='Input-Start'!X38*(1+Inflation_Rate)^'Input-Detail'!$AM33 -> 817499.17 | AP33: =Cost_PY*(PY_for_Inf+PY!$Q25)*(1+Inflation_Rate)^Year -> 627127.93 | AQ33: 8251.2461 | AR33: 200276.07 | AX33: Bus | AZ33: ='Input-Start'!AR25 -> 0.0013 | BG33: 20 | BH33: ='Input-Start'!AI22 -> 0.83 | BI33: =1-BH33 -> 0.17 | BJ33: ='Input-Start'!AI25 -> 1 | BK33: =1-BJ33 -> 0 | BL33: ='Input-Start'!AI28 -> 0.64 | BM33: =1-BL33 -> 0.36 | BT33: Hours per Unit Personal Year | BV33: ='Input-Start'!BA34 -> 1768
D34: 20 | E34: ='Input-Start'!G22 -> 30000000 | F34: 0.95 | L34: 16 | M34: =E30/$N$18 -> 11989.085 | N34: =E30/M34 -> 2319.0455 | O34: =O33 -> 2 | P34: =P33 -> 0.3 | U34: 16 | V34: =E30/$W$18 -> 11989.085 | W34: =E30/V34 -> 2319.0455 | X34: =X33 -> 2 | Y34: =Y33 -> 0.7 | AD34: 20 | AE34: ='Input-Start'!N40^(1+Inflation_Rate)^Year -> 0 | AF34: =Cost_PY*(PY_for_Inf+PY!$L26)*(1+Inflation_Rate)^Year -> 10924454 | AG34: 50557.631 | AH34: 513755.34 | AM34: 20 | AN34: ='Input-Start'!W39*(1+Inflation_Rate)^Year -> 0 | AO34: ='Input-Start'!X39*(1+Inflation_Rate)^'Input-Detail'!$AM34 -> 865535.91 | AP34: =Cost_PY*(PY_for_Inf+PY!$Q26)*(1+Inflation_Rate)^Year -> 655170.79 | AQ34: 8663.8085 | AR34: 206284.36 | AW34: Average Vehicle Occupancy | BT34: PY for Information Technology | BV34: ='Input-Start'!BA35 -> 0.11
L35: 17 | M35: =E31/$N$18 -> 12225.903 | N35: =E31/M35 -> 2319.0455 | O35: =O34 -> 2 | P35: =P34 -> 0.3 | U35: 17 | V35: =E31/$W$18 -> 12225.903 | W35: =E31/V35 -> 2319.0455 | X35: =X34 -> 2 | Y35: =Y34 -> 0.7 | AX35: Auto | AZ35: ='Input-Start'!AR27 -> 1.8 | BT35: PY for Program Costs (Toll Collection) | BV35: ='Input-Start'!BA36 -> 61.5
L36: 18 | M36: =E32/$N$18 -> 12462.721 | N36: =E32/M36 -> 2319.0455 | O36: =O35 -> 2 | P36: =P35 -> 0.3 | U36: 18 | V36: =E32/$W$18 -> 12462.721 | W36: =E32/V36 -> 2319.0455 | X36: =X35 -> 2 | Y36: =Y35 -> 0.7 | AX36: Truck | AZ36: ='Input-Start'!AR28 -> 1.1 | BT36: Unit Cost per Personal Year | BV36: ='Input-Start'!BA37 -> 65000
L37: 19 | M37: =E33/$N$18 -> 12699.539 | N37: =E33/M37 -> 2319.0455 | O37: =O36 -> 2 | P37: =P36 -> 0.3 | U37: 19 | V37: =E33/$W$18 -> 12699.539 | W37: =E33/V37 -> 2319.0455 | X37: =X36 -> 2 | Y37: =Y36 -> 0.7 | AX37: Bus | AZ37: ='Input-Start'!AR29 -> 20
L38: 20 | M38: =E34/$N$18 -> 12936.357 | N38: =E34/M38 -> 2319.0455 | O38: =O37 -> 2 | P38: =P37 -> 0.3 | U38: 20 | V38: =E34/$W$18 -> 12936.357 | W38: =E34/V38 -> 2319.0455 | X38: =X37 -> 2 | Y38: =Y37 -> 0.7 | AW38: Time Value for Each Mode ($/hr)
AX39: Auto | AZ39: ='Input-Start'!AR32 -> 12.75
AX40: Truck | AZ40: ='Input-Start'!AR33 -> 33.41
AX41: Bus (per rider) | AZ41: ='Input-Start'!AR34 -> 12.75
AC44: Footnote:
AC45: For costs other than staff:
AC46: C(m,n) of item m in year n = C(m,n-1)*(1+ inflation rate), given the amount of cost (m,o)
AC47: in base year
AC49: For staff costs,
AC50: SC(n) of staff costs in year n =
AC51: ($/PY in base year)*[(PY for technology information)+(PY for toll collection)]*(1+inflation rate)
AC52: Assumpions:
AC53: a. PY needed for technology information doesn't change over time.
AC54: b. PYs needed for toll collection are estimated in sheet "PY" based on traffic level.
AC56: Inflation Rate (If) | AF56: ='Input-Detail'!$BV$29 -> 0.03
AC57: $/PY(unit cost of personal year): | AF57: ='Input-Detail'!$BV$36 -> 65000
AC58: PY for Information Technology: | AF58: =PY_for_Inf -> 0.11

Sheet Results Summary
C3: y Analytical Results
C5: q For 20 years
D6: NPV1 = | E6: PVB2 = | F6: NPC3 = | G6: B/C4 = | H6: IRR5 =
C7: Overall | D7: ='Results-Detail'!S26 -> 1.0237546e+08 | E7: ='Results-Detail'!R26 -> 1.053848e+08 | F7: ='Results-Detail'!Q26 -> 3009340 | G7: =E7/F7 -> 35.019239 | H7: =IRR('Results-Detail'!P5:P25) -> 0.48438116
C8: Toll Agency | D8: ='Results-Detail'!R52 -> 55966011 | E8: ='Results-Detail'!Q52 -> 58975351 | F8: ='Results-Detail'!P52 -> 3009340 | G8: =E8/F8 -> 19.597437
C9: Users | D9: ='Results-Detail'!R78 -> 46345558 | E9: ='Results-Detail'!Q78 -> 46345558 | F9: ='Results-Detail'!P78 -> 0
C10: Community | D10: ='Results-Detail'!R104 -> 63886.949 | E10: ='Results-Detail'!Q104 -> 63886.949 | F10: ='Results-Detail'!P104 -> 0
C11: 1NPV: net present value, NPV = PVB - PVC
C12: 2PVB: present value of benefits
C13: 3PVC: present value of costs
C14: 4B/C: Total benefit over capital investment, B/C = PVB/PVC
C15: 5IRR: Internal Rate of Return
C18: q For 10 years
D20: NPV1 = | E20: PVB2 = | F20: NPC3 = | G20: B/C4 = | H20: IRR5 =
C21: Overall | D21: =SUM('Results-Detail'!S5:S15) -> 21137976 | E21: =SUM('Results-Detail'!R5:R15) -> 24147316 | F21: =SUM('Results-Detail'!Q5:Q15) -> 3009340 | G21: =E21/F21 -> 8.0241234 | H21: =IRR('Results-Detail'!P5:P15) -> 0.44574682
C22: Toll Agency | D22: =SUM('Results-Detail'!R31:R41) -> 11160310 | E22: =SUM('Results-Detail'!Q31:Q41) -> 14169650 | F22: =SUM('Results-Detail'!P31:P41) -> 3009340 | G22: =E22/F22 -> 4.7085574
C23: Users | D23: =SUM('Results-Detail'!R57:R67) -> 9960191.7 | E23: =SUM('Results-Detail'!Q57:Q67) -> 9960191.7 | F23: =SUM('Results-Detail'!P57:P67) -> 0
C24: Community | D24: =SUM('Results-Detail'!R83:R93) -> 17473.878 | E24: =SUM('Results-Detail'!Q83:Q93) -> 17473.878 | F24: =SUM('Results-Detail'!P83:P93) -> 0

Sheet Results-Detail
A2: y Total Cost Streams of Baseline and ETC | E2: y Total Benefit Streams | O2: y Total Net Benefit ($ in base year)
A3: Discount Rate: | C3: ='Input-Detail'!BV31 -> 0.03
A4: Year | B4: Capital Invesment | C4: PVC ($ in Base Year) | E4: Year | F4: DFuel Value | G4: DTime Value | H4: DEnv Value | I4: Agency Cost Reduction | J4: DOperational Revenue | K4: DInterest Gain | L4: Total Benefit | M4: PVB ($ in Base Year) | O4: Year | P4: B-C | Q4: PVC | R4: PVB | S4: NPV
A5: Base | B5: =B31+B57+B83 -> 3009340 | C5: =B5/(1+Discount_Rate)^0 -> 3009340 | E5: Base | F5: =F57 -> 0 | G5: =G57 -> 0 | H5: =F83 -> 0 | I5: =F31 -> -4640 | J5: =G31 -> 0 | K5: =H57 -> 0 | L5: =SUM(F5:K5) -> -4640 | M5: =L5/(1+Discount_Rate)^0 -> -4640 | O5: Base | P5: =L5-B5 -> -3013980 | Q5: =C5 -> 3009340 | R5: =M5 -> -4640 | S5: =R5-Q5 -> -3013980
A6: 1 | B6: =B32+B58+B84 -> 0 | C6: =B6/(1+Discount_Rate)^A6 -> 0 | E6: 1 | F6: =F58 -> 8178.3223 | G6: =G58 -> 97150.891 | H6: =F84 -> 298.93857 | I6: =F32 -> 2505.5121 | J6: =G32 -> 20214.934 | K6: =H58 -> -20214.934 | L6: =SUM(F6:K6) -> 108133.66 | M6: =L6/(1+Discount_Rate)^E6 -> 104984.14 | O6: 1 | P6: =L6-B6 -> 108133.66 | Q6: =C6 -> 0 | R6: =M6 -> 104984.14 | S6: =R6-Q6 -> 104984.14
A7: 2 | B7: =B33+B59+B85 -> 0 | C7: =B7/(1+Discount_Rate)^A7 -> 0 | E7: 2 | F7: =F59 -> 16815.769 | G7: =G59 -> 343912.54 | H7: =F85 -> 682.17609 | I7: =F33 -> 570105.61 | J7: =G33 -> 51955.897 | K7: =H59 -> -51955.897 | L7: =SUM(F7:K7) -> 931516.1 | M7: =L7/(1+Discount_Rate)^E7 -> 878043.26 | O7: 2 | P7: =L7-B7 -> 931516.1 | Q7: =C7 -> 0 | R7: =M7 -> 878043.26 | S7: =R7-Q7 -> 878043.26
A8: 3 | B8: =B34+B60+B86 -> 0 | C8: =B8/(1+Discount_Rate)^A8 -> 0 | E8: 3 | F8: =F60 -> 25912.339 | G8: =G60 -> 530377.59 | H8: =F86 -> 1043.8607 | I8: =F34 -> 789943.26 | J8: =G34 -> 71165.945 | K8: =H60 -> -71165.945 | L8: =SUM(F8:K8) -> 1347277 | M8: =L8/(1+Discount_Rate)^E8 -> 1232949.4 | O8: 3 | P8: =L8-B8 -> 1347277 | Q8: =C8 -> 0 | R8: =M8 -> 1232949.4 | S8: =R8-Q8 -> 1232949.4
A9: 4 | B9: =B35+B61+B87 -> 0 | C9: =B9/(1+Discount_Rate)^A9 -> 0 | E9: 4 | F9: =F61 -> 35468.033 | G9: =G61 -> 776598.07 | H9: =F87 -> 1442.0961 | I9: =F35 -> 1089790.8 | J9: =G35 -> 91321.7 | K9: =H61 -> -91321.7 | L9: =SUM(F9:K9) -> 1903299 | M9: =L9/(1+Discount_Rate)^E9 -> 1691056.5 | O9: 4 | P9: =L9-B9 -> 1903299 | Q9: =C9 -> 0 | R9: =M9 -> 1691056.5 | S9: =R9-Q9 -> 1691056.5
A10: 5 | B10: =B36+B62+B88 -> 0 | C10: =B10/(1+Discount_Rate)^A10 -> 0 | E10: 5 | F10: =F62 -> 45482.851 | G10: =G62 -> 1058900.8 | H10: =F88 -> 1864.1114 | I10: =F36 -> 1374851.9 | J10: =G36 -> 112423.16 | K10: =H62 -> -112423.16 | L10: =SUM(F10:K10) -> 2481099.7 | M10: =L10/(1+Discount_Rate)^E10 -> 2140218.4 | O10: 5 | P10: =L10-B10 -> 2481099.7 | Q10: =C10 -> 0 | R10: =M10 -> 2140218.4 | S10: =R10-Q10 -> 2140218.4
A11: 6 | B11: =B37+B63+B89 -> 0 | C11: =B11/(1+Discount_Rate)^A11 -> 0 | E11: 6 | F11: =F63 -> 55956.793 | G11: =G63 -> 1345197.9 | H11: =F89 -> 2294.8472 | I11: =F37 -> 1686692.9 | J11: =G37 -> 134470.33 | K11: =H63 -> -134470.33 | L11: =SUM(F11:K11) -> 3090142.4 | M11: =L11/(1+Discount_Rate)^E11 -> 2587945.6 | O11: 6 | P11: =L11-B11 -> 3090142.4 | Q11: =C11 -> 0 | R11: =M11 -> 2587945.6 | S11: =R11-Q11 -> 2587945.6
A12: 7 | B12: =B38+B64+B90 -> 0 | C12: =B12/(1+Discount_Rate)^A12 -> 0 | E12: 7 | F12: =F64 -> 66889.859 | G12: =G64 -> 1667968.7 | H12: =F90 -> 2748.1556 | I12: =F38 -> 2075858.4 | J12: =G38 -> 157463.21 | K12: =H64 -> -157463.21 | L12: =SUM(F12:K12) -> 3813465.2 | M12: =L12/(1+Discount_Rate)^E12 -> 3100696.1 | O12: 7 | P12: =L12-B12 -> 3813465.2 | Q12: =C12 -> 0 | R12: =M12 -> 3100696.1 | S12: =R12-Q12 -> 3100696.1
A13: 8 | B13: =B39+B65+B91 -> 0 | C13: =B13/(1+Discount_Rate)^A13 -> 0 | E13: 8 | F13: =F65 -> 78282.05 | G13: =G65 -> 2033817.2 | H13: =F91 -> 3225.7005 | I13: =F39 -> 2451674.9 | J13: =G39 -> 181401.79 | K13: =H65 -> -181401.79 | L13: =SUM(F13:K13) -> 4566999.8 | M13: =L13/(1+Discount_Rate)^E13 -> 3605231.8 | O13: 8 | P13: =L13-B13 -> 4566999.8 | Q13: =C13 -> 0 | R13: =M13 -> 3605231.8 | S13: =R13-Q13 -> 3605231.8
A14: 9 | B14: =B40+B66+B92 -> 0 | C14: =B14/(1+Discount_Rate)^A14 -> 0 | E14: 9 | F14: =F66 -> 90133.364 | G14: =G66 -> 2408482.7 | H14: =F92 -> 3712.6602 | I14: =F40 -> 2861875.1 | J14: =G40 -> 206286.09 | K14: =H66 -> -206286.09 | L14: =SUM(F14:K14) -> 5364203.8 | M14: =L14/(1+Discount_Rate)^E14 -> 4111215.6 | O14: 9 | P14: =L14-B14 -> 5364203.8 | Q14: =C14 -> 0 | R14: =M14 -> 4111215.6 | S14: =R14-Q14 -> 4111215.6
A15: 10 | B15: =B41+B67+B93 -> 0 | C15: =B15/(1+Discount_Rate)^A15 -> 0 | E15: 10 | F15: =F67 -> 102443.8 | G15: =G67 -> 2847232.9 | H15: =F93 -> 4230.4127 | I15: =F41 -> 3361982 | J15: =G41 -> 232116.09 | K15: =H67 -> -232116.09 | L15: =SUM(F15:K15) -> 6315889.2 | M15: =L15/(1+Discount_Rate)^E15 -> 4699614.7 | O15: 10 | P15: =L15-B15 -> 6315889.2 | Q15: =C15 -> 0 | R15: =M15 -> 4699614.7 | S15: =R15-Q15 -> 4699614.7
A16: 11 | B16: =B42+B68+B94 -> 0 | C16: =B16/(1+Discount_Rate)^A16 -> 0 | E16: 11 | F16: =F68 -> 115213.36 | G16: =G68 -> 3303460.8 | H16: =F94 -> 4759.7004 | I16: =F42 -> 3845866.1 | J16: =G42 -> 258891.79 | K16: =H68 -> -258891.79 | L16: =SUM(F16:K16) -> 7269299.9 | M16: =L16/(1+Discount_Rate)^E16 -> 5251496.9 | O16: 11 | P16: =L16-B16 -> 7269299.9 | Q16: =C16 -> 0 | R16: =M16 -> 5251496.9 | S16: =R16-Q16 -> 5251496.9
A17: 12 | B17: =B43+B69+B95 -> 0 | C17: =B17/(1+Discount_Rate)^A17 -> 0 | E17: 12 | F17: =F69 -> 128442.05 | G17: =G69 -> 3810007 | H17: =F95 -> 5312.3 | I17: =F43 -> 4424852.9 | J17: =G43 -> 286613.21 | K17: =H69 -> -286613.21 | L17: =SUM(F17:K17) -> 8368614.3 | M17: =L17/(1+Discount_Rate)^E17 -> 5869577.7 | O17: 12 | P17: =L17-B17 -> 8368614.3 | Q17: =C17 -> 0 | R17: =M17 -> 5869577.7 | S17: =R17-Q17 -> 5869577.7
... A25: 20 | B25: =B51+B77+B103 -> 0 | C25: =B25/(1+Discount_Rate)^A25 -> 0 | E25: 20 | F25: =F77 -> 250800 | G25: =G77 -> 9456912.9 | H25: =F103 -> 10382.358 | I25: =F51 -> 9753112.3 | J25: =G51 -> 490770 | K25: =H77 -> -490770 | L25: =SUM(F25:K25) -> 19471208 | M25: =L25/(1+Discount_Rate)^E25 -> 10780736 | O25: 20 | P25: =L25-B25 -> 19471208 | Q25: =C25 -> 0 | R25: =M25 -> 10780736 | S25: =R25-Q25 -> 10780736
O26: Total | Q26: =SUM(Q5:Q25) -> 3009340 | R26: =SUM(R5:R25) -> 1.053848e+08 | S26: =SUM(S5:S25) -> 1.0237546e+08
A28: a Cost Streams of Toll Agency | E28: a Benefit Streams of Toll Agency | O28: a Net Benefit of Toll Agency ($ in base year)
A30: Year | B30: Capital Investment | C30: PVC ($ in Base Year) | E30: Year | F30: Cost Reduction | G30: DOperational Revenue* | H30: Total Benefit | I30: PVB ($ in Base Year) | O30: Year | P30: PVC | Q30: PVB | R30: NPV
A31: Base | B31: ='Input-Detail'!AN14 -> 3009340 | C31: =B31/(1+Discount_Rate)^0 -> 3009340 | E31: Base | F31: ='Agency Costs Reduction'!L6 -> -4640 | G31: ='Interest Gain'!T6 -> 0 | H31: =SUM(F31:G31) -> -4640 | I31: =H31/(1+Discount_Rate)^0 -> -4640 | O31: Base | P31: =C31 -> 3009340 | Q31: =I31 -> -4640 | R31: =Q31-P31 -> -3013980
A32: 1 | B32: ='Input-Detail'!AN15 -> 0 | C32: =B32/(1+Discount_Rate)^A32 -> 0 | E32: 1 | F32: ='Agency Costs Reduction'!L7 -> 2505.5121 | G32: ='Interest Gain'!T7 -> 20214.934 | H32: =SUM(F32:G32) -> 22720.447 | I32: =H32/(1+Discount_Rate)^E32 -> 22058.686 | O32: 1 | P32: =C32 -> 0 | Q32: =I32 -> 22058.686 | R32: =Q32-P32 -> 22058.686
A33: 2 | B33: ='Input-Detail'!AN16 -> 0 | C33: =B33/(1+Discount_Rate)^A33 -> 0 | E33: 2 | F33: ='Agency Costs Reduction'!L8 -> 570105.61 | G33: ='Interest Gain'!T8 -> 51955.897 | H33: =SUM(F33:G33) -> 622061.51 | I33: =H33/(1+Discount_Rate)^E33 -> 586352.63 | O33: 2 | P33: =C33 -> 0 | Q33: =I33 -> 586352.63 | R33: =Q33-P33 -> 586352.63
A34: 3 | B34: ='Input-Detail'!AN17 -> 0 | C34: =B34/(1+Discount_Rate)^A34 -> 0 | E34: 3 | F34: ='Agency Costs Reduction'!L9 -> 789943.26 | G34: ='Interest Gain'!T9 -> 71165.945 | H34: =SUM(F34:G34) -> 861109.2 | I34: =H34/(1+Discount_Rate)^E34 -> 788036.9 | O34: 3 | P34: =C34 -> 0 | Q34: =I34 -> 788036.9 | R34: =Q34-P34 -> 788036.9
A35: 4 | B35: ='Input-Detail'!AN18 -> 0 | C35: =B35/(1+Discount_Rate)^A35 -> 0 | E35: 4 | F35: ='Agency Costs Reduction'!L10 -> 1089790.8 | G35: ='Interest Gain'!T10 -> 91321.7 | H35: =SUM(F35:G35) -> 1181112.5 | I35: =H35/(1+Discount_Rate)^E35 -> 1049403.2 | O35: 4 | P35: =C35 -> 0 | Q35: =I35 -> 1049403.2 | R35: =Q35-P35 -> 1049403.2
A36: 5 | B36: ='Input-Detail'!AN19 -> 0 | C36: =B36/(1+Discount_Rate)^A36 -> 0 | E36: 5 | F36: ='Agency Costs Reduction'!L11 -> 1374851.9 | G36: ='Interest Gain'!T11 -> 112423.16 | H36: =SUM(F36:G36) -> 1487275.1 | I36: =H36/(1+Discount_Rate)^E36 -> 1282936.6 | O36: 5 | P36: =C36 -> 0 | Q36: =I36 -> 1282936.6 | R36: =Q36-P36 -> 1282936.6
A37: 6 | B37: ='Input-Detail'!AN20 -> 0 | C37: =B37/(1+Discount_Rate)^A37 -> 0 | E37: 6 | F37: ='Agency Costs Reduction'!L12 -> 1686692.9 | G37: ='Interest Gain'!T12 -> 134470.33 | H37: =SUM(F37:G37) -> 1821163.2 | I37: =H37/(1+Discount_Rate)^E37 -> 1525195.5 | O37: 6 | P37: =C37 -> 0 | Q37: =I37 -> 1525195.5 | R37: =Q37-P37 -> 1525195.5
A38: 7 | B38: ='Input-Detail'!AN21 -> 0 | C38: =B38/(1+Discount_Rate)^A38 -> 0 | E38: 7 | F38: ='Agency Costs Reduction'!L13 -> 2075858.4 | G38: ='Interest Gain'!T13 -> 157463.21 | H38: =SUM(F38:G38) -> 2233321.6 | I38: =H38/(1+Discount_Rate)^E38 -> 1815894.8 | O38: 7 | P38: =C38 -> 0 | Q38: =I38 -> 1815894.8 | R38: =Q38-P38 -> 1815894.8
A39: 8 | B39: ='Input-Detail'!AN22 -> 0 | C39: =B39/(1+Discount_Rate)^A39 -> 0 | E39: 8 | F39: ='Agency Costs Reduction'!L14 -> 2451674.9 | G39: ='Interest Gain'!T14 -> 181401.79 | H39: =SUM(F39:G39) -> 2633076.6 | I39: =H39/(1+Discount_Rate)^E39 -> 2078575 | O39: 8 | P39: =C39 -> 0 | Q39: =I39 -> 2078575 | R39: =Q39-P39 -> 2078575
A40: 9 | B40: ='Input-Detail'!AN23 -> 0 | C40: =B40/(1+Discount_Rate)^A40 -> 0 | E40: 9 | F40: ='Agency Costs Reduction'!L15 -> 2861875.1 | G40: ='Interest Gain'!T15 -> 206286.09 | H40: =SUM(F40:G40) -> 3068161.2 | I40: =H40/(1+Discount_Rate)^E40 -> 2351490.1 | O40: 9 | P40: =C40 -> 0 | Q40: =I40 -> 2351490.1 | R40: =Q40-P40 -> 2351490.1
A41: 10 | B41: ='Input-Detail'!AN24 -> 0 | C41: =B41/(1+Discount_Rate)^A41 -> 0 | E41: 10 | F41: ='Agency Costs Reduction'!L16 -> 3361982 | G41: ='Interest Gain'!T16 -> 232116.09 | H41: =SUM(F41:G41) -> 3594098.1 | I41: =H41/(1+Discount_Rate)^E41 -> 2674346.6 | O41: 10 | P41: =C41 -> 0 | Q41: =I41 -> 2674346.6 | R41: =Q41-P41 -> 2674346.6
A42: 11 | B42: ='Input-Detail'!AN25 -> 0 | C42: =B42/(1+Discount_Rate)^A42 -> 0 | E42: 11 | F42: ='Agency Costs Reduction'!L17 -> 3845866.1 | G42: ='Interest Gain'!T17 -> 258891.79 | H42: =SUM(F42:G42) -> 4104757.8 | I42: =H42/(1+Discount_Rate)^E42 -> 2965364.4 | O42: 11 | P42: =C42 -> 0 | Q42: =I42 -> 2965364.4 | R42: =Q42-P42 -> 2965364.4
A43: 12 | B43: ='Input-Detail'!AN26 -> 0 | C43: =B43/(1+Discount_Rate)^A43 -> 0 | E43: 12 | F43: ='Agency Costs Reduction'!L18 -> 4424852.9 | G43: ='Interest Gain'!T18 -> 286613.21 | H43: =SUM(F43:G43) -> 4711466.2 | I43: =H43/(1+Discount_Rate)^E43 -> 3304527.6 | O43: 12 | P43: =C43 -> 0 | Q43: =I43 -> 3304527.6 | R43: =Q43-P43 -> 3304527.6
... A51: 20 | B51: ='Input-Detail'!AN34 -> 0 | C51: =B51/(1+Discount_Rate)^A51 -> 0 | E51: 20 | F51: ='Agency Costs Reduction'!L26 -> 9753112.3 | G51: ='Interest Gain'!T26 -> 490770 | H51: =SUM(F51:G51) -> 10243882 | I51: =H51/(1+Discount_Rate)^E51 -> 5671789.3 | O51: 20 | P51: =C51 -> 0 | Q51: =I51 -> 5671789.3 | R51: =Q51-P51 -> 5671789.3
E52: *DOperational Benefit = the amount of DInterest Gain of users | O52: Total | P52: =SUM(P31:P51) -> 3009340 | Q52: =SUM(Q31:Q51) -> 58975351 | R52: =SUM(R31:R51) -> 55966011
A54: a Cost Streams of Users | E54: a Benefit Streams of Users | O54: a Net Benefit of Users ($ in base year)
A56: Year | B56: Capital Investment | C56: PVC ($ in Base Year) | E56: Year | F56: DFuel Value | G56: DTime Value | H56: DInterest Gain | I56: DTotal | J56: PVB ($ in Base Year) | O56: Year | P56: PVC | Q56: PVB | R56: NPV
A57: Base | B57: 0 | C57: =B57/(1+Discount_Rate)^0 -> 0 | E57: Base | F57: ='Fuel & Emission'!O6 -> 0 | G57: ='Time Value'!P6 -> 0 | H57: =(-1)*'Interest Gain'!T6 -> 0 | I57: =SUM(F57:H57) -> 0 | J57: =I57/(1+Discount_Rate)^0 -> 0 | O57: Base | P57: =C57 -> 0 | Q57: =J57 -> 0 | R57: =Q57-P57 -> 0
A58: 1 | B58: 0 | C58: =B58/(1+Discount_Rate)^A58 -> 0 | E58: 1 | F58: ='Fuel & Emission'!O7 -> 8178.3223 | G58: ='Time Value'!P7 -> 97150.891 | H58: =(-1)*'Interest Gain'!T7 -> -20214.934 | I58: =SUM(F58:H58) -> 85114.279 | J58: =I58/(1+Discount_Rate)^E58 -> 82635.222 | O58: 1 | P58: =C58 -> 0 | Q58: =J58 -> 82635.222 | R58: =Q58-P58 -> 82635.222
A59: 2 | B59: 0 | C59: =B59/(1+Discount_Rate)^A59 -> 0 | E59: 2 | F59: ='Fuel & Emission'!O8 -> 16815.769 | G59: ='Time Value'!P8 -> 343912.54 | H59: =(-1)*'Interest Gain'!T8 -> -51955.897 | I59: =SUM(F59:H59) -> 308772.41 | J59: =I59/(1+Discount_Rate)^E59 -> 291047.61 | O59: 2 | P59: =C59 -> 0 | Q59: =J59 -> 291047.61 | R59: =Q59-P59 -> 291047.61
A60: 3 | B60: 0 | C60: =B60/(1+Discount_Rate)^A60 -> 0 | E60: 3 | F60: ='Fuel & Emission'!O9 -> 25912.339 | G60: ='Time Value'!P9 -> 530377.59 | H60: =(-1)*'Interest Gain'!T9 -> -71165.945 | I60: =SUM(F60:H60) -> 485123.99 | J60: =I60/(1+Discount_Rate)^E60 -> 443957.17 | O60: 3 | P60: =C60 -> 0 | Q60: =J60 -> 443957.17 | R60: =Q60-P60 -> 443957.17
A61: 4 | B61: 0 | C61: =B61/(1+Discount_Rate)^A61 -> 0 | E61: 4 | F61: ='Fuel & Emission'!O10 -> 35468.033 | G61: ='Time Value'!P10 -> 776598.07 | H61: =(-1)*'Interest Gain'!T10 -> -91321.7 | I61: =SUM(F61:H61) -> 720744.4 | J61: =I61/(1+Discount_Rate)^E61 -> 640372.06 | O61: 4 | P61: =C61 -> 0 | Q61: =J61 -> 640372.06 | R61: =Q61-P61 -> 640372.06
A62: 5 | B62: 0 | C62: =B62/(1+Discount_Rate)^A62 -> 0 | E62: 5 | F62: ='Fuel & Emission'!O11 -> 45482.851 | G62: ='Time Value'!P11 -> 1058900.8 | H62: =(-1)*'Interest Gain'!T11 -> -112423.16 | I62: =SUM(F62:H62) -> 991960.52 | J62: =I62/(1+Discount_Rate)^E62 -> 855673.86 | O62: 5 | P62: =C62 -> 0 | Q62: =J62 -> 855673.86 | R62: =Q62-P62 -> 855673.86
A63: 6 | B63: 0 | C63: =B63/(1+Discount_Rate)^A63 -> 0 | E63: 6 | F63: ='Fuel & Emission'!O12 -> 55956.793 | G63: ='Time Value'!P12 -> 1345197.9 | H63: =(-1)*'Interest Gain'!T12 -> -134470.33 | I63: =SUM(F63:H63) -> 1266684.4 | J63: =I63/(1+Discount_Rate)^E63 -> 1060828.2 | O63: 6 | P63: =C63 -> 0 | Q63: =J63 -> 1060828.2 | R63: =Q63-P63 -> 1060828.2
A64: 7 | B64: 0 | C64: =B64/(1+Discount_Rate)^A64 -> 0 | E64: 7 | F64: ='Fuel & Emission'!O13 -> 66889.859 | G64: ='Time Value'!P13 -> 1667968.7 | H64: =(-1)*'Interest Gain'!T13 -> -157463.21 | I64: =SUM(F64:H64) -> 1577395.4 | J64: =I64/(1+Discount_Rate)^E64 -> 1282566.8 | O64: 7 | P64: =C64 -> 0 | Q64: =J64 -> 1282566.8 | R64: =Q64-P64 -> 1282566.8
A65: 8 | B65: 0 | C65: =B65/(1+Discount_Rate)^A65 -> 0 | E65: 8 | F65: ='Fuel & Emission'!O14 -> 78282.05 | G65: ='Time Value'!P14 -> 2033817.2 | H65: =(-1)*'Interest Gain'!T14 -> -181401.79 | I65: =SUM(F65:H65) -> 1930697.5 | J65: =I65/(1+Discount_Rate)^E65 -> 1524110.4 | O65: 8 | P65: =C65 -> 0 | Q65: =J65 -> 1524110.4 | R65: =Q65-P65 -> 1524110.4
A66: 9 | B66: 0 | C66: =B66/(1+Discount_Rate)^A66 -> 0 | E66: 9 | F66: ='Fuel & Emission'!O15 -> 90133.364 | G66: ='Time Value'!P15 -> 2408482.7 | H66: =(-1)*'Interest Gain'!T15 -> -206286.09 | I66: =SUM(F66:H66) -> 2292329.9 | J66: =I66/(1+Discount_Rate)^E66 -> 1756880 | O66: 9 | P66: =C66 -> 0 | Q66: =J66 -> 1756880 | R66: =Q66-P66 -> 1756880
A67: 10 | B67: 0 | C67: =B67/(1+Discount_Rate)^A67 -> 0 | E67: 10 | F67: ='Fuel & Emission'!O16 -> 102443.8 | G67: ='Time Value'!P16 -> 2847232.9 | H67: =(-1)*'Interest Gain'!T16 -> -232116.09 | I67: =SUM(F67:H67) -> 2717560.6 | J67: =I67/(1+Discount_Rate)^E67 -> 2022120.3 | O67: 10 | P67: =C67 -> 0 | Q67: =J67 -> 2022120.3 | R67: =Q67-P67 -> 2022120.3
A68: 11 | B68: 0 | C68: =B68/(1+Discount_Rate)^A68 -> 0 | E68: 11 | F68: ='Fuel & Emission'!O17 -> 115213.36 | G68: ='Time Value'!P17 -> 3303460.8 | H68: =(-1)*'Interest Gain'!T17 -> -258891.79 | I68: =SUM(F68:H68) -> 3159782.4 | J68: =I68/(1+Discount_Rate)^E68 -> 2282694 | O68: 11 | P68: =C68 -> 0 | Q68: =J68 -> 2282694 | R68: =Q68-P68 -> 2282694
A69: 12 | B69: 0 | C69: =B69/(1+Discount_Rate)^A69 -> 0 | E69: 12 | F69: ='Fuel & Emission'!O18 -> 128442.05 | G69: ='Time Value'!P18 -> 3810007 | H69: =(-1)*'Interest Gain'!T18 -> -286613.21 | I69: =SUM(F69:H69) -> 3651835.8 | J69: =I69/(1+Discount_Rate)^E69 -> 2561324.2 | O69: 12 | P69: =C69 -> 0 | Q69: =J69 -> 2561324.2 | R69: =Q69-P69 -> 2561324.2
... A77: 20 | B77: 0 | C77: =B77/(1+Discount_Rate)^A77 -> 0 | E77: 20 | F77: ='Fuel & Emission'!O26 -> 250800 | G77: ='Time Value'!P26 -> 9456912.9 | H77: =(-1)*'Interest Gain'!T26 -> -490770 | I77: =SUM(F77:H77) -> 9216942.9 | J77: =I77/(1+Discount_Rate)^E77 -> 5103197.8 | O77: 20 | P77: =C77 -> 0 | Q77: =J77 -> 5103197.8 | R77: =Q77-P77 -> 5103197.8
O78: Total | P78: =SUM(P57:P77) -> 0 | Q78: =SUM(Q57:Q77) -> 46345558 | R78: =SUM(R57:R77) -> 46345558
A80: a Cost Streams of Community | E80: a Benefit Streams of Community | O80: a Net Benefit of Community ($ in base year)
A82: Year | B82: Capital Investment | C82: PVC ($ in Base Year) | E82: Year | F82: DEnv. Value** | G82: DTotal | H82: PVB | O82: Year | P82: PVC | Q82: PVB | R82: NPV
A83: Base | B83: =0 -> 0 | C83: =B83/(1+Discount_Rate)^0 -> 0 | E83: Base | F83: ='Fuel & Emission'!N6 -> 0 | G83: =SUM(F83) -> 0 | H83: =G83/(1+Discount_Rate)^0 -> 0 | O83: Base | P83: =C83 -> 0 | Q83: =H83 -> 0 | R83: =Q83-P83 -> 0
A84: 1 | B84: =0 -> 0 | C84: =B84/(1+Discount_Rate)^A84 -> 0 | E84: 1 | F84: ='Fuel & Emission'!N7 -> 298.93857 | G84: =SUM(F84) -> 298.93857 | H84: =G84/(1+Discount_Rate)^E84 -> 290.23162 | O84: 1 | P84: =C84 -> 0 | Q84: =H84 -> 290.23162 | R84: =Q84-P84 -> 290.23162
A85: 2 | B85: =0 -> 0 | C85: =B85/(1+Discount_Rate)^A85 -> 0 | E85: 2 | F85: ='Fuel & Emission'!N8 -> 682.17609 | G85: =SUM(F85) -> 682.17609 | H85: =G85/(1+Discount_Rate)^E85 -> 643.0164 | O85: 2 | P85: =C85 -> 0 | Q85: =H85 -> 643.0164 | R85: =Q85-P85 -> 643.0164
A86: 3 | B86: =0 -> 0 | C86: =B86/(1+Discount_Rate)^A86 -> 0 | E86: 3 | F86: ='Fuel & Emission'!N9 -> 1043.8607 | G86: =SUM(F86) -> 1043.8607 | H86: =G86/(1+Discount_Rate)^E86 -> 955.28044 | O86: 3 | P86: =C86 -> 0 | Q86: =H86 -> 955.28044 | R86: =Q86-P86 -> 955.28044
A87: 4 | B87: =0 -> 0 | C87: =B87/(1+Discount_Rate)^A87 -> 0 | E87: 4 | F87: ='Fuel & Emission'!N10 -> 1442.0961 | G87: =SUM(F87) -> 1442.0961 | H87: =G87/(1+Discount_Rate)^E87 -> 1281.2837 | O87: 4 | P87: =C87 -> 0 | Q87: =H87 -> 1281.2837 | R87: =Q87-P87 -> 1281.2837
A88: 5 | B88: =0 -> 0 | C88: =B88/(1+Discount_Rate)^A88 -> 0 | E88: 5 | F88: ='Fuel & Emission'!N11 -> 1864.1114 | G88: =SUM(F88) -> 1864.1114 | H88: =G88/(1+Discount_Rate)^E88 -> 1607.9988 | O88: 5 | P88: =C88 -> 0 | Q88: =H88 -> 1607.9988 | R88: =Q88-P88 -> 1607.9988
A89: 6 | B89: =0 -> 0 | C89: =B89/(1+Discount_Rate)^A89 -> 0 | E89: 6 | F89: ='Fuel & Emission'!N12 -> 2294.8472 | G89: =SUM(F89) -> 2294.8472 | H89: =G89/(1+Discount_Rate)^E89 -> 1921.8984 | O89: 6 | P89: =C89 -> 0 | Q89: =H89 -> 1921.8984 | R89: =Q89-P89 -> 1921.8984
A90: 7 | B90: =0 -> 0 | C90: =B90/(1+Discount_Rate)^A90 -> 0 | E90: 7 | F90: ='Fuel & Emission'!N13 -> 2748.1556 | G90: =SUM(F90) -> 2748.1556 | H90: =G90/(1+Discount_Rate)^E90 -> 2234.502 | O90: 7 | P90: =C90 -> 0 | Q90: =H90 -> 2234.502 | R90: =Q90-P90 -> 2234.502
A91: 8 | B91: =0 -> 0 | C91: =B91/(1+Discount_Rate)^A91 -> 0 | E91: 8 | F91: ='Fuel & Emission'!N14 -> 3225.7005 | G91: =SUM(F91) -> 3225.7005 | H91: =G91/(1+Discount_Rate)^E91 -> 2546.3977 | O91: 8 | P91: =C91 -> 0 | Q91: =H91 -> 2546.3977 | R91: =Q91-P91 -> 2546.3977
A92: 9 | B92: =0 -> 0 | C92: =B92/(1+Discount_Rate)^A92 -> 0 | E92: 9 | F92: ='Fuel & Emission'!N15 -> 3712.6602 | G92: =SUM(F92) -> 3712.6602 | H92: =G92/(1+Discount_Rate)^E92 -> 2845.4449 | O92: 9 | P92: =C92 -> 0 | Q92: =H92 -> 2845.4449 | R92: =Q92-P92 -> 2845.4449
A93: 10 | B93: =0 -> 0 | C93: =B93/(1+Discount_Rate)^A93 -> 0 | E93: 10 | F93: ='Fuel & Emission'!N16 -> 4230.4127 | G93: =SUM(F93) -> 4230.4127 | H93: =G93/(1+Discount_Rate)^E93 -> 3147.8243 | O93: 10 | P93: =C93 -> 0 | Q93: =H93 -> 3147.8243 | R93: =Q93-P93 -> 3147.8243
A94: 11 | B94: =0 -> 0 | C94: =B94/(1+Discount_Rate)^A94 -> 0 | E94: 11 | F94: ='Fuel & Emission'!N17 -> 4759.7004 | G94: =SUM(F94) -> 4759.7004 | H94: =G94/(1+Discount_Rate)^E94 -> 3438.5088 | O94: 11 | P94: =C94 -> 0 | Q94: =H94 -> 3438.5088 | R94: =Q94-P94 -> 3438.5088
A95: 12 | B95: =0 -> 0 | C95: =B95/(1+Discount_Rate)^A95 -> 0 | E95: 12 | F95: ='Fuel & Emission'!N18 -> 5312.3 | G95: =SUM(F95) -> 5312.3 | H95: =G95/(1+Discount_Rate)^E95 -> 3725.9403 | O95: 12 | P95: =C95 -> 0 | Q95: =H95 -> 3725.9403 | R95: =Q95-P95 -> 3725.9403
... A103: 20 | B103: =0 -> 0 | C103: =B103/(1+Discount_Rate)^A103 -> 0 | E103: 20 | F103: ='Fuel & Emission'!N26 -> 10382.358 | G103: =SUM(F103) -> 10382.358 | H103: =G103/(1+Discount_Rate)^E103 -> 5748.4601 | O103: 20 | P103: =C103 -> 0 | Q103: =H103 -> 5748.4601 | R103: =Q103-P103 -> 5748.4601
E104: ** Environmental value is estimated by the value of emission reduction. | O104: Total | P104: =SUM(P83:P103) -> 0 | Q104: =SUM(Q83:Q103) -> 63886.949 | R104: =SUM(R83:R103) -> 63886.949

Sheet Agency Costs Reduction
F2: y Reduction of Operating Costs
A4: Year | B4: Baseline | G4: ETC Alternative | L4: Cost Saving
B5: One-Time | C5: Staff | D5: Operations/Materials | E5: Others | F5: Total | G5: One-Time | H5: Staff | I5: Operations/Materials | J5: Others | K5: Total
A6: Base | B6: ='Input-Detail'!AE14 -> 0 | C6: ='Input-Detail'!AF14 -> 4004650 | D6: ='Input-Detail'!AG14 -> 8356.16 | E6: ='Input-Detail'!AH14 -> 297120 | F6: =SUM(B6:E6) -> 4310126.2 | G6: ='Input-Detail'!AO14 -> 0 | H6: ='Input-Detail'!AP14 -> 4004650 | I6: ='Input-Detail'!AQ14 -> 8356.16 | J6: ='Input-Detail'!AR14 -> 301760 | K6: =SUM(G6:J6) -> 4314766.2 | L6: =F6-K6 -> -4640
A7: 1 | B7: ='Input-Detail'!AE15 -> 0 | C7: ='Input-Detail'!AF15 -> 4230053.2 | D7: ='Input-Detail'!AG15 -> 9390.3712 | E7: ='Input-Detail'!AH15 -> 302720 | F7: =SUM(B7:E7) -> 4542163.6 | G7: ='Input-Detail'!AO15 -> 238842.84 | H7: ='Input-Detail'!AP15 -> 3965664.8 | I7: ='Input-Detail'!AQ15 -> 9390.4 | J7: ='Input-Detail'!AR15 -> 325760 | K7: =SUM(G7:J7) -> 4539658.1 | L7: =F7-K7 -> 2505.5121
A8: 2 | B8: ='Input-Detail'!AE16 -> 0 | C8: ='Input-Detail'!AF16 -> 4465376.4 | D8: ='Input-Detail'!AG16 -> 10586.833 | E8: ='Input-Detail'!AH16 -> 308800 | F8: =SUM(B8:E8) -> 4784763.3 | G8: ='Input-Detail'!AO16 -> 259818.81 | H8: ='Input-Detail'!AP16 -> 3829158.8 | I8: ='Input-Detail'!AQ16 -> 3600 | J8: ='Input-Detail'!AR16 -> 122080 | K8: =SUM(G8:J8) -> 4214657.6 | L8: =F8-K8 -> 570105.61
A9: 3 | B9: ='Input-Detail'!AE17 -> 0 | C9: ='Input-Detail'!AF17 -> 4711012 | D9: ='Input-Detail'!AG17 -> 11974.875 | E9: ='Input-Detail'!AH17 -> 315200 | F9: =SUM(B9:E9) -> 5038186.8 | G9: ='Input-Detail'!AO17 -> 281838.38 | H9: ='Input-Detail'!AP17 -> 3828865.2 | I9: ='Input-Detail'!AQ17 -> 3780 | J9: ='Input-Detail'!AR17 -> 133760 | K9: =SUM(G9:J9) -> 4248243.6 | L9: =F9-K9 -> 789943.26
A10: 4 | B10: ='Input-Detail'!AE18 -> 0 | C10: ='Input-Detail'!AF18 -> 4967366.8 | D10: ='Input-Detail'!AG18 -> 13589.472 | E10: ='Input-Detail'!AH18 -> 322240 | F10: =SUM(B10:E10) -> 5303196.3 | G10: ='Input-Detail'!AO18 -> 304945.28 | H10: ='Input-Detail'!AP18 -> 3770571.1 | I10: ='Input-Detail'!AQ18 -> 3969.04 | J10: ='Input-Detail'!AR18 -> 133920 | K10: =SUM(G10:J10) -> 4213405.5 | L10: =F10-K10 -> 1089790.8
A11: 5 | B11: ='Input-Detail'!AE19 -> 0 | C11: ='Input-Detail'!AF19 -> 5234863.1 | D11: ='Input-Detail'!AG19 -> 15472.362 | E11: ='Input-Detail'!AH19 -> 329760 | F11: =SUM(B11:E11) -> 5580095.4 | G11: ='Input-Detail'!AO19 -> 329184.95 | H11: ='Input-Detail'!AP19 -> 3737811.1 | I11: ='Input-Detail'!AQ19 -> 4167.44 | J11: ='Input-Detail'!AR19 -> 134080 | K11: =SUM(G11:J11) -> 4205243.5 | L11: =F11-K11 -> 1374851.9
A12: 6 | B12: ='Input-Detail'!AE20 -> 0 | C12: ='Input-Detail'!AF20 -> 5513938.4 | D12: ='Input-Detail'!AG20 -> 17673.38 | E12: ='Input-Detail'!AH20 -> 339652.8 | F12: =SUM(B12:E12) -> 5871264.6 | G12: ='Input-Detail'!AO20 -> 354604.55 | H12: ='Input-Detail'!AP20 -> 3687489 | I12: ='Input-Detail'!AQ20 -> 4375.812 | J12: ='Input-Detail'!AR20 -> 138102.4 | K12: =SUM(G12:J12) -> 4184571.7 | L12: =F12-K12 -> 1686692.9
A13: 7 | B13: ='Input-Detail'!AE21 -> 0 | C13: ='Input-Detail'!AF21 -> 5805047 | D13: ='Input-Detail'!AG21 -> 20252.059 | E13: ='Input-Detail'!AH21 -> 349842.38 | F13: =SUM(B13:E13) -> 6175141.4 | G13: ='Input-Detail'!AO21 -> 381253.05 | H13: ='Input-Detail'!AP21 -> 3571189.9 | I13: ='Input-Detail'!AQ21 -> 4594.6026 | J13: ='Input-Detail'!AR21 -> 142245.47 | K13: =SUM(G13:J13) -> 4099283 | L13: =F13-K13 -> 2075858.4
A14: 8 | B14: ='Input-Detail'!AE22 -> 0 | C14: ='Input-Detail'!AF22 -> 6108659.4 | D14: ='Input-Detail'!AG22 -> 23279.555 | E14: ='Input-Detail'!AH22 -> 360337.66 | F14: =SUM(B14:E14) -> 6492276.7 | G14: ='Input-Detail'!AO22 -> 409181.32 | H14: ='Input-Detail'!AP22 -> 3480083.3 | I14: ='Input-Detail'!AQ22 -> 4824.3327 | J14: ='Input-Detail'!AR22 -> 146512.84 | K14: =SUM(G14:J14) -> 4040601.8 | L14: =F14-K14 -> 2451674.9
A15: 9 | B15: ='Input-Detail'!AE23 -> 0 | C15: ='Input-Detail'!AF23 -> 6425264.1 | D15: ='Input-Detail'!AG23 -> 26840.945 | E15: ='Input-Detail'!AH23 -> 371147.79 | F15: =SUM(B15:E15) -> 6823252.9 | G15: ='Input-Detail'!AO23 -> 438442.16 | H15: ='Input-Detail'!AP23 -> 3366961.8 | I15: ='Input-Detail'!AQ23 -> 5065.5494 | J15: ='Input-Detail'!AR23 -> 150908.22 | K15: =SUM(G15:J15) -> 3961377.7 | L15: =F15-K15 -> 2861875.1
A16: 10 | B16: ='Input-Detail'!AE24 -> 0 | C16: ='Input-Detail'!AF24 -> 6755367.3 | D16: ='Input-Detail'!AG24 -> 31038 | E16: ='Input-Detail'!AH24 -> 382282.22 | F16: =SUM(B16:E16) -> 7168687.5 | G16: ='Input-Detail'!AO24 -> 469090.39 | H16: ='Input-Detail'!AP24 -> 3178801.3 | I16: ='Input-Detail'!AQ24 -> 5318.8268 | J16: ='Input-Detail'!AR24 -> 153494.93 | K16: =SUM(G16:J16) -> 3806705.5 | L16: =F16-K16 -> 3361982
A17: 11 | B17: ='Input-Detail'!AE25 -> 0 | C17: ='Input-Detail'!AF25 -> 7099494 | D17: ='Input-Detail'!AG25 -> 32589.9 | E17: ='Input-Detail'!AH25 -> 393750.69 | F17: =SUM(B17:E17) -> 7525834.5 | G17: ='Input-Detail'!AO25 -> 501182.91 | H17: ='Input-Detail'!AP25 -> 3015101 | I17: ='Input-Detail'!AQ25 -> 5584.7682 | J17: ='Input-Detail'!AR25 -> 158099.78 | K17: =SUM(G17:J17) -> 3679968.5 | L17: =F17-K17 -> 3845866.1
A18: 12 | B18: ='Input-Detail'!AE26 -> 0 | C18: ='Input-Detail'!AF26 -> 7458188.4 | D18: ='Input-Detail'!AG26 -> 34219.395 | E18: ='Input-Detail'!AH26 -> 405563.21 | F18: =SUM(B18:E18) -> 7897971 | G18: ='Input-Detail'!AO26 -> 534778.8 | H18: ='Input-Detail'!AP26 -> 2769632.4 | I18: ='Input-Detail'!AQ26 -> 5864.0066 | J18: ='Input-Detail'!AR26 -> 162842.78 | K18: =SUM(G18:J18) -> 3473118 | L18: =F18-K18 -> 4424852.9
... A26: 20 | B26: ='Input-Detail'!AE34 -> 0 | C26: ='Input-Detail'!AF34 -> 10924454 | D26: ='Input-Detail'!AG34 -> 50557.631 | E26: ='Input-Detail'!AH34 -> 513755.34 | F26: =SUM(B26:E26) -> 11488767 | G26: ='Input-Detail'!AO34 -> 865535.91 | H26: ='Input-Detail'!AP34 -> 655170.79 | I26: ='Input-Detail'!AQ34 -> 8663.8085 | J26: ='Input-Detail'!AR34 -> 206284.36 | K26: =SUM(G26:J26) -> 1735654.9 | L26: =F26-K26 -> 9753112.3

Sheet Delay
Z1: Optimal Number of ETC Lanes
B3: 1 Transaction Facts | K3: y Total Random and Stop Delay per Year (hrs) | V3: a) Total Random and Stop Delay in the System during the Evening Peak per Day (hr) | BF3: b) Average Random Delay per Manual User (sec) | CJ3: c) Average Random Delay per ETC User (sec)
H5: Year | I5: Traffic Vol. | J5: ETC (%) | K5: Peak Arrival Rate in the evening | L5: Delay per Day (Baseline) | O5: Delay Per Year* (hr) | P5: Delay per Day (ETC) | S5: Delay Per Year* (hr) | V5: Year | W5: Traffic Vol. | X5: ETC (%) | Y5: PHV | Z5: ATV/PHV | AA5: T (hr) | AB5: K | AC5: Total Arrival Rate | AD5: Number of ETC Lanes | AZ5: Optimal # of ETC Ln* | BA5: Delay per Day**(hr) | BB5: Suggested # of ETC Ln*** | BC5: Delay per Day**(hr) | BF5: Year | BG5: ETC (%) | BH5: Total Arrival Rate | BI5: Arrival Rate for Manual Lanes | BJ5: Number of ETC Lanes | CH5: Mean Transaction Time (sec) | CJ5: Year | CK5: ETC (%) | CL5: Total Arrival Rate | CM5: Arrival Rate for ETC Users | CN5: Number of ETC Lanes | DJ5: Mean headway (sec)
B6: Transaction Time (sec) | L6: Morning | M6: Evening | N6: Total | P6: Morning | Q6: Evening | R6: Total | AD6: Manual Only | AE6: 1 | AF6: 2 | AG6: 3 | AH6: 4 | AI6: 5 | AJ6: 6 | AK6: 7 | AL6: 8 | AM6: 9 | AN6: 10 | AO6: 11 | AP6: 12 | AQ6: 13 | AR6: 14 | AS6: 15 | AT6: 16 | AU6: 17 | AV6: 18 | AW6: 19 | AX6: 20 | AY6: 21 | BJ6: l/sc for no ETC | BK6: Manual Only | BL6: l/sc under ETC | BM6: 1 | BN6: 2 | BO6: 3 | BP6: 4 | BQ6: 5 | BR6: 6 | BS6: 7 | BT6: 8 | BU6: 9 | BV6: 10 | BW6: 11 | BX6: 12 | BY6: 13 | BZ6: 14 | CA6: 15 | CB6: 16 | CC6: 17 | CD6: 18 | CE6: 19 | CF6: 20 | CG6: 21 | CN6: l/sc under ETC | CO6: 1 | CP6: 2 | CQ6: 3 | CR6: 4 | CS6: 5 | CT6: 6 | CU6: 7 | CV6: 8 | CW6: 9 | CX6: 10 | CY6: 11 | CZ6: 12 | DA6: 13 | DB6: 14 | DC6: 15 | DD6: 16 | DE6: 17 | DF6: 18 | DG6: 19 | DH6: 20 | DI6: 21
C7: Cash | D7: ='Input-Detail'!AZ10 -> 7 | H7: Base | I7: ='Input-Detail'!E14 -> 19016173 | J7: ='Input-Detail'!F14 -> 0 | K7: =AC7 -> 5740 | V7: Base | W7: ='Input-Detail'!E14 -> 19016173 | X7: =J7 -> 0 | Y7: ='Input-Detail'!V18 -> 8200 | Z7: ='Input-Detail'!W18 -> 2319.0455 | AA7: ='Input-Detail'!X18 -> 2 | AB7: ='Input-Detail'!Y18 -> 0.7 | AC7: =Y7*AB7 -> 5740 | AD7: =Peak_Time_Eve*$BH7*(3600/K40+BK7)/3600 -> 32.946409 | BF7: Base | BG7: =$X7 -> 0 | BH7: =$AC7 -> 5740 | BI7: =BH7*(1-BG7) -> 5740 | BJ7: =Peak_Arrival_Manual/K40 -> 10.483472 | BK7: =900*Peak_Time_Eve*(BJ7/Total_Lanes-1+SQRT((BJ7/Total_Lanes-1)^2+8*(BJ7/Total_Lanes)/(Peak_Time_Eve*$K40*Total_Lanes))) -> 3.7566264 | BL7: =Peak_Arrival_Manual/N40 -> 10.483472 | BM7: =IF(BM$6<Total_Lanes,900*Peak_Time_Eve*(($BL7/(Total_Lanes-BM$6))-1+SQRT((($BL7/(Total_Lanes-BM$6))-1)^2+8*($BL7/(Total_Lanes-BM$6))/(Peak_Time_Eve*$N40*(Total_Lanes-BM$6)))),"-") -> 11.367139 | BN7: =IF(BN$6<Total_Lanes,900*Peak_Time_Eve*(($BL7/(Total_Lanes-BN$6))-1+SQRT((($BL7/(Total_Lanes-BN$6))-1)^2+8*($BL7/(Total_Lanes-BN$6))/(Peak_Time_Eve*$N40*(Total_Lanes-BN$6)))),"-") -> 187.29857 | BO7: =IF(BO$6<Total_Lanes,900*Peak_Time_Eve*(($BL7/(Total_Lanes-BO$6))-1+SQRT((($BL7/(Total_Lanes-BO$6))-1)^2+8*($BL7/(Total_Lanes-BO$6))/(Peak_Time_Eve*$N40*(Total_Lanes-BO$6)))),"-") -> 598.50746 | BP7: =IF(BP$6<Total_Lanes,900*Peak_Time_Eve*(($BL7/(Total_Lanes-BP$6))-1+SQRT((($BL7/(Total_Lanes-BP$6))-1)^2+8*($BL7/(Total_Lanes-BP$6))/(Peak_Time_Eve*$N40*(Total_Lanes-BP$6)))),"-") -> 1121.0212 | BQ7: =IF(BQ$6<Total_Lanes,900*Peak_Time_Eve*(($BL7/(Total_Lanes-BQ$6))-1+SQRT((($BL7/(Total_Lanes-BQ$6))-1)^2+8*($BL7/(Total_Lanes-BQ$6))/(Peak_Time_Eve*$N40*(Total_Lanes-BQ$6)))),"-") -> 1794.3223 | BR7: =IF(BR$6<Total_Lanes,900*Peak_Time_Eve*(($BL7/(Total_Lanes-BR$6))-1+SQRT((($BL7/(Total_Lanes-BR$6))-1)^2+8*($BL7/(Total_Lanes-BR$6))/(Peak_Time_Eve*$N40*(Total_Lanes-BR$6)))),"-") -> 2692.6432 | BS7: =IF(BS$6<Total_Lanes,900*Peak_Time_Eve*(($BL7/(Total_Lanes-BS$6))-1+SQRT((($BL7/(Total_Lanes-BS$6))-1)^2+8*($BL7/(Total_Lanes-BS$6))/(Peak_Time_Eve*$N40*(Total_Lanes-BS$6)))),"-") -> 3950.6125 | BT7: =IF(BT$6<Total_Lanes,900*Peak_Time_Eve*(($BL7/(Total_Lanes-BT$6))-1+SQRT((($BL7/(Total_Lanes-BT$6))-1)^2+8*($BL7/(Total_Lanes-BT$6))/(Peak_Time_Eve*$N40*(Total_Lanes-BT$6)))),"-") -> 5837.7817 | ... CG7: =IF(CG$6<Total_Lanes,900*Peak_Time_Eve*(($BL7/(Total_Lanes-CG$6))-1+SQRT((($BL7/(Total_Lanes-CG$6))-1)^2+8*($BL7/(Total_Lanes-CG$6))/(Peak_Time_Eve*$N40*(Total_Lanes-CG$6)))),"-") -> - | CH7: =3600/N40 -> 6.575 | CJ7: Base | CK7: =$X7 -> 0 | CL7: =$AC7 -> 5740 | CM7: =CL7*CK7 -> 0
C8: Ticket | D8: ='Input-Detail'!AZ11 -> 4.5 | H8: 1 | I8: ='Input-Detail'!E15 -> 19565364 | J8: ='Input-Detail'!F15 -> 0.06 | K8: =AC8 -> 5905.7725 | L8: =AD55 -> 9.7125238 | M8: =AD8 -> 31.315212 | N8: =SUM(L8:M8) -> 41.027736 | O8: =$S$34*N8 -> 10667.211 | P8: =BC55 -> 9.2617476 | Q8: =BC8 -> 42.619145 | R8: =SUM(P8:Q8) -> 51.880893 | S8: =$S$34*R8 -> 13489.032 | V8: 1 | W8: =W$7+(W$27-W$7)*$V8/20 -> 19565364 | X8: =J8 -> 0.06 | Y8: ='Input-Detail'!E15/Z8 -> 8436.8178 | Z8: =Z7 -> 2319.0455 | AA8: =AA7 -> 2 | AB8: =AB7 -> 0.7 | AC8: =Y8*AB8 -> 5905.7725 | AD8: =Peak_Time_Eve*$BH8*(3600/K41+BK8)/3600 -> 31.315212 | AE8: =IF(AE$6<Total_Lanes,($BI8*($CH8+BM8)+$CM8*CO8)*Peak_Time_Eve/3600,"-") -> 42.619145 | AF8: =IF(AF$6<Total_Lanes,($BI8*($CH8+BN8)+$CM8*CP8)*Peak_Time_Eve/3600,"-") -> 294.86107 | AG8: =IF(AG$6<Total_Lanes,($BI8*($CH8+BO8)+$CM8*CQ8)*Peak_Time_Eve/3600,"-") -> 1485.3494 | AH8: =IF(AH$6<Total_Lanes,($BI8*($CH8+BP8)+$CM8*CR8)*Peak_Time_Eve/3600,"-") -> 3046.4054 | AI8: =IF(AI$6<Total_Lanes,($BI8*($CH8+BQ8)+$CM8*CS8)*Peak_Time_Eve/3600,"-") -> 5060.5627 | AJ8: =IF(AJ$6<Total_Lanes,($BI8*($CH8+BR8)+$CM8*CT8)*Peak_Time_Eve/3600,"-") -> 7748.4772 | AK8: =IF(AK$6<Total_Lanes,($BI8*($CH8+BS8)+$CM8*CU8)*Peak_Time_Eve/3600,"-") -> 11512.76 | AL8: =IF(AL$6<Total_Lanes,($BI8*($CH8+BT8)+$CM8*CV8)*Peak_Time_Eve/3600,"-") -> 17159.958 | ... AY8: =IF(AY$6<Total_Lanes,($BI8*($CH8+CG8)+$CM8*DI8)*Peak_Time_Eve/3600,"-") -> - | AZ8: =SUMIF(AE8:AY8,BA8,$AE$6:$AY$6) -> 1 | BA8: =MIN(AE8:AY8) -> 42.619145 | BB8: =IF((SUMIF($BM6:$CG6,$AZ8,$BM8:$CG8)+$CH8)<(SUMIF($CO6:$DI6,$AZ8,$CO8:$DI8)+$DJ8),AZ8+1,AZ8) -> 1 | BC8: =SUMIF($AE$6:$AY$6,$BB8,$AE8:$AY8) -> 42.619145 | BF8: 1 | BG8: =$X8 -> 0.06 | BH8: =$AC8 -> 5905.7725 | BI8: =BH8*(1-BG8) -> 5551.4261 | BJ8: =Peak_Arrival_Manual/K41 -> 10.139063 | BK8: =900*Peak_Time_Eve*(BJ8/Total_Lanes-1+SQRT((BJ8/Total_Lanes-1)^2+8*(BJ8/Total_Lanes)/(Peak_Time_Eve*$K41*Total_Lanes))) -> 2.9694554 | BL8: =Peak_Arrival_Manual/N41 -> 10.171832 | BM8: =IF(BM$6<Total_Lanes,900*Peak_Time_Eve*(($BL8/(Total_Lanes-BM$6))-1+SQRT((($BL8/(Total_Lanes-BM$6))-1)^2+8*($BL8/(Total_Lanes-BM$6))/(Peak_Time_Eve*$N41*(Total_Lanes-BM$6)))),"-") -> 7.1752558 | BN8: =IF(BN$6<Total_Lanes,900*Peak_Time_Eve*(($BL8/(Total_Lanes-BN$6))-1+SQRT((($BL8/(Total_Lanes-BN$6))-1)^2+8*($BL8/(Total_Lanes-BN$6))/(Peak_Time_Eve*$N41*(Total_Lanes-BN$6)))),"-") -> 88.999541 | BO8: =IF(BO$6<Total_Lanes,900*Peak_Time_Eve*(($BL8/(Total_Lanes-BO$6))-1+SQRT((($BL8/(Total_Lanes-BO$6))-1)^2+8*($BL8/(Total_Lanes-BO$6))/(Peak_Time_Eve*$N41*(Total_Lanes-BO$6)))),"-") -> 475.01059 | BP8: =IF(BP$6<Total_Lanes,900*Peak_Time_Eve*(($BL8/(Total_Lanes-BP$6))-1+SQRT((($BL8/(Total_Lanes-BP$6))-1)^2+8*($BL8/(Total_Lanes-BP$6))/(Peak_Time_Eve*$N41*(Total_Lanes-BP$6)))),"-") -> 981.17091 | BQ8: =IF(BQ$6<Total_Lanes,900*Peak_Time_Eve*(($BL8/(Total_Lanes-BQ$6))-1+SQRT((($BL8/(Total_Lanes-BQ$6))-1)^2+8*($BL8/(Total_Lanes-BQ$6))/(Peak_Time_Eve*$N41*(Total_Lanes-BQ$6)))),"-") -> 1634.2442 | BR8: =IF(BR$6<Total_Lanes,900*Peak_Time_Eve*(($BL8/(Total_Lanes-BR$6))-1+SQRT((($BL8/(Total_Lanes-BR$6))-1)^2+8*($BL8/(Total_Lanes-BR$6))/(Peak_Time_Eve*$N41*(Total_Lanes-BR$6)))),"-") -> 2505.7768 | BS8: =IF(BS$6<Total_Lanes,900*Peak_Time_Eve*(($BL8/(Total_Lanes-BS$6))-1+SQRT((($BL8/(Total_Lanes-BS$6))-1)^2+8*($BL8/(Total_Lanes-BS$6))/(Peak_Time_Eve*$N41*(Total_Lanes-BS$6)))),"-") -> 3726.3118 | BT8: =IF(BT$6<Total_Lanes,900*Peak_Time_Eve*(($BL8/(Total_Lanes-BT$6))-1+SQRT((($BL8/(Total_Lanes-BT$6))-1)^2+8*($BL8/(Total_Lanes-BT$6))/(Peak_Time_Eve*$N41*(Total_Lanes-BT$6)))),"-") -> 5557.3652 | ... CG8: =IF(CG$6<Total_Lanes,900*Peak_Time_Eve*(($BL8/(Total_Lanes-CG$6))-1+SQRT((($BL8/(Total_Lanes-CG$6))-1)^2+8*($BL8/(Total_Lanes-CG$6))/(Peak_Time_Eve*$N41*(Total_Lanes-CG$6)))),"-") -> - | CH8: =3600/N41 -> 6.59625 | CJ8: 1 | CK8: =$X8 -> 0.06 | CL8: =$AC8 -> 5905.7725 | CM8: =CL8*CK8 -> 354.34635 | CN8: =CM8/O40 -> 0.2362309 | CO8: =IF(CO$6<Total_Lanes,900*Peak_Time_Eve*(($CN8/CO$6-1)+SQRT(($CN8/CO$6-1)^2+8*($CN8/CO$6)/(Peak_Time_Eve*$O41*CO$6))),"-") -> 0.74211064 | CP8: =IF(CP$6<Total_Lanes,900*Peak_Time_Eve*(($CN8/CP$6-1)+SQRT(($CN8/CP$6-1)^2+8*($CN8/CP$6)/(Peak_Time_Eve*$O41*CP$6))),"-") -> 0.16071419 | CQ8: =IF(CQ$6<Total_Lanes,900*Peak_Time_Eve*(($CN8/CQ$6-1)+SQRT(($CN8/CQ$6-1)^2+8*($CN8/CQ$6)/(Peak_Time_Eve*$O41*CQ$6))),"-") -> 0.068377935 | CR8: =IF(CR$6<Total_Lanes,900*Peak_Time_Eve*(($CN8/CR$6-1)+SQRT(($CN8/CR$6-1)^2+8*($CN8/CR$6)/(Peak_Time_Eve*$O41*CR$6))),"-") -> 0.037658252 | CS8: =IF(CS$6<Total_Lanes,900*Peak_Time_Eve*(($CN8/CS$6-1)+SQRT(($CN8/CS$6-1)^2+8*($CN8/CS$6)/(Peak_Time_Eve*$O41*CS$6))),"-") -> 0.02380259 | CT8: =IF(CT$6<Total_Lanes,900*Peak_Time_Eve*(($CN8/CT$6-1)+SQRT(($CN8/CT$6-1)^2+8*($CN8/CT$6)/(Peak_Time_Eve*$O41*CT$6))),"-") -> 0.016394118 | CU8: =IF(CU$6<Total_Lanes,900*Peak_Time_Eve*(($CN8/CU$6-1)+SQRT(($CN8/CU$6-1)^2+8*($CN8/CU$6)/(Peak_Time_Eve*$O41*CU$6))),"-") -> 0.011974562 | CV8: =IF(CV$6<Total_Lanes,900*Peak_Time_Eve*(($CN8/CV$6-1)+SQRT(($CN8/CV$6-1)^2+8*($CN8/CV$6)/(Peak_Time_Eve*$O41*CV$6))),"-") -> 0.0091281804 | ... DI8: =IF(DI$6<Total_Lanes,900*Peak_Time_Eve*(($CN8/DI$6-1)+SQRT(($CN8/DI$6-1)^2+8*($CN8/DI$6)/(Peak_Time_Eve*$O41*DI$6))),"-") -> - | DJ8: =3600/O41 -> 2.4
C9: ETC | D9: ='Input-Detail'!AZ12 -> 2.4 | H9: 2 | I9: ='Input-Detail'!E16 -> 20114556 | J9: ='Input-Detail'!F16 -> 0.15 | K9: =AC9 -> 6071.545 | L9: =AD56 -> 9.9681915 | M9: =AD9 -> 28.927349 | N9: =SUM(L9:M9) -> 38.895541 | O9: =$S$34*N9 -> 10112.841 | P9: =BC56 -> 8.7272388 | Q9: =BC9 -> 31.575689 | R9: =SUM(P9:Q9) -> 40.302928 | S9: =$S$34*R9 -> 10478.761 | V9: 2 | W9: =W$7+(W$27-W$7)*$V9/20 -> 20114556 | X9: =J9 -> 0.15 | Y9: ='Input-Detail'!E16/Z9 -> 8673.6357 | Z9: =Z8 -> 2319.0455 | AA9: =AA8 -> 2 | AB9: =AB8 -> 0.7 | AC9: =Y9*AB9 -> 6071.545 | AD9: =Peak_Time_Eve*$BH9*(3600/K42+BK9)/3600 -> 28.927349 | AE9: =IF(AE$6<Total_Lanes,($BI9*($CH9+BM9)+$CM9*CO9)*Peak_Time_Eve/3600,"-") -> 31.575689 | AF9: =IF(AF$6<Total_Lanes,($BI9*($CH9+BN9)+$CM9*CP9)*Peak_Time_Eve/3600,"-") -> 52.239581 | AG9: =IF(AG$6<Total_Lanes,($BI9*($CH9+BO9)+$CM9*CQ9)*Peak_Time_Eve/3600,"-") -> 615.55842 | AH9: =IF(AH$6<Total_Lanes,($BI9*($CH9+BP9)+$CM9*CR9)*Peak_Time_Eve/3600,"-") -> 1952.0326 | AI9: =IF(AI$6<Total_Lanes,($BI9*($CH9+BQ9)+$CM9*CS9)*Peak_Time_Eve/3600,"-") -> 3695.8229 | AJ9: =IF(AJ$6<Total_Lanes,($BI9*($CH9+BR9)+$CM9*CT9)*Peak_Time_Eve/3600,"-") -> 6025.4473 | AK9: =IF(AK$6<Total_Lanes,($BI9*($CH9+BS9)+$CM9*CU9)*Peak_Time_Eve/3600,"-") -> 9288.7631 | AL9: =IF(AL$6<Total_Lanes,($BI9*($CH9+BT9)+$CM9*CV9)*Peak_Time_Eve/3600,"-") -> 14184.785 | ... AY9: =IF(AY$6<Total_Lanes,($BI9*($CH9+CG9)+$CM9*DI9)*Peak_Time_Eve/3600,"-") -> - | AZ9: =SUMIF(AE9:AY9,BA9,$AE$6:$AY$6) -> 1 | BA9: =MIN(AE9:AY9) -> 31.575689 | BB9: =IF((SUMIF($BM7:$CG7,$AZ9,$BM9:$CG9)+$CH9)<(SUMIF($CO7:$DI7,$AZ9,$CO9:$DI9)+$DJ9),AZ9+1,AZ9) -> 1 | BC9: =SUMIF($AE$6:$AY$6,$BB9,$AE9:$AY9) -> 31.575689 | BF9: 2 | BG9: =$X9 -> 0.15 | BH9: =$AC9 -> 6071.545 | BI9: =BH9*(1-BG9) -> 5160.8132 | BJ9: =Peak_Arrival_Manual/K42 -> 9.4256519 | BK9: =900*Peak_Time_Eve*(BJ9/Total_Lanes-1+SQRT((BJ9/Total_Lanes-1)^2+8*(BJ9/Total_Lanes)/(Peak_Time_Eve*$K42*Total_Lanes))) -> 2.0009438 | BL9: =Peak_Arrival_Manual/N42 -> 9.4865782 | BM9: =IF(BM$6<Total_Lanes,900*Peak_Time_Eve*(($BL9/(Total_Lanes-BM$6))-1+SQRT((($BL9/(Total_Lanes-BM$6))-1)^2+8*($BL9/(Total_Lanes-BM$6))/(Peak_Time_Eve*$N42*(Total_Lanes-BM$6)))),"-") -> 3.74267 | BN9: =IF(BN$6<Total_Lanes,900*Peak_Time_Eve*(($BL9/(Total_Lanes-BN$6))-1+SQRT((($BL9/(Total_Lanes-BN$6))-1)^2+8*($BL9/(Total_Lanes-BN$6))/(Peak_Time_Eve*$N42*(Total_Lanes-BN$6)))),"-") -> 11.510447 | BO9: =IF(BO$6<Total_Lanes,900*Peak_Time_Eve*(($BL9/(Total_Lanes-BO$6))-1+SQRT((($BL9/(Total_Lanes-BO$6))-1)^2+8*($BL9/(Total_Lanes-BO$6))/(Peak_Time_Eve*$N42*(Total_Lanes-BO$6)))),"-") -> 208.04252 | BP9: =IF(BP$6<Total_Lanes,900*Peak_Time_Eve*(($BL9/(Total_Lanes-BP$6))-1+SQRT((($BL9/(Total_Lanes-BP$6))-1)^2+8*($BL9/(Total_Lanes-BP$6))/(Peak_Time_Eve*$N42*(Total_Lanes-BP$6)))),"-") -> 674.19787 | BQ9: =IF(BQ$6<Total_Lanes,900*Peak_Time_Eve*(($BL9/(Total_Lanes-BQ$6))-1+SQRT((($BL9/(Total_Lanes-BQ$6))-1)^2+8*($BL9/(Total_Lanes-BQ$6))/(Peak_Time_Eve*$N42*(Total_Lanes-BQ$6)))),"-") -> 1282.4082 | BR9: =IF(BR$6<Total_Lanes,900*Peak_Time_Eve*(($BL9/(Total_Lanes-BR$6))-1+SQRT((($BL9/(Total_Lanes-BR$6))-1)^2+8*($BL9/(Total_Lanes-BR$6))/(Peak_Time_Eve*$N42*(Total_Lanes-BR$6)))),"-") -> 2094.9435 | BS9: =IF(BS$6<Total_Lanes,900*Peak_Time_Eve*(($BL9/(Total_Lanes-BS$6))-1+SQRT((($BL9/(Total_Lanes-BS$6))-1)^2+8*($BL9/(Total_Lanes-BS$6))/(Peak_Time_Eve*$N42*(Total_Lanes-BS$6)))),"-") -> 3233.1323 | BT9: =IF(BT$6<Total_Lanes,900*Peak_Time_Eve*(($BL9/(Total_Lanes-BT$6))-1+SQRT((($BL9/(Total_Lanes-BT$6))-1)^2+8*($BL9/(Total_Lanes-BT$6))/(Peak_Time_Eve*$N42*(Total_Lanes-BT$6)))),"-") -> 4940.7792 | ... CG9: =IF(CG$6<Total_Lanes,900*Peak_Time_Eve*(($BL9/(Total_Lanes-CG$6))-1+SQRT((($BL9/(Total_Lanes-CG$6))-1)^2+8*($BL9/(Total_Lanes-CG$6))/(Peak_Time_Eve*$N42*(Total_Lanes-CG$6)))),"-") -> - | CH9: =3600/N42 -> 6.6175 | CJ9: 2 | CK9: =$X9 -> 0.15 | CL9: =$AC9 -> 6071.545 | CM9: =CL9*CK9 -> 910.73175 | CN9: =CM9/O41 -> 0.6071545 | CO9: =IF(CO$6<Total_Lanes,900*Peak_Time_Eve*(($CN9/CO$6-1)+SQRT(($CN9/CO$6-1)^2+8*($CN9/CO$6)/(Peak_Time_Eve*$O42*CO$6))),"-") -> 3.699594 | CP9: =IF(CP$6<Total_Lanes,900*Peak_Time_Eve*(($CN9/CP$6-1)+SQRT(($CN9/CP$6-1)^2+8*($CN9/CP$6)/(Peak_Time_Eve*$O42*CP$6))),"-") -> 0.52298223 | CQ9: =IF(CQ$6<Total_Lanes,900*Peak_Time_Eve*(($CN9/CQ$6-1)+SQRT(($CN9/CQ$6-1)^2+8*($CN9/CQ$6)/(Peak_Time_Eve*$O42*CQ$6))),"-") -> 0.20297561 | CR9: =IF(CR$6<Total_Lanes,900*Peak_Time_Eve*(($CN9/CR$6-1)+SQRT(($CN9/CR$6-1)^2+8*($CN9/CR$6)/(Peak_Time_Eve*$O42*CR$6))),"-") -> 0.10736707 | CS9: =IF(CS$6<Total_Lanes,900*Peak_Time_Eve*(($CN9/CS$6-1)+SQRT(($CN9/CS$6-1)^2+8*($CN9/CS$6)/(Peak_Time_Eve*$O42*CS$6))),"-") -> 0.06634152 | CT9: =IF(CT$6<Total_Lanes,900*Peak_Time_Eve*(($CN9/CT$6-1)+SQRT(($CN9/CT$6-1)^2+8*($CN9/CT$6)/(Peak_Time_Eve*$O42*CT$6))),"-") -> 0.045033446 | CU9: =IF(CU$6<Total_Lanes,900*Peak_Time_Eve*(($CN9/CU$6-1)+SQRT(($CN9/CU$6-1)^2+8*($CN9/CU$6)/(Peak_Time_Eve*$O42*CU$6))),"-") -> 0.032562213 | CV9: =IF(CV$6<Total_Lanes,900*Peak_Time_Eve*(($CN9/CV$6-1)+SQRT(($CN9/CV$6-1)^2+8*($CN9/CV$6)/(Peak_Time_Eve*$O42*CV$6))),"-") -> 0.02463801 | ... DI9: =IF(DI$6<Total_Lanes,900*Peak_Time_Eve*(($CN9/DI$6-1)+SQRT(($CN9/DI$6-1)^2+8*($CN9/DI$6)/(Peak_Time_Eve*$O42*DI$6))),"-") -> - | DJ9: =3600/O42 -> 2.4
B10: Total Number of Lanes | D10: ='Input-Detail'!AZ25 -> 12 | H10: 3 | I10: ='Input-Detail'!E17 -> 20663747 | J10: ='Input-Detail'!F17 -> 0.2 | K10: =AC10 -> 6237.3175 | L10: =AD57 -> 10.251639 | M10: =AD10 -> 28.76588 | N10: =SUM(L10:M10) -> 39.017519 | O10: =$S$34*N10 -> 10144.555 | P10: =BC57 -> 8.4779968 | Q10: =BC10 -> 34.981802 | R10: =SUM(P10:Q10) -> 43.459799 | S10: =$S$34*R10 -> 11299.548 | V10: 3 | W10: =W$7+(W$27-W$7)*$V10/20 -> 20663747 | X10: =J10 -> 0.2 | Y10: ='Input-Detail'!E17/Z10 -> 8910.4535 | Z10: =Z9 -> 2319.0455 | AA10: =AA9 -> 2 | AB10: =AB9 -> 0.7 | AC10: =Y10*AB10 -> 6237.3175 | AD10: =Peak_Time_Eve*$BH10*(3600/K43+BK10)/3600 -> 28.76588 | AE10: =IF(AE$6<Total_Lanes,($BI10*($CH10+BM10)+$CM10*CO10)*Peak_Time_Eve/3600,"-") -> 34.981802 | AF10: =IF(AF$6<Total_Lanes,($BI10*($CH10+BN10)+$CM10*CP10)*Peak_Time_Eve/3600,"-") -> 39.673764 | AG10: =IF(AG$6<Total_Lanes,($BI10*($CH10+BO10)+$CM10*CQ10)*Peak_Time_Eve/3600,"-") -> 313.18659 | AH10: =IF(AH$6<Total_Lanes,($BI10*($CH10+BP10)+$CM10*CR10)*Peak_Time_Eve/3600,"-") -> 1535.096 | AI10: =IF(AI$6<Total_Lanes,($BI10*($CH10+BQ10)+$CM10*CS10)*Peak_Time_Eve/3600,"-") -> 3168.4307 | AJ10: =IF(AJ$6<Total_Lanes,($BI10*($CH10+BR10)+$CM10*CT10)*Peak_Time_Eve/3600,"-") -> 5352.7135 | AK10: =IF(AK$6<Total_Lanes,($BI10*($CH10+BS10)+$CM10*CU10)*Peak_Time_Eve/3600,"-") -> 8412.9877 | AL10: =IF(AL$6<Total_Lanes,($BI10*($CH10+BT10)+$CM10*CV10)*Peak_Time_Eve/3600,"-") -> 13004.612 | ... AY10: =IF(AY$6<Total_Lanes,($BI10*($CH10+CG10)+$CM10*DI10)*Peak_Time_Eve/3600,"-") -> - | AZ10: =SUMIF(AE10:AY10,BA10,$AE$6:$AY$6) -> 1 | BA10: =MIN(AE10:AY10) -> 34.981802 | BB10: =IF((SUMIF($BM8:$CG8,$AZ10,$BM10:$CG10)+$CH10)<(SUMIF($CO8:$DI8,$AZ10,$CO10:$DI10)+$DJ10),AZ10+1,AZ10) -> 1 | BC10: =SUMIF($AE$6:$AY$6,$BB10,$AE10:$AY10) -> 34.981802 | BF10: 3 | BG10: =$X10 -> 0.2 | BH10: =$AC10 -> 6237.3175 | BI10: =BH10*(1-BG10) -> 4989.854 | BJ10: =Peak_Arrival_Manual/K43 -> 9.1134139 | BK10: =900*Peak_Time_Eve*(BJ10/Total_Lanes-1+SQRT((BJ10/Total_Lanes-1)^2+8*(BJ10/Total_Lanes)/(Peak_Time_Eve*$K43*Total_Lanes))) -> 1.7264187 | BL10: =Peak_Arrival_Manual/N43 -> 9.2017759 | BM10: =IF(BM$6<Total_Lanes,900*Peak_Time_Eve*(($BL10/(Total_Lanes-BM$6))-1+SQRT((($BL10/(Total_Lanes-BM$6))-1)^2+8*($BL10/(Total_Lanes-BM$6))/(Peak_Time_Eve*$N43*(Total_Lanes-BM$6)))),"-") -> 3.0722754 | BN10: =IF(BN$6<Total_Lanes,900*Peak_Time_Eve*(($BL10/(Total_Lanes-BN$6))-1+SQRT((($BL10/(Total_Lanes-BN$6))-1)^2+8*($BL10/(Total_Lanes-BN$6))/(Peak_Time_Eve*$N43*(Total_Lanes-BN$6)))),"-") -> 7.4593915 | BO10: =IF(BO$6<Total_Lanes,900*Peak_Time_Eve*(($BL10/(Total_Lanes-BO$6))-1+SQRT((($BL10/(Total_Lanes-BO$6))-1)^2+8*($BL10/(Total_Lanes-BO$6))/(Peak_Time_Eve*$N43*(Total_Lanes-BO$6)))),"-") -> 106.26097 | BP10: =IF(BP$6<Total_Lanes,900*Peak_Time_Eve*(($BL10/(Total_Lanes-BP$6))-1+SQRT((($BL10/(Total_Lanes-BP$6))-1)^2+8*($BL10/(Total_Lanes-BP$6))/(Peak_Time_Eve*$N43*(Total_Lanes-BP$6)))),"-") -> 547.08015 | BQ10: =IF(BQ$6<Total_Lanes,900*Peak_Time_Eve*(($BL10/(Total_Lanes-BQ$6))-1+SQRT((($BL10/(Total_Lanes-BQ$6))-1)^2+8*($BL10/(Total_Lanes-BQ$6))/(Peak_Time_Eve*$N43*(Total_Lanes-BQ$6)))),"-") -> 1136.2917 | BR10: =IF(BR$6<Total_Lanes,900*Peak_Time_Eve*(($BL10/(Total_Lanes-BR$6))-1+SQRT((($BL10/(Total_Lanes-BR$6))-1)^2+8*($BL10/(Total_Lanes-BR$6))/(Peak_Time_Eve*$N43*(Total_Lanes-BR$6)))),"-") -> 1924.2402 | BS10: =IF(BS$6<Total_Lanes,900*Peak_Time_Eve*(($BL10/(Total_Lanes-BS$6))-1+SQRT((($BL10/(Total_Lanes-BS$6))-1)^2+8*($BL10/(Total_Lanes-BS$6))/(Peak_Time_Eve*$N43*(Total_Lanes-BS$6)))),"-") -> 3028.1836 | BT10: =IF(BT$6<Total_Lanes,900*Peak_Time_Eve*(($BL10/(Total_Lanes-BT$6))-1+SQRT((($BL10/(Total_Lanes-BT$6))-1)^2+8*($BL10/(Total_Lanes-BT$6))/(Peak_Time_Eve*$N43*(Total_Lanes-BT$6)))),"-") -> 4684.5324 | ... CG10: =IF(CG$6<Total_Lanes,900*Peak_Time_Eve*(($BL10/(Total_Lanes-CG$6))-1+SQRT((($BL10/(Total_Lanes-CG$6))-1)^2+8*($BL10/(Total_Lanes-CG$6))/(Peak_Time_Eve*$N43*(Total_Lanes-CG$6)))),"-") -> - | CH10: =3600/N43 -> 6.63875 | CJ10: 3 | CK10: =$X10 -> 0.2 | CL10: =$AC10 -> 6237.3175 | CM10: =CL10*CK10 -> 1247.4635 | CN10: =CM10/O42 -> 0.83164233 | CO10: =IF(CO$6<Total_Lanes,900*Peak_Time_Eve*(($CN10/CO$6-1)+SQRT(($CN10/CO$6-1)^2+8*($CN10/CO$6)/(Peak_Time_Eve*$O43*CO$6))),"-") -> 11.632119 | CP10: =IF(CP$6<Total_Lanes,900*Peak_Time_Eve*(($CN10/CP$6-1)+SQRT(($CN10/CP$6-1)^2+8*($CN10/CP$6)/(Peak_Time_Eve*$O43*CP$6))),"-") -> 0.85381884 | CQ10: =IF(CQ$6<Total_Lanes,900*Peak_Time_Eve*(($CN10/CQ$6-1)+SQRT(($CN10/CQ$6-1)^2+8*($CN10/CQ$6)/(Peak_Time_Eve*$O43*CQ$6))),"-") -> 0.3067923 | CR10: =IF(CR$6<Total_Lanes,900*Peak_Time_Eve*(($CN10/CR$6-1)+SQRT(($CN10/CR$6-1)^2+8*($CN10/CR$6)/(Peak_Time_Eve*$O43*CR$6))),"-") -> 0.15748154 | CS10: =IF(CS$6<Total_Lanes,900*Peak_Time_Eve*(($CN10/CS$6-1)+SQRT(($CN10/CS$6-1)^2+8*($CN10/CS$6)/(Peak_Time_Eve*$O43*CS$6))),"-") -> 0.095763275 | CT10: =IF(CT$6<Total_Lanes,900*Peak_Time_Eve*(($CN10/CT$6-1)+SQRT(($CN10/CT$6-1)^2+8*($CN10/CT$6)/(Peak_Time_Eve*$O43*CT$6))),"-") -> 0.064362811 | CU10: =IF(CU$6<Total_Lanes,900*Peak_Time_Eve*(($CN10/CU$6-1)+SQRT(($CN10/CU$6-1)^2+8*($CN10/CU$6)/(Peak_Time_Eve*$O43*CU$6))),"-") -> 0.04622468 | CV10: =IF(CV$6<Total_Lanes,900*Peak_Time_Eve*(($CN10/CV$6-1)+SQRT(($CN10/CV$6-1)^2+8*($CN10/CV$6)/(Peak_Time_Eve*$O43*CV$6))),"-") -> 0.034804347 | ... DI10: =IF(DI$6<Total_Lanes,900*Peak_Time_Eve*(($CN10/DI$6-1)+SQRT(($CN10/DI$6-1)^2+8*($CN10/DI$6)/(Peak_Time_Eve*$O43*DI$6))),"-") -> - | DJ10: =3600/O43 -> 2.4
H11: 4 | I11: ='Input-Detail'!E18 -> 21212938 | J11: ='Input-Detail'!F18 -> 0.25 | K11: =AC11 -> 6403.09 | L11: =AD58 -> 10.534446 | M11: =AD11 -> 28.675081 | N11: =SUM(L11:M11) -> 39.209527 | O11: =$S$34*N11 -> 10194.477 | P11: =BC58 -> 8.21883 | Q11: =BC11 -> 32.955342 | R11: =SUM(P11:Q11) -> 41.174172 | S11: =$S$34*R11 -> 10705.285 | V11: 4 | W11: =W$7+(W$27-W$7)*$V11/20 -> 21212938 | X11: =J11 -> 0.25 | Y11: ='Input-Detail'!E18/Z11 -> 9147.2714 | Z11: =Z10 -> 2319.0455 | AA11: =AA10 -> 2 | AB11: =AB10 -> 0.7 | AC11: =Y11*AB11 -> 6403.09 | AD11: =Peak_Time_Eve*$BH11*(3600/K44+BK11)/3600 -> 28.675081 | AE11: =IF(AE$6<Total_Lanes,($BI11*($CH11+BM11)+$CM11*CO11)*Peak_Time_Eve/3600,"-") -> 269.39292 | AF11: =IF(AF$6<Total_Lanes,($BI11*($CH11+BN11)+$CM11*CP11)*Peak_Time_Eve/3600,"-") -> 32.955342 | AG11: =IF(AG$6<Total_Lanes,($BI11*($CH11+BO11)+$CM11*CQ11)*Peak_Time_Eve/3600,"-") -> 106.52048 | AH11: =IF(AH$6<Total_Lanes,($BI11*($CH11+BP11)+$CM11*CR11)*Peak_Time_Eve/3600,"-") -> 1101.4843 | AI11: =IF(AI$6<Total_Lanes,($BI11*($CH11+BQ11)+$CM11*CS11)*Peak_Time_Eve/3600,"-") -> 2615.2109 | AJ11: =IF(AJ$6<Total_Lanes,($BI11*($CH11+BR11)+$CM11*CT11)*Peak_Time_Eve/3600,"-") -> 4644.0373 | AK11: =IF(AK$6<Total_Lanes,($BI11*($CH11+BS11)+$CM11*CU11)*Peak_Time_Eve/3600,"-") -> 7487.3751 | AL11: =IF(AL$6<Total_Lanes,($BI11*($CH11+BT11)+$CM11*CV11)*Peak_Time_Eve/3600,"-") -> 11753.833 | ... AY11: =IF(AY$6<Total_Lanes,($BI11*($CH11+CG11)+$CM11*DI11)*Peak_Time_Eve/3600,"-") -> - | AZ11: =SUMIF(AE11:AY11,BA11,$AE$6:$AY$6) -> 2 | BA11: =MIN(AE11:AY11) -> 32.955342 | BB11: =IF((SUMIF($BM9:$CG9,$AZ11,$BM11:$CG11)+$CH11)<(SUMIF($CO9:$DI9,$AZ11,$CO11:$DI11)+$DJ11),AZ11+1,AZ11) -> 2 | BC11: =SUMIF($AE$6:$AY$6,$BB11,$AE11:$AY11) -> 32.955342 | BF11: 4 | BG11: =$X11 -> 0.25 | BH11: =$AC11 -> 6403.09 | BI11: =BH11*(1-BG11) -> 4802.3175 | BJ11: =Peak_Arrival_Manual/K44 -> 8.7708993 | BK11: =900*Peak_Time_Eve*(BJ11/Total_Lanes-1+SQRT((BJ11/Total_Lanes-1)^2+8*(BJ11/Total_Lanes)/(Peak_Time_Eve*$K44*Total_Lanes))) -> 1.4859745 | BL11: =Peak_Arrival_Manual/N44 -> 8.8842873 | BM11: =IF(BM$6<Total_Lanes,900*Peak_Time_Eve*(($BL11/(Total_Lanes-BM$6))-1+SQRT((($BL11/(Total_Lanes-BM$6))-1)^2+8*($BL11/(Total_Lanes-BM$6))/(Peak_Time_Eve*$N44*(Total_Lanes-BM$6)))),"-") -> 2.5331535 | BN11: =IF(BN$6<Total_Lanes,900*Peak_Time_Eve*(($BL11/(Total_Lanes-BN$6))-1+SQRT((($BL11/(Total_Lanes-BN$6))-1)^2+8*($BL11/(Total_Lanes-BN$6))/(Peak_Time_Eve*$N44*(Total_Lanes-BN$6)))),"-") -> 5.235047 | BO11: =IF(BO$6<Total_Lanes,900*Peak_Time_Eve*(($BL11/(Total_Lanes-BO$6))-1+SQRT((($BL11/(Total_Lanes-BO$6))-1)^2+8*($BL11/(Total_Lanes-BO$6))/(Peak_Time_Eve*$N44*(Total_Lanes-BO$6)))),"-") -> 33.118694 | BP11: =IF(BP$6<Total_Lanes,900*Peak_Time_Eve*(($BL11/(Total_Lanes-BP$6))-1+SQRT((($BL11/(Total_Lanes-BP$6))-1)^2+8*($BL11/(Total_Lanes-BP$6))/(Peak_Time_Eve*$N44*(Total_Lanes-BP$6)))),"-") -> 406.12451 | BQ11: =IF(BQ$6<Total_Lanes,900*Peak_Time_Eve*(($BL11/(Total_Lanes-BQ$6))-1+SQRT((($BL11/(Total_Lanes-BQ$6))-1)^2+8*($BL11/(Total_Lanes-BQ$6))/(Peak_Time_Eve*$N44*(Total_Lanes-BQ$6)))),"-") -> 973.5274 | BR11: =IF(BR$6<Total_Lanes,900*Peak_Time_Eve*(($BL11/(Total_Lanes-BR$6))-1+SQRT((($BL11/(Total_Lanes-BR$6))-1)^2+8*($BL11/(Total_Lanes-BR$6))/(Peak_Time_Eve*$N44*(Total_Lanes-BR$6)))),"-") -> 1733.9847 | BS11: =IF(BS$6<Total_Lanes,900*Peak_Time_Eve*(($BL11/(Total_Lanes-BS$6))-1+SQRT((($BL11/(Total_Lanes-BS$6))-1)^2+8*($BL11/(Total_Lanes-BS$6))/(Peak_Time_Eve*$N44*(Total_Lanes-BS$6)))),"-") -> 2799.7302 | BT11: =IF(BT$6<Total_Lanes,900*Peak_Time_Eve*(($BL11/(Total_Lanes-BT$6))-1+SQRT((($BL11/(Total_Lanes-BT$6))-1)^2+8*($BL11/(Total_Lanes-BT$6))/(Peak_Time_Eve*$N44*(Total_Lanes-BT$6)))),"-") -> 4398.8851 | ... CG11: =IF(CG$6<Total_Lanes,900*Peak_Time_Eve*(($BL11/(Total_Lanes-CG$6))-1+SQRT((($BL11/(Total_Lanes-CG$6))-1)^2+8*($BL11/(Total_Lanes-CG$6))/(Peak_Time_Eve*$N44*(Total_Lanes-CG$6)))),"-") -> - | CH11: =3600/N44 -> 6.66 | CJ11: 4 | CK11: =$X11 -> 0.25 | CL11: =$AC11 -> 6403.09 | CM11: =CL11*CK11 -> 1600.7725 | CN11: =CM11/O43 -> 1.0671817 | CO11: =IF(CO$6<Total_Lanes,900*Peak_Time_Eve*(($CN11/CO$6-1)+SQRT(($CN11/CO$6-1)^2+8*($CN11/CO$6)/(Peak_Time_Eve*$O44*CO$6))),"-") -> 275.34132 | CP11: =IF(CP$6<Total_Lanes,900*Peak_Time_Eve*(($CN11/CP$6-1)+SQRT(($CN11/CP$6-1)^2+8*($CN11/CP$6)/(Peak_Time_Eve*$O44*CP$6))),"-") -> 1.3717276 | CQ11: =IF(CQ$6<Total_Lanes,900*Peak_Time_Eve*(($CN11/CQ$6-1)+SQRT(($CN11/CQ$6-1)^2+8*($CN11/CQ$6)/(Peak_Time_Eve*$O44*CQ$6))),"-") -> 0.44162598 | CR11: =IF(CR$6<Total_Lanes,900*Peak_Time_Eve*(($CN11/CR$6-1)+SQRT(($CN11/CR$6-1)^2+8*($CN11/CR$6)/(Peak_Time_Eve*$O44*CR$6))),"-") -> 0.21830743 | CS11: =IF(CS$6<Total_Lanes,900*Peak_Time_Eve*(($CN11/CS$6-1)+SQRT(($CN11/CS$6-1)^2+8*($CN11/CS$6)/(Peak_Time_Eve*$O44*CS$6))),"-") -> 0.1302434 | CT11: =IF(CT$6<Total_Lanes,900*Peak_Time_Eve*(($CN11/CT$6-1)+SQRT(($CN11/CT$6-1)^2+8*($CN11/CT$6)/(Peak_Time_Eve*$O44*CT$6))),"-") -> 0.086534746 | CU11: =IF(CU$6<Total_Lanes,900*Peak_Time_Eve*(($CN11/CU$6-1)+SQRT(($CN11/CU$6-1)^2+8*($CN11/CU$6)/(Peak_Time_Eve*$O44*CU$6))),"-") -> 0.061671104 | CV11: =IF(CV$6<Total_Lanes,900*Peak_Time_Eve*(($CN11/CV$6-1)+SQRT(($CN11/CV$6-1)^2+8*($CN11/CV$6)/(Peak_Time_Eve*$O44*CV$6))),"-") -> 0.046178876 | ... DI11: =IF(DI$6<Total_Lanes,900*Peak_Time_Eve*(($CN11/DI$6-1)+SQRT(($CN11/DI$6-1)^2+8*($CN11/DI$6)/(Peak_Time_Eve*$O44*DI$6))),"-") -> - | DJ11: =3600/O44 -> 2.4
H12: 5 | I12: ='Input-Detail'!E19 -> 21762130 | J12: ='Input-Detail'!F19 -> 0.3 | K12: =AC12 -> 6568.8625 | L12: =AD59 -> 10.816686 | M12: =AD12 -> 28.651211 | N12: =SUM(L12:M12) -> 39.467897 | O12: =$S$34*N12 -> 10261.653 | P12: =BC59 -> 7.9569966 | Q12: =BC12 -> 29.440162 | R12: =SUM(P12:Q12) -> 37.397158 | S12: =$S$34*R12 -> 9723.2611 | V12: 5 | W12: =W$7+(W$27-W$7)*$V12/20 -> 21762130 | X12: =J12 -> 0.3 | Y12: ='Input-Detail'!E19/Z12 -> 9384.0892 | Z12: =Z11 -> 2319.0455 | AA12: =AA11 -> 2 | AB12: =AB11 -> 0.7 | AC12: =Y12*AB12 -> 6568.8625 | AD12: =Peak_Time_Eve*$BH12*(3600/K45+BK12)/3600 -> 28.651211 | AE12: =IF(AE$6<Total_Lanes,($BI12*($CH12+BM12)+$CM12*CO12)*Peak_Time_Eve/3600,"-") -> 1270.0052 | AF12: =IF(AF$6<Total_Lanes,($BI12*($CH12+BN12)+$CM12*CP12)*Peak_Time_Eve/3600,"-") -> 29.440162 | AG12: =IF(AG$6<Total_Lanes,($BI12*($CH12+BO12)+$CM12*CQ12)*Peak_Time_Eve/3600,"-") -> 50.247927 | AH12: =IF(AH$6<Total_Lanes,($BI12*($CH12+BP12)+$CM12*CR12)*Peak_Time_Eve/3600,"-") -> 663.43696 | AI12: =IF(AI$6<Total_Lanes,($BI12*($CH12+BQ12)+$CM12*CS12)*Peak_Time_Eve/3600,"-") -> 2045.8198 | AJ12: =IF(AJ$6<Total_Lanes,($BI12*($CH12+BR12)+$CM12*CT12)*Peak_Time_Eve/3600,"-") -> 3910.4195 | AK12: =IF(AK$6<Total_Lanes,($BI12*($CH12+BS12)+$CM12*CU12)*Peak_Time_Eve/3600,"-") -> 6525.0752 | AL12: =IF(AL$6<Total_Lanes,($BI12*($CH12+BT12)+$CM12*CV12)*Peak_Time_Eve/3600,"-") -> 10448.869 | ... AY12: =IF(AY$6<Total_Lanes,($BI12*($CH12+CG12)+$CM12*DI12)*Peak_Time_Eve/3600,"-") -> - | AZ12: =SUMIF(AE12:AY12,BA12,$AE$6:$AY$6) -> 2 | BA12: =MIN(AE12:AY12) -> 29.440162 | BB12: =IF((SUMIF($BM10:$CG10,$AZ12,$BM12:$CG12)+$CH12)<(SUMIF($CO10:$DI10,$AZ12,$CO12:$DI12)+$DJ12),AZ12+1,AZ12) -> 2 | BC12: =SUMIF($AE$6:$AY$6,$BB12,$AE12:$AY12) -> 29.440162 | BF12: 5 | BG12: =$X12 -> 0.3 | BH12: =$AC12 -> 6568.8625 | BI12: =BH12*(1-BG12) -> 4598.2037 | BJ12: =Peak_Arrival_Manual/K45 -> 8.3981082 | BK12: =900*Peak_Time_Eve*(BJ12/Total_Lanes-1+SQRT((BJ12/Total_Lanes-1)^2+8*(BJ12/Total_Lanes)/(Peak_Time_Eve*$K45*Total_Lanes))) -> 1.2760062 | BL12: =Peak_Arrival_Manual/N45 -> 8.533819 | BM12: =IF(BM$6<Total_Lanes,900*Peak_Time_Eve*(($BL12/(Total_Lanes-BM$6))-1+SQRT((($BL12/(Total_Lanes-BM$6))-1)^2+8*($BL12/(Total_Lanes-BM$6))/(Peak_Time_Eve*$N45*(Total_Lanes-BM$6)))),"-") -> 2.0963172 | BN12: =IF(BN$6<Total_Lanes,900*Peak_Time_Eve*(($BL12/(Total_Lanes-BN$6))-1+SQRT((($BL12/(Total_Lanes-BN$6))-1)^2+8*($BL12/(Total_Lanes-BN$6))/(Peak_Time_Eve*$N45*(Total_Lanes-BN$6)))),"-") -> 3.8605456 | BO12: =IF(BO$6<Total_Lanes,900*Peak_Time_Eve*(($BL12/(Total_Lanes-BO$6))-1+SQRT((($BL12/(Total_Lanes-BO$6))-1)^2+8*($BL12/(Total_Lanes-BO$6))/(Peak_Time_Eve*$N45*(Total_Lanes-BO$6)))),"-") -> 12.721619 | BP12: =IF(BP$6<Total_Lanes,900*Peak_Time_Eve*(($BL12/(Total_Lanes-BP$6))-1+SQRT((($BL12/(Total_Lanes-BP$6))-1)^2+8*($BL12/(Total_Lanes-BP$6))/(Peak_Time_Eve*$N45*(Total_Lanes-BP$6)))),"-") -> 252.90019 | BQ12: =IF(BQ$6<Total_Lanes,900*Peak_Time_Eve*(($BL12/(Total_Lanes-BQ$6))-1+SQRT((($BL12/(Total_Lanes-BQ$6))-1)^2+8*($BL12/(Total_Lanes-BQ$6))/(Peak_Time_Eve*$N45*(Total_Lanes-BQ$6)))),"-") -> 794.09637 | BR12: =IF(BR$6<Total_Lanes,900*Peak_Time_Eve*(($BL12/(Total_Lanes-BR$6))-1+SQRT((($BL12/(Total_Lanes-BR$6))-1)^2+8*($BL12/(Total_Lanes-BR$6))/(Peak_Time_Eve*$N45*(Total_Lanes-BR$6)))),"-") -> 1524.0326 | BS12: =IF(BS$6<Total_Lanes,900*Peak_Time_Eve*(($BL12/(Total_Lanes-BS$6))-1+SQRT((($BL12/(Total_Lanes-BS$6))-1)^2+8*($BL12/(Total_Lanes-BS$6))/(Peak_Time_Eve*$N45*(Total_Lanes-BS$6)))),"-") -> 2547.5725 | BT12: =IF(BT$6<Total_Lanes,900*Peak_Time_Eve*(($BL12/(Total_Lanes-BT$6))-1+SQRT((($BL12/(Total_Lanes-BT$6))-1)^2+8*($BL12/(Total_Lanes-BT$6))/(Peak_Time_Eve*$N45*(Total_Lanes-BT$6)))),"-") -> 4083.5787 | ... CG12: =IF(CG$6<Total_Lanes,900*Peak_Time_Eve*(($BL12/(Total_Lanes-CG$6))-1+SQRT((($BL12/(Total_Lanes-CG$6))-1)^2+8*($BL12/(Total_Lanes-CG$6))/(Peak_Time_Eve*$N45*(Total_Lanes-CG$6)))),"-") -> - | CH12: =3600/N45 -> 6.68125 | CJ12: 5 | CK12: =$X12 -> 0.3 | CL12: =$AC12 -> 6568.8625 | CM12: =CL12*CK12 -> 1970.6587 | CN12: =CM12/O44 -> 1.3137725 | CO12: =IF(CO$6<Total_Lanes,900*Peak_Time_Eve*(($CN12/CO$6-1)+SQRT(($CN12/CO$6-1)^2+8*($CN12/CO$6)/(Peak_Time_Eve*$O45*CO$6))),"-") -> 1139.542 | CP12: =IF(CP$6<Total_Lanes,900*Peak_Time_Eve*(($CN12/CP$6-1)+SQRT(($CN12/CP$6-1)^2+8*($CN12/CP$6)/(Peak_Time_Eve*$O45*CP$6))),"-") -> 2.2931253 | CQ12: =IF(CQ$6<Total_Lanes,900*Peak_Time_Eve*(($CN12/CQ$6-1)+SQRT(($CN12/CQ$6-1)^2+8*($CN12/CQ$6)/(Peak_Time_Eve*$O45*CQ$6))),"-") -> 0.62310361 | CR12: =IF(CR$6<Total_Lanes,900*Peak_Time_Eve*(($CN12/CR$6-1)+SQRT(($CN12/CR$6-1)^2+8*($CN12/CR$6)/(Peak_Time_Eve*$O45*CR$6))),"-") -> 0.29341068 | CS12: =IF(CS$6<Total_Lanes,900*Peak_Time_Eve*(($CN12/CS$6-1)+SQRT(($CN12/CS$6-1)^2+8*($CN12/CS$6)/(Peak_Time_Eve*$O45*CS$6))),"-") -> 0.17106111 | CT12: =IF(CT$6<Total_Lanes,900*Peak_Time_Eve*(($CN12/CT$6-1)+SQRT(($CN12/CT$6-1)^2+8*($CN12/CT$6)/(Peak_Time_Eve*$O45*CT$6))),"-") -> 0.11213456 | CU12: =IF(CU$6<Total_Lanes,900*Peak_Time_Eve*(($CN12/CU$6-1)+SQRT(($CN12/CU$6-1)^2+8*($CN12/CU$6)/(Peak_Time_Eve*$O45*CU$6))),"-") -> 0.079213166 | CV12: =IF(CV$6<Total_Lanes,900*Peak_Time_Eve*(($CN12/CV$6-1)+SQRT(($CN12/CV$6-1)^2+8*($CN12/CV$6)/(Peak_Time_Eve*$O45*CV$6))),"-") -> 0.05894565 | ... DI12: =IF(DI$6<Total_Lanes,900*Peak_Time_Eve*(($CN12/DI$6-1)+SQRT(($CN12/DI$6-1)^2+8*($CN12/DI$6)/(Peak_Time_Eve*$O45*DI$6))),"-") -> - | DJ12: =3600/O45 -> 2.4
H13: 6 | I13: ='Input-Detail'!E20 -> 22311321 | J13: ='Input-Detail'!F20 -> 0.35 | K13: =AC13 -> 6734.6349 | L13: =AD60 -> 11.09845 | M13: =AD13 -> 28.688811 | N13: =SUM(L13:M13) -> 39.787262 | O13: =$S$34*N13 -> 10344.688 | P13: =BC60 -> 7.6079339 | Q13: =BC13 -> 29.17897 | R13: =SUM(P13:Q13) -> 36.786904 | S13: =$S$34*R13 -> 9564.5949 | V13: 6 | W13: =W$7+(W$27-W$7)*$V13/20 -> 22311321 | X13: =J13 -> 0.35 | Y13: ='Input-Detail'!E20/Z13 -> 9620.9071 | Z13: =Z12 -> 2319.0455 | AA13: =AA12 -> 2 | AB13: =AB12 -> 0.7 | AC13: =Y13*AB13 -> 6734.6349 | AD13: =Peak_Time_Eve*$BH13*(3600/K46+BK13)/3600 -> 28.688811 | AE13: =IF(AE$6<Total_Lanes,($BI13*($CH13+BM13)+$CM13*CO13)*Peak_Time_Eve/3600,"-") -> 2722.9344 | AF13: =IF(AF$6<Total_Lanes,($BI13*($CH13+BN13)+$CM13*CP13)*Peak_Time_Eve/3600,"-") -> 29.17897 | AG13: =IF(AG$6<Total_Lanes,($BI13*($CH13+BO13)+$CM13*CQ13)*Peak_Time_Eve/3600,"-") -> 34.468941 | AH13: =IF(AH$6<Total_Lanes,($BI13*($CH13+BP13)+$CM13*CR13)*Peak_Time_Eve/3600,"-") -> 256.78041 | AI13: =IF(AI$6<Total_Lanes,($BI13*($CH13+BQ13)+$CM13*CS13)*Peak_Time_Eve/3600,"-") -> 1471.3273 | AJ13: =IF(AJ$6<Total_Lanes,($BI13*($CH13+BR13)+$CM13*CT13)*Peak_Time_Eve/3600,"-") -> 3164.0808 | AK13: =IF(AK$6<Total_Lanes,($BI13*($CH13+BS13)+$CM13*CU13)*Peak_Time_Eve/3600,"-") -> 5540.6535 | AL13: =IF(AL$6<Total_Lanes,($BI13*($CH13+BT13)+$CM13*CV13)*Peak_Time_Eve/3600,"-") -> 9107.9003 | ... AY13: =IF(AY$6<Total_Lanes,($BI13*($CH13+CG13)+$CM13*DI13)*Peak_Time_Eve/3600,"-") -> - | AZ13: =SUMIF(AE13:AY13,BA13,$AE$6:$AY$6) -> 2 | BA13: =MIN(AE13:AY13) -> 29.17897 | BB13: =IF((SUMIF($BM11:$CG11,$AZ13,$BM13:$CG13)+$CH13)<(SUMIF($CO11:$DI11,$AZ13,$CO13:$DI13)+$DJ13),AZ13+1,AZ13) -> 2 | BC13: =SUMIF($AE$6:$AY$6,$BB13,$AE13:$AY13) -> 29.17897 | BF13: 6 | BG13: =$X13 -> 0.35 | BH13: =$AC13 -> 6734.6349 | BI13: =BH13*(1-BG13) -> 4377.5127 | BJ13: =Peak_Arrival_Manual/K46 -> 7.9950406 | BK13: =900*Peak_Time_Eve*(BJ13/Total_Lanes-1+SQRT((BJ13/Total_Lanes-1)^2+8*(BJ13/Total_Lanes)/(Peak_Time_Eve*$K46*Total_Lanes))) -> 1.0928039 | BL13: =Peak_Arrival_Manual/N46 -> 8.1500775 | BM13: =IF(BM$6<Total_Lanes,900*Peak_Time_Eve*(($BL13/(Total_Lanes-BM$6))-1+SQRT((($BL13/(Total_Lanes-BM$6))-1)^2+8*($BL13/(Total_Lanes-BM$6))/(Peak_Time_Eve*$N46*(Total_Lanes-BM$6)))),"-") -> 1.7392569 | BN13: =IF(BN$6<Total_Lanes,900*Peak_Time_Eve*(($BL13/(Total_Lanes-BN$6))-1+SQRT((($BL13/(Total_Lanes-BN$6))-1)^2+8*($BL13/(Total_Lanes-BN$6))/(Peak_Time_Eve*$N46*(Total_Lanes-BN$6)))),"-") -> 2.9398967 | BO13: =IF(BO$6<Total_Lanes,900*Peak_Time_Eve*(($BL13/(Total_Lanes-BO$6))-1+SQRT((($BL13/(Total_Lanes-BO$6))-1)^2+8*($BL13/(Total_Lanes-BO$6))/(Peak_Time_Eve*$N46*(Total_Lanes-BO$6)))),"-") -> 6.9972723 | BP13: =IF(BP$6<Total_Lanes,900*Peak_Time_Eve*(($BL13/(Total_Lanes-BP$6))-1+SQRT((($BL13/(Total_Lanes-BP$6))-1)^2+8*($BL13/(Total_Lanes-BP$6))/(Peak_Time_Eve*$N46*(Total_Lanes-BP$6)))),"-") -> 98.674646 | BQ13: =IF(BQ$6<Total_Lanes,900*Peak_Time_Eve*(($BL13/(Total_Lanes-BQ$6))-1+SQRT((($BL13/(Total_Lanes-BQ$6))-1)^2+8*($BL13/(Total_Lanes-BQ$6))/(Peak_Time_Eve*$N46*(Total_Lanes-BQ$6)))),"-") -> 598.17768 | BR13: =IF(BR$6<Total_Lanes,900*Peak_Time_Eve*(($BL13/(Total_Lanes-BR$6))-1+SQRT((($BL13/(Total_Lanes-BR$6))-1)^2+8*($BL13/(Total_Lanes-BR$6))/(Peak_Time_Eve*$N46*(Total_Lanes-BR$6)))),"-") -> 1294.2671 | BS13: =IF(BS$6<Total_Lanes,900*Peak_Time_Eve*(($BL13/(Total_Lanes-BS$6))-1+SQRT((($BL13/(Total_Lanes-BS$6))-1)^2+8*($BL13/(Total_Lanes-BS$6))/(Peak_Time_Eve*$N46*(Total_Lanes-BS$6)))),"-") -> 2271.5187 | BT13: =IF(BT$6<Total_Lanes,900*Peak_Time_Eve*(($BL13/(Total_Lanes-BT$6))-1+SQRT((($BL13/(Total_Lanes-BT$6))-1)^2+8*($BL13/(Total_Lanes-BT$6))/(Peak_Time_Eve*$N46*(Total_Lanes-BT$6)))),"-") -> 3738.3575 | ... CG13: =IF(CG$6<Total_Lanes,900*Peak_Time_Eve*(($BL13/(Total_Lanes-CG$6))-1+SQRT((($BL13/(Total_Lanes-CG$6))-1)^2+8*($BL13/(Total_Lanes-CG$6))/(Peak_Time_Eve*$N46*(Total_Lanes-CG$6)))),"-") -> - | CH13: =3600/N46 -> 6.7025 | CJ13: 6 | CK13: =$X13 -> 0.35 | CL13: =$AC13 -> 6734.6349 | CM13: =CL13*CK13 -> 2357.1222 | CN13: =CM13/O45 -> 1.5714148 | CO13: =IF(CO$6<Total_Lanes,900*Peak_Time_Eve*(($CN13/CO$6-1)+SQRT(($CN13/CO$6-1)^2+8*($CN13/CO$6)/(Peak_Time_Eve*$O46*CO$6))),"-") -> 2063.6724 | CP13: =IF(CP$6<Total_Lanes,900*Peak_Time_Eve*(($CN13/CP$6-1)+SQRT(($CN13/CP$6-1)^2+8*($CN13/CP$6)/(Peak_Time_Eve*$O46*CP$6))),"-") -> 4.3750091 | CQ13: =IF(CQ$6<Total_Lanes,900*Peak_Time_Eve*(($CN13/CQ$6-1)+SQRT(($CN13/CQ$6-1)^2+8*($CN13/CQ$6)/(Peak_Time_Eve*$O46*CQ$6))),"-") -> 0.87953258 | CR13: =IF(CR$6<Total_Lanes,900*Peak_Time_Eve*(($CN13/CR$6-1)+SQRT(($CN13/CR$6-1)^2+8*($CN13/CR$6)/(Peak_Time_Eve*$O46*CR$6))),"-") -> 0.38816077 | CS13: =IF(CS$6<Total_Lanes,900*Peak_Time_Eve*(($CN13/CS$6-1)+SQRT(($CN13/CS$6-1)^2+8*($CN13/CS$6)/(Peak_Time_Eve*$O46*CS$6))),"-") -> 0.21997759 | CT13: =IF(CT$6<Total_Lanes,900*Peak_Time_Eve*(($CN13/CT$6-1)+SQRT(($CN13/CT$6-1)^2+8*($CN13/CT$6)/(Peak_Time_Eve*$O46*CT$6))),"-") -> 0.14192622 | CU13: =IF(CU$6<Total_Lanes,900*Peak_Time_Eve*(($CN13/CU$6-1)+SQRT(($CN13/CU$6-1)^2+8*($CN13/CU$6)/(Peak_Time_Eve*$O46*CU$6))),"-") -> 0.099243472 | CV13: =IF(CV$6<Total_Lanes,900*Peak_Time_Eve*(($CN13/CV$6-1)+SQRT(($CN13/CV$6-1)^2+8*($CN13/CV$6)/(Peak_Time_Eve*$O46*CV$6))),"-") -> 0.073330676 | ... DI13: =IF(DI$6<Total_Lanes,900*Peak_Time_Eve*(($CN13/DI$6-1)+SQRT(($CN13/DI$6-1)^2+8*($CN13/DI$6)/(Peak_Time_Eve*$O46*DI$6))),"-") -> - | DJ13: =3600/O46 -> 2.4
H14: 7 | I14: ='Input-Detail'!E21 -> 22860512 | J14: ='Input-Detail'!F21 -> 0.4 | K14: =AC14 -> 6900.4074 | L14: =AD61 -> 11.379841 | M14: =AD14 -> 28.781797 | N14: =SUM(L14:M14) -> 40.161638 | O14: =$S$34*N14 -> 10442.026 | P14: =BC61 -> 7.2447159 | Q14: =BC14 -> 27.803086 | R14: =SUM(P14:Q14) -> 35.047802 | S14: =$S$34*R14 -> 9112.4284 | V14: 7 | W14: =W$7+(W$27-W$7)*$V14/20 -> 22860512 | X14: =J14 -> 0.4 | Y14: ='Input-Detail'!E21/Z14 -> 9857.7249 | Z14: =Z13 -> 2319.0455 | AA14: =AA13 -> 2 | AB14: =AB13 -> 0.7 | AC14: =Y14*AB14 -> 6900.4074 | AD14: =Peak_Time_Eve*$BH14*(3600/K47+BK14)/3600 -> 28.781797 | AE14: =IF(AE$6<Total_Lanes,($BI14*($CH14+BM14)+$CM14*CO14)*Peak_Time_Eve/3600,"-") -> 4664.5091 | AF14: =IF(AF$6<Total_Lanes,($BI14*($CH14+BN14)+$CM14*CP14)*Peak_Time_Eve/3600,"-") -> 40.973491 | AG14: =IF(AG$6<Total_Lanes,($BI14*($CH14+BO14)+$CM14*CQ14)*Peak_Time_Eve/3600,"-") -> 27.803086 | AH14: =IF(AH$6<Total_Lanes,($BI14*($CH14+BP14)+$CM14*CR14)*Peak_Time_Eve/3600,"-") -> 63.95973 | AI14: =IF(AI$6<Total_Lanes,($BI14*($CH14+BQ14)+$CM14*CS14)*Peak_Time_Eve/3600,"-") -> 905.42591 | AJ14: =IF(AJ$6<Total_Lanes,($BI14*($CH14+BR14)+$CM14*CT14)*Peak_Time_Eve/3600,"-") -> 2418.5475 | AK14: =IF(AK$6<Total_Lanes,($BI14*($CH14+BS14)+$CM14*CU14)*Peak_Time_Eve/3600,"-") -> 4550.1214 | AL14: =IF(AL$6<Total_Lanes,($BI14*($CH14+BT14)+$CM14*CV14)*Peak_Time_Eve/3600,"-") -> 7750.8925 | ... AY14: =IF(AY$6<Total_Lanes,($BI14*($CH14+CG14)+$CM14*DI14)*Peak_Time_Eve/3600,"-") -> - | AZ14: =SUMIF(AE14:AY14,BA14,$AE$6:$AY$6) -> 3 | BA14: =MIN(AE14:AY14) -> 27.803086 | BB14: =IF((SUMIF($BM12:$CG12,$AZ14,$BM14:$CG14)+$CH14)<(SUMIF($CO12:$DI12,$AZ14,$CO14:$DI14)+$DJ14),AZ14+1,AZ14) -> 3 | BC14: =SUMIF($AE$6:$AY$6,$BB14,$AE14:$AY14) -> 27.803086 | BF14: 7 | BG14: =$X14 -> 0.4 | BH14: =$AC14 -> 6900.4074 | BI14: =BH14*(1-BG14) -> 4140.2445 | BJ14: =Peak_Arrival_Manual/K47 -> 7.5616965 | BK14: =900*Peak_Time_Eve*(BJ14/Total_Lanes-1+SQRT((BJ14/Total_Lanes-1)^2+8*(BJ14/Total_Lanes)/(Peak_Time_Eve*$K47*Total_Lanes))) -> 0.93285166 | BL14: =Peak_Arrival_Manual/N47 -> 7.7327691 | BM14: =IF(BM$6<Total_Lanes,900*Peak_Time_Eve*(($BL14/(Total_Lanes-BM$6))-1+SQRT((($BL14/(Total_Lanes-BM$6))-1)^2+8*($BL14/(Total_Lanes-BM$6))/(Peak_Time_Eve*$N47*(Total_Lanes-BM$6)))),"-") -> 1.4447333 | BN14: =IF(BN$6<Total_Lanes,900*Peak_Time_Eve*(($BL14/(Total_Lanes-BN$6))-1+SQRT((($BL14/(Total_Lanes-BN$6))-1)^2+8*($BL14/(Total_Lanes-BN$6))/(Peak_Time_Eve*$N47*(Total_Lanes-BN$6)))),"-") -> 2.2868398 | BO14: =IF(BO$6<Total_Lanes,900*Peak_Time_Eve*(($BL14/(Total_Lanes-BO$6))-1+SQRT((($BL14/(Total_Lanes-BO$6))-1)^2+8*($BL14/(Total_Lanes-BO$6))/(Peak_Time_Eve*$N47*(Total_Lanes-BO$6)))),"-") -> 4.5184983 | BP14: =IF(BP$6<Total_Lanes,900*Peak_Time_Eve*(($BL14/(Total_Lanes-BP$6))-1+SQRT((($BL14/(Total_Lanes-BP$6))-1)^2+8*($BL14/(Total_Lanes-BP$6))/(Peak_Time_Eve*$N47*(Total_Lanes-BP$6)))),"-") -> 20.742498 | BQ14: =IF(BQ$6<Total_Lanes,900*Peak_Time_Eve*(($BL14/(Total_Lanes-BQ$6))-1+SQRT((($BL14/(Total_Lanes-BQ$6))-1)^2+8*($BL14/(Total_Lanes-BQ$6))/(Peak_Time_Eve*$N47*(Total_Lanes-BQ$6)))),"-") -> 386.73012 | BR14: =IF(BR$6<Total_Lanes,900*Peak_Time_Eve*(($BL14/(Total_Lanes-BR$6))-1+SQRT((($BL14/(Total_Lanes-BR$6))-1)^2+8*($BL14/(Total_Lanes-BR$6))/(Peak_Time_Eve*$N47*(Total_Lanes-BR$6)))),"-") -> 1044.6386 | BS14: =IF(BS$6<Total_Lanes,900*Peak_Time_Eve*(($BL14/(Total_Lanes-BS$6))-1+SQRT((($BL14/(Total_Lanes-BS$6))-1)^2+8*($BL14/(Total_Lanes-BS$6))/(Peak_Time_Eve*$N47*(Total_Lanes-BS$6)))),"-") -> 1971.3916 | BT14: =IF(BT$6<Total_Lanes,900*Peak_Time_Eve*(($BL14/(Total_Lanes-BT$6))-1+SQRT((($BL14/(Total_Lanes-BT$6))-1)^2+8*($BL14/(Total_Lanes-BT$6))/(Peak_Time_Eve*$N47*(Total_Lanes-BT$6)))),"-") -> 3362.9708 | ... CG14: =IF(CG$6<Total_Lanes,900*Peak_Time_Eve*(($BL14/(Total_Lanes-CG$6))-1+SQRT((($BL14/(Total_Lanes-CG$6))-1)^2+8*($BL14/(Total_Lanes-CG$6))/(Peak_Time_Eve*$N47*(Total_Lanes-CG$6)))),"-") -> - | CH14: =3600/N47 -> 6.72375 | CJ14: 7 | CK14: =$X14 -> 0.4 | CL14: =$AC14 -> 6900.4074 | CM14: =CL14*CK14 -> 2760.163 | CN14: =CM14/O46 -> 1.8401086 | CO14: =IF(CO$6<Total_Lanes,900*Peak_Time_Eve*(($CN14/CO$6-1)+SQRT(($CN14/CO$6-1)^2+8*($CN14/CO$6)/(Peak_Time_Eve*$O47*CO$6))),"-") -> 3029.6388 | CP14: =IF(CP$6<Total_Lanes,900*Peak_Time_Eve*(($CN14/CP$6-1)+SQRT(($CN14/CP$6-1)^2+8*($CN14/CP$6)/(Peak_Time_Eve*$O47*CP$6))),"-") -> 13.20438 | CQ14: =IF(CQ$6<Total_Lanes,900*Peak_Time_Eve*(($CN14/CQ$6-1)+SQRT(($CN14/CQ$6-1)^2+8*($CN14/CQ$6)/(Peak_Time_Eve*$O47*CQ$6))),"-") -> 1.2680042 | CR14: =IF(CR$6<Total_Lanes,900*Peak_Time_Eve*(($CN14/CR$6-1)+SQRT(($CN14/CR$6-1)^2+8*($CN14/CR$6)/(Peak_Time_Eve*$O47*CR$6))),"-") -> 0.51103266 | CS14: =IF(CS$6<Total_Lanes,900*Peak_Time_Eve*(($CN14/CS$6-1)+SQRT(($CN14/CS$6-1)^2+8*($CN14/CS$6)/(Peak_Time_Eve*$O47*CS$6))),"-") -> 0.27948545 | CT14: =IF(CT$6<Total_Lanes,900*Peak_Time_Eve*(($CN14/CT$6-1)+SQRT(($CN14/CT$6-1)^2+8*($CN14/CT$6)/(Peak_Time_Eve*$O47*CT$6))),"-") -> 0.1769256 | CU14: =IF(CU$6<Total_Lanes,900*Peak_Time_Eve*(($CN14/CU$6-1)+SQRT(($CN14/CU$6-1)^2+8*($CN14/CU$6)/(Peak_Time_Eve*$O47*CU$6))),"-") -> 0.1222633 | CV14: =IF(CV$6<Total_Lanes,900*Peak_Time_Eve*(($CN14/CV$6-1)+SQRT(($CN14/CV$6-1)^2+8*($CN14/CV$6)/(Peak_Time_Eve*$O47*CV$6))),"-") -> 0.089614364 | ... DI14: =IF(DI$6<Total_Lanes,900*Peak_Time_Eve*(($CN14/DI$6-1)+SQRT(($CN14/DI$6-1)^2+8*($CN14/DI$6)/(Peak_Time_Eve*$O47*DI$6))),"-") -> - | DJ14: =3600/O47 -> 2.4
H15: 8 | I15: ='Input-Detail'!E22 -> 23409704 | J15: ='Input-Detail'!F22 -> 0.45 | K15: =AC15 -> 7066.1799 | L15: =AD62 -> 11.66097 | M15: =AD15 -> 28.924095 | N15: =SUM(L15:M15) -> 40.585065 | O15: =$S$34*N15 -> 10552.117 | P15: =BC62 -> 6.8724629 | Q15: =BC15 -> 24.786167 | R15: =SUM(P15:Q15) -> 31.65863 | S15: =$S$34*R15 -> 8231.2437 | V15: 8 | W15: =W$7+(W$27-W$7)*$V15/20 -> 23409704 | X15: =J15 -> 0.45 | Y15: ='Input-Detail'!E22/Z15 -> 10094.543 | Z15: =Z14 -> 2319.0455 | AA15: =AA14 -> 2 | AB15: =AB14 -> 0.7 | AC15: =Y15*AB15 -> 7066.1799 | AD15: =Peak_Time_Eve*$BH15*(3600/K48+BK15)/3600 -> 28.924095 | AE15: =IF(AE$6<Total_Lanes,($BI15*($CH15+BM15)+$CM15*CO15)*Peak_Time_Eve/3600,"-") -> 7146.9506 | AF15: =IF(AF$6<Total_Lanes,($BI15*($CH15+BN15)+$CM15*CP15)*Peak_Time_Eve/3600,"-") -> 433.95684 | AG15: =IF(AG$6<Total_Lanes,($BI15*($CH15+BO15)+$CM15*CQ15)*Peak_Time_Eve/3600,"-") -> 24.786167 | AH15: =IF(AH$6<Total_Lanes,($BI15*($CH15+BP15)+$CM15*CR15)*Peak_Time_Eve/3600,"-") -> 33.745553 | AI15: =IF(AI$6<Total_Lanes,($BI15*($CH15+BQ15)+$CM15*CS15)*Peak_Time_Eve/3600,"-") -> 374.66973 | AJ15: =IF(AJ$6<Total_Lanes,($BI15*($CH15+BR15)+$CM15*CT15)*Peak_Time_Eve/3600,"-") -> 1688.897 | AK15: =IF(AK$6<Total_Lanes,($BI15*($CH15+BS15)+$CM15*CU15)*Peak_Time_Eve/3600,"-") -> 3570.9811 | AL15: =IF(AL$6<Total_Lanes,($BI15*($CH15+BT15)+$CM15*CV15)*Peak_Time_Eve/3600,"-") -> 6399.6266 | ... AY15: =IF(AY$6<Total_Lanes,($BI15*($CH15+CG15)+$CM15*DI15)*Peak_Time_Eve/3600,"-") -> - | AZ15: =SUMIF(AE15:AY15,BA15,$AE$6:$AY$6) -> 3 | BA15: =MIN(AE15:AY15) -> 24.786167 | BB15: =IF((SUMIF($BM13:$CG13,$AZ15,$BM15:$CG15)+$CH15)<(SUMIF($CO13:$DI13,$AZ15,$CO15:$DI15)+$DJ15),AZ15+1,AZ15) -> 3 | BC15: =SUMIF($AE$6:$AY$6,$BB15,$AE15:$AY15) -> 24.786167 | BF15: 8 | BG15: =$X15 -> 0.45 | BH15: =$AC15 -> 7066.1799 | BI15: =BH15*(1-BG15) -> 3886.399 | BJ15: =Peak_Arrival_Manual/K48 -> 7.0980759 | BK15: =900*Peak_Time_Eve*(BJ15/Total_Lanes-1+SQRT((BJ15/Total_Lanes-1)^2+8*(BJ15/Total_Lanes)/(Peak_Time_Eve*$K48*Total_Lanes))) -> 0.79296578 | BL15: =Peak_Arrival_Manual/N48 -> 7.2816003 | BM15: =IF(BM$6<Total_Lanes,900*Peak_Time_Eve*(($BL15/(Total_Lanes-BM$6))-1+SQRT((($BL15/(Total_Lanes-BM$6))-1)^2+8*($BL15/(Total_Lanes-BM$6))/(Peak_Time_Eve*$N48*(Total_Lanes-BM$6)))),"-") -> 1.1995881 | BN15: =IF(BN$6<Total_Lanes,900*Peak_Time_Eve*(($BL15/(Total_Lanes-BN$6))-1+SQRT((($BL15/(Total_Lanes-BN$6))-1)^2+8*($BL15/(Total_Lanes-BN$6))/(Peak_Time_Eve*$N48*(Total_Lanes-BN$6)))),"-") -> 1.8034159 | BO15: =IF(BO$6<Total_Lanes,900*Peak_Time_Eve*(($BL15/(Total_Lanes-BO$6))-1+SQRT((($BL15/(Total_Lanes-BO$6))-1)^2+8*($BL15/(Total_Lanes-BO$6))/(Peak_Time_Eve*$N48*(Total_Lanes-BO$6)))),"-") -> 3.1611808 | BP15: =IF(BP$6<Total_Lanes,900*Peak_Time_Eve*(($BL15/(Total_Lanes-BP$6))-1+SQRT((($BL15/(Total_Lanes-BP$6))-1)^2+8*($BL15/(Total_Lanes-BP$6))/(Peak_Time_Eve*$N48*(Total_Lanes-BP$6)))),"-") -> 8.3311012 | BQ15: =IF(BQ$6<Total_Lanes,900*Peak_Time_Eve*(($BL15/(Total_Lanes-BQ$6))-1+SQRT((($BL15/(Total_Lanes-BQ$6))-1)^2+8*($BL15/(Total_Lanes-BQ$6))/(Peak_Time_Eve*$N48*(Total_Lanes-BQ$6)))),"-") -> 166.49566 | BR15: =IF(BR$6<Total_Lanes,900*Peak_Time_Eve*(($BL15/(Total_Lanes-BR$6))-1+SQRT((($BL15/(Total_Lanes-BR$6))-1)^2+8*($BL15/(Total_Lanes-BR$6))/(Peak_Time_Eve*$N48*(Total_Lanes-BR$6)))),"-") -> 775.29509 | BS15: =IF(BS$6<Total_Lanes,900*Peak_Time_Eve*(($BL15/(Total_Lanes-BS$6))-1+SQRT((($BL15/(Total_Lanes-BS$6))-1)^2+8*($BL15/(Total_Lanes-BS$6))/(Peak_Time_Eve*$N48*(Total_Lanes-BS$6)))),"-") -> 1647.0462 | BT15: =IF(BT$6<Total_Lanes,900*Peak_Time_Eve*(($BL15/(Total_Lanes-BT$6))-1+SQRT((($BL15/(Total_Lanes-BT$6))-1)^2+8*($BL15/(Total_Lanes-BT$6))/(Peak_Time_Eve*$N48*(Total_Lanes-BT$6)))),"-") -> 2957.1772 | ... CG15: =IF(CG$6<Total_Lanes,900*Peak_Time_Eve*(($BL15/(Total_Lanes-CG$6))-1+SQRT((($BL15/(Total_Lanes-CG$6))-1)^2+8*($BL15/(Total_Lanes-CG$6))/(Peak_Time_Eve*$N48*(Total_Lanes-CG$6)))),"-") -> - | CH15: =3600/N48 -> 6.745 | CJ15: 8 | CK15: =$X15 -> 0.45 | CL15: =$AC15 -> 7066.1799 | CM15: =CL15*CK15 -> 3179.781 | CN15: =CM15/O47 -> 2.119854 | CO15: =IF(CO$6<Total_Lanes,900*Peak_Time_Eve*(($CN15/CO$6-1)+SQRT(($CN15/CO$6-1)^2+8*($CN15/CO$6)/(Peak_Time_Eve*$O48*CO$6))),"-") -> 4036.0123 | CP15: =IF(CP$6<Total_Lanes,900*Peak_Time_Eve*(($CN15/CP$6-1)+SQRT(($CN15/CP$6-1)^2+8*($CN15/CP$6)/(Peak_Time_Eve*$O48*CP$6))),"-") -> 235.20481 | CQ15: =IF(CQ$6<Total_Lanes,900*Peak_Time_Eve*(($CN15/CQ$6-1)+SQRT(($CN15/CQ$6-1)^2+8*($CN15/CQ$6)/(Peak_Time_Eve*$O48*CQ$6))),"-") -> 1.9233178 | CR15: =IF(CR$6<Total_Lanes,900*Peak_Time_Eve*(($CN15/CR$6-1)+SQRT(($CN15/CR$6-1)^2+8*($CN15/CR$6)/(Peak_Time_Eve*$O48*CR$6))),"-") -> 0.67622636 | CS15: =IF(CS$6<Total_Lanes,900*Peak_Time_Eve*(($CN15/CS$6-1)+SQRT(($CN15/CS$6-1)^2+8*($CN15/CS$6)/(Peak_Time_Eve*$O48*CS$6))),"-") -> 0.35323091 | CT15: =IF(CT$6<Total_Lanes,900*Peak_Time_Eve*(($CN15/CT$6-1)+SQRT(($CN15/CT$6-1)^2+8*($CN15/CT$6)/(Peak_Time_Eve*$O48*CT$6))),"-") -> 0.21851291 | CU15: =IF(CU$6<Total_Lanes,900*Peak_Time_Eve*(($CN15/CU$6-1)+SQRT(($CN15/CU$6-1)^2+8*($CN15/CU$6)/(Peak_Time_Eve*$O48*CU$6))),"-") -> 0.14892258 | CV15: =IF(CV$6<Total_Lanes,900*Peak_Time_Eve*(($CN15/CV$6-1)+SQRT(($CN15/CV$6-1)^2+8*($CN15/CV$6)/(Peak_Time_Eve*$O48*CV$6))),"-") -> 0.10814871 | ... DI15: =IF(DI$6<Total_Lanes,900*Peak_Time_Eve*(($CN15/DI$6-1)+SQRT(($CN15/DI$6-1)^2+8*($CN15/DI$6)/(Peak_Time_Eve*$O48*DI$6))),"-") -> - | DJ15: =3600/O48 -> 2.4
H16: 9 | I16: ='Input-Detail'!E23 -> 23958895 | J16: ='Input-Detail'!F23 -> 0.5 | K16: =AC16 -> 7231.9524 | L16: =AD63 -> 11.941956 | M16: =AD16 -> 29.10998 | N16: =SUM(L16:M16) -> 41.051936 | O16: =$S$34*N16 -> 10673.503 | P16: =BC63 -> 6.4220686 | Q16: =BC16 -> 24.781565 | R16: =SUM(P16:Q16) -> 31.203633 | S16: =$S$34*R16 -> 8112.9447 | V16: 9 | W16: =W$7+(W$27-W$7)*$V16/20 -> 23958895 | X16: =J16 -> 0.5 | Y16: ='Input-Detail'!E23/Z16 -> 10331.361 | Z16: =Z15 -> 2319.0455 | AA16: =AA15 -> 2 | AB16: =AB15 -> 0.7 | AC16: =Y16*AB16 -> 7231.9524 | AD16: =Peak_Time_Eve*$BH16*(3600/K49+BK16)/3600 -> 29.10998 | AE16: =IF(AE$6<Total_Lanes,($BI16*($CH16+BM16)+$CM16*CO16)*Peak_Time_Eve/3600,"-") -> 10225.581 | AF16: =IF(AF$6<Total_Lanes,($BI16*($CH16+BN16)+$CM16*CP16)*Peak_Time_Eve/3600,"-") -> 1515.3949 | AG16: =IF(AG$6<Total_Lanes,($BI16*($CH16+BO16)+$CM16*CQ16)*Peak_Time_Eve/3600,"-") -> 24.781565 | AH16: =IF(AH$6<Total_Lanes,($BI16*($CH16+BP16)+$CM16*CR16)*Peak_Time_Eve/3600,"-") -> 24.929494 | AI16: =IF(AI$6<Total_Lanes,($BI16*($CH16+BQ16)+$CM16*CS16)*Peak_Time_Eve/3600,"-") -> 66.444461 | AJ16: =IF(AJ$6<Total_Lanes,($BI16*($CH16+BR16)+$CM16*CT16)*Peak_Time_Eve/3600,"-") -> 992.86662 | AK16: =IF(AK$6<Total_Lanes,($BI16*($CH16+BS16)+$CM16*CU16)*Peak_Time_Eve/3600,"-") -> 2622.3182 | AL16: =IF(AL$6<Total_Lanes,($BI16*($CH16+BT16)+$CM16*CV16)*Peak_Time_Eve/3600,"-") -> 5077.7346 | ... AY16: =IF(AY$6<Total_Lanes,($BI16*($CH16+CG16)+$CM16*DI16)*Peak_Time_Eve/3600,"-") -> - | AZ16: =SUMIF(AE16:AY16,BA16,$AE$6:$AY$6) -> 3 | BA16: =MIN(AE16:AY16) -> 24.781565 | BB16: =IF((SUMIF($BM14:$CG14,$AZ16,$BM16:$CG16)+$CH16)<(SUMIF($CO14:$DI14,$AZ16,$CO16:$DI16)+$DJ16),AZ16+1,AZ16) -> 3 | BC16: =SUMIF($AE$6:$AY$6,$BB16,$AE16:$AY16) -> 24.781565 | BF16: 9 | BG16: =$X16 -> 0.5 | BH16: =$AC16 -> 7231.9524 | BI16: =BH16*(1-BG16) -> 3615.9762 | BJ16: =Peak_Arrival_Manual/K49 -> 6.6041788 | BK16: =900*Peak_Time_Eve*(BJ16/Total_Lanes-1+SQRT((BJ16/Total_Lanes-1)^2+8*(BJ16/Total_Lanes)/(Peak_Time_Eve*$K49*Total_Lanes))) -> 0.67034129 | BL16: =Peak_Arrival_Manual/N49 -> 6.7962775 | BM16: =IF(BM$6<Total_Lanes,900*Peak_Time_Eve*(($BL16/(Total_Lanes-BM$6))-1+SQRT((($BL16/(Total_Lanes-BM$6))-1)^2+8*($BL16/(Total_Lanes-BM$6))/(Peak_Time_Eve*$N49*(Total_Lanes-BM$6)))),"-") -> 0.99375386 | BN16: =IF(BN$6<Total_Lanes,900*Peak_Time_Eve*(($BL16/(Total_Lanes-BN$6))-1+SQRT((($BL16/(Total_Lanes-BN$6))-1)^2+8*($BL16/(Total_Lanes-BN$6))/(Peak_Time_Eve*$N49*(Total_Lanes-BN$6)))),"-") -> 1.4335893 | BO16: =IF(BO$6<Total_Lanes,900*Peak_Time_Eve*(($BL16/(Total_Lanes-BO$6))-1+SQRT((($BL16/(Total_Lanes-BO$6))-1)^2+8*($BL16/(Total_Lanes-BO$6))/(Peak_Time_Eve*$N49*(Total_Lanes-BO$6)))),"-") -> 2.3125008 | BP16: =IF(BP$6<Total_Lanes,900*Peak_Time_Eve*(($BL16/(Total_Lanes-BP$6))-1+SQRT((($BL16/(Total_Lanes-BP$6))-1)^2+8*($BL16/(Total_Lanes-BP$6))/(Peak_Time_Eve*$N49*(Total_Lanes-BP$6)))),"-") -> 4.7339511 | BQ16: =IF(BQ$6<Total_Lanes,900*Peak_Time_Eve*(($BL16/(Total_Lanes-BQ$6))-1+SQRT((($BL16/(Total_Lanes-BQ$6))-1)^2+8*($BL16/(Total_Lanes-BQ$6))/(Peak_Time_Eve*$N49*(Total_Lanes-BQ$6)))),"-") -> 25.86243 | BR16: =IF(BR$6<Total_Lanes,900*Peak_Time_Eve*(($BL16/(Total_Lanes-BR$6))-1+SQRT((($BL16/(Total_Lanes-BR$6))-1)^2+8*($BL16/(Total_Lanes-BR$6))/(Peak_Time_Eve*$N49*(Total_Lanes-BR$6)))),"-") -> 487.20509 | BS16: =IF(BS$6<Total_Lanes,900*Peak_Time_Eve*(($BL16/(Total_Lanes-BS$6))-1+SQRT((($BL16/(Total_Lanes-BS$6))-1)^2+8*($BL16/(Total_Lanes-BS$6))/(Peak_Time_Eve*$N49*(Total_Lanes-BS$6)))),"-") -> 1298.4198 | BT16: =IF(BT$6<Total_Lanes,900*Peak_Time_Eve*(($BL16/(Total_Lanes-BT$6))-1+SQRT((($BL16/(Total_Lanes-BT$6))-1)^2+8*($BL16/(Total_Lanes-BT$6))/(Peak_Time_Eve*$N49*(Total_Lanes-BT$6)))),"-") -> 2520.7544 | ... CG16: =IF(CG$6<Total_Lanes,900*Peak_Time_Eve*(($BL16/(Total_Lanes-CG$6))-1+SQRT((($BL16/(Total_Lanes-CG$6))-1)^2+8*($BL16/(Total_Lanes-CG$6))/(Peak_Time_Eve*$N49*(Total_Lanes-CG$6)))),"-") -> - | CH16: =3600/N49 -> 6.76625 | CJ16: 9 | CK16: =$X16 -> 0.5 | CL16: =$AC16 -> 7231.9524 | CM16: =CL16*CK16 -> 3615.9762 | CN16: =CM16/O48 -> 2.4106508 | CO16: =IF(CO$6<Total_Lanes,900*Peak_Time_Eve*(($CN16/CO$6-1)+SQRT(($CN16/CO$6-1)^2+8*($CN16/CO$6)/(Peak_Time_Eve*$O49*CO$6))),"-") -> 5082.4409 | CP16: =IF(CP$6<Total_Lanes,900*Peak_Time_Eve*(($CN16/CP$6-1)+SQRT(($CN16/CP$6-1)^2+8*($CN16/CP$6)/(Peak_Time_Eve*$O49*CP$6))),"-") -> 746.14994 | CQ16: =IF(CQ$6<Total_Lanes,900*Peak_Time_Eve*(($CN16/CQ$6-1)+SQRT(($CN16/CQ$6-1)^2+8*($CN16/CQ$6)/(Peak_Time_Eve*$O49*CQ$6))),"-") -> 3.2572863 | CR16: =IF(CR$6<Total_Lanes,900*Peak_Time_Eve*(($CN16/CR$6-1)+SQRT(($CN16/CR$6-1)^2+8*($CN16/CR$6)/(Peak_Time_Eve*$O49*CR$6))),"-") -> 0.90947379 | CS16: =IF(CS$6<Total_Lanes,900*Peak_Time_Eve*(($CN16/CS$6-1)+SQRT(($CN16/CS$6-1)^2+8*($CN16/CS$6)/(Peak_Time_Eve*$O49*CS$6))),"-") -> 0.44676676 | CT16: =IF(CT$6<Total_Lanes,900*Peak_Time_Eve*(($CN16/CT$6-1)+SQRT(($CN16/CT$6-1)^2+8*($CN16/CT$6)/(Peak_Time_Eve*$O49*CT$6))),"-") -> 0.26861139 | CU16: =IF(CU$6<Total_Lanes,900*Peak_Time_Eve*(($CN16/CU$6-1)+SQRT(($CN16/CU$6-1)^2+8*($CN16/CU$6)/(Peak_Time_Eve*$O49*CU$6))),"-") -> 0.18007908 | CV16: =IF(CV$6<Total_Lanes,900*Peak_Time_Eve*(($CN16/CV$6-1)+SQRT(($CN16/CV$6-1)^2+8*($CN16/CV$6)/(Peak_Time_Eve*$O49*CV$6))),"-") -> 0.12938144 | ... DI16: =IF(DI$6<Total_Lanes,900*Peak_Time_Eve*(($CN16/DI$6-1)+SQRT(($CN16/DI$6-1)^2+8*($CN16/DI$6)/(Peak_Time_Eve*$O49*DI$6))),"-") -> - | DJ16: =3600/O49 -> 2.4
H17: 10 | I17: ='Input-Detail'!E24 -> 24508086 | J17: ='Input-Detail'!F24 -> 0.55 | K17: =AC17 -> 7397.7249 | L17: =AD64 -> 12.222924 | M17: =AD17 -> 29.334231 | N17: =SUM(L17:M17) -> 41.557156 | O17: =$S$34*N17 -> 10804.86 | P17: =BC64 -> 5.9585732 | Q17: =BC17 -> 21.099004 | R17: =SUM(P17:Q17) -> 27.057577 | S17: =$S$34*R17 -> 7034.9701 | V17: 10 | W17: =W$7+(W$27-W$7)*$V17/20 -> 24508086 | X17: =J17 -> 0.55 | Y17: ='Input-Detail'!E24/Z17 -> 10568.178 | Z17: =Z16 -> 2319.0455 | AA17: =AA16 -> 2 | AB17: =AB16 -> 0.7 | AC17: =Y17*AB17 -> 7397.7249 | AD17: =Peak_Time_Eve*$BH17*(3600/K50+BK17)/3600 -> 29.334231 | AE17: =IF(AE$6<Total_Lanes,($BI17*($CH17+BM17)+$CM17*CO17)*Peak_Time_Eve/3600,"-") -> 13958.113 | AF17: =IF(AF$6<Total_Lanes,($BI17*($CH17+BN17)+$CM17*CP17)*Peak_Time_Eve/3600,"-") -> 2923.9371 | AG17: =IF(AG$6<Total_Lanes,($BI17*($CH17+BO17)+$CM17*CQ17)*Peak_Time_Eve/3600,"-") -> 32.465685 | AH17: =IF(AH$6<Total_Lanes,($BI17*($CH17+BP17)+$CM17*CR17)*Peak_Time_Eve/3600,"-") -> 21.099004 | AI17: =IF(AI$6<Total_Lanes,($BI17*($CH17+BQ17)+$CM17*CS17)*Peak_Time_Eve/3600,"-") -> 29.059781 | AJ17: =IF(AJ$6<Total_Lanes,($BI17*($CH17+BR17)+$CM17*CT17)*Peak_Time_Eve/3600,"-") -> 361.92455 | AK17: =IF(AK$6<Total_Lanes,($BI17*($CH17+BS17)+$CM17*CU17)*Peak_Time_Eve/3600,"-") -> 1725.0842 | AL17: =IF(AL$6<Total_Lanes,($BI17*($CH17+BT17)+$CM17*CV17)*Peak_Time_Eve/3600,"-") -> 3810.7528 | ... AY17: =IF(AY$6<Total_Lanes,($BI17*($CH17+CG17)+$CM17*DI17)*Peak_Time_Eve/3600,"-") -> - | AZ17: =SUMIF(AE17:AY17,BA17,$AE$6:$AY$6) -> 4 | BA17: =MIN(AE17:AY17) -> 21.099004 | BB17: =IF((SUMIF($BM15:$CG15,$AZ17,$BM17:$CG17)+$CH17)<(SUMIF($CO15:$DI15,$AZ17,$CO17:$DI17)+$DJ17),AZ17+1,AZ17) -> 4 | BC17: =SUMIF($AE$6:$AY$6,$BB17,$AE17:$AY17) -> 21.099004 | BF17: 10 | BG17: =$X17 -> 0.55 | BH17: =$AC17 -> 7397.7249 | BI17: =BH17*(1-BG17) -> 3328.9762 | BJ17: =Peak_Arrival_Manual/K50 -> 6.0800052 | BK17: =900*Peak_Time_Eve*(BJ17/Total_Lanes-1+SQRT((BJ17/Total_Lanes-1)^2+8*(BJ17/Total_Lanes)/(Peak_Time_Eve*$K50*Total_Lanes))) -> 0.562548 | BL17: =Peak_Arrival_Manual/N50 -> 6.2765072 | BM17: =IF(BM$6<Total_Lanes,900*Peak_Time_Eve*(($BL17/(Total_Lanes-BM$6))-1+SQRT((($BL17/(Total_Lanes-BM$6))-1)^2+8*($BL17/(Total_Lanes-BM$6))/(Peak_Time_Eve*$N50*(Total_Lanes-BM$6)))),"-") -> 0.81948644 | BN17: =IF(BN$6<Total_Lanes,900*Peak_Time_Eve*(($BL17/(Total_Lanes-BN$6))-1+SQRT((($BL17/(Total_Lanes-BN$6))-1)^2+8*($BL17/(Total_Lanes-BN$6))/(Peak_Time_Eve*$N50*(Total_Lanes-BN$6)))),"-") -> 1.1431603 | BO17: =IF(BO$6<Total_Lanes,900*Peak_Time_Eve*(($BL17/(Total_Lanes-BO$6))-1+SQRT((($BL17/(Total_Lanes-BO$6))-1)^2+8*($BL17/(Total_Lanes-BO$6))/(Peak_Time_Eve*$N50*(Total_Lanes-BO$6)))),"-") -> 1.7352734 | BP17: =IF(BP$6<Total_Lanes,900*Peak_Time_Eve*(($BL17/(Total_Lanes-BP$6))-1+SQRT((($BL17/(Total_Lanes-BP$6))-1)^2+8*($BL17/(Total_Lanes-BP$6))/(Peak_Time_Eve*$N50*(Total_Lanes-BP$6)))),"-") -> 3.0775739 | BQ17: =IF(BQ$6<Total_Lanes,900*Peak_Time_Eve*(($BL17/(Total_Lanes-BQ$6))-1+SQRT((($BL17/(Total_Lanes-BQ$6))-1)^2+8*($BL17/(Total_Lanes-BQ$6))/(Peak_Time_Eve*$N50*(Total_Lanes-BQ$6)))),"-") -> 8.2298967 | BR17: =IF(BR$6<Total_Lanes,900*Peak_Time_Eve*(($BL17/(Total_Lanes-BR$6))-1+SQRT((($BL17/(Total_Lanes-BR$6))-1)^2+8*($BL17/(Total_Lanes-BR$6))/(Peak_Time_Eve*$N50*(Total_Lanes-BR$6)))),"-") -> 188.50424 | BS17: =IF(BS$6<Total_Lanes,900*Peak_Time_Eve*(($BL17/(Total_Lanes-BS$6))-1+SQRT((($BL17/(Total_Lanes-BS$6))-1)^2+8*($BL17/(Total_Lanes-BS$6))/(Peak_Time_Eve*$N50*(Total_Lanes-BS$6)))),"-") -> 925.71216 | BT17: =IF(BT$6<Total_Lanes,900*Peak_Time_Eve*(($BL17/(Total_Lanes-BT$6))-1+SQRT((($BL17/(Total_Lanes-BT$6))-1)^2+8*($BL17/(Total_Lanes-BT$6))/(Peak_Time_Eve*$N50*(Total_Lanes-BT$6)))),"-") -> 2053.5243 | ... CG17: =IF(CG$6<Total_Lanes,900*Peak_Time_Eve*(($BL17/(Total_Lanes-CG$6))-1+SQRT((($BL17/(Total_Lanes-CG$6))-1)^2+8*($BL17/(Total_Lanes-CG$6))/(Peak_Time_Eve*$N50*(Total_Lanes-CG$6)))),"-") -> - | CH17: =3600/N50 -> 6.7875 | CJ17: 10 | CK17: =$X17 -> 0.55 | CL17: =$AC17 -> 7397.7249 | CM17: =CL17*CK17 -> 4068.7487 | CN17: =CM17/O49 -> 2.7124991 | CO17: =IF(CO$6<Total_Lanes,900*Peak_Time_Eve*(($CN17/CO$6-1)+SQRT(($CN17/CO$6-1)^2+8*($CN17/CO$6)/(Peak_Time_Eve*$O50*CO$6))),"-") -> 6168.796 | CP17: =IF(CP$6<Total_Lanes,900*Peak_Time_Eve*(($CN17/CP$6-1)+SQRT(($CN17/CP$6-1)^2+8*($CN17/CP$6)/(Peak_Time_Eve*$O50*CP$6))),"-") -> 1287.0507 | CQ17: =IF(CQ$6<Total_Lanes,900*Peak_Time_Eve*(($CN17/CQ$6-1)+SQRT(($CN17/CQ$6-1)^2+8*($CN17/CQ$6)/(Peak_Time_Eve*$O50*CQ$6))),"-") -> 7.3895257 | CR17: =IF(CR$6<Total_Lanes,900*Peak_Time_Eve*(($CN17/CR$6-1)+SQRT(($CN17/CR$6-1)^2+8*($CN17/CR$6)/(Peak_Time_Eve*$O50*CR$6))),"-") -> 1.2627004 | CS17: =IF(CS$6<Total_Lanes,900*Peak_Time_Eve*(($CN17/CS$6-1)+SQRT(($CN17/CS$6-1)^2+8*($CN17/CS$6)/(Peak_Time_Eve*$O50*CS$6))),"-") -> 0.56898336 | CT17: =IF(CT$6<Total_Lanes,900*Peak_Time_Eve*(($CN17/CT$6-1)+SQRT(($CN17/CT$6-1)^2+8*($CN17/CT$6)/(Peak_Time_Eve*$O50*CT$6))),"-") -> 0.32998263 | CU17: =IF(CU$6<Total_Lanes,900*Peak_Time_Eve*(($CN17/CU$6-1)+SQRT(($CN17/CU$6-1)^2+8*($CN17/CU$6)/(Peak_Time_Eve*$O50*CU$6))),"-") -> 0.21688817 | CV17: =IF(CV$6<Total_Lanes,900*Peak_Time_Eve*(($CN17/CV$6-1)+SQRT(($CN17/CV$6-1)^2+8*($CN17/CV$6)/(Peak_Time_Eve*$O50*CV$6))),"-") -> 0.15389068 | ... DI17: =IF(DI$6<Total_Lanes,900*Peak_Time_Eve*(($CN17/DI$6-1)+SQRT(($CN17/DI$6-1)^2+8*($CN17/DI$6)/(Peak_Time_Eve*$O50*DI$6))),"-") -> - | DJ17: =3600/O50 -> 2.4
H18: 11 | I18: ='Input-Detail'!E25 -> 25057278 | J18: ='Input-Detail'!F25 -> 0.6 | K18: =AC18 -> 7563.4974 | L18: =AD65 -> 12.503999 | M18: =AD18 -> 29.592191 | N18: =SUM(L18:M18) -> 42.096191 | O18: =$S$34*N18 -> 10945.01 | P18: =BC65 -> 5.4638688 | Q18: =BC18 -> 19.715581 | R18: =SUM(P18:Q18) -> 25.17945 | S18: =$S$34*R18 -> 6546.657 | V18: 11 | W18: =W$7+(W$27-W$7)*$V18/20 -> 25057278 | X18: =J18 -> 0.6 | Y18: ='Input-Detail'!E25/Z18 -> 10804.996 | Z18: =Z17 -> 2319.0455 | AA18: =AA17 -> 2 | AB18: =AB17 -> 0.7 | AC18: =Y18*AB18 -> 7563.4974 | AD18: =Peak_Time_Eve*$BH18*(3600/K51+BK18)/3600 -> 29.592191 | AE18: =IF(AE$6<Total_Lanes,($BI18*($CH18+BM18)+$CM18*CO18)*Peak_Time_Eve/3600,"-") -> 18404.525 | AF18: =IF(AF$6<Total_Lanes,($BI18*($CH18+BN18)+$CM18*CP18)*Peak_Time_Eve/3600,"-") -> 4675.2444 | AG18: =IF(AG$6<Total_Lanes,($BI18*($CH18+BO18)+$CM18*CQ18)*Peak_Time_Eve/3600,"-") -> 193.28161 | AH18: =IF(AH$6<Total_Lanes,($BI18*($CH18+BP18)+$CM18*CR18)*Peak_Time_Eve/3600,"-") -> 19.715581 | AI18: =IF(AI$6<Total_Lanes,($BI18*($CH18+BQ18)+$CM18*CS18)*Peak_Time_Eve/3600,"-") -> 20.569046 | AJ18: =IF(AJ$6<Total_Lanes,($BI18*($CH18+BR18)+$CM18*CT18)*Peak_Time_Eve/3600,"-") -> 47.379863 | AK18: =IF(AK$6<Total_Lanes,($BI18*($CH18+BS18)+$CM18*CU18)*Peak_Time_Eve/3600,"-") -> 903.60968 | AL18: =IF(AL$6<Total_Lanes,($BI18*($CH18+BT18)+$CM18*CV18)*Peak_Time_Eve/3600,"-") -> 2626.2385 | ... AY18: =IF(AY$6<Total_Lanes,($BI18*($CH18+CG18)+$CM18*DI18)*Peak_Time_Eve/3600,"-") -> - | AZ18: =SUMIF(AE18:AY18,BA18,$AE$6:$AY$6) -> 4 | BA18: =MIN(AE18:AY18) -> 19.715581 | BB18: =IF((SUMIF($BM16:$CG16,$AZ18,$BM18:$CG18)+$CH18)<(SUMIF($CO16:$DI16,$AZ18,$CO18:$DI18)+$DJ18),AZ18+1,AZ18) -> 4 | BC18: =SUMIF($AE$6:$AY$6,$BB18,$AE18:$AY18) -> 19.715581 | BF18: 11 | BG18: =$X18 -> 0.6 | BH18: =$AC18 -> 7563.4974 | BI18: =BH18*(1-BG18) -> 3025.399 | BJ18: =Peak_Arrival_Manual/K51 -> 5.525555 | BK18: =900*Peak_Time_Eve*(BJ18/Total_Lanes-1+SQRT((BJ18/Total_Lanes-1)^2+8*(BJ18/Total_Lanes)/(Peak_Time_Eve*$K51*Total_Lanes))) -> 0.46750188 | BL18: =Peak_Arrival_Manual/N51 -> 5.7219959 | BM18: =IF(BM$6<Total_Lanes,900*Peak_Time_Eve*(($BL18/(Total_Lanes-BM$6))-1+SQRT((($BL18/(Total_Lanes-BM$6))-1)^2+8*($BL18/(Total_Lanes-BM$6))/(Peak_Time_Eve*$N51*(Total_Lanes-BM$6)))),"-") -> 0.67078586 | BN18: =IF(BN$6<Total_Lanes,900*Peak_Time_Eve*(($BL18/(Total_Lanes-BN$6))-1+SQRT((($BL18/(Total_Lanes-BN$6))-1)^2+8*($BL18/(Total_Lanes-BN$6))/(Peak_Time_Eve*$N51*(Total_Lanes-BN$6)))),"-") -> 0.91015874 | BO18: =IF(BO$6<Total_Lanes,900*Peak_Time_Eve*(($BL18/(Total_Lanes-BO$6))-1+SQRT((($BL18/(Total_Lanes-BO$6))-1)^2+8*($BL18/(Total_Lanes-BO$6))/(Peak_Time_Eve*$N51*(Total_Lanes-BO$6)))),"-") -> 1.3192472 | BP18: =IF(BP$6<Total_Lanes,900*Peak_Time_Eve*(($BL18/(Total_Lanes-BP$6))-1+SQRT((($BL18/(Total_Lanes-BP$6))-1)^2+8*($BL18/(Total_Lanes-BP$6))/(Peak_Time_Eve*$N51*(Total_Lanes-BP$6)))),"-") -> 2.1333767 | BQ18: =IF(BQ$6<Total_Lanes,900*Peak_Time_Eve*(($BL18/(Total_Lanes-BQ$6))-1+SQRT((($BL18/(Total_Lanes-BQ$6))-1)^2+8*($BL18/(Total_Lanes-BQ$6))/(Peak_Time_Eve*$N51*(Total_Lanes-BQ$6)))),"-") -> 4.326485 | BR18: =IF(BR$6<Total_Lanes,900*Peak_Time_Eve*(($BL18/(Total_Lanes-BR$6))-1+SQRT((($BL18/(Total_Lanes-BR$6))-1)^2+8*($BL18/(Total_Lanes-BR$6))/(Peak_Time_Eve*$N51*(Total_Lanes-BR$6)))),"-") -> 20.770401 | BS18: =IF(BS$6<Total_Lanes,900*Peak_Time_Eve*(($BL18/(Total_Lanes-BS$6))-1+SQRT((($BL18/(Total_Lanes-BS$6))-1)^2+8*($BL18/(Total_Lanes-BS$6))/(Peak_Time_Eve*$N51*(Total_Lanes-BS$6)))),"-") -> 530.41403 | BT18: =IF(BT$6<Total_Lanes,900*Peak_Time_Eve*(($BL18/(Total_Lanes-BT$6))-1+SQRT((($BL18/(Total_Lanes-BT$6))-1)^2+8*($BL18/(Total_Lanes-BT$6))/(Peak_Time_Eve*$N51*(Total_Lanes-BT$6)))),"-") -> 1555.432 | ... CG18: =IF(CG$6<Total_Lanes,900*Peak_Time_Eve*(($BL18/(Total_Lanes-CG$6))-1+SQRT((($BL18/(Total_Lanes-CG$6))-1)^2+8*($BL18/(Total_Lanes-CG$6))/(Peak_Time_Eve*$N51*(Total_Lanes-CG$6)))),"-") -> - | CH18: =3600/N51 -> 6.80875 | CJ18: 11 | CK18: =$X18 -> 0.6 | CL18: =$AC18 -> 7563.4974 | CM18: =CL18*CK18 -> 4538.0984 | CN18: =CM18/O50 -> 3.025399 | CO18: =IF(CO$6<Total_Lanes,900*Peak_Time_Eve*(($CN18/CO$6-1)+SQRT(($CN18/CO$6-1)^2+8*($CN18/CO$6)/(Peak_Time_Eve*$O51*CO$6))),"-") -> 7295.0194 | CP18: =IF(CP$6<Total_Lanes,900*Peak_Time_Eve*(($CN18/CP$6-1)+SQRT(($CN18/CP$6-1)^2+8*($CN18/CP$6)/(Peak_Time_Eve*$O51*CP$6))),"-") -> 1849.2519 | CQ18: =IF(CQ$6<Total_Lanes,900*Peak_Time_Eve*(($CN18/CQ$6-1)+SQRT(($CN18/CQ$6-1)^2+8*($CN18/CQ$6)/(Peak_Time_Eve*$O51*CQ$6))),"-") -> 71.244923 | CR18: =IF(CR$6<Total_Lanes,900*Peak_Time_Eve*(($CN18/CR$6-1)+SQRT(($CN18/CR$6-1)^2+8*($CN18/CR$6)/(Peak_Time_Eve*$O51*CR$6))),"-") -> 1.8586078 | CS18: =IF(CS$6<Total_Lanes,900*Peak_Time_Eve*(($CN18/CS$6-1)+SQRT(($CN18/CS$6-1)^2+8*($CN18/CS$6)/(Peak_Time_Eve*$O51*CS$6))),"-") -> 0.73505536 | CT18: =IF(CT$6<Total_Lanes,900*Peak_Time_Eve*(($CN18/CT$6-1)+SQRT(($CN18/CT$6-1)^2+8*($CN18/CT$6)/(Peak_Time_Eve*$O51*CT$6))),"-") -> 0.40673819 | CU18: =IF(CU$6<Total_Lanes,900*Peak_Time_Eve*(($CN18/CU$6-1)+SQRT(($CN18/CU$6-1)^2+8*($CN18/CU$6)/(Peak_Time_Eve*$O51*CU$6))),"-") -> 0.26094374 | CV18: =IF(CV$6<Total_Lanes,900*Peak_Time_Eve*(($CN18/CV$6-1)+SQRT(($CN18/CV$6-1)^2+8*($CN18/CV$6)/(Peak_Time_Eve*$O51*CV$6))),"-") -> 0.18243588 | ... DI18: =IF(DI$6<Total_Lanes,900*Peak_Time_Eve*(($CN18/DI$6-1)+SQRT(($CN18/DI$6-1)^2+8*($CN18/DI$6)/(Peak_Time_Eve*$O51*DI$6))),"-") -> - | DJ18: =3600/O51 -> 2.4
H19: 12 | I19: ='Input-Detail'!E26 -> 25606469 | J19: ='Input-Detail'!F26 -> 0.65 | K19: =AC19 -> 7729.2699 | L19: =AD66 -> 12.785309 | M19: =AD19 -> 29.879753 | N19: =SUM(L19:M19) -> 42.665062 | O19: =$S$34*N19 -> 11092.916 | P19: =BC66 -> 4.9183643 | Q19: =BC19 -> 17.000005 | R19: =SUM(P19:Q19) -> 21.918369 | S19: =$S$34*R19 -> 5698.776 | V19: 12 | W19: =W$7+(W$27-W$7)*$V19/20 -> 25606469 | X19: =J19 -> 0.65 | Y19: ='Input-Detail'!E26/Z19 -> 11041.814 | Z19: =Z18 -> 2319.0455 | AA19: =AA18 -> 2 | AB19: =AB18 -> 0.7 | AC19: =Y19*AB19 -> 7729.2699 | AD19: =Peak_Time_Eve*$BH19*(3600/K52+BK19)/3600 -> 29.879753 | AE19: =IF(AE$6<Total_Lanes,($BI19*($CH19+BM19)+$CM19*CO19)*Peak_Time_Eve/3600,"-") -> 23627.018 | AF19: =IF(AF$6<Total_Lanes,($BI19*($CH19+BN19)+$CM19*CP19)*Peak_Time_Eve/3600,"-") -> 6798.8205 | AG19: =IF(AG$6<Total_Lanes,($BI19*($CH19+BO19)+$CM19*CQ19)*Peak_Time_Eve/3600,"-") -> 1202.9036 | AH19: =IF(AH$6<Total_Lanes,($BI19*($CH19+BP19)+$CM19*CR19)*Peak_Time_Eve/3600,"-") -> 21.134481 | AI19: =IF(AI$6<Total_Lanes,($BI19*($CH19+BQ19)+$CM19*CS19)*Peak_Time_Eve/3600,"-") -> 17.000005 | AJ19: =IF(AJ$6<Total_Lanes,($BI19*($CH19+BR19)+$CM19*CT19)*Peak_Time_Eve/3600,"-") -> 21.668769 | AK19: =IF(AK$6<Total_Lanes,($BI19*($CH19+BS19)+$CM19*CU19)*Peak_Time_Eve/3600,"-") -> 211.402 | AL19: =IF(AL$6<Total_Lanes,($BI19*($CH19+BT19)+$CM19*CV19)*Peak_Time_Eve/3600,"-") -> 1554.1884 | ... AY19: =IF(AY$6<Total_Lanes,($BI19*($CH19+CG19)+$CM19*DI19)*Peak_Time_Eve/3600,"-") -> - | AZ19: =SUMIF(AE19:AY19,BA19,$AE$6:$AY$6) -> 5 | BA19: =MIN(AE19:AY19) -> 17.000005 | BB19: =IF((SUMIF($BM17:$CG17,$AZ19,$BM19:$CG19)+$CH19)<(SUMIF($CO17:$DI17,$AZ19,$CO19:$DI19)+$DJ19),AZ19+1,AZ19) -> 5 | BC19: =SUMIF($AE$6:$AY$6,$BB19,$AE19:$AY19) -> 17.000005 | BF19: 12 | BG19: =$X19 -> 0.65 | BH19: =$AC19 -> 7729.2699 | BI19: =BH19*(1-BG19) -> 2705.2445 | BJ19: =Peak_Arrival_Manual/K52 -> 4.9408284 | BK19: =900*Peak_Time_Eve*(BJ19/Total_Lanes-1+SQRT((BJ19/Total_Lanes-1)^2+8*(BJ19/Total_Lanes)/(Peak_Time_Eve*$K52*Total_Lanes))) -> 0.38342632 | BL19: =Peak_Arrival_Manual/N52 -> 5.1324499 | BM19: =IF(BM$6<Total_Lanes,900*Peak_Time_Eve*(($BL19/(Total_Lanes-BM$6))-1+SQRT((($BL19/(Total_Lanes-BM$6))-1)^2+8*($BL19/(Total_Lanes-BM$6))/(Peak_Time_Eve*$N52*(Total_Lanes-BM$6)))),"-") -> 0.54296664 | BN19: =IF(BN$6<Total_Lanes,900*Peak_Time_Eve*(($BL19/(Total_Lanes-BN$6))-1+SQRT((($BL19/(Total_Lanes-BN$6))-1)^2+8*($BL19/(Total_Lanes-BN$6))/(Peak_Time_Eve*$N52*(Total_Lanes-BN$6)))),"-") -> 0.71987421 | BO19: =IF(BO$6<Total_Lanes,900*Peak_Time_Eve*(($BL19/(Total_Lanes-BO$6))-1+SQRT((($BL19/(Total_Lanes-BO$6))-1)^2+8*($BL19/(Total_Lanes-BO$6))/(Peak_Time_Eve*$N52*(Total_Lanes-BO$6)))),"-") -> 1.0064322 | BP19: =IF(BP$6<Total_Lanes,900*Peak_Time_Eve*(($BL19/(Total_Lanes-BP$6))-1+SQRT((($BL19/(Total_Lanes-BP$6))-1)^2+8*($BL19/(Total_Lanes-BP$6))/(Peak_Time_Eve*$N52*(Total_Lanes-BP$6)))),"-") -> 1.5262689 | BQ19: =IF(BQ$6<Total_Lanes,900*Peak_Time_Eve*(($BL19/(Total_Lanes-BQ$6))-1+SQRT((($BL19/(Total_Lanes-BQ$6))-1)^2+8*($BL19/(Total_Lanes-BQ$6))/(Peak_Time_Eve*$N52*(Total_Lanes-BQ$6)))),"-") -> 2.6740386 | BR19: =IF(BR$6<Total_Lanes,900*Peak_Time_Eve*(($BL19/(Total_Lanes-BR$6))-1+SQRT((($BL19/(Total_Lanes-BR$6))-1)^2+8*($BL19/(Total_Lanes-BR$6))/(Peak_Time_Eve*$N52*(Total_Lanes-BR$6)))),"-") -> 6.6494678 | BS19: =IF(BS$6<Total_Lanes,900*Peak_Time_Eve*(($BL19/(Total_Lanes-BS$6))-1+SQRT((($BL19/(Total_Lanes-BS$6))-1)^2+8*($BL19/(Total_Lanes-BS$6))/(Peak_Time_Eve*$N52*(Total_Lanes-BS$6)))),"-") -> 133.24736 | BT19: =IF(BT$6<Total_Lanes,900*Peak_Time_Eve*(($BL19/(Total_Lanes-BT$6))-1+SQRT((($BL19/(Total_Lanes-BT$6))-1)^2+8*($BL19/(Total_Lanes-BT$6))/(Peak_Time_Eve*$N52*(Total_Lanes-BT$6)))),"-") -> 1026.8857 | ... CG19: =IF(CG$6<Total_Lanes,900*Peak_Time_Eve*(($BL19/(Total_Lanes-CG$6))-1+SQRT((($BL19/(Total_Lanes-CG$6))-1)^2+8*($BL19/(Total_Lanes-CG$6))/(Peak_Time_Eve*$N52*(Total_Lanes-CG$6)))),"-") -> - | CH19: =3600/N52 -> 6.83 | CJ19: 12 | CK19: =$X19 -> 0.65 | CL19: =$AC19 -> 7729.2699 | CM19: =CL19*CK19 -> 5024.0254 | CN19: =CM19/O51 -> 3.3493503 | CO19: =IF(CO$6<Total_Lanes,900*Peak_Time_Eve*(($CN19/CO$6-1)+SQRT(($CN19/CO$6-1)^2+8*($CN19/CO$6)/(Peak_Time_Eve*$O52*CO$6))),"-") -> 8461.0812 | CP19: =IF(CP$6<Total_Lanes,900*Peak_Time_Eve*(($CN19/CP$6-1)+SQRT(($CN19/CP$6-1)^2+8*($CN19/CP$6)/(Peak_Time_Eve*$O52*CP$6))),"-") -> 2431.8055 | CQ19: =IF(CQ$6<Total_Lanes,900*Peak_Time_Eve*(($CN19/CQ$6-1)+SQRT(($CN19/CQ$6-1)^2+8*($CN19/CQ$6)/(Peak_Time_Eve*$O52*CQ$6))),"-") -> 426.75482 | CR19: =IF(CR$6<Total_Lanes,900*Peak_Time_Eve*(($CN19/CR$6-1)+SQRT(($CN19/CR$6-1)^2+8*($CN19/CR$6)/(Peak_Time_Eve*$O52*CR$6))),"-") -> 3.0724996 | CS19: =IF(CS$6<Total_Lanes,900*Peak_Time_Eve*(($CN19/CS$6-1)+SQRT(($CN19/CS$6-1)^2+8*($CN19/CS$6)/(Peak_Time_Eve*$O52*CS$6))),"-") -> 0.97317604 | CT19: =IF(CT$6<Total_Lanes,900*Peak_Time_Eve*(($CN19/CT$6-1)+SQRT(($CN19/CT$6-1)^2+8*($CN19/CT$6)/(Peak_Time_Eve*$O52*CT$6))),"-") -> 0.50527785 | CU19: =IF(CU$6<Total_Lanes,900*Peak_Time_Eve*(($CN19/CU$6-1)+SQRT(($CN19/CU$6-1)^2+8*($CN19/CU$6)/(Peak_Time_Eve*$O52*CU$6))),"-") -> 0.3145074 | CV19: =IF(CV$6<Total_Lanes,900*Peak_Time_Eve*(($CN19/CV$6-1)+SQRT(($CN19/CV$6-1)^2+8*($CN19/CV$6)/(Peak_Time_Eve*$O52*CV$6))),"-") -> 0.21603463 | ... DI19: =IF(DI$6<Total_Lanes,900*Peak_Time_Eve*(($CN19/DI$6-1)+SQRT(($CN19/DI$6-1)^2+8*($CN19/DI$6)/(Peak_Time_Eve*$O52*DI$6))),"-") -> - | DJ19: =3600/O52 -> 2.4
H20: 13 | I20: ='Input-Detail'!E27 -> 26155661 | J20: ='Input-Detail'!F27 -> 0.7 | K20: =AC20 -> 7895.0424 | L20: =AD67 -> 13.066979 | M20: =AD20 -> 30.193324 | N20: =SUM(L20:M20) -> 43.260304 | O20: =$S$34*N20 -> 11247.679 | P20: =BC67 -> 4.3573267 | Q20: =BC20 -> 15.462329 | R20: =SUM(P20:Q20) -> 19.819656 | S20: =$S$34*R20 -> 5153.1105 | V20: 13 | W20: =W$7+(W$27-W$7)*$V20/20 -> 26155661 | X20: =J20 -> 0.7 | Y20: ='Input-Detail'!E27/Z20 -> 11278.632 | Z20: =Z19 -> 2319.0455 | AA20: =AA19 -> 2 | AB20: =AB19 -> 0.7 | AC20: =Y20*AB20 -> 7895.0424 | AD20: =Peak_Time_Eve*$BH20*(3600/K53+BK20)/3600 -> 30.193324 | AE20: =IF(AE$6<Total_Lanes,($BI20*($CH20+BM20)+$CM20*CO20)*Peak_Time_Eve/3600,"-") -> 29690.008 | AF20: =IF(AF$6<Total_Lanes,($BI20*($CH20+BN20)+$CM20*CP20)*Peak_Time_Eve/3600,"-") -> 9326.4344 | AG20: =IF(AG$6<Total_Lanes,($BI20*($CH20+BO20)+$CM20*CQ20)*Peak_Time_Eve/3600,"-") -> 2544.5733 | AH20: =IF(AH$6<Total_Lanes,($BI20*($CH20+BP20)+$CM20*CR20)*Peak_Time_Eve/3600,"-") -> 31.46571 | AI20: =IF(AI$6<Total_Lanes,($BI20*($CH20+BQ20)+$CM20*CS20)*Peak_Time_Eve/3600,"-") -> 15.462329 | AJ20: =IF(AJ$6<Total_Lanes,($BI20*($CH20+BR20)+$CM20*CT20)*Peak_Time_Eve/3600,"-") -> 15.489016 | AK20: =IF(AK$6<Total_Lanes,($BI20*($CH20+BS20)+$CM20*CU20)*Peak_Time_Eve/3600,"-") -> 26.143372 | AL20: =IF(AL$6<Total_Lanes,($BI20*($CH20+BT20)+$CM20*CV20)*Peak_Time_Eve/3600,"-") -> 630.29075 | ... AY20: =IF(AY$6<Total_Lanes,($BI20*($CH20+CG20)+$CM20*DI20)*Peak_Time_Eve/3600,"-") -> - | AZ20: =SUMIF(AE20:AY20,BA20,$AE$6:$AY$6) -> 5 | BA20: =MIN(AE20:AY20) -> 15.462329 | BB20: =IF((SUMIF($BM18:$CG18,$AZ20,$BM20:$CG20)+$CH20)<(SUMIF($CO18:$DI18,$AZ20,$CO20:$DI20)+$DJ20),AZ20+1,AZ20) -> 5 | BC20: =SUMIF($AE$6:$AY$6,$BB20,$AE20:$AY20) -> 15.462329 | BF20: 13 | BG20: =$X20 -> 0.7 | BH20: =$AC20 -> 7895.0424 | BI20: =BH20*(1-BG20) -> 2368.5127 | BJ20: =Peak_Arrival_Manual/K53 -> 4.3258253 | BK20: =900*Peak_Time_Eve*(BJ20/Total_Lanes-1+SQRT((BJ20/Total_Lanes-1)^2+8*(BJ20/Total_Lanes)/(Peak_Time_Eve*$K53*Total_Lanes))) -> 0.30881156 | BL20: =Peak_Arrival_Manual/N53 -> 4.5075758 | BM20: =IF(BM$6<Total_Lanes,900*Peak_Time_Eve*(($BL20/(Total_Lanes-BM$6))-1+SQRT((($BL20/(Total_Lanes-BM$6))-1)^2+8*($BL20/(Total_Lanes-BM$6))/(Peak_Time_Eve*$N53*(Total_Lanes-BM$6)))),"-") -> 0.4323395 | BN20: =IF(BN$6<Total_Lanes,900*Peak_Time_Eve*(($BL20/(Total_Lanes-BN$6))-1+SQRT((($BL20/(Total_Lanes-BN$6))-1)^2+8*($BL20/(Total_Lanes-BN$6))/(Peak_Time_Eve*$N53*(Total_Lanes-BN$6)))),"-") -> 0.5621152 | BO20: =IF(BO$6<Total_Lanes,900*Peak_Time_Eve*(($BL20/(Total_Lanes-BO$6))-1+SQRT((($BL20/(Total_Lanes-BO$6))-1)^2+8*($BL20/(Total_Lanes-BO$6))/(Peak_Time_Eve*$N53*(Total_Lanes-BO$6)))),"-") -> 0.76349306 | BP20: =IF(BP$6<Total_Lanes,900*Peak_Time_Eve*(($BL20/(Total_Lanes-BP$6))-1+SQRT((($BL20/(Total_Lanes-BP$6))-1)^2+8*($BL20/(Total_Lanes-BP$6))/(Peak_Time_Eve*$N53*(Total_Lanes-BP$6)))),"-") -> 1.1045636 | BQ20: =IF(BQ$6<Total_Lanes,900*Peak_Time_Eve*(($BL20/(Total_Lanes-BQ$6))-1+SQRT((($BL20/(Total_Lanes-BQ$6))-1)^2+8*($BL20/(Total_Lanes-BQ$6))/(Peak_Time_Eve*$N53*(Total_Lanes-BQ$6)))),"-") -> 1.7676422 | BR20: =IF(BR$6<Total_Lanes,900*Peak_Time_Eve*(($BL20/(Total_Lanes-BR$6))-1+SQRT((($BL20/(Total_Lanes-BR$6))-1)^2+8*($BL20/(Total_Lanes-BR$6))/(Peak_Time_Eve*$N53*(Total_Lanes-BR$6)))),"-") -> 3.4356286 | BS20: =IF(BS$6<Total_Lanes,900*Peak_Time_Eve*(($BL20/(Total_Lanes-BS$6))-1+SQRT((($BL20/(Total_Lanes-BS$6))-1)^2+8*($BL20/(Total_Lanes-BS$6))/(Peak_Time_Eve*$N53*(Total_Lanes-BS$6)))),"-") -> 12.128181 | BT20: =IF(BT$6<Total_Lanes,900*Peak_Time_Eve*(($BL20/(Total_Lanes-BT$6))-1+SQRT((($BL20/(Total_Lanes-BT$6))-1)^2+8*($BL20/(Total_Lanes-BT$6))/(Peak_Time_Eve*$N53*(Total_Lanes-BT$6)))),"-") -> 471.55366 | ... CG20: =IF(CG$6<Total_Lanes,900*Peak_Time_Eve*(($BL20/(Total_Lanes-CG$6))-1+SQRT((($BL20/(Total_Lanes-CG$6))-1)^2+8*($BL20/(Total_Lanes-CG$6))/(Peak_Time_Eve*$N53*(Total_Lanes-CG$6)))),"-") -> - | CH20: =3600/N53 -> 6.85125 | CJ20: 13 | CK20: =$X20 -> 0.7 | CL20: =$AC20 -> 7895.0424 | CM20: =CL20*CK20 -> 5526.5297 | CN20: =CM20/O52 -> 3.6843531 | CO20: =IF(CO$6<Total_Lanes,900*Peak_Time_Eve*(($CN20/CO$6-1)+SQRT(($CN20/CO$6-1)^2+8*($CN20/CO$6)/(Peak_Time_Eve*$O53*CO$6))),"-") -> 9666.9641 | CP20: =IF(CP$6<Total_Lanes,900*Peak_Time_Eve*(($CN20/CP$6-1)+SQRT(($CN20/CP$6-1)^2+8*($CN20/CP$6)/(Peak_Time_Eve*$O53*CP$6))),"-") -> 3034.4582 | CQ20: =IF(CQ$6<Total_Lanes,900*Peak_Time_Eve*(($CN20/CQ$6-1)+SQRT(($CN20/CQ$6-1)^2+8*($CN20/CQ$6)/(Peak_Time_Eve*$O53*CQ$6))),"-") -> 825.50833 | CR20: =IF(CR$6<Total_Lanes,900*Peak_Time_Eve*(($CN20/CR$6-1)+SQRT(($CN20/CR$6-1)^2+8*($CN20/CR$6)/(Peak_Time_Eve*$O53*CR$6))),"-") -> 6.8388004 | CS20: =IF(CS$6<Total_Lanes,900*Peak_Time_Eve*(($CN20/CS$6-1)+SQRT(($CN20/CS$6-1)^2+8*($CN20/CS$6)/(Peak_Time_Eve*$O53*CS$6))),"-") -> 1.3422956 | CT20: =IF(CT$6<Total_Lanes,900*Peak_Time_Eve*(($CN20/CT$6-1)+SQRT(($CN20/CT$6-1)^2+8*($CN20/CT$6)/(Peak_Time_Eve*$O53*CT$6))),"-") -> 0.63613619 | CU20: =IF(CU$6<Total_Lanes,900*Peak_Time_Eve*(($CN20/CU$6-1)+SQRT(($CN20/CU$6-1)^2+8*($CN20/CU$6)/(Peak_Time_Eve*$O53*CU$6))),"-") -> 0.38089842 | CV20: =IF(CV$6<Total_Lanes,900*Peak_Time_Eve*(($CN20/CV$6-1)+SQRT(($CN20/CV$6-1)^2+8*($CN20/CV$6)/(Peak_Time_Eve*$O53*CV$6))),"-") -> 0.25608217 | ... DI20: =IF(DI$6<Total_Lanes,900*Peak_Time_Eve*(($CN20/DI$6-1)+SQRT(($CN20/DI$6-1)^2+8*($CN20/DI$6)/(Peak_Time_Eve*$O53*DI$6))),"-") -> - | DJ20: =3600/O53 -> 2.4
H21: 14 | I21: ='Input-Detail'!E28 -> 26704852 | J21: ='Input-Detail'!F28 -> 0.75 | K21: =AC21 -> 8060.8149 | L21: =AD68 -> 13.349132 | M21: =AD21 -> 30.529781 | N21: =SUM(L21:M21) -> 43.878914 | O21: =$S$34*N21 -> 11408.518 | P21: =BC68 -> 3.7384597 | Q21: =BC21 -> 12.729265 | R21: =SUM(P21:Q21) -> 16.467725 | S21: =$S$34*R21 -> 4281.6085 | V21: 14 | W21: =W$7+(W$27-W$7)*$V21/20 -> 26704852 | X21: =J21 -> 0.75 | Y21: ='Input-Detail'!E28/Z21 -> 11515.45 | Z21: =Z20 -> 2319.0455 | AA21: =AA20 -> 2 | AB21: =AB20 -> 0.7 | AC21: =Y21*AB21 -> 8060.8149 | AD21: =Peak_Time_Eve*$BH21*(3600/K54+BK21)/3600 -> 30.529781 | AE21: =IF(AE$6<Total_Lanes,($BI21*($CH21+BM21)+$CM21*CO21)*Peak_Time_Eve/3600,"-") -> 36660.118 | AF21: =IF(AF$6<Total_Lanes,($BI21*($CH21+BN21)+$CM21*CP21)*Peak_Time_Eve/3600,"-") -> 12291.224 | AG21: =IF(AG$6<Total_Lanes,($BI21*($CH21+BO21)+$CM21*CQ21)*Peak_Time_Eve/3600,"-") -> 4171.7774 | AH21: =IF(AH$6<Total_Lanes,($BI21*($CH21+BP21)+$CM21*CR21)*Peak_Time_Eve/3600,"-") -> 217.83262 | AI21: =IF(AI$6<Total_Lanes,($BI21*($CH21+BQ21)+$CM21*CS21)*Peak_Time_Eve/3600,"-") -> 15.716735 | AJ21: =IF(AJ$6<Total_Lanes,($BI21*($CH21+BR21)+$CM21*CT21)*Peak_Time_Eve/3600,"-") -> 12.729265 | AK21: =IF(AK$6<Total_Lanes,($BI21*($CH21+BS21)+$CM21*CU21)*Peak_Time_Eve/3600,"-") -> 14.363325 | AL21: =IF(AL$6<Total_Lanes,($BI21*($CH21+BT21)+$CM21*CV21)*Peak_Time_Eve/3600,"-") -> 47.397922 | ... AY21: =IF(AY$6<Total_Lanes,($BI21*($CH21+CG21)+$CM21*DI21)*Peak_Time_Eve/3600,"-") -> - | AZ21: =SUMIF(AE21:AY21,BA21,$AE$6:$AY$6) -> 6 | BA21: =MIN(AE21:AY21) -> 12.729265 | BB21: =IF((SUMIF($BM19:$CG19,$AZ21,$BM21:$CG21)+$CH21)<(SUMIF($CO19:$DI19,$AZ21,$CO21:$DI21)+$DJ21),AZ21+1,AZ21) -> 6 | BC21: =SUMIF($AE$6:$AY$6,$BB21,$AE21:$AY21) -> 12.729265 | BF21: 14 | BG21: =$X21 -> 0.75 | BH21: =$AC21 -> 8060.8149 | BI21: =BH21*(1-BG21) -> 2015.2037 | BJ21: =Peak_Arrival_Manual/K54 -> 3.6805457 | BK21: =900*Peak_Time_Eve*(BJ21/Total_Lanes-1+SQRT((BJ21/Total_Lanes-1)^2+8*(BJ21/Total_Lanes)/(Peak_Time_Eve*$K54*Total_Lanes))) -> 0.24237605 | BL21: =Peak_Arrival_Manual/N54 -> 3.8470799 | BM21: =IF(BM$6<Total_Lanes,900*Peak_Time_Eve*(($BL21/(Total_Lanes-BM$6))-1+SQRT((($BL21/(Total_Lanes-BM$6))-1)^2+8*($BL21/(Total_Lanes-BM$6))/(Peak_Time_Eve*$N54*(Total_Lanes-BM$6)))),"-") -> 0.33597547 | BN21: =IF(BN$6<Total_Lanes,900*Peak_Time_Eve*(($BL21/(Total_Lanes-BN$6))-1+SQRT((($BL21/(Total_Lanes-BN$6))-1)^2+8*($BL21/(Total_Lanes-BN$6))/(Peak_Time_Eve*$N54*(Total_Lanes-BN$6)))),"-") -> 0.429616 | BO21: =IF(BO$6<Total_Lanes,900*Peak_Time_Eve*(($BL21/(Total_Lanes-BO$6))-1+SQRT((($BL21/(Total_Lanes-BO$6))-1)^2+8*($BL21/(Total_Lanes-BO$6))/(Peak_Time_Eve*$N54*(Total_Lanes-BO$6)))),"-") -> 0.56994108 | BP21: =IF(BP$6<Total_Lanes,900*Peak_Time_Eve*(($BL21/(Total_Lanes-BP$6))-1+SQRT((($BL21/(Total_Lanes-BP$6))-1)^2+8*($BL21/(Total_Lanes-BP$6))/(Peak_Time_Eve*$N54*(Total_Lanes-BP$6)))),"-") -> 0.79545858 | BQ21: =IF(BQ$6<Total_Lanes,900*Peak_Time_Eve*(($BL21/(Total_Lanes-BQ$6))-1+SQRT((($BL21/(Total_Lanes-BQ$6))-1)^2+8*($BL21/(Total_Lanes-BQ$6))/(Peak_Time_Eve*$N54*(Total_Lanes-BQ$6)))),"-") -> 1.1970559 | BR21: =IF(BR$6<Total_Lanes,900*Peak_Time_Eve*(($BL21/(Total_Lanes-BR$6))-1+SQRT((($BL21/(Total_Lanes-BR$6))-1)^2+8*($BL21/(Total_Lanes-BR$6))/(Peak_Time_Eve*$N54*(Total_Lanes-BR$6)))),"-") -> 2.0435265 | BS21: =IF(BS$6<Total_Lanes,900*Peak_Time_Eve*(($BL21/(Total_Lanes-BS$6))-1+SQRT((($BL21/(Total_Lanes-BS$6))-1)^2+8*($BL21/(Total_Lanes-BS$6))/(Peak_Time_Eve*$N54*(Total_Lanes-BS$6)))),"-") -> 4.561386 | BT21: =IF(BT$6<Total_Lanes,900*Peak_Time_Eve*(($BL21/(Total_Lanes-BT$6))-1+SQRT((($BL21/(Total_Lanes-BT$6))-1)^2+8*($BL21/(Total_Lanes-BT$6))/(Peak_Time_Eve*$N54*(Total_Lanes-BT$6)))),"-") -> 34.550163 | ... CG21: =IF(CG$6<Total_Lanes,900*Peak_Time_Eve*(($BL21/(Total_Lanes-CG$6))-1+SQRT((($BL21/(Total_Lanes-CG$6))-1)^2+8*($BL21/(Total_Lanes-CG$6))/(Peak_Time_Eve*$N54*(Total_Lanes-CG$6)))),"-") -> - | CH21: =3600/N54 -> 6.8725 | CJ21: 14 | CK21: =$X21 -> 0.75 | CL21: =$AC21 -> 8060.8149 | CM21: =CL21*CK21 -> 6045.6111 | CN21: =CM21/O53 -> 4.0304074 | CO21: =IF(CO$6<Total_Lanes,900*Peak_Time_Eve*(($CN21/CO$6-1)+SQRT(($CN21/CO$6-1)^2+8*($CN21/CO$6)/(Peak_Time_Eve*$O54*CO$6))),"-") -> 10912.658 | CP21: =IF(CP$6<Total_Lanes,900*Peak_Time_Eve*(($CN21/CP$6-1)+SQRT(($CN21/CP$6-1)^2+8*($CN21/CP$6)/(Peak_Time_Eve*$O54*CP$6))),"-") -> 3657.1139 | CQ21: =IF(CQ$6<Total_Lanes,900*Peak_Time_Eve*(($CN21/CQ$6-1)+SQRT(($CN21/CQ$6-1)^2+8*($CN21/CQ$6)/(Peak_Time_Eve*$O54*CQ$6))),"-") -> 1239.6102 | CR21: =IF(CR$6<Total_Lanes,900*Peak_Time_Eve*(($CN21/CR$6-1)+SQRT(($CN21/CR$6-1)^2+8*($CN21/CR$6)/(Peak_Time_Eve*$O54*CR$6))),"-") -> 62.300767 | CS21: =IF(CS$6<Total_Lanes,900*Peak_Time_Eve*(($CN21/CS$6-1)+SQRT(($CN21/CS$6-1)^2+8*($CN21/CS$6)/(Peak_Time_Eve*$O54*CS$6))),"-") -> 1.9895962 | CT21: =IF(CT$6<Total_Lanes,900*Peak_Time_Eve*(($CN21/CT$6-1)+SQRT(($CN21/CT$6-1)^2+8*($CN21/CT$6)/(Peak_Time_Eve*$O54*CT$6))),"-") -> 0.81795997 | CU21: =IF(CU$6<Total_Lanes,900*Peak_Time_Eve*(($CN21/CU$6-1)+SQRT(($CN21/CU$6-1)^2+8*($CN21/CU$6)/(Peak_Time_Eve*$O54*CU$6))),"-") -> 0.46519284 | CV21: =IF(CV$6<Total_Lanes,900*Peak_Time_Eve*(($CN21/CV$6-1)+SQRT(($CN21/CV$6-1)^2+8*($CN21/CV$6)/(Peak_Time_Eve*$O54*CV$6))),"-") -> 0.30454413 | ... DI21: =IF(DI$6<Total_Lanes,900*Peak_Time_Eve*(($CN21/DI$6-1)+SQRT(($CN21/DI$6-1)^2+8*($CN21/DI$6)/(Peak_Time_Eve*$O54*DI$6))),"-") -> - | DJ21: =3600/O54 -> 2.4
H22: 15 | I22: ='Input-Detail'!E29 -> 27254043 | J22: ='Input-Detail'!F29 -> 0.8 | K22: =AC22 -> 8226.5874 | L22: =AD69 -> 13.631888 | M22: =AD22 -> 30.88641 | N22: =SUM(L22:M22) -> 44.518299 | O22: =$S$34*N22 -> 11574.758 | P22: =BC69 -> 3.0976737 | Q22: =BC22 -> 10.549058 | R22: =SUM(P22:Q22) -> 13.646731 | S22: =$S$34*R22 -> 3548.1501 | V22: 15 | W22: =W$7+(W$27-W$7)*$V22/20 -> 27254043 | X22: =J22 -> 0.8 | Y22: ='Input-Detail'!E29/Z22 -> 11752.268 | Z22: =Z21 -> 2319.0455 | AA22: =AA21 -> 2 | AB22: =AB21 -> 0.7 | AC22: =Y22*AB22 -> 8226.5874 | AD22: =Peak_Time_Eve*$BH22*(3600/K55+BK22)/3600 -> 30.88641 | AE22: =IF(AE$6<Total_Lanes,($BI22*($CH22+BM22)+$CM22*CO22)*Peak_Time_Eve/3600,"-") -> 44606.172 | AF22: =IF(AF$6<Total_Lanes,($BI22*($CH22+BN22)+$CM22*CP22)*Peak_Time_Eve/3600,"-") -> 15727.519 | AG22: =IF(AG$6<Total_Lanes,($BI22*($CH22+BO22)+$CM22*CQ22)*Peak_Time_Eve/3600,"-") -> 6103.6465 | AH22: =IF(AH$6<Total_Lanes,($BI22*($CH22+BP22)+$CM22*CR22)*Peak_Time_Eve/3600,"-") -> 1306.35 | AI22: =IF(AI$6<Total_Lanes,($BI22*($CH22+BQ22)+$CM22*CS22)*Peak_Time_Eve/3600,"-") -> 19.513196 | AJ22: =IF(AJ$6<Total_Lanes,($BI22*($CH22+BR22)+$CM22*CT22)*Peak_Time_Eve/3600,"-") -> 11.436718 | AK22: =IF(AK$6<Total_Lanes,($BI22*($CH22+BS22)+$CM22*CU22)*Peak_Time_Eve/3600,"-") -> 10.549058 | AL22: =IF(AL$6<Total_Lanes,($BI22*($CH22+BT22)+$CM22*CV22)*Peak_Time_Eve/3600,"-") -> 13.429007 | ... AY22: =IF(AY$6<Total_Lanes,($BI22*($CH22+CG22)+$CM22*DI22)*Peak_Time_Eve/3600,"-") -> - | AZ22: =SUMIF(AE22:AY22,BA22,$AE$6:$AY$6) -> 7 | BA22: =MIN(AE22:AY22) -> 10.549058 | BB22: =IF((SUMIF($BM20:$CG20,$AZ22,$BM22:$CG22)+$CH22)<(SUMIF($CO20:$DI20,$AZ22,$CO22:$DI22)+$DJ22),AZ22+1,AZ22) -> 7 | BC22: =SUMIF($AE$6:$AY$6,$BB22,$AE22:$AY22) -> 10.549058 | BF22: 15 | BG22: =$X22 -> 0.8 | BH22: =$AC22 -> 8226.5874 | BI22: =BH22*(1-BG22) -> 1645.3175 | BJ22: =Peak_Arrival_Manual/K55 -> 3.0049895 | BK22: =900*Peak_Time_Eve*(BJ22/Total_Lanes-1+SQRT((BJ22/Total_Lanes-1)^2+8*(BJ22/Total_Lanes)/(Peak_Time_Eve*$K55*Total_Lanes))) -> 0.18303171 | BL22: =Peak_Arrival_Manual/N55 -> 3.1506687 | BM22: =IF(BM$6<Total_Lanes,900*Peak_Time_Eve*(($BL22/(Total_Lanes-BM$6))-1+SQRT((($BL22/(Total_Lanes-BM$6))-1)^2+8*($BL22/(Total_Lanes-BM$6))/(Peak_Time_Eve*$N55*(Total_Lanes-BM$6)))),"-") -> 0.25153035 | BN22: =IF(BN$6<Total_Lanes,900*Peak_Time_Eve*(($BL22/(Total_Lanes-BN$6))-1+SQRT((($BL22/(Total_Lanes-BN$6))-1)^2+8*($BL22/(Total_Lanes-BN$6))/(Peak_Time_Eve*$N55*(Total_Lanes-BN$6)))),"-") -> 0.31706934 | BO22: =IF(BO$6<Total_Lanes,900*Peak_Time_Eve*(($BL22/(Total_Lanes-BO$6))-1+SQRT((($BL22/(Total_Lanes-BO$6))-1)^2+8*($BL22/(Total_Lanes-BO$6))/(Peak_Time_Eve*$N55*(Total_Lanes-BO$6)))),"-") -> 0.41250857 | BP22: =IF(BP$6<Total_Lanes,900*Peak_Time_Eve*(($BL22/(Total_Lanes-BP$6))-1+SQRT((($BL22/(Total_Lanes-BP$6))-1)^2+8*($BL22/(Total_Lanes-BP$6))/(Peak_Time_Eve*$N55*(Total_Lanes-BP$6)))),"-") -> 0.55972544 | BQ22: =IF(BQ$6<Total_Lanes,900*Peak_Time_Eve*(($BL22/(Total_Lanes-BQ$6))-1+SQRT((($BL22/(Total_Lanes-BQ$6))-1)^2+8*($BL22/(Total_Lanes-BQ$6))/(Peak_Time_Eve*$N55*(Total_Lanes-BQ$6)))),"-") -> 0.80574609 | BR22: =IF(BR$6<Total_Lanes,900*Peak_Time_Eve*(($BL22/(Total_Lanes-BR$6))-1+SQRT((($BL22/(Total_Lanes-BR$6))-1)^2+8*($BL22/(Total_Lanes-BR$6))/(Peak_Time_Eve*$N55*(Total_Lanes-BR$6)))),"-") -> 1.2695263 | BS22: =IF(BS$6<Total_Lanes,900*Peak_Time_Eve*(($BL22/(Total_Lanes-BS$6))-1+SQRT((($BL22/(Total_Lanes-BS$6))-1)^2+8*($BL22/(Total_Lanes-BS$6))/(Peak_Time_Eve*$N55*(Total_Lanes-BS$6)))),"-") -> 2.3448195 | BT22: =IF(BT$6<Total_Lanes,900*Peak_Time_Eve*(($BL22/(Total_Lanes-BT$6))-1+SQRT((($BL22/(Total_Lanes-BT$6))-1)^2+8*($BL22/(Total_Lanes-BT$6))/(Peak_Time_Eve*$N55*(Total_Lanes-BT$6)))),"-") -> 6.3406467 | ... CG22: =IF(CG$6<Total_Lanes,900*Peak_Time_Eve*(($BL22/(Total_Lanes-CG$6))-1+SQRT((($BL22/(Total_Lanes-CG$6))-1)^2+8*($BL22/(Total_Lanes-CG$6))/(Peak_Time_Eve*$N55*(Total_Lanes-CG$6)))),"-") -> - | CH22: =3600/N55 -> 6.89375 | CJ22: 15 | CK22: =$X22 -> 0.8 | CL22: =$AC22 -> 8226.5874 | CM22: =CL22*CK22 -> 6581.2699 | CN22: =CM22/O54 -> 4.3875133 | CO22: =IF(CO$6<Total_Lanes,900*Peak_Time_Eve*(($CN22/CO$6-1)+SQRT(($CN22/CO$6-1)^2+8*($CN22/CO$6)/(Peak_Time_Eve*$O55*CO$6))),"-") -> 12198.155 | CP22: =IF(CP$6<Total_Lanes,900*Peak_Time_Eve*(($CN22/CP$6-1)+SQRT(($CN22/CP$6-1)^2+8*($CN22/CP$6)/(Peak_Time_Eve*$O55*CP$6))),"-") -> 4299.728 | CQ22: =IF(CQ$6<Total_Lanes,900*Peak_Time_Eve*(($CN22/CQ$6-1)+SQRT(($CN22/CQ$6-1)^2+8*($CN22/CQ$6)/(Peak_Time_Eve*$O55*CQ$6))),"-") -> 1667.5418 | CR22: =IF(CR$6<Total_Lanes,900*Peak_Time_Eve*(($CN22/CR$6-1)+SQRT(($CN22/CR$6-1)^2+8*($CN22/CR$6)/(Peak_Time_Eve*$O55*CR$6))),"-") -> 355.42786 | CS22: =IF(CS$6<Total_Lanes,900*Peak_Time_Eve*(($CN22/CS$6-1)+SQRT(($CN22/CS$6-1)^2+8*($CN22/CS$6)/(Peak_Time_Eve*$O55*CS$6))),"-") -> 3.4120522 | CT22: =IF(CT$6<Total_Lanes,900*Peak_Time_Eve*(($CN22/CT$6-1)+SQRT(($CN22/CT$6-1)^2+8*($CN22/CT$6)/(Peak_Time_Eve*$O55*CT$6))),"-") -> 1.0871627 | CU22: =IF(CU$6<Total_Lanes,900*Peak_Time_Eve*(($CN22/CU$6-1)+SQRT(($CN22/CU$6-1)^2+8*($CN22/CU$6)/(Peak_Time_Eve*$O55*CU$6))),"-") -> 0.57556124 | CV22: =IF(CV$6<Total_Lanes,900*Peak_Time_Eve*(($CN22/CV$6-1)+SQRT(($CN22/CV$6-1)^2+8*($CN22/CV$6)/(Peak_Time_Eve*$O55*CV$6))),"-") -> 0.36428067 | ... DI22: =IF(DI$6<Total_Lanes,900*Peak_Time_Eve*(($CN22/DI$6-1)+SQRT(($CN22/DI$6-1)^2+8*($CN22/DI$6)/(Peak_Time_Eve*$O55*DI$6))),"-") -> - | DJ22: =3600/O55 -> 2.4
... H26: 19 | I26: ='Input-Detail'!E33 -> 29450809 | J26: ='Input-Detail'!F33 -> 0.95 | K26: =AC26 -> 8889.6773 | L26: =AD73 -> 14.805779 | M26: =AD26 -> 32.668357 | N26: =SUM(L26:M26) -> 47.474136 | O26: =$S$34*N26 -> 12343.275 | P26: =BC73 -> 0.96952037 | Q26: =BC26 -> 3.8251545 | R26: =SUM(P26:Q26) -> 4.7946749 | S26: =$S$34*R26 -> 1246.6155 | V26: 19 | W26: =W$7+(W$27-W$7)*$V26/20 -> 29450809 | X26: =J26 -> 0.95 | Y26: ='Input-Detail'!E33/Z26 -> 12699.539 | Z26: =Z25 -> 2319.0455 | AA26: =AA25 -> 2 | AB26: =AB25 -> 0.7 | AC26: =Y26*AB26 -> 8889.6773 | AD26: =Peak_Time_Eve*$BH26*(3600/K59+BK26)/3600 -> 32.668357 | AE26: =IF(AE$6<Total_Lanes,($BI26*($CH26+BM26)+$CM26*CO26)*Peak_Time_Eve/3600,"-") -> 78220.096 | AF26: =IF(AF$6<Total_Lanes,($BI26*($CH26+BN26)+$CM26*CP26)*Peak_Time_Eve/3600,"-") -> 30667.61 | AG26: =IF(AG$6<Total_Lanes,($BI26*($CH26+BO26)+$CM26*CQ26)*Peak_Time_Eve/3600,"-") -> 14817.739 | AH26: =IF(AH$6<Total_Lanes,($BI26*($CH26+BP26)+$CM26*CR26)*Peak_Time_Eve/3600,"-") -> 6894.8355 | AI26: =IF(AI$6<Total_Lanes,($BI26*($CH26+BQ26)+$CM26*CS26)*Peak_Time_Eve/3600,"-") -> 2150.3174 | AJ26: =IF(AJ$6<Total_Lanes,($BI26*($CH26+BR26)+$CM26*CT26)*Peak_Time_Eve/3600,"-") -> 29.594985 | AK26: =IF(AK$6<Total_Lanes,($BI26*($CH26+BS26)+$CM26*CU26)*Peak_Time_Eve/3600,"-") -> 8.3932168 | AL26: =IF(AL$6<Total_Lanes,($BI26*($CH26+BT26)+$CM26*CV26)*Peak_Time_Eve/3600,"-") -> 5.1832245 | ... AY26: =IF(AY$6<Total_Lanes,($BI26*($CH26+CG26)+$CM26*DI26)*Peak_Time_Eve/3600,"-") -> - | AZ26: =SUMIF(AE26:AY26,BA26,$AE$6:$AY$6) -> 10 | BA26: =MIN(AE26:AY26) -> 3.8251545 | BB26: =IF((SUMIF($BM24:$CG24,$AZ26,$BM26:$CG26)+$CH26)<(SUMIF($CO24:$DI24,$AZ26,$CO26:$DI26)+$DJ26),AZ26+1,AZ26) -> 10 | BC26: =SUMIF($AE$6:$AY$6,$BB26,$AE26:$AY26) -> 3.8251545 | BF26: 19 | BG26: =$X26 -> 0.95 | BH26: =$AC26 -> 8889.6773 | BI26: =BH26*(1-BG26) -> 444.48387 | BJ26: =Peak_Arrival_Manual/K59 -> 0.81180039 | BK26: =900*Peak_Time_Eve*(BJ26/Total_Lanes-1+SQRT((BJ26/Total_Lanes-1)^2+8*(BJ26/Total_Lanes)/(Peak_Time_Eve*$K59*Total_Lanes))) -> 0.03975561 | BL26: =Peak_Arrival_Manual/N59 -> 0.86165049 | BM26: =IF(BM$6<Total_Lanes,900*Peak_Time_Eve*(($BL26/(Total_Lanes-BM$6))-1+SQRT((($BL26/(Total_Lanes-BM$6))-1)^2+8*($BL26/(Total_Lanes-BM$6))/(Peak_Time_Eve*$N59*(Total_Lanes-BM$6)))),"-") -> 0.053918994 | BN26: =IF(BN$6<Total_Lanes,900*Peak_Time_Eve*(($BL26/(Total_Lanes-BN$6))-1+SQRT((($BL26/(Total_Lanes-BN$6))-1)^2+8*($BL26/(Total_Lanes-BN$6))/(Peak_Time_Eve*$N59*(Total_Lanes-BN$6)))),"-") -> 0.065800975 | BO26: =IF(BO$6<Total_Lanes,900*Peak_Time_Eve*(($BL26/(Total_Lanes-BO$6))-1+SQRT((($BL26/(Total_Lanes-BO$6))-1)^2+8*($BL26/(Total_Lanes-BO$6))/(Peak_Time_Eve*$N59*(Total_Lanes-BO$6)))),"-") -> 0.08209543 | BP26: =IF(BP$6<Total_Lanes,900*Peak_Time_Eve*(($BL26/(Total_Lanes-BP$6))-1+SQRT((($BL26/(Total_Lanes-BP$6))-1)^2+8*($BL26/(Total_Lanes-BP$6))/(Peak_Time_Eve*$N59*(Total_Lanes-BP$6)))),"-") -> 0.10529476 | BQ26: =IF(BQ$6<Total_Lanes,900*Peak_Time_Eve*(($BL26/(Total_Lanes-BQ$6))-1+SQRT((($BL26/(Total_Lanes-BQ$6))-1)^2+8*($BL26/(Total_Lanes-BQ$6))/(Peak_Time_Eve*$N59*(Total_Lanes-BQ$6)))),"-") -> 0.13993936 | BR26: =IF(BR$6<Total_Lanes,900*Peak_Time_Eve*(($BL26/(Total_Lanes-BR$6))-1+SQRT((($BL26/(Total_Lanes-BR$6))-1)^2+8*($BL26/(Total_Lanes-BR$6))/(Peak_Time_Eve*$N59*(Total_Lanes-BR$6)))),"-") -> 0.19503224 | BS26: =IF(BS$6<Total_Lanes,900*Peak_Time_Eve*(($BL26/(Total_Lanes-BS$6))-1+SQRT((($BL26/(Total_Lanes-BS$6))-1)^2+8*($BL26/(Total_Lanes-BS$6))/(Peak_Time_Eve*$N59*(Total_Lanes-BS$6)))),"-") -> 0.29058237 | BT26: =IF(BT$6<Total_Lanes,900*Peak_Time_Eve*(($BL26/(Total_Lanes-BT$6))-1+SQRT((($BL26/(Total_Lanes-BT$6))-1)^2+8*($BL26/(Total_Lanes-BT$6))/(Peak_Time_Eve*$N59*(Total_Lanes-BT$6)))),"-") -> 0.47893199 | ... CG26: =IF(CG$6<Total_Lanes,900*Peak_Time_Eve*(($BL26/(Total_Lanes-CG$6))-1+SQRT((($BL26/(Total_Lanes-CG$6))-1)^2+8*($BL26/(Total_Lanes-CG$6))/(Peak_Time_Eve*$N59*(Total_Lanes-CG$6)))),"-") -> - | CH26: =3600/N59 -> 6.97875 | CJ26: 19 | CK26: =$X26 -> 0.95 | CL26: =$AC26 -> 8889.6773 | CM26: =CL26*CK26 -> 8445.1934 | CN26: =CM26/O58 -> 5.630129 | CO26: =IF(CO$6<Total_Lanes,900*Peak_Time_Eve*(($CN26/CO$6-1)+SQRT(($CN26/CO$6-1)^2+8*($CN26/CO$6)/(Peak_Time_Eve*$O59*CO$6))),"-") -> 16671.382 | CP26: =IF(CP$6<Total_Lanes,900*Peak_Time_Eve*(($CN26/CP$6-1)+SQRT(($CN26/CP$6-1)^2+8*($CN26/CP$6)/(Peak_Time_Eve*$O59*CP$6))),"-") -> 6536.0927 | CQ26: =IF(CQ$6<Total_Lanes,900*Peak_Time_Eve*(($CN26/CQ$6-1)+SQRT(($CN26/CQ$6-1)^2+8*($CN26/CQ$6)/(Peak_Time_Eve*$O59*CQ$6))),"-") -> 3157.8663 | CR26: =IF(CR$6<Total_Lanes,900*Peak_Time_Eve*(($CN26/CR$6-1)+SQRT(($CN26/CR$6-1)^2+8*($CN26/CR$6)/(Peak_Time_Eve*$O59*CR$6))),"-") -> 1469.1854 | CS26: =IF(CS$6<Total_Lanes,900*Peak_Time_Eve*(($CN26/CS$6-1)+SQRT(($CN26/CS$6-1)^2+8*($CN26/CS$6)/(Peak_Time_Eve*$O59*CS$6))),"-") -> 457.94181 | CT26: =IF(CT$6<Total_Lanes,900*Peak_Time_Eve*(($CN26/CT$6-1)+SQRT(($CN26/CT$6-1)^2+8*($CN26/CT$6)/(Peak_Time_Eve*$O59*CT$6))),"-") -> 5.9302776 | CU26: =IF(CU$6<Total_Lanes,900*Peak_Time_Eve*(($CN26/CU$6-1)+SQRT(($CN26/CU$6-1)^2+8*($CN26/CU$6)/(Peak_Time_Eve*$O59*CU$6))),"-") -> 1.4063253 | CV26: =IF(CV$6<Total_Lanes,900*Peak_Time_Eve*(($CN26/CV$6-1)+SQRT(($CN26/CV$6-1)^2+8*($CN26/CV$6)/(Peak_Time_Eve*$O59*CV$6))),"-") -> 0.71223766 | ... DI26: =IF(DI$6<Total_Lanes,900*Peak_Time_Eve*(($CN26/DI$6-1)+SQRT(($CN26/DI$6-1)^2+8*($CN26/DI$6)/(Peak_Time_Eve*$O59*DI$6))),"-") -> - | DJ26: =3600/O59 -> 2.4
H27: 20 | I27: ='Input-Detail'!E34 -> 30000000 | J27: ='Input-Detail'!F34 -> 0.95 | K27: =AC27 -> 9055.4498 | L27: =AD74 -> 15.128367 | M27: =AD27 -> 33.281554 | N27: =SUM(L27:M27) -> 48.409921 | O27: =$S$34*N27 -> 12586.58 | P27: =BC74 -> 0.99600832 | Q27: =BC27 -> 3.9942378 | R27: =SUM(P27:Q27) -> 4.9902461 | S27: =$S$34*R27 -> 1297.464 | V27: 20 | W27: ='Input-Detail'!E34 -> 30000000 | X27: =J27 -> 0.95 | Y27: ='Input-Detail'!E34/Z27 -> 12936.357 | Z27: =Z26 -> 2319.0455 | AA27: =AA26 -> 2 | AB27: =AB26 -> 0.7 | AC27: =Y27*AB27 -> 9055.4498 | AD27: =Peak_Time_Eve*$BH27*(3600/K60+BK27)/3600 -> 33.281554 | AE27: =IF(AE$6<Total_Lanes,($BI27*($CH27+BM27)+$CM27*CO27)*Peak_Time_Eve/3600,"-") -> 81485.053 | AF27: =IF(AF$6<Total_Lanes,($BI27*($CH27+BN27)+$CM27*CP27)*Peak_Time_Eve/3600,"-") -> 32142.598 | AG27: =IF(AG$6<Total_Lanes,($BI27*($CH27+BO27)+$CM27*CQ27)*Peak_Time_Eve/3600,"-") -> 15696.021 | AH27: =IF(AH$6<Total_Lanes,($BI27*($CH27+BP27)+$CM27*CR27)*Peak_Time_Eve/3600,"-") -> 7474.5852 | AI27: =IF(AI$6<Total_Lanes,($BI27*($CH27+BQ27)+$CM27*CS27)*Peak_Time_Eve/3600,"-") -> 2549.1633 | AJ27: =IF(AJ$6<Total_Lanes,($BI27*($CH27+BR27)+$CM27*CT27)*Peak_Time_Eve/3600,"-") -> 41.163921 | AK27: =IF(AK$6<Total_Lanes,($BI27*($CH27+BS27)+$CM27*CU27)*Peak_Time_Eve/3600,"-") -> 9.2479849 | AL27: =IF(AL$6<Total_Lanes,($BI27*($CH27+BT27)+$CM27*CV27)*Peak_Time_Eve/3600,"-") -> 5.5128932 | ... AY27: =IF(AY$6<Total_Lanes,($BI27*($CH27+CG27)+$CM27*DI27)*Peak_Time_Eve/3600,"-") -> - | AZ27: =SUMIF(AE27:AY27,BA27,$AE$6:$AY$6) -> 10 | BA27: =MIN(AE27:AY27) -> 3.9942378 | BB27: =IF((SUMIF($BM25:$CG25,$AZ27,$BM27:$CG27)+$CH27)<(SUMIF($CO25:$DI25,$AZ27,$CO27:$DI27)+$DJ27),AZ27+1,AZ27) -> 10 | BC27: =SUMIF($AE$6:$AY$6,$BB27,$AE27:$AY27) -> 3.9942378 | BF27: 20 | BG27: =$X27 -> 0.95 | BH27: =$AC27 -> 9055.4498 | BI27: =BH27*(1-BG27) -> 452.77249 | BJ27: =Peak_Arrival_Manual/K60 -> 0.82693864 | BK27: =900*Peak_Time_Eve*(BJ27/Total_Lanes-1+SQRT((BJ27/Total_Lanes-1)^2+8*(BJ27/Total_Lanes)/(Peak_Time_Eve*$K60*Total_Lanes))) -> 0.040551821 | BL27: =Peak_Arrival_Manual/N60 -> 0.88039095 | BM27: =IF(BM$6<Total_Lanes,900*Peak_Time_Eve*(($BL27/(Total_Lanes-BM$6))-1+SQRT((($BL27/(Total_Lanes-BM$6))-1)^2+8*($BL27/(Total_Lanes-BM$6))/(Peak_Time_Eve*$N60*(Total_Lanes-BM$6)))),"-") -> 0.055361766 | BN27: =IF(BN$6<Total_Lanes,900*Peak_Time_Eve*(($BL27/(Total_Lanes-BN$6))-1+SQRT((($BL27/(Total_Lanes-BN$6))-1)^2+8*($BL27/(Total_Lanes-BN$6))/(Peak_Time_Eve*$N60*(Total_Lanes-BN$6)))),"-") -> 0.067575373 | BO27: =IF(BO$6<Total_Lanes,900*Peak_Time_Eve*(($BL27/(Total_Lanes-BO$6))-1+SQRT((($BL27/(Total_Lanes-BO$6))-1)^2+8*($BL27/(Total_Lanes-BO$6))/(Peak_Time_Eve*$N60*(Total_Lanes-BO$6)))),"-") -> 0.084330506 | BP27: =IF(BP$6<Total_Lanes,900*Peak_Time_Eve*(($BL27/(Total_Lanes-BP$6))-1+SQRT((($BL27/(Total_Lanes-BP$6))-1)^2+8*($BL27/(Total_Lanes-BP$6))/(Peak_Time_Eve*$N60*(Total_Lanes-BP$6)))),"-") -> 0.1081964 | BQ27: =IF(BQ$6<Total_Lanes,900*Peak_Time_Eve*(($BL27/(Total_Lanes-BQ$6))-1+SQRT((($BL27/(Total_Lanes-BQ$6))-1)^2+8*($BL27/(Total_Lanes-BQ$6))/(Peak_Time_Eve*$N60*(Total_Lanes-BQ$6)))),"-") -> 0.14385735 | BR27: =IF(BR$6<Total_Lanes,900*Peak_Time_Eve*(($BL27/(Total_Lanes-BR$6))-1+SQRT((($BL27/(Total_Lanes-BR$6))-1)^2+8*($BL27/(Total_Lanes-BR$6))/(Peak_Time_Eve*$N60*(Total_Lanes-BR$6)))),"-") -> 0.20061214 | BS27: =IF(BS$6<Total_Lanes,900*Peak_Time_Eve*(($BL27/(Total_Lanes-BS$6))-1+SQRT((($BL27/(Total_Lanes-BS$6))-1)^2+8*($BL27/(Total_Lanes-BS$6))/(Peak_Time_Eve*$N60*(Total_Lanes-BS$6)))),"-") -> 0.29916019 | BT27: =IF(BT$6<Total_Lanes,900*Peak_Time_Eve*(($BL27/(Total_Lanes-BT$6))-1+SQRT((($BL27/(Total_Lanes-BT$6))-1)^2+8*($BL27/(Total_Lanes-BT$6))/(Peak_Time_Eve*$N60*(Total_Lanes-BT$6)))),"-") -> 0.49378407 | ... CG27: =IF(CG$6<Total_Lanes,900*Peak_Time_Eve*(($BL27/(Total_Lanes-CG$6))-1+SQRT((($BL27/(Total_Lanes-CG$6))-1)^2+8*($BL27/(Total_Lanes-CG$6))/(Peak_Time_Eve*$N60*(Total_Lanes-CG$6)))),"-") -> - | CH27: =3600/N60 -> 7 | CJ27: 20 | CK27: =$X27 -> 0.95 | CL27: =$AC27 -> 9055.4498 | CM27: =CL27*CK27 -> 8602.6773 | CN27: =CM27/O59 -> 5.7351182 | CO27: =IF(CO$6<Total_Lanes,900*Peak_Time_Eve*(($CN27/CO$6-1)+SQRT(($CN27/CO$6-1)^2+8*($CN27/CO$6)/(Peak_Time_Eve*$O60*CO$6))),"-") -> 17049.332 | CP27: =IF(CP$6<Total_Lanes,900*Peak_Time_Eve*(($CN27/CP$6-1)+SQRT(($CN27/CP$6-1)^2+8*($CN27/CP$6)/(Peak_Time_Eve*$O60*CP$6))),"-") -> 6725.0548 | CQ27: =IF(CQ$6<Total_Lanes,900*Peak_Time_Eve*(($CN27/CQ$6-1)+SQRT(($CN27/CQ$6-1)^2+8*($CN27/CQ$6)/(Peak_Time_Eve*$O60*CQ$6))),"-") -> 3283.8185 | CR27: =IF(CR$6<Total_Lanes,900*Peak_Time_Eve*(($CN27/CR$6-1)+SQRT(($CN27/CR$6-1)^2+8*($CN27/CR$6)/(Peak_Time_Eve*$O60*CR$6))),"-") -> 1563.5871 | CS27: =IF(CS$6<Total_Lanes,900*Peak_Time_Eve*(($CN27/CS$6-1)+SQRT(($CN27/CS$6-1)^2+8*($CN27/CS$6)/(Peak_Time_Eve*$O60*CS$6))),"-") -> 533.00376 | CT27: =IF(CT$6<Total_Lanes,900*Peak_Time_Eve*(($CN27/CT$6-1)+SQRT(($CN27/CT$6-1)^2+8*($CN27/CT$6)/(Peak_Time_Eve*$O60*CT$6))),"-") -> 8.2340434 | CU27: =IF(CU$6<Total_Lanes,900*Peak_Time_Eve*(($CN27/CU$6-1)+SQRT(($CN27/CU$6-1)^2+8*($CN27/CU$6)/(Peak_Time_Eve*$O60*CU$6))),"-") -> 1.550856 | CV27: =IF(CV$6<Total_Lanes,900*Peak_Time_Eve*(($CN27/CV$6-1)+SQRT(($CN27/CV$6-1)^2+8*($CN27/CV$6)/(Peak_Time_Eve*$O60*CV$6))),"-") -> 0.75909258 | ... DI27: =IF(DI$6<Total_Lanes,900*Peak_Time_Eve*(($CN27/DI$6-1)+SQRT(($CN27/DI$6-1)^2+8*($CN27/DI$6)/(Peak_Time_Eve*$O60*DI$6))),"-") -> - | DJ27: =3600/O60 -> 2.4
H30: Footnote: | V30: Footnote:
H31: *Suppose peak hours happen in weekdays. Therefore, 5 weekdays per week. | V31: *Criterion of Choosing Optimal Number of ETC Lanes--Minimize Total Delay in the System During the Peak Hour
H32: Or you can change the number of days (in white cell) | V32: Average Delay Formula: ADi = (1/mi) + 900* (T)*{(r-1)+[(r-1)2+8*k*I*r/(T*mimi)]0.5}
H33: # of weeks per year | S33: 52 | V33: where
H34: # of weekdays per year | S34: =5*S33 -> 260 | V34: m : mean service rate (veh/hr)
V35: i : 1 for manual lane and 2 for ETC lane.
V36: T : duration of peak period (hr) per day,
H37: y Estimated Mean Service Rate (vhe/hrs) given payment split | V37: r : degree of ri = li/mimi
H38: Year | I38: Payment Split (Baseline)-Manual | L38: Payment Split (ETC Alternative)-Manual | O38: Capacity-ETC Lane | V38: m : number of lanes,
I39: Cash/Chect | J39: Ticket | K39: Mean Service Rate | L39: Cash/Check | M39: Ticket | N39: Mean Service Rate | V39: l : arrival rate during the peak period (veh/hr),
H40: Base | I40: ='Input-Detail'!BH13 -> 0.83 | J40: =1-I40 -> 0.17 | K40: =3600/(Trans_Time_Cash*I40+Trans_Time_Ticket*J40) -> 547.52852 | L40: ='Input-Detail'!BJ13 -> 0.83 | M40: =1-L40 -> 0.17 | N40: =3600/(Trans_Time_Cash*L40+Trans_Time_Ticket*M40) -> 547.52852 | O40: =3600/Headway_ETC -> 1500 | V40: k : parameter for given arrival and service distribution, k = 1 for Poisson Arrivals and exponentil service time,
H41: 1 | I41: ='Input-Detail'!BH14 -> 0.83 | J41: =1-I41 -> 0.17 | K41: =3600/(Trans_Time_Cash*I41+Trans_Time_Ticket*J41) -> 547.52852 | L41: ='Input-Detail'!BJ14 -> 0.8385 | M41: =1-L41 -> 0.1615 | N41: =3600/(Trans_Time_Cash*L41+Trans_Time_Ticket*M41) -> 545.76464 | O41: =3600/Headway_ETC -> 1500 | V41: I : variance to mean ratio of arrivals; I = 1 for Poisson Arrivals.
H42: 2 | I42: ='Input-Detail'!BH15 -> 0.83 | J42: =1-I42 -> 0.17 | K42: =3600/(Trans_Time_Cash*I42+Trans_Time_Ticket*J42) -> 547.52852 | L42: ='Input-Detail'!BJ15 -> 0.847 | M42: =1-L42 -> 0.153 | N42: =3600/(Trans_Time_Cash*L42+Trans_Time_Ticket*M42) -> 544.01209 | O42: =3600/Headway_ETC -> 1500
H43: 3 | I43: ='Input-Detail'!BH16 -> 0.83 | J43: =1-I43 -> 0.17 | K43: =3600/(Trans_Time_Cash*I43+Trans_Time_Ticket*J43) -> 547.52852 | L43: ='Input-Detail'!BJ16 -> 0.8555 | M43: =1-L43 -> 0.1445 | N43: =3600/(Trans_Time_Cash*L43+Trans_Time_Ticket*M43) -> 542.27076 | O43: =3600/Headway_ETC -> 1500 | V43: Total Time (hr) Spent in the System per day: (AD1*l1+AD2*l2)*T/3600
H44: 4 | I44: ='Input-Detail'!BH17 -> 0.83 | J44: =1-I44 -> 0.17 | K44: =3600/(Trans_Time_Cash*I44+Trans_Time_Ticket*J44) -> 547.52852 | L44: ='Input-Detail'!BJ17 -> 0.864 | M44: =1-L44 -> 0.136 | N44: =3600/(Trans_Time_Cash*L44+Trans_Time_Ticket*M44) -> 540.54054 | O44: =3600/Headway_ETC -> 1500 | V44: Given total number of lanes, peak hour traffic and ETC split, we can find out the optimal number of ETC lanes.
H45: 5 | I45: ='Input-Detail'!BH18 -> 0.83 | J45: =1-I45 -> 0.17 | K45: =3600/(Trans_Time_Cash*I45+Trans_Time_Ticket*J45) -> 547.52852 | L45: ='Input-Detail'!BJ18 -> 0.8725 | M45: =1-L45 -> 0.1275 | N45: =3600/(Trans_Time_Cash*L45+Trans_Time_Ticket*M45) -> 538.82133 | O45: =3600/Headway_ETC -> 1500 | V45: ** Delay happens to those people who arrival during the evening peak period.
H46: 6 | I46: ='Input-Detail'!BH19 -> 0.83 | J46: =1-I46 -> 0.17 | K46: =3600/(Trans_Time_Cash*I46+Trans_Time_Ticket*J46) -> 547.52852 | L46: ='Input-Detail'!BJ19 -> 0.881 | M46: =1-L46 -> 0.119 | N46: =3600/(Trans_Time_Cash*L46+Trans_Time_Ticket*M46) -> 537.11302 | O46: =3600/Headway_ETC -> 1500
H47: 7 | I47: ='Input-Detail'!BH20 -> 0.83 | J47: =1-I47 -> 0.17 | K47: =3600/(Trans_Time_Cash*I47+Trans_Time_Ticket*J47) -> 547.52852 | L47: ='Input-Detail'!BJ20 -> 0.8895 | M47: =1-L47 -> 0.1105 | N47: =3600/(Trans_Time_Cash*L47+Trans_Time_Ticket*M47) -> 535.4155 | O47: =3600/Headway_ETC -> 1500 | V47: ***Suggested Number of ETC Lanes:The number of ETC Lanes, which is close to optimal number of ETC Lanes, such that average delay in ETC lanes is less than average delay in Manual Lanes.
H48: 8 | I48: ='Input-Detail'!BH21 -> 0.83 | J48: =1-I48 -> 0.17 | K48: =3600/(Trans_Time_Cash*I48+Trans_Time_Ticket*J48) -> 547.52852 | L48: ='Input-Detail'!BJ21 -> 0.898 | M48: =1-L48 -> 0.102 | N48: =3600/(Trans_Time_Cash*L48+Trans_Time_Ticket*M48) -> 533.72869 | O48: =3600/Headway_ETC -> 1500
H49: 9 | I49: ='Input-Detail'!BH22 -> 0.83 | J49: =1-I49 -> 0.17 | K49: =3600/(Trans_Time_Cash*I49+Trans_Time_Ticket*J49) -> 547.52852 | L49: ='Input-Detail'!BJ22 -> 0.9065 | M49: =1-L49 -> 0.0935 | N49: =3600/(Trans_Time_Cash*L49+Trans_Time_Ticket*M49) -> 532.05247 | O49: =3600/Headway_ETC -> 1500
H50: 10 | I50: ='Input-Detail'!BH23 -> 0.83 | J50: =1-I50 -> 0.17 | K50: =3600/(Trans_Time_Cash*I50+Trans_Time_Ticket*J50) -> 547.52852 | L50: ='Input-Detail'!BJ23 -> 0.915 | M50: =1-L50 -> 0.085 | N50: =3600/(Trans_Time_Cash*L50+Trans_Time_Ticket*M50) -> 530.38674 | O50: =3600/Headway_ETC -> 1500 | V50: a) Total Time Spent in the System during the Morning Peak per Day (hr) | BF50: b) Average Random Delay per Manual User (sec) | CJ50: c) Average Random Delay per ETC User (sec)
H51: 11 | I51: ='Input-Detail'!BH24 -> 0.83 | J51: =1-I51 -> 0.17 | K51: =3600/(Trans_Time_Cash*I51+Trans_Time_Ticket*J51) -> 547.52852 | L51: ='Input-Detail'!BJ24 -> 0.9235 | M51: =1-L51 -> 0.0765 | N51: =3600/(Trans_Time_Cash*L51+Trans_Time_Ticket*M51) -> 528.73141 | O51: =3600/Headway_ETC -> 1500
H52: 12 | I52: ='Input-Detail'!BH25 -> 0.83 | J52: =1-I52 -> 0.17 | K52: =3600/(Trans_Time_Cash*I52+Trans_Time_Ticket*J52) -> 547.52852 | L52: ='Input-Detail'!BJ25 -> 0.932 | M52: =1-L52 -> 0.068 | N52: =3600/(Trans_Time_Cash*L52+Trans_Time_Ticket*M52) -> 527.08638 | O52: =3600/Headway_ETC -> 1500 | V52: Year | W52: Traffic Vol. | X52: ETC (%) | Y52: PHV | Z52: ATV/PHV | AA52: T (hr) | AB52: K | AC52: Total Arrival Rate | AD52: Number of ETC Lanes | AZ52: Optimal # of ETC Ln* | BA52: Delay per Day**(hr) | BB52: Suggested # of ETC Ln*** | BC52: Delay per Day**(hr) | BF52: Year | BG52: ETC (%) | BH52: Total Arrival Rate | BI52: Arrival Rate for Manual Users | BJ52: Number of ETC Lanes | CH52: Mean Transaction Time (sec) | CJ52: Year | CK52: ETC (%) | CL52: Total Arrival Rate | CM52: Arrival Rate for ETC Users | CN52: Number of ETC Lanes | DJ52: Mean headway (sec)
H53: 13 | I53: ='Input-Detail'!BH26 -> 0.83 | J53: =1-I53 -> 0.17 | K53: =3600/(Trans_Time_Cash*I53+Trans_Time_Ticket*J53) -> 547.52852 | L53: ='Input-Detail'!BJ26 -> 0.9405 | M53: =1-L53 -> 0.0595 | N53: =3600/(Trans_Time_Cash*L53+Trans_Time_Ticket*M53) -> 525.45156 | O53: =3600/Headway_ETC -> 1500 | AD53: Manual Only | AE53: 1 | AF53: 2 | AG53: 3 | AH53: 4 | AI53: 5 | AJ53: 6 | AK53: 7 | AL53: 8 | AM53: 9 | AN53: 10 | AO53: 11 | AP53: 12 | AQ53: 13 | AR53: 14 | AS53: 15 | AT53: 16 | AU53: 17 | AV53: 18 | AW53: 19 | AX53: 20 | AY53: 21 | BJ53: l/sc for no ETC | BK53: Manual Only | BL53: l/sc under ETC | BM53: 1 | BN53: 2 | BO53: 3 | BP53: 4 | BQ53: 5 | BR53: 6 | BS53: 7 | BT53: 8 | BU53: 9 | BV53: 10 | BW53: 11 | BX53: 12 | BY53: 13 | BZ53: 14 | CA53: 15 | CB53: 16 | CC53: 17 | CD53: 18 | CE53: 19 | CF53: 20 | CG53: 21 | CN53: l/sc under ETC | CO53: 1 | CP53: 2 | CQ53: 3 | CR53: 4 | CS53: 5 | CT53: 6 | CU53: 7 | CV53: 8 | CW53: 9 | CX53: 10 | CY53: 11 | CZ53: 12 | DA53: 13 | DB53: 14 | DC53: 15 | DD53: 16 | DE53: 17 | DF53: 18 | DG53: 19 | DH53: 20 | DI53: 21
H54: 14 | I54: ='Input-Detail'!BH27 -> 0.83 | J54: =1-I54 -> 0.17 | K54: =3600/(Trans_Time_Cash*I54+Trans_Time_Ticket*J54) -> 547.52852 | L54: ='Input-Detail'!BJ27 -> 0.949 | M54: =1-L54 -> 0.051 | N54: =3600/(Trans_Time_Cash*L54+Trans_Time_Ticket*M54) -> 523.82685 | O54: =3600/Headway_ETC -> 1500 | V54: Base | W54: =W7 -> 19016173 | X54: =X7 -> 0 | Y54: ='Input-Detail'!M18 -> 8200 | Z54: ='Input-Detail'!N18 -> 2319.0455 | AA54: ='Input-Detail'!O18 -> 2 | AB54: ='Input-Detail'!P18 -> 0.3 | AC54: =Y54*AB54 -> 2460 | AD54: =Peak_Time_Mor*$BH54*(CH54+BK54)/3600 -> 9.4339293 | BF54: Base | BG54: =$X54 -> 0 | BH54: =$AC54 -> 2460 | BI54: =BH54*(1-BG54) -> 2460 | BJ54: =Peak_Arrival_Manual_Mor/K40 -> 4.4929167 | BK54: =900*Peak_Time_Mor*($BJ54/Total_Lanes-1+SQRT(($BJ54/Total_Lanes-1)^2+8*($BJ54/Total_Lanes)/(Peak_Time_Mor*$K40*Total_Lanes))) -> 0.32787508 | BL54: =Peak_Arrival_Manual_Mor/N40 -> 4.4929167 | BM54: =IF(BM$6<Total_Lanes,900*Peak_Time_Mor*($BL54/(Total_Lanes-BM$6)-1+SQRT(($BL54/(Total_Lanes-BM$6)-1)^2+8*($BL54/(Total_Lanes-BM$6))/(Peak_Time_Mor*$N40*(Total_Lanes-BM$6)))),"-") -> 0.41263012 | BN54: =IF(BN$6<Total_Lanes,900*Peak_Time_Mor*($BL54/(Total_Lanes-BN$6)-1+SQRT(($BL54/(Total_Lanes-BN$6)-1)^2+8*($BL54/(Total_Lanes-BN$6))/(Peak_Time_Mor*$N40*(Total_Lanes-BN$6)))),"-") -> 0.53627187 | BO54: =IF(BO$6<Total_Lanes,900*Peak_Time_Mor*($BL54/(Total_Lanes-BO$6)-1+SQRT(($BL54/(Total_Lanes-BO$6)-1)^2+8*($BL54/(Total_Lanes-BO$6))/(Peak_Time_Mor*$N40*(Total_Lanes-BO$6)))),"-") -> 0.72796533 | BP54: =IF(BP$6<Total_Lanes,900*Peak_Time_Mor*($BL54/(Total_Lanes-BP$6)-1+SQRT(($BL54/(Total_Lanes-BP$6)-1)^2+8*($BL54/(Total_Lanes-BP$6))/(Peak_Time_Mor*$N40*(Total_Lanes-BP$6)))),"-") -> 1.0522007 | BQ54: =IF(BQ$6<Total_Lanes,900*Peak_Time_Mor*($BL54/(Total_Lanes-BQ$6)-1+SQRT(($BL54/(Total_Lanes-BQ$6)-1)^2+8*($BL54/(Total_Lanes-BQ$6))/(Peak_Time_Mor*$N40*(Total_Lanes-BQ$6)))),"-") -> 1.6810918 | BR54: =IF(BR$6<Total_Lanes,900*Peak_Time_Mor*($BL54/(Total_Lanes-BR$6)-1+SQRT(($BL54/(Total_Lanes-BR$6)-1)^2+8*($BL54/(Total_Lanes-BR$6))/(Peak_Time_Mor*$N40*(Total_Lanes-BR$6)))),"-") -> 3.25518 | BS54: =IF(BS$6<Total_Lanes,900*Peak_Time_Mor*($BL54/(Total_Lanes-BS$6)-1+SQRT(($BL54/(Total_Lanes-BS$6)-1)^2+8*($BL54/(Total_Lanes-BS$6))/(Peak_Time_Mor*$N40*(Total_Lanes-BS$6)))),"-") -> 11.301479 | BT54: =IF(BT$6<Total_Lanes,900*Peak_Time_Mor*($BL54/(Total_Lanes-BT$6)-1+SQRT(($BL54/(Total_Lanes-BT$6)-1)^2+8*($BL54/(Total_Lanes-BT$6))/(Peak_Time_Mor*$N40*(Total_Lanes-BT$6)))),"-") -> 458.13324 | ... CG54: =IF(CG$6<Total_Lanes,900*Peak_Time_Mor*($BL54/(Total_Lanes-CG$6)-1+SQRT(($BL54/(Total_Lanes-CG$6)-1)^2+8*($BL54/(Total_Lanes-CG$6))/(Peak_Time_Mor*$N40*(Total_Lanes-CG$6)))),"-") -> - | CH54: =3600/N40 -> 6.575 | CJ54: Base | CK54: =$X54 -> 0 | CL54: =$AC54 -> 2460 | CM54: =CL54*CK54 -> 0
H55: 15 | I55: ='Input-Detail'!BH28 -> 0.83 | J55: =1-I55 -> 0.17 | K55: =3600/(Trans_Time_Cash*I55+Trans_Time_Ticket*J55) -> 547.52852 | L55: ='Input-Detail'!BJ28 -> 0.9575 | M55: =1-L55 -> 0.0425 | N55: =3600/(Trans_Time_Cash*L55+Trans_Time_Ticket*M55) -> 522.21215 | O55: =3600/Headway_ETC -> 1500 | V55: 1 | W55: =W8 -> 19565364 | X55: =X8 -> 0.06 | Y55: =Y8 -> 8436.8178 | Z55: =W55/Y55 -> 2319.0455 | AA55: =AA8 -> 2 | AB55: =1-AB8 -> 0.3 | AC55: =Y55*AB55 -> 2531.0454 | AD55: =Peak_Time_Mor*$BH55*(CH55+BK55)/3600 -> 9.7125238 | AE55: =IF(AE$53<Total_Lanes,($BI55*($CH55+BM55)+$CM55*CO55)*Peak_Time_Mor/3600,"-") -> 9.2617476 | AF55: =IF(AF$53<Total_Lanes,($BI55*($CH55+BN55)+$CM55*CP55)*Peak_Time_Mor/3600,"-") -> 9.3977655 | AG55: =IF(AG$53<Total_Lanes,($BI55*($CH55+BO55)+$CM55*CQ55)*Peak_Time_Mor/3600,"-") -> 9.6307596 | AH55: =IF(AH$53<Total_Lanes,($BI55*($CH55+BP55)+$CM55*CR55)*Peak_Time_Mor/3600,"-") -> 10.02423 | AI55: =IF(AI$53<Total_Lanes,($BI55*($CH55+BQ55)+$CM55*CS55)*Peak_Time_Mor/3600,"-") -> 10.773408 | AJ55: =IF(AJ$53<Total_Lanes,($BI55*($CH55+BR55)+$CM55*CT55)*Peak_Time_Mor/3600,"-") -> 12.568986 | AK55: =IF(AK$53<Total_Lanes,($BI55*($CH55+BS55)+$CM55*CU55)*Peak_Time_Mor/3600,"-") -> 20.362348 | AL55: =IF(AL$53<Total_Lanes,($BI55*($CH55+BT55)+$CM55*CV55)*Peak_Time_Mor/3600,"-") -> 461.18821 | ... AY55: =IF(AY$53<Total_Lanes,($BI55*($CH55+CG55)+$CM55*DI55)*Peak_Time_Mor/3600,"-") -> - | AZ55: =SUMIF(AE55:AY55,BA55,$AE$53:$AY$53) -> 1 | BA55: =MIN(AE55:AY55) -> 9.2617476 | BB55: =IF((SUMIF($BM53:$CG53,$AZ55,$BM55:$CG55)+$CH55)<(SUMIF($CO53:$DI53,$AZ55,$CO55:$DI55)+$DJ55),AZ55+1,AZ55) -> 1 | BC55: =SUMIF($AE$53:$AY$53,$BB55,$AE55:$AY55) -> 9.2617476 | BF55: 1 | BG55: =$X55 -> 0.06 | BH55: =$AC55 -> 2531.0454 | BI55: =BH55*(1-BG55) -> 2379.1826 | BJ55: =Peak_Arrival_Manual_Mor/K41 -> 4.3453127 | BK55: =900*Peak_Time_Mor*($BJ55/Total_Lanes-1+SQRT(($BJ55/Total_Lanes-1)^2+8*($BJ55/Total_Lanes)/(Peak_Time_Mor*$K41*Total_Lanes))) -> 0.31099205 | BL55: =Peak_Arrival_Manual_Mor/N41 -> 4.3593565 | BM55: =IF(BM$6<Total_Lanes,900*Peak_Time_Mor*($BL55/(Total_Lanes-BM$6)-1+SQRT(($BL55/(Total_Lanes-BM$6)-1)^2+8*($BL55/(Total_Lanes-BM$6))/(Peak_Time_Mor*$N41*(Total_Lanes-BM$6)))),"-") -> 0.39358451 | BN55: =IF(BN$6<Total_Lanes,900*Peak_Time_Mor*($BL55/(Total_Lanes-BN$6)-1+SQRT(($BL55/(Total_Lanes-BN$6)-1)^2+8*($BL55/(Total_Lanes-BN$6))/(Peak_Time_Mor*$N41*(Total_Lanes-BN$6)))),"-") -> 0.50966153 | BO55: =IF(BO$6<Total_Lanes,900*Peak_Time_Mor*($BL55/(Total_Lanes-BO$6)-1+SQRT(($BL55/(Total_Lanes-BO$6)-1)^2+8*($BL55/(Total_Lanes-BO$6))/(Peak_Time_Mor*$N41*(Total_Lanes-BO$6)))),"-") -> 0.68823664 | BP55: =IF(BP$6<Total_Lanes,900*Peak_Time_Mor*($BL55/(Total_Lanes-BP$6)-1+SQRT(($BL55/(Total_Lanes-BP$6)-1)^2+8*($BL55/(Total_Lanes-BP$6))/(Peak_Time_Mor*$N41*(Total_Lanes-BP$6)))),"-") -> 0.98671076 | BQ55: =IF(BQ$6<Total_Lanes,900*Peak_Time_Mor*($BL55/(Total_Lanes-BQ$6)-1+SQRT(($BL55/(Total_Lanes-BQ$6)-1)^2+8*($BL55/(Total_Lanes-BQ$6))/(Peak_Time_Mor*$N41*(Total_Lanes-BQ$6)))),"-") -> 1.5538713 | BR55: =IF(BR$6<Total_Lanes,900*Peak_Time_Mor*($BL55/(Total_Lanes-BR$6)-1+SQRT(($BL55/(Total_Lanes-BR$6)-1)^2+8*($BL55/(Total_Lanes-BR$6))/(Peak_Time_Mor*$N41*(Total_Lanes-BR$6)))),"-") -> 2.9125337 | BS55: =IF(BS$6<Total_Lanes,900*Peak_Time_Mor*($BL55/(Total_Lanes-BS$6)-1+SQRT(($BL55/(Total_Lanes-BS$6)-1)^2+8*($BL55/(Total_Lanes-BS$6))/(Peak_Time_Mor*$N41*(Total_Lanes-BS$6)))),"-") -> 8.8088149 | BT55: =IF(BT$6<Total_Lanes,900*Peak_Time_Mor*($BL55/(Total_Lanes-BT$6)-1+SQRT(($BL55/(Total_Lanes-BT$6)-1)^2+8*($BL55/(Total_Lanes-BT$6))/(Peak_Time_Mor*$N41*(Total_Lanes-BT$6)))),"-") -> 342.32114 | ... CG55: =IF(CG$6<Total_Lanes,900*Peak_Time_Mor*($BL55/(Total_Lanes-CG$6)-1+SQRT(($BL55/(Total_Lanes-CG$6)-1)^2+8*($BL55/(Total_Lanes-CG$6))/(Peak_Time_Mor*$N41*(Total_Lanes-CG$6)))),"-") -> - | CH55: =3600/N41 -> 6.59625 | CJ55: 1 | CK55: =$X55 -> 0.06 | CL55: =$AC55 -> 2531.0454 | CM55: =CL55*CK55 -> 151.86272 | CN55: =CM55/O41 -> 0.10124181 | CO55: =IF(CO$53<Total_Lanes,900*Peak_Time_Mor*($CN55/CO$53-1+SQRT(($CN55/CO$53-1)^2+8*($CN55/CO$53)/(Peak_Time_Mor*$O41*CO$53))),"-") -> 0.27032861 | CP55: =IF(CP$53<Total_Lanes,900*Peak_Time_Mor*($CN55/CP$53-1+SQRT(($CN55/CP$53-1)^2+8*($CN55/CP$53)/(Peak_Time_Mor*$O41*CP$53))),"-") -> 0.06398282 | CQ55: =IF(CQ$53<Total_Lanes,900*Peak_Time_Mor*($CN55/CQ$53-1+SQRT(($CN55/CQ$53-1)^2+8*($CN55/CQ$53)/(Peak_Time_Mor*$O41*CQ$53))),"-") -> 0.027940516 | CR55: =IF(CR$53<Total_Lanes,900*Peak_Time_Mor*($CN55/CR$53-1+SQRT(($CN55/CR$53-1)^2+8*($CN55/CR$53)/(Peak_Time_Mor*$O41*CR$53))),"-") -> 0.015580556 | CS55: =IF(CS$53<Total_Lanes,900*Peak_Time_Mor*($CN55/CS$53-1+SQRT(($CN55/CS$53-1)^2+8*($CN55/CS$53)/(Peak_Time_Mor*$O41*CS$53))),"-") -> 0.0099200516 | CT55: =IF(CT$53<Total_Lanes,900*Peak_Time_Mor*($CN55/CT$53-1+SQRT(($CN55/CT$53-1)^2+8*($CN55/CT$53)/(Peak_Time_Mor*$O41*CT$53))),"-") -> 0.0068652835 | CU55: =IF(CU$53<Total_Lanes,900*Peak_Time_Mor*($CN55/CU$53-1+SQRT(($CN55/CU$53-1)^2+8*($CN55/CU$53)/(Peak_Time_Mor*$O41*CU$53))),"-") -> 0.0050315476 | CV55: =IF(CV$53<Total_Lanes,900*Peak_Time_Mor*($CN55/CV$53-1+SQRT(($CN55/CV$53-1)^2+8*($CN55/CV$53)/(Peak_Time_Mor*$O41*CV$53))),"-") -> 0.0038452261 | ... DI55: =IF(DI$53<Total_Lanes,900*Peak_Time_Mor*($CN55/DI$53-1+SQRT(($CN55/DI$53-1)^2+8*($CN55/DI$53)/(Peak_Time_Mor*$O41*DI$53))),"-") -> - | DJ55: =3600/$O41 -> 2.4
H56: 16 | I56: ='Input-Detail'!BH29 -> 0.83 | J56: =1-I56 -> 0.17 | K56: =3600/(Trans_Time_Cash*I56+Trans_Time_Ticket*J56) -> 547.52852 | L56: ='Input-Detail'!BJ29 -> 0.966 | M56: =1-L56 -> 0.034 | N56: =3600/(Trans_Time_Cash*L56+Trans_Time_Ticket*M56) -> 520.60738 | O56: =3600/Headway_ETC -> 1500 | V56: 2 | W56: =W9 -> 20114556 | X56: =X9 -> 0.15 | Y56: =Y9 -> 8673.6357 | Z56: =W56/Y56 -> 2319.0455 | AA56: =AA9 -> 2 | AB56: =1-AB9 -> 0.3 | AC56: =Y56*AB56 -> 2602.0907 | AD56: =Peak_Time_Mor*$BH56*(CH56+BK56)/3600 -> 9.9681915 | AE56: =IF(AE$53<Total_Lanes,($BI56*($CH56+BM56)+$CM56*CO56)*Peak_Time_Mor/3600,"-") -> 8.7476857 | AF56: =IF(AF$53<Total_Lanes,($BI56*($CH56+BN56)+$CM56*CP56)*Peak_Time_Mor/3600,"-") -> 8.7272388 | AG56: =IF(AG$53<Total_Lanes,($BI56*($CH56+BO56)+$CM56*CQ56)*Peak_Time_Mor/3600,"-") -> 8.8920322 | AH56: =IF(AH$53<Total_Lanes,($BI56*($CH56+BP56)+$CM56*CR56)*Peak_Time_Mor/3600,"-") -> 9.1902521 | AI56: =IF(AI$53<Total_Lanes,($BI56*($CH56+BQ56)+$CM56*CS56)*Peak_Time_Mor/3600,"-") -> 9.7451669 | AJ56: =IF(AJ$53<Total_Lanes,($BI56*($CH56+BR56)+$CM56*CT56)*Peak_Time_Mor/3600,"-") -> 10.978111 | AK56: =IF(AK$53<Total_Lanes,($BI56*($CH56+BS56)+$CM56*CU56)*Peak_Time_Mor/3600,"-") -> 15.151314 | AL56: =IF(AL$53<Total_Lanes,($BI56*($CH56+BT56)+$CM56*CV56)*Peak_Time_Mor/3600,"-") -> 146.7173 | ... AY56: =IF(AY$53<Total_Lanes,($BI56*($CH56+CG56)+$CM56*DI56)*Peak_Time_Mor/3600,"-") -> - | AZ56: =SUMIF(AE56:AY56,BA56,$AE$53:$AY$53) -> 2 | BA56: =MIN(AE56:AY56) -> 8.7272388 | BB56: =IF((SUMIF($BM54:$CG54,$AZ56,$BM56:$CG56)+$CH56)<(SUMIF($CO54:$DI54,$AZ56,$CO56:$DI56)+$DJ56),AZ56+1,AZ56) -> 2 | BC56: =SUMIF($AE$53:$AY$53,$BB56,$AE56:$AY56) -> 8.7272388 | BF56: 2 | BG56: =$X56 -> 0.15 | BH56: =$AC56 -> 2602.0907 | BI56: =BH56*(1-BG56) -> 2211.7771 | BJ56: =Peak_Arrival_Manual_Mor/K42 -> 4.0395651 | BK56: =900*Peak_Time_Mor*($BJ56/Total_Lanes-1+SQRT(($BJ56/Total_Lanes-1)^2+8*($BJ56/Total_Lanes)/(Peak_Time_Mor*$K42*Total_Lanes))) -> 0.27801087 | BL56: =Peak_Arrival_Manual_Mor/N42 -> 4.0656764 | BM56: =IF(BM$6<Total_Lanes,900*Peak_Time_Mor*($BL56/(Total_Lanes-BM$6)-1+SQRT(($BL56/(Total_Lanes-BM$6)-1)^2+8*($BL56/(Total_Lanes-BM$6))/(Peak_Time_Mor*$N42*(Total_Lanes-BM$6)))),"-") -> 0.3526651 | BN56: =IF(BN$6<Total_Lanes,900*Peak_Time_Mor*($BL56/(Total_Lanes-BN$6)-1+SQRT(($BL56/(Total_Lanes-BN$6)-1)^2+8*($BL56/(Total_Lanes-BN$6))/(Peak_Time_Mor*$N42*(Total_Lanes-BN$6)))),"-") -> 0.4532767 | BO56: =IF(BO$6<Total_Lanes,900*Peak_Time_Mor*($BL56/(Total_Lanes-BO$6)-1+SQRT(($BL56/(Total_Lanes-BO$6)-1)^2+8*($BL56/(Total_Lanes-BO$6))/(Peak_Time_Mor*$N42*(Total_Lanes-BO$6)))),"-") -> 0.6056523 | BP56: =IF(BP$6<Total_Lanes,900*Peak_Time_Mor*($BL56/(Total_Lanes-BP$6)-1+SQRT(($BL56/(Total_Lanes-BP$6)-1)^2+8*($BL56/(Total_Lanes-BP$6))/(Peak_Time_Mor*$N42*(Total_Lanes-BP$6)))),"-") -> 0.85439196 | BQ56: =IF(BQ$6<Total_Lanes,900*Peak_Time_Mor*($BL56/(Total_Lanes-BQ$6)-1+SQRT(($BL56/(Total_Lanes-BQ$6)-1)^2+8*($BL56/(Total_Lanes-BQ$6))/(Peak_Time_Mor*$N42*(Total_Lanes-BQ$6)))),"-") -> 1.3087125 | BR56: =IF(BR$6<Total_Lanes,900*Peak_Time_Mor*($BL56/(Total_Lanes-BR$6)-1+SQRT(($BL56/(Total_Lanes-BR$6)-1)^2+8*($BL56/(Total_Lanes-BR$6))/(Peak_Time_Mor*$N42*(Total_Lanes-BR$6)))),"-") -> 2.3135639 | BS56: =IF(BS$6<Total_Lanes,900*Peak_Time_Mor*($BL56/(Total_Lanes-BS$6)-1+SQRT(($BL56/(Total_Lanes-BS$6)-1)^2+8*($BL56/(Total_Lanes-BS$6))/(Peak_Time_Mor*$N42*(Total_Lanes-BS$6)))),"-") -> 5.7106855 | BT56: =IF(BT$6<Total_Lanes,900*Peak_Time_Mor*($BL56/(Total_Lanes-BT$6)-1+SQRT(($BL56/(Total_Lanes-BT$6)-1)^2+8*($BL56/(Total_Lanes-BT$6))/(Peak_Time_Mor*$N42*(Total_Lanes-BT$6)))),"-") -> 112.78296 | ... CG56: =IF(CG$6<Total_Lanes,900*Peak_Time_Mor*($BL56/(Total_Lanes-CG$6)-1+SQRT(($BL56/(Total_Lanes-CG$6)-1)^2+8*($BL56/(Total_Lanes-CG$6))/(Peak_Time_Mor*$N42*(Total_Lanes-CG$6)))),"-") -> - | CH56: =3600/N42 -> 6.6175 | CJ56: 2 | CK56: =$X56 -> 0.15 | CL56: =$AC56 -> 2602.0907 | CM56: =CL56*CK56 -> 390.31361 | CN56: =CM56/O42 -> 0.26020907 | CO56: =IF(CO$53<Total_Lanes,900*Peak_Time_Mor*($CN56/CO$53-1+SQRT(($CN56/CO$53-1)^2+8*($CN56/CO$53)/(Peak_Time_Mor*$O42*CO$53))),"-") -> 0.84389241 | CP56: =IF(CP$53<Total_Lanes,900*Peak_Time_Mor*($CN56/CP$53-1+SQRT(($CN56/CP$53-1)^2+8*($CN56/CP$53)/(Peak_Time_Mor*$O42*CP$53))),"-") -> 0.17946581 | CQ56: =IF(CQ$53<Total_Lanes,900*Peak_Time_Mor*($CN56/CQ$53-1+SQRT(($CN56/CQ$53-1)^2+8*($CN56/CQ$53)/(Peak_Time_Mor*$O42*CQ$53))),"-") -> 0.075977493 | CR56: =IF(CR$53<Total_Lanes,900*Peak_Time_Mor*($CN56/CR$53-1+SQRT(($CN56/CR$53-1)^2+8*($CN56/CR$53)/(Peak_Time_Mor*$O42*CR$53))),"-") -> 0.041746587 | CS56: =IF(CS$53<Total_Lanes,900*Peak_Time_Mor*($CN56/CS$53-1+SQRT(($CN56/CS$53-1)^2+8*($CN56/CS$53)/(Peak_Time_Mor*$O42*CS$53))),"-") -> 0.026351244 | CT56: =IF(CT$53<Total_Lanes,900*Peak_Time_Mor*($CN56/CT$53-1+SQRT(($CN56/CT$53-1)^2+8*($CN56/CT$53)/(Peak_Time_Mor*$O42*CT$53))),"-") -> 0.018133601 | CU56: =IF(CU$53<Total_Lanes,900*Peak_Time_Mor*($CN56/CU$53-1+SQRT(($CN56/CU$53-1)^2+8*($CN56/CU$53)/(Peak_Time_Mor*$O42*CU$53))),"-") -> 0.013236938 | CV56: =IF(CV$53<Total_Lanes,900*Peak_Time_Mor*($CN56/CV$53-1+SQRT(($CN56/CV$53-1)^2+8*($CN56/CV$53)/(Peak_Time_Mor*$O42*CV$53))),"-") -> 0.010085866 | ... DI56: =IF(DI$53<Total_Lanes,900*Peak_Time_Mor*($CN56/DI$53-1+SQRT(($CN56/DI$53-1)^2+8*($CN56/DI$53)/(Peak_Time_Mor*$O42*DI$53))),"-") -> - | DJ56: =3600/$O42 -> 2.4
H57: 17 | I57: ='Input-Detail'!BH30 -> 0.83 | J57: =1-I57 -> 0.17 | K57: =3600/(Trans_Time_Cash*I57+Trans_Time_Ticket*J57) -> 547.52852 | L57: ='Input-Detail'!BJ30 -> 0.9745 | M57: =1-L57 -> 0.0255 | N57: =3600/(Trans_Time_Cash*L57+Trans_Time_Ticket*M57) -> 519.01243 | O57: =3600/Headway_ETC -> 1500 | V57: 3 | W57: =W10 -> 20663747 | X57: =X10 -> 0.2 | Y57: =Y10 -> 8910.4535 | Z57: =W57/Y57 -> 2319.0455 | AA57: =AA10 -> 2 | AB57: =1-AB10 -> 0.3 | AC57: =Y57*AB57 -> 2673.1361 | AD57: =Peak_Time_Mor*$BH57*(CH57+BK57)/3600 -> 10.251639 | AE57: =IF(AE$53<Total_Lanes,($BI57*($CH57+BM57)+$CM57*CO57)*Peak_Time_Mor/3600,"-") -> 8.6824469 | AF57: =IF(AF$53<Total_Lanes,($BI57*($CH57+BN57)+$CM57*CP57)*Peak_Time_Mor/3600,"-") -> 8.4779968 | AG57: =IF(AG$53<Total_Lanes,($BI57*($CH57+BO57)+$CM57*CQ57)*Peak_Time_Mor/3600,"-") -> 8.602575 | AH57: =IF(AH$53<Total_Lanes,($BI57*($CH57+BP57)+$CM57*CR57)*Peak_Time_Mor/3600,"-") -> 8.8627428 | AI57: =IF(AI$53<Total_Lanes,($BI57*($CH57+BQ57)+$CM57*CS57)*Peak_Time_Mor/3600,"-") -> 9.3508805 | AJ57: =IF(AJ$53<Total_Lanes,($BI57*($CH57+BR57)+$CM57*CT57)*Peak_Time_Mor/3600,"-") -> 10.411372 | AK57: =IF(AK$53<Total_Lanes,($BI57*($CH57+BS57)+$CM57*CU57)*Peak_Time_Mor/3600,"-") -> 13.743643 | AL57: =IF(AL$53<Total_Lanes,($BI57*($CH57+BT57)+$CM57*CV57)*Peak_Time_Mor/3600,"-") -> 73.785671 | ... AY57: =IF(AY$53<Total_Lanes,($BI57*($CH57+CG57)+$CM57*DI57)*Peak_Time_Mor/3600,"-") -> - | AZ57: =SUMIF(AE57:AY57,BA57,$AE$53:$AY$53) -> 2 | BA57: =MIN(AE57:AY57) -> 8.4779968 | BB57: =IF((SUMIF($BM55:$CG55,$AZ57,$BM57:$CG57)+$CH57)<(SUMIF($CO55:$DI55,$AZ57,$CO57:$DI57)+$DJ57),AZ57+1,AZ57) -> 2 | BC57: =SUMIF($AE$53:$AY$53,$BB57,$AE57:$AY57) -> 8.4779968 | BF57: 3 | BG57: =$X57 -> 0.2 | BH57: =$AC57 -> 2673.1361 | BI57: =BH57*(1-BG57) -> 2138.5088 | BJ57: =Peak_Arrival_Manual_Mor/K43 -> 3.9057488 | BK57: =900*Peak_Time_Mor*($BJ57/Total_Lanes-1+SQRT(($BJ57/Total_Lanes-1)^2+8*($BJ57/Total_Lanes)/(Peak_Time_Mor*$K43*Total_Lanes))) -> 0.26435946 | BL57: =Peak_Arrival_Manual_Mor/N43 -> 3.9436182 | BM57: =IF(BM$6<Total_Lanes,900*Peak_Time_Mor*($BL57/(Total_Lanes-BM$6)-1+SQRT(($BL57/(Total_Lanes-BM$6)-1)^2+8*($BL57/(Total_Lanes-BM$6))/(Peak_Time_Mor*$N43*(Total_Lanes-BM$6)))),"-") -> 0.33724305 | BN57: =IF(BN$6<Total_Lanes,900*Peak_Time_Mor*($BL57/(Total_Lanes-BN$6)-1+SQRT(($BL57/(Total_Lanes-BN$6)-1)^2+8*($BL57/(Total_Lanes-BN$6))/(Peak_Time_Mor*$N43*(Total_Lanes-BN$6)))),"-") -> 0.43219711 | BO57: =IF(BO$6<Total_Lanes,900*Peak_Time_Mor*($BL57/(Total_Lanes-BO$6)-1+SQRT(($BL57/(Total_Lanes-BO$6)-1)^2+8*($BL57/(Total_Lanes-BO$6))/(Peak_Time_Mor*$N43*(Total_Lanes-BO$6)))),"-") -> 0.57514233 | BP57: =IF(BP$6<Total_Lanes,900*Peak_Time_Mor*($BL57/(Total_Lanes-BP$6)-1+SQRT(($BL57/(Total_Lanes-BP$6)-1)^2+8*($BL57/(Total_Lanes-BP$6))/(Peak_Time_Mor*$N43*(Total_Lanes-BP$6)))),"-") -> 0.80641862 | BQ57: =IF(BQ$6<Total_Lanes,900*Peak_Time_Mor*($BL57/(Total_Lanes-BQ$6)-1+SQRT(($BL57/(Total_Lanes-BQ$6)-1)^2+8*($BL57/(Total_Lanes-BQ$6))/(Peak_Time_Mor*$N43*(Total_Lanes-BQ$6)))),"-") -> 1.2227504 | BR57: =IF(BR$6<Total_Lanes,900*Peak_Time_Mor*($BL57/(Total_Lanes-BR$6)-1+SQRT(($BL57/(Total_Lanes-BR$6)-1)^2+8*($BL57/(Total_Lanes-BR$6))/(Peak_Time_Mor*$N43*(Total_Lanes-BR$6)))),"-") -> 2.1182695 | BS57: =IF(BS$6<Total_Lanes,900*Peak_Time_Mor*($BL57/(Total_Lanes-BS$6)-1+SQRT(($BL57/(Total_Lanes-BS$6)-1)^2+8*($BL57/(Total_Lanes-BS$6))/(Peak_Time_Mor*$N43*(Total_Lanes-BS$6)))),"-") -> 4.9247855 | BT57: =IF(BT$6<Total_Lanes,900*Peak_Time_Mor*($BL57/(Total_Lanes-BT$6)-1+SQRT(($BL57/(Total_Lanes-BT$6)-1)^2+8*($BL57/(Total_Lanes-BT$6))/(Peak_Time_Mor*$N43*(Total_Lanes-BT$6)))),"-") -> 55.463742 | ... CG57: =IF(CG$6<Total_Lanes,900*Peak_Time_Mor*($BL57/(Total_Lanes-CG$6)-1+SQRT(($BL57/(Total_Lanes-CG$6)-1)^2+8*($BL57/(Total_Lanes-CG$6))/(Peak_Time_Mor*$N43*(Total_Lanes-CG$6)))),"-") -> - | CH57: =3600/N43 -> 6.63875 | CJ57: 3 | CK57: =$X57 -> 0.2 | CL57: =$AC57 -> 2673.1361 | CM57: =CL57*CK57 -> 534.62721 | CN57: =CM57/O43 -> 0.35641814 | CO57: =IF(CO$53<Total_Lanes,900*Peak_Time_Mor*($CN57/CO$53-1+SQRT(($CN57/CO$53-1)^2+8*($CN57/CO$53)/(Peak_Time_Mor*$O43*CO$53))),"-") -> 1.3283677 | CP57: =IF(CP$53<Total_Lanes,900*Peak_Time_Mor*($CN57/CP$53-1+SQRT(($CN57/CP$53-1)^2+8*($CN57/CP$53)/(Peak_Time_Mor*$O43*CP$53))),"-") -> 0.26020253 | CQ57: =IF(CQ$53<Total_Lanes,900*Peak_Time_Mor*($CN57/CQ$53-1+SQRT(($CN57/CQ$53-1)^2+8*($CN57/CQ$53)/(Peak_Time_Mor*$O43*CQ$53))),"-") -> 0.10785549 | CR57: =IF(CR$53<Total_Lanes,900*Peak_Time_Mor*($CN57/CR$53-1+SQRT(($CN57/CR$53-1)^2+8*($CN57/CR$53)/(Peak_Time_Mor*$O43*CR$53))),"-") -> 0.058691438 | CS57: =IF(CS$53<Total_Lanes,900*Peak_Time_Mor*($CN57/CS$53-1+SQRT(($CN57/CS$53-1)^2+8*($CN57/CS$53)/(Peak_Time_Mor*$O43*CS$53))),"-") -> 0.036841996 | CT57: =IF(CT$53<Total_Lanes,900*Peak_Time_Mor*($CN57/CT$53-1+SQRT(($CN57/CT$53-1)^2+8*($CN57/CT$53)/(Peak_Time_Mor*$O43*CT$53))),"-") -> 0.025261651 | CU57: =IF(CU$53<Total_Lanes,900*Peak_Time_Mor*($CN57/CU$53-1+SQRT(($CN57/CU$53-1)^2+8*($CN57/CU$53)/(Peak_Time_Mor*$O43*CU$53))),"-") -> 0.018393669 | CV57: =IF(CV$53<Total_Lanes,900*Peak_Time_Mor*($CN57/CV$53-1+SQRT(($CN57/CV$53-1)^2+8*($CN57/CV$53)/(Peak_Time_Mor*$O43*CV$53))),"-") -> 0.013988861 | ... DI57: =IF(DI$53<Total_Lanes,900*Peak_Time_Mor*($CN57/DI$53-1+SQRT(($CN57/DI$53-1)^2+8*($CN57/DI$53)/(Peak_Time_Mor*$O43*DI$53))),"-") -> - | DJ57: =3600/$O43 -> 2.4
H58: 18 | I58: ='Input-Detail'!BH31 -> 0.83 | J58: =1-I58 -> 0.17 | K58: =3600/(Trans_Time_Cash*I58+Trans_Time_Ticket*J58) -> 547.52852 | L58: ='Input-Detail'!BJ31 -> 0.983 | M58: =1-L58 -> 0.017 | N58: =3600/(Trans_Time_Cash*L58+Trans_Time_Ticket*M58) -> 517.42724 | O58: =3600/Headway_ETC -> 1500 | V58: 4 | W58: =W11 -> 21212938 | X58: =X11 -> 0.25 | Y58: =Y11 -> 9147.2714 | Z58: =W58/Y58 -> 2319.0455 | AA58: =AA11 -> 2 | AB58: =1-AB11 -> 0.3 | AC58: =Y58*AB58 -> 2744.1814 | AD58: =Peak_Time_Mor*$BH58*(CH58+BK58)/3600 -> 10.534446 | AE58: =IF(AE$53<Total_Lanes,($BI58*($CH58+BM58)+$CM58*CO58)*Peak_Time_Mor/3600,"-") -> 8.7517203 | AF58: =IF(AF$53<Total_Lanes,($BI58*($CH58+BN58)+$CM58*CP58)*Peak_Time_Mor/3600,"-") -> 8.21883 | AG58: =IF(AG$53<Total_Lanes,($BI58*($CH58+BO58)+$CM58*CQ58)*Peak_Time_Mor/3600,"-") -> 8.2902353 | AH58: =IF(AH$53<Total_Lanes,($BI58*($CH58+BP58)+$CM58*CR58)*Peak_Time_Mor/3600,"-") -> 8.5087778 | AI58: =IF(AI$53<Total_Lanes,($BI58*($CH58+BQ58)+$CM58*CS58)*Peak_Time_Mor/3600,"-") -> 8.9301041 | AJ58: =IF(AJ$53<Total_Lanes,($BI58*($CH58+BR58)+$CM58*CT58)*Peak_Time_Mor/3600,"-") -> 9.8286122 | AK58: =IF(AK$53<Total_Lanes,($BI58*($CH58+BS58)+$CM58*CU58)*Peak_Time_Mor/3600,"-") -> 12.46347 | AL58: =IF(AL$53<Total_Lanes,($BI58*($CH58+BT58)+$CM58*CV58)*Peak_Time_Mor/3600,"-") -> 39.995775 | ... AY58: =IF(AY$53<Total_Lanes,($BI58*($CH58+CG58)+$CM58*DI58)*Peak_Time_Mor/3600,"-") -> - | AZ58: =SUMIF(AE58:AY58,BA58,$AE$53:$AY$53) -> 2 | BA58: =MIN(AE58:AY58) -> 8.21883 | BB58: =IF((SUMIF($BM56:$CG56,$AZ58,$BM58:$CG58)+$CH58)<(SUMIF($CO56:$DI56,$AZ58,$CO58:$DI58)+$DJ58),AZ58+1,AZ58) -> 2 | BC58: =SUMIF($AE$53:$AY$53,$BB58,$AE58:$AY58) -> 8.21883 | BF58: 4 | BG58: =$X58 -> 0.25 | BH58: =$AC58 -> 2744.1814 | BI58: =BH58*(1-BG58) -> 2058.1361 | BJ58: =Peak_Arrival_Manual_Mor/K44 -> 3.7589568 | BK58: =900*Peak_Time_Mor*($BJ58/Total_Lanes-1+SQRT(($BJ58/Total_Lanes-1)^2+8*($BJ58/Total_Lanes)/(Peak_Time_Mor*$K44*Total_Lanes))) -> 0.24989396 | BL58: =Peak_Arrival_Manual_Mor/N44 -> 3.8075517 | BM58: =IF(BM$6<Total_Lanes,900*Peak_Time_Mor*($BL58/(Total_Lanes-BM$6)-1+SQRT(($BL58/(Total_Lanes-BM$6)-1)^2+8*($BL58/(Total_Lanes-BM$6))/(Peak_Time_Mor*$N44*(Total_Lanes-BM$6)))),"-") -> 0.32047303 | BN58: =IF(BN$6<Total_Lanes,900*Peak_Time_Mor*($BL58/(Total_Lanes-BN$6)-1+SQRT(($BL58/(Total_Lanes-BN$6)-1)^2+8*($BL58/(Total_Lanes-BN$6))/(Peak_Time_Mor*$N44*(Total_Lanes-BN$6)))),"-") -> 0.40942834 | BO58: =IF(BO$6<Total_Lanes,900*Peak_Time_Mor*($BL58/(Total_Lanes-BO$6)-1+SQRT(($BL58/(Total_Lanes-BO$6)-1)^2+8*($BL58/(Total_Lanes-BO$6))/(Peak_Time_Mor*$N44*(Total_Lanes-BO$6)))),"-") -> 0.54249024 | BP58: =IF(BP$6<Total_Lanes,900*Peak_Time_Mor*($BL58/(Total_Lanes-BP$6)-1+SQRT(($BL58/(Total_Lanes-BP$6)-1)^2+8*($BL58/(Total_Lanes-BP$6))/(Peak_Time_Mor*$N44*(Total_Lanes-BP$6)))),"-") -> 0.75576782 | BQ58: =IF(BQ$6<Total_Lanes,900*Peak_Time_Mor*($BL58/(Total_Lanes-BQ$6)-1+SQRT(($BL58/(Total_Lanes-BQ$6)-1)^2+8*($BL58/(Total_Lanes-BQ$6))/(Peak_Time_Mor*$N44*(Total_Lanes-BQ$6)))),"-") -> 1.1339614 | BR58: =IF(BR$6<Total_Lanes,900*Peak_Time_Mor*($BL58/(Total_Lanes-BR$6)-1+SQRT(($BL58/(Total_Lanes-BR$6)-1)^2+8*($BL58/(Total_Lanes-BR$6))/(Peak_Time_Mor*$N44*(Total_Lanes-BR$6)))),"-") -> 1.9248833 | BS58: =IF(BS$6<Total_Lanes,900*Peak_Time_Mor*($BL58/(Total_Lanes-BS$6)-1+SQRT(($BL58/(Total_Lanes-BS$6)-1)^2+8*($BL58/(Total_Lanes-BS$6))/(Peak_Time_Mor*$N44*(Total_Lanes-BS$6)))),"-") -> 4.2322848 | BT58: =IF(BT$6<Total_Lanes,900*Peak_Time_Mor*($BL58/(Total_Lanes-BT$6)-1+SQRT(($BL58/(Total_Lanes-BT$6)-1)^2+8*($BL58/(Total_Lanes-BT$6))/(Peak_Time_Mor*$N44*(Total_Lanes-BT$6)))),"-") -> 28.313351 | ... CG58: =IF(CG$6<Total_Lanes,900*Peak_Time_Mor*($BL58/(Total_Lanes-CG$6)-1+SQRT(($BL58/(Total_Lanes-CG$6)-1)^2+8*($BL58/(Total_Lanes-CG$6))/(Peak_Time_Mor*$N44*(Total_Lanes-CG$6)))),"-") -> - | CH58: =3600/N44 -> 6.66 | CJ58: 4 | CK58: =$X58 -> 0.25 | CL58: =$AC58 -> 2744.1814 | CM58: =CL58*CK58 -> 686.04535 | CN58: =CM58/O44 -> 0.45736357 | CO58: =IF(CO$53<Total_Lanes,900*Peak_Time_Mor*($CN58/CO$53-1+SQRT(($CN58/CO$53-1)^2+8*($CN58/CO$53)/(Peak_Time_Mor*$O44*CO$53))),"-") -> 2.0207605 | CP58: =IF(CP$53<Total_Lanes,900*Peak_Time_Mor*($CN58/CP$53-1+SQRT(($CN58/CP$53-1)^2+8*($CN58/CP$53)/(Peak_Time_Mor*$O44*CP$53))),"-") -> 0.35573254 | CQ58: =IF(CQ$53<Total_Lanes,900*Peak_Time_Mor*($CN58/CQ$53-1+SQRT(($CN58/CQ$53-1)^2+8*($CN58/CQ$53)/(Peak_Time_Mor*$O44*CQ$53))),"-") -> 0.14389537 | CR58: =IF(CR$53<Total_Lanes,900*Peak_Time_Mor*($CN58/CR$53-1+SQRT(($CN58/CR$53-1)^2+8*($CN58/CR$53)/(Peak_Time_Mor*$O44*CR$53))),"-") -> 0.077459677 | CS58: =IF(CS$53<Total_Lanes,900*Peak_Time_Mor*($CN58/CS$53-1+SQRT(($CN58/CS$53-1)^2+8*($CN58/CS$53)/(Peak_Time_Mor*$O44*CS$53))),"-") -> 0.048326841 | CT58: =IF(CT$53<Total_Lanes,900*Peak_Time_Mor*($CN58/CT$53-1+SQRT(($CN58/CT$53-1)^2+8*($CN58/CT$53)/(Peak_Time_Mor*$O44*CT$53))),"-") -> 0.033006605 | CU58: =IF(CU$53<Total_Lanes,900*Peak_Time_Mor*($CN58/CU$53-1+SQRT(($CN58/CU$53-1)^2+8*($CN58/CU$53)/(Peak_Time_Mor*$O44*CU$53))),"-") -> 0.023967288 | CV58: =IF(CV$53<Total_Lanes,900*Peak_Time_Mor*($CN58/CV$53-1+SQRT(($CN58/CV$53-1)^2+8*($CN58/CV$53)/(Peak_Time_Mor*$O44*CV$53))),"-") -> 0.018191031 | ... DI58: =IF(DI$53<Total_Lanes,900*Peak_Time_Mor*($CN58/DI$53-1+SQRT(($CN58/DI$53-1)^2+8*($CN58/DI$53)/(Peak_Time_Mor*$O44*DI$53))),"-") -> - | DJ58: =3600/$O44 -> 2.4
