Workbook

Sheet Price
K1: Optimal Number of ETC Lanes
B3: 1 Transaction Facts | H3: a) Total Random and Stop Delay in the System during the Evening Peak per Day (hr) | BT3: c) Average Random Delay per ETC User (sec)
H5: Year | I5: Price Diff. | J5: Time Difference (min) | K5: Split (ETC/Manual) | L5: d | M5: NPV | N5: ETC (%) | O5: T (hr) | P5: Total Arrival Rate | Q5: Delay in Manual Lanes | W5: Number of ETC Lanes
B6: Transaction Time (sec) | G6: 0.065587921 | Q6: Arrival rate | R6: Nr. of Lanes | S6: Mean Serive Rate | T6: r | U6: Random Delay (sec) | V6: Acc/Dec Delay (sec) | W6: Arrival rate | X6: Nr. of Lanes | Y6: Mean Serive Rate | Z6: r | AA6: Random Delay (sec)
C7: Cash | D7: ='Input-Detail'!AZ10 -> 7 | G7: NPV0 | N7: 0
C8: Ticket | D8: ='Input-Detail'!AZ11 -> 4.5 | G8: 22059 | H8: 1 | I8: 0 | J8: -1.0727208 | K8: 0.075250573 | L8: 7.4215731e-06 | M8: 31729.96 | N8: 0.06998422 | O8: ='Input-Detail'!X18 -> 2 | P8: ='Input-Detail'!V19*'Input-Detail'!Y19 -> 5905.7725 | Q8: =P8*(1-N8) -> 5492.4616 | R8: =$D$12-X8 -> 11 | S8: =Delay!$N41 -> 545.76464 | T8: =Q8/(R8*S8) -> 0.91489015 | U8: 12.912107 | V8: 52.363636 | W8: =P8-Q8 -> 413.31088 | X8: =ETCLANE!BB8 -> 1 | Y8: =Delay!$O41 -> 1500 | Z8: =W8/(X8*Y8) -> 0.27554059 | AA8: 0.91249573
C9: ETC | D9: ='Input-Detail'!AZ12 -> 2.4 | E9: 0 | H9: 2 | I9: 0 | J9: -1.0083182 | K9: 0.15404974 | L9: 8.9849683e-06 | M9: 783006.26 | N9: 0.13348622 | O9: ='Input-Detail'!X19 -> 2 | P9: ='Input-Detail'!V20*'Input-Detail'!Y20 -> 6071.545 | Q9: =P9*(1-N9) -> 5261.0774 | R9: =$D$12-X9 -> 11 | S9: =Delay!$N42 -> 544.01209 | T9: =Q9/(R9*S9) -> 0.8791712 | U9: 10.951595 | V9: 52.363636 | W9: =P9-Q9 -> 810.46759 | X9: =ETCLANE!BB9 -> 1 | Y9: =Delay!$O42 -> 1500 | Z9: =W9/(X9*Y9) -> 0.54031173 | AA9: 2.8161371
B10: Total Number of Lanes | D10: ='Input-Detail'!AZ25 -> 12 | H10: 3 | I10: 0 | J10: -1.1103072 | K10: 0.23807043 | L10: 5.7807439e-06 | M10: 1245032.8 | N10: 0.19229151 | O10: ='Input-Detail'!X20 -> 2 | P10: ='Input-Detail'!V21*'Input-Detail'!Y21 -> 6237.3175 | Q10: =P10*(1-N10) -> 5037.9343 | R10: =$D$12-X10 -> 10 | S10: =Delay!$N43 -> 542.27076 | T10: =Q10/(R10*S10) -> 0.92904406 | U10: 15.053814 | V10: 52.363636 | W10: =P10-Q10 -> 1199.3832 | X10: =ETCLANE!BB10 -> 2 | Y10: =Delay!$O43 -> 1500 | Z10: =W10/(X10*Y10) -> 0.39979439 | AA10: 0.79901942
B11: Configuration of the Toll Plaza | H11: 4 | I11: 0 | J11: -1.0516707 | K11: 0.32826275 | L11: 5.0809504e-06 | M11: 1786952.8 | N11: 0.24713691 | O11: ='Input-Detail'!X21 -> 2 | P11: ='Input-Detail'!V22*'Input-Detail'!Y22 -> 6403.09 | Q11: =P11*(1-N11) -> 4820.6501 | R11: =$D$12-X11 -> 10 | S11: =Delay!$N44 -> 540.54054 | T11: =Q11/(R11*S11) -> 0.89182027 | U11: 12.075126 | V11: 52.363636 | W11: =P11-Q11 -> 1582.4398 | X11: =ETCLANE!BB11 -> 2 | Y11: =Delay!$O44 -> 1500 | Z11: =W11/(X11*Y11) -> 0.52747995 | AA11: 1.3385215
C12: Total Number of Lanes | D12: ='Input-Detail'!AZ25 -> 12 | H12: 5 | I12: 0 | J12: -1.0112119 | K12: 0.42650201 | L12: 8.2629947e-06 | M12: 2290995.5 | N12: 0.29898451 | O12: ='Input-Detail'!X22 -> 2 | P12: ='Input-Detail'!V23*'Input-Detail'!Y23 -> 6568.8625 | Q12: =P12*(1-N12) -> 4604.8743 | R12: =$D$12-X12 -> 10 | S12: =Delay!$N45 -> 538.82133 | T12: =Q12/(R12*S12) -> 0.8546199 | U12: 10.579796 | V12: 52.363636 | W12: =P12-Q12 -> 1963.9881 | X12: =ETCLANE!BB12 -> 2 | Y12: =Delay!$O45 -> 1500 | Z12: =W12/(X12*Y12) -> 0.65466272 | AA12: 2.2707163
C13: Ramp Distance prior to the Toll Plaza (miles) | D13: ='Input-Detail'!AZ26 -> 0.2 | H13: 6 | I13: 0 | J13: -1.0887094 | K13: 0.53565597 | L13: 5.2565051e-06 | M13: 2774294.3 | N13: 0.34881248 | O13: ='Input-Detail'!X23 -> 2 | P13: ='Input-Detail'!V24*'Input-Detail'!Y24 -> 6734.6349 | Q13: =P13*(1-N13) -> 4385.5102 | R13: =$D$12-X13 -> 9 | S13: =Delay!$N46 -> 537.11302 | T13: =Q13/(R13*S13) -> 0.90721858 | U13: 13.832221 | V13: 52.363636 | W13: =P13-Q13 -> 2349.1247 | X13: =ETCLANE!BB13 -> 3 | Y13: =Delay!$O46 -> 1500 | Z13: =W13/(X13*Y13) -> 0.52202772 | AA13: 0.87329401
C14: Ramp Distance leading from the toll Plaza (miles) | D14: ='Input-Detail'!AZ27 -> 0.2 | H14: 7 | I14: 0 | J14: -1.0423843 | K14: 0.65759171 | L14: 9.5234278e-06 | M14: 3297579.6 | N14: 0.39671513 | O14: ='Input-Detail'!X24 -> 2 | P14: ='Input-Detail'!V25*'Input-Detail'!Y25 -> 6900.4074 | Q14: =P14*(1-N14) -> 4162.9114 | R14: =$D$12-X14 -> 9 | S14: =Delay!$N47 -> 535.4155 | T14: =Q14/(R14*S14) -> 0.86390048 | U14: 11.420879 | V14: 52.363636 | W14: =P14-Q14 -> 2737.496 | X14: =ETCLANE!BB14 -> 3 | Y14: =Delay!$O47 -> 1500 | Z14: =W14/(X14*Y14) -> 0.60833245 | AA14: 1.2414555
B15: Average Travel Speed (mph) | D15: ='Input-Detail'!AZ29 -> 55 | H15: 8 | I15: 0 | J15: -1.0110577 | K15: 0.79545306 | L15: 8.093132e-06 | M15: 3803281.4 | N15: 0.44303751 | O15: ='Input-Detail'!X25 -> 2 | P15: ='Input-Detail'!V26*'Input-Detail'!Y26 -> 7066.1799 | Q15: =P15*(1-N15) -> 3935.5971 | R15: =$D$12-X15 -> 9 | S15: =Delay!$N48 -> 533.72869 | T15: =Q15/(R15*S15) -> 0.81930872 | U15: 10.125638 | V15: 52.363636 | W15: =P15-Q15 -> 3130.5828 | X15: =ETCLANE!BB15 -> 3 | Y15: =Delay!$O48 -> 1500 | Z15: =W15/(X15*Y15) -> 0.69568506 | AA15: 1.8258126
B16: ETC Survival Rate | D16: 0.84 | H16: 9 | I16: 0 | J16: -1.0641648 | K16: 0.95370764 | L16: 7.9325893e-06 | M16: 4324612.4 | N16: 0.48815269 | O16: ='Input-Detail'!X26 -> 2 | P16: ='Input-Detail'!V27*'Input-Detail'!Y27 -> 7231.9524 | Q16: =P16*(1-N16) -> 3701.6554 | R16: =$D$12-X16 -> 8 | S16: =Delay!$N49 -> 532.05247 | T16: =Q16/(R16*S16) -> 0.86966409 | U16: 12.343419 | V16: 52.363636 | W16: =P16-Q16 -> 3530.297 | X16: =ETCLANE!BB16 -> 4 | Y16: =Delay!$O49 -> 1500 | Z16: =W16/(X16*Y16) -> 0.58838284 | AA16: 0.85716933
H17: 10 | I17: 0 | J17: -1.029363 | K17: 1.1355253 | L17: 7.1061015e-06 | M17: 4853905.7 | N17: 0.53173113 | O17: ='Input-Detail'!X27 -> 2 | P17: ='Input-Detail'!V28*'Input-Detail'!Y28 -> 7397.7249 | Q17: =P17*(1-N17) -> 3464.1243 | R17: =$D$12-X17 -> 8 | S17: =Delay!$N50 -> 530.38674 | T17: =Q17/(R17*S17) -> 0.81641471 | U17: 10.539255 | V17: 52.363636 | W17: =P17-Q17 -> 3933.6006 | X17: =ETCLANE!BB17 -> 4 | Y17: =Delay!$O50 -> 1500 | Z17: =W17/(X17*Y17) -> 0.6556001 | AA17: 1.1411105
H18: 11 | I18: 0 | J18: -1.0054556 | K18: 1.3458196 | L18: 6.0171627e-06 | M18: 5368564.1 | N18: 0.57370976 | O18: ='Input-Detail'!X28 -> 2 | P18: ='Input-Detail'!V29*'Input-Detail'!Y29 -> 7563.4974 | Q18: =P18*(1-N18) -> 3224.2451 | R18: =$D$12-X18 -> 8 | S18: =Delay!$N51 -> 528.73141 | T18: =Q18/(R18*S18) -> 0.76225968 | U18: 9.5289408 | V18: 52.363636 | W18: =P18-Q18 -> 4339.2523 | X18: =ETCLANE!BB18 -> 4 | Y18: =Delay!$O51 -> 1500 | Z18: =W18/(X18*Y18) -> 0.72320872 | AA18: 1.5652396
H19: 12 | I19: 0 | J19: -1.0410105 | K19: 1.5912161 | L19: 5.4568003e-06 | M19: 5915262.3 | N19: 0.61408081 | O19: ='Input-Detail'!X29 -> 2 | P19: ='Input-Detail'!V30*'Input-Detail'!Y30 -> 7729.2699 | Q19: =P19*(1-N19) -> 2982.8736 | R19: =$D$12-X19 -> 7 | S19: =Delay!$N52 -> 527.08638 | T19: =Q19/(R19*S19) -> 0.80845343 | U19: 10.923856 | V19: 52.363636 | W19: =P19-Q19 -> 4746.3963 | X19: =ETCLANE!BB19 -> 5 | Y19: =Delay!$O52 -> 1500 | Z19: =W19/(X19*Y19) -> 0.63285284 | AA19: 0.82686041
H20: 13 | I20: 0 | J20: -1.0171937 | K20: 1.8766808 | L20: 9.5794369e-06 | M20: 6434905.6 | N20: 0.65237714 | O20: ='Input-Detail'!X30 -> 2 | P20: ='Input-Detail'!V31*'Input-Detail'!Y31 -> 7895.0424 | Q20: =P20*(1-N20) -> 2744.4972 | R20: =$D$12-X20 -> 7 | S20: =Delay!$N53 -> 525.45156 | T20: =Q20/(R20*S20) -> 0.74616018 | U20: 9.7192767 | V20: 52.363636 | W20: =P20-Q20 -> 5150.5452 | X20: =ETCLANE!BB20 -> 5 | Y20: =Delay!$O53 -> 1500 | Z20: =W20/(X20*Y20) -> 0.68673936 | AA20: 1.0512903
H21: 14 | I21: 0 | J21: -1.0518488 | K21: 2.2108944 | L21: 7.9857443e-06 | M21: 6972281.4 | N21: 0.68856029 | O21: ='Input-Detail'!X31 -> 2 | P21: ='Input-Detail'!V32*'Input-Detail'!Y32 -> 8060.8149 | Q21: =P21*(1-N21) -> 2510.4578 | R21: =$D$12-X21 -> 6 | S21: =Delay!$N54 -> 523.82685 | T21: =Q21/(R21*S21) -> 0.79875562 | U21: 11.390578 | V21: 52.363636 | W21: =P21-Q21 -> 5550.357 | X21: =ETCLANE!BB21 -> 6 | Y21: =Delay!$O54 -> 1500 | Z21: =W21/(X21*Y21) -> 0.61670634 | AA21: 0.64328636
H22: 15 | I22: 0 | J22: -1.0261345 | K22: 2.5996438 | L22: 7.1529341e-06 | M22: 7480146.3 | N22: 0.72219474 | O22: ='Input-Detail'!X32 -> 2 | P22: ='Input-Detail'!V33*'Input-Detail'!Y33 -> 8226.5874 | Q22: =P22*(1-N22) -> 2285.3893 | R22: =$D$12-X22 -> 6 | S22: =Delay!$N55 -> 522.21215 | T22: =Q22/(R22*S22) -> 0.72939362 | U22: 9.9808744 | V22: 52.363636 | W22: =P22-Q22 -> 5941.1981 | X22: =ETCLANE!BB22 -> 6 | Y22: =Delay!$O55 -> 1500 | Z22: =W22/(X22*Y22) -> 0.66013312 | AA22: 0.77643867
H23: 16 | I23: 0 | J23: -1.0099904 | K23: 3.0519616 | L23: 6.0726046e-06 | M23: 7967363.8 | N23: 0.75320595 | O23: ='Input-Detail'!X33 -> 2 | P23: ='Input-Detail'!V34*'Input-Detail'!Y34 -> 8392.3598 | Q23: =P23*(1-N23) -> 2071.1845 | R23: =$D$12-X23 -> 6 | S23: =Delay!$N56 -> 520.60738 | T23: =Q23/(R23*S23) -> 0.66306669 | U23: 9.1788331 | V23: 52.363636 | W23: =P23-Q23 -> 6321.1754 | X23: =ETCLANE!BB23 -> 6 | Y23: =Delay!$O56 -> 1500 | Z23: =W23/(X23*Y23) -> 0.70235282 | AA23: 0.94304301
H24: 17 | I24: 0 | J24: -1.0375728 | K24: 3.5798342 | L24: 5.2706862e-06 | M24: 8474466.1 | N24: 0.78165149 | O24: ='Input-Detail'!X34 -> 2 | P24: ='Input-Detail'!V35*'Input-Detail'!Y35 -> 8558.1323 | Q24: =P24*(1-N24) -> 1868.6555 | R24: =$D$12-X24 -> 5 | S24: =Delay!$N57 -> 519.01243 | T24: =Q24/(R24*S24) -> 0.7200812 | U24: 10.492352 | V24: 52.363636 | W24: =P24-Q24 -> 6689.4769 | X24: =ETCLANE!BB24 -> 7 | Y24: =Delay!$O57 -> 1500 | Z24: =W24/(X24*Y24) -> 0.63709303 | AA24: 0.60161798
B25: 1 Estimation of a0 | H25: 18 | I25: 0 | J25: -1.0199565 | K25: 4.1909234 | L25: 9.1993363e-06 | M25: 8931657.9 | N25: 0.80735605 | O25: ='Input-Detail'!X35 -> 2 | P25: ='Input-Detail'!V36*'Input-Detail'!Y36 -> 8723.9048 | Q25: =P25*(1-N25) -> 1680.6075 | R25: =$D$12-X25 -> 5 | S25: =Delay!$N58 -> 517.42724 | T25: =Q25/(R25*S25) -> 0.64960149 | U25: 9.5319385 | V25: 52.363636 | W25: =P25-Q25 -> 7043.2973 | X25: =ETCLANE!BB25 -> 7 | Y25: =Delay!$O58 -> 1500 | Z25: =W25/(X25*Y25) -> 0.67079022 | AA25: 0.69818646
H26: 19 | I26: 0 | J26: -1.0592761 | K26: 4.9019317 | L26: 7.92225e-06 | M26: 9398822.5 | N26: 0.83056395 | O26: ='Input-Detail'!X36 -> 2 | P26: ='Input-Detail'!V37*'Input-Detail'!Y37 -> 8889.6773 | Q26: =P26*(1-N26) -> 1506.2318 | R26: =$D$12-X26 -> 4 | S26: =Delay!$N59 -> 515.85169 | T26: =Q26/(R26*S26) -> 0.72997328 | U26: 11.672564 | V26: 52.363636 | W26: =P26-Q26 -> 7383.4455 | X26: =ETCLANE!BB26 -> 8 | Y26: =Delay!$O59 -> 1500 | Z26: =W26/(X26*Y26) -> 0.61528713 | AA26: 0.47963623
B27: ATV | C27: 19016173 | H27: 20 | I27: 0 | J27: -1.0356639 | K27: 5.7197755 | L27: 7.1260609e-06 | M27: 9820875.8 | N27: 0.85118551 | O27: ='Input-Detail'!X37 -> 2 | P27: ='Input-Detail'!V38*'Input-Detail'!Y38 -> 9055.4498 | Q27: =P27*(1-N27) -> 1347.5822 | R27: =$D$12-X27 -> 4 | S27: =Delay!$N60 -> 514.28571 | T27: =Q27/(R27*S27) -> 0.65507467 | U27: 10.314714 | V27: 52.363636 | W27: =P27-Q27 -> 7707.8676 | X27: =ETCLANE!BB27 -> 8 | Y27: =Delay!$O60 -> 1500 | Z27: =W27/(X27*Y27) -> 0.6423223 | AA27: 0.53851871
B28: ETC % | C28: 0.06
B29: rel. % | C29: =C28/(1-C28) -> 0.063829787
B30: Time Diff | C30: =-11.06/60 -> -0.18433333
B31: Price Diff | C31: 0
B32: a0 | C32: =LN(C29)-C33*C30-C34*C31 -> -2.7570653
B33: a1 | C33: -0.03
B34: a2 | C34: =C33/('Input-Detail'!AZ39/60) -> -0.14117647

Sheet ETCLANE
Z1: Optimal Number of ETC Lanes
B3: 1 Transaction Facts | K3: y Total Random and Stop Delay per Year (hrs) | V3: a) Total Random and Stop Delay in the System during the Evening Peak per Day (hr) | BF3: b) Average Random Delay per Manual User (sec) | CJ3: c) Average Random Delay per ETC User (sec)
H5: Year | I5: Traffic Vol. | J5: ETC (%) | K5: Peak Arrival Rate in the evening | L5: Delay per Day (Baseline) | O5: Delay Per Year* (hr) | P5: Delay per Day (ETC) | S5: Delay Per Year* (hr) | V5: Year | W5: Traffic Vol. | X5: ETC (%) | Y5: PHV | Z5: ATV/PHV | AA5: T (hr) | AB5: K | AC5: Total Arrival Rate | AD5: Number of ETC Lanes | AZ5: Optimal # of ETC Ln* | BA5: Delay per Day**(hr) | BB5: Suggested # of ETC Ln*** | BC5: Delay per Day**(hr) | BF5: Year | BG5: ETC (%) | BH5: Total Arrival Rate | BI5: Arrival Rate for Manual Lanes | BJ5: Number of ETC Lanes | CH5: Mean Transaction Time (sec) | CJ5: Year | CK5: ETC (%) | CL5: Total Arrival Rate | CM5: Arrival Rate for ETC Users | CN5: Number of ETC Lanes | DJ5: Mean headway (sec)
B6: Transaction Time (sec) | L6: Morning | M6: Evening | N6: Total | P6: Morning | Q6: Evening | R6: Total | AD6: Manual Only | AE6: 1 | AF6: 2 | AG6: 3 | AH6: 4 | AI6: 5 | AJ6: 6 | AK6: 7 | AL6: 8 | AM6: 9 | AN6: 10 | AO6: 11 | AP6: 12 | AQ6: 13 | AR6: 14 | AS6: 15 | AT6: 16 | AU6: 17 | AV6: 18 | AW6: 19 | AX6: 20 | AY6: 21 | BJ6: l/sc for no ETC | BK6: Manual Only | BL6: l/sc under ETC | BM6: 1 | BN6: 2 | BO6: 3 | BP6: 4 | BQ6: 5 | BR6: 6 | BS6: 7 | BT6: 8 | BU6: 9 | BV6: 10 | BW6: 11 | BX6: 12 | BY6: 13 | BZ6: 14 | CA6: 15 | CB6: 16 | CC6: 17 | CD6: 18 | CE6: 19 | CF6: 20 | CG6: 21 | CN6: l/sc under ETC | CO6: 1 | CP6: 2 | CQ6: 3 | CR6: 4 | CS6: 5 | CT6: 6 | CU6: 7 | CV6: 8 | CW6: 9 | CX6: 10 | CY6: 11 | CZ6: 12 | DA6: 13 | DB6: 14 | DC6: 15 | DD6: 16 | DE6: 17 | DF6: 18 | DG6: 19 | DH6: 20 | DI6: 21
C7: Cash | D7: ='Input-Detail'!AZ10 -> 7 | H7: Base | I7: ='Input-Detail'!E14 -> 19016173 | J7: ='Input-Detail'!F14 -> 0 | K7: =AC7 -> 5740 | V7: Base | W7: ='Input-Detail'!E14 -> 19016173 | X7: =J7 -> 0 | Y7: ='Input-Detail'!V18 -> 8200 | Z7: ='Input-Detail'!W18 -> 2319.0455 | AA7: ='Input-Detail'!X18 -> 2 | AB7: ='Input-Detail'!Y18 -> 0.7 | AC7: =Y7*AB7 -> 5740 | AD7: =Peak_Time_Eve*$BH7*(3600/K40+BK7)/3600 -> 32.946409 | BF7: Base | BG7: =$X7 -> 0 | BH7: =$AC7 -> 5740 | BI7: =BH7*(1-BG7) -> 5740 | BJ7: =Peak_Arrival_Manual/K40 -> 10.483472 | BK7: =900*Peak_Time_Eve*(BJ7/Total_Lanes-1+SQRT((BJ7/Total_Lanes-1)^2+8*(BJ7/Total_Lanes)/(Peak_Time_Eve*$K40*Total_Lanes))) -> 3.7566264 | BL7: =Peak_Arrival_Manual/N40 -> 10.483472 | BM7: =IF(BM$6<Total_Lanes,900*Peak_Time_Eve*(($BL7/(Total_Lanes-BM$6))-1+SQRT((($BL7/(Total_Lanes-BM$6))-1)^2+8*($BL7/(Total_Lanes-BM$6))/(Peak_Time_Eve*$N40*(Total_Lanes-BM$6)))),"-") -> 11.367139 | BN7: =IF(BN$6<Total_Lanes,900*Peak_Time_Eve*(($BL7/(Total_Lanes-BN$6))-1+SQRT((($BL7/(Total_Lanes-BN$6))-1)^2+8*($BL7/(Total_Lanes-BN$6))/(Peak_Time_Eve*$N40*(Total_Lanes-BN$6)))),"-") -> 187.29857 | BO7: =IF(BO$6<Total_Lanes,900*Peak_Time_Eve*(($BL7/(Total_Lanes-BO$6))-1+SQRT((($BL7/(Total_Lanes-BO$6))-1)^2+8*($BL7/(Total_Lanes-BO$6))/(Peak_Time_Eve*$N40*(Total_Lanes-BO$6)))),"-") -> 598.50746 | BP7: =IF(BP$6<Total_Lanes,900*Peak_Time_Eve*(($BL7/(Total_Lanes-BP$6))-1+SQRT((($BL7/(Total_Lanes-BP$6))-1)^2+8*($BL7/(Total_Lanes-BP$6))/(Peak_Time_Eve*$N40*(Total_Lanes-BP$6)))),"-") -> 1121.0212 | BQ7: =IF(BQ$6<Total_Lanes,900*Peak_Time_Eve*(($BL7/(Total_Lanes-BQ$6))-1+SQRT((($BL7/(Total_Lanes-BQ$6))-1)^2+8*($BL7/(Total_Lanes-BQ$6))/(Peak_Time_Eve*$N40*(Total_Lanes-BQ$6)))),"-") -> 1794.3223 | BR7: =IF(BR$6<Total_Lanes,900*Peak_Time_Eve*(($BL7/(Total_Lanes-BR$6))-1+SQRT((($BL7/(Total_Lanes-BR$6))-1)^2+8*($BL7/(Total_Lanes-BR$6))/(Peak_Time_Eve*$N40*(Total_Lanes-BR$6)))),"-") -> 2692.6432 | BS7: =IF(BS$6<Total_Lanes,900*Peak_Time_Eve*(($BL7/(Total_Lanes-BS$6))-1+SQRT((($BL7/(Total_Lanes-BS$6))-1)^2+8*($BL7/(Total_Lanes-BS$6))/(Peak_Time_Eve*$N40*(Total_Lanes-BS$6)))),"-") -> 3950.6125 | BT7: =IF(BT$6<Total_Lanes,900*Peak_Time_Eve*(($BL7/(Total_Lanes-BT$6))-1+SQRT((($BL7/(Total_Lanes-BT$6))-1)^2+8*($BL7/(Total_Lanes-BT$6))/(Peak_Time_Eve*$N40*(Total_Lanes-BT$6)))),"-") -> 5837.7817 | ... CG7: =IF(CG$6<Total_Lanes,900*Peak_Time_Eve*(($BL7/(Total_Lanes-CG$6))-1+SQRT((($BL7/(Total_Lanes-CG$6))-1)^2+8*($BL7/(Total_Lanes-CG$6))/(Peak_Time_Eve*$N40*(Total_Lanes-CG$6)))),"-") -> - | CH7: =3600/N40 -> 6.575 | CJ7: Base | CK7: =$X7 -> 0 | CL7: =$AC7 -> 5740 | CM7: =CL7*CK7 -> 0
C8: Ticket | D8: ='Input-Detail'!AZ11 -> 4.5 | H8: 1 | I8: ='Input-Detail'!E15 -> 19565364 | J8: 0.06998422 | K8: =AC8 -> 5905.7725 | L8: =AD55 -> 9.7052873 | M8: =AD8 -> 30.689988 | N8: =SUM(L8:M8) -> 40.395275 | O8: =$S$34*N8 -> 10502.772 | P8: =BC55 -> 9.1634394 | Q8: =BC8 -> 39.609108 | R8: =SUM(P8:Q8) -> 48.772548 | S8: =$S$34*R8 -> 12680.862 | V8: 1 | W8: =W$7+(W$27-W$7)*$V8/20 -> 19565364 | X8: =J8 -> 0.06998422 | Y8: ='Input-Detail'!E15/Z8 -> 8436.8178 | Z8: =Z7 -> 2319.0455 | AA8: =AA7 -> 2 | AB8: =AB7 -> 0.7 | AC8: =Y8*AB8 -> 5905.7725 | AD8: =Peak_Time_Eve*$BH8*(3600/K41+BK8)/3600 -> 30.689988 | AE8: =IF(AE$6<Total_Lanes,($BI8*($CH8+BM8)+$CM8*CO8)*Peak_Time_Eve/3600,"-") -> 39.609108 | AF8: =IF(AF$6<Total_Lanes,($BI8*($CH8+BN8)+$CM8*CP8)*Peak_Time_Eve/3600,"-") -> 208.43637 | AG8: =IF(AG$6<Total_Lanes,($BI8*($CH8+BO8)+$CM8*CQ8)*Peak_Time_Eve/3600,"-") -> 1339.3769 | AH8: =IF(AH$6<Total_Lanes,($BI8*($CH8+BP8)+$CM8*CR8)*Peak_Time_Eve/3600,"-") -> 2866.1779 | AI8: =IF(AI$6<Total_Lanes,($BI8*($CH8+BQ8)+$CM8*CS8)*Peak_Time_Eve/3600,"-") -> 4837.4912 | AJ8: =IF(AJ$6<Total_Lanes,($BI8*($CH8+BR8)+$CM8*CT8)*Peak_Time_Eve/3600,"-") -> 7468.5034 | AK8: =IF(AK$6<Total_Lanes,($BI8*($CH8+BS8)+$CM8*CU8)*Peak_Time_Eve/3600,"-") -> 11153.198 | AL8: =IF(AL$6<Total_Lanes,($BI8*($CH8+BT8)+$CM8*CV8)*Peak_Time_Eve/3600,"-") -> 16681.048 | ... AY8: =IF(AY$6<Total_Lanes,($BI8*($CH8+CG8)+$CM8*DI8)*Peak_Time_Eve/3600,"-") -> - | AZ8: =SUMIF(AE8:AY8,BA8,$AE$6:$AY$6) -> 1 | BA8: =MIN(AE8:AY8) -> 39.609108 | BB8: =IF((SUMIF($BM6:$CG6,$AZ8,$BM8:$CG8)+$CH8)<(SUMIF($CO6:$DI6,$AZ8,$CO8:$DI8)+$DJ8),AZ8+1,AZ8) -> 1 | BC8: =SUMIF($AE$6:$AY$6,$BB8,$AE8:$AY8) -> 39.609108 | BF8: 1 | BG8: =$X8 -> 0.06998422 | BH8: =$AC8 -> 5905.7725 | BI8: =BH8*(1-BG8) -> 5492.4616 | BJ8: =Peak_Arrival_Manual/K41 -> 10.031371 | BK8: =900*Peak_Time_Eve*(BJ8/Total_Lanes-1+SQRT((BJ8/Total_Lanes-1)^2+8*(BJ8/Total_Lanes)/(Peak_Time_Eve*$K41*Total_Lanes))) -> 2.7788954 | BL8: =Peak_Arrival_Manual/N41 -> 10.063792 | BM8: =IF(BM$6<Total_Lanes,900*Peak_Time_Eve*(($BL8/(Total_Lanes-BM$6))-1+SQRT((($BL8/(Total_Lanes-BM$6))-1)^2+8*($BL8/(Total_Lanes-BM$6))/(Peak_Time_Eve*$N41*(Total_Lanes-BM$6)))),"-") -> 6.3158567 | BN8: =IF(BN$6<Total_Lanes,900*Peak_Time_Eve*(($BL8/(Total_Lanes-BN$6))-1+SQRT((($BL8/(Total_Lanes-BN$6))-1)^2+8*($BL8/(Total_Lanes-BN$6))/(Peak_Time_Eve*$N41*(Total_Lanes-BN$6)))),"-") -> 61.698487 | BO8: =IF(BO$6<Total_Lanes,900*Peak_Time_Eve*(($BL8/(Total_Lanes-BO$6))-1+SQRT((($BL8/(Total_Lanes-BO$6))-1)^2+8*($BL8/(Total_Lanes-BO$6))/(Peak_Time_Eve*$N41*(Total_Lanes-BO$6)))),"-") -> 432.34083 | BP8: =IF(BP$6<Total_Lanes,900*Peak_Time_Eve*(($BL8/(Total_Lanes-BP$6))-1+SQRT((($BL8/(Total_Lanes-BP$6))-1)^2+8*($BL8/(Total_Lanes-BP$6))/(Peak_Time_Eve*$N41*(Total_Lanes-BP$6)))),"-") -> 932.70969 | BQ8: =IF(BQ$6<Total_Lanes,900*Peak_Time_Eve*(($BL8/(Total_Lanes-BQ$6))-1+SQRT((($BL8/(Total_Lanes-BQ$6))-1)^2+8*($BL8/(Total_Lanes-BQ$6))/(Peak_Time_Eve*$N41*(Total_Lanes-BQ$6)))),"-") -> 1578.7535 | BR8: =IF(BR$6<Total_Lanes,900*Peak_Time_Eve*(($BL8/(Total_Lanes-BR$6))-1+SQRT((($BL8/(Total_Lanes-BR$6))-1)^2+8*($BL8/(Total_Lanes-BR$6))/(Peak_Time_Eve*$N41*(Total_Lanes-BR$6)))),"-") -> 2440.9945 | BS8: =IF(BS$6<Total_Lanes,900*Peak_Time_Eve*(($BL8/(Total_Lanes-BS$6))-1+SQRT((($BL8/(Total_Lanes-BS$6))-1)^2+8*($BL8/(Total_Lanes-BS$6))/(Peak_Time_Eve*$N41*(Total_Lanes-BS$6)))),"-") -> 3648.55 | BT8: =IF(BT$6<Total_Lanes,900*Peak_Time_Eve*(($BL8/(Total_Lanes-BT$6))-1+SQRT((($BL8/(Total_Lanes-BT$6))-1)^2+8*($BL8/(Total_Lanes-BT$6))/(Peak_Time_Eve*$N41*(Total_Lanes-BT$6)))),"-") -> 5460.148 | ... CG8: =IF(CG$6<Total_Lanes,900*Peak_Time_Eve*(($BL8/(Total_Lanes-CG$6))-1+SQRT((($BL8/(Total_Lanes-CG$6))-1)^2+8*($BL8/(Total_Lanes-CG$6))/(Peak_Time_Eve*$N41*(Total_Lanes-CG$6)))),"-") -> - | CH8: =3600/N41 -> 6.59625 | CJ8: 1 | CK8: =$X8 -> 0.06998422 | CL8: =$AC8 -> 5905.7725 | CM8: =CL8*CK8 -> 413.31088 | CN8: =CM8/O40 -> 0.27554059 | CO8: =IF(CO$6<Total_Lanes,900*Peak_Time_Eve*(($CN8/CO$6-1)+SQRT(($CN8/CO$6-1)^2+8*($CN8/CO$6)/(Peak_Time_Eve*$O41*CO$6))),"-") -> 0.91249573 | CP8: =IF(CP$6<Total_Lanes,900*Peak_Time_Eve*(($CN8/CP$6-1)+SQRT(($CN8/CP$6-1)^2+8*($CN8/CP$6)/(Peak_Time_Eve*$O41*CP$6))),"-") -> 0.19172866 | CQ8: =IF(CQ$6<Total_Lanes,900*Peak_Time_Eve*(($CN8/CQ$6-1)+SQRT(($CN8/CQ$6-1)^2+8*($CN8/CQ$6)/(Peak_Time_Eve*$O41*CQ$6))),"-") -> 0.080906698 | CR8: =IF(CR$6<Total_Lanes,900*Peak_Time_Eve*(($CN8/CR$6-1)+SQRT(($CN8/CR$6-1)^2+8*($CN8/CR$6)/(Peak_Time_Eve*$O41*CR$6))),"-") -> 0.044388231 | CS8: =IF(CS$6<Total_Lanes,900*Peak_Time_Eve*(($CN8/CS$6-1)+SQRT(($CN8/CS$6-1)^2+8*($CN8/CS$6)/(Peak_Time_Eve*$O41*CS$6))),"-") -> 0.027994397 | CT8: =IF(CT$6<Total_Lanes,900*Peak_Time_Eve*(($CN8/CT$6-1)+SQRT(($CN8/CT$6-1)^2+8*($CN8/CT$6)/(Peak_Time_Eve*$O41*CT$6))),"-") -> 0.019253454 | CU8: =IF(CU$6<Total_Lanes,900*Peak_Time_Eve*(($CN8/CU$6-1)+SQRT(($CN8/CU$6-1)^2+8*($CN8/CU$6)/(Peak_Time_Eve*$O41*CU$6))),"-") -> 0.014048813 | CV8: =IF(CV$6<Total_Lanes,900*Peak_Time_Eve*(($CN8/CV$6-1)+SQRT(($CN8/CV$6-1)^2+8*($CN8/CV$6)/(Peak_Time_Eve*$O41*CV$6))),"-") -> 0.010701321 | ... DI8: =IF(DI$6<Total_Lanes,900*Peak_Time_Eve*(($CN8/DI$6-1)+SQRT(($CN8/DI$6-1)^2+8*($CN8/DI$6)/(Peak_Time_Eve*$O41*DI$6))),"-") -> - | DJ8: =3600/O41 -> 2.4
C9: ETC | D9: ='Input-Detail'!AZ12 -> 2.4 | H9: 2 | I9: ='Input-Detail'!E16 -> 20114556 | J9: 0.13348622 | K9: =AC9 -> 6071.545 | L9: =AD56 -> 9.9541178 | M9: =AD9 -> 28.248991 | N9: =SUM(L9:M9) -> 38.203109 | O9: =$S$34*N9 -> 9932.8083 | P9: =BC56 -> 8.5138447 | Q9: =BC9 -> 30.482994 | R9: =SUM(P9:Q9) -> 38.996839 | S9: =$S$34*R9 -> 10139.178 | V9: 2 | W9: =W$7+(W$27-W$7)*$V9/20 -> 20114556 | X9: =MIN((J8+0.1),0.95) -> 0.16998422 | Y9: ='Input-Detail'!E16/Z9 -> 8673.6357 | Z9: =Z8 -> 2319.0455 | AA9: =AA8 -> 2 | AB9: =AB8 -> 0.7 | AC9: =Y9*AB9 -> 6071.545 | AD9: =Peak_Time_Eve*$BH9*(3600/K42+BK9)/3600 -> 28.248991 | AE9: =IF(AE$6<Total_Lanes,($BI9*($CH9+BM9)+$CM9*CO9)*Peak_Time_Eve/3600,"-") -> 30.482994 | AF9: =IF(AF$6<Total_Lanes,($BI9*($CH9+BN9)+$CM9*CP9)*Peak_Time_Eve/3600,"-") -> 41.503054 | AG9: =IF(AG$6<Total_Lanes,($BI9*($CH9+BO9)+$CM9*CQ9)*Peak_Time_Eve/3600,"-") -> 373.91334 | AH9: =IF(AH$6<Total_Lanes,($BI9*($CH9+BP9)+$CM9*CR9)*Peak_Time_Eve/3600,"-") -> 1627.2964 | AI9: =IF(AI$6<Total_Lanes,($BI9*($CH9+BQ9)+$CM9*CS9)*Peak_Time_Eve/3600,"-") -> 3288.5281 | AJ9: =IF(AJ$6<Total_Lanes,($BI9*($CH9+BR9)+$CM9*CT9)*Peak_Time_Eve/3600,"-") -> 5509.4884 | AK9: =IF(AK$6<Total_Lanes,($BI9*($CH9+BS9)+$CM9*CU9)*Peak_Time_Eve/3600,"-") -> 8621 | AL9: =IF(AL$6<Total_Lanes,($BI9*($CH9+BT9)+$CM9*CV9)*Peak_Time_Eve/3600,"-") -> 13289.439 | ... AY9: =IF(AY$6<Total_Lanes,($BI9*($CH9+CG9)+$CM9*DI9)*Peak_Time_Eve/3600,"-") -> - | AZ9: =SUMIF(AE9:AY9,BA9,$AE$6:$AY$6) -> 1 | BA9: =MIN(AE9:AY9) -> 30.482994 | BB9: =IF((SUMIF($BM7:$CG7,$AZ9,$BM9:$CG9)+$CH9)<(SUMIF($CO7:$DI7,$AZ9,$CO9:$DI9)+$DJ9),AZ9+1,AZ9) -> 1 | BC9: =SUMIF($AE$6:$AY$6,$BB9,$AE9:$AY9) -> 30.482994 | BF9: 2 | BG9: =$X9 -> 0.16998422 | BH9: =$AC9 -> 6071.545 | BI9: =BH9*(1-BG9) -> 5039.4781 | BJ9: =Peak_Arrival_Manual/K42 -> 9.2040469 | BK9: =900*Peak_Time_Eve*(BJ9/Total_Lanes-1+SQRT((BJ9/Total_Lanes-1)^2+8*(BJ9/Total_Lanes)/(Peak_Time_Eve*$K42*Total_Lanes))) -> 1.7998344 | BL9: =Peak_Arrival_Manual/N42 -> 9.2635407 | BM9: =IF(BM$6<Total_Lanes,900*Peak_Time_Eve*(($BL9/(Total_Lanes-BM$6))-1+SQRT((($BL9/(Total_Lanes-BM$6))-1)^2+8*($BL9/(Total_Lanes-BM$6))/(Peak_Time_Eve*$N42*(Total_Lanes-BM$6)))),"-") -> 3.1914027 | BN9: =IF(BN$6<Total_Lanes,900*Peak_Time_Eve*(($BL9/(Total_Lanes-BN$6))-1+SQRT((($BL9/(Total_Lanes-BN$6))-1)^2+8*($BL9/(Total_Lanes-BN$6))/(Peak_Time_Eve*$N42*(Total_Lanes-BN$6)))),"-") -> 8.0777039 | BO9: =IF(BO$6<Total_Lanes,900*Peak_Time_Eve*(($BL9/(Total_Lanes-BO$6))-1+SQRT((($BL9/(Total_Lanes-BO$6))-1)^2+8*($BL9/(Total_Lanes-BO$6))/(Peak_Time_Eve*$N42*(Total_Lanes-BO$6)))),"-") -> 126.88805 | BP9: =IF(BP$6<Total_Lanes,900*Peak_Time_Eve*(($BL9/(Total_Lanes-BP$6))-1+SQRT((($BL9/(Total_Lanes-BP$6))-1)^2+8*($BL9/(Total_Lanes-BP$6))/(Peak_Time_Eve*$N42*(Total_Lanes-BP$6)))),"-") -> 574.59444 | BQ9: =IF(BQ$6<Total_Lanes,900*Peak_Time_Eve*(($BL9/(Total_Lanes-BQ$6))-1+SQRT((($BL9/(Total_Lanes-BQ$6))-1)^2+8*($BL9/(Total_Lanes-BQ$6))/(Peak_Time_Eve*$N42*(Total_Lanes-BQ$6)))),"-") -> 1167.9628 | BR9: =IF(BR$6<Total_Lanes,900*Peak_Time_Eve*(($BL9/(Total_Lanes-BR$6))-1+SQRT((($BL9/(Total_Lanes-BR$6))-1)^2+8*($BL9/(Total_Lanes-BR$6))/(Peak_Time_Eve*$N42*(Total_Lanes-BR$6)))),"-") -> 1961.2501 | BS9: =IF(BS$6<Total_Lanes,900*Peak_Time_Eve*(($BL9/(Total_Lanes-BS$6))-1+SQRT((($BL9/(Total_Lanes-BS$6))-1)^2+8*($BL9/(Total_Lanes-BS$6))/(Peak_Time_Eve*$N42*(Total_Lanes-BS$6)))),"-") -> 3072.6222 | BT9: =IF(BT$6<Total_Lanes,900*Peak_Time_Eve*(($BL9/(Total_Lanes-BT$6))-1+SQRT((($BL9/(Total_Lanes-BT$6))-1)^2+8*($BL9/(Total_Lanes-BT$6))/(Peak_Time_Eve*$N42*(Total_Lanes-BT$6)))),"-") -> 4740.0965 | ... CG9: =IF(CG$6<Total_Lanes,900*Peak_Time_Eve*(($BL9/(Total_Lanes-CG$6))-1+SQRT((($BL9/(Total_Lanes-CG$6))-1)^2+8*($BL9/(Total_Lanes-CG$6))/(Peak_Time_Eve*$N42*(Total_Lanes-CG$6)))),"-") -> - | CH9: =3600/N42 -> 6.6175 | CJ9: 2 | CK9: =$X9 -> 0.16998422 | CL9: =$AC9 -> 6071.545 | CM9: =CL9*CK9 -> 1032.0668 | CN9: =CM9/O41 -> 0.68804456 | CO9: =IF(CO$6<Total_Lanes,900*Peak_Time_Eve*(($CN9/CO$6-1)+SQRT(($CN9/CO$6-1)^2+8*($CN9/CO$6)/(Peak_Time_Eve*$O42*CO$6))),"-") -> 5.2686886 | CP9: =IF(CP$6<Total_Lanes,900*Peak_Time_Eve*(($CN9/CP$6-1)+SQRT(($CN9/CP$6-1)^2+8*($CN9/CP$6)/(Peak_Time_Eve*$O42*CP$6))),"-") -> 0.6291628 | CQ9: =IF(CQ$6<Total_Lanes,900*Peak_Time_Eve*(($CN9/CQ$6-1)+SQRT(($CN9/CQ$6-1)^2+8*($CN9/CQ$6)/(Peak_Time_Eve*$O42*CQ$6))),"-") -> 0.23806186 | CR9: =IF(CR$6<Total_Lanes,900*Peak_Time_Eve*(($CN9/CR$6-1)+SQRT(($CN9/CR$6-1)^2+8*($CN9/CR$6)/(Peak_Time_Eve*$O42*CR$6))),"-") -> 0.12464222 | CS9: =IF(CS$6<Total_Lanes,900*Peak_Time_Eve*(($CN9/CS$6-1)+SQRT(($CN9/CS$6-1)^2+8*($CN9/CS$6)/(Peak_Time_Eve*$O42*CS$6))),"-") -> 0.076590133 | CT9: =IF(CT$6<Total_Lanes,900*Peak_Time_Eve*(($CN9/CT$6-1)+SQRT(($CN9/CT$6-1)^2+8*($CN9/CT$6)/(Peak_Time_Eve*$O42*CT$6))),"-") -> 0.051810177 | CU9: =IF(CU$6<Total_Lanes,900*Peak_Time_Eve*(($CN9/CU$6-1)+SQRT(($CN9/CU$6-1)^2+8*($CN9/CU$6)/(Peak_Time_Eve*$O42*CU$6))),"-") -> 0.037373248 | CV9: =IF(CV$6<Total_Lanes,900*Peak_Time_Eve*(($CN9/CV$6-1)+SQRT(($CN9/CV$6-1)^2+8*($CN9/CV$6)/(Peak_Time_Eve*$O42*CV$6))),"-") -> 0.028229329 | ... DI9: =IF(DI$6<Total_Lanes,900*Peak_Time_Eve*(($CN9/DI$6-1)+SQRT(($CN9/DI$6-1)^2+8*($CN9/DI$6)/(Peak_Time_Eve*$O42*DI$6))),"-") -> - | DJ9: =3600/O42 -> 2.4
B10: Total Number of Lanes | D10: ='Input-Detail'!AZ25 -> 12 | H10: 3 | I10: ='Input-Detail'!E17 -> 20663747 | J10: 0.19229151 | K10: =AC10 -> 6237.3175 | L10: =AD57 -> 10.227762 | M10: =AD10 -> 27.848946 | N10: =SUM(L10:M10) -> 38.076708 | O10: =$S$34*N10 -> 9899.9442 | P10: =BC57 -> 8.1252815 | Q10: =BC10 -> 31.536807 | R10: =SUM(P10:Q10) -> 39.662089 | S10: =$S$34*R10 -> 10312.143 | V10: 3 | W10: =W$7+(W$27-W$7)*$V10/20 -> 20663747 | X10: =MIN((J9+0.1),0.95) -> 0.23348622 | Y10: ='Input-Detail'!E17/Z10 -> 8910.4535 | Z10: =Z9 -> 2319.0455 | AA10: =AA9 -> 2 | AB10: =AB9 -> 0.7 | AC10: =Y10*AB10 -> 6237.3175 | AD10: =Peak_Time_Eve*$BH10*(3600/K43+BK10)/3600 -> 27.848946 | AE10: =IF(AE$6<Total_Lanes,($BI10*($CH10+BM10)+$CM10*CO10)*Peak_Time_Eve/3600,"-") -> 67.058426 | AF10: =IF(AF$6<Total_Lanes,($BI10*($CH10+BN10)+$CM10*CP10)*Peak_Time_Eve/3600,"-") -> 31.536807 | AG10: =IF(AG$6<Total_Lanes,($BI10*($CH10+BO10)+$CM10*CQ10)*Peak_Time_Eve/3600,"-") -> 87.385392 | AH10: =IF(AH$6<Total_Lanes,($BI10*($CH10+BP10)+$CM10*CR10)*Peak_Time_Eve/3600,"-") -> 1017.0836 | AI10: =IF(AI$6<Total_Lanes,($BI10*($CH10+BQ10)+$CM10*CS10)*Peak_Time_Eve/3600,"-") -> 2511.3768 | AJ10: =IF(AJ$6<Total_Lanes,($BI10*($CH10+BR10)+$CM10*CT10)*Peak_Time_Eve/3600,"-") -> 4515.6041 | AK10: =IF(AK$6<Total_Lanes,($BI10*($CH10+BS10)+$CM10*CU10)*Peak_Time_Eve/3600,"-") -> 7324.6849 | AL10: =IF(AL$6<Total_Lanes,($BI10*($CH10+BT10)+$CM10*CV10)*Peak_Time_Eve/3600,"-") -> 11539.812 | ... AY10: =IF(AY$6<Total_Lanes,($BI10*($CH10+CG10)+$CM10*DI10)*Peak_Time_Eve/3600,"-") -> - | AZ10: =SUMIF(AE10:AY10,BA10,$AE$6:$AY$6) -> 2 | BA10: =MIN(AE10:AY10) -> 31.536807 | BB10: =IF((SUMIF($BM8:$CG8,$AZ10,$BM10:$CG10)+$CH10)<(SUMIF($CO8:$DI8,$AZ10,$CO10:$DI10)+$DJ10),AZ10+1,AZ10) -> 2 | BC10: =SUMIF($AE$6:$AY$6,$BB10,$AE10:$AY10) -> 31.536807 | BF10: 3 | BG10: =$X10 -> 0.23348622 | BH10: =$AC10 -> 6237.3175 | BI10: =BH10*(1-BG10) -> 4780.9898 | BJ10: =Peak_Arrival_Manual/K43 -> 8.7319466 | BK10: =900*Peak_Time_Eve*(BJ10/Total_Lanes-1+SQRT((BJ10/Total_Lanes-1)^2+8*(BJ10/Total_Lanes)/(Peak_Time_Eve*$K43*Total_Lanes))) -> 1.4618048 | BL10: =Peak_Arrival_Manual/N43 -> 8.81661 | BM10: =IF(BM$6<Total_Lanes,900*Peak_Time_Eve*(($BL10/(Total_Lanes-BM$6))-1+SQRT((($BL10/(Total_Lanes-BM$6))-1)^2+8*($BL10/(Total_Lanes-BM$6))/(Peak_Time_Eve*$N43*(Total_Lanes-BM$6)))),"-") -> 2.4287918 | BN10: =IF(BN$6<Total_Lanes,900*Peak_Time_Eve*(($BL10/(Total_Lanes-BN$6))-1+SQRT((($BL10/(Total_Lanes-BN$6))-1)^2+8*($BL10/(Total_Lanes-BN$6))/(Peak_Time_Eve*$N43*(Total_Lanes-BN$6)))),"-") -> 4.8899399 | BO10: =IF(BO$6<Total_Lanes,900*Peak_Time_Eve*(($BL10/(Total_Lanes-BO$6))-1+SQRT((($BL10/(Total_Lanes-BO$6))-1)^2+8*($BL10/(Total_Lanes-BO$6))/(Peak_Time_Eve*$N43*(Total_Lanes-BO$6)))),"-") -> 26.14449 | BP10: =IF(BP$6<Total_Lanes,900*Peak_Time_Eve*(($BL10/(Total_Lanes-BP$6))-1+SQRT((($BL10/(Total_Lanes-BP$6))-1)^2+8*($BL10/(Total_Lanes-BP$6))/(Peak_Time_Eve*$N43*(Total_Lanes-BP$6)))),"-") -> 376.22558 | BQ10: =IF(BQ$6<Total_Lanes,900*Peak_Time_Eve*(($BL10/(Total_Lanes-BQ$6))-1+SQRT((($BL10/(Total_Lanes-BQ$6))-1)^2+8*($BL10/(Total_Lanes-BQ$6))/(Peak_Time_Eve*$N43*(Total_Lanes-BQ$6)))),"-") -> 938.83697 | BR10: =IF(BR$6<Total_Lanes,900*Peak_Time_Eve*(($BL10/(Total_Lanes-BR$6))-1+SQRT((($BL10/(Total_Lanes-BR$6))-1)^2+8*($BL10/(Total_Lanes-BR$6))/(Peak_Time_Eve*$N43*(Total_Lanes-BR$6)))),"-") -> 1693.4224 | BS10: =IF(BS$6<Total_Lanes,900*Peak_Time_Eve*(($BL10/(Total_Lanes-BS$6))-1+SQRT((($BL10/(Total_Lanes-BS$6))-1)^2+8*($BL10/(Total_Lanes-BS$6))/(Peak_Time_Eve*$N43*(Total_Lanes-BS$6)))),"-") -> 2751.023 | BT10: =IF(BT$6<Total_Lanes,900*Peak_Time_Eve*(($BL10/(Total_Lanes-BT$6))-1+SQRT((($BL10/(Total_Lanes-BT$6))-1)^2+8*($BL10/(Total_Lanes-BT$6))/(Peak_Time_Eve*$N43*(Total_Lanes-BT$6)))),"-") -> 4337.9849 | ... CG10: =IF(CG$6<Total_Lanes,900*Peak_Time_Eve*(($BL10/(Total_Lanes-CG$6))-1+SQRT((($BL10/(Total_Lanes-CG$6))-1)^2+8*($BL10/(Total_Lanes-CG$6))/(Peak_Time_Eve*$N43*(Total_Lanes-CG$6)))),"-") -> - | CH10: =3600/N43 -> 6.63875 | CJ10: 3 | CK10: =$X10 -> 0.23348622 | CL10: =$AC10 -> 6237.3175 | CM10: =CL10*CK10 -> 1456.3277 | CN10: =CM10/O42 -> 0.97088512 | CO10: =IF(CO$6<Total_Lanes,900*Peak_Time_Eve*(($CN10/CO$6-1)+SQRT(($CN10/CO$6-1)^2+8*($CN10/CO$6)/(Peak_Time_Eve*$O43*CO$6))),"-") -> 53.115341 | CP10: =IF(CP$6<Total_Lanes,900*Peak_Time_Eve*(($CN10/CP$6-1)+SQRT(($CN10/CP$6-1)^2+8*($CN10/CP$6)/(Peak_Time_Eve*$O43*CP$6))),"-") -> 1.1314101 | CQ10: =IF(CQ$6<Total_Lanes,900*Peak_Time_Eve*(($CN10/CQ$6-1)+SQRT(($CN10/CQ$6-1)^2+8*($CN10/CQ$6)/(Peak_Time_Eve*$O43*CQ$6))),"-") -> 0.38272157 | CR10: =IF(CR$6<Total_Lanes,900*Peak_Time_Eve*(($CN10/CR$6-1)+SQRT(($CN10/CR$6-1)^2+8*($CN10/CR$6)/(Peak_Time_Eve*$O43*CR$6))),"-") -> 0.19229709 | CS10: =IF(CS$6<Total_Lanes,900*Peak_Time_Eve*(($CN10/CS$6-1)+SQRT(($CN10/CS$6-1)^2+8*($CN10/CS$6)/(Peak_Time_Eve*$O43*CS$6))),"-") -> 0.11565972 | CT10: =IF(CT$6<Total_Lanes,900*Peak_Time_Eve*(($CN10/CT$6-1)+SQRT(($CN10/CT$6-1)^2+8*($CN10/CT$6)/(Peak_Time_Eve*$O43*CT$6))),"-") -> 0.077219177 | CU10: =IF(CU$6<Total_Lanes,900*Peak_Time_Eve*(($CN10/CU$6-1)+SQRT(($CN10/CU$6-1)^2+8*($CN10/CU$6)/(Peak_Time_Eve*$O43*CU$6))),"-") -> 0.055210255 | CV10: =IF(CV$6<Total_Lanes,900*Peak_Time_Eve*(($CN10/CV$6-1)+SQRT(($CN10/CV$6-1)^2+8*($CN10/CV$6)/(Peak_Time_Eve*$O43*CV$6))),"-") -> 0.041436472 | ... DI10: =IF(DI$6<Total_Lanes,900*Peak_Time_Eve*(($CN10/DI$6-1)+SQRT(($CN10/DI$6-1)^2+8*($CN10/DI$6)/(Peak_Time_Eve*$O43*DI$6))),"-") -> - | DJ10: =3600/O43 -> 2.4
H11: 4 | I11: ='Input-Detail'!E18 -> 21212938 | J11: 0.24713691 | K11: =AC11 -> 6403.09 | L11: =AD58 -> 10.503952 | M11: =AD11 -> 27.716433 | N11: =SUM(L11:M11) -> 38.220385 | O11: =$S$34*N11 -> 9937.3002 | P11: =BC58 -> 7.7836883 | Q11: =BC11 -> 27.476336 | R11: =SUM(P11:Q11) -> 35.260024 | S11: =$S$34*R11 -> 9167.6063 | V11: 4 | W11: =W$7+(W$27-W$7)*$V11/20 -> 21212938 | X11: =MIN((J10+0.1),0.95) -> 0.29229151 | Y11: ='Input-Detail'!E18/Z11 -> 9147.2714 | Z11: =Z10 -> 2319.0455 | AA11: =AA10 -> 2 | AB11: =AB10 -> 0.7 | AC11: =Y11*AB11 -> 6403.09 | AD11: =Peak_Time_Eve*$BH11*(3600/K44+BK11)/3600 -> 27.716433 | AE11: =IF(AE$6<Total_Lanes,($BI11*($CH11+BM11)+$CM11*CO11)*Peak_Time_Eve/3600,"-") -> 961.26451 | AF11: =IF(AF$6<Total_Lanes,($BI11*($CH11+BN11)+$CM11*CP11)*Peak_Time_Eve/3600,"-") -> 27.476336 | AG11: =IF(AG$6<Total_Lanes,($BI11*($CH11+BO11)+$CM11*CQ11)*Peak_Time_Eve/3600,"-") -> 41.727803 | AH11: =IF(AH$6<Total_Lanes,($BI11*($CH11+BP11)+$CM11*CR11)*Peak_Time_Eve/3600,"-") -> 493.10969 | AI11: =IF(AI$6<Total_Lanes,($BI11*($CH11+BQ11)+$CM11*CS11)*Peak_Time_Eve/3600,"-") -> 1822.3375 | AJ11: =IF(AJ$6<Total_Lanes,($BI11*($CH11+BR11)+$CM11*CT11)*Peak_Time_Eve/3600,"-") -> 3626.6913 | AK11: =IF(AK$6<Total_Lanes,($BI11*($CH11+BS11)+$CM11*CU11)*Peak_Time_Eve/3600,"-") -> 6157.7655 | AL11: =IF(AL$6<Total_Lanes,($BI11*($CH11+BT11)+$CM11*CV11)*Peak_Time_Eve/3600,"-") -> 9956.3748 | ... AY11: =IF(AY$6<Total_Lanes,($BI11*($CH11+CG11)+$CM11*DI11)*Peak_Time_Eve/3600,"-") -> - | AZ11: =SUMIF(AE11:AY11,BA11,$AE$6:$AY$6) -> 2 | BA11: =MIN(AE11:AY11) -> 27.476336 | BB11: =IF((SUMIF($BM9:$CG9,$AZ11,$BM11:$CG11)+$CH11)<(SUMIF($CO9:$DI9,$AZ11,$CO11:$DI11)+$DJ11),AZ11+1,AZ11) -> 2 | BC11: =SUMIF($AE$6:$AY$6,$BB11,$AE11:$AY11) -> 27.476336 | BF11: 4 | BG11: =$X11 -> 0.29229151 | BH11: =$AC11 -> 6403.09 | BI11: =BH11*(1-BG11) -> 4531.5211 | BJ11: =Peak_Arrival_Manual/K44 -> 8.2763199 | BK11: =900*Peak_Time_Eve*(BJ11/Total_Lanes-1+SQRT((BJ11/Total_Lanes-1)^2+8*(BJ11/Total_Lanes)/(Peak_Time_Eve*$K44*Total_Lanes))) -> 1.2164849 | BL11: =Peak_Arrival_Manual/N44 -> 8.3833141 | BM11: =IF(BM$6<Total_Lanes,900*Peak_Time_Eve*(($BL11/(Total_Lanes-BM$6))-1+SQRT((($BL11/(Total_Lanes-BM$6))-1)^2+8*($BL11/(Total_Lanes-BM$6))/(Peak_Time_Eve*$N44*(Total_Lanes-BM$6)))),"-") -> 1.9353758 | BN11: =IF(BN$6<Total_Lanes,900*Peak_Time_Eve*(($BL11/(Total_Lanes-BN$6))-1+SQRT((($BL11/(Total_Lanes-BN$6))-1)^2+8*($BL11/(Total_Lanes-BN$6))/(Peak_Time_Eve*$N44*(Total_Lanes-BN$6)))),"-") -> 3.4332855 | BO11: =IF(BO$6<Total_Lanes,900*Peak_Time_Eve*(($BL11/(Total_Lanes-BO$6))-1+SQRT((($BL11/(Total_Lanes-BO$6))-1)^2+8*($BL11/(Total_Lanes-BO$6))/(Peak_Time_Eve*$N44*(Total_Lanes-BO$6)))),"-") -> 9.679815 | BP11: =IF(BP$6<Total_Lanes,900*Peak_Time_Eve*(($BL11/(Total_Lanes-BP$6))-1+SQRT((($BL11/(Total_Lanes-BP$6))-1)^2+8*($BL11/(Total_Lanes-BP$6))/(Peak_Time_Eve*$N44*(Total_Lanes-BP$6)))),"-") -> 189.09953 | BQ11: =IF(BQ$6<Total_Lanes,900*Peak_Time_Eve*(($BL11/(Total_Lanes-BQ$6))-1+SQRT((($BL11/(Total_Lanes-BQ$6))-1)^2+8*($BL11/(Total_Lanes-BQ$6))/(Peak_Time_Eve*$N44*(Total_Lanes-BQ$6)))),"-") -> 717.13865 | BR11: =IF(BR$6<Total_Lanes,900*Peak_Time_Eve*(($BL11/(Total_Lanes-BR$6))-1+SQRT((($BL11/(Total_Lanes-BR$6))-1)^2+8*($BL11/(Total_Lanes-BR$6))/(Peak_Time_Eve*$N44*(Total_Lanes-BR$6)))),"-") -> 1433.8823 | BS11: =IF(BS$6<Total_Lanes,900*Peak_Time_Eve*(($BL11/(Total_Lanes-BS$6))-1+SQRT((($BL11/(Total_Lanes-BS$6))-1)^2+8*($BL11/(Total_Lanes-BS$6))/(Peak_Time_Eve*$N44*(Total_Lanes-BS$6)))),"-") -> 2439.2822 | BT11: =IF(BT$6<Total_Lanes,900*Peak_Time_Eve*(($BL11/(Total_Lanes-BT$6))-1+SQRT((($BL11/(Total_Lanes-BT$6))-1)^2+8*($BL11/(Total_Lanes-BT$6))/(Peak_Time_Eve*$N44*(Total_Lanes-BT$6)))),"-") -> 3948.1645 | ... CG11: =IF(CG$6<Total_Lanes,900*Peak_Time_Eve*(($BL11/(Total_Lanes-CG$6))-1+SQRT((($BL11/(Total_Lanes-CG$6))-1)^2+8*($BL11/(Total_Lanes-CG$6))/(Peak_Time_Eve*$N44*(Total_Lanes-CG$6)))),"-") -> - | CH11: =3600/N44 -> 6.66 | CJ11: 4 | CK11: =$X11 -> 0.29229151 | CL11: =$AC11 -> 6403.09 | CM11: =CL11*CK11 -> 1871.5688 | CN11: =CM11/O43 -> 1.2477125 | CO11: =IF(CO$6<Total_Lanes,900*Peak_Time_Eve*(($CN11/CO$6-1)+SQRT(($CN11/CO$6-1)^2+8*($CN11/CO$6)/(Peak_Time_Eve*$O44*CO$6))),"-") -> 903.69425 | CP11: =IF(CP$6<Total_Lanes,900*Peak_Time_Eve*(($CN11/CP$6-1)+SQRT(($CN11/CP$6-1)^2+8*($CN11/CP$6)/(Peak_Time_Eve*$O44*CP$6))),"-") -> 1.9873532 | CQ11: =IF(CQ$6<Total_Lanes,900*Peak_Time_Eve*(($CN11/CQ$6-1)+SQRT(($CN11/CQ$6-1)^2+8*($CN11/CQ$6)/(Peak_Time_Eve*$O44*CQ$6))),"-") -> 0.56948406 | CR11: =IF(CR$6<Total_Lanes,900*Peak_Time_Eve*(($CN11/CR$6-1)+SQRT(($CN11/CR$6-1)^2+8*($CN11/CR$6)/(Peak_Time_Eve*$O44*CR$6))),"-") -> 0.27197208 | CS11: =IF(CS$6<Total_Lanes,900*Peak_Time_Eve*(($CN11/CS$6-1)+SQRT(($CN11/CS$6-1)^2+8*($CN11/CS$6)/(Peak_Time_Eve*$O44*CS$6))),"-") -> 0.15960042 | CT11: =IF(CT$6<Total_Lanes,900*Peak_Time_Eve*(($CN11/CT$6-1)+SQRT(($CN11/CT$6-1)^2+8*($CN11/CT$6)/(Peak_Time_Eve*$O44*CT$6))),"-") -> 0.10501609 | CU11: =IF(CU$6<Total_Lanes,900*Peak_Time_Eve*(($CN11/CU$6-1)+SQRT(($CN11/CU$6-1)^2+8*($CN11/CU$6)/(Peak_Time_Eve*$O44*CU$6))),"-") -> 0.074366312 | CV11: =IF(CV$6<Total_Lanes,900*Peak_Time_Eve*(($CN11/CV$6-1)+SQRT(($CN11/CV$6-1)^2+8*($CN11/CV$6)/(Peak_Time_Eve*$O44*CV$6))),"-") -> 0.055434094 | ... DI11: =IF(DI$6<Total_Lanes,900*Peak_Time_Eve*(($CN11/DI$6-1)+SQRT(($CN11/DI$6-1)^2+8*($CN11/DI$6)/(Peak_Time_Eve*$O44*DI$6))),"-") -> - | DJ11: =3600/O44 -> 2.4
H12: 5 | I12: ='Input-Detail'!E19 -> 21762130 | J12: 0.29898451 | K12: =AC12 -> 6568.8625 | L12: =AD59 -> 10.782368 | M12: =AD12 -> 27.749634 | N12: =SUM(L12:M12) -> 38.532002 | O12: =$S$34*N12 -> 10018.321 | P12: =BC59 -> 7.4051694 | Q12: =BC12 -> 26.900073 | R12: =SUM(P12:Q12) -> 34.305243 | S12: =$S$34*R12 -> 8919.3632 | V12: 5 | W12: =W$7+(W$27-W$7)*$V12/20 -> 21762130 | X12: =MIN((J11+0.1),0.95) -> 0.34713691 | Y12: ='Input-Detail'!E19/Z12 -> 9384.0892 | Z12: =Z11 -> 2319.0455 | AA12: =AA11 -> 2 | AB12: =AB11 -> 0.7 | AC12: =Y12*AB12 -> 6568.8625 | AD12: =Peak_Time_Eve*$BH12*(3600/K45+BK12)/3600 -> 27.749634 | AE12: =IF(AE$6<Total_Lanes,($BI12*($CH12+BM12)+$CM12*CO12)*Peak_Time_Eve/3600,"-") -> 2400.9541 | AF12: =IF(AF$6<Total_Lanes,($BI12*($CH12+BN12)+$CM12*CP12)*Peak_Time_Eve/3600,"-") -> 26.900073 | AG12: =IF(AG$6<Total_Lanes,($BI12*($CH12+BO12)+$CM12*CQ12)*Peak_Time_Eve/3600,"-") -> 30.304528 | AH12: =IF(AH$6<Total_Lanes,($BI12*($CH12+BP12)+$CM12*CR12)*Peak_Time_Eve/3600,"-") -> 126.62547 | AI12: =IF(AI$6<Total_Lanes,($BI12*($CH12+BQ12)+$CM12*CS12)*Peak_Time_Eve/3600,"-") -> 1210.0302 | AJ12: =IF(AJ$6<Total_Lanes,($BI12*($CH12+BR12)+$CM12*CT12)*Peak_Time_Eve/3600,"-") -> 2827.4979 | AK12: =IF(AK$6<Total_Lanes,($BI12*($CH12+BS12)+$CM12*CU12)*Peak_Time_Eve/3600,"-") -> 5100.8194 | AL12: =IF(AL$6<Total_Lanes,($BI12*($CH12+BT12)+$CM12*CV12)*Peak_Time_Eve/3600,"-") -> 8513.5741 | ... AY12: =IF(AY$6<Total_Lanes,($BI12*($CH12+CG12)+$CM12*DI12)*Peak_Time_Eve/3600,"-") -> - | AZ12: =SUMIF(AE12:AY12,BA12,$AE$6:$AY$6) -> 2 | BA12: =MIN(AE12:AY12) -> 26.900073 | BB12: =IF((SUMIF($BM10:$CG10,$AZ12,$BM12:$CG12)+$CH12)<(SUMIF($CO10:$DI10,$AZ12,$CO12:$DI12)+$DJ12),AZ12+1,AZ12) -> 2 | BC12: =SUMIF($AE$6:$AY$6,$BB12,$AE12:$AY12) -> 26.900073 | BF12: 5 | BG12: =$X12 -> 0.34713691 | BH12: =$AC12 -> 6568.8625 | BI12: =BH12*(1-BG12) -> 4288.5679 | BJ12: =Peak_Arrival_Manual/K45 -> 7.8325927 | BK12: =900*Peak_Time_Eve*(BJ12/Total_Lanes-1+SQRT((BJ12/Total_Lanes-1)^2+8*(BJ12/Total_Lanes)/(Peak_Time_Eve*$K45*Total_Lanes))) -> 1.028956 | BL12: =Peak_Arrival_Manual/N45 -> 7.959165 | BM12: =IF(BM$6<Total_Lanes,900*Peak_Time_Eve*(($BL12/(Total_Lanes-BM$6))-1+SQRT((($BL12/(Total_Lanes-BM$6))-1)^2+8*($BL12/(Total_Lanes-BM$6))/(Peak_Time_Eve*$N45*(Total_Lanes-BM$6)))),"-") -> 1.5872582 | BN12: =IF(BN$6<Total_Lanes,900*Peak_Time_Eve*(($BL12/(Total_Lanes-BN$6))-1+SQRT((($BL12/(Total_Lanes-BN$6))-1)^2+8*($BL12/(Total_Lanes-BN$6))/(Peak_Time_Eve*$N45*(Total_Lanes-BN$6)))),"-") -> 2.5964814 | BO12: =IF(BO$6<Total_Lanes,900*Peak_Time_Eve*(($BL12/(Total_Lanes-BO$6))-1+SQRT((($BL12/(Total_Lanes-BO$6))-1)^2+8*($BL12/(Total_Lanes-BO$6))/(Peak_Time_Eve*$N45*(Total_Lanes-BO$6)))),"-") -> 5.6014021 | BP12: =IF(BP$6<Total_Lanes,900*Peak_Time_Eve*(($BL12/(Total_Lanes-BP$6))-1+SQRT((($BL12/(Total_Lanes-BP$6))-1)^2+8*($BL12/(Total_Lanes-BP$6))/(Peak_Time_Eve*$N45*(Total_Lanes-BP$6)))),"-") -> 46.270516 | BQ12: =IF(BQ$6<Total_Lanes,900*Peak_Time_Eve*(($BL12/(Total_Lanes-BQ$6))-1+SQRT((($BL12/(Total_Lanes-BQ$6))-1)^2+8*($BL12/(Total_Lanes-BQ$6))/(Peak_Time_Eve*$N45*(Total_Lanes-BQ$6)))),"-") -> 501.08178 | BR12: =IF(BR$6<Total_Lanes,900*Peak_Time_Eve*(($BL12/(Total_Lanes-BR$6))-1+SQRT((($BL12/(Total_Lanes-BR$6))-1)^2+8*($BL12/(Total_Lanes-BR$6))/(Peak_Time_Eve*$N45*(Total_Lanes-BR$6)))),"-") -> 1180.0055 | BS12: =IF(BS$6<Total_Lanes,900*Peak_Time_Eve*(($BL12/(Total_Lanes-BS$6))-1+SQRT((($BL12/(Total_Lanes-BS$6))-1)^2+8*($BL12/(Total_Lanes-BS$6))/(Peak_Time_Eve*$N45*(Total_Lanes-BS$6)))),"-") -> 2134.1868 | BT12: =IF(BT$6<Total_Lanes,900*Peak_Time_Eve*(($BL12/(Total_Lanes-BT$6))-1+SQRT((($BL12/(Total_Lanes-BT$6))-1)^2+8*($BL12/(Total_Lanes-BT$6))/(Peak_Time_Eve*$N45*(Total_Lanes-BT$6)))),"-") -> 3566.6032 | ... CG12: =IF(CG$6<Total_Lanes,900*Peak_Time_Eve*(($BL12/(Total_Lanes-CG$6))-1+SQRT((($BL12/(Total_Lanes-CG$6))-1)^2+8*($BL12/(Total_Lanes-CG$6))/(Peak_Time_Eve*$N45*(Total_Lanes-CG$6)))),"-") -> - | CH12: =3600/N45 -> 6.68125 | CJ12: 5 | CK12: =$X12 -> 0.34713691 | CL12: =$AC12 -> 6568.8625 | CM12: =CL12*CK12 -> 2280.2946 | CN12: =CM12/O44 -> 1.5201964 | CO12: =IF(CO$6<Total_Lanes,900*Peak_Time_Eve*(($CN12/CO$6-1)+SQRT(($CN12/CO$6-1)^2+8*($CN12/CO$6)/(Peak_Time_Eve*$O45*CO$6))),"-") -> 1879.6946 | CP12: =IF(CP$6<Total_Lanes,900*Peak_Time_Eve*(($CN12/CP$6-1)+SQRT(($CN12/CP$6-1)^2+8*($CN12/CP$6)/(Peak_Time_Eve*$O45*CP$6))),"-") -> 3.7854545 | CQ12: =IF(CQ$6<Total_Lanes,900*Peak_Time_Eve*(($CN12/CQ$6-1)+SQRT(($CN12/CQ$6-1)^2+8*($CN12/CQ$6)/(Peak_Time_Eve*$O45*CQ$6))),"-") -> 0.82145683 | CR12: =IF(CR$6<Total_Lanes,900*Peak_Time_Eve*(($CN12/CR$6-1)+SQRT(($CN12/CR$6-1)^2+8*($CN12/CR$6)/(Peak_Time_Eve*$O45*CR$6))),"-") -> 0.36775798 | CS12: =IF(CS$6<Total_Lanes,900*Peak_Time_Eve*(($CN12/CS$6-1)+SQRT(($CN12/CS$6-1)^2+8*($CN12/CS$6)/(Peak_Time_Eve*$O45*CS$6))),"-") -> 0.20967655 | CT12: =IF(CT$6<Total_Lanes,900*Peak_Time_Eve*(($CN12/CT$6-1)+SQRT(($CN12/CT$6-1)^2+8*($CN12/CT$6)/(Peak_Time_Eve*$O45*CT$6))),"-") -> 0.13573092 | CU12: =IF(CU$6<Total_Lanes,900*Peak_Time_Eve*(($CN12/CU$6-1)+SQRT(($CN12/CU$6-1)^2+8*($CN12/CU$6)/(Peak_Time_Eve*$O45*CU$6))),"-") -> 0.095111548 | CV12: =IF(CV$6<Total_Lanes,900*Peak_Time_Eve*(($CN12/CV$6-1)+SQRT(($CN12/CV$6-1)^2+8*($CN12/CV$6)/(Peak_Time_Eve*$O45*CV$6))),"-") -> 0.070379897 | ... DI12: =IF(DI$6<Total_Lanes,900*Peak_Time_Eve*(($CN12/DI$6-1)+SQRT(($CN12/DI$6-1)^2+8*($CN12/DI$6)/(Peak_Time_Eve*$O45*DI$6))),"-") -> - | DJ12: =3600/O45 -> 2.4
H13: 6 | I13: ='Input-Detail'!E20 -> 22311321 | J13: 0.34881248 | K13: =AC13 -> 6734.6349 | L13: =AD60 -> 11.062503 | M13: =AD13 -> 27.887206 | N13: =SUM(L13:M13) -> 38.949709 | O13: =$S$34*N13 -> 10126.924 | P13: =BC60 -> 7.036956 | Q13: =BC13 -> 25.404034 | R13: =SUM(P13:Q13) -> 32.44099 | S13: =$S$34*R13 -> 8434.6573 | V13: 6 | W13: =W$7+(W$27-W$7)*$V13/20 -> 22311321 | X13: =MIN((J12+0.1),0.95) -> 0.39898451 | Y13: ='Input-Detail'!E20/Z13 -> 9620.9071 | Z13: =Z12 -> 2319.0455 | AA13: =AA12 -> 2 | AB13: =AB12 -> 0.7 | AC13: =Y13*AB13 -> 6734.6349 | AD13: =Peak_Time_Eve*$BH13*(3600/K46+BK13)/3600 -> 27.887206 | AE13: =IF(AE$6<Total_Lanes,($BI13*($CH13+BM13)+$CM13*CO13)*Peak_Time_Eve/3600,"-") -> 4278.8466 | AF13: =IF(AF$6<Total_Lanes,($BI13*($CH13+BN13)+$CM13*CP13)*Peak_Time_Eve/3600,"-") -> 34.64921 | AG13: =IF(AG$6<Total_Lanes,($BI13*($CH13+BO13)+$CM13*CQ13)*Peak_Time_Eve/3600,"-") -> 25.404034 | AH13: =IF(AH$6<Total_Lanes,($BI13*($CH13+BP13)+$CM13*CR13)*Peak_Time_Eve/3600,"-") -> 44.619275 | AI13: =IF(AI$6<Total_Lanes,($BI13*($CH13+BQ13)+$CM13*CS13)*Peak_Time_Eve/3600,"-") -> 664.12642 | AJ13: =IF(AJ$6<Total_Lanes,($BI13*($CH13+BR13)+$CM13*CT13)*Peak_Time_Eve/3600,"-") -> 2099.7996 | AK13: =IF(AK$6<Total_Lanes,($BI13*($CH13+BS13)+$CM13*CU13)*Peak_Time_Eve/3600,"-") -> 4129.8993 | AL13: =IF(AL$6<Total_Lanes,($BI13*($CH13+BT13)+$CM13*CV13)*Peak_Time_Eve/3600,"-") -> 7179.174 | ... AY13: =IF(AY$6<Total_Lanes,($BI13*($CH13+CG13)+$CM13*DI13)*Peak_Time_Eve/3600,"-") -> - | AZ13: =SUMIF(AE13:AY13,BA13,$AE$6:$AY$6) -> 3 | BA13: =MIN(AE13:AY13) -> 25.404034 | BB13: =IF((SUMIF($BM11:$CG11,$AZ13,$BM13:$CG13)+$CH13)<(SUMIF($CO11:$DI11,$AZ13,$CO13:$DI13)+$DJ13),AZ13+1,AZ13) -> 3 | BC13: =SUMIF($AE$6:$AY$6,$BB13,$AE13:$AY13) -> 25.404034 | BF13: 6 | BG13: =$X13 -> 0.39898451 | BH13: =$AC13 -> 6734.6349 | BI13: =BH13*(1-BG13) -> 4047.6199 | BJ13: =Peak_Arrival_Manual/K46 -> 7.392528 | BK13: =900*Peak_Time_Eve*(BJ13/Total_Lanes-1+SQRT((BJ13/Total_Lanes-1)^2+8*(BJ13/Total_Lanes)/(Peak_Time_Eve*$K46*Total_Lanes))) -> 0.87855475 | BL13: =Peak_Arrival_Manual/N46 -> 7.5358812 | BM13: =IF(BM$6<Total_Lanes,900*Peak_Time_Eve*(($BL13/(Total_Lanes-BM$6))-1+SQRT((($BL13/(Total_Lanes-BM$6))-1)^2+8*($BL13/(Total_Lanes-BM$6))/(Peak_Time_Eve*$N46*(Total_Lanes-BM$6)))),"-") -> 1.3239711 | BN13: =IF(BN$6<Total_Lanes,900*Peak_Time_Eve*(($BL13/(Total_Lanes-BN$6))-1+SQRT((($BL13/(Total_Lanes-BN$6))-1)^2+8*($BL13/(Total_Lanes-BN$6))/(Peak_Time_Eve*$N46*(Total_Lanes-BN$6)))),"-") -> 2.0450746 | BO13: =IF(BO$6<Total_Lanes,900*Peak_Time_Eve*(($BL13/(Total_Lanes-BO$6))-1+SQRT((($BL13/(Total_Lanes-BO$6))-1)^2+8*($BL13/(Total_Lanes-BO$6))/(Peak_Time_Eve*$N46*(Total_Lanes-BO$6)))),"-") -> 3.8083517 | BP13: =IF(BP$6<Total_Lanes,900*Peak_Time_Eve*(($BL13/(Total_Lanes-BP$6))-1+SQRT((($BL13/(Total_Lanes-BP$6))-1)^2+8*($BL13/(Total_Lanes-BP$6))/(Peak_Time_Eve*$N46*(Total_Lanes-BP$6)))),"-") -> 12.816977 | BQ13: =IF(BQ$6<Total_Lanes,900*Peak_Time_Eve*(($BL13/(Total_Lanes-BQ$6))-1+SQRT((($BL13/(Total_Lanes-BQ$6))-1)^2+8*($BL13/(Total_Lanes-BQ$6))/(Peak_Time_Eve*$N46*(Total_Lanes-BQ$6)))),"-") -> 288.46049 | BR13: =IF(BR$6<Total_Lanes,900*Peak_Time_Eve*(($BL13/(Total_Lanes-BR$6))-1+SQRT((($BL13/(Total_Lanes-BR$6))-1)^2+8*($BL13/(Total_Lanes-BR$6))/(Peak_Time_Eve*$N46*(Total_Lanes-BR$6)))),"-") -> 926.97753 | BS13: =IF(BS$6<Total_Lanes,900*Peak_Time_Eve*(($BL13/(Total_Lanes-BS$6))-1+SQRT((($BL13/(Total_Lanes-BS$6))-1)^2+8*($BL13/(Total_Lanes-BS$6))/(Peak_Time_Eve*$N46*(Total_Lanes-BS$6)))),"-") -> 1829.8094 | BT13: =IF(BT$6<Total_Lanes,900*Peak_Time_Eve*(($BL13/(Total_Lanes-BT$6))-1+SQRT((($BL13/(Total_Lanes-BT$6))-1)^2+8*($BL13/(Total_Lanes-BT$6))/(Peak_Time_Eve*$N46*(Total_Lanes-BT$6)))),"-") -> 3185.8603 | ... CG13: =IF(CG$6<Total_Lanes,900*Peak_Time_Eve*(($BL13/(Total_Lanes-CG$6))-1+SQRT((($BL13/(Total_Lanes-CG$6))-1)^2+8*($BL13/(Total_Lanes-CG$6))/(Peak_Time_Eve*$N46*(Total_Lanes-CG$6)))),"-") -> - | CH13: =3600/N46 -> 6.7025 | CJ13: 6 | CK13: =$X13 -> 0.39898451 | CL13: =$AC13 -> 6734.6349 | CM13: =CL13*CK13 -> 2687.0151 | CN13: =CM13/O45 -> 1.7913434 | CO13: =IF(CO$6<Total_Lanes,900*Peak_Time_Eve*(($CN13/CO$6-1)+SQRT(($CN13/CO$6-1)^2+8*($CN13/CO$6)/(Peak_Time_Eve*$O46*CO$6))),"-") -> 2854.2586 | CP13: =IF(CP$6<Total_Lanes,900*Peak_Time_Eve*(($CN13/CP$6-1)+SQRT(($CN13/CP$6-1)^2+8*($CN13/CP$6)/(Peak_Time_Eve*$O46*CP$6))),"-") -> 10.034079 | CQ13: =IF(CQ$6<Total_Lanes,900*Peak_Time_Eve*(($CN13/CQ$6-1)+SQRT(($CN13/CQ$6-1)^2+8*($CN13/CQ$6)/(Peak_Time_Eve*$O46*CQ$6))),"-") -> 1.1847079 | CR13: =IF(CR$6<Total_Lanes,900*Peak_Time_Eve*(($CN13/CR$6-1)+SQRT(($CN13/CR$6-1)^2+8*($CN13/CR$6)/(Peak_Time_Eve*$O46*CR$6))),"-") -> 0.48651429 | CS13: =IF(CS$6<Total_Lanes,900*Peak_Time_Eve*(($CN13/CS$6-1)+SQRT(($CN13/CS$6-1)^2+8*($CN13/CS$6)/(Peak_Time_Eve*$O46*CS$6))),"-") -> 0.2679455 | CT13: =IF(CT$6<Total_Lanes,900*Peak_Time_Eve*(($CN13/CT$6-1)+SQRT(($CN13/CT$6-1)^2+8*($CN13/CT$6)/(Peak_Time_Eve*$O46*CT$6))),"-") -> 0.17024174 | CU13: =IF(CU$6<Total_Lanes,900*Peak_Time_Eve*(($CN13/CU$6-1)+SQRT(($CN13/CU$6-1)^2+8*($CN13/CU$6)/(Peak_Time_Eve*$O46*CU$6))),"-") -> 0.11790907 | CV13: =IF(CV$6<Total_Lanes,900*Peak_Time_Eve*(($CN13/CV$6-1)+SQRT(($CN13/CV$6-1)^2+8*($CN13/CV$6)/(Peak_Time_Eve*$O46*CV$6))),"-") -> 0.08655437 | ... DI13: =IF(DI$6<Total_Lanes,900*Peak_Time_Eve*(($CN13/DI$6-1)+SQRT(($CN13/DI$6-1)^2+8*($CN13/DI$6)/(Peak_Time_Eve*$O46*DI$6))),"-") -> - | DJ13: =3600/O46 -> 2.4
H14: 7 | I14: ='Input-Detail'!E21 -> 22860512 | J14: 0.39671513 | K14: =AC14 -> 6900.4074 | L14: =AD61 -> 11.343812 | M14: =AD14 -> 28.091534 | N14: =SUM(L14:M14) -> 39.435345 | O14: =$S$34*N14 -> 10253.19 | P14: =BC61 -> 6.6813999 | Q14: =BC14 -> 23.13272 | R14: =SUM(P14:Q14) -> 29.81412 | S14: =$S$34*R14 -> 7751.6712 | V14: 7 | W14: =W$7+(W$27-W$7)*$V14/20 -> 22860512 | X14: =MIN((J13+0.1),0.95) -> 0.44881248 | Y14: ='Input-Detail'!E21/Z14 -> 9857.7249 | Z14: =Z13 -> 2319.0455 | AA14: =AA13 -> 2 | AB14: =AB13 -> 0.7 | AC14: =Y14*AB14 -> 6900.4074 | AD14: =Peak_Time_Eve*$BH14*(3600/K47+BK14)/3600 -> 28.091534 | AE14: =IF(AE$6<Total_Lanes,($BI14*($CH14+BM14)+$CM14*CO14)*Peak_Time_Eve/3600,"-") -> 6619.0347 | AF14: =IF(AF$6<Total_Lanes,($BI14*($CH14+BN14)+$CM14*CP14)*Peak_Time_Eve/3600,"-") -> 270.21459 | AG14: =IF(AG$6<Total_Lanes,($BI14*($CH14+BO14)+$CM14*CQ14)*Peak_Time_Eve/3600,"-") -> 23.13272 | AH14: =IF(AH$6<Total_Lanes,($BI14*($CH14+BP14)+$CM14*CR14)*Peak_Time_Eve/3600,"-") -> 29.15797 | AI14: =IF(AI$6<Total_Lanes,($BI14*($CH14+BQ14)+$CM14*CS14)*Peak_Time_Eve/3600,"-") -> 208.38261 | AJ14: =IF(AJ$6<Total_Lanes,($BI14*($CH14+BR14)+$CM14*CT14)*Peak_Time_Eve/3600,"-") -> 1428.8942 | AK14: =IF(AK$6<Total_Lanes,($BI14*($CH14+BS14)+$CM14*CU14)*Peak_Time_Eve/3600,"-") -> 3224.4851 | AL14: =IF(AL$6<Total_Lanes,($BI14*($CH14+BT14)+$CM14*CV14)*Peak_Time_Eve/3600,"-") -> 5924.795 | ... AY14: =IF(AY$6<Total_Lanes,($BI14*($CH14+CG14)+$CM14*DI14)*Peak_Time_Eve/3600,"-") -> - | AZ14: =SUMIF(AE14:AY14,BA14,$AE$6:$AY$6) -> 3 | BA14: =MIN(AE14:AY14) -> 23.13272 | BB14: =IF((SUMIF($BM12:$CG12,$AZ14,$BM14:$CG14)+$CH14)<(SUMIF($CO12:$DI12,$AZ14,$CO14:$DI14)+$DJ14),AZ14+1,AZ14) -> 3 | BC14: =SUMIF($AE$6:$AY$6,$BB14,$AE14:$AY14) -> 23.13272 | BF14: 7 | BG14: =$X14 -> 0.44881248 | BH14: =$AC14 -> 6900.4074 | BI14: =BH14*(1-BG14) -> 3803.4184 | BJ14: =Peak_Arrival_Manual/K47 -> 6.9465212 | BK14: =900*Peak_Time_Eve*(BJ14/Total_Lanes-1+SQRT((BJ14/Total_Lanes-1)^2+8*(BJ14/Total_Lanes)/(Peak_Time_Eve*$K47*Total_Lanes))) -> 0.75279344 | BL14: =Peak_Arrival_Manual/N47 -> 7.1036763 | BM14: =IF(BM$6<Total_Lanes,900*Peak_Time_Eve*(($BL14/(Total_Lanes-BM$6))-1+SQRT((($BL14/(Total_Lanes-BM$6))-1)^2+8*($BL14/(Total_Lanes-BM$6))/(Peak_Time_Eve*$N47*(Total_Lanes-BM$6)))),"-") -> 1.1134429 | BN14: =IF(BN$6<Total_Lanes,900*Peak_Time_Eve*(($BL14/(Total_Lanes-BN$6))-1+SQRT((($BL14/(Total_Lanes-BN$6))-1)^2+8*($BL14/(Total_Lanes-BN$6))/(Peak_Time_Eve*$N47*(Total_Lanes-BN$6)))),"-") -> 1.6465024 | BO14: =IF(BO$6<Total_Lanes,900*Peak_Time_Eve*(($BL14/(Total_Lanes-BO$6))-1+SQRT((($BL14/(Total_Lanes-BO$6))-1)^2+8*($BL14/(Total_Lanes-BO$6))/(Peak_Time_Eve*$N47*(Total_Lanes-BO$6)))),"-") -> 2.7883431 | BP14: =IF(BP$6<Total_Lanes,900*Peak_Time_Eve*(($BL14/(Total_Lanes-BP$6))-1+SQRT((($BL14/(Total_Lanes-BP$6))-1)^2+8*($BL14/(Total_Lanes-BP$6))/(Peak_Time_Eve*$N47*(Total_Lanes-BP$6)))),"-") -> 6.5544939 | BQ14: =IF(BQ$6<Total_Lanes,900*Peak_Time_Eve*(($BL14/(Total_Lanes-BQ$6))-1+SQRT((($BL14/(Total_Lanes-BQ$6))-1)^2+8*($BL14/(Total_Lanes-BQ$6))/(Peak_Time_Eve*$N47*(Total_Lanes-BQ$6)))),"-") -> 91.620217 | BR14: =IF(BR$6<Total_Lanes,900*Peak_Time_Eve*(($BL14/(Total_Lanes-BR$6))-1+SQRT((($BL14/(Total_Lanes-BR$6))-1)^2+8*($BL14/(Total_Lanes-BR$6))/(Peak_Time_Eve*$N47*(Total_Lanes-BR$6)))),"-") -> 669.34165 | BS14: =IF(BS$6<Total_Lanes,900*Peak_Time_Eve*(($BL14/(Total_Lanes-BS$6))-1+SQRT((($BL14/(Total_Lanes-BS$6))-1)^2+8*($BL14/(Total_Lanes-BS$6))/(Peak_Time_Eve*$N47*(Total_Lanes-BS$6)))),"-") -> 1519.1743 | BT14: =IF(BT$6<Total_Lanes,900*Peak_Time_Eve*(($BL14/(Total_Lanes-BT$6))-1+SQRT((($BL14/(Total_Lanes-BT$6))-1)^2+8*($BL14/(Total_Lanes-BT$6))/(Peak_Time_Eve*$N47*(Total_Lanes-BT$6)))),"-") -> 2797.1507 | ... CG14: =IF(CG$6<Total_Lanes,900*Peak_Time_Eve*(($BL14/(Total_Lanes-CG$6))-1+SQRT((($BL14/(Total_Lanes-CG$6))-1)^2+8*($BL14/(Total_Lanes-CG$6))/(Peak_Time_Eve*$N47*(Total_Lanes-CG$6)))),"-") -> - | CH14: =3600/N47 -> 6.72375 | CJ14: 7 | CK14: =$X14 -> 0.44881248 | CL14: =$AC14 -> 6900.4074 | CM14: =CL14*CK14 -> 3096.989 | CN14: =CM14/O46 -> 2.0646593 | CO14: =IF(CO$6<Total_Lanes,900*Peak_Time_Eve*(($CN14/CO$6-1)+SQRT(($CN14/CO$6-1)^2+8*($CN14/CO$6)/(Peak_Time_Eve*$O47*CO$6))),"-") -> 3837.4222 | CP14: =IF(CP$6<Total_Lanes,900*Peak_Time_Eve*(($CN14/CP$6-1)+SQRT(($CN14/CP$6-1)^2+8*($CN14/CP$6)/(Peak_Time_Eve*$O47*CP$6))),"-") -> 146.77181 | CQ14: =IF(CQ$6<Total_Lanes,900*Peak_Time_Eve*(($CN14/CQ$6-1)+SQRT(($CN14/CQ$6-1)^2+8*($CN14/CQ$6)/(Peak_Time_Eve*$O47*CQ$6))),"-") -> 1.7631404 | CR14: =IF(CR$6<Total_Lanes,900*Peak_Time_Eve*(($CN14/CR$6-1)+SQRT(($CN14/CR$6-1)^2+8*($CN14/CR$6)/(Peak_Time_Eve*$O47*CR$6))),"-") -> 0.6398567 | CS14: =IF(CS$6<Total_Lanes,900*Peak_Time_Eve*(($CN14/CS$6-1)+SQRT(($CN14/CS$6-1)^2+8*($CN14/CS$6)/(Peak_Time_Eve*$O47*CS$6))),"-") -> 0.33756839 | CT14: =IF(CT$6<Total_Lanes,900*Peak_Time_Eve*(($CN14/CT$6-1)+SQRT(($CN14/CT$6-1)^2+8*($CN14/CT$6)/(Peak_Time_Eve*$O47*CT$6))),"-") -> 0.20983961 | CU14: =IF(CU$6<Total_Lanes,900*Peak_Time_Eve*(($CN14/CU$6-1)+SQRT(($CN14/CU$6-1)^2+8*($CN14/CU$6)/(Peak_Time_Eve*$O47*CU$6))),"-") -> 0.14342337 | CV14: =IF(CV$6<Total_Lanes,900*Peak_Time_Eve*(($CN14/CV$6-1)+SQRT(($CN14/CV$6-1)^2+8*($CN14/CV$6)/(Peak_Time_Eve*$O47*CV$6))),"-") -> 0.1043535 | ... DI14: =IF(DI$6<Total_Lanes,900*Peak_Time_Eve*(($CN14/DI$6-1)+SQRT(($CN14/DI$6-1)^2+8*($CN14/DI$6)/(Peak_Time_Eve*$O47*DI$6))),"-") -> - | DJ14: =3600/O47 -> 2.4
H15: 8 | I15: ='Input-Detail'!E22 -> 23409704 | J15: 0.44303751 | K15: =AC15 -> 7066.1799 | L15: =AD62 -> 11.626355 | M15: =AD15 -> 28.348102 | N15: =SUM(L15:M15) -> 39.974457 | O15: =$S$34*N15 -> 10393.359 | P15: =BC62 -> 6.2752119 | Q15: =BC15 -> 23.048736 | R15: =SUM(P15:Q15) -> 29.323948 | S15: =$S$34*R15 -> 7624.2265 | V15: 8 | W15: =W$7+(W$27-W$7)*$V15/20 -> 23409704 | X15: =MIN((J14+0.1),0.95) -> 0.49671513 | Y15: ='Input-Detail'!E22/Z15 -> 10094.543 | Z15: =Z14 -> 2319.0455 | AA15: =AA14 -> 2 | AB15: =AB14 -> 0.7 | AC15: =Y15*AB15 -> 7066.1799 | AD15: =Peak_Time_Eve*$BH15*(3600/K48+BK15)/3600 -> 28.348102 | AE15: =IF(AE$6<Total_Lanes,($BI15*($CH15+BM15)+$CM15*CO15)*Peak_Time_Eve/3600,"-") -> 9429.2574 | AF15: =IF(AF$6<Total_Lanes,($BI15*($CH15+BN15)+$CM15*CP15)*Peak_Time_Eve/3600,"-") -> 1224.9543 | AG15: =IF(AG$6<Total_Lanes,($BI15*($CH15+BO15)+$CM15*CQ15)*Peak_Time_Eve/3600,"-") -> 23.048736 | AH15: =IF(AH$6<Total_Lanes,($BI15*($CH15+BP15)+$CM15*CR15)*Peak_Time_Eve/3600,"-") -> 23.21964 | AI15: =IF(AI$6<Total_Lanes,($BI15*($CH15+BQ15)+$CM15*CS15)*Peak_Time_Eve/3600,"-") -> 48.38083 | AJ15: =IF(AJ$6<Total_Lanes,($BI15*($CH15+BR15)+$CM15*CT15)*Peak_Time_Eve/3600,"-") -> 821.63386 | AK15: =IF(AK$6<Total_Lanes,($BI15*($CH15+BS15)+$CM15*CU15)*Peak_Time_Eve/3600,"-") -> 2390.123 | AL15: =IF(AL$6<Total_Lanes,($BI15*($CH15+BT15)+$CM15*CV15)*Peak_Time_Eve/3600,"-") -> 4757.3282 | ... AY15: =IF(AY$6<Total_Lanes,($BI15*($CH15+CG15)+$CM15*DI15)*Peak_Time_Eve/3600,"-") -> - | AZ15: =SUMIF(AE15:AY15,BA15,$AE$6:$AY$6) -> 3 | BA15: =MIN(AE15:AY15) -> 23.048736 | BB15: =IF((SUMIF($BM13:$CG13,$AZ15,$BM15:$CG15)+$CH15)<(SUMIF($CO13:$DI13,$AZ15,$CO15:$DI15)+$DJ15),AZ15+1,AZ15) -> 3 | BC15: =SUMIF($AE$6:$AY$6,$BB15,$AE15:$AY15) -> 23.048736 | BF15: 8 | BG15: =$X15 -> 0.49671513 | BH15: =$AC15 -> 7066.1799 | BI15: =BH15*(1-BG15) -> 3556.3014 | BJ15: =Peak_Arrival_Manual/K48 -> 6.4951894 | BK15: =900*Peak_Time_Eve*(BJ15/Total_Lanes-1+SQRT((BJ15/Total_Lanes-1)^2+8*(BJ15/Total_Lanes)/(Peak_Time_Eve*$K48*Total_Lanes))) -> 0.6462403 | BL15: =Peak_Arrival_Manual/N48 -> 6.6631259 | BM15: =IF(BM$6<Total_Lanes,900*Peak_Time_Eve*(($BL15/(Total_Lanes-BM$6))-1+SQRT((($BL15/(Total_Lanes-BM$6))-1)^2+8*($BL15/(Total_Lanes-BM$6))/(Peak_Time_Eve*$N48*(Total_Lanes-BM$6)))),"-") -> 0.94146135 | BN15: =IF(BN$6<Total_Lanes,900*Peak_Time_Eve*(($BL15/(Total_Lanes-BN$6))-1+SQRT((($BL15/(Total_Lanes-BN$6))-1)^2+8*($BL15/(Total_Lanes-BN$6))/(Peak_Time_Eve*$N48*(Total_Lanes-BN$6)))),"-") -> 1.3453462 | BO15: =IF(BO$6<Total_Lanes,900*Peak_Time_Eve*(($BL15/(Total_Lanes-BO$6))-1+SQRT((($BL15/(Total_Lanes-BO$6))-1)^2+8*($BL15/(Total_Lanes-BO$6))/(Peak_Time_Eve*$N48*(Total_Lanes-BO$6)))),"-") -> 2.132027 | BP15: =IF(BP$6<Total_Lanes,900*Peak_Time_Eve*(($BL15/(Total_Lanes-BP$6))-1+SQRT((($BL15/(Total_Lanes-BP$6))-1)^2+8*($BL15/(Total_Lanes-BP$6))/(Peak_Time_Eve*$N48*(Total_Lanes-BP$6)))),"-") -> 4.1732764 | BQ15: =IF(BQ$6<Total_Lanes,900*Peak_Time_Eve*(($BL15/(Total_Lanes-BQ$6))-1+SQRT((($BL15/(Total_Lanes-BQ$6))-1)^2+8*($BL15/(Total_Lanes-BQ$6))/(Peak_Time_Eve*$N48*(Total_Lanes-BQ$6)))),"-") -> 17.326033 | BR15: =IF(BR$6<Total_Lanes,900*Peak_Time_Eve*(($BL15/(Total_Lanes-BR$6))-1+SQRT((($BL15/(Total_Lanes-BR$6))-1)^2+8*($BL15/(Total_Lanes-BR$6))/(Peak_Time_Eve*$N48*(Total_Lanes-BR$6)))),"-") -> 408.86755 | BS15: =IF(BS$6<Total_Lanes,900*Peak_Time_Eve*(($BL15/(Total_Lanes-BS$6))-1+SQRT((($BL15/(Total_Lanes-BS$6))-1)^2+8*($BL15/(Total_Lanes-BS$6))/(Peak_Time_Eve*$N48*(Total_Lanes-BS$6)))),"-") -> 1202.8311 | BT15: =IF(BT$6<Total_Lanes,900*Peak_Time_Eve*(($BL15/(Total_Lanes-BT$6))-1+SQRT((($BL15/(Total_Lanes-BT$6))-1)^2+8*($BL15/(Total_Lanes-BT$6))/(Peak_Time_Eve*$N48*(Total_Lanes-BT$6)))),"-") -> 2401.0249 | ... CG15: =IF(CG$6<Total_Lanes,900*Peak_Time_Eve*(($BL15/(Total_Lanes-CG$6))-1+SQRT((($BL15/(Total_Lanes-CG$6))-1)^2+8*($BL15/(Total_Lanes-CG$6))/(Peak_Time_Eve*$N48*(Total_Lanes-CG$6)))),"-") -> - | CH15: =3600/N48 -> 6.745 | CJ15: 8 | CK15: =$X15 -> 0.49671513 | CL15: =$AC15 -> 7066.1799 | CM15: =CL15*CK15 -> 3509.8785 | CN15: =CM15/O47 -> 2.339919 | CO15: =IF(CO$6<Total_Lanes,900*Peak_Time_Eve*(($CN15/CO$6-1)+SQRT(($CN15/CO$6-1)^2+8*($CN15/CO$6)/(Peak_Time_Eve*$O48*CO$6))),"-") -> 4827.8959 | CP15: =IF(CP$6<Total_Lanes,900*Peak_Time_Eve*(($CN15/CP$6-1)+SQRT(($CN15/CP$6-1)^2+8*($CN15/CP$6)/(Peak_Time_Eve*$O48*CP$6))),"-") -> 620.00608 | CQ15: =IF(CQ$6<Total_Lanes,900*Peak_Time_Eve*(($CN15/CQ$6-1)+SQRT(($CN15/CQ$6-1)^2+8*($CN15/CQ$6)/(Peak_Time_Eve*$O48*CQ$6))),"-") -> 2.8258361 | CR15: =IF(CR$6<Total_Lanes,900*Peak_Time_Eve*(($CN15/CR$6-1)+SQRT(($CN15/CR$6-1)^2+8*($CN15/CR$6)/(Peak_Time_Eve*$O48*CR$6))),"-") -> 0.84523441 | CS15: =IF(CS$6<Total_Lanes,900*Peak_Time_Eve*(($CN15/CS$6-1)+SQRT(($CN15/CS$6-1)^2+8*($CN15/CS$6)/(Peak_Time_Eve*$O48*CS$6))),"-") -> 0.42213512 | CT15: =IF(CT$6<Total_Lanes,900*Peak_Time_Eve*(($CN15/CT$6-1)+SQRT(($CN15/CT$6-1)^2+8*($CN15/CT$6)/(Peak_Time_Eve*$O48*CT$6))),"-") -> 0.25569342 | CU15: =IF(CU$6<Total_Lanes,900*Peak_Time_Eve*(($CN15/CU$6-1)+SQRT(($CN15/CU$6-1)^2+8*($CN15/CU$6)/(Peak_Time_Eve*$O48*CU$6))),"-") -> 0.172143 | CV15: =IF(CV$6<Total_Lanes,900*Peak_Time_Eve*(($CN15/CV$6-1)+SQRT(($CN15/CV$6-1)^2+8*($CN15/CV$6)/(Peak_Time_Eve*$O48*CV$6))),"-") -> 0.12401616 | ... DI15: =IF(DI$6<Total_Lanes,900*Peak_Time_Eve*(($CN15/DI$6-1)+SQRT(($CN15/DI$6-1)^2+8*($CN15/DI$6)/(Peak_Time_Eve*$O48*DI$6))),"-") -> - | DJ15: =3600/O48 -> 2.4
H16: 9 | I16: ='Input-Detail'!E23 -> 23958895 | J16: 0.48815269 | K16: =AC16 -> 7231.9524 | L16: =AD63 -> 11.910006 | M16: =AD16 -> 28.643789 | N16: =SUM(L16:M16) -> 40.553795 | O16: =$S$34*N16 -> 10543.987 | P16: =BC63 -> 5.8744917 | Q16: =BC16 -> 20.273197 | R16: =SUM(P16:Q16) -> 26.147689 | S16: =$S$34*R16 -> 6798.3991 | V16: 9 | W16: =W$7+(W$27-W$7)*$V16/20 -> 23958895 | X16: =MIN((J15+0.1),0.95) -> 0.54303751 | Y16: ='Input-Detail'!E23/Z16 -> 10331.361 | Z16: =Z15 -> 2319.0455 | AA16: =AA15 -> 2 | AB16: =AB15 -> 0.7 | AC16: =Y16*AB16 -> 7231.9524 | AD16: =Peak_Time_Eve*$BH16*(3600/K49+BK16)/3600 -> 28.643789 | AE16: =IF(AE$6<Total_Lanes,($BI16*($CH16+BM16)+$CM16*CO16)*Peak_Time_Eve/3600,"-") -> 12732.002 | AF16: =IF(AF$6<Total_Lanes,($BI16*($CH16+BN16)+$CM16*CP16)*Peak_Time_Eve/3600,"-") -> 2453.0991 | AG16: =IF(AG$6<Total_Lanes,($BI16*($CH16+BO16)+$CM16*CQ16)*Peak_Time_Eve/3600,"-") -> 27.319802 | AH16: =IF(AH$6<Total_Lanes,($BI16*($CH16+BP16)+$CM16*CR16)*Peak_Time_Eve/3600,"-") -> 20.273197 | AI16: =IF(AI$6<Total_Lanes,($BI16*($CH16+BQ16)+$CM16*CS16)*Peak_Time_Eve/3600,"-") -> 27.296299 | AJ16: =IF(AJ$6<Total_Lanes,($BI16*($CH16+BR16)+$CM16*CT16)*Peak_Time_Eve/3600,"-") -> 295.93442 | AK16: =IF(AK$6<Total_Lanes,($BI16*($CH16+BS16)+$CM16*CU16)*Peak_Time_Eve/3600,"-") -> 1626.7019 | AL16: =IF(AL$6<Total_Lanes,($BI16*($CH16+BT16)+$CM16*CV16)*Peak_Time_Eve/3600,"-") -> 3675.2992 | ... AY16: =IF(AY$6<Total_Lanes,($BI16*($CH16+CG16)+$CM16*DI16)*Peak_Time_Eve/3600,"-") -> - | AZ16: =SUMIF(AE16:AY16,BA16,$AE$6:$AY$6) -> 4 | BA16: =MIN(AE16:AY16) -> 20.273197 | BB16: =IF((SUMIF($BM14:$CG14,$AZ16,$BM16:$CG16)+$CH16)<(SUMIF($CO14:$DI14,$AZ16,$CO16:$DI16)+$DJ16),AZ16+1,AZ16) -> 4 | BC16: =SUMIF($AE$6:$AY$6,$BB16,$AE16:$AY16) -> 20.273197 | BF16: 9 | BG16: =$X16 -> 0.54303751 | BH16: =$AC16 -> 7231.9524 | BI16: =BH16*(1-BG16) -> 3304.731 | BJ16: =Peak_Arrival_Manual/K49 -> 6.0357239 | BK16: =900*Peak_Time_Eve*(BJ16/Total_Lanes-1+SQRT((BJ16/Total_Lanes-1)^2+8*(BJ16/Total_Lanes)/(Peak_Time_Eve*$K49*Total_Lanes))) -> 0.5543086 | BL16: =Peak_Arrival_Manual/N49 -> 6.2112877 | BM16: =IF(BM$6<Total_Lanes,900*Peak_Time_Eve*(($BL16/(Total_Lanes-BM$6))-1+SQRT((($BL16/(Total_Lanes-BM$6))-1)^2+8*($BL16/(Total_Lanes-BM$6))/(Peak_Time_Eve*$N49*(Total_Lanes-BM$6)))),"-") -> 0.79743875 | BN16: =IF(BN$6<Total_Lanes,900*Peak_Time_Eve*(($BL16/(Total_Lanes-BN$6))-1+SQRT((($BL16/(Total_Lanes-BN$6))-1)^2+8*($BL16/(Total_Lanes-BN$6))/(Peak_Time_Eve*$N49*(Total_Lanes-BN$6)))),"-") -> 1.1083713 | BO16: =IF(BO$6<Total_Lanes,900*Peak_Time_Eve*(($BL16/(Total_Lanes-BO$6))-1+SQRT((($BL16/(Total_Lanes-BO$6))-1)^2+8*($BL16/(Total_Lanes-BO$6))/(Peak_Time_Eve*$N49*(Total_Lanes-BO$6)))),"-") -> 1.6719874 | BP16: =IF(BP$6<Total_Lanes,900*Peak_Time_Eve*(($BL16/(Total_Lanes-BP$6))-1+SQRT((($BL16/(Total_Lanes-BP$6))-1)^2+8*($BL16/(Total_Lanes-BP$6))/(Peak_Time_Eve*$N49*(Total_Lanes-BP$6)))),"-") -> 2.9263292 | BQ16: =IF(BQ$6<Total_Lanes,900*Peak_Time_Eve*(($BL16/(Total_Lanes-BQ$6))-1+SQRT((($BL16/(Total_Lanes-BQ$6))-1)^2+8*($BL16/(Total_Lanes-BQ$6))/(Peak_Time_Eve*$N49*(Total_Lanes-BQ$6)))),"-") -> 7.4745155 | BR16: =IF(BR$6<Total_Lanes,900*Peak_Time_Eve*(($BL16/(Total_Lanes-BR$6))-1+SQRT((($BL16/(Total_Lanes-BR$6))-1)^2+8*($BL16/(Total_Lanes-BR$6))/(Peak_Time_Eve*$N49*(Total_Lanes-BR$6)))),"-") -> 154.0535 | BS16: =IF(BS$6<Total_Lanes,900*Peak_Time_Eve*(($BL16/(Total_Lanes-BS$6))-1+SQRT((($BL16/(Total_Lanes-BS$6))-1)^2+8*($BL16/(Total_Lanes-BS$6))/(Peak_Time_Eve*$N49*(Total_Lanes-BS$6)))),"-") -> 879.01206 | BT16: =IF(BT$6<Total_Lanes,900*Peak_Time_Eve*(($BL16/(Total_Lanes-BT$6))-1+SQRT((($BL16/(Total_Lanes-BT$6))-1)^2+8*($BL16/(Total_Lanes-BT$6))/(Peak_Time_Eve*$N49*(Total_Lanes-BT$6)))),"-") -> 1994.8991 | ... CG16: =IF(CG$6<Total_Lanes,900*Peak_Time_Eve*(($BL16/(Total_Lanes-CG$6))-1+SQRT((($BL16/(Total_Lanes-CG$6))-1)^2+8*($BL16/(Total_Lanes-CG$6))/(Peak_Time_Eve*$N49*(Total_Lanes-CG$6)))),"-") -> - | CH16: =3600/N49 -> 6.76625 | CJ16: 9 | CK16: =$X16 -> 0.54303751 | CL16: =$AC16 -> 7231.9524 | CM16: =CL16*CK16 -> 3927.2215 | CN16: =CM16/O48 -> 2.6181476 | CO16: =IF(CO$6<Total_Lanes,900*Peak_Time_Eve*(($CN16/CO$6-1)+SQRT(($CN16/CO$6-1)^2+8*($CN16/CO$6)/(Peak_Time_Eve*$O49*CO$6))),"-") -> 5829.2121 | CP16: =IF(CP$6<Total_Lanes,900*Peak_Time_Eve*(($CN16/CP$6-1)+SQRT(($CN16/CP$6-1)^2+8*($CN16/CP$6)/(Peak_Time_Eve*$O49*CP$6))),"-") -> 1117.7253 | CQ16: =IF(CQ$6<Total_Lanes,900*Peak_Time_Eve*(($CN16/CQ$6-1)+SQRT(($CN16/CQ$6-1)^2+8*($CN16/CQ$6)/(Peak_Time_Eve*$O49*CQ$6))),"-") -> 5.4210181 | CR16: =IF(CR$6<Total_Lanes,900*Peak_Time_Eve*(($CN16/CR$6-1)+SQRT(($CN16/CR$6-1)^2+8*($CN16/CR$6)/(Peak_Time_Eve*$O49*CR$6))),"-") -> 1.1357619 | CS16: =IF(CS$6<Total_Lanes,900*Peak_Time_Eve*(($CN16/CS$6-1)+SQRT(($CN16/CS$6-1)^2+8*($CN16/CS$6)/(Peak_Time_Eve*$O49*CS$6))),"-") -> 0.5274569 | CT16: =IF(CT$6<Total_Lanes,900*Peak_Time_Eve*(($CN16/CT$6-1)+SQRT(($CN16/CT$6-1)^2+8*($CN16/CT$6)/(Peak_Time_Eve*$O49*CT$6))),"-") -> 0.309623 | CU16: =IF(CU$6<Total_Lanes,900*Peak_Time_Eve*(($CN16/CU$6-1)+SQRT(($CN16/CU$6-1)^2+8*($CN16/CU$6)/(Peak_Time_Eve*$O49*CU$6))),"-") -> 0.20483781 | CV16: =IF(CV$6<Total_Lanes,900*Peak_Time_Eve*(($CN16/CV$6-1)+SQRT(($CN16/CV$6-1)^2+8*($CN16/CV$6)/(Peak_Time_Eve*$O49*CV$6))),"-") -> 0.14593432 | ... DI16: =IF(DI$6<Total_Lanes,900*Peak_Time_Eve*(($CN16/DI$6-1)+SQRT(($CN16/DI$6-1)^2+8*($CN16/DI$6)/(Peak_Time_Eve*$O49*DI$6))),"-") -> - | DJ16: =3600/O49 -> 2.4
H17: 10 | I17: ='Input-Detail'!E24 -> 24508086 | J17: 0.53173113 | K17: =AC17 -> 7397.7249 | L17: =AD64 -> 12.194603 | M17: =AD17 -> 28.968861 | N17: =SUM(L17:M17) -> 41.163464 | O17: =$S$34*N17 -> 10702.501 | P17: =BC64 -> 5.4697636 | Q17: =BC17 -> 18.958882 | R17: =SUM(P17:Q17) -> 24.428646 | S17: =$S$34*R17 -> 6351.4479 | V17: 10 | W17: =W$7+(W$27-W$7)*$V17/20 -> 24508086 | X17: =MIN((J16+0.1),0.95) -> 0.58815269 | Y17: ='Input-Detail'!E24/Z17 -> 10568.178 | Z17: =Z16 -> 2319.0455 | AA17: =AA16 -> 2 | AB17: =AB16 -> 0.7 | AC17: =Y17*AB17 -> 7397.7249 | AD17: =Peak_Time_Eve*$BH17*(3600/K50+BK17)/3600 -> 28.968861 | AE17: =IF(AE$6<Total_Lanes,($BI17*($CH17+BM17)+$CM17*CO17)*Peak_Time_Eve/3600,"-") -> 16561.001 | AF17: =IF(AF$6<Total_Lanes,($BI17*($CH17+BN17)+$CM17*CP17)*Peak_Time_Eve/3600,"-") -> 3941.1277 | AG17: =IF(AG$6<Total_Lanes,($BI17*($CH17+BO17)+$CM17*CQ17)*Peak_Time_Eve/3600,"-") -> 62.090769 | AH17: =IF(AH$6<Total_Lanes,($BI17*($CH17+BP17)+$CM17*CR17)*Peak_Time_Eve/3600,"-") -> 18.958882 | AI17: =IF(AI$6<Total_Lanes,($BI17*($CH17+BQ17)+$CM17*CS17)*Peak_Time_Eve/3600,"-") -> 20.548737 | AJ17: =IF(AJ$6<Total_Lanes,($BI17*($CH17+BR17)+$CM17*CT17)*Peak_Time_Eve/3600,"-") -> 49.978711 | AK17: =IF(AK$6<Total_Lanes,($BI17*($CH17+BS17)+$CM17*CU17)*Peak_Time_Eve/3600,"-") -> 936.62164 | AL17: =IF(AL$6<Total_Lanes,($BI17*($CH17+BT17)+$CM17*CV17)*Peak_Time_Eve/3600,"-") -> 2678.6279 | ... AY17: =IF(AY$6<Total_Lanes,($BI17*($CH17+CG17)+$CM17*DI17)*Peak_Time_Eve/3600,"-") -> - | AZ17: =SUMIF(AE17:AY17,BA17,$AE$6:$AY$6) -> 4 | BA17: =MIN(AE17:AY17) -> 18.958882 | BB17: =IF((SUMIF($BM15:$CG15,$AZ17,$BM17:$CG17)+$CH17)<(SUMIF($CO15:$DI15,$AZ17,$CO17:$DI17)+$DJ17),AZ17+1,AZ17) -> 4 | BC17: =SUMIF($AE$6:$AY$6,$BB17,$AE17:$AY17) -> 18.958882 | BF17: 10 | BG17: =$X17 -> 0.58815269 | BH17: =$AC17 -> 7397.7249 | BI17: =BH17*(1-BG17) -> 3046.7331 | BJ17: =Peak_Arrival_Manual/K50 -> 5.5645195 | BK17: =900*Peak_Time_Eve*(BJ17/Total_Lanes-1+SQRT((BJ17/Total_Lanes-1)^2+8*(BJ17/Total_Lanes)/(Peak_Time_Eve*$K50*Total_Lanes))) -> 0.47364686 | BL17: =Peak_Arrival_Manual/N50 -> 5.7443614 | BM17: =IF(BM$6<Total_Lanes,900*Peak_Time_Eve*(($BL17/(Total_Lanes-BM$6))-1+SQRT((($BL17/(Total_Lanes-BM$6))-1)^2+8*($BL17/(Total_Lanes-BM$6))/(Peak_Time_Eve*$N50*(Total_Lanes-BM$6)))),"-") -> 0.67416038 | BN17: =IF(BN$6<Total_Lanes,900*Peak_Time_Eve*(($BL17/(Total_Lanes-BN$6))-1+SQRT((($BL17/(Total_Lanes-BN$6))-1)^2+8*($BL17/(Total_Lanes-BN$6))/(Peak_Time_Eve*$N50*(Total_Lanes-BN$6)))),"-") -> 0.9156455 | BO17: =IF(BO$6<Total_Lanes,900*Peak_Time_Eve*(($BL17/(Total_Lanes-BO$6))-1+SQRT((($BL17/(Total_Lanes-BO$6))-1)^2+8*($BL17/(Total_Lanes-BO$6))/(Peak_Time_Eve*$N50*(Total_Lanes-BO$6)))),"-") -> 1.3293208 | BP17: =IF(BP$6<Total_Lanes,900*Peak_Time_Eve*(($BL17/(Total_Lanes-BP$6))-1+SQRT((($BL17/(Total_Lanes-BP$6))-1)^2+8*($BL17/(Total_Lanes-BP$6))/(Peak_Time_Eve*$N50*(Total_Lanes-BP$6)))),"-") -> 2.1561082 | BQ17: =IF(BQ$6<Total_Lanes,900*Peak_Time_Eve*(($BL17/(Total_Lanes-BQ$6))-1+SQRT((($BL17/(Total_Lanes-BQ$6))-1)^2+8*($BL17/(Total_Lanes-BQ$6))/(Peak_Time_Eve*$N50*(Total_Lanes-BQ$6)))),"-") -> 4.405912 | BR17: =IF(BR$6<Total_Lanes,900*Peak_Time_Eve*(($BL17/(Total_Lanes-BR$6))-1+SQRT((($BL17/(Total_Lanes-BR$6))-1)^2+8*($BL17/(Total_Lanes-BR$6))/(Peak_Time_Eve*$N50*(Total_Lanes-BR$6)))),"-") -> 22.205252 | BS17: =IF(BS$6<Total_Lanes,900*Peak_Time_Eve*(($BL17/(Total_Lanes-BS$6))-1+SQRT((($BL17/(Total_Lanes-BS$6))-1)^2+8*($BL17/(Total_Lanes-BS$6))/(Peak_Time_Eve*$N50*(Total_Lanes-BS$6)))),"-") -> 546.2191 | BT17: =IF(BT$6<Total_Lanes,900*Peak_Time_Eve*(($BL17/(Total_Lanes-BT$6))-1+SQRT((($BL17/(Total_Lanes-BT$6))-1)^2+8*($BL17/(Total_Lanes-BT$6))/(Peak_Time_Eve*$N50*(Total_Lanes-BT$6)))),"-") -> 1575.4935 | ... CG17: =IF(CG$6<Total_Lanes,900*Peak_Time_Eve*(($BL17/(Total_Lanes-CG$6))-1+SQRT((($BL17/(Total_Lanes-CG$6))-1)^2+8*($BL17/(Total_Lanes-CG$6))/(Peak_Time_Eve*$N50*(Total_Lanes-CG$6)))),"-") -> - | CH17: =3600/N50 -> 6.7875 | CJ17: 10 | CK17: =$X17 -> 0.58815269 | CL17: =$AC17 -> 7397.7249 | CM17: =CL17*CK17 -> 4350.9918 | CN17: =CM17/O49 -> 2.9006612 | CO17: =IF(CO$6<Total_Lanes,900*Peak_Time_Eve*(($CN17/CO$6-1)+SQRT(($CN17/CO$6-1)^2+8*($CN17/CO$6)/(Peak_Time_Eve*$O50*CO$6))),"-") -> 6846.0411 | CP17: =IF(CP$6<Total_Lanes,900*Peak_Time_Eve*(($CN17/CP$6-1)+SQRT(($CN17/CP$6-1)^2+8*($CN17/CP$6)/(Peak_Time_Eve*$O50*CP$6))),"-") -> 1625.0457 | CQ17: =IF(CQ$6<Total_Lanes,900*Peak_Time_Eve*(($CN17/CQ$6-1)+SQRT(($CN17/CQ$6-1)^2+8*($CN17/CQ$6)/(Peak_Time_Eve*$O50*CQ$6))),"-") -> 20.003163 | CR17: =IF(CR$6<Total_Lanes,900*Peak_Time_Eve*(($CN17/CR$6-1)+SQRT(($CN17/CR$6-1)^2+8*($CN17/CR$6)/(Peak_Time_Eve*$O50*CR$6))),"-") -> 1.5806054 | CS17: =IF(CS$6<Total_Lanes,900*Peak_Time_Eve*(($CN17/CS$6-1)+SQRT(($CN17/CS$6-1)^2+8*($CN17/CS$6)/(Peak_Time_Eve*$O50*CS$6))),"-") -> 0.66292635 | CT17: =IF(CT$6<Total_Lanes,900*Peak_Time_Eve*(($CN17/CT$6-1)+SQRT(($CN17/CT$6-1)^2+8*($CN17/CT$6)/(Peak_Time_Eve*$O50*CT$6))),"-") -> 0.37428338 | CU17: =IF(CU$6<Total_Lanes,900*Peak_Time_Eve*(($CN17/CU$6-1)+SQRT(($CN17/CU$6-1)^2+8*($CN17/CU$6)/(Peak_Time_Eve*$O50*CU$6))),"-") -> 0.24257522 | CV17: =IF(CV$6<Total_Lanes,900*Peak_Time_Eve*(($CN17/CV$6-1)+SQRT(($CN17/CV$6-1)^2+8*($CN17/CV$6)/(Peak_Time_Eve*$O50*CV$6))),"-") -> 0.17063656 | ... DI17: =IF(DI$6<Total_Lanes,900*Peak_Time_Eve*(($CN17/DI$6-1)+SQRT(($CN17/DI$6-1)^2+8*($CN17/DI$6)/(Peak_Time_Eve*$O50*DI$6))),"-") -> - | DJ17: =3600/O50 -> 2.4
H18: 11 | I18: ='Input-Detail'!E25 -> 25057278 | J18: 0.57370976 | K18: =AC18 -> 7563.4974 | L18: =AD65 -> 12.517958 | M18: =AD18 -> 29.765157 | N18: =SUM(L18:M18) -> 42.283116 | O18: =$S$34*N18 -> 10993.61 | P18: =BC65 -> 5.7189949 | Q18: =BC18 -> 20.418515 | R18: =SUM(P18:Q18) -> 26.13751 | S18: =$S$34*R18 -> 6795.7525 | V18: 11 | W18: =W$7+(W$27-W$7)*$V18/20 -> 25057278 | X18: =MIN((J17+0.05),0.95) -> 0.58173113 | Y18: ='Input-Detail'!E25/Z18 -> 10804.996 | Z18: =Z17 -> 2319.0455 | AA18: =AA17 -> 2 | AB18: =AB17 -> 0.7 | AC18: =Y18*AB18 -> 7563.4974 | AD18: =Peak_Time_Eve*$BH18*(3600/K51+BK18)/3600 -> 29.765157 | AE18: =IF(AE$6<Total_Lanes,($BI18*($CH18+BM18)+$CM18*CO18)*Peak_Time_Eve/3600,"-") -> 17034.733 | AF18: =IF(AF$6<Total_Lanes,($BI18*($CH18+BN18)+$CM18*CP18)*Peak_Time_Eve/3600,"-") -> 4129.3112 | AG18: =IF(AG$6<Total_Lanes,($BI18*($CH18+BO18)+$CM18*CQ18)*Peak_Time_Eve/3600,"-") -> 79.231012 | AH18: =IF(AH$6<Total_Lanes,($BI18*($CH18+BP18)+$CM18*CR18)*Peak_Time_Eve/3600,"-") -> 20.418515 | AI18: =IF(AI$6<Total_Lanes,($BI18*($CH18+BQ18)+$CM18*CS18)*Peak_Time_Eve/3600,"-") -> 23.584323 | AJ18: =IF(AJ$6<Total_Lanes,($BI18*($CH18+BR18)+$CM18*CT18)*Peak_Time_Eve/3600,"-") -> 116.63579 | AK18: =IF(AK$6<Total_Lanes,($BI18*($CH18+BS18)+$CM18*CU18)*Peak_Time_Eve/3600,"-") -> 1271.3053 | AL18: =IF(AL$6<Total_Lanes,($BI18*($CH18+BT18)+$CM18*CV18)*Peak_Time_Eve/3600,"-") -> 3158.6008 | ... AY18: =IF(AY$6<Total_Lanes,($BI18*($CH18+CG18)+$CM18*DI18)*Peak_Time_Eve/3600,"-") -> - | AZ18: =SUMIF(AE18:AY18,BA18,$AE$6:$AY$6) -> 4 | BA18: =MIN(AE18:AY18) -> 20.418515 | BB18: =IF((SUMIF($BM16:$CG16,$AZ18,$BM18:$CG18)+$CH18)<(SUMIF($CO16:$DI16,$AZ18,$CO18:$DI18)+$DJ18),AZ18+1,AZ18) -> 4 | BC18: =SUMIF($AE$6:$AY$6,$BB18,$AE18:$AY18) -> 20.418515 | BF18: 11 | BG18: =$X18 -> 0.58173113 | BH18: =$AC18 -> 7563.4974 | BI18: =BH18*(1-BG18) -> 3163.5755 | BJ18: =Peak_Arrival_Manual/K51 -> 5.7779192 | BK18: =900*Peak_Time_Eve*(BJ18/Total_Lanes-1+SQRT((BJ18/Total_Lanes-1)^2+8*(BJ18/Total_Lanes)/(Peak_Time_Eve*$K51*Total_Lanes))) -> 0.50866516 | BL18: =Peak_Arrival_Manual/N51 -> 5.9833319 | BM18: =IF(BM$6<Total_Lanes,900*Peak_Time_Eve*(($BL18/(Total_Lanes-BM$6))-1+SQRT((($BL18/(Total_Lanes-BM$6))-1)^2+8*($BL18/(Total_Lanes-BM$6))/(Peak_Time_Eve*$N51*(Total_Lanes-BM$6)))),"-") -> 0.73791659 | BN18: =IF(BN$6<Total_Lanes,900*Peak_Time_Eve*(($BL18/(Total_Lanes-BN$6))-1+SQRT((($BL18/(Total_Lanes-BN$6))-1)^2+8*($BL18/(Total_Lanes-BN$6))/(Peak_Time_Eve*$N51*(Total_Lanes-BN$6)))),"-") -> 1.0135385 | BO18: =IF(BO$6<Total_Lanes,900*Peak_Time_Eve*(($BL18/(Total_Lanes-BO$6))-1+SQRT((($BL18/(Total_Lanes-BO$6))-1)^2+8*($BL18/(Total_Lanes-BO$6))/(Peak_Time_Eve*$N51*(Total_Lanes-BO$6)))),"-") -> 1.498654 | BP18: =IF(BP$6<Total_Lanes,900*Peak_Time_Eve*(($BL18/(Total_Lanes-BP$6))-1+SQRT((($BL18/(Total_Lanes-BP$6))-1)^2+8*($BL18/(Total_Lanes-BP$6))/(Peak_Time_Eve*$N51*(Total_Lanes-BP$6)))),"-") -> 2.5181561 | BQ18: =IF(BQ$6<Total_Lanes,900*Peak_Time_Eve*(($BL18/(Total_Lanes-BQ$6))-1+SQRT((($BL18/(Total_Lanes-BQ$6))-1)^2+8*($BL18/(Total_Lanes-BQ$6))/(Peak_Time_Eve*$N51*(Total_Lanes-BQ$6)))),"-") -> 5.6631057 | BR18: =IF(BR$6<Total_Lanes,900*Peak_Time_Eve*(($BL18/(Total_Lanes-BR$6))-1+SQRT((($BL18/(Total_Lanes-BR$6))-1)^2+8*($BL18/(Total_Lanes-BR$6))/(Peak_Time_Eve*$N51*(Total_Lanes-BR$6)))),"-") -> 59.022263 | BS18: =IF(BS$6<Total_Lanes,900*Peak_Time_Eve*(($BL18/(Total_Lanes-BS$6))-1+SQRT((($BL18/(Total_Lanes-BS$6))-1)^2+8*($BL18/(Total_Lanes-BS$6))/(Peak_Time_Eve*$N51*(Total_Lanes-BS$6)))),"-") -> 716.19011 | BT18: =IF(BT$6<Total_Lanes,900*Peak_Time_Eve*(($BL18/(Total_Lanes-BT$6))-1+SQRT((($BL18/(Total_Lanes-BT$6))-1)^2+8*($BL18/(Total_Lanes-BT$6))/(Peak_Time_Eve*$N51*(Total_Lanes-BT$6)))),"-") -> 1790.1192 | ... CG18: =IF(CG$6<Total_Lanes,900*Peak_Time_Eve*(($BL18/(Total_Lanes-CG$6))-1+SQRT((($BL18/(Total_Lanes-CG$6))-1)^2+8*($BL18/(Total_Lanes-CG$6))/(Peak_Time_Eve*$N51*(Total_Lanes-CG$6)))),"-") -> - | CH18: =3600/N51 -> 6.80875 | CJ18: 11 | CK18: =$X18 -> 0.58173113 | CL18: =$AC18 -> 7563.4974 | CM18: =CL18*CK18 -> 4399.9219 | CN18: =CM18/O50 -> 2.9332812 | CO18: =IF(CO$6<Total_Lanes,900*Peak_Time_Eve*(($CN18/CO$6-1)+SQRT(($CN18/CO$6-1)^2+8*($CN18/CO$6)/(Peak_Time_Eve*$O51*CO$6))),"-") -> 6963.452 | CP18: =IF(CP$6<Total_Lanes,900*Peak_Time_Eve*(($CN18/CP$6-1)+SQRT(($CN18/CP$6-1)^2+8*($CN18/CP$6)/(Peak_Time_Eve*$O51*CP$6))),"-") -> 1683.6694 | CQ18: =IF(CQ$6<Total_Lanes,900*Peak_Time_Eve*(($CN18/CQ$6-1)+SQRT(($CN18/CQ$6-1)^2+8*($CN18/CQ$6)/(Peak_Time_Eve*$O51*CQ$6))),"-") -> 26.440179 | CR18: =IF(CR$6<Total_Lanes,900*Peak_Time_Eve*(($CN18/CR$6-1)+SQRT(($CN18/CR$6-1)^2+8*($CN18/CR$6)/(Peak_Time_Eve*$O51*CR$6))),"-") -> 1.6470644 | CS18: =IF(CS$6<Total_Lanes,900*Peak_Time_Eve*(($CN18/CS$6-1)+SQRT(($CN18/CS$6-1)^2+8*($CN18/CS$6)/(Peak_Time_Eve*$O51*CS$6))),"-") -> 0.68094944 | CT18: =IF(CT$6<Total_Lanes,900*Peak_Time_Eve*(($CN18/CT$6-1)+SQRT(($CN18/CT$6-1)^2+8*($CN18/CT$6)/(Peak_Time_Eve*$O51*CT$6))),"-") -> 0.38251588 | CU18: =IF(CU$6<Total_Lanes,900*Peak_Time_Eve*(($CN18/CU$6-1)+SQRT(($CN18/CU$6-1)^2+8*($CN18/CU$6)/(Peak_Time_Eve*$O51*CU$6))),"-") -> 0.24727 | CV18: =IF(CV$6<Total_Lanes,900*Peak_Time_Eve*(($CN18/CV$6-1)+SQRT(($CN18/CV$6-1)^2+8*($CN18/CV$6)/(Peak_Time_Eve*$O51*CV$6))),"-") -> 0.17366611 | ... DI18: =IF(DI$6<Total_Lanes,900*Peak_Time_Eve*(($CN18/DI$6-1)+SQRT(($CN18/DI$6-1)^2+8*($CN18/DI$6)/(Peak_Time_Eve*$O51*DI$6))),"-") -> - | DJ18: =3600/O51 -> 2.4
H19: 12 | I19: ='Input-Detail'!E26 -> 25606469 | J19: 0.61408081 | K19: =AC19 -> 7729.2699 | L19: =AD66 -> 12.805336 | M19: =AD19 -> 30.101586 | N19: =SUM(L19:M19) -> 42.906921 | O19: =$S$34*N19 -> 11155.8 | P19: =BC66 -> 5.2838108 | Q19: =BC19 -> 19.189821 | R19: =SUM(P19:Q19) -> 24.473632 | S19: =$S$34*R19 -> 6363.1443 | V19: 12 | W19: =W$7+(W$27-W$7)*$V19/20 -> 25606469 | X19: =MIN((J18+0.05),0.95) -> 0.62370976 | Y19: ='Input-Detail'!E26/Z19 -> 11041.814 | Z19: =Z18 -> 2319.0455 | AA19: =AA18 -> 2 | AB19: =AB18 -> 0.7 | AC19: =Y19*AB19 -> 7729.2699 | AD19: =Peak_Time_Eve*$BH19*(3600/K52+BK19)/3600 -> 30.101586 | AE19: =IF(AE$6<Total_Lanes,($BI19*($CH19+BM19)+$CM19*CO19)*Peak_Time_Eve/3600,"-") -> 21366.818 | AF19: =IF(AF$6<Total_Lanes,($BI19*($CH19+BN19)+$CM19*CP19)*Peak_Time_Eve/3600,"-") -> 5872.7925 | AG19: =IF(AG$6<Total_Lanes,($BI19*($CH19+BO19)+$CM19*CQ19)*Peak_Time_Eve/3600,"-") -> 731.17888 | AH19: =IF(AH$6<Total_Lanes,($BI19*($CH19+BP19)+$CM19*CR19)*Peak_Time_Eve/3600,"-") -> 20.644617 | AI19: =IF(AI$6<Total_Lanes,($BI19*($CH19+BQ19)+$CM19*CS19)*Peak_Time_Eve/3600,"-") -> 19.189821 | AJ19: =IF(AJ$6<Total_Lanes,($BI19*($CH19+BR19)+$CM19*CT19)*Peak_Time_Eve/3600,"-") -> 32.455202 | AK19: =IF(AK$6<Total_Lanes,($BI19*($CH19+BS19)+$CM19*CU19)*Peak_Time_Eve/3600,"-") -> 637.07626 | AL19: =IF(AL$6<Total_Lanes,($BI19*($CH19+BT19)+$CM19*CV19)*Peak_Time_Eve/3600,"-") -> 2229.0338 | ... AY19: =IF(AY$6<Total_Lanes,($BI19*($CH19+CG19)+$CM19*DI19)*Peak_Time_Eve/3600,"-") -> - | AZ19: =SUMIF(AE19:AY19,BA19,$AE$6:$AY$6) -> 5 | BA19: =MIN(AE19:AY19) -> 19.189821 | BB19: =IF((SUMIF($BM17:$CG17,$AZ19,$BM19:$CG19)+$CH19)<(SUMIF($CO17:$DI17,$AZ19,$CO19:$DI19)+$DJ19),AZ19+1,AZ19) -> 5 | BC19: =SUMIF($AE$6:$AY$6,$BB19,$AE19:$AY19) -> 19.189821 | BF19: 12 | BG19: =$X19 -> 0.62370976 | BH19: =$AC19 -> 7729.2699 | BI19: =BH19*(1-BG19) -> 2908.4488 | BJ19: =Peak_Arrival_Manual/K52 -> 5.3119585 | BK19: =900*Peak_Time_Eve*(BJ19/Total_Lanes-1+SQRT((BJ19/Total_Lanes-1)^2+8*(BJ19/Total_Lanes)/(Peak_Time_Eve*$K52*Total_Lanes))) -> 0.43508696 | BL19: =Peak_Arrival_Manual/N52 -> 5.5179737 | BM19: =IF(BM$6<Total_Lanes,900*Peak_Time_Eve*(($BL19/(Total_Lanes-BM$6))-1+SQRT((($BL19/(Total_Lanes-BM$6))-1)^2+8*($BL19/(Total_Lanes-BM$6))/(Peak_Time_Eve*$N52*(Total_Lanes-BM$6)))),"-") -> 0.62476302 | BN19: =IF(BN$6<Total_Lanes,900*Peak_Time_Eve*(($BL19/(Total_Lanes-BN$6))-1+SQRT((($BL19/(Total_Lanes-BN$6))-1)^2+8*($BL19/(Total_Lanes-BN$6))/(Peak_Time_Eve*$N52*(Total_Lanes-BN$6)))),"-") -> 0.84042657 | BO19: =IF(BO$6<Total_Lanes,900*Peak_Time_Eve*(($BL19/(Total_Lanes-BO$6))-1+SQRT((($BL19/(Total_Lanes-BO$6))-1)^2+8*($BL19/(Total_Lanes-BO$6))/(Peak_Time_Eve*$N52*(Total_Lanes-BO$6)))),"-") -> 1.201576 | BP19: =IF(BP$6<Total_Lanes,900*Peak_Time_Eve*(($BL19/(Total_Lanes-BP$6))-1+SQRT((($BL19/(Total_Lanes-BP$6))-1)^2+8*($BL19/(Total_Lanes-BP$6))/(Peak_Time_Eve*$N52*(Total_Lanes-BP$6)))),"-") -> 1.8948193 | BQ19: =IF(BQ$6<Total_Lanes,900*Peak_Time_Eve*(($BL19/(Total_Lanes-BQ$6))-1+SQRT((($BL19/(Total_Lanes-BQ$6))-1)^2+8*($BL19/(Total_Lanes-BQ$6))/(Peak_Time_Eve*$N52*(Total_Lanes-BQ$6)))),"-") -> 3.6156885 | BR19: =IF(BR$6<Total_Lanes,900*Peak_Time_Eve*(($BL19/(Total_Lanes-BR$6))-1+SQRT((($BL19/(Total_Lanes-BR$6))-1)^2+8*($BL19/(Total_Lanes-BR$6))/(Peak_Time_Eve*$N52*(Total_Lanes-BR$6)))),"-") -> 12.491498 | BS19: =IF(BS$6<Total_Lanes,900*Peak_Time_Eve*(($BL19/(Total_Lanes-BS$6))-1+SQRT((($BL19/(Total_Lanes-BS$6))-1)^2+8*($BL19/(Total_Lanes-BS$6))/(Peak_Time_Eve*$N52*(Total_Lanes-BS$6)))),"-") -> 386.96564 | BT19: =IF(BT$6<Total_Lanes,900*Peak_Time_Eve*(($BL19/(Total_Lanes-BT$6))-1+SQRT((($BL19/(Total_Lanes-BT$6))-1)^2+8*($BL19/(Total_Lanes-BT$6))/(Peak_Time_Eve*$N52*(Total_Lanes-BT$6)))),"-") -> 1372.3553 | ... CG19: =IF(CG$6<Total_Lanes,900*Peak_Time_Eve*(($BL19/(Total_Lanes-CG$6))-1+SQRT((($BL19/(Total_Lanes-CG$6))-1)^2+8*($BL19/(Total_Lanes-CG$6))/(Peak_Time_Eve*$N52*(Total_Lanes-CG$6)))),"-") -> - | CH19: =3600/N52 -> 6.83 | CJ19: 12 | CK19: =$X19 -> 0.62370976 | CL19: =$AC19 -> 7729.2699 | CM19: =CL19*CK19 -> 4820.8211 | CN19: =CM19/O51 -> 3.2138807 | CO19: =IF(CO$6<Total_Lanes,900*Peak_Time_Eve*(($CN19/CO$6-1)+SQRT(($CN19/CO$6-1)^2+8*($CN19/CO$6)/(Peak_Time_Eve*$O52*CO$6))),"-") -> 7973.4532 | CP19: =IF(CP$6<Total_Lanes,900*Peak_Time_Eve*(($CN19/CP$6-1)+SQRT(($CN19/CP$6-1)^2+8*($CN19/CP$6)/(Peak_Time_Eve*$O52*CP$6))),"-") -> 2188.1578 | CQ19: =IF(CQ$6<Total_Lanes,900*Peak_Time_Eve*(($CN19/CQ$6-1)+SQRT(($CN19/CQ$6-1)^2+8*($CN19/CQ$6)/(Peak_Time_Eve*$O52*CQ$6))),"-") -> 268.16232 | CR19: =IF(CR$6<Total_Lanes,900*Peak_Time_Eve*(($CN19/CR$6-1)+SQRT(($CN19/CR$6-1)^2+8*($CN19/CR$6)/(Peak_Time_Eve*$O52*CR$6))),"-") -> 2.4445257 | CS19: =IF(CS$6<Total_Lanes,900*Peak_Time_Eve*(($CN19/CS$6-1)+SQRT(($CN19/CS$6-1)^2+8*($CN19/CS$6)/(Peak_Time_Eve*$O52*CS$6))),"-") -> 0.86311597 | CT19: =IF(CT$6<Total_Lanes,900*Peak_Time_Eve*(($CN19/CT$6-1)+SQRT(($CN19/CT$6-1)^2+8*($CN19/CT$6)/(Peak_Time_Eve*$O52*CT$6))),"-") -> 0.46128594 | CU19: =IF(CU$6<Total_Lanes,900*Peak_Time_Eve*(($CN19/CU$6-1)+SQRT(($CN19/CU$6-1)^2+8*($CN19/CU$6)/(Peak_Time_Eve*$O52*CU$6))),"-") -> 0.29099382 | CV19: =IF(CV$6<Total_Lanes,900*Peak_Time_Eve*(($CN19/CV$6-1)+SQRT(($CN19/CV$6-1)^2+8*($CN19/CV$6)/(Peak_Time_Eve*$O52*CV$6))),"-") -> 0.20143126 | ... DI19: =IF(DI$6<Total_Lanes,900*Peak_Time_Eve*(($CN19/DI$6-1)+SQRT(($CN19/DI$6-1)^2+8*($CN19/DI$6)/(Peak_Time_Eve*$O52*DI$6))),"-") -> - | DJ19: =3600/O52 -> 2.4
H20: 13 | I20: ='Input-Detail'!E27 -> 26155661 | J20: 0.65237714 | K20: =AC20 -> 7895.0424 | L20: =AD67 -> 13.094223 | M20: =AD20 -> 30.465204 | N20: =SUM(L20:M20) -> 43.559428 | O20: =$S$34*N20 -> 11325.451 | P20: =BC67 -> 4.8588595 | Q20: =BC20 -> 17.056951 | R20: =SUM(P20:Q20) -> 21.91581 | S20: =$S$34*R20 -> 5698.1107 | V20: 13 | W20: =W$7+(W$27-W$7)*$V20/20 -> 26155661 | X20: =MIN((J19+0.05),0.95) -> 0.66408081 | Y20: ='Input-Detail'!E27/Z20 -> 11278.632 | Z20: =Z19 -> 2319.0455 | AA20: =AA19 -> 2 | AB20: =AB19 -> 0.7 | AC20: =Y20*AB20 -> 7895.0424 | AD20: =Peak_Time_Eve*$BH20*(3600/K53+BK20)/3600 -> 30.465204 | AE20: =IF(AE$6<Total_Lanes,($BI20*($CH20+BM20)+$CM20*CO20)*Peak_Time_Eve/3600,"-") -> 26186.081 | AF20: =IF(AF$6<Total_Lanes,($BI20*($CH20+BN20)+$CM20*CP20)*Peak_Time_Eve/3600,"-") -> 7859.0486 | AG20: =IF(AG$6<Total_Lanes,($BI20*($CH20+BO20)+$CM20*CQ20)*Peak_Time_Eve/3600,"-") -> 1759.0285 | AH20: =IF(AH$6<Total_Lanes,($BI20*($CH20+BP20)+$CM20*CR20)*Peak_Time_Eve/3600,"-") -> 24.2436 | AI20: =IF(AI$6<Total_Lanes,($BI20*($CH20+BQ20)+$CM20*CS20)*Peak_Time_Eve/3600,"-") -> 17.056951 | AJ20: =IF(AJ$6<Total_Lanes,($BI20*($CH20+BR20)+$CM20*CT20)*Peak_Time_Eve/3600,"-") -> 20.54042 | AK20: =IF(AK$6<Total_Lanes,($BI20*($CH20+BS20)+$CM20*CU20)*Peak_Time_Eve/3600,"-") -> 143.11492 | AL20: =IF(AL$6<Total_Lanes,($BI20*($CH20+BT20)+$CM20*CV20)*Peak_Time_Eve/3600,"-") -> 1411.5616 | ... AY20: =IF(AY$6<Total_Lanes,($BI20*($CH20+CG20)+$CM20*DI20)*Peak_Time_Eve/3600,"-") -> - | AZ20: =SUMIF(AE20:AY20,BA20,$AE$6:$AY$6) -> 5 | BA20: =MIN(AE20:AY20) -> 17.056951 | BB20: =IF((SUMIF($BM18:$CG18,$AZ20,$BM20:$CG20)+$CH20)<(SUMIF($CO18:$DI18,$AZ20,$CO20:$DI20)+$DJ20),AZ20+1,AZ20) -> 5 | BC20: =SUMIF($AE$6:$AY$6,$BB20,$AE20:$AY20) -> 17.056951 | BF20: 13 | BG20: =$X20 -> 0.66408081 | BH20: =$AC20 -> 7895.0424 | BI20: =BH20*(1-BG20) -> 2652.0962 | BJ20: =Peak_Arrival_Manual/K53 -> 4.8437591 | BK20: =900*Peak_Time_Eve*(BJ20/Total_Lanes-1+SQRT((BJ20/Total_Lanes-1)^2+8*(BJ20/Total_Lanes)/(Peak_Time_Eve*$K53*Total_Lanes))) -> 0.37079775 | BL20: =Peak_Arrival_Manual/N53 -> 5.0472706 | BM20: =IF(BM$6<Total_Lanes,900*Peak_Time_Eve*(($BL20/(Total_Lanes-BM$6))-1+SQRT((($BL20/(Total_Lanes-BM$6))-1)^2+8*($BL20/(Total_Lanes-BM$6))/(Peak_Time_Eve*$N53*(Total_Lanes-BM$6)))),"-") -> 0.52795864 | BN20: =IF(BN$6<Total_Lanes,900*Peak_Time_Eve*(($BL20/(Total_Lanes-BN$6))-1+SQRT((($BL20/(Total_Lanes-BN$6))-1)^2+8*($BL20/(Total_Lanes-BN$6))/(Peak_Time_Eve*$N53*(Total_Lanes-BN$6)))),"-") -> 0.69792996 | BO20: =IF(BO$6<Total_Lanes,900*Peak_Time_Eve*(($BL20/(Total_Lanes-BO$6))-1+SQRT((($BL20/(Total_Lanes-BO$6))-1)^2+8*($BL20/(Total_Lanes-BO$6))/(Peak_Time_Eve*$N53*(Total_Lanes-BO$6)))),"-") -> 0.97144913 | BP20: =IF(BP$6<Total_Lanes,900*Peak_Time_Eve*(($BL20/(Total_Lanes-BP$6))-1+SQRT((($BL20/(Total_Lanes-BP$6))-1)^2+8*($BL20/(Total_Lanes-BP$6))/(Peak_Time_Eve*$N53*(Total_Lanes-BP$6)))),"-") -> 1.4622953 | BQ20: =IF(BQ$6<Total_Lanes,900*Peak_Time_Eve*(($BL20/(Total_Lanes-BQ$6))-1+SQRT((($BL20/(Total_Lanes-BQ$6))-1)^2+8*($BL20/(Total_Lanes-BQ$6))/(Peak_Time_Eve*$N53*(Total_Lanes-BQ$6)))),"-") -> 2.5234599 | BR20: =IF(BR$6<Total_Lanes,900*Peak_Time_Eve*(($BL20/(Total_Lanes-BR$6))-1+SQRT((($BL20/(Total_Lanes-BR$6))-1)^2+8*($BL20/(Total_Lanes-BR$6))/(Peak_Time_Eve*$N53*(Total_Lanes-BR$6)))),"-") -> 5.9866105 | BS20: =IF(BS$6<Total_Lanes,900*Peak_Time_Eve*(($BL20/(Total_Lanes-BS$6))-1+SQRT((($BL20/(Total_Lanes-BS$6))-1)^2+8*($BL20/(Total_Lanes-BS$6))/(Peak_Time_Eve*$N53*(Total_Lanes-BS$6)))),"-") -> 89.606197 | BT20: =IF(BT$6<Total_Lanes,900*Peak_Time_Eve*(($BL20/(Total_Lanes-BT$6))-1+SQRT((($BL20/(Total_Lanes-BT$6))-1)^2+8*($BL20/(Total_Lanes-BT$6))/(Peak_Time_Eve*$N53*(Total_Lanes-BT$6)))),"-") -> 950.72733 | ... CG20: =IF(CG$6<Total_Lanes,900*Peak_Time_Eve*(($BL20/(Total_Lanes-CG$6))-1+SQRT((($BL20/(Total_Lanes-CG$6))-1)^2+8*($BL20/(Total_Lanes-CG$6))/(Peak_Time_Eve*$N53*(Total_Lanes-CG$6)))),"-") -> - | CH20: =3600/N53 -> 6.85125 | CJ20: 13 | CK20: =$X20 -> 0.66408081 | CL20: =$AC20 -> 7895.0424 | CM20: =CL20*CK20 -> 5242.9461 | CN20: =CM20/O52 -> 3.4952974 | CO20: =IF(CO$6<Total_Lanes,900*Peak_Time_Eve*(($CN20/CO$6-1)+SQRT(($CN20/CO$6-1)^2+8*($CN20/CO$6)/(Peak_Time_Eve*$O53*CO$6))),"-") -> 8986.4313 | CP20: =IF(CP$6<Total_Lanes,900*Peak_Time_Eve*(($CN20/CP$6-1)+SQRT(($CN20/CP$6-1)^2+8*($CN20/CP$6)/(Peak_Time_Eve*$O53*CP$6))),"-") -> 2694.3375 | CQ20: =IF(CQ$6<Total_Lanes,900*Peak_Time_Eve*(($CN20/CQ$6-1)+SQRT(($CN20/CQ$6-1)^2+8*($CN20/CQ$6)/(Peak_Time_Eve*$O53*CQ$6))),"-") -> 599.94986 | CR20: =IF(CR$6<Total_Lanes,900*Peak_Time_Eve*(($CN20/CR$6-1)+SQRT(($CN20/CR$6-1)^2+8*($CN20/CR$6)/(Peak_Time_Eve*$O53*CR$6))),"-") -> 4.1179438 | CS20: =IF(CS$6<Total_Lanes,900*Peak_Time_Eve*(($CN20/CS$6-1)+SQRT(($CN20/CS$6-1)^2+8*($CN20/CS$6)/(Peak_Time_Eve*$O53*CS$6))),"-") -> 1.1138544 | CT20: =IF(CT$6<Total_Lanes,900*Peak_Time_Eve*(($CN20/CT$6-1)+SQRT(($CN20/CT$6-1)^2+8*($CN20/CT$6)/(Peak_Time_Eve*$O53*CT$6))),"-") -> 0.55799042 | CU20: =IF(CU$6<Total_Lanes,900*Peak_Time_Eve*(($CN20/CU$6-1)+SQRT(($CN20/CU$6-1)^2+8*($CN20/CU$6)/(Peak_Time_Eve*$O53*CU$6))),"-") -> 0.34187221 | CV20: =IF(CV$6<Total_Lanes,900*Peak_Time_Eve*(($CN20/CV$6-1)+SQRT(($CN20/CV$6-1)^2+8*($CN20/CV$6)/(Peak_Time_Eve*$O53*CV$6))),"-") -> 0.23274985 | ... DI20: =IF(DI$6<Total_Lanes,900*Peak_Time_Eve*(($CN20/DI$6-1)+SQRT(($CN20/DI$6-1)^2+8*($CN20/DI$6)/(Peak_Time_Eve*$O53*DI$6))),"-") -> - | DJ20: =3600/O53 -> 2.4
H21: 14 | I21: ='Input-Detail'!E28 -> 26704852 | J21: 0.68856029 | K21: =AC21 -> 8060.8149 | L21: =AD68 -> 13.385071 | M21: =AD21 -> 30.855405 | N21: =SUM(L21:M21) -> 44.240476 | O21: =$S$34*N21 -> 11502.524 | P21: =BC68 -> 4.4426932 | Q21: =BC21 -> 16.195004 | R21: =SUM(P21:Q21) -> 20.637697 | S21: =$S$34*R21 -> 5365.8013 | V21: 14 | W21: =W$7+(W$27-W$7)*$V21/20 -> 26704852 | X21: =MIN((J20+0.05),0.95) -> 0.70237714 | Y21: ='Input-Detail'!E28/Z21 -> 11515.45 | Z21: =Z20 -> 2319.0455 | AA21: =AA20 -> 2 | AB21: =AB20 -> 0.7 | AC21: =Y21*AB21 -> 8060.8149 | AD21: =Peak_Time_Eve*$BH21*(3600/K54+BK21)/3600 -> 30.855405 | AE21: =IF(AE$6<Total_Lanes,($BI21*($CH21+BM21)+$CM21*CO21)*Peak_Time_Eve/3600,"-") -> 31436.836 | AF21: =IF(AF$6<Total_Lanes,($BI21*($CH21+BN21)+$CM21*CP21)*Peak_Time_Eve/3600,"-") -> 10064.632 | AG21: =IF(AG$6<Total_Lanes,($BI21*($CH21+BO21)+$CM21*CQ21)*Peak_Time_Eve/3600,"-") -> 2945.7222 | AH21: =IF(AH$6<Total_Lanes,($BI21*($CH21+BP21)+$CM21*CR21)*Peak_Time_Eve/3600,"-") -> 40.854451 | AI21: =IF(AI$6<Total_Lanes,($BI21*($CH21+BQ21)+$CM21*CS21)*Peak_Time_Eve/3600,"-") -> 16.274816 | AJ21: =IF(AJ$6<Total_Lanes,($BI21*($CH21+BR21)+$CM21*CT21)*Peak_Time_Eve/3600,"-") -> 16.195004 | AK21: =IF(AK$6<Total_Lanes,($BI21*($CH21+BS21)+$CM21*CU21)*Peak_Time_Eve/3600,"-") -> 29.492106 | AL21: =IF(AL$6<Total_Lanes,($BI21*($CH21+BT21)+$CM21*CV21)*Peak_Time_Eve/3600,"-") -> 723.27328 | ... AY21: =IF(AY$6<Total_Lanes,($BI21*($CH21+CG21)+$CM21*DI21)*Peak_Time_Eve/3600,"-") -> - | AZ21: =SUMIF(AE21:AY21,BA21,$AE$6:$AY$6) -> 6 | BA21: =MIN(AE21:AY21) -> 16.195004 | BB21: =IF((SUMIF($BM19:$CG19,$AZ21,$BM21:$CG21)+$CH21)<(SUMIF($CO19:$DI19,$AZ21,$CO21:$DI21)+$DJ21),AZ21+1,AZ21) -> 6 | BC21: =SUMIF($AE$6:$AY$6,$BB21,$AE21:$AY21) -> 16.195004 | BF21: 14 | BG21: =$X21 -> 0.70237714 | BH21: =$AC21 -> 8060.8149 | BI21: =BH21*(1-BG21) -> 2399.0828 | BJ21: =Peak_Arrival_Manual/K54 -> 4.3816581 | BK21: =900*Peak_Time_Eve*(BJ21/Total_Lanes-1+SQRT((BJ21/Total_Lanes-1)^2+8*(BJ21/Total_Lanes)/(Peak_Time_Eve*$K54*Total_Lanes))) -> 0.31508858 | BL21: =Peak_Arrival_Manual/N54 -> 4.5799156 | BM21: =IF(BM$6<Total_Lanes,900*Peak_Time_Eve*(($BL21/(Total_Lanes-BM$6))-1+SQRT((($BL21/(Total_Lanes-BM$6))-1)^2+8*($BL21/(Total_Lanes-BM$6))/(Peak_Time_Eve*$N54*(Total_Lanes-BM$6)))),"-") -> 0.44560157 | BN21: =IF(BN$6<Total_Lanes,900*Peak_Time_Eve*(($BL21/(Total_Lanes-BN$6))-1+SQRT((($BL21/(Total_Lanes-BN$6))-1)^2+8*($BL21/(Total_Lanes-BN$6))/(Peak_Time_Eve*$N54*(Total_Lanes-BN$6)))),"-") -> 0.58054646 | BO21: =IF(BO$6<Total_Lanes,900*Peak_Time_Eve*(($BL21/(Total_Lanes-BO$6))-1+SQRT((($BL21/(Total_Lanes-BO$6))-1)^2+8*($BL21/(Total_Lanes-BO$6))/(Peak_Time_Eve*$N54*(Total_Lanes-BO$6)))),"-") -> 0.7908697 | BP21: =IF(BP$6<Total_Lanes,900*Peak_Time_Eve*(($BL21/(Total_Lanes-BP$6))-1+SQRT((($BL21/(Total_Lanes-BP$6))-1)^2+8*($BL21/(Total_Lanes-BP$6))/(Peak_Time_Eve*$N54*(Total_Lanes-BP$6)))),"-") -> 1.1495323 | BQ21: =IF(BQ$6<Total_Lanes,900*Peak_Time_Eve*(($BL21/(Total_Lanes-BQ$6))-1+SQRT((($BL21/(Total_Lanes-BQ$6))-1)^2+8*($BL21/(Total_Lanes-BQ$6))/(Peak_Time_Eve*$N54*(Total_Lanes-BQ$6)))),"-") -> 1.8552259 | BR21: =IF(BR$6<Total_Lanes,900*Peak_Time_Eve*(($BL21/(Total_Lanes-BR$6))-1+SQRT((($BL21/(Total_Lanes-BR$6))-1)^2+8*($BL21/(Total_Lanes-BR$6))/(Peak_Time_Eve*$N54*(Total_Lanes-BR$6)))),"-") -> 3.6782062 | BS21: =IF(BS$6<Total_Lanes,900*Peak_Time_Eve*(($BL21/(Total_Lanes-BS$6))-1+SQRT((($BL21/(Total_Lanes-BS$6))-1)^2+8*($BL21/(Total_Lanes-BS$6))/(Peak_Time_Eve*$N54*(Total_Lanes-BS$6)))),"-") -> 14.308425 | BT21: =IF(BT$6<Total_Lanes,900*Peak_Time_Eve*(($BL21/(Total_Lanes-BT$6))-1+SQRT((($BL21/(Total_Lanes-BT$6))-1)^2+8*($BL21/(Total_Lanes-BT$6))/(Peak_Time_Eve*$N54*(Total_Lanes-BT$6)))),"-") -> 535.15753 | ... CG21: =IF(CG$6<Total_Lanes,900*Peak_Time_Eve*(($BL21/(Total_Lanes-CG$6))-1+SQRT((($BL21/(Total_Lanes-CG$6))-1)^2+8*($BL21/(Total_Lanes-CG$6))/(Peak_Time_Eve*$N54*(Total_Lanes-CG$6)))),"-") -> - | CH21: =3600/N54 -> 6.8725 | CJ21: 14 | CK21: =$X21 -> 0.70237714 | CL21: =$AC21 -> 8060.8149 | CM21: =CL21*CK21 -> 5661.7321 | CN21: =CM21/O53 -> 3.7744881 | CO21: =IF(CO$6<Total_Lanes,900*Peak_Time_Eve*(($CN21/CO$6-1)+SQRT(($CN21/CO$6-1)^2+8*($CN21/CO$6)/(Peak_Time_Eve*$O54*CO$6))),"-") -> 9991.421 | CP21: =IF(CP$6<Total_Lanes,900*Peak_Time_Eve*(($CN21/CP$6-1)+SQRT(($CN21/CP$6-1)^2+8*($CN21/CP$6)/(Peak_Time_Eve*$O54*CP$6))),"-") -> 3196.629 | CQ21: =IF(CQ$6<Total_Lanes,900*Peak_Time_Eve*(($CN21/CQ$6-1)+SQRT(($CN21/CQ$6-1)^2+8*($CN21/CQ$6)/(Peak_Time_Eve*$O54*CQ$6))),"-") -> 933.26828 | CR21: =IF(CR$6<Total_Lanes,900*Peak_Time_Eve*(($CN21/CR$6-1)+SQRT(($CN21/CR$6-1)^2+8*($CN21/CR$6)/(Peak_Time_Eve*$O54*CR$6))),"-") -> 9.5893785 | CS21: =IF(CS$6<Total_Lanes,900*Peak_Time_Eve*(($CN21/CS$6-1)+SQRT(($CN21/CS$6-1)^2+8*($CN21/CS$6)/(Peak_Time_Eve*$O54*CS$6))),"-") -> 1.4758966 | CT21: =IF(CT$6<Total_Lanes,900*Peak_Time_Eve*(($CN21/CT$6-1)+SQRT(($CN21/CT$6-1)^2+8*($CN21/CT$6)/(Peak_Time_Eve*$O54*CT$6))),"-") -> 0.67805925 | CU21: =IF(CU$6<Total_Lanes,900*Peak_Time_Eve*(($CN21/CU$6-1)+SQRT(($CN21/CU$6-1)^2+8*($CN21/CU$6)/(Peak_Time_Eve*$O54*CU$6))),"-") -> 0.4011138 | CV21: =IF(CV$6<Total_Lanes,900*Peak_Time_Eve*(($CN21/CV$6-1)+SQRT(($CN21/CV$6-1)^2+8*($CN21/CV$6)/(Peak_Time_Eve*$O54*CV$6))),"-") -> 0.26794076 | ... DI21: =IF(DI$6<Total_Lanes,900*Peak_Time_Eve*(($CN21/DI$6-1)+SQRT(($CN21/DI$6-1)^2+8*($CN21/DI$6)/(Peak_Time_Eve*$O54*DI$6))),"-") -> - | DJ21: =3600/O54 -> 2.4
H22: 15 | I22: ='Input-Detail'!E29 -> 27254043 | J22: 0.72219474 | K22: =AC22 -> 8226.5874 | L22: =AD69 -> 13.67799 | M22: =AD22 -> 31.26839 | N22: =SUM(L22:M22) -> 44.94638 | O22: =$S$34*N22 -> 11686.059 | P22: =BC69 -> 4.0109284 | Q22: =BC22 -> 14.03906 | R22: =SUM(P22:Q22) -> 18.049989 | S22: =$S$34*R22 -> 4692.9971 | V22: 15 | W22: =W$7+(W$27-W$7)*$V22/20 -> 27254043 | X22: =MIN((J21+0.05),0.95) -> 0.73856029 | Y22: ='Input-Detail'!E29/Z22 -> 11752.268 | Z22: =Z21 -> 2319.0455 | AA22: =AA21 -> 2 | AB22: =AB21 -> 0.7 | AC22: =Y22*AB22 -> 8226.5874 | AD22: =Peak_Time_Eve*$BH22*(3600/K55+BK22)/3600 -> 31.26839 | AE22: =IF(AE$6<Total_Lanes,($BI22*($CH22+BM22)+$CM22*CO22)*Peak_Time_Eve/3600,"-") -> 37088.736 | AF22: =IF(AF$6<Total_Lanes,($BI22*($CH22+BN22)+$CM22*CP22)*Peak_Time_Eve/3600,"-") -> 12475.628 | AG22: =IF(AG$6<Total_Lanes,($BI22*($CH22+BO22)+$CM22*CQ22)*Peak_Time_Eve/3600,"-") -> 4274.7202 | AH22: =IF(AH$6<Total_Lanes,($BI22*($CH22+BP22)+$CM22*CR22)*Peak_Time_Eve/3600,"-") -> 261.66902 | AI22: =IF(AI$6<Total_Lanes,($BI22*($CH22+BQ22)+$CM22*CS22)*Peak_Time_Eve/3600,"-") -> 16.809092 | AJ22: =IF(AJ$6<Total_Lanes,($BI22*($CH22+BR22)+$CM22*CT22)*Peak_Time_Eve/3600,"-") -> 14.03906 | AK22: =IF(AK$6<Total_Lanes,($BI22*($CH22+BS22)+$CM22*CU22)*Peak_Time_Eve/3600,"-") -> 17.446887 | AL22: =IF(AL$6<Total_Lanes,($BI22*($CH22+BT22)+$CM22*CV22)*Peak_Time_Eve/3600,"-") -> 187.83843 | ... AY22: =IF(AY$6<Total_Lanes,($BI22*($CH22+CG22)+$CM22*DI22)*Peak_Time_Eve/3600,"-") -> - | AZ22: =SUMIF(AE22:AY22,BA22,$AE$6:$AY$6) -> 6 | BA22: =MIN(AE22:AY22) -> 14.03906 | BB22: =IF((SUMIF($BM20:$CG20,$AZ22,$BM22:$CG22)+$CH22)<(SUMIF($CO20:$DI20,$AZ22,$CO22:$DI22)+$DJ22),AZ22+1,AZ22) -> 6 | BC22: =SUMIF($AE$6:$AY$6,$BB22,$AE22:$AY22) -> 14.03906 | BF22: 15 | BG22: =$X22 -> 0.73856029 | BH22: =$AC22 -> 8226.5874 | BI22: =BH22*(1-BG22) -> 2150.7566 | BJ22: =Peak_Arrival_Manual/K55 -> 3.9281179 | BK22: =900*Peak_Time_Eve*(BJ22/Total_Lanes-1+SQRT((BJ22/Total_Lanes-1)^2+8*(BJ22/Total_Lanes)/(Peak_Time_Eve*$K55*Total_Lanes))) -> 0.26660999 | BL22: =Peak_Arrival_Manual/N55 -> 4.1185495 | BM22: =IF(BM$6<Total_Lanes,900*Peak_Time_Eve*(($BL22/(Total_Lanes-BM$6))-1+SQRT((($BL22/(Total_Lanes-BM$6))-1)^2+8*($BL22/(Total_Lanes-BM$6))/(Peak_Time_Eve*$N55*(Total_Lanes-BM$6)))),"-") -> 0.37502035 | BN22: =IF(BN$6<Total_Lanes,900*Peak_Time_Eve*(($BL22/(Total_Lanes-BN$6))-1+SQRT((($BL22/(Total_Lanes-BN$6))-1)^2+8*($BL22/(Total_Lanes-BN$6))/(Peak_Time_Eve*$N55*(Total_Lanes-BN$6)))),"-") -> 0.48263231 | BO22: =IF(BO$6<Total_Lanes,900*Peak_Time_Eve*(($BL22/(Total_Lanes-BO$6))-1+SQRT((($BL22/(Total_Lanes-BO$6))-1)^2+8*($BL22/(Total_Lanes-BO$6))/(Peak_Time_Eve*$N55*(Total_Lanes-BO$6)))),"-") -> 0.64604795 | BP22: =IF(BP$6<Total_Lanes,900*Peak_Time_Eve*(($BL22/(Total_Lanes-BP$6))-1+SQRT((($BL22/(Total_Lanes-BP$6))-1)^2+8*($BL22/(Total_Lanes-BP$6))/(Peak_Time_Eve*$N55*(Total_Lanes-BP$6)))),"-") -> 0.91387883 | BQ22: =IF(BQ$6<Total_Lanes,900*Peak_Time_Eve*(($BL22/(Total_Lanes-BQ$6))-1+SQRT((($BL22/(Total_Lanes-BQ$6))-1)^2+8*($BL22/(Total_Lanes-BQ$6))/(Peak_Time_Eve*$N55*(Total_Lanes-BQ$6)))),"-") -> 1.4063023 | BR22: =IF(BR$6<Total_Lanes,900*Peak_Time_Eve*(($BL22/(Total_Lanes-BR$6))-1+SQRT((($BL22/(Total_Lanes-BR$6))-1)^2+8*($BL22/(Total_Lanes-BR$6))/(Peak_Time_Eve*$N55*(Total_Lanes-BR$6)))),"-") -> 2.5095243 | BS22: =IF(BS$6<Total_Lanes,900*Peak_Time_Eve*(($BL22/(Total_Lanes-BS$6))-1+SQRT((($BL22/(Total_Lanes-BS$6))-1)^2+8*($BL22/(Total_Lanes-BS$6))/(Peak_Time_Eve*$N55*(Total_Lanes-BS$6)))),"-") -> 6.3780674 | BT22: =IF(BT$6<Total_Lanes,900*Peak_Time_Eve*(($BL22/(Total_Lanes-BT$6))-1+SQRT((($BL22/(Total_Lanes-BT$6))-1)^2+8*($BL22/(Total_Lanes-BT$6))/(Peak_Time_Eve*$N55*(Total_Lanes-BT$6)))),"-") -> 149.44197 | ... CG22: =IF(CG$6<Total_Lanes,900*Peak_Time_Eve*(($BL22/(Total_Lanes-CG$6))-1+SQRT((($BL22/(Total_Lanes-CG$6))-1)^2+8*($BL22/(Total_Lanes-CG$6))/(Peak_Time_Eve*$N55*(Total_Lanes-CG$6)))),"-") -> - | CH22: =3600/N55 -> 6.89375 | CJ22: 15 | CK22: =$X22 -> 0.73856029 | CL22: =$AC22 -> 8226.5874 | CM22: =CL22*CK22 -> 6075.8308 | CN22: =CM22/O54 -> 4.0505538 | CO22: =IF(CO$6<Total_Lanes,900*Peak_Time_Eve*(($CN22/CO$6-1)+SQRT(($CN22/CO$6-1)^2+8*($CN22/CO$6)/(Peak_Time_Eve*$O55*CO$6))),"-") -> 10985.18 | CP22: =IF(CP$6<Total_Lanes,900*Peak_Time_Eve*(($CN22/CP$6-1)+SQRT(($CN22/CP$6-1)^2+8*($CN22/CP$6)/(Peak_Time_Eve*$O55*CP$6))),"-") -> 3693.3658 | CQ22: =IF(CQ$6<Total_Lanes,900*Peak_Time_Eve*(($CN22/CQ$6-1)+SQRT(($CN22/CQ$6-1)^2+8*($CN22/CQ$6)/(Peak_Time_Eve*$O55*CQ$6))),"-") -> 1263.7416 | CR22: =IF(CR$6<Total_Lanes,900*Peak_Time_Eve*(($CN22/CR$6-1)+SQRT(($CN22/CR$6-1)^2+8*($CN22/CR$6)/(Peak_Time_Eve*$O55*CR$6))),"-") -> 74.757172 | CS22: =IF(CS$6<Total_Lanes,900*Peak_Time_Eve*(($CN22/CS$6-1)+SQRT(($CN22/CS$6-1)^2+8*($CN22/CS$6)/(Peak_Time_Eve*$O55*CS$6))),"-") -> 2.0416916 | CT22: =IF(CT$6<Total_Lanes,900*Peak_Time_Eve*(($CN22/CT$6-1)+SQRT(($CN22/CT$6-1)^2+8*($CN22/CT$6)/(Peak_Time_Eve*$O55*CT$6))),"-") -> 0.83052917 | CU22: =IF(CU$6<Total_Lanes,900*Peak_Time_Eve*(($CN22/CU$6-1)+SQRT(($CN22/CU$6-1)^2+8*($CN22/CU$6)/(Peak_Time_Eve*$O55*CU$6))),"-") -> 0.47070888 | CV22: =IF(CV$6<Total_Lanes,900*Peak_Time_Eve*(($CN22/CV$6-1)+SQRT(($CN22/CV$6-1)^2+8*($CN22/CV$6)/(Peak_Time_Eve*$O55*CV$6))),"-") -> 0.30762689 | ... DI22: =IF(DI$6<Total_Lanes,900*Peak_Time_Eve*(($CN22/DI$6-1)+SQRT(($CN22/DI$6-1)^2+8*($CN22/DI$6)/(Peak_Time_Eve*$O55*DI$6))),"-") -> - | DJ22: =3600/O55 -> 2.4
H23: 16 | I23: ='Input-Detail'!E30 -> 27803235 | J23: 0.75320595 | K23: =AC23 -> 8392.3598 | L23: =AD70 -> 13.9734 | M23: =AD23 -> 31.703731 | N23: =SUM(L23:M23) -> 45.677131 | O23: =$S$34*N23 -> 11876.054 | P23: =BC70 -> 3.6096481 | Q23: =BC23 -> 12.973759 | R23: =SUM(P23:Q23) -> 16.583407 | S23: =$S$34*R23 -> 4311.6859 | V23: 16 | W23: =W$7+(W$27-W$7)*$V23/20 -> 27803235 | X23: =MIN((J22+0.05),0.95) -> 0.77219474 | Y23: ='Input-Detail'!E30/Z23 -> 11989.085 | Z23: =Z22 -> 2319.0455 | AA23: =AA22 -> 2 | AB23: =AB22 -> 0.7 | AC23: =Y23*AB23 -> 8392.3598 | AD23: =Peak_Time_Eve*$BH23*(3600/K56+BK23)/3600 -> 31.703731 | AE23: =IF(AE$6<Total_Lanes,($BI23*($CH23+BM23)+$CM23*CO23)*Peak_Time_Eve/3600,"-") -> 43054.311 | AF23: =IF(AF$6<Total_Lanes,($BI23*($CH23+BN23)+$CM23*CP23)*Peak_Time_Eve/3600,"-") -> 15052.971 | AG23: =IF(AG$6<Total_Lanes,($BI23*($CH23+BO23)+$CM23*CQ23)*Peak_Time_Eve/3600,"-") -> 5721.7318 | AH23: =IF(AH$6<Total_Lanes,($BI23*($CH23+BP23)+$CM23*CR23)*Peak_Time_Eve/3600,"-") -> 1074.5248 | AI23: =IF(AI$6<Total_Lanes,($BI23*($CH23+BQ23)+$CM23*CS23)*Peak_Time_Eve/3600,"-") -> 19.419544 | AJ23: =IF(AJ$6<Total_Lanes,($BI23*($CH23+BR23)+$CM23*CT23)*Peak_Time_Eve/3600,"-") -> 12.973759 | AK23: =IF(AK$6<Total_Lanes,($BI23*($CH23+BS23)+$CM23*CU23)*Peak_Time_Eve/3600,"-") -> 13.380727 | AL23: =IF(AL$6<Total_Lanes,($BI23*($CH23+BT23)+$CM23*CV23)*Peak_Time_Eve/3600,"-") -> 27.989872 | ... AY23: =IF(AY$6<Total_Lanes,($BI23*($CH23+CG23)+$CM23*DI23)*Peak_Time_Eve/3600,"-") -> - | AZ23: =SUMIF(AE23:AY23,BA23,$AE$6:$AY$6) -> 6 | BA23: =MIN(AE23:AY23) -> 12.973759 | BB23: =IF((SUMIF($BM21:$CG21,$AZ23,$BM23:$CG23)+$CH23)<(SUMIF($CO21:$DI21,$AZ23,$CO23:$DI23)+$DJ23),AZ23+1,AZ23) -> 6 | BC23: =SUMIF($AE$6:$AY$6,$BB23,$AE23:$AY23) -> 12.973759 | BF23: 16 | BG23: =$X23 -> 0.77219474 | BH23: =$AC23 -> 8392.3598 | BI23: =BH23*(1-BG23) -> 1911.8237 | BJ23: =Peak_Arrival_Manual/K56 -> 3.4917336 | BK23: =900*Peak_Time_Eve*(BJ23/Total_Lanes-1+SQRT((BJ23/Total_Lanes-1)^2+8*(BJ23/Total_Lanes)/(Peak_Time_Eve*$K56*Total_Lanes))) -> 0.2248414 | BL23: =Peak_Arrival_Manual/N56 -> 3.6722948 | BM23: =IF(BM$6<Total_Lanes,900*Peak_Time_Eve*(($BL23/(Total_Lanes-BM$6))-1+SQRT((($BL23/(Total_Lanes-BM$6))-1)^2+8*($BL23/(Total_Lanes-BM$6))/(Peak_Time_Eve*$N56*(Total_Lanes-BM$6)))),"-") -> 0.31500105 | BN23: =IF(BN$6<Total_Lanes,900*Peak_Time_Eve*(($BL23/(Total_Lanes-BN$6))-1+SQRT((($BL23/(Total_Lanes-BN$6))-1)^2+8*($BL23/(Total_Lanes-BN$6))/(Peak_Time_Eve*$N56*(Total_Lanes-BN$6)))),"-") -> 0.40124256 | BO23: =IF(BO$6<Total_Lanes,900*Peak_Time_Eve*(($BL23/(Total_Lanes-BO$6))-1+SQRT((($BL23/(Total_Lanes-BO$6))-1)^2+8*($BL23/(Total_Lanes-BO$6))/(Peak_Time_Eve*$N56*(Total_Lanes-BO$6)))),"-") -> 0.52946729 | BP23: =IF(BP$6<Total_Lanes,900*Peak_Time_Eve*(($BL23/(Total_Lanes-BP$6))-1+SQRT((($BL23/(Total_Lanes-BP$6))-1)^2+8*($BL23/(Total_Lanes-BP$6))/(Peak_Time_Eve*$N56*(Total_Lanes-BP$6)))),"-") -> 0.73319346 | BQ23: =IF(BQ$6<Total_Lanes,900*Peak_Time_Eve*(($BL23/(Total_Lanes-BQ$6))-1+SQRT((($BL23/(Total_Lanes-BQ$6))-1)^2+8*($BL23/(Total_Lanes-BQ$6))/(Peak_Time_Eve*$N56*(Total_Lanes-BQ$6)))),"-") -> 1.0894579 | BR23: =IF(BR$6<Total_Lanes,900*Peak_Time_Eve*(($BL23/(Total_Lanes-BR$6))-1+SQRT((($BL23/(Total_Lanes-BR$6))-1)^2+8*($BL23/(Total_Lanes-BR$6))/(Peak_Time_Eve*$N56*(Total_Lanes-BR$6)))),"-") -> 1.815876 | BS23: =IF(BS$6<Total_Lanes,900*Peak_Time_Eve*(($BL23/(Total_Lanes-BS$6))-1+SQRT((($BL23/(Total_Lanes-BS$6))-1)^2+8*($BL23/(Total_Lanes-BS$6))/(Peak_Time_Eve*$N56*(Total_Lanes-BS$6)))),"-") -> 3.8100489 | BT23: =IF(BT$6<Total_Lanes,900*Peak_Time_Eve*(($BL23/(Total_Lanes-BT$6))-1+SQRT((($BL23/(Total_Lanes-BT$6))-1)^2+8*($BL23/(Total_Lanes-BT$6))/(Peak_Time_Eve*$N56*(Total_Lanes-BT$6)))),"-") -> 18.243998 | ... CG23: =IF(CG$6<Total_Lanes,900*Peak_Time_Eve*(($BL23/(Total_Lanes-CG$6))-1+SQRT((($BL23/(Total_Lanes-CG$6))-1)^2+8*($BL23/(Total_Lanes-CG$6))/(Peak_Time_Eve*$N56*(Total_Lanes-CG$6)))),"-") -> - | CH23: =3600/N56 -> 6.915 | CJ23: 16 | CK23: =$X23 -> 0.77219474 | CL23: =$AC23 -> 8392.3598 | CM23: =CL23*CK23 -> 6480.5361 | CN23: =CM23/O55 -> 4.3203574 | CO23: =IF(CO$6<Total_Lanes,900*Peak_Time_Eve*(($CN23/CO$6-1)+SQRT(($CN23/CO$6-1)^2+8*($CN23/CO$6)/(Peak_Time_Eve*$O56*CO$6))),"-") -> 11956.409 | CP23: =IF(CP$6<Total_Lanes,900*Peak_Time_Eve*(($CN23/CP$6-1)+SQRT(($CN23/CP$6-1)^2+8*($CN23/CP$6)/(Peak_Time_Eve*$O56*CP$6))),"-") -> 4178.8765 | CQ23: =IF(CQ$6<Total_Lanes,900*Peak_Time_Eve*(($CN23/CQ$6-1)+SQRT(($CN23/CQ$6-1)^2+8*($CN23/CQ$6)/(Peak_Time_Eve*$O56*CQ$6))),"-") -> 1587.0423 | CR23: =IF(CR$6<Total_Lanes,900*Peak_Time_Eve*(($CN23/CR$6-1)+SQRT(($CN23/CR$6-1)^2+8*($CN23/CR$6)/(Peak_Time_Eve*$O56*CR$6))),"-") -> 296.19812 | CS23: =IF(CS$6<Total_Lanes,900*Peak_Time_Eve*(($CN23/CS$6-1)+SQRT(($CN23/CS$6-1)^2+8*($CN23/CS$6)/(Peak_Time_Eve*$O56*CS$6))),"-") -> 3.0324754 | CT23: =IF(CT$6<Total_Lanes,900*Peak_Time_Eve*(($CN23/CT$6-1)+SQRT(($CN23/CT$6-1)^2+8*($CN23/CT$6)/(Peak_Time_Eve*$O56*CT$6))),"-") -> 1.0278271 | CU23: =IF(CU$6<Total_Lanes,900*Peak_Time_Eve*(($CN23/CU$6-1)+SQRT(($CN23/CU$6-1)^2+8*($CN23/CU$6)/(Peak_Time_Eve*$O56*CU$6))),"-") -> 0.55256313 | CV23: =IF(CV$6<Total_Lanes,900*Peak_Time_Eve*(($CN23/CV$6-1)+SQRT(($CN23/CV$6-1)^2+8*($CN23/CV$6)/(Peak_Time_Eve*$O56*CV$6))),"-") -> 0.35216236 | ... DI23: =IF(DI$6<Total_Lanes,900*Peak_Time_Eve*(($CN23/DI$6-1)+SQRT(($CN23/DI$6-1)^2+8*($CN23/DI$6)/(Peak_Time_Eve*$O56*DI$6))),"-") -> - | DJ23: =3600/O56 -> 2.4
H24: 17 | I24: ='Input-Detail'!E31 -> 28352426 | J24: 0.78165149 | K24: =AC24 -> 8558.1323 | L24: =AD71 -> 14.271438 | M24: =AD24 -> 32.158827 | N24: =SUM(L24:M24) -> 46.430266 | O24: =$S$34*N24 -> 12071.869 | P24: =BC71 -> 3.2145443 | Q24: =BC24 -> 11.365895 | R24: =SUM(P24:Q24) -> 14.580439 | S24: =$S$34*R24 -> 3790.9142 | V24: 17 | W24: =W$7+(W$27-W$7)*$V24/20 -> 28352426 | X24: =MIN((J23+0.05),0.95) -> 0.80320595 | Y24: ='Input-Detail'!E31/Z24 -> 12225.903 | Z24: =Z23 -> 2319.0455 | AA24: =AA23 -> 2 | AB24: =AB23 -> 0.7 | AC24: =Y24*AB24 -> 8558.1323 | AD24: =Peak_Time_Eve*$BH24*(3600/K57+BK24)/3600 -> 32.158827 | AE24: =IF(AE$6<Total_Lanes,($BI24*($CH24+BM24)+$CM24*CO24)*Peak_Time_Eve/3600,"-") -> 49272.025 | AF24: =IF(AF$6<Total_Lanes,($BI24*($CH24+BN24)+$CM24*CP24)*Peak_Time_Eve/3600,"-") -> 17767.77 | AG24: =IF(AG$6<Total_Lanes,($BI24*($CH24+BO24)+$CM24*CQ24)*Peak_Time_Eve/3600,"-") -> 7268.3307 | AH24: =IF(AH$6<Total_Lanes,($BI24*($CH24+BP24)+$CM24*CR24)*Peak_Time_Eve/3600,"-") -> 2027.384 | AI24: =IF(AI$6<Total_Lanes,($BI24*($CH24+BQ24)+$CM24*CS24)*Peak_Time_Eve/3600,"-") -> 27.076143 | AJ24: =IF(AJ$6<Total_Lanes,($BI24*($CH24+BR24)+$CM24*CT24)*Peak_Time_Eve/3600,"-") -> 12.694311 | AK24: =IF(AK$6<Total_Lanes,($BI24*($CH24+BS24)+$CM24*CU24)*Peak_Time_Eve/3600,"-") -> 11.365895 | AL24: =IF(AL$6<Total_Lanes,($BI24*($CH24+BT24)+$CM24*CV24)*Peak_Time_Eve/3600,"-") -> 14.924403 | ... AY24: =IF(AY$6<Total_Lanes,($BI24*($CH24+CG24)+$CM24*DI24)*Peak_Time_Eve/3600,"-") -> - | AZ24: =SUMIF(AE24:AY24,BA24,$AE$6:$AY$6) -> 7 | BA24: =MIN(AE24:AY24) -> 11.365895 | BB24: =IF((SUMIF($BM22:$CG22,$AZ24,$BM24:$CG24)+$CH24)<(SUMIF($CO22:$DI22,$AZ24,$CO24:$DI24)+$DJ24),AZ24+1,AZ24) -> 7 | BC24: =SUMIF($AE$6:$AY$6,$BB24,$AE24:$AY24) -> 11.365895 | BF24: 17 | BG24: =$X24 -> 0.80320595 | BH24: =$AC24 -> 8558.1323 | BI24: =BH24*(1-BG24) -> 1684.1895 | BJ24: =Peak_Arrival_Manual/K57 -> 3.075985 | BK24: =900*Peak_Time_Eve*(BJ24/Total_Lanes-1+SQRT((BJ24/Total_Lanes-1)^2+8*(BJ24/Total_Lanes)/(Peak_Time_Eve*$K57*Total_Lanes))) -> 0.188846 | BL24: =Peak_Arrival_Manual/N57 -> 3.2449887 | BM24: =IF(BM$6<Total_Lanes,900*Peak_Time_Eve*(($BL24/(Total_Lanes-BM$6))-1+SQRT((($BL24/(Total_Lanes-BM$6))-1)^2+8*($BL24/(Total_Lanes-BM$6))/(Peak_Time_Eve*$N57*(Total_Lanes-BM$6)))),"-") -> 0.26382605 | BN24: =IF(BN$6<Total_Lanes,900*Peak_Time_Eve*(($BL24/(Total_Lanes-BN$6))-1+SQRT((($BL24/(Total_Lanes-BN$6))-1)^2+8*($BL24/(Total_Lanes-BN$6))/(Peak_Time_Eve*$N57*(Total_Lanes-BN$6)))),"-") -> 0.33315962 | BO24: =IF(BO$6<Total_Lanes,900*Peak_Time_Eve*(($BL24/(Total_Lanes-BO$6))-1+SQRT((($BL24/(Total_Lanes-BO$6))-1)^2+8*($BL24/(Total_Lanes-BO$6))/(Peak_Time_Eve*$N57*(Total_Lanes-BO$6)))),"-") -> 0.43447749 | BP24: =IF(BP$6<Total_Lanes,900*Peak_Time_Eve*(($BL24/(Total_Lanes-BP$6))-1+SQRT((($BL24/(Total_Lanes-BP$6))-1)^2+8*($BL24/(Total_Lanes-BP$6))/(Peak_Time_Eve*$N57*(Total_Lanes-BP$6)))),"-") -> 0.59152943 | BQ24: =IF(BQ$6<Total_Lanes,900*Peak_Time_Eve*(($BL24/(Total_Lanes-BQ$6))-1+SQRT((($BL24/(Total_Lanes-BQ$6))-1)^2+8*($BL24/(Total_Lanes-BQ$6))/(Peak_Time_Eve*$N57*(Total_Lanes-BQ$6)))),"-") -> 0.85592597 | BR24: =IF(BR$6<Total_Lanes,900*Peak_Time_Eve*(($BL24/(Total_Lanes-BR$6))-1+SQRT((($BL24/(Total_Lanes-BR$6))-1)^2+8*($BL24/(Total_Lanes-BR$6))/(Peak_Time_Eve*$N57*(Total_Lanes-BR$6)))),"-") -> 1.3605234 | BS24: =IF(BS$6<Total_Lanes,900*Peak_Time_Eve*(($BL24/(Total_Lanes-BS$6))-1+SQRT((($BL24/(Total_Lanes-BS$6))-1)^2+8*($BL24/(Total_Lanes-BS$6))/(Peak_Time_Eve*$N57*(Total_Lanes-BS$6)))),"-") -> 2.5598182 | BT24: =IF(BT$6<Total_Lanes,900*Peak_Time_Eve*(($BL24/(Total_Lanes-BT$6))-1+SQRT((($BL24/(Total_Lanes-BT$6))-1)^2+8*($BL24/(Total_Lanes-BT$6))/(Peak_Time_Eve*$N57*(Total_Lanes-BT$6)))),"-") -> 7.3728886 | ... CG24: =IF(CG$6<Total_Lanes,900*Peak_Time_Eve*(($BL24/(Total_Lanes-CG$6))-1+SQRT((($BL24/(Total_Lanes-CG$6))-1)^2+8*($BL24/(Total_Lanes-CG$6))/(Peak_Time_Eve*$N57*(Total_Lanes-CG$6)))),"-") -> - | CH24: =3600/N57 -> 6.93625 | CJ24: 17 | CK24: =$X24 -> 0.80320595 | CL24: =$AC24 -> 8558.1323 | CM24: =CL24*CK24 -> 6873.9428 | CN24: =CM24/O56 -> 4.5826285 | CO24: =IF(CO$6<Total_Lanes,900*Peak_Time_Eve*(($CN24/CO$6-1)+SQRT(($CN24/CO$6-1)^2+8*($CN24/CO$6)/(Peak_Time_Eve*$O57*CO$6))),"-") -> 12900.532 | CP24: =IF(CP$6<Total_Lanes,900*Peak_Time_Eve*(($CN24/CP$6-1)+SQRT(($CN24/CP$6-1)^2+8*($CN24/CP$6)/(Peak_Time_Eve*$O57*CP$6))),"-") -> 4650.8597 | CQ24: =IF(CQ$6<Total_Lanes,900*Peak_Time_Eve*(($CN24/CQ$6-1)+SQRT(($CN24/CQ$6-1)^2+8*($CN24/CQ$6)/(Peak_Time_Eve*$O57*CQ$6))),"-") -> 1901.4679 | CR24: =IF(CR$6<Total_Lanes,900*Peak_Time_Eve*(($CN24/CR$6-1)+SQRT(($CN24/CR$6-1)^2+8*($CN24/CR$6)/(Peak_Time_Eve*$O57*CR$6))),"-") -> 529.04323 | CS24: =IF(CS$6<Total_Lanes,900*Peak_Time_Eve*(($CN24/CS$6-1)+SQRT(($CN24/CS$6-1)^2+8*($CN24/CS$6)/(Peak_Time_Eve*$O57*CS$6))),"-") -> 5.1809504 | CT24: =IF(CT$6<Total_Lanes,900*Peak_Time_Eve*(($CN24/CT$6-1)+SQRT(($CN24/CT$6-1)^2+8*($CN24/CT$6)/(Peak_Time_Eve*$O57*CT$6))),"-") -> 1.2913145 | CU24: =IF(CU$6<Total_Lanes,900*Peak_Time_Eve*(($CN24/CU$6-1)+SQRT(($CN24/CU$6-1)^2+8*($CN24/CU$6)/(Peak_Time_Eve*$O57*CU$6))),"-") -> 0.64961732 | CV24: =IF(CV$6<Total_Lanes,900*Peak_Time_Eve*(($CN24/CV$6-1)+SQRT(($CN24/CV$6-1)^2+8*($CN24/CV$6)/(Peak_Time_Eve*$O57*CV$6))),"-") -> 0.40218897 | ... DI24: =IF(DI$6<Total_Lanes,900*Peak_Time_Eve*(($CN24/DI$6-1)+SQRT(($CN24/DI$6-1)^2+8*($CN24/DI$6)/(Peak_Time_Eve*$O57*DI$6))),"-") -> - | DJ24: =3600/O57 -> 2.4
H25: 18 | I25: ='Input-Detail'!E32 -> 28901617 | J25: 0.80735605 | K25: =AC25 -> 8723.9048 | L25: =AD72 -> 14.572139 | M25: =AD25 -> 32.630911 | N25: =SUM(L25:M25) -> 47.20305 | O25: =$S$34*N25 -> 12272.793 | P25: =BC72 -> 2.8384788 | Q25: =BC25 -> 10.253743 | R25: =SUM(P25:Q25) -> 13.092222 | S25: =$S$34*R25 -> 3403.9776 | V25: 18 | W25: =W$7+(W$27-W$7)*$V25/20 -> 28901617 | X25: =MIN((J24+0.05),0.95) -> 0.83165149 | Y25: ='Input-Detail'!E32/Z25 -> 12462.721 | Z25: =Z24 -> 2319.0455 | AA25: =AA24 -> 2 | AB25: =AB24 -> 0.7 | AC25: =Y25*AB25 -> 8723.9048 | AD25: =Peak_Time_Eve*$BH25*(3600/K58+BK25)/3600 -> 32.630911 | AE25: =IF(AE$6<Total_Lanes,($BI25*($CH25+BM25)+$CM25*CO25)*Peak_Time_Eve/3600,"-") -> 55692.391 | AF25: =IF(AF$6<Total_Lanes,($BI25*($CH25+BN25)+$CM25*CP25)*Peak_Time_Eve/3600,"-") -> 20596.068 | AG25: =IF(AG$6<Total_Lanes,($BI25*($CH25+BO25)+$CM25*CQ25)*Peak_Time_Eve/3600,"-") -> 8898.8998 | AH25: =IF(AH$6<Total_Lanes,($BI25*($CH25+BP25)+$CM25*CR25)*Peak_Time_Eve/3600,"-") -> 3055.6944 | AI25: =IF(AI$6<Total_Lanes,($BI25*($CH25+BQ25)+$CM25*CS25)*Peak_Time_Eve/3600,"-") -> 57.935674 | AJ25: =IF(AJ$6<Total_Lanes,($BI25*($CH25+BR25)+$CM25*CT25)*Peak_Time_Eve/3600,"-") -> 13.214172 | AK25: =IF(AK$6<Total_Lanes,($BI25*($CH25+BS25)+$CM25*CU25)*Peak_Time_Eve/3600,"-") -> 10.253743 | AL25: =IF(AL$6<Total_Lanes,($BI25*($CH25+BT25)+$CM25*CV25)*Peak_Time_Eve/3600,"-") -> 10.978955 | ... AY25: =IF(AY$6<Total_Lanes,($BI25*($CH25+CG25)+$CM25*DI25)*Peak_Time_Eve/3600,"-") -> - | AZ25: =SUMIF(AE25:AY25,BA25,$AE$6:$AY$6) -> 7 | BA25: =MIN(AE25:AY25) -> 10.253743 | BB25: =IF((SUMIF($BM23:$CG23,$AZ25,$BM25:$CG25)+$CH25)<(SUMIF($CO23:$DI23,$AZ25,$CO25:$DI25)+$DJ25),AZ25+1,AZ25) -> 7 | BC25: =SUMIF($AE$6:$AY$6,$BB25,$AE25:$AY25) -> 10.253743 | BF25: 18 | BG25: =$X25 -> 0.83165149 | BH25: =$AC25 -> 8723.9048 | BI25: =BH25*(1-BG25) -> 1468.6564 | BJ25: =Peak_Arrival_Manual/K58 -> 2.6823378 | BK25: =900*Peak_Time_Eve*(BJ25/Total_Lanes-1+SQRT((BJ25/Total_Lanes-1)^2+8*(BJ25/Total_Lanes)/(Peak_Time_Eve*$K58*Total_Lanes))) -> 0.15772354 | BL25: =Peak_Arrival_Manual/N58 -> 2.8383825 | BM25: =IF(BM$6<Total_Lanes,900*Peak_Time_Eve*(($BL25/(Total_Lanes-BM$6))-1+SQRT((($BL25/(Total_Lanes-BM$6))-1)^2+8*($BL25/(Total_Lanes-BM$6))/(Peak_Time_Eve*$N58*(Total_Lanes-BM$6)))),"-") -> 0.21994771 | BN25: =IF(BN$6<Total_Lanes,900*Peak_Time_Eve*(($BL25/(Total_Lanes-BN$6))-1+SQRT((($BL25/(Total_Lanes-BN$6))-1)^2+8*($BL25/(Total_Lanes-BN$6))/(Peak_Time_Eve*$N58*(Total_Lanes-BN$6)))),"-") -> 0.27571892 | BO25: =IF(BO$6<Total_Lanes,900*Peak_Time_Eve*(($BL25/(Total_Lanes-BO$6))-1+SQRT((($BL25/(Total_Lanes-BO$6))-1)^2+8*($BL25/(Total_Lanes-BO$6))/(Peak_Time_Eve*$N58*(Total_Lanes-BO$6)))),"-") -> 0.35606079 | BP25: =IF(BP$6<Total_Lanes,900*Peak_Time_Eve*(($BL25/(Total_Lanes-BP$6))-1+SQRT((($BL25/(Total_Lanes-BP$6))-1)^2+8*($BL25/(Total_Lanes-BP$6))/(Peak_Time_Eve*$N58*(Total_Lanes-BP$6)))),"-") -> 0.47814425 | BQ25: =IF(BQ$6<Total_Lanes,900*Peak_Time_Eve*(($BL25/(Total_Lanes-BQ$6))-1+SQRT((($BL25/(Total_Lanes-BQ$6))-1)^2+8*($BL25/(Total_Lanes-BQ$6))/(Peak_Time_Eve*$N58*(Total_Lanes-BQ$6)))),"-") -> 0.67768277 | BR25: =IF(BR$6<Total_Lanes,900*Peak_Time_Eve*(($BL25/(Total_Lanes-BR$6))-1+SQRT((($BL25/(Total_Lanes-BR$6))-1)^2+8*($BL25/(Total_Lanes-BR$6))/(Peak_Time_Eve*$N58*(Total_Lanes-BR$6)))),"-") -> 1.0404601 | BS25: =IF(BS$6<Total_Lanes,900*Peak_Time_Eve*(($BL25/(Total_Lanes-BS$6))-1+SQRT((($BL25/(Total_Lanes-BS$6))-1)^2+8*($BL25/(Total_Lanes-BS$6))/(Peak_Time_Eve*$N58*(Total_Lanes-BS$6)))),"-") -> 1.8250145 | BT25: =IF(BT$6<Total_Lanes,900*Peak_Time_Eve*(($BL25/(Total_Lanes-BT$6))-1+SQRT((($BL25/(Total_Lanes-BT$6))-1)^2+8*($BL25/(Total_Lanes-BT$6))/(Peak_Time_Eve*$N58*(Total_Lanes-BT$6)))),"-") -> 4.2329791 | ... CG25: =IF(CG$6<Total_Lanes,900*Peak_Time_Eve*(($BL25/(Total_Lanes-CG$6))-1+SQRT((($BL25/(Total_Lanes-CG$6))-1)^2+8*($BL25/(Total_Lanes-CG$6))/(Peak_Time_Eve*$N58*(Total_Lanes-CG$6)))),"-") -> - | CH25: =3600/N58 -> 6.9575 | CJ25: 18 | CK25: =$X25 -> 0.83165149 | CL25: =$AC25 -> 8723.9048 | CM25: =CL25*CK25 -> 7255.2484 | CN25: =CM25/O57 -> 4.8368323 | CO25: =IF(CO$6<Total_Lanes,900*Peak_Time_Eve*(($CN25/CO$6-1)+SQRT(($CN25/CO$6-1)^2+8*($CN25/CO$6)/(Peak_Time_Eve*$O58*CO$6))),"-") -> 13815.621 | CP25: =IF(CP$6<Total_Lanes,900*Peak_Time_Eve*(($CN25/CP$6-1)+SQRT(($CN25/CP$6-1)^2+8*($CN25/CP$6)/(Peak_Time_Eve*$O58*CP$6))),"-") -> 5108.3433 | CQ25: =IF(CQ$6<Total_Lanes,900*Peak_Time_Eve*(($CN25/CQ$6-1)+SQRT(($CN25/CQ$6-1)^2+8*($CN25/CQ$6)/(Peak_Time_Eve*$O58*CQ$6))),"-") -> 2206.3033 | CR25: =IF(CR$6<Total_Lanes,900*Peak_Time_Eve*(($CN25/CR$6-1)+SQRT(($CN25/CR$6-1)^2+8*($CN25/CR$6)/(Peak_Time_Eve*$O58*CR$6))),"-") -> 756.60118 | CS25: =IF(CS$6<Total_Lanes,900*Peak_Time_Eve*(($CN25/CS$6-1)+SQRT(($CN25/CS$6-1)^2+8*($CN25/CS$6)/(Peak_Time_Eve*$O58*CS$6))),"-") -> 12.828059 | CT25: =IF(CT$6<Total_Lanes,900*Peak_Time_Eve*(($CN25/CT$6-1)+SQRT(($CN25/CT$6-1)^2+8*($CN25/CT$6)/(Peak_Time_Eve*$O58*CT$6))),"-") -> 1.6593855 | CU25: =IF(CU$6<Total_Lanes,900*Peak_Time_Eve*(($CN25/CU$6-1)+SQRT(($CN25/CU$6-1)^2+8*($CN25/CU$6)/(Peak_Time_Eve*$O58*CU$6))),"-") -> 0.7660993 | CV25: =IF(CV$6<Total_Lanes,900*Peak_Time_Eve*(($CN25/CV$6-1)+SQRT(($CN25/CV$6-1)^2+8*($CN25/CV$6)/(Peak_Time_Eve*$O58*CV$6))),"-") -> 0.45858534 | ... DI25: =IF(DI$6<Total_Lanes,900*Peak_Time_Eve*(($CN25/DI$6-1)+SQRT(($CN25/DI$6-1)^2+8*($CN25/DI$6)/(Peak_Time_Eve*$O58*DI$6))),"-") -> - | DJ25: =3600/O58 -> 2.4
H26: 19 | I26: ='Input-Detail'!E33 -> 29450809 | J26: 0.83056395 | K26: =AC26 -> 8889.6773 | L26: =AD73 -> 14.875723 | M26: =AD26 -> 33.119136 | N26: =SUM(L26:M26) -> 47.994859 | O26: =$S$34*N26 -> 12478.663 | P26: =BC73 -> 2.4989102 | Q26: =BC26 -> 9.0823827 | R26: =SUM(P26:Q26) -> 11.581293 | S26: =$S$34*R26 -> 3011.1362 | V26: 19 | W26: =W$7+(W$27-W$7)*$V26/20 -> 29450809 | X26: =MIN((J25+0.05),0.95) -> 0.85735605 | Y26: ='Input-Detail'!E33/Z26 -> 12699.539 | Z26: =Z25 -> 2319.0455 | AA26: =AA25 -> 2 | AB26: =AB25 -> 0.7 | AC26: =Y26*AB26 -> 8889.6773 | AD26: =Peak_Time_Eve*$BH26*(3600/K59+BK26)/3600 -> 33.119136 | AE26: =IF(AE$6<Total_Lanes,($BI26*($CH26+BM26)+$CM26*CO26)*Peak_Time_Eve/3600,"-") -> 62226.551 | AF26: =IF(AF$6<Total_Lanes,($BI26*($CH26+BN26)+$CM26*CP26)*Peak_Time_Eve/3600,"-") -> 23496.262 | AG26: =IF(AG$6<Total_Lanes,($BI26*($CH26+BO26)+$CM26*CQ26)*Peak_Time_Eve/3600,"-") -> 10587.513 | AH26: =IF(AH$6<Total_Lanes,($BI26*($CH26+BP26)+$CM26*CR26)*Peak_Time_Eve/3600,"-") -> 4136.8812 | AI26: =IF(AI$6<Total_Lanes,($BI26*($CH26+BQ26)+$CM26*CS26)*Peak_Time_Eve/3600,"-") -> 345.12288 | AJ26: =IF(AJ$6<Total_Lanes,($BI26*($CH26+BR26)+$CM26*CT26)*Peak_Time_Eve/3600,"-") -> 14.812684 | AK26: =IF(AK$6<Total_Lanes,($BI26*($CH26+BS26)+$CM26*CU26)*Peak_Time_Eve/3600,"-") -> 9.7070916 | AL26: =IF(AL$6<Total_Lanes,($BI26*($CH26+BT26)+$CM26*CV26)*Peak_Time_Eve/3600,"-") -> 9.0823827 | ... AY26: =IF(AY$6<Total_Lanes,($BI26*($CH26+CG26)+$CM26*DI26)*Peak_Time_Eve/3600,"-") -> - | AZ26: =SUMIF(AE26:AY26,BA26,$AE$6:$AY$6) -> 8 | BA26: =MIN(AE26:AY26) -> 9.0823827 | BB26: =IF((SUMIF($BM24:$CG24,$AZ26,$BM26:$CG26)+$CH26)<(SUMIF($CO24:$DI24,$AZ26,$CO26:$DI26)+$DJ26),AZ26+1,AZ26) -> 8 | BC26: =SUMIF($AE$6:$AY$6,$BB26,$AE26:$AY26) -> 9.0823827 | BF26: 19 | BG26: =$X26 -> 0.85735605 | BH26: =$AC26 -> 8889.6773 | BI26: =BH26*(1-BG26) -> 1268.0587 | BJ26: =Peak_Arrival_Manual/K59 -> 2.3159683 | BK26: =900*Peak_Time_Eve*(BJ26/Total_Lanes-1+SQRT((BJ26/Total_Lanes-1)^2+8*(BJ26/Total_Lanes)/(Peak_Time_Eve*$K59*Total_Lanes))) -> 0.13103018 | BL26: =Peak_Arrival_Manual/N59 -> 2.4581846 | BM26: =IF(BM$6<Total_Lanes,900*Peak_Time_Eve*(($BL26/(Total_Lanes-BM$6))-1+SQRT((($BL26/(Total_Lanes-BM$6))-1)^2+8*($BL26/(Total_Lanes-BM$6))/(Peak_Time_Eve*$N59*(Total_Lanes-BM$6)))),"-") -> 0.18256643 | BN26: =IF(BN$6<Total_Lanes,900*Peak_Time_Eve*(($BL26/(Total_Lanes-BN$6))-1+SQRT((($BL26/(Total_Lanes-BN$6))-1)^2+8*($BL26/(Total_Lanes-BN$6))/(Peak_Time_Eve*$N59*(Total_Lanes-BN$6)))),"-") -> 0.22744682 | BO26: =IF(BO$6<Total_Lanes,900*Peak_Time_Eve*(($BL26/(Total_Lanes-BO$6))-1+SQRT((($BL26/(Total_Lanes-BO$6))-1)^2+8*($BL26/(Total_Lanes-BO$6))/(Peak_Time_Eve*$N59*(Total_Lanes-BO$6)))),"-") -> 0.29134193 | BP26: =IF(BP$6<Total_Lanes,900*Peak_Time_Eve*(($BL26/(Total_Lanes-BP$6))-1+SQRT((($BL26/(Total_Lanes-BP$6))-1)^2+8*($BL26/(Total_Lanes-BP$6))/(Peak_Time_Eve*$N59*(Total_Lanes-BP$6)))),"-") -> 0.38688575 | BQ26: =IF(BQ$6<Total_Lanes,900*Peak_Time_Eve*(($BL26/(Total_Lanes-BQ$6))-1+SQRT((($BL26/(Total_Lanes-BQ$6))-1)^2+8*($BL26/(Total_Lanes-BQ$6))/(Peak_Time_Eve*$N59*(Total_Lanes-BQ$6)))),"-") -> 0.53946632 | BR26: =IF(BR$6<Total_Lanes,900*Peak_Time_Eve*(($BL26/(Total_Lanes-BR$6))-1+SQRT((($BL26/(Total_Lanes-BR$6))-1)^2+8*($BL26/(Total_Lanes-BR$6))/(Peak_Time_Eve*$N59*(Total_Lanes-BR$6)))),"-") -> 0.80695644 | BS26: =IF(BS$6<Total_Lanes,900*Peak_Time_Eve*(($BL26/(Total_Lanes-BS$6))-1+SQRT((($BL26/(Total_Lanes-BS$6))-1)^2+8*($BL26/(Total_Lanes-BS$6))/(Peak_Time_Eve*$N59*(Total_Lanes-BS$6)))),"-") -> 1.348833 | BT26: =IF(BT$6<Total_Lanes,900*Peak_Time_Eve*(($BL26/(Total_Lanes-BT$6))-1+SQRT((($BL26/(Total_Lanes-BT$6))-1)^2+8*($BL26/(Total_Lanes-BT$6))/(Peak_Time_Eve*$N59*(Total_Lanes-BT$6)))),"-") -> 2.7760789 | ... CG26: =IF(CG$6<Total_Lanes,900*Peak_Time_Eve*(($BL26/(Total_Lanes-CG$6))-1+SQRT((($BL26/(Total_Lanes-CG$6))-1)^2+8*($BL26/(Total_Lanes-CG$6))/(Peak_Time_Eve*$N59*(Total_Lanes-CG$6)))),"-") -> - | CH26: =3600/N59 -> 6.97875 | CJ26: 19 | CK26: =$X26 -> 0.85735605 | CL26: =$AC26 -> 8889.6773 | CM26: =CL26*CK26 -> 7621.6186 | CN26: =CM26/O58 -> 5.0810791 | CO26: =IF(CO$6<Total_Lanes,900*Peak_Time_Eve*(($CN26/CO$6-1)+SQRT(($CN26/CO$6-1)^2+8*($CN26/CO$6)/(Peak_Time_Eve*$O59*CO$6))),"-") -> 14694.872 | CP26: =IF(CP$6<Total_Lanes,900*Peak_Time_Eve*(($CN26/CP$6-1)+SQRT(($CN26/CP$6-1)^2+8*($CN26/CP$6)/(Peak_Time_Eve*$O59*CP$6))),"-") -> 5547.9206 | CQ26: =IF(CQ$6<Total_Lanes,900*Peak_Time_Eve*(($CN26/CQ$6-1)+SQRT(($CN26/CQ$6-1)^2+8*($CN26/CQ$6)/(Peak_Time_Eve*$O59*CQ$6))),"-") -> 2499.2466 | CR26: =IF(CR$6<Total_Lanes,900*Peak_Time_Eve*(($CN26/CR$6-1)+SQRT(($CN26/CR$6-1)^2+8*($CN26/CR$6)/(Peak_Time_Eve*$O59*CR$6))),"-") -> 975.78304 | CS26: =IF(CS$6<Total_Lanes,900*Peak_Time_Eve*(($CN26/CS$6-1)+SQRT(($CN26/CS$6-1)^2+8*($CN26/CS$6)/(Peak_Time_Eve*$O59*CS$6))),"-") -> 80.256922 | CT26: =IF(CT$6<Total_Lanes,900*Peak_Time_Eve*(($CN26/CT$6-1)+SQRT(($CN26/CT$6-1)^2+8*($CN26/CT$6)/(Peak_Time_Eve*$O59*CT$6))),"-") -> 2.202957 | CU26: =IF(CU$6<Total_Lanes,900*Peak_Time_Eve*(($CN26/CU$6-1)+SQRT(($CN26/CU$6-1)^2+8*($CN26/CU$6)/(Peak_Time_Eve*$O59*CU$6))),"-") -> 0.90701216 | CV26: =IF(CV$6<Total_Lanes,900*Peak_Time_Eve*(($CN26/CV$6-1)+SQRT(($CN26/CV$6-1)^2+8*($CN26/CV$6)/(Peak_Time_Eve*$O59*CV$6))),"-") -> 0.5220142 | ... DI26: =IF(DI$6<Total_Lanes,900*Peak_Time_Eve*(($CN26/DI$6-1)+SQRT(($CN26/DI$6-1)^2+8*($CN26/DI$6)/(Peak_Time_Eve*$O59*DI$6))),"-") -> - | DJ26: =3600/O59 -> 2.4
H27: 20 | I27: ='Input-Detail'!E34 -> 30000000 | J27: 0.85118551 | K27: =AC27 -> 9055.4498 | L27: =AD74 -> 15.182081 | M27: =AD27 -> 33.620677 | N27: =SUM(L27:M27) -> 48.802759 | O27: =$S$34*N27 -> 12688.717 | P27: =BC74 -> 2.1604051 | Q27: =BC27 -> 8.0012249 | R27: =SUM(P27:Q27) -> 10.16163 | S27: =$S$34*R27 -> 2642.0238 | V27: 20 | W27: ='Input-Detail'!E34 -> 30000000 | X27: =MIN((J26+0.05),0.95) -> 0.88056395 | Y27: ='Input-Detail'!E34/Z27 -> 12936.357 | Z27: =Z26 -> 2319.0455 | AA27: =AA26 -> 2 | AB27: =AB26 -> 0.7 | AC27: =Y27*AB27 -> 9055.4498 | AD27: =Peak_Time_Eve*$BH27*(3600/K60+BK27)/3600 -> 33.620677 | AE27: =IF(AE$6<Total_Lanes,($BI27*($CH27+BM27)+$CM27*CO27)*Peak_Time_Eve/3600,"-") -> 68847.082 | AF27: =IF(AF$6<Total_Lanes,($BI27*($CH27+BN27)+$CM27*CP27)*Peak_Time_Eve/3600,"-") -> 26453.781 | AG27: =IF(AG$6<Total_Lanes,($BI27*($CH27+BO27)+$CM27*CQ27)*Peak_Time_Eve/3600,"-") -> 12323.839 | AH27: =IF(AH$6<Total_Lanes,($BI27*($CH27+BP27)+$CM27*CR27)*Peak_Time_Eve/3600,"-") -> 5261.6781 | AI27: =IF(AI$6<Total_Lanes,($BI27*($CH27+BQ27)+$CM27*CS27)*Peak_Time_Eve/3600,"-") -> 1046.7493 | AJ27: =IF(AJ$6<Total_Lanes,($BI27*($CH27+BR27)+$CM27*CT27)*Peak_Time_Eve/3600,"-") -> 18.25169 | AK27: =IF(AK$6<Total_Lanes,($BI27*($CH27+BS27)+$CM27*CU27)*Peak_Time_Eve/3600,"-") -> 9.6047769 | AL27: =IF(AL$6<Total_Lanes,($BI27*($CH27+BT27)+$CM27*CV27)*Peak_Time_Eve/3600,"-") -> 8.0012249 | ... AY27: =IF(AY$6<Total_Lanes,($BI27*($CH27+CG27)+$CM27*DI27)*Peak_Time_Eve/3600,"-") -> - | AZ27: =SUMIF(AE27:AY27,BA27,$AE$6:$AY$6) -> 8 | BA27: =MIN(AE27:AY27) -> 8.0012249 | BB27: =IF((SUMIF($BM25:$CG25,$AZ27,$BM27:$CG27)+$CH27)<(SUMIF($CO25:$DI25,$AZ27,$CO27:$DI27)+$DJ27),AZ27+1,AZ27) -> 8 | BC27: =SUMIF($AE$6:$AY$6,$BB27,$AE27:$AY27) -> 8.0012249 | BF27: 20 | BG27: =$X27 -> 0.88056395 | BH27: =$AC27 -> 9055.4498 | BI27: =BH27*(1-BG27) -> 1081.5472 | BJ27: =Peak_Arrival_Manual/K60 -> 1.9753257 | BK27: =900*Peak_Time_Eve*(BJ27/Total_Lanes-1+SQRT((BJ27/Total_Lanes-1)^2+8*(BJ27/Total_Lanes)/(Peak_Time_Eve*$K60*Total_Lanes))) -> 0.10796112 | BL27: =Peak_Arrival_Manual/N60 -> 2.1030084 | BM27: =IF(BM$6<Total_Lanes,900*Peak_Time_Eve*(($BL27/(Total_Lanes-BM$6))-1+SQRT((($BL27/(Total_Lanes-BM$6))-1)^2+8*($BL27/(Total_Lanes-BM$6))/(Peak_Time_Eve*$N60*(Total_Lanes-BM$6)))),"-") -> 0.15041139 | BN27: =IF(BN$6<Total_Lanes,900*Peak_Time_Eve*(($BL27/(Total_Lanes-BN$6))-1+SQRT((($BL27/(Total_Lanes-BN$6))-1)^2+8*($BL27/(Total_Lanes-BN$6))/(Peak_Time_Eve*$N60*(Total_Lanes-BN$6)))),"-") -> 0.18640128 | BO27: =IF(BO$6<Total_Lanes,900*Peak_Time_Eve*(($BL27/(Total_Lanes-BO$6))-1+SQRT((($BL27/(Total_Lanes-BO$6))-1)^2+8*($BL27/(Total_Lanes-BO$6))/(Peak_Time_Eve*$N60*(Total_Lanes-BO$6)))),"-") -> 0.2371371 | BP27: =IF(BP$6<Total_Lanes,900*Peak_Time_Eve*(($BL27/(Total_Lanes-BP$6))-1+SQRT((($BL27/(Total_Lanes-BP$6))-1)^2+8*($BL27/(Total_Lanes-BP$6))/(Peak_Time_Eve*$N60*(Total_Lanes-BP$6)))),"-") -> 0.31200926 | BQ27: =IF(BQ$6<Total_Lanes,900*Peak_Time_Eve*(($BL27/(Total_Lanes-BQ$6))-1+SQRT((($BL27/(Total_Lanes-BQ$6))-1)^2+8*($BL27/(Total_Lanes-BQ$6))/(Peak_Time_Eve*$N60*(Total_Lanes-BQ$6)))),"-") -> 0.42937583 | BR27: =IF(BR$6<Total_Lanes,900*Peak_Time_Eve*(($BL27/(Total_Lanes-BR$6))-1+SQRT((($BL27/(Total_Lanes-BR$6))-1)^2+8*($BL27/(Total_Lanes-BR$6))/(Peak_Time_Eve*$N60*(Total_Lanes-BR$6)))),"-") -> 0.62942128 | BS27: =IF(BS$6<Total_Lanes,900*Peak_Time_Eve*(($BL27/(Total_Lanes-BS$6))-1+SQRT((($BL27/(Total_Lanes-BS$6))-1)^2+8*($BL27/(Total_Lanes-BS$6))/(Peak_Time_Eve*$N60*(Total_Lanes-BS$6)))),"-") -> 1.015805 | BT27: =IF(BT$6<Total_Lanes,900*Peak_Time_Eve*(($BL27/(Total_Lanes-BT$6))-1+SQRT((($BL27/(Total_Lanes-BT$6))-1)^2+8*($BL27/(Total_Lanes-BT$6))/(Peak_Time_Eve*$N60*(Total_Lanes-BT$6)))),"-") -> 1.9378536 | ... CG27: =IF(CG$6<Total_Lanes,900*Peak_Time_Eve*(($BL27/(Total_Lanes-CG$6))-1+SQRT((($BL27/(Total_Lanes-CG$6))-1)^2+8*($BL27/(Total_Lanes-CG$6))/(Peak_Time_Eve*$N60*(Total_Lanes-CG$6)))),"-") -> - | CH27: =3600/N60 -> 7 | CJ27: 20 | CK27: =$X27 -> 0.88056395 | CL27: =$AC27 -> 9055.4498 | CM27: =CL27*CK27 -> 7973.9026 | CN27: =CM27/O59 -> 5.3159351 | CO27: =IF(CO$6<Total_Lanes,900*Peak_Time_Eve*(($CN27/CO$6-1)+SQRT(($CN27/CO$6-1)^2+8*($CN27/CO$6)/(Peak_Time_Eve*$O60*CO$6))),"-") -> 15540.322 | CP27: =IF(CP$6<Total_Lanes,900*Peak_Time_Eve*(($CN27/CP$6-1)+SQRT(($CN27/CP$6-1)^2+8*($CN27/CP$6)/(Peak_Time_Eve*$O60*CP$6))),"-") -> 5970.6063 | CQ27: =IF(CQ$6<Total_Lanes,900*Peak_Time_Eve*(($CN27/CQ$6-1)+SQRT(($CN27/CQ$6-1)^2+8*($CN27/CQ$6)/(Peak_Time_Eve*$O60*CQ$6))),"-") -> 2780.9572 | CR27: =IF(CR$6<Total_Lanes,900*Peak_Time_Eve*(($CN27/CR$6-1)+SQRT(($CN27/CR$6-1)^2+8*($CN27/CR$6)/(Peak_Time_Eve*$O60*CR$6))),"-") -> 1186.7604 | CS27: =IF(CS$6<Total_Lanes,900*Peak_Time_Eve*(($CN27/CS$6-1)+SQRT(($CN27/CS$6-1)^2+8*($CN27/CS$6)/(Peak_Time_Eve*$O60*CS$6))),"-") -> 235.28173 | CT27: =IF(CT$6<Total_Lanes,900*Peak_Time_Eve*(($CN27/CT$6-1)+SQRT(($CN27/CT$6-1)^2+8*($CN27/CT$6)/(Peak_Time_Eve*$O60*CT$6))),"-") -> 3.0852474 | CU27: =IF(CU$6<Total_Lanes,900*Peak_Time_Eve*(($CN27/CU$6-1)+SQRT(($CN27/CU$6-1)^2+8*($CN27/CU$6)/(Peak_Time_Eve*$O60*CU$6))),"-") -> 1.080917 | CV27: =IF(CV$6<Total_Lanes,900*Peak_Time_Eve*(($CN27/CV$6-1)+SQRT(($CN27/CV$6-1)^2+8*($CN27/CV$6)/(Peak_Time_Eve*$O60*CV$6))),"-") -> 0.59387416 | ... DI27: =IF(DI$6<Total_Lanes,900*Peak_Time_Eve*(($CN27/DI$6-1)+SQRT(($CN27/DI$6-1)^2+8*($CN27/DI$6)/(Peak_Time_Eve*$O60*DI$6))),"-") -> - | DJ27: =3600/O60 -> 2.4
H30: Footnote: | V30: Footnote:
H31: *Suppose peak hours happen in weekdays. Therefore, 5 weekdays per week. | V31: *Criterion of Choosing Optimal Number of ETC Lanes--Minimize Total Delay in the System During the Peak Hour
H32: Or you can change the number of days (in white cell) | V32: Average Delay Formula: ADi = (1/mi) + 900* (T)*{(r-1)+[(r-1)2+8*k*I*r/(T*mimi)]0.5}
H33: # of weeks per year | S33: 52 | V33: where
H34: # of weekdays per year | S34: =5*S33 -> 260 | V34: m : mean service rate (veh/hr)
V35: i : 1 for manual lane and 2 for ETC lane.
V36: T : duration of peak period (hr) per day,
H37: y Estimated Mean Service Rate (vhe/hrs) given payment split | V37: r : degree of ri = li/mimi
H38: Year | I38: Payment Split (Baseline)-Manual | L38: Payment Split (ETC Alternative)-Manual | O38: Capacity-ETC Lane | V38: m : number of lanes,
I39: Cash/Chect | J39: Ticket | K39: Mean Service Rate | L39: Cash/Check | M39: Ticket | N39: Mean Service Rate | V39: l : arrival rate during the peak period (veh/hr),
H40: Base | I40: ='Input-Detail'!BH13 -> 0.83 | J40: =1-I40 -> 0.17 | K40: =3600/(Trans_Time_Cash*I40+Trans_Time_Ticket*J40) -> 547.52852 | L40: ='Input-Detail'!BJ13 -> 0.83 | M40: =1-L40 -> 0.17 | N40: =3600/(Trans_Time_Cash*L40+Trans_Time_Ticket*M40) -> 547.52852 | O40: =3600/Headway_ETC -> 1500 | V40: k : parameter for given arrival and service distribution, k = 1 for Poisson Arrivals and exponentil service time,
H41: 1 | I41: ='Input-Detail'!BH14 -> 0.83 | J41: =1-I41 -> 0.17 | K41: =3600/(Trans_Time_Cash*I41+Trans_Time_Ticket*J41) -> 547.52852 | L41: ='Input-Detail'!BJ14 -> 0.8385 | M41: =1-L41 -> 0.1615 | N41: =3600/(Trans_Time_Cash*L41+Trans_Time_Ticket*M41) -> 545.76464 | O41: =3600/Headway_ETC -> 1500 | V41: I : variance to mean ratio of arrivals; I = 1 for Poisson Arrivals.
H42: 2 | I42: ='Input-Detail'!BH15 -> 0.83 | J42: =1-I42 -> 0.17 | K42: =3600/(Trans_Time_Cash*I42+Trans_Time_Ticket*J42) -> 547.52852 | L42: ='Input-Detail'!BJ15 -> 0.847 | M42: =1-L42 -> 0.153 | N42: =3600/(Trans_Time_Cash*L42+Trans_Time_Ticket*M42) -> 544.01209 | O42: =3600/Headway_ETC -> 1500
H43: 3 | I43: ='Input-Detail'!BH16 -> 0.83 | J43: =1-I43 -> 0.17 | K43: =3600/(Trans_Time_Cash*I43+Trans_Time_Ticket*J43) -> 547.52852 | L43: ='Input-Detail'!BJ16 -> 0.8555 | M43: =1-L43 -> 0.1445 | N43: =3600/(Trans_Time_Cash*L43+Trans_Time_Ticket*M43) -> 542.27076 | O43: =3600/Headway_ETC -> 1500 | V43: Total Time (hr) Spent in the System per day: (AD1*l1+AD2*l2)*T/3600
H44: 4 | I44: ='Input-Detail'!BH17 -> 0.83 | J44: =1-I44 -> 0.17 | K44: =3600/(Trans_Time_Cash*I44+Trans_Time_Ticket*J44) -> 547.52852 | L44: ='Input-Detail'!BJ17 -> 0.864 | M44: =1-L44 -> 0.136 | N44: =3600/(Trans_Time_Cash*L44+Trans_Time_Ticket*M44) -> 540.54054 | O44: =3600/Headway_ETC -> 1500 | V44: Given total number of lanes, peak hour traffic and ETC split, we can find out the optimal number of ETC lanes.
H45: 5 | I45: ='Input-Detail'!BH18 -> 0.83 | J45: =1-I45 -> 0.17 | K45: =3600/(Trans_Time_Cash*I45+Trans_Time_Ticket*J45) -> 547.52852 | L45: ='Input-Detail'!BJ18 -> 0.8725 | M45: =1-L45 -> 0.1275 | N45: =3600/(Trans_Time_Cash*L45+Trans_Time_Ticket*M45) -> 538.82133 | O45: =3600/Headway_ETC -> 1500 | V45: ** Delay happens to those people who arrival during the evening peak period.
H46: 6 | I46: ='Input-Detail'!BH19 -> 0.83 | J46: =1-I46 -> 0.17 | K46: =3600/(Trans_Time_Cash*I46+Trans_Time_Ticket*J46) -> 547.52852 | L46: ='Input-Detail'!BJ19 -> 0.881 | M46: =1-L46 -> 0.119 | N46: =3600/(Trans_Time_Cash*L46+Trans_Time_Ticket*M46) -> 537.11302 | O46: =3600/Headway_ETC -> 1500
H47: 7 | I47: ='Input-Detail'!BH20 -> 0.83 | J47: =1-I47 -> 0.17 | K47: =3600/(Trans_Time_Cash*I47+Trans_Time_Ticket*J47) -> 547.52852 | L47: ='Input-Detail'!BJ20 -> 0.8895 | M47: =1-L47 -> 0.1105 | N47: =3600/(Trans_Time_Cash*L47+Trans_Time_Ticket*M47) -> 535.4155 | O47: =3600/Headway_ETC -> 1500 | V47: ***Suggested Number of ETC Lanes:The number of ETC Lanes, which is close to optimal number of ETC Lanes, such that average delay in ETC lanes is less than average delay in Manual Lanes.
H48: 8 | I48: ='Input-Detail'!BH21 -> 0.83 | J48: =1-I48 -> 0.17 | K48: =3600/(Trans_Time_Cash*I48+Trans_Time_Ticket*J48) -> 547.52852 | L48: ='Input-Detail'!BJ21 -> 0.898 | M48: =1-L48 -> 0.102 | N48: =3600/(Trans_Time_Cash*L48+Trans_Time_Ticket*M48) -> 533.72869 | O48: =3600/Headway_ETC -> 1500
H49: 9 | I49: ='Input-Detail'!BH22 -> 0.83 | J49: =1-I49 -> 0.17 | K49: =3600/(Trans_Time_Cash*I49+Trans_Time_Ticket*J49) -> 547.52852 | L49: ='Input-Detail'!BJ22 -> 0.9065 | M49: =1-L49 -> 0.0935 | N49: =3600/(Trans_Time_Cash*L49+Trans_Time_Ticket*M49) -> 532.05247 | O49: =3600/Headway_ETC -> 1500
H50: 10 | I50: ='Input-Detail'!BH23 -> 0.83 | J50: =1-I50 -> 0.17 | K50: =3600/(Trans_Time_Cash*I50+Trans_Time_Ticket*J50) -> 547.52852 | L50: ='Input-Detail'!BJ23 -> 0.915 | M50: =1-L50 -> 0.085 | N50: =3600/(Trans_Time_Cash*L50+Trans_Time_Ticket*M50) -> 530.38674 | O50: =3600/Headway_ETC -> 1500 | V50: a) Total Time Spent in the System during the Morning Peak per Day (hr) | BF50: b) Average Random Delay per Manual User (sec) | CJ50: c) Average Random Delay per ETC User (sec)
H51: 11 | I51: ='Input-Detail'!BH24 -> 0.83 | J51: =1-I51 -> 0.17 | K51: =3600/(Trans_Time_Cash*I51+Trans_Time_Ticket*J51) -> 547.52852 | L51: ='Input-Detail'!BJ24 -> 0.9235 | M51: =1-L51 -> 0.0765 | N51: =3600/(Trans_Time_Cash*L51+Trans_Time_Ticket*M51) -> 528.73141 | O51: =3600/Headway_ETC -> 1500
H52: 12 | I52: ='Input-Detail'!BH25 -> 0.83 | J52: =1-I52 -> 0.17 | K52: =3600/(Trans_Time_Cash*I52+Trans_Time_Ticket*J52) -> 547.52852 | L52: ='Input-Detail'!BJ25 -> 0.932 | M52: =1-L52 -> 0.068 | N52: =3600/(Trans_Time_Cash*L52+Trans_Time_Ticket*M52) -> 527.08638 | O52: =3600/Headway_ETC -> 1500 | V52: Year | W52: Traffic Vol. | X52: ETC (%) | Y52: PHV | Z52: ATV/PHV | AA52: T (hr) | AB52: K | AC52: Total Arrival Rate | AD52: Number of ETC Lanes | AZ52: Optimal # of ETC Ln* | BA52: Delay per Day**(hr) | BB52: Suggested # of ETC Ln*** | BC52: Delay per Day**(hr) | BF52: Year | BG52: ETC (%) | BH52: Total Arrival Rate | BI52: Arrival Rate for Manual Users | BJ52: Number of ETC Lanes | CH52: Mean Transaction Time (sec) | CJ52: Year | CK52: ETC (%) | CL52: Total Arrival Rate | CM52: Arrival Rate for ETC Users | CN52: Number of ETC Lanes | DJ52: Mean headway (sec)
H53: 13 | I53: ='Input-Detail'!BH26 -> 0.83 | J53: =1-I53 -> 0.17 | K53: =3600/(Trans_Time_Cash*I53+Trans_Time_Ticket*J53) -> 547.52852 | L53: ='Input-Detail'!BJ26 -> 0.9405 | M53: =1-L53 -> 0.0595 | N53: =3600/(Trans_Time_Cash*L53+Trans_Time_Ticket*M53) -> 525.45156 | O53: =3600/Headway_ETC -> 1500 | AD53: Manual Only | AE53: 1 | AF53: 2 | AG53: 3 | AH53: 4 | AI53: 5 | AJ53: 6 | AK53: 7 | AL53: 8 | AM53: 9 | AN53: 10 | AO53: 11 | AP53: 12 | AQ53: 13 | AR53: 14 | AS53: 15 | AT53: 16 | AU53: 17 | AV53: 18 | AW53: 19 | AX53: 20 | AY53: 21 | BJ53: l/sc for no ETC | BK53: Manual Only | BL53: l/sc under ETC | BM53: 1 | BN53: 2 | BO53: 3 | BP53: 4 | BQ53: 5 | BR53: 6 | BS53: 7 | BT53: 8 | BU53: 9 | BV53: 10 | BW53: 11 | BX53: 12 | BY53: 13 | BZ53: 14 | CA53: 15 | CB53: 16 | CC53: 17 | CD53: 18 | CE53: 19 | CF53: 20 | CG53: 21 | CN53: l/sc under ETC | CO53: 1 | CP53: 2 | CQ53: 3 | CR53: 4 | CS53: 5 | CT53: 6 | CU53: 7 | CV53: 8 | CW53: 9 | CX53: 10 | CY53: 11 | CZ53: 12 | DA53: 13 | DB53: 14 | DC53: 15 | DD53: 16 | DE53: 17 | DF53: 18 | DG53: 19 | DH53: 20 | DI53: 21
H54: 14 | I54: ='Input-Detail'!BH27 -> 0.83 | J54: =1-I54 -> 0.17 | K54: =3600/(Trans_Time_Cash*I54+Trans_Time_Ticket*J54) -> 547.52852 | L54: ='Input-Detail'!BJ27 -> 0.949 | M54: =1-L54 -> 0.051 | N54: =3600/(Trans_Time_Cash*L54+Trans_Time_Ticket*M54) -> 523.82685 | O54: =3600/Headway_ETC -> 1500 | V54: Base | W54: =W7 -> 19016173 | X54: =X7 -> 0 | Y54: ='Input-Detail'!M18 -> 8200 | Z54: ='Input-Detail'!N18 -> 2319.0455 | AA54: ='Input-Detail'!O18 -> 2 | AB54: ='Input-Detail'!P18 -> 0.3 | AC54: =Y54*AB54 -> 2460 | AD54: =Peak_Time_Mor*$BH54*(CH54+BK54)/3600 -> 9.4339293 | BF54: Base | BG54: =$X54 -> 0 | BH54: =$AC54 -> 2460 | BI54: =BH54*(1-BG54) -> 2460 | BJ54: =Peak_Arrival_Manual_Mor/K40 -> 4.4929167 | BK54: =900*Peak_Time_Mor*($BJ54/Total_Lanes-1+SQRT(($BJ54/Total_Lanes-1)^2+8*($BJ54/Total_Lanes)/(Peak_Time_Mor*$K40*Total_Lanes))) -> 0.32787508 | BL54: =Peak_Arrival_Manual_Mor/N40 -> 4.4929167 | BM54: =IF(BM$6<Total_Lanes,900*Peak_Time_Mor*($BL54/(Total_Lanes-BM$6)-1+SQRT(($BL54/(Total_Lanes-BM$6)-1)^2+8*($BL54/(Total_Lanes-BM$6))/(Peak_Time_Mor*$N40*(Total_Lanes-BM$6)))),"-") -> 0.41263012 | BN54: =IF(BN$6<Total_Lanes,900*Peak_Time_Mor*($BL54/(Total_Lanes-BN$6)-1+SQRT(($BL54/(Total_Lanes-BN$6)-1)^2+8*($BL54/(Total_Lanes-BN$6))/(Peak_Time_Mor*$N40*(Total_Lanes-BN$6)))),"-") -> 0.53627187 | BO54: =IF(BO$6<Total_Lanes,900*Peak_Time_Mor*($BL54/(Total_Lanes-BO$6)-1+SQRT(($BL54/(Total_Lanes-BO$6)-1)^2+8*($BL54/(Total_Lanes-BO$6))/(Peak_Time_Mor*$N40*(Total_Lanes-BO$6)))),"-") -> 0.72796533 | BP54: =IF(BP$6<Total_Lanes,900*Peak_Time_Mor*($BL54/(Total_Lanes-BP$6)-1+SQRT(($BL54/(Total_Lanes-BP$6)-1)^2+8*($BL54/(Total_Lanes-BP$6))/(Peak_Time_Mor*$N40*(Total_Lanes-BP$6)))),"-") -> 1.0522007 | BQ54: =IF(BQ$6<Total_Lanes,900*Peak_Time_Mor*($BL54/(Total_Lanes-BQ$6)-1+SQRT(($BL54/(Total_Lanes-BQ$6)-1)^2+8*($BL54/(Total_Lanes-BQ$6))/(Peak_Time_Mor*$N40*(Total_Lanes-BQ$6)))),"-") -> 1.6810918 | BR54: =IF(BR$6<Total_Lanes,900*Peak_Time_Mor*($BL54/(Total_Lanes-BR$6)-1+SQRT(($BL54/(Total_Lanes-BR$6)-1)^2+8*($BL54/(Total_Lanes-BR$6))/(Peak_Time_Mor*$N40*(Total_Lanes-BR$6)))),"-") -> 3.25518 | BS54: =IF(BS$6<Total_Lanes,900*Peak_Time_Mor*($BL54/(Total_Lanes-BS$6)-1+SQRT(($BL54/(Total_Lanes-BS$6)-1)^2+8*($BL54/(Total_Lanes-BS$6))/(Peak_Time_Mor*$N40*(Total_Lanes-BS$6)))),"-") -> 11.301479 | BT54: =IF(BT$6<Total_Lanes,900*Peak_Time_Mor*($BL54/(Total_Lanes-BT$6)-1+SQRT(($BL54/(Total_Lanes-BT$6)-1)^2+8*($BL54/(Total_Lanes-BT$6))/(Peak_Time_Mor*$N40*(Total_Lanes-BT$6)))),"-") -> 458.13324 | ... CG54: =IF(CG$6<Total_Lanes,900*Peak_Time_Mor*($BL54/(Total_Lanes-CG$6)-1+SQRT(($BL54/(Total_Lanes-CG$6)-1)^2+8*($BL54/(Total_Lanes-CG$6))/(Peak_Time_Mor*$N40*(Total_Lanes-CG$6)))),"-") -> - | CH54: =3600/N40 -> 6.575 | CJ54: Base | CK54: =$X54 -> 0 | CL54: =$AC54 -> 2460 | CM54: =CL54*CK54 -> 0
H55: 15 | I55: ='Input-Detail'!BH28 -> 0.83 | J55: =1-I55 -> 0.17 | K55: =3600/(Trans_Time_Cash*I55+Trans_Time_Ticket*J55) -> 547.52852 | L55: ='Input-Detail'!BJ28 -> 0.9575 | M55: =1-L55 -> 0.0425 | N55: =3600/(Trans_Time_Cash*L55+Trans_Time_Ticket*M55) -> 522.21215 | O55: =3600/Headway_ETC -> 1500 | V55: 1 | W55: =W8 -> 19565364 | X55: =X8 -> 0.06998422 | Y55: =Y8 -> 8436.8178 | Z55: =W55/Y55 -> 2319.0455 | AA55: =AA8 -> 2 | AB55: =1-AB8 -> 0.3 | AC55: =Y55*AB55 -> 2531.0454 | AD55: =Peak_Time_Mor*$BH55*(CH55+BK55)/3600 -> 9.7052873 | AE55: =IF(AE$53<Total_Lanes,($BI55*($CH55+BM55)+$CM55*CO55)*Peak_Time_Mor/3600,"-") -> 9.1634394 | AF55: =IF(AF$53<Total_Lanes,($BI55*($CH55+BN55)+$CM55*CP55)*Peak_Time_Mor/3600,"-") -> 9.2875723 | AG55: =IF(AG$53<Total_Lanes,($BI55*($CH55+BO55)+$CM55*CQ55)*Peak_Time_Mor/3600,"-") -> 9.5110131 | AH55: =IF(AH$53<Total_Lanes,($BI55*($CH55+BP55)+$CM55*CR55)*Peak_Time_Mor/3600,"-") -> 9.8885419 | AI55: =IF(AI$53<Total_Lanes,($BI55*($CH55+BQ55)+$CM55*CS55)*Peak_Time_Mor/3600,"-") -> 10.603164 | AJ55: =IF(AJ$53<Total_Lanes,($BI55*($CH55+BR55)+$CM55*CT55)*Peak_Time_Mor/3600,"-") -> 12.292506 | AK55: =IF(AK$53<Total_Lanes,($BI55*($CH55+BS55)+$CM55*CU55)*Peak_Time_Mor/3600,"-") -> 19.283072 | AL55: =IF(AL$53<Total_Lanes,($BI55*($CH55+BT55)+$CM55*CV55)*Peak_Time_Mor/3600,"-") -> 404.71491 | ... AY55: =IF(AY$53<Total_Lanes,($BI55*($CH55+CG55)+$CM55*DI55)*Peak_Time_Mor/3600,"-") -> - | AZ55: =SUMIF(AE55:AY55,BA55,$AE$53:$AY$53) -> 1 | BA55: =MIN(AE55:AY55) -> 9.1634394 | BB55: =IF((SUMIF($BM53:$CG53,$AZ55,$BM55:$CG55)+$CH55)<(SUMIF($CO53:$DI53,$AZ55,$CO55:$DI55)+$DJ55),AZ55+1,AZ55) -> 1 | BC55: =SUMIF($AE$53:$AY$53,$BB55,$AE55:$AY55) -> 9.1634394 | BF55: 1 | BG55: =$X55 -> 0.06998422 | BH55: =$AC55 -> 2531.0454 | BI55: =BH55*(1-BG55) -> 2353.9121 | BJ55: =Peak_Arrival_Manual_Mor/K41 -> 4.2991589 | BK55: =900*Peak_Time_Mor*($BJ55/Total_Lanes-1+SQRT(($BJ55/Total_Lanes-1)^2+8*($BJ55/Total_Lanes)/(Peak_Time_Mor*$K41*Total_Lanes))) -> 0.30584569 | BL55: =Peak_Arrival_Manual_Mor/N41 -> 4.3130536 | BM55: =IF(BM$6<Total_Lanes,900*Peak_Time_Mor*($BL55/(Total_Lanes-BM$6)-1+SQRT(($BL55/(Total_Lanes-BM$6)-1)^2+8*($BL55/(Total_Lanes-BM$6))/(Peak_Time_Mor*$N41*(Total_Lanes-BM$6)))),"-") -> 0.38670937 | BN55: =IF(BN$6<Total_Lanes,900*Peak_Time_Mor*($BL55/(Total_Lanes-BN$6)-1+SQRT(($BL55/(Total_Lanes-BN$6)-1)^2+8*($BL55/(Total_Lanes-BN$6))/(Peak_Time_Mor*$N41*(Total_Lanes-BN$6)))),"-") -> 0.50014593 | BO55: =IF(BO$6<Total_Lanes,900*Peak_Time_Mor*($BL55/(Total_Lanes-BO$6)-1+SQRT(($BL55/(Total_Lanes-BO$6)-1)^2+8*($BL55/(Total_Lanes-BO$6))/(Peak_Time_Mor*$N41*(Total_Lanes-BO$6)))),"-") -> 0.67420707 | BP55: =IF(BP$6<Total_Lanes,900*Peak_Time_Mor*($BL55/(Total_Lanes-BP$6)-1+SQRT(($BL55/(Total_Lanes-BP$6)-1)^2+8*($BL55/(Total_Lanes-BP$6))/(Peak_Time_Mor*$N41*(Total_Lanes-BP$6)))),"-") -> 0.96399078 | BQ55: =IF(BQ$6<Total_Lanes,900*Peak_Time_Mor*($BL55/(Total_Lanes-BQ$6)-1+SQRT(($BL55/(Total_Lanes-BQ$6)-1)^2+8*($BL55/(Total_Lanes-BQ$6))/(Peak_Time_Mor*$N41*(Total_Lanes-BQ$6)))),"-") -> 1.5109507 | BR55: =IF(BR$6<Total_Lanes,900*Peak_Time_Mor*($BL55/(Total_Lanes-BR$6)-1+SQRT(($BL55/(Total_Lanes-BR$6)-1)^2+8*($BL55/(Total_Lanes-BR$6))/(Peak_Time_Mor*$N41*(Total_Lanes-BR$6)))),"-") -> 2.803034 | BS55: =IF(BS$6<Total_Lanes,900*Peak_Time_Mor*($BL55/(Total_Lanes-BS$6)-1+SQRT(($BL55/(Total_Lanes-BS$6)-1)^2+8*($BL55/(Total_Lanes-BS$6))/(Peak_Time_Mor*$N41*(Total_Lanes-BS$6)))),"-") -> 8.1487724 | BT55: =IF(BT$6<Total_Lanes,900*Peak_Time_Mor*($BL55/(Total_Lanes-BT$6)-1+SQRT(($BL55/(Total_Lanes-BT$6)-1)^2+8*($BL55/(Total_Lanes-BT$6))/(Peak_Time_Mor*$N41*(Total_Lanes-BT$6)))),"-") -> 302.88261 | ... CG55: =IF(CG$6<Total_Lanes,900*Peak_Time_Mor*($BL55/(Total_Lanes-CG$6)-1+SQRT(($BL55/(Total_Lanes-CG$6)-1)^2+8*($BL55/(Total_Lanes-CG$6))/(Peak_Time_Mor*$N41*(Total_Lanes-CG$6)))),"-") -> - | CH55: =3600/N41 -> 6.59625 | CJ55: 1 | CK55: =$X55 -> 0.06998422 | CL55: =$AC55 -> 2531.0454 | CM55: =CL55*CK55 -> 177.13324 | CN55: =CM55/O41 -> 0.11808882 | CO55: =IF(CO$53<Total_Lanes,900*Peak_Time_Mor*($CN55/CO$53-1+SQRT(($CN55/CO$53-1)^2+8*($CN55/CO$53)/(Peak_Time_Mor*$O41*CO$53))),"-") -> 0.32132997 | CP55: =IF(CP$53<Total_Lanes,900*Peak_Time_Mor*($CN55/CP$53-1+SQRT(($CN55/CP$53-1)^2+8*($CN55/CP$53)/(Peak_Time_Mor*$O41*CP$53))),"-") -> 0.075297623 | CQ55: =IF(CQ$53<Total_Lanes,900*Peak_Time_Mor*($CN55/CQ$53-1+SQRT(($CN55/CQ$53-1)^2+8*($CN55/CQ$53)/(Peak_Time_Mor*$O41*CQ$53))),"-") -> 0.032780387 | CR55: =IF(CR$53<Total_Lanes,900*Peak_Time_Mor*($CN55/CR$53-1+SQRT(($CN55/CR$53-1)^2+8*($CN55/CR$53)/(Peak_Time_Mor*$O41*CR$53))),"-") -> 0.018252072 | CS55: =IF(CS$53<Total_Lanes,900*Peak_Time_Mor*($CN55/CS$53-1+SQRT(($CN55/CS$53-1)^2+8*($CN55/CS$53)/(Peak_Time_Mor*$O41*CS$53))),"-") -> 0.011610709 | CT55: =IF(CT$53<Total_Lanes,900*Peak_Time_Mor*($CN55/CT$53-1+SQRT(($CN55/CT$53-1)^2+8*($CN55/CT$53)/(Peak_Time_Mor*$O41*CT$53))),"-") -> 0.0080306248 | CU55: =IF(CU$53<Total_Lanes,900*Peak_Time_Mor*($CN55/CU$53-1+SQRT(($CN55/CU$53-1)^2+8*($CN55/CU$53)/(Peak_Time_Mor*$O41*CU$53))),"-") -> 0.005883181 | CV55: =IF(CV$53<Total_Lanes,900*Peak_Time_Mor*($CN55/CV$53-1+SQRT(($CN55/CV$53-1)^2+8*($CN55/CV$53)/(Peak_Time_Mor*$O41*CV$53))),"-") -> 0.0044946716 | ... DI55: =IF(DI$53<Total_Lanes,900*Peak_Time_Mor*($CN55/DI$53-1+SQRT(($CN55/DI$53-1)^2+8*($CN55/DI$53)/(Peak_Time_Mor*$O41*DI$53))),"-") -> - | DJ55: =3600/$O41 -> 2.4
H56: 16 | I56: ='Input-Detail'!BH29 -> 0.83 | J56: =1-I56 -> 0.17 | K56: =3600/(Trans_Time_Cash*I56+Trans_Time_Ticket*J56) -> 547.52852 | L56: ='Input-Detail'!BJ29 -> 0.966 | M56: =1-L56 -> 0.034 | N56: =3600/(Trans_Time_Cash*L56+Trans_Time_Ticket*M56) -> 520.60738 | O56: =3600/Headway_ETC -> 1500 | V56: 2 | W56: =W9 -> 20114556 | X56: =X9 -> 0.16998422 | Y56: =Y9 -> 8673.6357 | Z56: =W56/Y56 -> 2319.0455 | AA56: =AA9 -> 2 | AB56: =1-AB9 -> 0.3 | AC56: =Y56*AB56 -> 2602.0907 | AD56: =Peak_Time_Mor*$BH56*(CH56+BK56)/3600 -> 9.9541178 | AE56: =IF(AE$53<Total_Lanes,($BI56*($CH56+BM56)+$CM56*CO56)*Peak_Time_Mor/3600,"-") -> 8.5942996 | AF56: =IF(AF$53<Total_Lanes,($BI56*($CH56+BN56)+$CM56*CP56)*Peak_Time_Mor/3600,"-") -> 8.5138447 | AG56: =IF(AG$53<Total_Lanes,($BI56*($CH56+BO56)+$CM56*CQ56)*Peak_Time_Mor/3600,"-") -> 8.6577555 | AH56: =IF(AH$53<Total_Lanes,($BI56*($CH56+BP56)+$CM56*CR56)*Peak_Time_Mor/3600,"-") -> 8.9292613 | AI56: =IF(AI$53<Total_Lanes,($BI56*($CH56+BQ56)+$CM56*CS56)*Peak_Time_Mor/3600,"-") -> 9.4326767 | AJ56: =IF(AJ$53<Total_Lanes,($BI56*($CH56+BR56)+$CM56*CT56)*Peak_Time_Mor/3600,"-") -> 10.528916 | AK56: =IF(AK$53<Total_Lanes,($BI56*($CH56+BS56)+$CM56*CU56)*Peak_Time_Mor/3600,"-") -> 14.023876 | AL56: =IF(AL$53<Total_Lanes,($BI56*($CH56+BT56)+$CM56*CV56)*Peak_Time_Mor/3600,"-") -> 85.447453 | ... AY56: =IF(AY$53<Total_Lanes,($BI56*($CH56+CG56)+$CM56*DI56)*Peak_Time_Mor/3600,"-") -> - | AZ56: =SUMIF(AE56:AY56,BA56,$AE$53:$AY$53) -> 2 | BA56: =MIN(AE56:AY56) -> 8.5138447 | BB56: =IF((SUMIF($BM54:$CG54,$AZ56,$BM56:$CG56)+$CH56)<(SUMIF($CO54:$DI54,$AZ56,$CO56:$DI56)+$DJ56),AZ56+1,AZ56) -> 2 | BC56: =SUMIF($AE$53:$AY$53,$BB56,$AE56:$AY56) -> 8.5138447 | BF56: 2 | BG56: =$X56 -> 0.16998422 | BH56: =$AC56 -> 2602.0907 | BI56: =BH56*(1-BG56) -> 2159.7763 | BJ56: =Peak_Arrival_Manual_Mor/K42 -> 3.9445915 | BK56: =900*Peak_Time_Mor*($BJ56/Total_Lanes-1+SQRT(($BJ56/Total_Lanes-1)^2+8*($BJ56/Total_Lanes)/(Peak_Time_Mor*$K42*Total_Lanes))) -> 0.26827535 | BL56: =Peak_Arrival_Manual_Mor/N42 -> 3.9700889 | BM56: =IF(BM$6<Total_Lanes,900*Peak_Time_Mor*($BL56/(Total_Lanes-BM$6)-1+SQRT(($BL56/(Total_Lanes-BM$6)-1)^2+8*($BL56/(Total_Lanes-BM$6))/(Peak_Time_Mor*$N42*(Total_Lanes-BM$6)))),"-") -> 0.33969374 | BN56: =IF(BN$6<Total_Lanes,900*Peak_Time_Mor*($BL56/(Total_Lanes-BN$6)-1+SQRT(($BL56/(Total_Lanes-BN$6)-1)^2+8*($BL56/(Total_Lanes-BN$6))/(Peak_Time_Mor*$N42*(Total_Lanes-BN$6)))),"-") -> 0.43560828 | BO56: =IF(BO$6<Total_Lanes,900*Peak_Time_Mor*($BL56/(Total_Lanes-BO$6)-1+SQRT(($BL56/(Total_Lanes-BO$6)-1)^2+8*($BL56/(Total_Lanes-BO$6))/(Peak_Time_Mor*$N42*(Total_Lanes-BO$6)))),"-") -> 0.58018453 | BP56: =IF(BP$6<Total_Lanes,900*Peak_Time_Mor*($BL56/(Total_Lanes-BP$6)-1+SQRT(($BL56/(Total_Lanes-BP$6)-1)^2+8*($BL56/(Total_Lanes-BP$6))/(Peak_Time_Mor*$N42*(Total_Lanes-BP$6)))),"-") -> 0.81454241 | BQ56: =IF(BQ$6<Total_Lanes,900*Peak_Time_Mor*($BL56/(Total_Lanes-BQ$6)-1+SQRT(($BL56/(Total_Lanes-BQ$6)-1)^2+8*($BL56/(Total_Lanes-BQ$6))/(Peak_Time_Mor*$N42*(Total_Lanes-BQ$6)))),"-") -> 1.2377172 | BR56: =IF(BR$6<Total_Lanes,900*Peak_Time_Mor*($BL56/(Total_Lanes-BR$6)-1+SQRT(($BL56/(Total_Lanes-BR$6)-1)^2+8*($BL56/(Total_Lanes-BR$6))/(Peak_Time_Mor*$N42*(Total_Lanes-BR$6)))),"-") -> 2.1532714 | BS56: =IF(BS$6<Total_Lanes,900*Peak_Time_Mor*($BL56/(Total_Lanes-BS$6)-1+SQRT(($BL56/(Total_Lanes-BS$6)-1)^2+8*($BL56/(Total_Lanes-BS$6))/(Peak_Time_Mor*$N42*(Total_Lanes-BS$6)))),"-") -> 5.0671858 | BT56: =IF(BT$6<Total_Lanes,900*Peak_Time_Mor*($BL56/(Total_Lanes-BT$6)-1+SQRT(($BL56/(Total_Lanes-BT$6)-1)^2+8*($BL56/(Total_Lanes-BT$6))/(Peak_Time_Mor*$N42*(Total_Lanes-BT$6)))),"-") -> 64.593734 | ... CG56: =IF(CG$6<Total_Lanes,900*Peak_Time_Mor*($BL56/(Total_Lanes-CG$6)-1+SQRT(($BL56/(Total_Lanes-CG$6)-1)^2+8*($BL56/(Total_Lanes-CG$6))/(Peak_Time_Mor*$N42*(Total_Lanes-CG$6)))),"-") -> - | CH56: =3600/N42 -> 6.6175 | CJ56: 2 | CK56: =$X56 -> 0.16998422 | CL56: =$AC56 -> 2602.0907 | CM56: =CL56*CK56 -> 442.31436 | CN56: =CM56/O42 -> 0.29487624 | CO56: =IF(CO$53<Total_Lanes,900*Peak_Time_Mor*($CN56/CO$53-1+SQRT(($CN56/CO$53-1)^2+8*($CN56/CO$53)/(Peak_Time_Mor*$O42*CO$53))),"-") -> 1.0032613 | CP56: =IF(CP$53<Total_Lanes,900*Peak_Time_Mor*($CN56/CP$53-1+SQRT(($CN56/CP$53-1)^2+8*($CN56/CP$53)/(Peak_Time_Mor*$O42*CP$53))),"-") -> 0.20750844 | CQ56: =IF(CQ$53<Total_Lanes,900*Peak_Time_Mor*($CN56/CQ$53-1+SQRT(($CN56/CQ$53-1)^2+8*($CN56/CQ$53)/(Peak_Time_Mor*$O42*CQ$53))),"-") -> 0.087202907 | CR56: =IF(CR$53<Total_Lanes,900*Peak_Time_Mor*($CN56/CR$53-1+SQRT(($CN56/CR$53-1)^2+8*($CN56/CR$53)/(Peak_Time_Mor*$O42*CR$53))),"-") -> 0.047750958 | CS56: =IF(CS$53<Total_Lanes,900*Peak_Time_Mor*($CN56/CS$53-1+SQRT(($CN56/CS$53-1)^2+8*($CN56/CS$53)/(Peak_Time_Mor*$O42*CS$53))),"-") -> 0.030081959 | CT56: =IF(CT$53<Total_Lanes,900*Peak_Time_Mor*($CN56/CT$53-1+SQRT(($CN56/CT$53-1)^2+8*($CN56/CT$53)/(Peak_Time_Mor*$O42*CT$53))),"-") -> 0.02067436 | CU56: =IF(CU$53<Total_Lanes,900*Peak_Time_Mor*($CN56/CU$53-1+SQRT(($CN56/CU$53-1)^2+8*($CN56/CU$53)/(Peak_Time_Mor*$O42*CU$53))),"-") -> 0.015078019 | CV56: =IF(CV$53<Total_Lanes,900*Peak_Time_Mor*($CN56/CV$53-1+SQRT(($CN56/CV$53-1)^2+8*($CN56/CV$53)/(Peak_Time_Mor*$O42*CV$53))),"-") -> 0.011481007 | ... DI56: =IF(DI$53<Total_Lanes,900*Peak_Time_Mor*($CN56/DI$53-1+SQRT(($CN56/DI$53-1)^2+8*($CN56/DI$53)/(Peak_Time_Mor*$O42*DI$53))),"-") -> - | DJ56: =3600/$O42 -> 2.4
H57: 17 | I57: ='Input-Detail'!BH30 -> 0.83 | J57: =1-I57 -> 0.17 | K57: =3600/(Trans_Time_Cash*I57+Trans_Time_Ticket*J57) -> 547.52852 | L57: ='Input-Detail'!BJ30 -> 0.9745 | M57: =1-L57 -> 0.0255 | N57: =3600/(Trans_Time_Cash*L57+Trans_Time_Ticket*M57) -> 519.01243 | O57: =3600/Headway_ETC -> 1500 | V57: 3 | W57: =W10 -> 20663747 | X57: =X10 -> 0.23348622 | Y57: =Y10 -> 8910.4535 | Z57: =W57/Y57 -> 2319.0455 | AA57: =AA10 -> 2 | AB57: =1-AB10 -> 0.3 | AC57: =Y57*AB57 -> 2673.1361 | AD57: =Peak_Time_Mor*$BH57*(CH57+BK57)/3600 -> 10.227762 | AE57: =IF(AE$53<Total_Lanes,($BI57*($CH57+BM57)+$CM57*CO57)*Peak_Time_Mor/3600,"-") -> 8.5090538 | AF57: =IF(AF$53<Total_Lanes,($BI57*($CH57+BN57)+$CM57*CP57)*Peak_Time_Mor/3600,"-") -> 8.1252815 | AG57: =IF(AG$53<Total_Lanes,($BI57*($CH57+BO57)+$CM57*CQ57)*Peak_Time_Mor/3600,"-") -> 8.2092462 | AH57: =IF(AH$53<Total_Lanes,($BI57*($CH57+BP57)+$CM57*CR57)*Peak_Time_Mor/3600,"-") -> 8.4264453 | AI57: =IF(AI$53<Total_Lanes,($BI57*($CH57+BQ57)+$CM57*CS57)*Peak_Time_Mor/3600,"-") -> 8.8376333 | AJ57: =IF(AJ$53<Total_Lanes,($BI57*($CH57+BR57)+$CM57*CT57)*Peak_Time_Mor/3600,"-") -> 9.7067675 | AK57: =IF(AK$53<Total_Lanes,($BI57*($CH57+BS57)+$CM57*CU57)*Peak_Time_Mor/3600,"-") -> 12.218525 | AL57: =IF(AL$53<Total_Lanes,($BI57*($CH57+BT57)+$CM57*CV57)*Peak_Time_Mor/3600,"-") -> 36.187166 | ... AY57: =IF(AY$53<Total_Lanes,($BI57*($CH57+CG57)+$CM57*DI57)*Peak_Time_Mor/3600,"-") -> - | AZ57: =SUMIF(AE57:AY57,BA57,$AE$53:$AY$53) -> 2 | BA57: =MIN(AE57:AY57) -> 8.1252815 | BB57: =IF((SUMIF($BM55:$CG55,$AZ57,$BM57:$CG57)+$CH57)<(SUMIF($CO55:$DI55,$AZ57,$CO57:$DI57)+$DJ57),AZ57+1,AZ57) -> 2 | BC57: =SUMIF($AE$53:$AY$53,$BB57,$AE57:$AY57) -> 8.1252815 | BF57: 3 | BG57: =$X57 -> 0.23348622 | BH57: =$AC57 -> 2673.1361 | BI57: =BH57*(1-BG57) -> 2048.9956 | BJ57: =Peak_Arrival_Manual_Mor/K43 -> 3.7422628 | BK57: =900*Peak_Time_Mor*($BJ57/Total_Lanes-1+SQRT(($BJ57/Total_Lanes-1)^2+8*($BJ57/Total_Lanes)/(Peak_Time_Mor*$K43*Total_Lanes))) -> 0.24828142 | BL57: =Peak_Arrival_Manual_Mor/N43 -> 3.7785471 | BM57: =IF(BM$6<Total_Lanes,900*Peak_Time_Mor*($BL57/(Total_Lanes-BM$6)-1+SQRT(($BL57/(Total_Lanes-BM$6)-1)^2+8*($BL57/(Total_Lanes-BM$6))/(Peak_Time_Mor*$N43*(Total_Lanes-BM$6)))),"-") -> 0.31574456 | BN57: =IF(BN$6<Total_Lanes,900*Peak_Time_Mor*($BL57/(Total_Lanes-BN$6)-1+SQRT(($BL57/(Total_Lanes-BN$6)-1)^2+8*($BL57/(Total_Lanes-BN$6))/(Peak_Time_Mor*$N43*(Total_Lanes-BN$6)))),"-") -> 0.40312635 | BO57: =IF(BO$6<Total_Lanes,900*Peak_Time_Mor*($BL57/(Total_Lanes-BO$6)-1+SQRT(($BL57/(Total_Lanes-BO$6)-1)^2+8*($BL57/(Total_Lanes-BO$6))/(Peak_Time_Mor*$N43*(Total_Lanes-BO$6)))),"-") -> 0.53366207 | BP57: =IF(BP$6<Total_Lanes,900*Peak_Time_Mor*($BL57/(Total_Lanes-BP$6)-1+SQRT(($BL57/(Total_Lanes-BP$6)-1)^2+8*($BL57/(Total_Lanes-BP$6))/(Peak_Time_Mor*$N43*(Total_Lanes-BP$6)))),"-") -> 0.74248813 | BQ57: =IF(BQ$6<Total_Lanes,900*Peak_Time_Mor*($BL57/(Total_Lanes-BQ$6)-1+SQRT(($BL57/(Total_Lanes-BQ$6)-1)^2+8*($BL57/(Total_Lanes-BQ$6))/(Peak_Time_Mor*$N43*(Total_Lanes-BQ$6)))),"-") -> 1.111655 | BR57: =IF(BR$6<Total_Lanes,900*Peak_Time_Mor*($BL57/(Total_Lanes-BR$6)-1+SQRT(($BL57/(Total_Lanes-BR$6)-1)^2+8*($BL57/(Total_Lanes-BR$6))/(Peak_Time_Mor*$N43*(Total_Lanes-BR$6)))),"-") -> 1.8793639 | BS57: =IF(BS$6<Total_Lanes,900*Peak_Time_Mor*($BL57/(Total_Lanes-BS$6)-1+SQRT(($BL57/(Total_Lanes-BS$6)-1)^2+8*($BL57/(Total_Lanes-BS$6))/(Peak_Time_Mor*$N43*(Total_Lanes-BS$6)))),"-") -> 4.0883698 | BT57: =IF(BT$6<Total_Lanes,900*Peak_Time_Mor*($BL57/(Total_Lanes-BT$6)-1+SQRT(($BL57/(Total_Lanes-BT$6)-1)^2+8*($BL57/(Total_Lanes-BT$6))/(Peak_Time_Mor*$N43*(Total_Lanes-BT$6)))),"-") -> 25.145908 | ... CG57: =IF(CG$6<Total_Lanes,900*Peak_Time_Mor*($BL57/(Total_Lanes-CG$6)-1+SQRT(($BL57/(Total_Lanes-CG$6)-1)^2+8*($BL57/(Total_Lanes-CG$6))/(Peak_Time_Mor*$N43*(Total_Lanes-CG$6)))),"-") -> - | CH57: =3600/N43 -> 6.63875 | CJ57: 3 | CK57: =$X57 -> 0.23348622 | CL57: =$AC57 -> 2673.1361 | CM57: =CL57*CK57 -> 624.14044 | CN57: =CM57/O43 -> 0.41609362 | CO57: =IF(CO$53<Total_Lanes,900*Peak_Time_Mor*($CN57/CO$53-1+SQRT(($CN57/CO$53-1)^2+8*($CN57/CO$53)/(Peak_Time_Mor*$O43*CO$53))),"-") -> 1.7088588 | CP57: =IF(CP$53<Total_Lanes,900*Peak_Time_Mor*($CN57/CP$53-1+SQRT(($CN57/CP$53-1)^2+8*($CN57/CP$53)/(Peak_Time_Mor*$O43*CP$53))),"-") -> 0.31520623 | CQ57: =IF(CQ$53<Total_Lanes,900*Peak_Time_Mor*($CN57/CQ$53-1+SQRT(($CN57/CQ$53-1)^2+8*($CN57/CQ$53)/(Peak_Time_Mor*$O43*CQ$53))),"-") -> 0.12882087 | CR57: =IF(CR$53<Total_Lanes,900*Peak_Time_Mor*($CN57/CR$53-1+SQRT(($CN57/CR$53-1)^2+8*($CN57/CR$53)/(Peak_Time_Mor*$O43*CR$53))),"-") -> 0.069658846 | CS57: =IF(CS$53<Total_Lanes,900*Peak_Time_Mor*($CN57/CS$53-1+SQRT(($CN57/CS$53-1)^2+8*($CN57/CS$53)/(Peak_Time_Mor*$O43*CS$53))),"-") -> 0.043570328 | CT57: =IF(CT$53<Total_Lanes,900*Peak_Time_Mor*($CN57/CT$53-1+SQRT(($CN57/CT$53-1)^2+8*($CN57/CT$53)/(Peak_Time_Mor*$O43*CT$53))),"-") -> 0.029806368 | CU57: =IF(CU$53<Total_Lanes,900*Peak_Time_Mor*($CN57/CU$53-1+SQRT(($CN57/CU$53-1)^2+8*($CN57/CU$53)/(Peak_Time_Mor*$O43*CU$53))),"-") -> 0.021667951 | CV57: =IF(CV$53<Total_Lanes,900*Peak_Time_Mor*($CN57/CV$53-1+SQRT(($CN57/CV$53-1)^2+8*($CN57/CV$53)/(Peak_Time_Mor*$O43*CV$53))),"-") -> 0.016459523 | ... DI57: =IF(DI$53<Total_Lanes,900*Peak_Time_Mor*($CN57/DI$53-1+SQRT(($CN57/DI$53-1)^2+8*($CN57/DI$53)/(Peak_Time_Mor*$O43*DI$53))),"-") -> - | DJ57: =3600/$O43 -> 2.4
H58: 18 | I58: ='Input-Detail'!BH31 -> 0.83 | J58: =1-I58 -> 0.17 | K58: =3600/(Trans_Time_Cash*I58+Trans_Time_Ticket*J58) -> 547.52852 | L58: ='Input-Detail'!BJ31 -> 0.983 | M58: =1-L58 -> 0.017 | N58: =3600/(Trans_Time_Cash*L58+Trans_Time_Ticket*M58) -> 517.42724 | O58: =3600/Headway_ETC -> 1500 | V58: 4 | W58: =W11 -> 21212938 | X58: =X11 -> 0.29229151 | Y58: =Y11 -> 9147.2714 | Z58: =W58/Y58 -> 2319.0455 | AA58: =AA11 -> 2 | AB58: =1-AB11 -> 0.3 | AC58: =Y58*AB58 -> 2744.1814 | AD58: =Peak_Time_Mor*$BH58*(CH58+BK58)/3600 -> 10.503952 | AE58: =IF(AE$53<Total_Lanes,($BI58*($CH58+BM58)+$CM58*CO58)*Peak_Time_Mor/3600,"-") -> 8.7296473 | AF58: =IF(AF$53<Total_Lanes,($BI58*($CH58+BN58)+$CM58*CP58)*Peak_Time_Mor/3600,"-") -> 7.7836883 | AG58: =IF(AG$53<Total_Lanes,($BI58*($CH58+BO58)+$CM58*CQ58)*Peak_Time_Mor/3600,"-") -> 7.7934119 | AH58: =IF(AH$53<Total_Lanes,($BI58*($CH58+BP58)+$CM58*CR58)*Peak_Time_Mor/3600,"-") -> 7.9589552 | AI58: =IF(AI$53<Total_Lanes,($BI58*($CH58+BQ58)+$CM58*CS58)*Peak_Time_Mor/3600,"-") -> 8.2931694 | AJ58: =IF(AJ$53<Total_Lanes,($BI58*($CH58+BR58)+$CM58*CT58)*Peak_Time_Mor/3600,"-") -> 8.9886215 | AK58: =IF(AK$53<Total_Lanes,($BI58*($CH58+BS58)+$CM58*CU58)*Peak_Time_Mor/3600,"-") -> 10.855516 | AL58: =IF(AL$53<Total_Lanes,($BI58*($CH58+BT58)+$CM58*CV58)*Peak_Time_Mor/3600,"-") -> 22.458336 | ... AY58: =IF(AY$53<Total_Lanes,($BI58*($CH58+CG58)+$CM58*DI58)*Peak_Time_Mor/3600,"-") -> - | AZ58: =SUMIF(AE58:AY58,BA58,$AE$53:$AY$53) -> 2 | BA58: =MIN(AE58:AY58) -> 7.7836883 | BB58: =IF((SUMIF($BM56:$CG56,$AZ58,$BM58:$CG58)+$CH58)<(SUMIF($CO56:$DI56,$AZ58,$CO58:$DI58)+$DJ58),AZ58+1,AZ58) -> 2 | BC58: =SUMIF($AE$53:$AY$53,$BB58,$AE58:$AY58) -> 7.7836883 | BF58: 4 | BG58: =$X58 -> 0.29229151 | BH58: =$AC58 -> 2744.1814 | BI58: =BH58*(1-BG58) -> 1942.0805 | BJ58: =Peak_Arrival_Manual_Mor/K44 -> 3.5469942 | BK58: =900*Peak_Time_Mor*($BJ58/Total_Lanes-1+SQRT(($BJ58/Total_Lanes-1)^2+8*($BJ58/Total_Lanes)/(Peak_Time_Mor*$K44*Total_Lanes))) -> 0.22989232 | BL58: =Peak_Arrival_Manual_Mor/N44 -> 3.5928489 | BM58: =IF(BM$6<Total_Lanes,900*Peak_Time_Mor*($BL58/(Total_Lanes-BM$6)-1+SQRT(($BL58/(Total_Lanes-BM$6)-1)^2+8*($BL58/(Total_Lanes-BM$6))/(Peak_Time_Mor*$N44*(Total_Lanes-BM$6)))),"-") -> 0.293641 | BN58: =IF(BN$6<Total_Lanes,900*Peak_Time_Mor*($BL58/(Total_Lanes-BN$6)-1+SQRT(($BL58/(Total_Lanes-BN$6)-1)^2+8*($BL58/(Total_Lanes-BN$6))/(Peak_Time_Mor*$N44*(Total_Lanes-BN$6)))),"-") -> 0.3734031 | BO58: =IF(BO$6<Total_Lanes,900*Peak_Time_Mor*($BL58/(Total_Lanes-BO$6)-1+SQRT(($BL58/(Total_Lanes-BO$6)-1)^2+8*($BL58/(Total_Lanes-BO$6))/(Peak_Time_Mor*$N44*(Total_Lanes-BO$6)))),"-") -> 0.49159049 | BP58: =IF(BP$6<Total_Lanes,900*Peak_Time_Mor*($BL58/(Total_Lanes-BP$6)-1+SQRT(($BL58/(Total_Lanes-BP$6)-1)^2+8*($BL58/(Total_Lanes-BP$6))/(Peak_Time_Mor*$N44*(Total_Lanes-BP$6)))),"-") -> 0.67844822 | BQ58: =IF(BQ$6<Total_Lanes,900*Peak_Time_Mor*($BL58/(Total_Lanes-BQ$6)-1+SQRT(($BL58/(Total_Lanes-BQ$6)-1)^2+8*($BL58/(Total_Lanes-BQ$6))/(Peak_Time_Mor*$N44*(Total_Lanes-BQ$6)))),"-") -> 1.0027099 | BR58: =IF(BR$6<Total_Lanes,900*Peak_Time_Mor*($BL58/(Total_Lanes-BR$6)-1+SQRT(($BL58/(Total_Lanes-BR$6)-1)^2+8*($BL58/(Total_Lanes-BR$6))/(Peak_Time_Mor*$N44*(Total_Lanes-BR$6)))),"-") -> 1.65486 | BS58: =IF(BS$6<Total_Lanes,900*Peak_Time_Mor*($BL58/(Total_Lanes-BS$6)-1+SQRT(($BL58/(Total_Lanes-BS$6)-1)^2+8*($BL58/(Total_Lanes-BS$6))/(Peak_Time_Mor*$N44*(Total_Lanes-BS$6)))),"-") -> 3.3896267 | BT58: =IF(BT$6<Total_Lanes,900*Peak_Time_Mor*($BL58/(Total_Lanes-BT$6)-1+SQRT(($BL58/(Total_Lanes-BT$6)-1)^2+8*($BL58/(Total_Lanes-BT$6))/(Peak_Time_Mor*$N44*(Total_Lanes-BT$6)))),"-") -> 14.146434 | ... CG58: =IF(CG$6<Total_Lanes,900*Peak_Time_Mor*($BL58/(Total_Lanes-CG$6)-1+SQRT(($BL58/(Total_Lanes-CG$6)-1)^2+8*($BL58/(Total_Lanes-CG$6))/(Peak_Time_Mor*$N44*(Total_Lanes-CG$6)))),"-") -> - | CH58: =3600/N44 -> 6.66 | CJ58: 4 | CK58: =$X58 -> 0.29229151 | CL58: =$AC58 -> 2744.1814 | CM58: =CL58*CK58 -> 802.10092 | CN58: =CM58/O44 -> 0.53473395 | CO58: =IF(CO$53<Total_Lanes,900*Peak_Time_Mor*($CN58/CO$53-1+SQRT(($CN58/CO$53-1)^2+8*($CN58/CO$53)/(Peak_Time_Mor*$O44*CO$53))),"-") -> 2.7538114 | CP58: =IF(CP$53<Total_Lanes,900*Peak_Time_Mor*($CN58/CP$53-1+SQRT(($CN58/CP$53-1)^2+8*($CN58/CP$53)/(Peak_Time_Mor*$O44*CP$53))),"-") -> 0.43785511 | CQ58: =IF(CQ$53<Total_Lanes,900*Peak_Time_Mor*($CN58/CQ$53-1+SQRT(($CN58/CQ$53-1)^2+8*($CN58/CQ$53)/(Peak_Time_Mor*$O44*CQ$53))),"-") -> 0.17351558 | CR58: =IF(CR$53<Total_Lanes,900*Peak_Time_Mor*($CN58/CR$53-1+SQRT(($CN58/CR$53-1)^2+8*($CN58/CR$53)/(Peak_Time_Mor*$O44*CR$53))),"-") -> 0.092584766 | CS58: =IF(CS$53<Total_Lanes,900*Peak_Time_Mor*($CN58/CS$53-1+SQRT(($CN58/CS$53-1)^2+8*($CN58/CS$53)/(Peak_Time_Mor*$O44*CS$53))),"-") -> 0.057480944 | CT58: =IF(CT$53<Total_Lanes,900*Peak_Time_Mor*($CN58/CT$53-1+SQRT(($CN58/CT$53-1)^2+8*($CN58/CT$53)/(Peak_Time_Mor*$O44*CT$53))),"-") -> 0.039136435 | CU58: =IF(CU$53<Total_Lanes,900*Peak_Time_Mor*($CN58/CU$53-1+SQRT(($CN58/CU$53-1)^2+8*($CN58/CU$53)/(Peak_Time_Mor*$O44*CU$53))),"-") -> 0.028357037 | CV58: =IF(CV$53<Total_Lanes,900*Peak_Time_Mor*($CN58/CV$53-1+SQRT(($CN58/CV$53-1)^2+8*($CN58/CV$53)/(Peak_Time_Mor*$O44*CV$53))),"-") -> 0.02148874 | ... DI58: =IF(DI$53<Total_Lanes,900*Peak_Time_Mor*($CN58/DI$53-1+SQRT(($CN58/DI$53-1)^2+8*($CN58/DI$53)/(Peak_Time_Mor*$O44*DI$53))),"-") -> - | DJ58: =3600/$O44 -> 2.4
H59: 19 | I59: ='Input-Detail'!BH32 -> 0.83 | J59: =1-I59 -> 0.17 | K59: =3600/(Trans_Time_Cash*I59+Trans_Time_Ticket*J59) -> 547.52852 | L59: ='Input-Detail'!BJ32 -> 0.9915 | M59: =1-L59 -> 0.0085 | N59: =3600/(Trans_Time_Cash*L59+Trans_Time_Ticket*M59) -> 515.85169 | O59: =3600/Headway_ETC -> 1500 | V59: 5 | W59: =W12 -> 21762130 | X59: =X12 -> 0.34713691 | Y59: =Y12 -> 9384.0892 | Z59: =W59/Y59 -> 2319.0455 | AA59: =AA12 -> 2 | AB59: =1-AB12 -> 0.3 | AC59: =Y59*AB59 -> 2815.2268 | AD59: =Peak_Time_Mor*$BH59*(CH59+BK59)/3600 -> 10.782368 | AE59: =IF(AE$53<Total_Lanes,($BI59*($CH59+BM59)+$CM59*CO59)*Peak_Time_Mor/3600,"-") -> 9.5282902 | AF59: =IF(AF$53<Total_Lanes,($BI59*($CH59+BN59)+$CM59*CP59)*Peak_Time_Mor/3600,"-") -> 7.4899693 | AG59: =IF(AG$53<Total_Lanes,($BI59*($CH59+BO59)+$CM59*CQ59)*Peak_Time_Mor/3600,"-") -> 7.4051694 | AH59: =IF(AH$53<Total_Lanes,($BI59*($CH59+BP59)+$CM59*CR59)*Peak_Time_Mor/3600,"-") -> 7.5192152 | AI59: =IF(AI$53<Total_Lanes,($BI59*($CH59+BQ59)+$CM59*CS59)*Peak_Time_Mor/3600,"-") -> 7.7870242 | AJ59: =IF(AJ$53<Total_Lanes,($BI59*($CH59+BR59)+$CM59*CT59)*Peak_Time_Mor/3600,"-") -> 8.3452801 | AK59: =IF(AK$53<Total_Lanes,($BI59*($CH59+BS59)+$CM59*CU59)*Peak_Time_Mor/3600,"-") -> 9.7630544 | AL59: =IF(AL$53<Total_Lanes,($BI59*($CH59+BT59)+$CM59*CV59)*Peak_Time_Mor/3600,"-") -> 16.541012 | ... AY59: =IF(AY$53<Total_Lanes,($BI59*($CH59+CG59)+$CM59*DI59)*Peak_Time_Mor/3600,"-") -> - | AZ59: =SUMIF(AE59:AY59,BA59,$AE$53:$AY$53) -> 3 | BA59: =MIN(AE59:AY59) -> 7.4051694 | BB59: =IF((SUMIF($BM57:$CG57,$AZ59,$BM59:$CG59)+$CH59)<(SUMIF($CO57:$DI57,$AZ59,$CO59:$DI59)+$DJ59),AZ59+1,AZ59) -> 3 | BC59: =SUMIF($AE$53:$AY$53,$BB59,$AE59:$AY59) -> 7.4051694 | BF59: 5 | BG59: =$X59 -> 0.34713691 | BH59: =$AC59 -> 2815.2268 | BI59: =BH59*(1-BG59) -> 1837.9577 | BJ59: =Peak_Arrival_Manual_Mor/K45 -> 3.3568254 | BK59: =900*Peak_Time_Mor*($BJ59/Total_Lanes-1+SQRT(($BJ59/Total_Lanes-1)^2+8*($BJ59/Total_Lanes)/(Peak_Time_Mor*$K45*Total_Lanes))) -> 0.21278174 | BL59: =Peak_Arrival_Manual_Mor/N45 -> 3.4110707 | BM59: =IF(BM$6<Total_Lanes,900*Peak_Time_Mor*($BL59/(Total_Lanes-BM$6)-1+SQRT(($BL59/(Total_Lanes-BM$6)-1)^2+8*($BL59/(Total_Lanes-BM$6))/(Peak_Time_Mor*$N45*(Total_Lanes-BM$6)))),"-") -> 0.27297792 | BN59: =IF(BN$6<Total_Lanes,900*Peak_Time_Mor*($BL59/(Total_Lanes-BN$6)-1+SQRT(($BL59/(Total_Lanes-BN$6)-1)^2+8*($BL59/(Total_Lanes-BN$6))/(Peak_Time_Mor*$N45*(Total_Lanes-BN$6)))),"-") -> 0.34583607 | BO59: =IF(BO$6<Total_Lanes,900*Peak_Time_Mor*($BL59/(Total_Lanes-BO$6)-1+SQRT(($BL59/(Total_Lanes-BO$6)-1)^2+8*($BL59/(Total_Lanes-BO$6))/(Peak_Time_Mor*$N45*(Total_Lanes-BO$6)))),"-") -> 0.45299075 | BP59: =IF(BP$6<Total_Lanes,900*Peak_Time_Mor*($BL59/(Total_Lanes-BP$6)-1+SQRT(($BL59/(Total_Lanes-BP$6)-1)^2+8*($BL59/(Total_Lanes-BP$6))/(Peak_Time_Mor*$N45*(Total_Lanes-BP$6)))),"-") -> 0.62060689 | BQ59: =IF(BQ$6<Total_Lanes,900*Peak_Time_Mor*($BL59/(Total_Lanes-BQ$6)-1+SQRT(($BL59/(Total_Lanes-BQ$6)-1)^2+8*($BL59/(Total_Lanes-BQ$6))/(Peak_Time_Mor*$N45*(Total_Lanes-BQ$6)))),"-") -> 0.90671794 | BR59: =IF(BR$6<Total_Lanes,900*Peak_Time_Mor*($BL59/(Total_Lanes-BR$6)-1+SQRT(($BL59/(Total_Lanes-BR$6)-1)^2+8*($BL59/(Total_Lanes-BR$6))/(Peak_Time_Mor*$N45*(Total_Lanes-BR$6)))),"-") -> 1.4657753 | BS59: =IF(BS$6<Total_Lanes,900*Peak_Time_Mor*($BL59/(Total_Lanes-BS$6)-1+SQRT(($BL59/(Total_Lanes-BS$6)-1)^2+8*($BL59/(Total_Lanes-BS$6))/(Peak_Time_Mor*$N45*(Total_Lanes-BS$6)))),"-") -> 2.8614685 | BT59: =IF(BT$6<Total_Lanes,900*Peak_Time_Mor*($BL59/(Total_Lanes-BT$6)-1+SQRT(($BL59/(Total_Lanes-BT$6)-1)^2+8*($BL59/(Total_Lanes-BT$6))/(Peak_Time_Mor*$N45*(Total_Lanes-BT$6)))),"-") -> 9.504013 | ... CG59: =IF(CG$6<Total_Lanes,900*Peak_Time_Mor*($BL59/(Total_Lanes-CG$6)-1+SQRT(($BL59/(Total_Lanes-CG$6)-1)^2+8*($BL59/(Total_Lanes-CG$6))/(Peak_Time_Mor*$N45*(Total_Lanes-CG$6)))),"-") -> - | CH59: =3600/N45 -> 6.68125 | CJ59: 5 | CK59: =$X59 -> 0.34713691 | CL59: =$AC59 -> 2815.2268 | CM59: =CL59*CK59 -> 977.26911 | CN59: =CM59/O45 -> 0.65151274 | CO59: =IF(CO$53<Total_Lanes,900*Peak_Time_Mor*($CN59/CO$53-1+SQRT(($CN59/CO$53-1)^2+8*($CN59/CO$53)/(Peak_Time_Mor*$O45*CO$53))),"-") -> 4.4709752 | CP59: =IF(CP$53<Total_Lanes,900*Peak_Time_Mor*($CN59/CP$53-1+SQRT(($CN59/CP$53-1)^2+8*($CN59/CP$53)/(Peak_Time_Mor*$O45*CP$53))),"-") -> 0.57963368 | CQ59: =IF(CQ$53<Total_Lanes,900*Peak_Time_Mor*($CN59/CQ$53-1+SQRT(($CN59/CQ$53-1)^2+8*($CN59/CQ$53)/(Peak_Time_Mor*$O45*CQ$53))),"-") -> 0.22191696 | CR59: =IF(CR$53<Total_Lanes,900*Peak_Time_Mor*($CN59/CR$53-1+SQRT(($CN59/CR$53-1)^2+8*($CN59/CR$53)/(Peak_Time_Mor*$O45*CR$53))),"-") -> 0.11673704 | CS59: =IF(CS$53<Total_Lanes,900*Peak_Time_Mor*($CN59/CS$53-1+SQRT(($CN59/CS$53-1)^2+8*($CN59/CS$53)/(Peak_Time_Mor*$O45*CS$53))),"-") -> 0.071914418 | CT59: =IF(CT$53<Total_Lanes,900*Peak_Time_Mor*($CN59/CT$53-1+SQRT(($CN59/CT$53-1)^2+8*($CN59/CT$53)/(Peak_Time_Mor*$O45*CT$53))),"-") -> 0.04872427 | CU59: =IF(CU$53<Total_Lanes,900*Peak_Time_Mor*($CN59/CU$53-1+SQRT(($CN59/CU$53-1)^2+8*($CN59/CU$53)/(Peak_Time_Mor*$O45*CU$53))),"-") -> 0.035185294 | CV59: =IF(CV$53<Total_Lanes,900*Peak_Time_Mor*($CN59/CV$53-1+SQRT(($CN59/CV$53-1)^2+8*($CN59/CV$53)/(Peak_Time_Mor*$O45*CV$53))),"-") -> 0.026597617 | ... DI59: =IF(DI$53<Total_Lanes,900*Peak_Time_Mor*($CN59/DI$53-1+SQRT(($CN59/DI$53-1)^2+8*($CN59/DI$53)/(Peak_Time_Mor*$O45*DI$53))),"-") -> - | DJ59: =3600/$O45 -> 2.4
H60: 20 | I60: ='Input-Detail'!BH33 -> 0.83 | J60: =1-I60 -> 0.17 | K60: =3600/(Trans_Time_Cash*I60+Trans_Time_Ticket*J60) -> 547.52852 | L60: ='Input-Detail'!BJ33 -> 1 | M60: =1-L60 -> 0 | N60: =3600/(Trans_Time_Cash*L60+Trans_Time_Ticket*M60) -> 514.28571 | O60: =3600/Headway_ETC -> 1500 | V60: 6 | W60: =W13 -> 22311321 | X60: =X13 -> 0.39898451 | Y60: =Y13 -> 9620.9071 | Z60: =W60/Y60 -> 2319.0455 | AA60: =AA13 -> 2 | AB60: =1-AB13 -> 0.3 | AC60: =Y60*AB60 -> 2886.2721 | AD60: =Peak_Time_Mor*$BH60*(CH60+BK60)/3600 -> 11.062503 | AE60: =IF(AE$53<Total_Lanes,($BI60*($CH60+BM60)+$CM60*CO60)*Peak_Time_Mor/3600,"-") -> 11.730932 | AF60: =IF(AF$53<Total_Lanes,($BI60*($CH60+BN60)+$CM60*CP60)*Peak_Time_Mor/3600,"-") -> 7.2455486 | AG60: =IF(AG$53<Total_Lanes,($BI60*($CH60+BO60)+$CM60*CQ60)*Peak_Time_Mor/3600,"-") -> 7.036956 | AH60: =IF(AH$53<Total_Lanes,($BI60*($CH60+BP60)+$CM60*CR60)*Peak_Time_Mor/3600,"-") -> 7.0969958 | AI60: =IF(AI$53<Total_Lanes,($BI60*($CH60+BQ60)+$CM60*CS60)*Peak_Time_Mor/3600,"-") -> 7.3051308 | AJ60: =IF(AJ$53<Total_Lanes,($BI60*($CH60+BR60)+$CM60*CT60)*Peak_Time_Mor/3600,"-") -> 7.7509418 | AK60: =IF(AK$53<Total_Lanes,($BI60*($CH60+BS60)+$CM60*CU60)*Peak_Time_Mor/3600,"-") -> 8.8386201 | AL60: =IF(AL$53<Total_Lanes,($BI60*($CH60+BT60)+$CM60*CV60)*Peak_Time_Mor/3600,"-") -> 13.182693 | ... AY60: =IF(AY$53<Total_Lanes,($BI60*($CH60+CG60)+$CM60*DI60)*Peak_Time_Mor/3600,"-") -> - | AZ60: =SUMIF(AE60:AY60,BA60,$AE$53:$AY$53) -> 3 | BA60: =MIN(AE60:AY60) -> 7.036956 | BB60: =IF((SUMIF($BM58:$CG58,$AZ60,$BM60:$CG60)+$CH60)<(SUMIF($CO58:$DI58,$AZ60,$CO60:$DI60)+$DJ60),AZ60+1,AZ60) -> 3 | BC60: =SUMIF($AE$53:$AY$53,$BB60,$AE60:$AY60) -> 7.036956 | BF60: 6 | BG60: =$X60 -> 0.39898451 | BH60: =$AC60 -> 2886.2721 | BI60: =BH60*(1-BG60) -> 1734.6942 | BJ60: =Peak_Arrival_Manual_Mor/K46 -> 3.1682263 | BK60: =900*Peak_Time_Mor*($BJ60/Total_Lanes-1+SQRT(($BJ60/Total_Lanes-1)^2+8*($BJ60/Total_Lanes)/(Peak_Time_Mor*$K46*Total_Lanes))) -> 0.19653982 | BL60: =Peak_Arrival_Manual_Mor/N46 -> 3.2296634 | BM60: =IF(BM$6<Total_Lanes,900*Peak_Time_Mor*($BL60/(Total_Lanes-BM$6)-1+SQRT(($BL60/(Total_Lanes-BM$6)-1)^2+8*($BL60/(Total_Lanes-BM$6))/(Peak_Time_Mor*$N46*(Total_Lanes-BM$6)))),"-") -> 0.25323184 | BN60: =IF(BN$6<Total_Lanes,900*Peak_Time_Mor*($BL60/(Total_Lanes-BN$6)-1+SQRT(($BL60/(Total_Lanes-BN$6)-1)^2+8*($BL60/(Total_Lanes-BN$6))/(Peak_Time_Mor*$N46*(Total_Lanes-BN$6)))),"-") -> 0.31968839 | BO60: =IF(BO$6<Total_Lanes,900*Peak_Time_Mor*($BL60/(Total_Lanes-BO$6)-1+SQRT(($BL60/(Total_Lanes-BO$6)-1)^2+8*($BL60/(Total_Lanes-BO$6))/(Peak_Time_Mor*$N46*(Total_Lanes-BO$6)))),"-") -> 0.41674655 | BP60: =IF(BP$6<Total_Lanes,900*Peak_Time_Mor*($BL60/(Total_Lanes-BP$6)-1+SQRT(($BL60/(Total_Lanes-BP$6)-1)^2+8*($BL60/(Total_Lanes-BP$6))/(Peak_Time_Mor*$N46*(Total_Lanes-BP$6)))),"-") -> 0.56707481 | BQ60: =IF(BQ$6<Total_Lanes,900*Peak_Time_Mor*($BL60/(Total_Lanes-BQ$6)-1+SQRT(($BL60/(Total_Lanes-BQ$6)-1)^2+8*($BL60/(Total_Lanes-BQ$6))/(Peak_Time_Mor*$N46*(Total_Lanes-BQ$6)))),"-") -> 0.81984608 | BR60: =IF(BR$6<Total_Lanes,900*Peak_Time_Mor*($BL60/(Total_Lanes-BR$6)-1+SQRT(($BL60/(Total_Lanes-BR$6)-1)^2+8*($BL60/(Total_Lanes-BR$6))/(Peak_Time_Mor*$N46*(Total_Lanes-BR$6)))),"-") -> 1.301279 | BS60: =IF(BS$6<Total_Lanes,900*Peak_Time_Mor*($BL60/(Total_Lanes-BS$6)-1+SQRT(($BL60/(Total_Lanes-BS$6)-1)^2+8*($BL60/(Total_Lanes-BS$6))/(Peak_Time_Mor*$N46*(Total_Lanes-BS$6)))),"-") -> 2.4408291 | BT60: =IF(BT$6<Total_Lanes,900*Peak_Time_Mor*($BL60/(Total_Lanes-BT$6)-1+SQRT(($BL60/(Total_Lanes-BT$6)-1)^2+8*($BL60/(Total_Lanes-BT$6))/(Peak_Time_Mor*$N46*(Total_Lanes-BT$6)))),"-") -> 6.9553394 | ... CG60: =IF(CG$6<Total_Lanes,900*Peak_Time_Mor*($BL60/(Total_Lanes-CG$6)-1+SQRT(($BL60/(Total_Lanes-CG$6)-1)^2+8*($BL60/(Total_Lanes-CG$6))/(Peak_Time_Mor*$N46*(Total_Lanes-CG$6)))),"-") -> - | CH60: =3600/N46 -> 6.7025 | CJ60: 6 | CK60: =$X60 -> 0.39898451 | CL60: =$AC60 -> 2886.2721 | CM60: =CL60*CK60 -> 1151.5779 | CN60: =CM60/O46 -> 0.76771859 | CO60: =IF(CO$53<Total_Lanes,900*Peak_Time_Mor*($CN60/CO$53-1+SQRT(($CN60/CO$53-1)^2+8*($CN60/CO$53)/(Peak_Time_Mor*$O46*CO$53))),"-") -> 7.8584436 | CP60: =IF(CP$53<Total_Lanes,900*Peak_Time_Mor*($CN60/CP$53-1+SQRT(($CN60/CP$53-1)^2+8*($CN60/CP$53)/(Peak_Time_Mor*$O46*CP$53))),"-") -> 0.74735527 | CQ60: =IF(CQ$53<Total_Lanes,900*Peak_Time_Mor*($CN60/CQ$53-1+SQRT(($CN60/CQ$53-1)^2+8*($CN60/CQ$53)/(Peak_Time_Mor*$O46*CQ$53))),"-") -> 0.27510501 | CR60: =IF(CR$53<Total_Lanes,900*Peak_Time_Mor*($CN60/CR$53-1+SQRT(($CN60/CR$53-1)^2+8*($CN60/CR$53)/(Peak_Time_Mor*$O46*CR$53))),"-") -> 0.14250263 | CS60: =IF(CS$53<Total_Lanes,900*Peak_Time_Mor*($CN60/CS$53-1+SQRT(($CN60/CS$53-1)^2+8*($CN60/CS$53)/(Peak_Time_Mor*$O46*CS$53))),"-") -> 0.087067554 | CT60: =IF(CT$53<Total_Lanes,900*Peak_Time_Mor*($CN60/CT$53-1+SQRT(($CN60/CT$53-1)^2+8*($CN60/CT$53)/(Peak_Time_Mor*$O46*CT$53))),"-") -> 0.058689827 | CU60: =IF(CU$53<Total_Lanes,900*Peak_Time_Mor*($CN60/CU$53-1+SQRT(($CN60/CU$53-1)^2+8*($CN60/CU$53)/(Peak_Time_Mor*$O46*CU$53))),"-") -> 0.042234026 | CV60: =IF(CV$53<Total_Lanes,900*Peak_Time_Mor*($CN60/CV$53-1+SQRT(($CN60/CV$53-1)^2+8*($CN60/CV$53)/(Peak_Time_Mor*$O46*CV$53))),"-") -> 0.031845183 | ... DI60: =IF(DI$53<Total_Lanes,900*Peak_Time_Mor*($CN60/DI$53-1+SQRT(($CN60/DI$53-1)^2+8*($CN60/DI$53)/(Peak_Time_Mor*$O46*DI$53))),"-") -> - | DJ60: =3600/$O46 -> 2.4
V61: 7 | W61: =W14 -> 22860512 | X61: =X14 -> 0.44881248 | Y61: =Y14 -> 9857.7249 | Z61: =W61/Y61 -> 2319.0455 | AA61: =AA14 -> 2 | AB61: =1-AB14 -> 0.3 | AC61: =Y61*AB61 -> 2957.3175 | AD61: =Peak_Time_Mor*$BH61*(CH61+BK61)/3600 -> 11.343812 | AE61: =IF(AE$53<Total_Lanes,($BI61*($CH61+BM61)+$CM61*CO61)*Peak_Time_Mor/3600,"-") -> 19.343657 | AF61: =IF(AF$53<Total_Lanes,($BI61*($CH61+BN61)+$CM61*CP61)*Peak_Time_Mor/3600,"-") -> 7.0571296 | AG61: =IF(AG$53<Total_Lanes,($BI61*($CH61+BO61)+$CM61*CQ61)*Peak_Time_Mor/3600,"-") -> 6.6813999 | AH61: =IF(AH$53<Total_Lanes,($BI61*($CH61+BP61)+$CM61*CR61)*Peak_Time_Mor/3600,"-") -> 6.6820042 | AI61: =IF(AI$53<Total_Lanes,($BI61*($CH61+BQ61)+$CM61*CS61)*Peak_Time_Mor/3600,"-") -> 6.8342029 | AJ61: =IF(AJ$53<Total_Lanes,($BI61*($CH61+BR61)+$CM61*CT61)*Peak_Time_Mor/3600,"-") -> 7.1845308 | AK61: =IF(AK$53<Total_Lanes,($BI61*($CH61+BS61)+$CM61*CU61)*Peak_Time_Mor/3600,"-") -> 8.018469 | AL61: =IF(AL$53<Total_Lanes,($BI61*($CH61+BT61)+$CM61*CV61)*Peak_Time_Mor/3600,"-") -> 10.936319 | ... AY61: =IF(AY$53<Total_Lanes,($BI61*($CH61+CG61)+$CM61*DI61)*Peak_Time_Mor/3600,"-") -> - | AZ61: =SUMIF(AE61:AY61,BA61,$AE$53:$AY$53) -> 3 | BA61: =MIN(AE61:AY61) -> 6.6813999 | BB61: =IF((SUMIF($BM59:$CG59,$AZ61,$BM61:$CG61)+$CH61)<(SUMIF($CO59:$DI59,$AZ61,$CO61:$DI61)+$DJ61),AZ61+1,AZ61) -> 3 | BC61: =SUMIF($AE$53:$AY$53,$BB61,$AE61:$AY61) -> 6.6813999 | BF61: 7 | BG61: =$X61 -> 0.44881248 | BH61: =$AC61 -> 2957.3175 | BI61: =BH61*(1-BG61) -> 1630.0365 | BJ61: =Peak_Arrival_Manual_Mor/K47 -> 2.9770805 | BK61: =900*Peak_Time_Mor*($BJ61/Total_Lanes-1+SQRT(($BJ61/Total_Lanes-1)^2+8*($BJ61/Total_Lanes)/(Peak_Time_Mor*$K47*Total_Lanes))) -> 0.1807711 | BL61: =Peak_Arrival_Manual_Mor/N47 -> 3.0444327 | BM61: =IF(BM$6<Total_Lanes,900*Peak_Time_Mor*($BL61/(Total_Lanes-BM$6)-1+SQRT(($BL61/(Total_Lanes-BM$6)-1)^2+8*($BL61/(Total_Lanes-BM$6))/(Peak_Time_Mor*$N47*(Total_Lanes-BM$6)))),"-") -> 0.23389185 | BN61: =IF(BN$6<Total_Lanes,900*Peak_Time_Mor*($BL61/(Total_Lanes-BN$6)-1+SQRT(($BL61/(Total_Lanes-BN$6)-1)^2+8*($BL61/(Total_Lanes-BN$6))/(Peak_Time_Mor*$N47*(Total_Lanes-BN$6)))),"-") -> 0.29426211 | BO61: =IF(BO$6<Total_Lanes,900*Peak_Time_Mor*($BL61/(Total_Lanes-BO$6)-1+SQRT(($BL61/(Total_Lanes-BO$6)-1)^2+8*($BL61/(Total_Lanes-BO$6))/(Peak_Time_Mor*$N47*(Total_Lanes-BO$6)))),"-") -> 0.38184111 | BP61: =IF(BP$6<Total_Lanes,900*Peak_Time_Mor*($BL61/(Total_Lanes-BP$6)-1+SQRT(($BL61/(Total_Lanes-BP$6)-1)^2+8*($BL61/(Total_Lanes-BP$6))/(Peak_Time_Mor*$N47*(Total_Lanes-BP$6)))),"-") -> 0.51621907 | BQ61: =IF(BQ$6<Total_Lanes,900*Peak_Time_Mor*($BL61/(Total_Lanes-BQ$6)-1+SQRT(($BL61/(Total_Lanes-BQ$6)-1)^2+8*($BL61/(Total_Lanes-BQ$6))/(Peak_Time_Mor*$N47*(Total_Lanes-BQ$6)))),"-") -> 0.73901521 | BR61: =IF(BR$6<Total_Lanes,900*Peak_Time_Mor*($BL61/(Total_Lanes-BR$6)-1+SQRT(($BL61/(Total_Lanes-BR$6)-1)^2+8*($BL61/(Total_Lanes-BR$6))/(Peak_Time_Mor*$N47*(Total_Lanes-BR$6)))),"-") -> 1.1535686 | BS61: =IF(BS$6<Total_Lanes,900*Peak_Time_Mor*($BL61/(Total_Lanes-BS$6)-1+SQRT(($BL61/(Total_Lanes-BS$6)-1)^2+8*($BL61/(Total_Lanes-BS$6))/(Peak_Time_Mor*$N47*(Total_Lanes-BS$6)))),"-") -> 2.0904071 | BT61: =IF(BT$6<Total_Lanes,900*Peak_Time_Mor*($BL61/(Total_Lanes-BT$6)-1+SQRT(($BL61/(Total_Lanes-BT$6)-1)^2+8*($BL61/(Total_Lanes-BT$6))/(Peak_Time_Mor*$N47*(Total_Lanes-BT$6)))),"-") -> 5.3225181 | ... CG61: =IF(CG$6<Total_Lanes,900*Peak_Time_Mor*($BL61/(Total_Lanes-CG$6)-1+SQRT(($BL61/(Total_Lanes-CG$6)-1)^2+8*($BL61/(Total_Lanes-CG$6))/(Peak_Time_Mor*$N47*(Total_Lanes-CG$6)))),"-") -> - | CH61: =3600/N47 -> 6.72375 | CJ61: 7 | CK61: =$X61 -> 0.44881248 | CL61: =$AC61 -> 2957.3175 | CM61: =CL61*CK61 -> 1327.281 | CN61: =CM61/O47 -> 0.884854 | CO61: =IF(CO$53<Total_Lanes,900*Peak_Time_Mor*($CN61/CO$53-1+SQRT(($CN61/CO$53-1)^2+8*($CN61/CO$53)/(Peak_Time_Mor*$O47*CO$53))),"-") -> 17.688321 | CP61: =IF(CP$53<Total_Lanes,900*Peak_Time_Mor*($CN61/CP$53-1+SQRT(($CN61/CP$53-1)^2+8*($CN61/CP$53)/(Peak_Time_Mor*$O47*CP$53))),"-") -> 0.9517333 | CQ61: =IF(CQ$53<Total_Lanes,900*Peak_Time_Mor*($CN61/CQ$53-1+SQRT(($CN61/CQ$53-1)^2+8*($CN61/CQ$53)/(Peak_Time_Mor*$O47*CQ$53))),"-") -> 0.33462933 | CR61: =IF(CR$53<Total_Lanes,900*Peak_Time_Mor*($CN61/CR$53-1+SQRT(($CN61/CR$53-1)^2+8*($CN61/CR$53)/(Peak_Time_Mor*$O47*CR$53))),"-") -> 0.17041902 | CS61: =IF(CS$53<Total_Lanes,900*Peak_Time_Mor*($CN61/CS$53-1+SQRT(($CN61/CS$53-1)^2+8*($CN61/CS$53)/(Peak_Time_Mor*$O47*CS$53))),"-") -> 0.10320779 | CT61: =IF(CT$53<Total_Lanes,900*Peak_Time_Mor*($CN61/CT$53-1+SQRT(($CN61/CT$53-1)^2+8*($CN61/CT$53)/(Peak_Time_Mor*$O47*CT$53))),"-") -> 0.069193259 | CU61: =IF(CU$53<Total_Lanes,900*Peak_Time_Mor*($CN61/CU$53-1+SQRT(($CN61/CU$53-1)^2+8*($CN61/CU$53)/(Peak_Time_Mor*$O47*CU$53))),"-") -> 0.049610218 | CV61: =IF(CV$53<Total_Lanes,900*Peak_Time_Mor*($CN61/CV$53-1+SQRT(($CN61/CV$53-1)^2+8*($CN61/CV$53)/(Peak_Time_Mor*$O47*CV$53))),"-") -> 0.037308174 | ... DI61: =IF(DI$53<Total_Lanes,900*Peak_Time_Mor*($CN61/DI$53-1+SQRT(($CN61/DI$53-1)^2+8*($CN61/DI$53)/(Peak_Time_Mor*$O47*DI$53))),"-") -> - | DJ61: =3600/$O47 -> 2.4
V62: 8 | W62: =W15 -> 23409704 | X62: =X15 -> 0.49671513 | Y62: =Y15 -> 10094.543 | Z62: =W62/Y62 -> 2319.0455 | AA62: =AA15 -> 2 | AB62: =1-AB15 -> 0.3 | AC62: =Y62*AB62 -> 3028.3628 | AD62: =Peak_Time_Mor*$BH62*(CH62+BK62)/3600 -> 11.626355 | AE62: =IF(AE$53<Total_Lanes,($BI62*($CH62+BM62)+$CM62*CO62)*Peak_Time_Mor/3600,"-") -> 88.042476 | AF62: =IF(AF$53<Total_Lanes,($BI62*($CH62+BN62)+$CM62*CP62)*Peak_Time_Mor/3600,"-") -> 6.9473291 | AG62: =IF(AG$53<Total_Lanes,($BI62*($CH62+BO62)+$CM62*CQ62)*Peak_Time_Mor/3600,"-") -> 6.3417695 | AH62: =IF(AH$53<Total_Lanes,($BI62*($CH62+BP62)+$CM62*CR62)*Peak_Time_Mor/3600,"-") -> 6.2752119 | AI62: =IF(AI$53<Total_Lanes,($BI62*($CH62+BQ62)+$CM62*CS62)*Peak_Time_Mor/3600,"-") -> 6.3738879 | AJ62: =IF(AJ$53<Total_Lanes,($BI62*($CH62+BR62)+$CM62*CT62)*Peak_Time_Mor/3600,"-") -> 6.6423271 | AK62: =IF(AK$53<Total_Lanes,($BI62*($CH62+BS62)+$CM62*CU62)*Peak_Time_Mor/3600,"-") -> 7.278509 | AL62: =IF(AL$53<Total_Lanes,($BI62*($CH62+BT62)+$CM62*CV62)*Peak_Time_Mor/3600,"-") -> 9.2956475 | ... AY62: =IF(AY$53<Total_Lanes,($BI62*($CH62+CG62)+$CM62*DI62)*Peak_Time_Mor/3600,"-") -> - | AZ62: =SUMIF(AE62:AY62,BA62,$AE$53:$AY$53) -> 4 | BA62: =MIN(AE62:AY62) -> 6.2752119 | BB62: =IF((SUMIF($BM60:$CG60,$AZ62,$BM62:$CG62)+$CH62)<(SUMIF($CO60:$DI60,$AZ62,$CO62:$DI62)+$DJ62),AZ62+1,AZ62) -> 4 | BC62: =SUMIF($AE$53:$AY$53,$BB62,$AE62:$AY62) -> 6.2752119 | BF62: 8 | BG62: =$X62 -> 0.49671513 | BH62: =$AC62 -> 3028.3628 | BI62: =BH62*(1-BG62) -> 1524.1292 | BJ62: =Peak_Arrival_Manual_Mor/K48 -> 2.7836526 | BK62: =900*Peak_Time_Mor*($BJ62/Total_Lanes-1+SQRT(($BJ62/Total_Lanes-1)^2+8*($BJ62/Total_Lanes)/(Peak_Time_Mor*$K48*Total_Lanes))) -> 0.1654797 | BL62: =Peak_Arrival_Manual_Mor/N48 -> 2.8556254 | BM62: =IF(BM$6<Total_Lanes,900*Peak_Time_Mor*($BL62/(Total_Lanes-BM$6)-1+SQRT(($BL62/(Total_Lanes-BM$6)-1)^2+8*($BL62/(Total_Lanes-BM$6))/(Peak_Time_Mor*$N48*(Total_Lanes-BM$6)))),"-") -> 0.21497984 | BN62: =IF(BN$6<Total_Lanes,900*Peak_Time_Mor*($BL62/(Total_Lanes-BN$6)-1+SQRT(($BL62/(Total_Lanes-BN$6)-1)^2+8*($BL62/(Total_Lanes-BN$6))/(Peak_Time_Mor*$N48*(Total_Lanes-BN$6)))),"-") -> 0.26957117 | BO62: =IF(BO$6<Total_Lanes,900*Peak_Time_Mor*($BL62/(Total_Lanes-BO$6)-1+SQRT(($BL62/(Total_Lanes-BO$6)-1)^2+8*($BL62/(Total_Lanes-BO$6))/(Peak_Time_Mor*$N48*(Total_Lanes-BO$6)))),"-") -> 0.34825828 | BP62: =IF(BP$6<Total_Lanes,900*Peak_Time_Mor*($BL62/(Total_Lanes-BP$6)-1+SQRT(($BL62/(Total_Lanes-BP$6)-1)^2+8*($BL62/(Total_Lanes-BP$6))/(Peak_Time_Mor*$N48*(Total_Lanes-BP$6)))),"-") -> 0.46792133 | BQ62: =IF(BQ$6<Total_Lanes,900*Peak_Time_Mor*($BL62/(Total_Lanes-BQ$6)-1+SQRT(($BL62/(Total_Lanes-BQ$6)-1)^2+8*($BL62/(Total_Lanes-BQ$6))/(Peak_Time_Mor*$N48*(Total_Lanes-BQ$6)))),"-") -> 0.66372919 | BR62: =IF(BR$6<Total_Lanes,900*Peak_Time_Mor*($BL62/(Total_Lanes-BR$6)-1+SQRT(($BL62/(Total_Lanes-BR$6)-1)^2+8*($BL62/(Total_Lanes-BR$6))/(Peak_Time_Mor*$N48*(Total_Lanes-BR$6)))),"-") -> 1.0203821 | BS62: =IF(BS$6<Total_Lanes,900*Peak_Time_Mor*($BL62/(Total_Lanes-BS$6)-1+SQRT(($BL62/(Total_Lanes-BS$6)-1)^2+8*($BL62/(Total_Lanes-BS$6))/(Peak_Time_Mor*$N48*(Total_Lanes-BS$6)))),"-") -> 1.7943538 | BT62: =IF(BT$6<Total_Lanes,900*Peak_Time_Mor*($BL62/(Total_Lanes-BT$6)-1+SQRT(($BL62/(Total_Lanes-BT$6)-1)^2+8*($BL62/(Total_Lanes-BT$6))/(Peak_Time_Mor*$N48*(Total_Lanes-BT$6)))),"-") -> 4.190747 | ... CG62: =IF(CG$6<Total_Lanes,900*Peak_Time_Mor*($BL62/(Total_Lanes-CG$6)-1+SQRT(($BL62/(Total_Lanes-CG$6)-1)^2+8*($BL62/(Total_Lanes-CG$6))/(Peak_Time_Mor*$N48*(Total_Lanes-CG$6)))),"-") -> - | CH62: =3600/N48 -> 6.745 | CJ62: 8 | CK62: =$X62 -> 0.49671513 | CL62: =$AC62 -> 3028.3628 | CM62: =CL62*CK62 -> 1504.2336 | CN62: =CM62/O48 -> 1.0028224 | CO62: =IF(CO$53<Total_Lanes,900*Peak_Time_Mor*($CN62/CO$53-1+SQRT(($CN62/CO$53-1)^2+8*($CN62/CO$53)/(Peak_Time_Mor*$O48*CO$53))),"-") -> 98.301584 | CP62: =IF(CP$53<Total_Lanes,900*Peak_Time_Mor*($CN62/CP$53-1+SQRT(($CN62/CP$53-1)^2+8*($CN62/CP$53)/(Peak_Time_Mor*$O48*CP$53))),"-") -> 1.2059827 | CQ62: =IF(CQ$53<Total_Lanes,900*Peak_Time_Mor*($CN62/CQ$53-1+SQRT(($CN62/CQ$53-1)^2+8*($CN62/CQ$53)/(Peak_Time_Mor*$O48*CQ$53))),"-") -> 0.40162854 | CR62: =IF(CR$53<Total_Lanes,900*Peak_Time_Mor*($CN62/CR$53-1+SQRT(($CN62/CR$53-1)^2+8*($CN62/CR$53)/(Peak_Time_Mor*$O48*CR$53))),"-") -> 0.20073842 | CS62: =IF(CS$53<Total_Lanes,900*Peak_Time_Mor*($CN62/CS$53-1+SQRT(($CN62/CS$53-1)^2+8*($CN62/CS$53)/(Peak_Time_Mor*$O48*CS$53))),"-") -> 0.12041862 | CT62: =IF(CT$53<Total_Lanes,900*Peak_Time_Mor*($CN62/CT$53-1+SQRT(($CN62/CT$53-1)^2+8*($CN62/CT$53)/(Peak_Time_Mor*$O48*CT$53))),"-") -> 0.080268957 | CU62: =IF(CU$53<Total_Lanes,900*Peak_Time_Mor*($CN62/CU$53-1+SQRT(($CN62/CU$53-1)^2+8*($CN62/CU$53)/(Peak_Time_Mor*$O48*CU$53))),"-") -> 0.057330042 | CV62: =IF(CV$53<Total_Lanes,900*Peak_Time_Mor*($CN62/CV$53-1+SQRT(($CN62/CV$53-1)^2+8*($CN62/CV$53)/(Peak_Time_Mor*$O48*CV$53))),"-") -> 0.042994853 | ... DI62: =IF(DI$53<Total_Lanes,900*Peak_Time_Mor*($CN62/DI$53-1+SQRT(($CN62/DI$53-1)^2+8*($CN62/DI$53)/(Peak_Time_Mor*$O48*DI$53))),"-") -> - | DJ62: =3600/$O48 -> 2.4
V63: 9 | W63: =W16 -> 23958895 | X63: =X16 -> 0.54303751 | Y63: =Y16 -> 10331.361 | Z63: =W63/Y63 -> 2319.0455 | AA63: =AA16 -> 2 | AB63: =1-AB16 -> 0.3 | AC63: =Y63*AB63 -> 3099.4082 | AD63: =Peak_Time_Mor*$BH63*(CH63+BK63)/3600 -> 11.910006 | AE63: =IF(AE$53<Total_Lanes,($BI63*($CH63+BM63)+$CM63*CO63)*Peak_Time_Mor/3600,"-") -> 436.05253 | AF63: =IF(AF$53<Total_Lanes,($BI63*($CH63+BN63)+$CM63*CP63)*Peak_Time_Mor/3600,"-") -> 6.9497625 | AG63: =IF(AG$53<Total_Lanes,($BI63*($CH63+BO63)+$CM63*CQ63)*Peak_Time_Mor/3600,"-") -> 6.0192415 | AH63: =IF(AH$53<Total_Lanes,($BI63*($CH63+BP63)+$CM63*CR63)*Peak_Time_Mor/3600,"-") -> 5.8744917 | AI63: =IF(AI$53<Total_Lanes,($BI63*($CH63+BQ63)+$CM63*CS63)*Peak_Time_Mor/3600,"-") -> 5.9204093 | AJ63: =IF(AJ$53<Total_Lanes,($BI63*($CH63+BR63)+$CM63*CT63)*Peak_Time_Mor/3600,"-") -> 6.1172953 | AK63: =IF(AK$53<Total_Lanes,($BI63*($CH63+BS63)+$CM63*CU63)*Peak_Time_Mor/3600,"-") -> 6.5963826 | AL63: =IF(AL$53<Total_Lanes,($BI63*($CH63+BT63)+$CM63*CV63)*Peak_Time_Mor/3600,"-") -> 8.01036 | ... AY63: =IF(AY$53<Total_Lanes,($BI63*($CH63+CG63)+$CM63*DI63)*Peak_Time_Mor/3600,"-") -> - | AZ63: =SUMIF(AE63:AY63,BA63,$AE$53:$AY$53) -> 4 | BA63: =MIN(AE63:AY63) -> 5.8744917 | BB63: =IF((SUMIF($BM61:$CG61,$AZ63,$BM63:$CG63)+$CH63)<(SUMIF($CO61:$DI61,$AZ63,$CO63:$DI63)+$DJ63),AZ63+1,AZ63) -> 4 | BC63: =SUMIF($AE$53:$AY$53,$BB63,$AE63:$AY63) -> 5.8744917 | BF63: 9 | BG63: =$X63 -> 0.54303751 | BH63: =$AC63 -> 3099.4082 | BI63: =BH63*(1-BG63) -> 1416.3133 | BJ63: =Peak_Arrival_Manual_Mor/K49 -> 2.5867388 | BK63: =900*Peak_Time_Mor*($BJ63/Total_Lanes-1+SQRT(($BJ63/Total_Lanes-1)^2+8*($BJ63/Total_Lanes)/(Peak_Time_Mor*$K49*Total_Lanes))) -> 0.150558 | BL63: =Peak_Arrival_Manual_Mor/N49 -> 2.6619805 | BM63: =IF(BM$6<Total_Lanes,900*Peak_Time_Mor*($BL63/(Total_Lanes-BM$6)-1+SQRT(($BL63/(Total_Lanes-BM$6)-1)^2+8*($BL63/(Total_Lanes-BM$6))/(Peak_Time_Mor*$N49*(Total_Lanes-BM$6)))),"-") -> 0.19636589 | BN63: =IF(BN$6<Total_Lanes,900*Peak_Time_Mor*($BL63/(Total_Lanes-BN$6)-1+SQRT(($BL63/(Total_Lanes-BN$6)-1)^2+8*($BL63/(Total_Lanes-BN$6))/(Peak_Time_Mor*$N49*(Total_Lanes-BN$6)))),"-") -> 0.24543342 | BO63: =IF(BO$6<Total_Lanes,900*Peak_Time_Mor*($BL63/(Total_Lanes-BO$6)-1+SQRT(($BL63/(Total_Lanes-BO$6)-1)^2+8*($BL63/(Total_Lanes-BO$6))/(Peak_Time_Mor*$N49*(Total_Lanes-BO$6)))),"-") -> 0.31572047 | BP63: =IF(BP$6<Total_Lanes,900*Peak_Time_Mor*($BL63/(Total_Lanes-BP$6)-1+SQRT(($BL63/(Total_Lanes-BP$6)-1)^2+8*($BL63/(Total_Lanes-BP$6))/(Peak_Time_Mor*$N49*(Total_Lanes-BP$6)))),"-") -> 0.42170283 | BQ63: =IF(BQ$6<Total_Lanes,900*Peak_Time_Mor*($BL63/(Total_Lanes-BQ$6)-1+SQRT(($BL63/(Total_Lanes-BQ$6)-1)^2+8*($BL63/(Total_Lanes-BQ$6))/(Peak_Time_Mor*$N49*(Total_Lanes-BQ$6)))),"-") -> 0.59299078 | BR63: =IF(BR$6<Total_Lanes,900*Peak_Time_Mor*($BL63/(Total_Lanes-BR$6)-1+SQRT(($BL63/(Total_Lanes-BR$6)-1)^2+8*($BL63/(Total_Lanes-BR$6))/(Peak_Time_Mor*$N49*(Total_Lanes-BR$6)))),"-") -> 0.89891349 | BS63: =IF(BS$6<Total_Lanes,900*Peak_Time_Mor*($BL63/(Total_Lanes-BS$6)-1+SQRT(($BL63/(Total_Lanes-BS$6)-1)^2+8*($BL63/(Total_Lanes-BS$6))/(Peak_Time_Mor*$N49*(Total_Lanes-BS$6)))),"-") -> 1.5393515 | BT63: =IF(BT$6<Total_Lanes,900*Peak_Time_Mor*($BL63/(Total_Lanes-BT$6)-1+SQRT(($BL63/(Total_Lanes-BT$6)-1)^2+8*($BL63/(Total_Lanes-BT$6))/(Peak_Time_Mor*$N49*(Total_Lanes-BT$6)))),"-") -> 3.3559989 | ... CG63: =IF(CG$6<Total_Lanes,900*Peak_Time_Mor*($BL63/(Total_Lanes-CG$6)-1+SQRT(($BL63/(Total_Lanes-CG$6)-1)^2+8*($BL63/(Total_Lanes-CG$6))/(Peak_Time_Mor*$N49*(Total_Lanes-CG$6)))),"-") -> - | CH63: =3600/N49 -> 6.76625 | CJ63: 9 | CK63: =$X63 -> 0.54303751 | CL63: =$AC63 -> 3099.4082 | CM63: =CL63*CK63 -> 1683.0949 | CN63: =CM63/O49 -> 1.1220633 | CO63: =IF(CO$53<Total_Lanes,900*Peak_Time_Mor*($CN63/CO$53-1+SQRT(($CN63/CO$53-1)^2+8*($CN63/CO$53)/(Peak_Time_Mor*$O49*CO$53))),"-") -> 460.48104 | CP63: =IF(CP$53<Total_Lanes,900*Peak_Time_Mor*($CN63/CP$53-1+SQRT(($CN63/CP$53-1)^2+8*($CN63/CP$53)/(Peak_Time_Mor*$O49*CP$53))),"-") -> 1.5321966 | CQ63: =IF(CQ$53<Total_Lanes,900*Peak_Time_Mor*($CN63/CQ$53-1+SQRT(($CN63/CQ$53-1)^2+8*($CN63/CQ$53)/(Peak_Time_Mor*$O49*CQ$53))),"-") -> 0.47789698 | CR63: =IF(CR$53<Total_Lanes,900*Peak_Time_Mor*($CN63/CR$53-1+SQRT(($CN63/CR$53-1)^2+8*($CN63/CR$53)/(Peak_Time_Mor*$O49*CR$53))),"-") -> 0.23390965 | CS63: =IF(CS$53<Total_Lanes,900*Peak_Time_Mor*($CN63/CS$53-1+SQRT(($CN63/CS$53-1)^2+8*($CN63/CS$53)/(Peak_Time_Mor*$O49*CS$53))),"-") -> 0.1388789 | CT63: =IF(CT$53<Total_Lanes,900*Peak_Time_Mor*($CN63/CT$53-1+SQRT(($CN63/CT$53-1)^2+8*($CN63/CT$53)/(Peak_Time_Mor*$O49*CT$53))),"-") -> 0.09200841 | CU63: =IF(CU$53<Total_Lanes,900*Peak_Time_Mor*($CN63/CU$53-1+SQRT(($CN63/CU$53-1)^2+8*($CN63/CU$53)/(Peak_Time_Mor*$O49*CU$53))),"-") -> 0.065447979 | CV63: =IF(CV$53<Total_Lanes,900*Peak_Time_Mor*($CN63/CV$53-1+SQRT(($CN63/CV$53-1)^2+8*($CN63/CV$53)/(Peak_Time_Mor*$O49*CV$53))),"-") -> 0.048941081 | ... DI63: =IF(DI$53<Total_Lanes,900*Peak_Time_Mor*($CN63/DI$53-1+SQRT(($CN63/DI$53-1)^2+8*($CN63/DI$53)/(Peak_Time_Mor*$O49*DI$53))),"-") -> - | DJ63: =3600/$O49 -> 2.4
V64: 10 | W64: =W17 -> 24508086 | X64: =X17 -> 0.58815269 | Y64: =Y17 -> 10568.178 | Z64: =W64/Y64 -> 2319.0455 | AA64: =AA17 -> 2 | AB64: =1-AB17 -> 0.3 | AC64: =Y64*AB64 -> 3170.4535 | AD64: =Peak_Time_Mor*$BH64*(CH64+BK64)/3600 -> 12.194603 | AE64: =IF(AE$53<Total_Lanes,($BI64*($CH64+BM64)+$CM64*CO64)*Peak_Time_Mor/3600,"-") -> 924.36486 | AF64: =IF(AF$53<Total_Lanes,($BI64*($CH64+BN64)+$CM64*CP64)*Peak_Time_Mor/3600,"-") -> 7.1234397 | AG64: =IF(AG$53<Total_Lanes,($BI64*($CH64+BO64)+$CM64*CQ64)*Peak_Time_Mor/3600,"-") -> 5.7159815 | AH64: =IF(AH$53<Total_Lanes,($BI64*($CH64+BP64)+$CM64*CR64)*Peak_Time_Mor/3600,"-") -> 5.4775429 | AI64: =IF(AI$53<Total_Lanes,($BI64*($CH64+BQ64)+$CM64*CS64)*Peak_Time_Mor/3600,"-") -> 5.4697636 | AJ64: =IF(AJ$53<Total_Lanes,($BI64*($CH64+BR64)+$CM64*CT64)*Peak_Time_Mor/3600,"-") -> 5.6028137 | AK64: =IF(AK$53<Total_Lanes,($BI64*($CH64+BS64)+$CM64*CU64)*Peak_Time_Mor/3600,"-") -> 5.9549072 | AL64: =IF(AL$53<Total_Lanes,($BI64*($CH64+BT64)+$CM64*CV64)*Peak_Time_Mor/3600,"-") -> 6.9472493 | ... AY64: =IF(AY$53<Total_Lanes,($BI64*($CH64+CG64)+$CM64*DI64)*Peak_Time_Mor/3600,"-") -> - | AZ64: =SUMIF(AE64:AY64,BA64,$AE$53:$AY$53) -> 5 | BA64: =MIN(AE64:AY64) -> 5.4697636 | BB64: =IF((SUMIF($BM62:$CG62,$AZ64,$BM64:$CG64)+$CH64)<(SUMIF($CO62:$DI62,$AZ64,$CO64:$DI64)+$DJ64),AZ64+1,AZ64) -> 5 | BC64: =SUMIF($AE$53:$AY$53,$BB64,$AE64:$AY64) -> 5.4697636 | BF64: 10 | BG64: =$X64 -> 0.58815269 | BH64: =$AC64 -> 3170.4535 | BI64: =BH64*(1-BG64) -> 1305.7428 | BJ64: =Peak_Arrival_Manual_Mor/K50 -> 2.3847941 | BK64: =900*Peak_Time_Mor*($BJ64/Total_Lanes-1+SQRT(($BJ64/Total_Lanes-1)^2+8*($BJ64/Total_Lanes)/(Peak_Time_Mor*$K50*Total_Lanes))) -> 0.13588964 | BL64: =Peak_Arrival_Manual_Mor/N50 -> 2.4618692 | BM64: =IF(BM$6<Total_Lanes,900*Peak_Time_Mor*($BL64/(Total_Lanes-BM$6)-1+SQRT(($BL64/(Total_Lanes-BM$6)-1)^2+8*($BL64/(Total_Lanes-BM$6))/(Peak_Time_Mor*$N50*(Total_Lanes-BM$6)))),"-") -> 0.17790644 | BN64: =IF(BN$6<Total_Lanes,900*Peak_Time_Mor*($BL64/(Total_Lanes-BN$6)-1+SQRT(($BL64/(Total_Lanes-BN$6)-1)^2+8*($BL64/(Total_Lanes-BN$6))/(Peak_Time_Mor*$N50*(Total_Lanes-BN$6)))),"-") -> 0.22165405 | BO64: =IF(BO$6<Total_Lanes,900*Peak_Time_Mor*($BL64/(Total_Lanes-BO$6)-1+SQRT(($BL64/(Total_Lanes-BO$6)-1)^2+8*($BL64/(Total_Lanes-BO$6))/(Peak_Time_Mor*$N50*(Total_Lanes-BO$6)))),"-") -> 0.28394325 | BP64: =IF(BP$6<Total_Lanes,900*Peak_Time_Mor*($BL64/(Total_Lanes-BP$6)-1+SQRT(($BL64/(Total_Lanes-BP$6)-1)^2+8*($BL64/(Total_Lanes-BP$6))/(Peak_Time_Mor*$N50*(Total_Lanes-BP$6)))),"-") -> 0.37709945 | BQ64: =IF(BQ$6<Total_Lanes,900*Peak_Time_Mor*($BL64/(Total_Lanes-BQ$6)-1+SQRT(($BL64/(Total_Lanes-BQ$6)-1)^2+8*($BL64/(Total_Lanes-BQ$6))/(Peak_Time_Mor*$N50*(Total_Lanes-BQ$6)))),"-") -> 0.52589847 | BR64: =IF(BR$6<Total_Lanes,900*Peak_Time_Mor*($BL64/(Total_Lanes-BR$6)-1+SQRT(($BL64/(Total_Lanes-BR$6)-1)^2+8*($BL64/(Total_Lanes-BR$6))/(Peak_Time_Mor*$N50*(Total_Lanes-BR$6)))),"-") -> 0.78684417 | BS64: =IF(BS$6<Total_Lanes,900*Peak_Time_Mor*($BL64/(Total_Lanes-BS$6)-1+SQRT(($BL64/(Total_Lanes-BS$6)-1)^2+8*($BL64/(Total_Lanes-BS$6))/(Peak_Time_Mor*$N50*(Total_Lanes-BS$6)))),"-") -> 1.3157647 | BT64: =IF(BT$6<Total_Lanes,900*Peak_Time_Mor*($BL64/(Total_Lanes-BT$6)-1+SQRT(($BL64/(Total_Lanes-BT$6)-1)^2+8*($BL64/(Total_Lanes-BT$6))/(Peak_Time_Mor*$N50*(Total_Lanes-BT$6)))),"-") -> 2.7106408 | ... CG64: =IF(CG$6<Total_Lanes,900*Peak_Time_Mor*($BL64/(Total_Lanes-CG$6)-1+SQRT(($BL64/(Total_Lanes-CG$6)-1)^2+8*($BL64/(Total_Lanes-CG$6))/(Peak_Time_Mor*$N50*(Total_Lanes-CG$6)))),"-") -> - | CH64: =3600/N50 -> 6.7875 | CJ64: 10 | CK64: =$X64 -> 0.58815269 | CL64: =$AC64 -> 3170.4535 | CM64: =CL64*CK64 -> 1864.7108 | CN64: =CM64/O50 -> 1.2431405 | CO64: =IF(CO$53<Total_Lanes,900*Peak_Time_Mor*($CN64/CO$53-1+SQRT(($CN64/CO$53-1)^2+8*($CN64/CO$53)/(Peak_Time_Mor*$O50*CO$53))),"-") -> 887.40932 | CP64: =IF(CP$53<Total_Lanes,900*Peak_Time_Mor*($CN64/CP$53-1+SQRT(($CN64/CP$53-1)^2+8*($CN64/CP$53)/(Peak_Time_Mor*$O50*CP$53))),"-") -> 1.9681548 | CQ64: =IF(CQ$53<Total_Lanes,900*Peak_Time_Mor*($CN64/CQ$53-1+SQRT(($CN64/CQ$53-1)^2+8*($CN64/CQ$53)/(Peak_Time_Mor*$O50*CQ$53))),"-") -> 0.56592205 | CR64: =IF(CR$53<Total_Lanes,900*Peak_Time_Mor*($CN64/CR$53-1+SQRT(($CN64/CR$53-1)^2+8*($CN64/CR$53)/(Peak_Time_Mor*$O50*CR$53))),"-") -> 0.2705263 | CS64: =IF(CS$53<Total_Lanes,900*Peak_Time_Mor*($CN64/CS$53-1+SQRT(($CN64/CS$53-1)^2+8*($CN64/CS$53)/(Peak_Time_Mor*$O50*CS$53))),"-") -> 0.15882213 | CT64: =IF(CT$53<Total_Lanes,900*Peak_Time_Mor*($CN64/CT$53-1+SQRT(($CN64/CT$53-1)^2+8*($CN64/CT$53)/(Peak_Time_Mor*$O50*CT$53))),"-") -> 0.10453073 | CU64: =IF(CU$53<Total_Lanes,900*Peak_Time_Mor*($CN64/CU$53-1+SQRT(($CN64/CU$53-1)^2+8*($CN64/CU$53)/(Peak_Time_Mor*$O50*CU$53))),"-") -> 0.074034975 | CV64: =IF(CV$53<Total_Lanes,900*Peak_Time_Mor*($CN64/CV$53-1+SQRT(($CN64/CV$53-1)^2+8*($CN64/CV$53)/(Peak_Time_Mor*$O50*CV$53))),"-") -> 0.055193598 | ... DI64: =IF(DI$53<Total_Lanes,900*Peak_Time_Mor*($CN64/DI$53-1+SQRT(($CN64/DI$53-1)^2+8*($CN64/DI$53)/(Peak_Time_Mor*$O50*DI$53))),"-") -> - | DJ64: =3600/$O50 -> 2.4
V65: 11 | W65: =W18 -> 25057278 | X65: =X18 -> 0.58173113 | Y65: =Y18 -> 10804.996 | Z65: =W65/Y65 -> 2319.0455 | AA65: =AA18 -> 2 | AB65: =1-AB18 -> 0.3 | AC65: =Y65*AB65 -> 3241.4989 | AD65: =Peak_Time_Mor*$BH65*(CH65+BK65)/3600 -> 12.517958 | AE65: =IF(AE$53<Total_Lanes,($BI65*($CH65+BM65)+$CM65*CO65)*Peak_Time_Mor/3600,"-") -> 987.10549 | AF65: =IF(AF$53<Total_Lanes,($BI65*($CH65+BN65)+$CM65*CP65)*Peak_Time_Mor/3600,"-") -> 7.4295311 | AG65: =IF(AG$53<Total_Lanes,($BI65*($CH65+BO65)+$CM65*CQ65)*Peak_Time_Mor/3600,"-") -> 5.9599264 | AH65: =IF(AH$53<Total_Lanes,($BI65*($CH65+BP65)+$CM65*CR65)*Peak_Time_Mor/3600,"-") -> 5.7189949 | AI65: =IF(AI$53<Total_Lanes,($BI65*($CH65+BQ65)+$CM65*CS65)*Peak_Time_Mor/3600,"-") -> 5.7208937 | AJ65: =IF(AJ$53<Total_Lanes,($BI65*($CH65+BR65)+$CM65*CT65)*Peak_Time_Mor/3600,"-") -> 5.8773337 | AK65: =IF(AK$53<Total_Lanes,($BI65*($CH65+BS65)+$CM65*CU65)*Peak_Time_Mor/3600,"-") -> 6.2861678 | AL65: =IF(AL$53<Total_Lanes,($BI65*($CH65+BT65)+$CM65*CV65)*Peak_Time_Mor/3600,"-") -> 7.471794 | ... AY65: =IF(AY$53<Total_Lanes,($BI65*($CH65+CG65)+$CM65*DI65)*Peak_Time_Mor/3600,"-") -> - | AZ65: =SUMIF(AE65:AY65,BA65,$AE$53:$AY$53) -> 4 | BA65: =MIN(AE65:AY65) -> 5.7189949 | BB65: =IF((SUMIF($BM63:$CG63,$AZ65,$BM65:$CG65)+$CH65)<(SUMIF($CO63:$DI63,$AZ65,$CO65:$DI65)+$DJ65),AZ65+1,AZ65) -> 4 | BC65: =SUMIF($AE$53:$AY$53,$BB65,$AE65:$AY65) -> 5.7189949 | BF65: 11 | BG65: =$X65 -> 0.58173113 | BH65: =$AC65 -> 3241.4989 | BI65: =BH65*(1-BG65) -> 1355.8181 | BJ65: =Peak_Arrival_Manual_Mor/K51 -> 2.4762511 | BK65: =900*Peak_Time_Mor*($BJ65/Total_Lanes-1+SQRT(($BJ65/Total_Lanes-1)^2+8*($BJ65/Total_Lanes)/(Peak_Time_Mor*$K51*Total_Lanes))) -> 0.14245562 | BL65: =Peak_Arrival_Manual_Mor/N51 -> 2.5642851 | BM65: =IF(BM$6<Total_Lanes,900*Peak_Time_Mor*($BL65/(Total_Lanes-BM$6)-1+SQRT(($BL65/(Total_Lanes-BM$6)-1)^2+8*($BL65/(Total_Lanes-BM$6))/(Peak_Time_Mor*$N51*(Total_Lanes-BM$6)))),"-") -> 0.18814363 | BN65: =IF(BN$6<Total_Lanes,900*Peak_Time_Mor*($BL65/(Total_Lanes-BN$6)-1+SQRT(($BL65/(Total_Lanes-BN$6)-1)^2+8*($BL65/(Total_Lanes-BN$6))/(Peak_Time_Mor*$N51*(Total_Lanes-BN$6)))),"-") -> 0.23478637 | BO65: =IF(BO$6<Total_Lanes,900*Peak_Time_Mor*($BL65/(Total_Lanes-BO$6)-1+SQRT(($BL65/(Total_Lanes-BO$6)-1)^2+8*($BL65/(Total_Lanes-BO$6))/(Peak_Time_Mor*$N51*(Total_Lanes-BO$6)))),"-") -> 0.30140021 | BP65: =IF(BP$6<Total_Lanes,900*Peak_Time_Mor*($BL65/(Total_Lanes-BP$6)-1+SQRT(($BL65/(Total_Lanes-BP$6)-1)^2+8*($BL65/(Total_Lanes-BP$6))/(Peak_Time_Mor*$N51*(Total_Lanes-BP$6)))),"-") -> 0.4014355 | BQ65: =IF(BQ$6<Total_Lanes,900*Peak_Time_Mor*($BL65/(Total_Lanes-BQ$6)-1+SQRT(($BL65/(Total_Lanes-BQ$6)-1)^2+8*($BL65/(Total_Lanes-BQ$6))/(Peak_Time_Mor*$N51*(Total_Lanes-BQ$6)))),"-") -> 0.56216658 | BR65: =IF(BR$6<Total_Lanes,900*Peak_Time_Mor*($BL65/(Total_Lanes-BR$6)-1+SQRT(($BL65/(Total_Lanes-BR$6)-1)^2+8*($BL65/(Total_Lanes-BR$6))/(Peak_Time_Mor*$N51*(Total_Lanes-BR$6)))),"-") -> 0.84661703 | BS65: =IF(BS$6<Total_Lanes,900*Peak_Time_Mor*($BL65/(Total_Lanes-BS$6)-1+SQRT(($BL65/(Total_Lanes-BS$6)-1)^2+8*($BL65/(Total_Lanes-BS$6))/(Peak_Time_Mor*$N51*(Total_Lanes-BS$6)))),"-") -> 1.4324605 | BT65: =IF(BT$6<Total_Lanes,900*Peak_Time_Mor*($BL65/(Total_Lanes-BT$6)-1+SQRT(($BL65/(Total_Lanes-BT$6)-1)^2+8*($BL65/(Total_Lanes-BT$6))/(Peak_Time_Mor*$N51*(Total_Lanes-BT$6)))),"-") -> 3.0331037 | ... CG65: =IF(CG$6<Total_Lanes,900*Peak_Time_Mor*($BL65/(Total_Lanes-CG$6)-1+SQRT(($BL65/(Total_Lanes-CG$6)-1)^2+8*($BL65/(Total_Lanes-CG$6))/(Peak_Time_Mor*$N51*(Total_Lanes-CG$6)))),"-") -> - | CH65: =3600/N51 -> 6.80875 | CJ65: 11 | CK65: =$X65 -> 0.58173113 | CL65: =$AC65 -> 3241.4989 | CM65: =CL65*CK65 -> 1885.6808 | CN65: =CM65/O51 -> 1.2571205 | CO65: =IF(CO$53<Total_Lanes,900*Peak_Time_Mor*($CN65/CO$53-1+SQRT(($CN65/CO$53-1)^2+8*($CN65/CO$53)/(Peak_Time_Mor*$O51*CO$53))),"-") -> 937.22297 | CP65: =IF(CP$53<Total_Lanes,900*Peak_Time_Mor*($CN65/CP$53-1+SQRT(($CN65/CP$53-1)^2+8*($CN65/CP$53)/(Peak_Time_Mor*$O51*CP$53))),"-") -> 2.0275977 | CQ65: =IF(CQ$53<Total_Lanes,900*Peak_Time_Mor*($CN65/CQ$53-1+SQRT(($CN65/CQ$53-1)^2+8*($CN65/CQ$53)/(Peak_Time_Mor*$O51*CQ$53))),"-") -> 0.57687243 | CR65: =IF(CR$53<Total_Lanes,900*Peak_Time_Mor*($CN65/CR$53-1+SQRT(($CN65/CR$53-1)^2+8*($CN65/CR$53)/(Peak_Time_Mor*$O51*CR$53))),"-") -> 0.27496225 | CS65: =IF(CS$53<Total_Lanes,900*Peak_Time_Mor*($CN65/CS$53-1+SQRT(($CN65/CS$53-1)^2+8*($CN65/CS$53)/(Peak_Time_Mor*$O51*CS$53))),"-") -> 0.16120791 | CT65: =IF(CT$53<Total_Lanes,900*Peak_Time_Mor*($CN65/CT$53-1+SQRT(($CN65/CT$53-1)^2+8*($CN65/CT$53)/(Peak_Time_Mor*$O51*CT$53))),"-") -> 0.10601777 | CU65: =IF(CU$53<Total_Lanes,900*Peak_Time_Mor*($CN65/CU$53-1+SQRT(($CN65/CU$53-1)^2+8*($CN65/CU$53)/(Peak_Time_Mor*$O51*CU$53))),"-") -> 0.075049773 | CV65: =IF(CV$53<Total_Lanes,900*Peak_Time_Mor*($CN65/CV$53-1+SQRT(($CN65/CV$53-1)^2+8*($CN65/CV$53)/(Peak_Time_Mor*$O51*CV$53))),"-") -> 0.055929994 | ... DI65: =IF(DI$53<Total_Lanes,900*Peak_Time_Mor*($CN65/DI$53-1+SQRT(($CN65/DI$53-1)^2+8*($CN65/DI$53)/(Peak_Time_Mor*$O51*DI$53))),"-") -> - | DJ65: =3600/$O51 -> 2.4
V66: 12 | W66: =W19 -> 25606469 | X66: =X19 -> 0.62370976 | Y66: =Y19 -> 11041.814 | Z66: =W66/Y66 -> 2319.0455 | AA66: =AA19 -> 2 | AB66: =1-AB19 -> 0.3 | AC66: =Y66*AB66 -> 3312.5442 | AD66: =Peak_Time_Mor*$BH66*(CH66+BK66)/3600 -> 12.805336 | AE66: =IF(AE$53<Total_Lanes,($BI66*($CH66+BM66)+$CM66*CO66)*Peak_Time_Mor/3600,"-") -> 1574.2115 | AF66: =IF(AF$53<Total_Lanes,($BI66*($CH66+BN66)+$CM66*CP66)*Peak_Time_Mor/3600,"-") -> 7.9160508 | AG66: =IF(AG$53<Total_Lanes,($BI66*($CH66+BO66)+$CM66*CQ66)*Peak_Time_Mor/3600,"-") -> 5.6961689 | AH66: =IF(AH$53<Total_Lanes,($BI66*($CH66+BP66)+$CM66*CR66)*Peak_Time_Mor/3600,"-") -> 5.3394089 | AI66: =IF(AI$53<Total_Lanes,($BI66*($CH66+BQ66)+$CM66*CS66)*Peak_Time_Mor/3600,"-") -> 5.2838108 | AJ66: =IF(AJ$53<Total_Lanes,($BI66*($CH66+BR66)+$CM66*CT66)*Peak_Time_Mor/3600,"-") -> 5.3791311 | AK66: =IF(AK$53<Total_Lanes,($BI66*($CH66+BS66)+$CM66*CU66)*Peak_Time_Mor/3600,"-") -> 5.6744521 | AL66: =IF(AL$53<Total_Lanes,($BI66*($CH66+BT66)+$CM66*CV66)*Peak_Time_Mor/3600,"-") -> 6.5085294 | ... AY66: =IF(AY$53<Total_Lanes,($BI66*($CH66+CG66)+$CM66*DI66)*Peak_Time_Mor/3600,"-") -> - | AZ66: =SUMIF(AE66:AY66,BA66,$AE$53:$AY$53) -> 5 | BA66: =MIN(AE66:AY66) -> 5.2838108 | BB66: =IF((SUMIF($BM64:$CG64,$AZ66,$BM66:$CG66)+$CH66)<(SUMIF($CO64:$DI64,$AZ66,$CO66:$DI66)+$DJ66),AZ66+1,AZ66) -> 5 | BC66: =SUMIF($AE$53:$AY$53,$BB66,$AE66:$AY66) -> 5.2838108 | BF66: 12 | BG66: =$X66 -> 0.62370976 | BH66: =$AC66 -> 3312.5442 | BI66: =BH66*(1-BG66) -> 1246.4781 | BJ66: =Peak_Arrival_Manual_Mor/K52 -> 2.2765537 | BK66: =900*Peak_Time_Mor*($BJ66/Total_Lanes-1+SQRT(($BJ66/Total_Lanes-1)^2+8*($BJ66/Total_Lanes)/(Peak_Time_Mor*$K52*Total_Lanes))) -> 0.12827827 | BL66: =Peak_Arrival_Manual_Mor/N52 -> 2.3648459 | BM66: =IF(BM$6<Total_Lanes,900*Peak_Time_Mor*($BL66/(Total_Lanes-BM$6)-1+SQRT(($BL66/(Total_Lanes-BM$6)-1)^2+8*($BL66/(Total_Lanes-BM$6))/(Peak_Time_Mor*$N52*(Total_Lanes-BM$6)))),"-") -> 0.17003355 | BN66: =IF(BN$6<Total_Lanes,900*Peak_Time_Mor*($BL66/(Total_Lanes-BN$6)-1+SQRT(($BL66/(Total_Lanes-BN$6)-1)^2+8*($BL66/(Total_Lanes-BN$6))/(Peak_Time_Mor*$N52*(Total_Lanes-BN$6)))),"-") -> 0.21153017 | BO66: =IF(BO$6<Total_Lanes,900*Peak_Time_Mor*($BL66/(Total_Lanes-BO$6)-1+SQRT(($BL66/(Total_Lanes-BO$6)-1)^2+8*($BL66/(Total_Lanes-BO$6))/(Peak_Time_Mor*$N52*(Total_Lanes-BO$6)))),"-") -> 0.27044924 | BP66: =IF(BP$6<Total_Lanes,900*Peak_Time_Mor*($BL66/(Total_Lanes-BP$6)-1+SQRT(($BL66/(Total_Lanes-BP$6)-1)^2+8*($BL66/(Total_Lanes-BP$6))/(Peak_Time_Mor*$N52*(Total_Lanes-BP$6)))),"-") -> 0.35823367 | BQ66: =IF(BQ$6<Total_Lanes,900*Peak_Time_Mor*($BL66/(Total_Lanes-BQ$6)-1+SQRT(($BL66/(Total_Lanes-BQ$6)-1)^2+8*($BL66/(Total_Lanes-BQ$6))/(Peak_Time_Mor*$N52*(Total_Lanes-BQ$6)))),"-") -> 0.49770345 | BR66: =IF(BR$6<Total_Lanes,900*Peak_Time_Mor*($BL66/(Total_Lanes-BR$6)-1+SQRT(($BL66/(Total_Lanes-BR$6)-1)^2+8*($BL66/(Total_Lanes-BR$6))/(Peak_Time_Mor*$N52*(Total_Lanes-BR$6)))),"-") -> 0.74029034 | BS66: =IF(BS$6<Total_Lanes,900*Peak_Time_Mor*($BL66/(Total_Lanes-BS$6)-1+SQRT(($BL66/(Total_Lanes-BS$6)-1)^2+8*($BL66/(Total_Lanes-BS$6))/(Peak_Time_Mor*$N52*(Total_Lanes-BS$6)))),"-") -> 1.2250877 | BT66: =IF(BT$6<Total_Lanes,900*Peak_Time_Mor*($BL66/(Total_Lanes-BT$6)-1+SQRT(($BL66/(Total_Lanes-BT$6)-1)^2+8*($BL66/(Total_Lanes-BT$6))/(Peak_Time_Mor*$N52*(Total_Lanes-BT$6)))),"-") -> 2.4653462 | ... CG66: =IF(CG$6<Total_Lanes,900*Peak_Time_Mor*($BL66/(Total_Lanes-CG$6)-1+SQRT(($BL66/(Total_Lanes-CG$6)-1)^2+8*($BL66/(Total_Lanes-CG$6))/(Peak_Time_Mor*$N52*(Total_Lanes-CG$6)))),"-") -> - | CH66: =3600/N52 -> 6.83 | CJ66: 12 | CK66: =$X66 -> 0.62370976 | CL66: =$AC66 -> 3312.5442 | CM66: =CL66*CK66 -> 2066.0662 | CN66: =CM66/O52 -> 1.3773775 | CO66: =IF(CO$53<Total_Lanes,900*Peak_Time_Mor*($CN66/CO$53-1+SQRT(($CN66/CO$53-1)^2+8*($CN66/CO$53)/(Peak_Time_Mor*$O52*CO$53))),"-") -> 1367.2628 | CP66: =IF(CP$53<Total_Lanes,900*Peak_Time_Mor*($CN66/CP$53-1+SQRT(($CN66/CP$53-1)^2+8*($CN66/CP$53)/(Peak_Time_Mor*$O52*CP$53))),"-") -> 2.6484044 | CQ66: =IF(CQ$53<Total_Lanes,900*Peak_Time_Mor*($CN66/CQ$53-1+SQRT(($CN66/CQ$53-1)^2+8*($CN66/CQ$53)/(Peak_Time_Mor*$O52*CQ$53))),"-") -> 0.67885038 | CR66: =IF(CR$53<Total_Lanes,900*Peak_Time_Mor*($CN66/CR$53-1+SQRT(($CN66/CR$53-1)^2+8*($CN66/CR$53)/(Peak_Time_Mor*$O52*CR$53))),"-") -> 0.31507247 | CS66: =IF(CS$53<Total_Lanes,900*Peak_Time_Mor*($CN66/CS$53-1+SQRT(($CN66/CS$53-1)^2+8*($CN66/CS$53)/(Peak_Time_Mor*$O52*CS$53))),"-") -> 0.1824907 | CT66: =IF(CT$53<Total_Lanes,900*Peak_Time_Mor*($CN66/CT$53-1+SQRT(($CN66/CT$53-1)^2+8*($CN66/CT$53)/(Peak_Time_Mor*$O52*CT$53))),"-") -> 0.11918068 | CU66: =IF(CU$53<Total_Lanes,900*Peak_Time_Mor*($CN66/CU$53-1+SQRT(($CN66/CU$53-1)^2+8*($CN66/CU$53)/(Peak_Time_Mor*$O52*CU$53))),"-") -> 0.083987495 | CV66: =IF(CV$53<Total_Lanes,900*Peak_Time_Mor*($CN66/CV$53-1+SQRT(($CN66/CV$53-1)^2+8*($CN66/CV$53)/(Peak_Time_Mor*$O52*CV$53))),"-") -> 0.062392894 | ... DI66: =IF(DI$53<Total_Lanes,900*Peak_Time_Mor*($CN66/DI$53-1+SQRT(($CN66/DI$53-1)^2+8*($CN66/DI$53)/(Peak_Time_Mor*$O52*DI$53))),"-") -> - | DJ66: =3600/$O52 -> 2.4
